Workbook

Sheet Sheet2
A1: Year | B1: 2025
A2: Month | B2: 2
A4: Row Labels | B4: Sum of Total Capex Cost | C4: Sum of Remaining Capex Cost | D4: Sum of Total Spend
A5: Adonis 1P | B5: 1296200 | C5: 1296200 | D5: 0
A6: Alto Device | B6: 600000 | C6: 0 | D6: 0
A7: Alto Pod | B7: 67776119 | C7: 5755257.4 | D7: 8645429.5
A8: Box 5000 Full 2.0 | C8: 0 | D8: 0
A9: Box 800 Full 2.0 | B9: 14000 | C9: -1699.0204 | D9: 0
A10: Hyper Core | B10: 3254051 | C10: 1639779 | D10: 61858.57
A11: Hyper Pro | D11: 6711.73
A12: Hyper Pro | B12: 1314400 | C12: -346227.87 | D12: 301707.37
A13: KUMA E-Box NZ | B13: 0 | C13: 0 | D13: 0
A14: KUMA E-Pen 1.0 ROW | B14: 1960000 | C14: 1423826.1 | D14: 1089578.7
A15: Pen 800 Full 2.0 | B15: 111000 | C15: 110343.87 | D15: 178941.57
A16: Prismatic Device | B16: 0 | C16: 0 | D16: 0
A17: Prismatic Pod | B17: 8518207.2 | C17: 8518207.2 | D17: 0
A18: Vega | B18: 18800000 | C18: 0 | D18: 126545.15
A19: Grand Total | B19: 1.0364398e+08 | C19: 18395687 | D19: 10410773

Sheet Sheet3
A1: Tool type | B1: (Multiple Items)
A3: Row Labels | B3: Sum of Total Tool cost
A4: Adonis 1P | B4: 1296200
A5: Alto Device | B5: 600000
A6: Alto Pod | B6: 67776120
A7: Box 5000 Full 2.0 | B7: 0
A8: Box 800 Full 2.0 | B8: 14000
A9: Hyper Core | B9: 3241452
A10: Hyper Pro 2P | B10: 1327000
A11: KUMA E-Pen 1.0 ROW | B11: 1960000
A12: Pen 800 Full 2.0 | B12: 111000
A13: Prismatic Pod | B13: 8518207.2
A14: VEGA | B14: 18800000
A15: Grand Total | B15: 1.0364398e+08

Sheet Spend Track (part)
A1: Product category | B1: RCS POD | C1: RCS DEVICE | D1: MODI | E1: HP | F1: MO | G1: Update date：2025/3/12
C2: 请确保和最新的2D 图纸一样，包括大小写. 字体请用Calibri， 10 号字体
A3: Project | B3: Product Category | C3: Part Name | D3: Part No. | E3: Supplier | F3: Commonality | G3: Commodity | H3: Year | I3: Month | J3: Data Submit Date | K3: Split | L3: Unit price w/o amortization | M3: Unit Price with Amortization | N3: Amortization Cost | O3: Blended Amortization Cost | P3: Usage in BOM | Q3: BOM cost | R3: Shipped Volume | S3: Cum Shipped Volume | T3: Total Capex Cost | U3: Remaining Capex Cost | V3: Material Type | W3: Color | X3: Material Usage/part (g) | Y3: Material Supplier | Z3: CMF Type | AA3: CMF Cost/part | AB3: Total Spend | AC3: Total CMF Cost | AD3: Total Material Usage (kg) | AE3: Remark
A4: Vega | B4: =VLOOKUP(A4,Sheet1!A:B,2,0) -> MODI | C4: Mouth Piece | D4: 310493191000 | E4: JEE | F4: unique | G4: Plastic | H4: 2023 | I4: 12 | J4: 45590 | K4: 0.5 | L4: 0.31352499 | M4: 0.33477499 | N4: =M4-L4 -> 0.02125 | O4: =N4*K4 -> 0.010625 | P4: 1 | Q4: =P4*L4 -> 0.31352499 | R4: 30954490 | S4: =R4 -> 30954490 | T4: 4760000 | U4: =T4-N4*S4 -> 4102217.1 | V4: PCTG TX1501HF | X4: 6.728 | Y4: Eastman | AA4: 0 | AB4: =M4*R4 -> 10362789 | AC4: =R4*AA4 -> 0 | AD4: =R4*X4/1000 -> 208261.81
A5: Vega | B5: =VLOOKUP(A5,Sheet1!A:B,2,0) -> MODI | C5: Top Plastic Bracket | D5: 310493192000 | E5: JEE | F5: unique | G5: Plastic | H5: 2023 | I5: 12 | J5: 45590 | K5: 0.5 | L5: 0.042153932 | M5: 0.056528932 | N5: =M5-L5 -> 0.014375 | O5: =N5*K5 -> 0.0071875 | P5: 1 | Q5: =P5*L5 -> 0.042153932 | R5: 27721346 | S5: =R5 -> 27721346 | T5: 3450000 | U5: =T5-N5*S5 -> 3051505.7 | V5: PCTG TX1501HF | X5: 0.87 | Y5: Eastman | AA5: 0 | AB5: =M5*R5 -> 1567058.1 | AC5: =R5*AA5 -> 0 | AD5: =R5*X5/1000 -> 24117.571
A6: Vega | B6: =VLOOKUP(A6,Sheet1!A:B,2,0) -> MODI | C6: Bottom Plastic Bracket | D6: 310493193000 | E6: JEE | F6: unique | G6: Plastic | H6: 2023 | I6: 12 | J6: 45590 | K6: 0.5 | L6: 0.072210435 | M6: 0.087793768 | N6: =M6-L6 -> 0.015583333 | O6: =N6*K6 -> 0.0077916667 | P6: 1 | Q6: =P6*L6 -> 0.072210435 | R6: 30135782 | S6: =R6 -> 30135782 | T6: 3740000 | U6: =T6-N6*S6 -> 3270384.1 | V6: PCTG TX1501HF | X6: 1.178 | Y6: Eastman | AA6: 0 | AB6: =M6*R6 -> 2645733.9 | AC6: =R6*AA6 -> 0 | AD6: =R6*X6/1000 -> 35499.951
A7: Vega | B7: =VLOOKUP(A7,Sheet1!A:B,2,0) -> MODI | C7: Bottom cap | D7: 310493194000 | E7: JEE | F7: unique | G7: Plastic | H7: 2023 | I7: 12 | J7: 45590 | K7: 0.5 | L7: 0.066190725 | M7: 0.080565725 | N7: =M7-L7 -> 0.014375 | O7: =N7*K7 -> 0.0071875 | P7: 1 | Q7: =P7*L7 -> 0.066190725 | R7: 15794015 | S7: =R7 -> 15794015 | T7: 3450000 | U7: =T7-N7*S7 -> 3222961 | V7: LUPOY ER1000MA | X7: 1.178 | Y7: Ruicheng | AA7: 0 | AB7: =M7*R7 -> 1272456.3 | AC7: =R7*AA7 -> 0 | AD7: =R7*X7/1000 -> 18605.35
A8: Vega | B8: =VLOOKUP(A8,Sheet1!A:B,2,0) -> MODI | C8: Air Flow slider | D8: 310493195000 | E8: JEE | F8: unique | G8: Plastic | H8: 2023 | I8: 12 | J8: 45590 | K8: 0.5 | L8: 0.038519575 | M8: 0.052686242 | N8: =M8-L8 -> 0.014166667 | O8: =N8*K8 -> 0.0070833333 | P8: 1 | Q8: =P8*L8 -> 0.038519575 | R8: 42312050 | S8: =R8 -> 42312050 | T8: 3400000 | U8: =T8-N8*S8 -> 2800579.3 | V8: LUPOY ER1000MA | X8: 0.134 | Y8: Ruicheng | AA8: 0 | AB8: =M8*R8 -> 2229262.9 | AC8: =R8*AA8 -> 0 | AD8: =R8*X8/1000 -> 5669.8147
A9: Vega | B9: =VLOOKUP(A9,Sheet1!A:B,2,0) -> MODI | C9: Mouth Piece | D9: 310493191000 | E9: JEE | F9: unique | G9: Plastic | H9: 2024 | I9: 1 | J9: 45590 | K9: 0.5 | L9: 0.31352499 | M9: 0.33477499 | N9: =M9-L9 -> 0.02125 | O9: =N9*K9 -> 0.010625 | P9: 1 | Q9: =P9*L9 -> 0.31352499 | R9: 2479038 | S9: =R9+S4 -> 33433528 | T9: 4760000 | U9: =T9-N9*S9 -> 4049537.5 | V9: PCTG TX1501HF | X9: 6.728 | Y9: Eastman | AA9: 0 | AB9: =M9*R9 -> 829919.91 | AC9: =R9*AA9 -> 0 | AD9: =R9*X9/1000 -> 16678.968
A10: Vega | B10: =VLOOKUP(A10,Sheet1!A:B,2,0) -> MODI | C10: Top Plastic Bracket | D10: 310493192000 | E10: JEE | F10: unique | G10: Plastic | H10: 2024 | I10: 1 | J10: 45590 | K10: 0.5 | L10: 0.042153932 | M10: 0.056528932 | N10: =M10-L10 -> 0.014375 | O10: =N10*K10 -> 0.0071875 | P10: 1 | Q10: =P10*L10 -> 0.042153932 | R10: 2530321 | S10: =R10+S5 -> 30251667 | T10: 3450000 | U10: =T10-N10*S10 -> 3015132.3 | V10: PCTG TX1501HF | X10: 0.87 | Y10: Eastman | AA10: 0 | AB10: =M10*R10 -> 143036.34 | AC10: =R10*AA10 -> 0 | AD10: =R10*X10/1000 -> 2201.3793
A11: Vega | B11: =VLOOKUP(A11,Sheet1!A:B,2,0) -> MODI | C11: Bottom Plastic Bracket | D11: 310493193000 | E11: JEE | F11: unique | G11: Plastic | H11: 2024 | I11: 1 | J11: 45590 | K11: 0.5 | L11: 0.072210435 | M11: 0.087793768 | N11: =M11-L11 -> 0.015583333 | O11: =N11*K11 -> 0.0077916667 | P11: 1 | Q11: =P11*L11 -> 0.072210435 | R11: 2184407 | S11: =R11+S6 -> 32320189 | T11: 3740000 | U11: =T11-N11*S11 -> 3236343.7 | V11: PCTG TX1501HF | X11: 1.178 | Y11: Eastman | AA11: 0 | AB11: =M11*R11 -> 191777.32 | AC11: =R11*AA11 -> 0 | AD11: =R11*X11/1000 -> 2573.2314
A12: Vega | B12: =VLOOKUP(A12,Sheet1!A:B,2,0) -> MODI | C12: Bottom cap | D12: 310493194000 | E12: JEE | F12: unique | G12: Plastic | H12: 2024 | I12: 1 | J12: 45590 | K12: 0.5 | L12: 0.066190725 | M12: 0.080565725 | N12: =M12-L12 -> 0.014375 | O12: =N12*K12 -> 0.0071875 | P12: 1 | Q12: =P12*L12 -> 0.066190725 | R12: 2258856 | S12: =R12+S7 -> 18052871 | T12: 3450000 | U12: =T12-N12*S12 -> 3190490 | V12: LUPOY ER1000MA | X12: 1.178 | Y12: Ruicheng | AA12: 0 | AB12: =M12*R12 -> 181986.37 | AC12: =R12*AA12 -> 0 | AD12: =R12*X12/1000 -> 2660.9324
A13: Vega | B13: =VLOOKUP(A13,Sheet1!A:B,2,0) -> MODI | C13: Air Flow slider | D13: 310493195000 | E13: JEE | F13: unique | G13: Plastic | H13: 2024 | I13: 1 | J13: 45590 | K13: 0.5 | L13: 0.038519575 | M13: 0.052686242 | N13: =M13-L13 -> 0.014166667 | O13: =N13*K13 -> 0.0070833333 | P13: 1 | Q13: =P13*L13 -> 0.038519575 | R13: 1792586 | S13: =R13+S8 -> 44104636 | T13: 3400000 | U13: =T13-N13*S13 -> 2775184.3 | V13: LUPOY ER1000MA | X13: 0.134 | Y13: Ruicheng | AA13: 0 | AB13: =M13*R13 -> 94444.619 | AC13: =R13*AA13 -> 0 | AD13: =R13*X13/1000 -> 240.20652
A14: Vega | B14: =VLOOKUP(A14,Sheet1!A:B,2,0) -> MODI | C14: Mouth Piece | D14: 310493191000 | E14: JEE | F14: unique | G14: Plastic | H14: 2024 | I14: 2 | J14: 45590 | K14: 0.5 | L14: 0.31352499 | M14: 0.33477499 | N14: =M14-L14 -> 0.02125 | O14: =N14*K14 -> 0.010625 | P14: 1 | Q14: =P14*L14 -> 0.31352499 | R14: 1002816 | S14: =R14+S9 -> 34436344 | T14: 4760000 | U14: =T14-N14*S14 -> 4028227.7 | V14: PCTG TX1501HF | X14: 6.728 | Y14: Eastman | AA14: 0 | AB14: =M14*R14 -> 335717.71 | AC14: =R14*AA14 -> 0 | AD14: =R14*X14/1000 -> 6746.946
A15: Vega | B15: =VLOOKUP(A15,Sheet1!A:B,2,0) -> MODI | C15: Top Plastic Bracket | D15: 310493192000 | E15: JEE | F15: unique | G15: Plastic | H15: 2024 | I15: 2 | J15: 45590 | K15: 0.5 | L15: 0.042153932 | M15: 0.056528932 | N15: =M15-L15 -> 0.014375 | O15: =N15*K15 -> 0.0071875 | P15: 1 | Q15: =P15*L15 -> 0.042153932 | R15: 1600000 | S15: =R15+S10 -> 31851667 | T15: 3450000 | U15: =T15-N15*S15 -> 2992132.3 | V15: PCTG TX1501HF | X15: 0.87 | Y15: Eastman | AA15: 0 | AB15: =M15*R15 -> 90446.291 | AC15: =R15*AA15 -> 0 | AD15: =R15*X15/1000 -> 1392
A16: Vega | B16: =VLOOKUP(A16,Sheet1!A:B,2,0) -> MODI | C16: Bottom Plastic Bracket | D16: 310493193000 | E16: JEE | F16: unique | G16: Plastic | H16: 2024 | I16: 2 | J16: 45590 | K16: 0.5 | L16: 0.072210435 | M16: 0.087793768 | N16: =M16-L16 -> 0.015583333 | O16: =N16*K16 -> 0.0077916667 | P16: 1 | Q16: =P16*L16 -> 0.072210435 | R16: 1332000 | S16: =R16+S11 -> 33652189 | T16: 3740000 | U16: =T16-N16*S16 -> 3215586.7 | V16: PCTG TX1501HF | X16: 1.178 | Y16: Eastman | AA16: 0 | AB16: =M16*R16 -> 116941.3 | AC16: =R16*AA16 -> 0 | AD16: =R16*X16/1000 -> 1569.096
A17: Vega | B17: =VLOOKUP(A17,Sheet1!A:B,2,0) -> MODI | C17: Bottom cap | D17: 310493194000 | E17: JEE | F17: unique | G17: Plastic | H17: 2024 | I17: 2 | J17: 45590 | K17: 0.5 | L17: 0.066190725 | M17: 0.080565725 | N17: =M17-L17 -> 0.014375 | O17: =N17*K17 -> 0.0071875 | P17: 1 | Q17: =P17*L17 -> 0.066190725 | R17: 1095430 | S17: =R17+S12 -> 19148301 | T17: 3450000 | U17: =T17-N17*S17 -> 3174743.2 | V17: LUPOY ER1000MA | X17: 1.178 | Y17: Ruicheng | AA17: 0 | AB17: =M17*R17 -> 88254.113 | AC17: =R17*AA17 -> 0 | AD17: =R17*X17/1000 -> 1290.4165
A18: Vega | B18: =VLOOKUP(A18,Sheet1!A:B,2,0) -> MODI | C18: Air Flow slider | D18: 310493195000 | E18: JEE | F18: unique | G18: Plastic | H18: 2024 | I18: 2 | J18: 45590 | K18: 0.5 | L18: 0.038519575 | M18: 0.052686242 | N18: =M18-L18 -> 0.014166667 | O18: =N18*K18 -> 0.0070833333 | P18: 1 | Q18: =P18*L18 -> 0.038519575 | R18: 1241998 | S18: =R18+S13 -> 45346634 | T18: 3400000 | U18: =T18-N18*S18 -> 2757589.4 | V18: LUPOY ER1000MA | X18: 0.134 | Y18: Ruicheng | AA18: 0 | AB18: =M18*R18 -> 65436.207 | AC18: =R18*AA18 -> 0 | AD18: =R18*X18/1000 -> 166.42773
A19: Vega | B19: =VLOOKUP(A19,Sheet1!A:B,2,0) -> MODI | C19: Mouth Piece | D19: 310493191000 | E19: JEE | F19: unique | G19: Plastic | H19: 2024 | I19: 3 | J19: 45590 | K19: 0.5 | L19: 0.31352499 | M19: 0.33477499 | N19: =M19-L19 -> 0.02125 | O19: =N19*K19 -> 0.010625 | P19: 1 | Q19: =P19*L19 -> 0.31352499 | R19: 3074296 | S19: =R19+S14 -> 37510640 | T19: 4760000 | U19: =T19-N19*S19 -> 3962898.9 | V19: PCTG TX1501HF | X19: 6.728 | Y19: Eastman | AA19: 0 | AB19: =M19*R19 -> 1029197.4 | AC19: =R19*AA19 -> 0 | AD19: =R19*X19/1000 -> 20683.863
A20: Vega | B20: =VLOOKUP(A20,Sheet1!A:B,2,0) -> MODI | C20: Top Plastic Bracket | D20: 310493192000 | E20: JEE | F20: unique | G20: Plastic | H20: 2024 | I20: 3 | J20: 45590 | K20: 0.5 | L20: 0.042153932 | M20: 0.056528932 | N20: =M20-L20 -> 0.014375 | O20: =N20*K20 -> 0.0071875 | P20: 1 | Q20: =P20*L20 -> 0.042153932 | R20: 1600000 | S20: =R20+S15 -> 33451667 | T20: 3450000 | U20: =T20-N20*S20 -> 2969132.3 | V20: PCTG TX1501HF | X20: 0.87 | Y20: Eastman | AA20: 0 | AB20: =M20*R20 -> 90446.291 | AC20: =R20*AA20 -> 0 | AD20: =R20*X20/1000 -> 1392
... A53: Vega | B53: =VLOOKUP(A53,Sheet1!A:B,2,0) -> MODI | C53: Air Flow slider | D53: 310493195000 | E53: JEE | F53: unique | G53: Plastic | H53: 2024 | I53: 9 | J53: 45590 | K53: 0.5 | L53: 0.038519575 | M53: 0.052686242 | N53: =M53-L53 -> 0.014166667 | O53: =N53*K53 -> 0.0070833333 | P53: 1 | Q53: =P53*L53 -> 0.038519575 | R53: 162943 | S53: =R53+S48 -> 56288362 | T53: 3400000 | U53: =T53-N53*S53 -> 2602581.5 | V53: LUPOY ER1000MA | X53: 0.134 | Y53: Ruicheng | AA53: 0 | AB53: =M53*R53 -> 8584.8543 | AC53: =R53*AA53 -> 0 | AD53: =R53*X53/1000 -> 21.834362
A54: KUMA E-Box NZ | B54: =VLOOKUP(A54,Sheet1!A:B,2,0) -> RCS DEVICE | C54: Top cover | D54: 130040670021260 | E54: JEE | F54: Unique | G54: Plastic | H54: 2023 | I54: 12 | J54: 45590 | K54: 1 | L54: 2.3583409 | M54: 2.3583409 | N54: =M54-L54 -> 0 | O54: =N54*K54 -> 0 | P54: 1 | Q54: =P54*L54 -> 2.3583409 | R54: 3350 | S54: =R54 -> 3350 | T54: 0 | U54: 0 | V54: LUPOY GP1000ML | X54: 16.26 | Y54: LG | Z54: Printing | AA54: 1.308 | AB54: =M54*R54 -> 7900.4419 | AC54: =R54*AA54 -> 4381.8 | AD54: =R54*X54/1000 -> 54.471
A55: KUMA E-Box NZ | B55: =VLOOKUP(A55,Sheet1!A:B,2,0) -> RCS DEVICE | C55: Bottom cover | D55: 130040670021261 | E55: JEE | F55: Unique | G55: Plastic | H55: 2023 | I55: 12 | J55: 45590 | K55: 1 | L55: 2.3165273 | M55: 2.3165273 | N55: =M55-L55 -> 0 | O55: =N55*K55 -> 0 | P55: 1 | Q55: =P55*L55 -> 2.3165273 | R55: 3794 | S55: =R55 -> 3794 | T55: 0 | U55: 0 | V55: LUPOY GP1000ML | X55: 8.302 | Y55: LG | Z55: Printing | AA55: 1.428 | AB55: =M55*R55 -> 8788.9045 | AC55: =R55*AA55 -> 5417.832 | AD55: =R55*X55/1000 -> 31.497788
A56: KUMA E-Box NZ | B56: =VLOOKUP(A56,Sheet1!A:B,2,0) -> RCS DEVICE | C56: Button | D56: 130040670021263 | E56: JEE | F56: Unique | G56: Plastic | H56: 2023 | I56: 12 | J56: 45590 | K56: 1 | L56: 0.37651638 | M56: 0.37651638 | N56: =M56-L56 -> 0 | O56: =N56*K56 -> 0 | P56: 1 | Q56: =P56*L56 -> 0.37651638 | R56: 4036 | S56: =R56 -> 4036 | T56: 0 | U56: 0 | V56: LUPOY GP1000ML | X56: 0.572 | Y56: LG | AA56: 0 | AB56: =M56*R56 -> 1519.6201 | AC56: =R56*AA56 -> 0 | AD56: =R56*X56/1000 -> 2.308592
A57: KUMA E-Box NZ | B57: =VLOOKUP(A57,Sheet1!A:B,2,0) -> RCS DEVICE | C57: PCB holder | D57: 130040670021262 | E57: JEE | F57: Unique | G57: Plastic | H57: 2023 | I57: 12 | J57: 45590 | K57: 1 | L57: 0.37927345 | M57: 0.37927345 | N57: =M57-L57 -> 0 | O57: =N57*K57 -> 0 | P57: 1 | Q57: =P57*L57 -> 0.37927345 | R57: 4000 | S57: =R57 -> 4000 | T57: 0 | U57: 0 | V57: PC Makrolon 2456 | X57: 1.87 | Y57: Makrolon | AA57: 0 | AB57: =M57*R57 -> 1517.0938 | AC57: =R57*AA57 -> 0 | AD57: =R57*X57/1000 -> 7.48
A58: KUMA E-Box NZ | B58: =VLOOKUP(A58,Sheet1!A:B,2,0) -> RCS DEVICE | C58: Top cover | D58: 130040670021260 | E58: JEE | F58: Unique | G58: Plastic | H58: 2024 | I58: 1 | J58: 45590 | K58: 1 | L58: 2.3583409 | M58: 2.3583409 | N58: =M58-L58 -> 0 | O58: =N58*K58 -> 0 | P58: 1 | Q58: =P58*L58 -> 2.3583409 | R58: 201800 | S58: =R58+S54 -> 205150 | T58: 0 | U58: 0 | V58: LUPOY GP1000ML | X58: 16.26 | Y58: LG | Z58: Printing | AA58: 1.308 | AB58: =M58*R58 -> 475913.19 | AC58: =R58*AA58 -> 263954.4 | AD58: =R58*X58/1000 -> 3281.268
A59: KUMA E-Box NZ | B59: =VLOOKUP(A59,Sheet1!A:B,2,0) -> RCS DEVICE | C59: Bottom cover | D59: 130040670021261 | E59: JEE | F59: Unique | G59: Plastic | H59: 2024 | I59: 1 | J59: 45590 | K59: 1 | L59: 2.3165273 | M59: 2.3165273 | N59: =M59-L59 -> 0 | O59: =N59*K59 -> 0 | P59: 1 | Q59: =P59*L59 -> 2.3165273 | R59: 182616 | S59: =R59+S55 -> 186410 | T59: 0 | U59: 0 | V59: LUPOY GP1000ML | X59: 8.302 | Y59: LG | Z59: Printing | AA59: 1.428 | AB59: =M59*R59 -> 423034.95 | AC59: =R59*AA59 -> 260775.65 | AD59: =R59*X59/1000 -> 1516.078
A60: KUMA E-Box NZ | B60: =VLOOKUP(A60,Sheet1!A:B,2,0) -> RCS DEVICE | C60: Button | D60: 130040670021263 | E60: JEE | F60: Unique | G60: Plastic | H60: 2024 | I60: 1 | J60: 45590 | K60: 1 | L60: 0.37651638 | M60: 0.37651638 | N60: =M60-L60 -> 0 | O60: =N60*K60 -> 0 | P60: 1 | Q60: =P60*L60 -> 0.37651638 | R60: 185032 | S60: =R60+S56 -> 189068 | T60: 0 | U60: 0 | V60: LUPOY GP1000ML | X60: 0.572 | Y60: LG | AA60: 0 | AB60: =M60*R60 -> 69667.579 | AC60: =R60*AA60 -> 0 | AD60: =R60*X60/1000 -> 105.8383
A61: KUMA E-Box NZ | B61: =VLOOKUP(A61,Sheet1!A:B,2,0) -> RCS DEVICE | C61: PCB holder | D61: 130040670021262 | E61: JEE | F61: Unique | G61: Plastic | H61: 2024 | I61: 1 | J61: 45590 | K61: 1 | L61: 0.37927345 | M61: 0.37927345 | N61: =M61-L61 -> 0 | O61: =N61*K61 -> 0 | P61: 1 | Q61: =P61*L61 -> 0.37927345 | R61: 286070 | S61: =R61+S57 -> 290070 | T61: 0 | U61: 0 | V61: PC Makrolon 2456 | X61: 1.87 | Y61: Makrolon | AA61: 0 | AB61: =M61*R61 -> 108498.76 | AC61: =R61*AA61 -> 0 | AD61: =R61*X61/1000 -> 534.9509
A62: KUMA E-Box NZ | B62: =VLOOKUP(A62,Sheet1!A:B,2,0) -> RCS DEVICE | C62: Top cover | D62: 130040670021260 | E62: JEE | F62: Unique | G62: Plastic | H62: 2024 | I62: 2 | J62: 45590 | K62: 1 | L62: 2.3583409 | M62: 2.3583409 | N62: =M62-L62 -> 0 | O62: =N62*K62 -> 0 | P62: 1 | Q62: =P62*L62 -> 2.3583409 | R62: 10445 | S62: =R62+S58 -> 215595 | T62: 0 | U62: 0 | V62: LUPOY GP1000ML | X62: 16.26 | Y62: LG | Z62: Printing | AA62: 1.308 | AB62: =M62*R62 -> 24632.87 | AC62: =R62*AA62 -> 13662.06 | AD62: =R62*X62/1000 -> 169.8357
A63: KUMA E-Box NZ | B63: =VLOOKUP(A63,Sheet1!A:B,2,0) -> RCS DEVICE | C63: Bottom cover | D63: 130040670021261 | E63: JEE | F63: Unique | G63: Plastic | H63: 2024 | I63: 2 | J63: 45590 | K63: 1 | L63: 2.3165273 | M63: 2.3165273 | N63: =M63-L63 -> 0 | O63: =N63*K63 -> 0 | P63: 1 | Q63: =P63*L63 -> 2.3165273 | R63: 110305 | S63: =R63+S59 -> 296715 | T63: 0 | U63: 0 | V63: LUPOY GP1000ML | X63: 8.302 | Y63: LG | Z63: Printing | AA63: 1.428 | AB63: =M63*R63 -> 255524.54 | AC63: =R63*AA63 -> 157515.54 | AD63: =R63*X63/1000 -> 915.75211
A64: KUMA E-Box NZ | B64: =VLOOKUP(A64,Sheet1!A:B,2,0) -> RCS DEVICE | C64: Button | D64: 130040670021263 | E64: JEE | F64: Unique | G64: Plastic | H64: 2024 | I64: 2 | J64: 45590 | K64: 1 | L64: 0.37651638 | M64: 0.37651638 | N64: =M64-L64 -> 0 | O64: =N64*K64 -> 0 | P64: 1 | Q64: =P64*L64 -> 0.37651638 | R64: 45462 | S64: =R64+S60 -> 234530 | T64: 0 | U64: 0 | V64: LUPOY GP1000ML | X64: 0.572 | Y64: LG | AA64: 0 | AB64: =M64*R64 -> 17117.188 | AC64: =R64*AA64 -> 0 | AD64: =R64*X64/1000 -> 26.004264
A65: KUMA E-Box NZ | B65: =VLOOKUP(A65,Sheet1!A:B,2,0) -> RCS DEVICE | C65: PCB holder | D65: 130040670021262 | E65: JEE | F65: Unique | G65: Plastic | H65: 2024 | I65: 2 | J65: 45590 | K65: 1 | L65: 0.37927345 | M65: 0.37927345 | N65: =M65-L65 -> 0 | O65: =N65*K65 -> 0 | P65: 1 | Q65: =P65*L65 -> 0.37927345 | R65: 33000 | S65: =R65+S61 -> 323070 | T65: 0 | U65: 0 | V65: PC Makrolon 2456 | X65: 1.87 | Y65: Makrolon | AA65: 0 | AB65: =M65*R65 -> 12516.024 | AC65: =R65*AA65 -> 0 | AD65: =R65*X65/1000 -> 61.71
A66: KUMA E-Box NZ | B66: =VLOOKUP(A66,Sheet1!A:B,2,0) -> RCS DEVICE | C66: Top cover | D66: 130040670021260 | E66: JEE | F66: Unique | G66: Plastic | H66: 2024 | I66: 3 | J66: 45590 | K66: 1 | L66: 2.3583409 | M66: 2.3583409 | N66: =M66-L66 -> 0 | O66: =N66*K66 -> 0 | P66: 1 | Q66: =P66*L66 -> 2.3583409 | R66: 88849 | S66: =R66+S62 -> 304444 | T66: 0 | U66: 0 | V66: LUPOY GP1000ML | X66: 16.26 | Y66: LG | Z66: Printing | AA66: 1.308 | AB66: =M66*R66 -> 209536.23 | AC66: =R66*AA66 -> 116214.49 | AD66: =R66*X66/1000 -> 1444.6847
A67: KUMA E-Box NZ | B67: =VLOOKUP(A67,Sheet1!A:B,2,0) -> RCS DEVICE | C67: Bottom cover | D67: 130040670021261 | E67: JEE | F67: Unique | G67: Plastic | H67: 2024 | I67: 3 | J67: 45590 | K67: 1 | L67: 2.3165273 | M67: 2.3165273 | N67: =M67-L67 -> 0 | O67: =N67*K67 -> 0 | P67: 1 | Q67: =P67*L67 -> 2.3165273 | R67: 23024 | S67: =R67+S63 -> 319739 | T67: 0 | U67: 0 | V67: LUPOY GP1000ML | X67: 8.302 | Y67: LG | Z67: Printing | AA67: 1.428 | AB67: =M67*R67 -> 53335.724 | AC67: =R67*AA67 -> 32878.272 | AD67: =R67*X67/1000 -> 191.14525
A68: KUMA E-Box NZ | B68: =VLOOKUP(A68,Sheet1!A:B,2,0) -> RCS DEVICE | C68: Button | D68: 130040670021263 | E68: JEE | F68: Unique | G68: Plastic | H68: 2024 | I68: 3 | J68: 45590 | K68: 1 | L68: 0.37651638 | M68: 0.37651638 | N68: =M68-L68 -> 0 | O68: =N68*K68 -> 0 | P68: 1 | Q68: =P68*L68 -> 0.37651638 | R68: 74845 | S68: =R68+S64 -> 309375 | T68: 0 | U68: 0 | V68: LUPOY GP1000ML | X68: 0.572 | Y68: LG | AA68: 0 | AB68: =M68*R68 -> 28180.368 | AC68: =R68*AA68 -> 0 | AD68: =R68*X68/1000 -> 42.81134
A69: KUMA E-Box NZ | B69: =VLOOKUP(A69,Sheet1!A:B,2,0) -> RCS DEVICE | C69: PCB holder | D69: 130040670021262 | E69: JEE | F69: Unique | G69: Plastic | H69: 2024 | I69: 3 | J69: 45590 | K69: 1 | L69: 0.37927345 | M69: 0.37927345 | N69: =M69-L69 -> 0 | O69: =N69*K69 -> 0 | P69: 1 | Q69: =P69*L69 -> 0.37927345 | R69: 0 | S69: =R69+S65 -> 323070 | T69: 0 | U69: 0 | V69: PC Makrolon 2456 | X69: 1.87 | Y69: Makrolon | AA69: 0 | AB69: =M69*R69 -> 0 | AC69: =R69*AA69 -> 0 | AD69: =R69*X69/1000 -> 0
A70: KUMA E-Box NZ | B70: =VLOOKUP(A70,Sheet1!A:B,2,0) -> RCS DEVICE | C70: Top cover | D70: 130040670021260 | E70: JEE | F70: Unique | G70: Plastic | H70: 2024 | I70: 4 | J70: 45590 | K70: 1 | L70: 2.3583409 | M70: 2.3583409 | N70: =M70-L70 -> 0 | O70: =N70*K70 -> 0 | P70: 1 | Q70: =P70*L70 -> 2.3583409 | R70: 0 | S70: =R70+S66 -> 304444 | T70: 0 | U70: 0 | V70: LUPOY GP1000ML | X70: 16.26 | Y70: LG | Z70: Printing | AA70: 1.308 | AB70: =M70*R70 -> 0 | AC70: =R70*AA70 -> 0 | AD70: =R70*X70/1000 -> 0
A71: KUMA E-Box NZ | B71: =VLOOKUP(A71,Sheet1!A:B,2,0) -> RCS DEVICE | C71: Bottom cover | D71: 130040670021261 | E71: JEE | F71: Unique | G71: Plastic | H71: 2024 | I71: 4 | J71: 45590 | K71: 1 | L71: 2.3165273 | M71: 2.3165273 | N71: =M71-L71 -> 0 | O71: =N71*K71 -> 0 | P71: 1 | Q71: =P71*L71 -> 2.3165273 | R71: 0 | S71: =R71+S67 -> 319739 | T71: 0 | U71: 0 | V71: LUPOY GP1000ML | X71: 8.302 | Y71: LG | Z71: Printing | AA71: 1.428 | AB71: =M71*R71 -> 0 | AC71: =R71*AA71 -> 0 | AD71: =R71*X71/1000 -> 0
A72: KUMA E-Box NZ | B72: =VLOOKUP(A72,Sheet1!A:B,2,0) -> RCS DEVICE | C72: Button | D72: 130040670021263 | E72: JEE | F72: Unique | G72: Plastic | H72: 2024 | I72: 4 | J72: 45590 | K72: 1 | L72: 0.37651638 | M72: 0.37651638 | N72: =M72-L72 -> 0 | O72: =N72*K72 -> 0 | P72: 1 | Q72: =P72*L72 -> 0.37651638 | R72: 0 | S72: =R72+S68 -> 309375 | T72: 0 | U72: 0 | V72: LUPOY GP1000ML | X72: 0.572 | Y72: LG | AA72: 0 | AB72: =M72*R72 -> 0 | AC72: =R72*AA72 -> 0 | AD72: =R72*X72/1000 -> 0
A73: KUMA E-Box NZ | B73: =VLOOKUP(A73,Sheet1!A:B,2,0) -> RCS DEVICE | C73: PCB holder | D73: 130040670021262 | E73: JEE | F73: Unique | G73: Plastic | H73: 2024 | I73: 4 | J73: 45590 | K73: 1 | L73: 0.37927345 | M73: 0.37927345 | N73: =M73-L73 -> 0 | O73: =N73*K73 -> 0 | P73: 1 | Q73: =P73*L73 -> 0.37927345 | R73: 0 | S73: =R73+S69 -> 323070 | T73: 0 | U73: 0 | V73: PC Makrolon 2456 | X73: 1.87 | Y73: Makrolon | AA73: 0 | AB73: =M73*R73 -> 0 | AC73: =R73*AA73 -> 0 | AD73: =R73*X73/1000 -> 0
A74: KUMA E-Box NZ | B74: =VLOOKUP(A74,Sheet1!A:B,2,0) -> RCS DEVICE | C74: Top cover | D74: 130040670021260 | E74: JEE | F74: Unique | G74: Plastic | H74: 2024 | I74: 5 | J74: 45590 | K74: 1 | L74: 2.3583409 | M74: 2.3583409 | N74: =M74-L74 -> 0 | O74: =N74*K74 -> 0 | P74: 1 | Q74: =P74*L74 -> 2.3583409 | R74: 169904 | S74: =R74+S70 -> 474348 | T74: 0 | U74: 0 | V74: LUPOY GP1000ML | X74: 16.26 | Y74: LG | Z74: Printing | AA74: 1.308 | AB74: =M74*R74 -> 400691.55 | AC74: =R74*AA74 -> 222234.43 | AD74: =R74*X74/1000 -> 2762.639
A75: KUMA E-Box NZ | B75: =VLOOKUP(A75,Sheet1!A:B,2,0) -> RCS DEVICE | C75: Bottom cover | D75: 130040670021261 | E75: JEE | F75: Unique | G75: Plastic | H75: 2024 | I75: 5 | J75: 45590 | K75: 1 | L75: 2.3165273 | M75: 2.3165273 | N75: =M75-L75 -> 0 | O75: =N75*K75 -> 0 | P75: 1 | Q75: =P75*L75 -> 2.3165273 | R75: 199544 | S75: =R75+S71 -> 519283 | T75: 0 | U75: 0 | V75: LUPOY GP1000ML | X75: 8.302 | Y75: LG | Z75: Printing | AA75: 1.428 | AB75: =M75*R75 -> 462249.12 | AC75: =R75*AA75 -> 284948.83 | AD75: =R75*X75/1000 -> 1656.6143
A76: KUMA E-Box NZ | B76: =VLOOKUP(A76,Sheet1!A:B,2,0) -> RCS DEVICE | C76: Button | D76: 130040670021263 | E76: JEE | F76: Unique | G76: Plastic | H76: 2024 | I76: 5 | J76: 45590 | K76: 1 | L76: 0.37651638 | M76: 0.37651638 | N76: =M76-L76 -> 0 | O76: =N76*K76 -> 0 | P76: 1 | Q76: =P76*L76 -> 0.37651638 | R76: 191283 | S76: =R76+S72 -> 500658 | T76: 0 | U76: 0 | V76: LUPOY GP1000ML | X76: 0.572 | Y76: LG | AA76: 0 | AB76: =M76*R76 -> 72021.183 | AC76: =R76*AA76 -> 0 | AD76: =R76*X76/1000 -> 109.41388
A77: KUMA E-Box NZ | B77: =VLOOKUP(A77,Sheet1!A:B,2,0) -> RCS DEVICE | C77: PCB holder | D77: 130040670021262 | E77: JEE | F77: Unique | G77: Plastic | H77: 2024 | I77: 5 | J77: 45590 | K77: 1 | L77: 0.37927345 | M77: 0.37927345 | N77: =M77-L77 -> 0 | O77: =N77*K77 -> 0 | P77: 1 | Q77: =P77*L77 -> 0.37927345 | R77: 292000 | S77: =R77+S73 -> 615070 | T77: 0 | U77: 0 | V77: PC Makrolon 2456 | X77: 1.87 | Y77: Makrolon | AA77: 0 | AB77: =M77*R77 -> 110747.85 | AC77: =R77*AA77 -> 0 | AD77: =R77*X77/1000 -> 546.04
A78: KUMA E-Box NZ | B78: =VLOOKUP(A78,Sheet1!A:B,2,0) -> RCS DEVICE | C78: Top cover | D78: 130040670021260 | E78: JEE | F78: Unique | G78: Plastic | H78: 2024 | I78: 6 | J78: 45590 | K78: 1 | L78: 2.3583409 | M78: 2.3583409 | N78: =M78-L78 -> 0 | O78: =N78*K78 -> 0 | P78: 1 | Q78: =P78*L78 -> 2.3583409 | R78: 92599 | S78: =R78+S74 -> 566947 | T78: 0 | U78: 0 | V78: LUPOY GP1000ML | X78: 16.26 | Y78: LG | Z78: Printing | AA78: 1.308 | AB78: =M78*R78 -> 218380.01 | AC78: =R78*AA78 -> 121119.49 | AD78: =R78*X78/1000 -> 1505.6597
A79: KUMA E-Box NZ | B79: =VLOOKUP(A79,Sheet1!A:B,2,0) -> RCS DEVICE | C79: Bottom cover | D79: 130040670021261 | E79: JEE | F79: Unique | G79: Plastic | H79: 2024 | I79: 6 | J79: 45590 | K79: 1 | L79: 2.3165273 | M79: 2.3165273 | N79: =M79-L79 -> 0 | O79: =N79*K79 -> 0 | P79: 1 | Q79: =P79*L79 -> 2.3165273 | R79: 132609 | S79: =R79+S75 -> 651892 | T79: 0 | U79: 0 | V79: LUPOY GP1000ML | X79: 8.302 | Y79: LG | Z79: Printing | AA79: 1.428 | AB79: =M79*R79 -> 307192.37 | AC79: =R79*AA79 -> 189365.65 | AD79: =R79*X79/1000 -> 1100.9199
A80: KUMA E-Box NZ | B80: =VLOOKUP(A80,Sheet1!A:B,2,0) -> RCS DEVICE | C80: Button | D80: 130040670021263 | E80: JEE | F80: Unique | G80: Plastic | H80: 2024 | I80: 6 | J80: 45590 | K80: 1 | L80: 0.37651638 | M80: 0.37651638 | N80: =M80-L80 -> 0 | O80: =N80*K80 -> 0 | P80: 1 | Q80: =P80*L80 -> 0.37651638 | R80: 118241 | S80: =R80+S76 -> 618899 | T80: 0 | U80: 0 | V80: LUPOY GP1000ML | X80: 0.572 | Y80: LG | AA80: 0 | AB80: =M80*R80 -> 44519.673 | AC80: =R80*AA80 -> 0 | AD80: =R80*X80/1000 -> 67.633852
A81: KUMA E-Box NZ | B81: =VLOOKUP(A81,Sheet1!A:B,2,0) -> RCS DEVICE | C81: PCB holder | D81: 130040670021262 | E81: JEE | F81: Unique | G81: Plastic | H81: 2024 | I81: 6 | J81: 45590 | K81: 1 | L81: 0.37927345 | M81: 0.37927345 | N81: =M81-L81 -> 0 | O81: =N81*K81 -> 0 | P81: 1 | Q81: =P81*L81 -> 0.37927345 | R81: 0 | S81: =R81+S77 -> 615070 | T81: 0 | U81: 0 | V81: PC Makrolon 2456 | X81: 1.87 | Y81: Makrolon | AA81: 0 | AB81: =M81*R81 -> 0 | AC81: =R81*AA81 -> 0 | AD81: =R81*X81/1000 -> 0
A82: KUMA E-Box NZ | B82: =VLOOKUP(A82,Sheet1!A:B,2,0) -> RCS DEVICE | C82: Top cover | D82: 130040670021260 | E82: JEE | F82: Unique | G82: Plastic | H82: 2024 | I82: 7 | J82: 45590 | K82: 1 | L82: 2.3583409 | M82: 2.3583409 | N82: =M82-L82 -> 0 | O82: =N82*K82 -> 0 | P82: 1 | Q82: =P82*L82 -> 2.3583409 | R82: 43876 | S82: =R82+S78 -> 610823 | T82: 0 | U82: 0 | V82: LUPOY GP1000ML | X82: 16.26 | Y82: LG | Z82: Printing | AA82: 1.308 | AB82: =M82*R82 -> 103474.56 | AC82: =R82*AA82 -> 57389.808 | AD82: =R82*X82/1000 -> 713.42376
A83: KUMA E-Box NZ | B83: =VLOOKUP(A83,Sheet1!A:B,2,0) -> RCS DEVICE | C83: Bottom cover | D83: 130040670021261 | E83: JEE | F83: Unique | G83: Plastic | H83: 2024 | I83: 7 | J83: 45590 | K83: 1 | L83: 2.3165273 | M83: 2.3165273 | N83: =M83-L83 -> 0 | O83: =N83*K83 -> 0 | P83: 1 | Q83: =P83*L83 -> 2.3165273 | R83: 35090 | S83: =R83+S79 -> 686982 | T83: 0 | U83: 0 | V83: LUPOY GP1000ML | X83: 8.302 | Y83: LG | Z83: Printing | AA83: 1.428 | AB83: =M83*R83 -> 81286.942 | AC83: =R83*AA83 -> 50108.52 | AD83: =R83*X83/1000 -> 291.31718
A84: KUMA E-Box NZ | B84: =VLOOKUP(A84,Sheet1!A:B,2,0) -> RCS DEVICE | C84: Button | D84: 130040670021263 | E84: JEE | F84: Unique | G84: Plastic | H84: 2024 | I84: 7 | J84: 45590 | K84: 1 | L84: 0.37651638 | M84: 0.37651638 | N84: =M84-L84 -> 0 | O84: =N84*K84 -> 0 | P84: 1 | Q84: =P84*L84 -> 0.37651638 | R84: 46292 | S84: =R84+S80 -> 665191 | T84: 0 | U84: 0 | V84: LUPOY GP1000ML | X84: 0.572 | Y84: LG | AA84: 0 | AB84: =M84*R84 -> 17429.696 | AC84: =R84*AA84 -> 0 | AD84: =R84*X84/1000 -> 26.479024
A85: KUMA E-Box NZ | B85: =VLOOKUP(A85,Sheet1!A:B,2,0) -> RCS DEVICE | C85: PCB holder | D85: 130040670021262 | E85: JEE | F85: Unique | G85: Plastic | H85: 2024 | I85: 7 | J85: 45590 | K85: 1 | L85: 0.37927345 | M85: 0.37927345 | N85: =M85-L85 -> 0 | O85: =N85*K85 -> 0 | P85: 1 | Q85: =P85*L85 -> 0.37927345 | R85: 40000 | S85: =R85+S81 -> 655070 | T85: 0 | U85: 0 | V85: PC Makrolon 2456 | X85: 1.87 | Y85: Makrolon | AA85: 0 | AB85: =M85*R85 -> 15170.938 | AC85: =R85*AA85 -> 0 | AD85: =R85*X85/1000 -> 74.8
A86: KUMA E-Box NZ | B86: =VLOOKUP(A86,Sheet1!A:B,2,0) -> RCS DEVICE | C86: Top cover | D86: 130040670021260 | E86: JEE | F86: Unique | G86: Plastic | H86: 2024 | I86: 8 | J86: 45590 | K86: 1 | L86: 2.3583409 | M86: 2.3583409 | N86: =M86-L86 -> 0 | O86: =N86*K86 -> 0 | P86: 1 | Q86: =P86*L86 -> 2.3583409 | R86: 33780 | S86: =R86+S82 -> 644603 | T86: 0 | U86: 0 | V86: LUPOY GP1000ML | X86: 16.26 | Y86: LG | Z86: Printing | AA86: 1.308 | AB86: =M86*R86 -> 79664.754 | AC86: =R86*AA86 -> 44184.24 | AD86: =R86*X86/1000 -> 549.2628
A87: KUMA E-Box NZ | B87: =VLOOKUP(A87,Sheet1!A:B,2,0) -> RCS DEVICE | C87: Bottom cover | D87: 130040670021261 | E87: JEE | F87: Unique | G87: Plastic | H87: 2024 | I87: 8 | J87: 45590 | K87: 1 | L87: 2.3165273 | M87: 2.3165273 | N87: =M87-L87 -> 0 | O87: =N87*K87 -> 0 | P87: 1 | Q87: =P87*L87 -> 2.3165273 | R87: 0 | S87: =R87+S83 -> 686982 | T87: 0 | U87: 0 | V87: LUPOY GP1000ML | X87: 8.302 | Y87: LG | Z87: Printing | AA87: 1.428 | AB87: =M87*R87 -> 0 | AC87: =R87*AA87 -> 0 | AD87: =R87*X87/1000 -> 0
A88: KUMA E-Box NZ | B88: =VLOOKUP(A88,Sheet1!A:B,2,0) -> RCS DEVICE | C88: Button | D88: 130040670021263 | E88: JEE | F88: Unique | G88: Plastic | H88: 2024 | I88: 8 | J88: 45590 | K88: 1 | L88: 0.37651638 | M88: 0.37651638 | N88: =M88-L88 -> 0 | O88: =N88*K88 -> 0 | P88: 1 | Q88: =P88*L88 -> 0.37651638 | R88: 0 | S88: =R88+S84 -> 665191 | T88: 0 | U88: 0 | V88: LUPOY GP1000ML | X88: 0.572 | Y88: LG | AA88: 0 | AB88: =M88*R88 -> 0 | AC88: =R88*AA88 -> 0 | AD88: =R88*X88/1000 -> 0
A89: KUMA E-Box NZ | B89: =VLOOKUP(A89,Sheet1!A:B,2,0) -> RCS DEVICE | C89: PCB holder | D89: 130040670021262 | E89: JEE | F89: Unique | G89: Plastic | H89: 2024 | I89: 8 | J89: 45590 | K89: 1 | L89: 0.37927345 | M89: 0.37927345 | N89: =M89-L89 -> 0 | O89: =N89*K89 -> 0 | P89: 1 | Q89: =P89*L89 -> 0.37927345 | R89: 0 | S89: =R89+S85 -> 655070 | T89: 0 | U89: 0 | V89: PC Makrolon 2456 | X89: 1.87 | Y89: Makrolon | AA89: 0 | AB89: =M89*R89 -> 0 | AC89: =R89*AA89 -> 0 | AD89: =R89*X89/1000 -> 0
A90: KUMA E-Box NZ | B90: =VLOOKUP(A90,Sheet1!A:B,2,0) -> RCS DEVICE | C90: Top cover | D90: 130040670021260 | E90: JEE | F90: Unique | G90: Plastic | H90: 2024 | I90: 9 | J90: 45590 | K90: 1 | L90: 2.3583409 | M90: 2.3583409 | N90: =M90-L90 -> 0 | O90: =N90*K90 -> 0 | P90: 1 | Q90: =P90*L90 -> 2.3583409 | R90: 0 | S90: =R90+S86 -> 644603 | T90: 0 | U90: 0 | V90: LUPOY GP1000ML | X90: 16.26 | Y90: LG | Z90: Printing | AA90: 1.308 | AB90: =M90*R90 -> 0 | AC90: =R90*AA90 -> 0 | AD90: =R90*X90/1000 -> 0
A91: KUMA E-Box NZ | B91: =VLOOKUP(A91,Sheet1!A:B,2,0) -> RCS DEVICE | C91: Bottom cover | D91: 130040670021261 | E91: JEE | F91: Unique | G91: Plastic | H91: 2024 | I91: 9 | J91: 45590 | K91: 1 | L91: 2.3165273 | M91: 2.3165273 | N91: =M91-L91 -> 0 | O91: =N91*K91 -> 0 | P91: 1 | Q91: =P91*L91 -> 2.3165273 | R91: 0 | S91: =R91+S87 -> 686982 | T91: 0 | U91: 0 | V91: LUPOY GP1000ML | X91: 8.302 | Y91: LG | Z91: Printing | AA91: 1.428 | AB91: =M91*R91 -> 0 | AC91: =R91*AA91 -> 0 | AD91: =R91*X91/1000 -> 0
A92: KUMA E-Box NZ | B92: =VLOOKUP(A92,Sheet1!A:B,2,0) -> RCS DEVICE | C92: Button | D92: 130040670021263 | E92: JEE | F92: Unique | G92: Plastic | H92: 2024 | I92: 9 | J92: 45590 | K92: 1 | L92: 0.37651638 | M92: 0.37651638 | N92: =M92-L92 -> 0 | O92: =N92*K92 -> 0 | P92: 1 | Q92: =P92*L92 -> 0.37651638 | R92: 0 | S92: =R92+S88 -> 665191 | T92: 0 | U92: 0 | V92: LUPOY GP1000ML | X92: 0.572 | Y92: LG | AA92: 0 | AB92: =M92*R92 -> 0 | AC92: =R92*AA92 -> 0 | AD92: =R92*X92/1000 -> 0
A93: KUMA E-Box NZ | B93: =VLOOKUP(A93,Sheet1!A:B,2,0) -> RCS DEVICE | C93: PCB holder | D93: 130040670021262 | E93: JEE | F93: Unique | G93: Plastic | H93: 2024 | I93: 9 | J93: 45590 | K93: 1 | L93: 0.37927345 | M93: 0.37927345 | N93: =M93-L93 -> 0 | O93: =N93*K93 -> 0 | P93: 1 | Q93: =P93*L93 -> 0.37927345 | R93: 0 | S93: =R93+S89 -> 655070 | T93: 0 | U93: 0 | V93: PC Makrolon 2456 | X93: 1.87 | Y93: Makrolon | AA93: 0 | AB93: =M93*R93 -> 0 | AC93: =R93*AA93 -> 0 | AD93: =R93*X93/1000 -> 0
A94: KUMA E-Pen 1.0 ROW | B94: =VLOOKUP(A94,Sheet1!A:B,2,0) -> RCS DEVICE | C94: Battery tube | D94: 120020670031773 | E94: JEE | F94: Unique | G94: Plastic | H94: 2024 | I94: 5 | J94: 45590 | K94: 0.3 | L94: 1.8774416 | M94: 1.9124416 | N94: =M94-L94 -> 0.035 | O94: =N94*K94 -> 0.0105 | P94: 1 | Q94: =P94*L94 -> 1.8774416 | R94: 3937 | S94: =R94 -> 3937 | T94: 280000 | U94: =T94-N94*S94 -> 279862.21 | V94: PC LUPOY GP1000ML | X94: 6.539 | Y94: LG | Z94: Printing | AA94: 1.2 | AB94: =M94*R94 -> 7529.2826 | AC94: =R94*AA94 -> 4724.4 | AD94: =R94*X94/1000 -> 25.744043
A95: KUMA E-Pen 1.0 ROW | B95: =VLOOKUP(A95,Sheet1!A:B,2,0) -> RCS DEVICE | C95: Bottom cap | D95: 130020670031775 | E95: JEE | F95: Unique | G95: Plastic | H95: 2024 | I95: 5 | J95: 45590 | K95: 0.3 | L95: 0.27335793 | M95: 0.33085793 | N95: =M95-L95 -> 0.0575 | O95: =N95*K95 -> 0.01725 | P95: 1 | Q95: =P95*L95 -> 0.27335793 | R95: 3950 | S95: =R95 -> 3950 | T95: 460000 | U95: =T95-N95*S95 -> 459772.88 | V95: PC LUPOY GP1000ML | X95: 3.317 | Y95: LG | AA95: 0 | AB95: =M95*R95 -> 1306.8888 | AC95: =R95*AA95 -> 0 | AD95: =R95*X95/1000 -> 13.10215
A96: KUMA E-Pen 1.0 ROW | B96: =VLOOKUP(A96,Sheet1!A:B,2,0) -> RCS DEVICE | C96: Holder | D96: 130020670031776 | E96: JEE | F96: Unique | G96: Plastic | H96: 2024 | I96: 5 | J96: 45590 | K96: 0.3 | L96: 0.20453293 | M96: 0.23078293 | N96: =M96-L96 -> 0.02625 | O96: =N96*K96 -> 0.007875 | P96: 1 | Q96: =P96*L96 -> 0.20453293 | R96: 3600 | S96: =R96 -> 3600 | T96: 420000 | U96: =T96-N96*S96 -> 419905.5 | V96: PC Makrolon 2456 | X96: 4.247 | Y96: Makrolon | AA96: 0 | AB96: =M96*R96 -> 830.81856 | AC96: =R96*AA96 -> 0 | AD96: =R96*X96/1000 -> 15.2892
A97: KUMA E-Pen 1.0 ROW | B97: =VLOOKUP(A97,Sheet1!A:B,2,0) -> RCS DEVICE | C97: Button | D97: 130020670031777 | E97: JEE | F97: Unique | G97: Plastic | H97: 2024 | I97: 5 | J97: 45590 | K97: 0.3 | L97: 0.12026275 | M97: 0.14526275 | N97: =M97-L97 -> 0.025 | O97: =N97*K97 -> 0.0075 | P97: 1 | Q97: =P97*L97 -> 0.12026275 | R97: 3950 | S97: =R97 -> 3950 | T97: 400000 | U97: =T97-N97*S97 -> 399901.25 | V97: PC Makrolon 2456 | X97: 0.535 | Y97: Makrolon | AA97: 0 | AB97: =M97*R97 -> 573.78786 | AC97: =R97*AA97 -> 0 | AD97: =R97*X97/1000 -> 2.11325
A98: KUMA E-Pen 1.0 ROW | B98: =VLOOKUP(A98,Sheet1!A:B,2,0) -> RCS DEVICE | C98: Light guide | D98: 130020670035243 | E98: JEE | F98: Unique | G98: Plastic | H98: 2024 | I98: 5 | J98: 45590 | K98: 0.3 | L98: 0.12248804 | M98: 0.14748804 | N98: =M98-L98 -> 0.025 | O98: =N98*K98 -> 0.0075 | P98: 1 | Q98: =P98*L98 -> 0.12248804 | R98: 3350 | S98: =R98 -> 3350 | T98: 400000 | U98: =T98-N98*S98 -> 399916.25 | V98: PC LUPOY GP1000ML | X98: 0.509 | Y98: LG | AA98: 0 | AB98: =M98*R98 -> 494.08494 | AC98: =R98*AA98 -> 0 | AD98: =R98*X98/1000 -> 1.70515
A99: KUMA E-Pen 1.0 ROW | B99: =VLOOKUP(A99,Sheet1!A:B,2,0) -> RCS DEVICE | C99: Battery tube | D99: 120020670031773 | E99: JEE | F99: Unique | G99: Plastic | H99: 2024 | I99: 6 | J99: 45590 | K99: 0.3 | L99: 1.8774416 | M99: 1.9124416 | N99: =M99-L99 -> 0.035 | O99: =N99*K99 -> 0.0105 | P99: 1 | Q99: =P99*L99 -> 1.8774416 | R99: 2300 | S99: =S94+R99 -> 6237 | T99: 280000 | U99: =T99-N99*S99 -> 279781.71 | V99: PC LUPOY GP1000ML | X99: 6.539 | Y99: LG | Z99: Printing | AA99: 1.2 | AB99: =M99*R99 -> 4398.6157 | AC99: =R99*AA99 -> 2760 | AD99: =R99*X99/1000 -> 15.0397
A100: KUMA E-Pen 1.0 ROW | B100: =VLOOKUP(A100,Sheet1!A:B,2,0) -> RCS DEVICE | C100: Bottom cap | D100: 130020670031775 | E100: JEE | F100: Unique | G100: Plastic | H100: 2024 | I100: 6 | J100: 45590 | K100: 0.3 | L100: 0.27335793 | M100: 0.33085793 | N100: =M100-L100 -> 0.0575 | O100: =N100*K100 -> 0.01725 | P100: 1 | Q100: =P100*L100 -> 0.27335793 | R100: 2300 | S100: =S95+R100 -> 6250 | T100: 460000 | U100: =T100-N100*S100 -> 459640.62 | V100: PC LUPOY GP1000ML | X100: 3.317 | Y100: LG | AA100: 0 | AB100: =M100*R100 -> 760.97323 | AC100: =R100*AA100 -> 0 | AD100: =R100*X100/1000 -> 7.6291
A101: KUMA E-Pen 1.0 ROW | B101: =VLOOKUP(A101,Sheet1!A:B,2,0) -> RCS DEVICE | C101: Holder | D101: 130020670031776 | E101: JEE | F101: Unique | G101: Plastic | H101: 2024 | I101: 6 | J101: 45590 | K101: 0.3 | L101: 0.20453293 | M101: 0.23078293 | N101: =M101-L101 -> 0.02625 | O101: =N101*K101 -> 0.007875 | P101: 1 | Q101: =P101*L101 -> 0.20453293 | R101: 12000 | S101: =S96+R101 -> 15600 | T101: 420000 | U101: =T101-N101*S101 -> 419590.5 | V101: PC Makrolon 2456 | X101: 4.247 | Y101: Makrolon | AA101: 0 | AB101: =M101*R101 -> 2769.3952 | AC101: =R101*AA101 -> 0 | AD101: =R101*X101/1000 -> 50.964
A102: KUMA E-Pen 1.0 ROW | B102: =VLOOKUP(A102,Sheet1!A:B,2,0) -> RCS DEVICE | C102: Button | D102: 130020670031777 | E102: JEE | F102: Unique | G102: Plastic | H102: 2024 | I102: 6 | J102: 45590 | K102: 0.3 | L102: 0.12026275 | M102: 0.14526275 | N102: =M102-L102 -> 0.025 | O102: =N102*K102 -> 0.0075 | P102: 1 | Q102: =P102*L102 -> 0.12026275 | R102: 1800 | S102: =S97+R102 -> 5750 | T102: 400000 | U102: =T102-N102*S102 -> 399856.25 | V102: PC Makrolon 2456 | X102: 0.535 | Y102: Makrolon | AA102: 0 | AB102: =M102*R102 -> 261.47295 | AC102: =R102*AA102 -> 0 | AD102: =R102*X102/1000 -> 0.963
A103: KUMA E-Pen 1.0 ROW | B103: =VLOOKUP(A103,Sheet1!A:B,2,0) -> RCS DEVICE | C103: Light guide | D103: 130020670035243 | E103: JEE | F103: Unique | G103: Plastic | H103: 2024 | I103: 6 | J103: 45590 | K103: 0.3 | L103: 0.12248804 | M103: 0.14748804 | N103: =M103-L103 -> 0.025 | O103: =N103*K103 -> 0.0075 | P103: 1 | Q103: =P103*L103 -> 0.12248804 | R103: 0 | S103: =S98+R103 -> 3350 | T103: 400000 | U103: =T103-N103*S103 -> 399916.25 | V103: PC LUPOY GP1000ML | X103: 0.509 | Y103: LG | AA103: 0 | AB103: =M103*R103 -> 0 | AC103: =R103*AA103 -> 0 | AD103: =R103*X103/1000 -> 0
A104: KUMA E-Pen 1.0 ROW | B104: =VLOOKUP(A104,Sheet1!A:B,2,0) -> RCS DEVICE | C104: Battery tube | D104: 120020670031773 | E104: JEE | F104: Unique | G104: Plastic | H104: 2024 | I104: 7 | J104: 45590 | K104: 0.3 | L104: 1.8774416 | M104: 1.9124416 | N104: =M104-L104 -> 0.035 | O104: =N104*K104 -> 0.0105 | P104: 1 | Q104: =P104*L104 -> 1.8774416 | R104: 23150 | S104: =S99+R104 -> 29387 | T104: 280000 | U104: =T104-N104*S104 -> 278971.46 | V104: PC LUPOY GP1000ML | X104: 6.539 | Y104: LG | Z104: Printing | AA104: 1.2 | AB104: =M104*R104 -> 44273.023 | AC104: =R104*AA104 -> 27780 | AD104: =R104*X104/1000 -> 151.37785
A105: KUMA E-Pen 1.0 ROW | B105: =VLOOKUP(A105,Sheet1!A:B,2,0) -> RCS DEVICE | C105: Bottom cap | D105: 130020670031775 | E105: JEE | F105: Unique | G105: Plastic | H105: 2024 | I105: 7 | J105: 45590 | K105: 0.3 | L105: 0.27335793 | M105: 0.33085793 | N105: =M105-L105 -> 0.0575 | O105: =N105*K105 -> 0.01725 | P105: 1 | Q105: =P105*L105 -> 0.27335793 | R105: 111670 | S105: =S100+R105 -> 117920 | T105: 460000 | U105: =T105-N105*S105 -> 453219.6 | V105: PC LUPOY GP1000ML | X105: 3.317 | Y105: LG | AA105: 0 | AB105: =M105*R105 -> 36946.905 | AC105: =R105*AA105 -> 0 | AD105: =R105*X105/1000 -> 370.40939
A106: KUMA E-Pen 1.0 ROW | B106: =VLOOKUP(A106,Sheet1!A:B,2,0) -> RCS DEVICE | C106: Holder | D106: 130020670031776 | E106: JEE | F106: Unique | G106: Plastic | H106: 2024 | I106: 7 | J106: 45590 | K106: 0.3 | L106: 0.20453293 | M106: 0.23078293 | N106: =M106-L106 -> 0.02625 | O106: =N106*K106 -> 0.007875 | P106: 1 | Q106: =P106*L106 -> 0.20453293 | R106: 139000 | S106: =S101+R106 -> 154600 | T106: 420000 | U106: =T106-N106*S106 -> 415941.75 | V106: PC Makrolon 2456 | X106: 4.247 | Y106: Makrolon | AA106: 0 | AB106: =M106*R106 -> 32078.828 | AC106: =R106*AA106 -> 0 | AD106: =R106*X106/1000 -> 590.333
A107: KUMA E-Pen 1.0 ROW | B107: =VLOOKUP(A107,Sheet1!A:B,2,0) -> RCS DEVICE | C107: Button | D107: 130020670031777 | E107: JEE | F107: Unique | G107: Plastic | H107: 2024 | I107: 7 | J107: 45590 | K107: 0.3 | L107: 0.12026275 | M107: 0.14526275 | N107: =M107-L107 -> 0.025 | O107: =N107*K107 -> 0.0075 | P107: 1 | Q107: =P107*L107 -> 0.12026275 | R107: 135940 | S107: =S102+R107 -> 141690 | T107: 400000 | U107: =T107-N107*S107 -> 396457.75 | V107: PC Makrolon 2456 | X107: 0.535 | Y107: Makrolon | AA107: 0 | AB107: =M107*R107 -> 19747.018 | AC107: =R107*AA107 -> 0 | AD107: =R107*X107/1000 -> 72.7279
A108: KUMA E-Pen 1.0 ROW | B108: =VLOOKUP(A108,Sheet1!A:B,2,0) -> RCS DEVICE | C108: Light guide | D108: 130020670035243 | E108: JEE | F108: Unique | G108: Plastic | H108: 2024 | I108: 7 | J108: 45590 | K108: 0.3 | L108: 0.12248804 | M108: 0.14748804 | N108: =M108-L108 -> 0.025 | O108: =N108*K108 -> 0.0075 | P108: 1 | Q108: =P108*L108 -> 0.12248804 | R108: 313200 | S108: =S103+R108 -> 316550 | T108: 400000 | U108: =T108-N108*S108 -> 392086.25 | V108: PC LUPOY GP1000ML | X108: 0.509 | Y108: LG | AA108: 0 | AB108: =M108*R108 -> 46193.255 | AC108: =R108*AA108 -> 0 | AD108: =R108*X108/1000 -> 159.4188
A109: KUMA E-Pen 1.0 ROW | B109: =VLOOKUP(A109,Sheet1!A:B,2,0) -> RCS DEVICE | C109: Battery tube | D109: 120020670031773 | E109: JEE | F109: Unique | G109: Plastic | H109: 2024 | I109: 8 | J109: 45590 | K109: 0.3 | L109: 1.8774416 | M109: 1.9124416 | N109: =M109-L109 -> 0.035 | O109: =N109*K109 -> 0.0105 | P109: 1 | Q109: =P109*L109 -> 1.8774416 | R109: 214361 | S109: =S104+R109 -> 243748 | T109: 280000 | U109: =T109-N109*S109 -> 271468.82 | V109: PC LUPOY GP1000ML | X109: 6.539 | Y109: LG | Z109: Printing | AA109: 1.2 | AB109: =M109*R109 -> 409952.9 | AC109: =R109*AA109 -> 257233.2 | AD109: =R109*X109/1000 -> 1401.7066
A110: KUMA E-Pen 1.0 ROW | B110: =VLOOKUP(A110,Sheet1!A:B,2,0) -> RCS DEVICE | C110: Bottom cap | D110: 130020670031775 | E110: JEE | F110: Unique | G110: Plastic | H110: 2024 | I110: 8 | J110: 45590 | K110: 0.3 | L110: 0.27335793 | M110: 0.33085793 | N110: =M110-L110 -> 0.0575 | O110: =N110*K110 -> 0.01725 | P110: 1 | Q110: =P110*L110 -> 0.27335793 | R110: 432465 | S110: =S105+R110 -> 550385 | T110: 460000 | U110: =T110-N110*S110 -> 428352.86 | V110: PC LUPOY GP1000ML | X110: 3.317 | Y110: LG | AA110: 0 | AB110: =M110*R110 -> 143084.47 | AC110: =R110*AA110 -> 0 | AD110: =R110*X110/1000 -> 1434.4864
A111: KUMA E-Pen 1.0 ROW | B111: =VLOOKUP(A111,Sheet1!A:B,2,0) -> RCS DEVICE | C111: Holder | D111: 130020670031776 | E111: JEE | F111: Unique | G111: Plastic | H111: 2024 | I111: 8 | J111: 45590 | K111: 0.3 | L111: 0.20453293 | M111: 0.23078293 | N111: =M111-L111 -> 0.02625 | O111: =N111*K111 -> 0.007875 | P111: 1 | Q111: =P111*L111 -> 0.20453293 | R111: 876117 | S111: =S106+R111 -> 1030717 | T111: 420000 | U111: =T111-N111*S111 -> 392943.68 | V111: PC Makrolon 2456 | X111: 4.247 | Y111: Makrolon | AA111: 0 | AB111: =M111*R111 -> 202192.85 | AC111: =R111*AA111 -> 0 | AD111: =R111*X111/1000 -> 3720.8689
A112: KUMA E-Pen 1.0 ROW | B112: =VLOOKUP(A112,Sheet1!A:B,2,0) -> RCS DEVICE | C112: Button | D112: 130020670031777 | E112: JEE | F112: Unique | G112: Plastic | H112: 2024 | I112: 8 | J112: 45590 | K112: 0.3 | L112: 0.12026275 | M112: 0.14526275 | N112: =M112-L112 -> 0.025 | O112: =N112*K112 -> 0.0075 | P112: 1 | Q112: =P112*L112 -> 0.12026275 | R112: 674635 | S112: =S107+R112 -> 816325 | T112: 400000 | U112: =T112-N112*S112 -> 379591.88 | V112: PC Makrolon 2456 | X112: 0.535 | Y112: Makrolon | AA112: 0 | AB112: =M112*R112 -> 97999.335 | AC112: =R112*AA112 -> 0 | AD112: =R112*X112/1000 -> 360.92973
A113: KUMA E-Pen 1.0 ROW | B113: =VLOOKUP(A113,Sheet1!A:B,2,0) -> RCS DEVICE | C113: Light guide | D113: 130020670035243 | E113: JEE | F113: Unique | G113: Plastic | H113: 2024 | I113: 8 | J113: 45590 | K113: 0.3 | L113: 0.12248804 | M113: 0.14748804 | N113: =M113-L113 -> 0.025 | O113: =N113*K113 -> 0.0075 | P113: 1 | Q113: =P113*L113 -> 0.12248804 | R113: 653125 | S113: =S108+R113 -> 969675 | T113: 400000 | U113: =T113-N113*S113 -> 375758.12 | V113: PC LUPOY GP1000ML | X113: 0.509 | Y113: LG | AA113: 0 | AB113: =M113*R113 -> 96328.127 | AC113: =R113*AA113 -> 0 | AD113: =R113*X113/1000 -> 332.44063
A114: KUMA E-Pen 1.0 ROW | B114: =VLOOKUP(A114,Sheet1!A:B,2,0) -> RCS DEVICE | C114: Battery tube | D114: 120020670031773 | E114: JEE | F114: Unique | G114: Plastic | H114: 2024 | I114: 9 | J114: 45590 | K114: 0.3 | L114: 1.8774416 | M114: 1.9124416 | N114: =M114-L114 -> 0.035 | O114: =N114*K114 -> 0.0105 | P114: 1 | Q114: =P114*L114 -> 1.8774416 | R114: 246042 | S114: =S109+R114 -> 489790 | T114: 280000 | U114: =T114-N114*S114 -> 262857.35 | V114: PC LUPOY GP1000ML | X114: 6.539 | Y114: LG | Z114: Printing | AA114: 1.2 | AB114: =M114*R114 -> 470540.96 | AC114: =R114*AA114 -> 295250.4 | AD114: =R114*X114/1000 -> 1608.8686
A115: KUMA E-Pen 1.0 ROW | B115: =VLOOKUP(A115,Sheet1!A:B,2,0) -> RCS DEVICE | C115: Bottom cap | D115: 130020670031775 | E115: JEE | F115: Unique | G115: Plastic | H115: 2024 | I115: 9 | J115: 45590 | K115: 0.3 | L115: 0.27335793 | M115: 0.33085793 | N115: =M115-L115 -> 0.0575 | O115: =N115*K115 -> 0.01725 | P115: 1 | Q115: =P115*L115 -> 0.27335793 | R115: 360351 | S115: =S110+R115 -> 910736 | T115: 460000 | U115: =T115-N115*S115 -> 407632.68 | V115: PC LUPOY GP1000ML | X115: 3.317 | Y115: LG | AA115: 0 | AB115: =M115*R115 -> 119224.98 | AC115: =R115*AA115 -> 0 | AD115: =R115*X115/1000 -> 1195.2843
A116: KUMA E-Pen 1.0 ROW | B116: =VLOOKUP(A116,Sheet1!A:B,2,0) -> RCS DEVICE | C116: Holder | D116: 130020670031776 | E116: JEE | F116: Unique | G116: Plastic | H116: 2024 | I116: 9 | J116: 45590 | K116: 0.3 | L116: 0.20453293 | M116: 0.23078293 | N116: =M116-L116 -> 0.02625 | O116: =N116*K116 -> 0.007875 | P116: 1 | Q116: =P116*L116 -> 0.20453293 | R116: 833120 | S116: =S111+R116 -> 1863837 | T116: 420000 | U116: =T116-N116*S116 -> 371074.28 | V116: PC Makrolon 2456 | X116: 4.247 | Y116: Makrolon | AA116: 0 | AB116: =M116*R116 -> 192269.88 | AC116: =R116*AA116 -> 0 | AD116: =R116*X116/1000 -> 3538.2606
A117: KUMA E-Pen 1.0 ROW | B117: =VLOOKUP(A117,Sheet1!A:B,2,0) -> RCS DEVICE | C117: Button | D117: 130020670031777 | E117: JEE | F117: Unique | G117: Plastic | H117: 2024 | I117: 9 | J117: 45590 | K117: 0.3 | L117: 0.12026275 | M117: 0.14526275 | N117: =M117-L117 -> 0.025 | O117: =N117*K117 -> 0.0075 | P117: 1 | Q117: =P117*L117 -> 0.12026275 | R117: 733954 | S117: =S112+R117 -> 1550279 | T117: 400000 | U117: =T117-N117*S117 -> 361243.03 | V117: PC Makrolon 2456 | X117: 0.535 | Y117: Makrolon | AA117: 0 | AB117: =M117*R117 -> 106616.18 | AC117: =R117*AA117 -> 0 | AD117: =R117*X117/1000 -> 392.66539
A118: KUMA E-Pen 1.0 ROW | B118: =VLOOKUP(A118,Sheet1!A:B,2,0) -> RCS DEVICE | C118: Light guide | D118: 130020670035243 | E118: JEE | F118: Unique | G118: Plastic | H118: 2024 | I118: 9 | J118: 45590 | K118: 0.3 | L118: 0.12248804 | M118: 0.14748804 | N118: =M118-L118 -> 0.025 | O118: =N118*K118 -> 0.0075 | P118: 1 | Q118: =P118*L118 -> 0.12248804 | R118: 875525 | S118: =S113+R118 -> 1845200 | T118: 400000 | U118: =T118-N118*S118 -> 353870 | V118: PC LUPOY GP1000ML | X118: 0.509 | Y118: LG | AA118: 0 | AB118: =M118*R118 -> 129129.47 | AC118: =R118*AA118 -> 0 | AD118: =R118*X118/1000 -> 445.64223
A119: Prismatic Pod | B119: =VLOOKUP(A119,Sheet1!A:B,2,0) -> RCS POD | C119: Cartomizer tube | D119: 130010390000214 | E119: JEE | F119: Unique | G119: Plastic | H119: 2023 | I119: 3 | J119: 45590 | K119: 1 | L119: 0.97679221 | M119: 0.97985471 | N119: =M119-L119 -> 0.0030625 | O119: =N119*K119 -> 0.0030625 | P119: 1 | Q119: =P119*L119 -> 0.97679221 | R119: 21270 | S119: =R119 -> 21270 | T119: 98000 | U119: =T119-N119*S119 -> 97934.861 | V119: PCTG TX1501HF | X119: 2.09 | Y119: Eastman | AA119: 0.93117705 | AB119: =M119*R119 -> 20841.51 | AC119: =R119*AA119 -> 19806.136 | AD119: =R119*X119/1000 -> 44.4543 | AE119: China- Black (Capex no including mold injection tools)
A120: Prismatic Pod | B120: =VLOOKUP(A120,Sheet1!A:B,2,0) -> RCS POD | C120: Cartomizer tube | D120: 130010390000214 | E120: JEE | F120: Unique | G120: Plastic | H120: 2023 | I120: 4 | J120: 45590 | K120: 1 | L120: 0.97679221 | M120: 0.97985471 | N120: =M120-L120 -> 0.0030625 | O120: =N120*K120 -> 0.0030625 | P120: 1 | Q120: =P120*L120 -> 0.97679221 | R120: 3152752 | S120: =S119+R120 -> 3174022 | T120: 98000 | U120: =T120-N120*S120 -> 88279.558 | V120: PCTG TX1501HF | X120: 2.09 | Y120: Eastman | AA120: 0.93117705 | AB120: =M120*R120 -> 3089238.9 | AC120: =R120*AA120 -> 2935770.3 | AD120: =R120*X120/1000 -> 6589.2517 | AE120: China- Black (Capex no including mold injection tools)
A121: Prismatic Pod | B121: =VLOOKUP(A121,Sheet1!A:B,2,0) -> RCS POD | C121: Cartomizer tube | D121: 130010390000214 | E121: JEE | F121: Unique | G121: Plastic | H121: 2023 | I121: 5 | J121: 45590 | K121: 1 | L121: 0.97679221 | M121: 0.97985471 | N121: =M121-L121 -> 0.0030625 | O121: =N121*K121 -> 0.0030625 | P121: 1 | Q121: =P121*L121 -> 0.97679221 | R121: 1753316 | S121: =S120+R121 -> 4927338 | T121: 98000 | U121: =T121-N121*S121 -> 82910.027 | V121: PCTG TX1501HF | X121: 2.09 | Y121: Eastman | AA121: 0.93117705 | AB121: =M121*R121 -> 1717994.9 | AC121: =R121*AA121 -> 1632647.6 | AD121: =R121*X121/1000 -> 3664.4304 | AE121: China- Black (Capex no including mold injection tools)
A122: Prismatic Pod | B122: =VLOOKUP(A122,Sheet1!A:B,2,0) -> RCS POD | C122: Cartomizer tube | D122: 130010390000214 | E122: JEE | F122: Unique | G122: Plastic | H122: 2023 | I122: 6 | J122: 45590 | K122: 1 | L122: 0.97679221 | M122: 0.97985471 | N122: =M122-L122 -> 0.0030625 | O122: =N122*K122 -> 0.0030625 | P122: 1 | Q122: =P122*L122 -> 0.97679221 | R122: 367792 | S122: =S121+R122 -> 5295130 | T122: 98000 | U122: =T122-N122*S122 -> 81783.664 | V122: PCTG TX1501HF | X122: 2.09 | Y122: Eastman | AA122: 0.93117705 | AB122: =M122*R122 -> 360382.72 | AC122: =R122*AA122 -> 342479.47 | AD122: =R122*X122/1000 -> 768.68528 | AE122: China- Black (Capex no including mold injection tools)
A123: Prismatic Pod | B123: =VLOOKUP(A123,Sheet1!A:B,2,0) -> RCS POD | C123: Cartomizer tube | D123: 130010390000214 | E123: JEE | F123: Unique | G123: Plastic | H123: 2023 | I123: 7 | J123: 45590 | K123: 1 | L123: 0.97679221 | M123: 0.97985471 | N123: =M123-L123 -> 0.0030625 | O123: =N123*K123 -> 0.0030625 | P123: 1 | Q123: =P123*L123 -> 0.97679221 | R123: 1991913 | S123: =S122+R123 -> 7287043 | T123: 98000 | U123: =T123-N123*S123 -> 75683.431 | V123: PCTG TX1501HF | X123: 2.09 | Y123: Eastman | AA123: 0.93117705 | AB123: =M123*R123 -> 1951785.3 | AC123: =R123*AA123 -> 1854823.7 | AD123: =R123*X123/1000 -> 4163.0982 | AE123: China- Black (Capex no including mold injection tools)
A124: Prismatic Pod | B124: =VLOOKUP(A124,Sheet1!A:B,2,0) -> RCS POD | C124: Cartomizer tube | D124: 130010390000214 | E124: JEE | F124: Unique | G124: Plastic | H124: 2023 | I124: 8 | J124: 45590 | K124: 1 | L124: 0.97679221 | M124: 0.97985471 | N124: =M124-L124 -> 0.0030625 | O124: =N124*K124 -> 0.0030625 | P124: 1 | Q124: =P124*L124 -> 0.97679221 | R124: 2159574 | S124: =S123+R124 -> 9446617 | T124: 98000 | U124: =T124-N124*S124 -> 69069.735 | V124: PCTG TX1501HF | X124: 2.09 | Y124: Eastman | AA124: 0.93117705 | AB124: =M124*R124 -> 2116068.8 | AC124: =R124*AA124 -> 2010945.7 | AD124: =R124*X124/1000 -> 4513.5097 | AE124: China- Black (Capex no including mold injection tools)
A125: Prismatic Pod | B125: =VLOOKUP(A125,Sheet1!A:B,2,0) -> RCS POD | C125: Cartomizer tube | D125: 130010390000214 | E125: JEE | F125: Unique | G125: Plastic | H125: 2023 | I125: 9 | J125: 45590 | K125: 1 | L125: 0.97679221 | M125: 0.97985471 | N125: =M125-L125 -> 0.0030625 | O125: =N125*K125 -> 0.0030625 | P125: 1 | Q125: =P125*L125 -> 0.97679221 | R125: 734433 | S125: =S124+R125 -> 10181050 | T125: 98000 | U125: =T125-N125*S125 -> 66820.534 | V125: PCTG TX1501HF | X125: 2.09 | Y125: Eastman | AA125: 0.93117705 | AB125: =M125*R125 -> 719637.63 | AC125: =R125*AA125 -> 683887.15 | AD125: =R125*X125/1000 -> 1534.965 | AE125: China- Black (Capex no including mold injection tools)
A126: Prismatic Pod | B126: =VLOOKUP(A126,Sheet1!A:B,2,0) -> RCS POD | C126: Cartomizer tube | D126: 130010390000214 | E126: JEE | F126: Unique | G126: Plastic | H126: 2024 | I126: 9 | J126: 45590 | K126: 1 | L126: 1.0541285 | M126: 1.223652 | N126: =M126-L126 -> 0.16952346 | O126: =N126*K126 -> 0.16952346 | P126: 1 | Q126: =P126*L126 -> 1.0541285 | R126: 0 | S126: =R126 -> 0 | T126: =5424750.84955752-(2800000*30%) -> 4584750.8 | U126: =T126-N126*S126 -> 4584750.8 | V126: PCTG TX1501HF | X126: 2.09 | Y126: Eastman | AA126: =L126-L291 -> 0.9411585 | AB126: =M126*R126 -> 0 | AC126: =R126*AA126 -> 0 | AD126: =R126*X126/1000 -> 0 | AE126: Indonesia- Black (Capex no including mold injection tools)
A127: Prismatic Pod | B127: =VLOOKUP(A127,Sheet1!A:B,2,0) -> RCS POD | C127: Cartomizer tube | D127: 130010390000214 | E127: JEE | F127: Unique | G127: Plastic | H127: 2024 | I127: 9 | J127: 45590 | K127: 1 | L127: 1.1741172 | M127: 1.3582877 | N127: =M127-L127 -> 0.18417051 | O127: =N127*K127 -> 0.18417051 | P127: 1 | Q127: =P127*L127 -> 1.1741172 | R127: 0 | S127: =R127 -> 0 | T127: =5893456.35840708-(2800000*70%) -> 3933456.4 | U127: =T127-N127*S127 -> 3933456.4 | V127: PCTG TX1501HF | X127: 2.09 | Y127: Eastman | AA127: =L127-L291 -> 1.0611472 | AB127: =M127*R127 -> 0 | AC127: =R127*AA127 -> 0 | AD127: =R127*X127/1000 -> 0 | AE127: Indonesia- White(Capex no including mold injection tools)
A128: Hyper Pro | B128: =VLOOKUP(A128,Sheet1!A:B,2,0) -> HP | C128: Botton cover | D128: 22150202014 | E128: JEE | F128: X3 Pro/unibody/Core | G128: Plastic | H128: 2023 | I128: 12 | J128: 45590 | K128: 0.4 | L128: =M128-N128 -> 2.3162 | M128: 2.3537 | N128: 0.0375 | O128: =N128*K128 -> 0.015 | P128: 1 | Q128: =P128*L128 -> 2.3162 | R128: 374403 | S128: =R128 -> 374403 | T128: 105000 | U128: =T128-N128*S128 -> 90959.887 | V128: RTP 299 AX 152528（PA+GF）(panting(5 color)) | X128: 1.555 | Y128: Ruicheng | Z128: Painting | AA128: 1.9423 | AB128: =M128*R128 -> 881232.34 | AC128: =R128*AA128 -> 727202.95 | AD128: =R128*X128/1000 -> 582.19666
A129: Hyper Pro | B129: =VLOOKUP(A129,Sheet1!A:B,2,0) -> HP | C129: Cleanout door | D129: 22150202015 | E129: JEE | F129: X3 Pro/unibody/Core | G129: Plastic | H129: 2023 | I129: 12 | J129: 45590 | K129: 0.6 | L129: =M129-N129 -> 1.5443588 | M129: 1.6338826 | N129: 0.08952381 | O129: =N129*K129 -> 0.053714286 | P129: 1 | Q129: =P129*L129 -> 1.5443588 | R129: 354871 | S129: =R129 -> 354871 | T129: 376000 | U129: =T129-N129*S129 -> 344230.6 | V129: PC:LG LUPOY SC1004L(panting(5 color))+ TPU:BASF ELASTONLLAN 1190A | X129: 1.745 | Y129: Ruicheng | Z129: Painting | AA129: 1.1438 | AB129: =M129*R129 -> 579817.56 | AC129: =R129*AA129 -> 405901.45 | AD129: =R129*X129/1000 -> 619.2499
A130: Hyper Pro | B130: =VLOOKUP(A130,Sheet1!A:B,2,0) -> HP | C130: Button | D130: 22150202010 | E130: JEE | F130: X3 Pro/unibody | G130: Plastic | H130: 2023 | I130: 12 | J130: 45590 | K130: 0.4 | L130: =M130-N130 -> 0.916225 | M130: 1.1621 | N130: 0.245875 | O130: =N130*K130 -> 0.09835 | P130: 1 | Q130: =P130*L130 -> 0.916225 | R130: 495791 | S130: =R130 -> 495791 | T130: 98350 | U130: =T130-N130*S130 -> -23552.612 | V130: PC:LG LUPOY SC1004L-Colored | X130: 0.579 | Y130: Ruicheng | Z130: Painting | AA130: 0.7559 | AB130: =M130*R130 -> 576158.72 | AC130: =R130*AA130 -> 374768.42 | AD130: =R130*X130/1000 -> 287.06299
A131: Hyper Pro | B131: =VLOOKUP(A131,Sheet1!A:B,2,0) -> HP | C131: Crown Support | D131: 22150202008 | E131: JEE | F131: X3 Pro | G131: Plastic | H131: 2023 | I131: 12 | J131: 45590 | K131: 0.5 | L131: =M131-N131 -> 0.1278 | M131: 0.1558 | N131: 0.028 | O131: =N131*K131 -> 0.014 | P131: 1 | Q131: =P131*L131 -> 0.1278 | R131: 457257 | S131: =R131 -> 457257 | T131: =98000+12600 -> 110600 | U131: =T131-N131*S131 -> 97796.804 | V131: POM C9021 black | X131: 0.763 | Y131: Ruicheng | AA131: 0 | AB131: =M131*R131 -> 71240.641 | AC131: =R131*AA131 -> 0 | AD131: =R131*X131/1000 -> 348.88709
A132: Hyper Pro | B132: =VLOOKUP(A132,Sheet1!A:B,2,0) -> HP | C132: Connector frame | D132: 22150202017 | E132: JEE | F132: X3 Pro | G132: Plastic | H132: 2023 | I132: 12 | J132: 45590 | K132: 0.4 | L132: =M132-N132 -> 0.1725 | M132: 0.4175 | N132: 0.245 | O132: =N132*K132 -> 0.098 | P132: 1 | Q132: =P132*L132 -> 0.1725 | R132: 314717 | S132: =R132 -> 314717 | T132: 98000 | U132: =T132-N132*S132 -> 20894.335 | V132: PC(PCR):LUPOY ER1000MA_RC00101 | X132: 1.173 | Y132: Ruicheng | AA132: 0 | AB132: =M132*R132 -> 131394.35 | AC132: =R132*AA132 -> 0 | AD132: =R132*X132/1000 -> 369.16304
...

Sheet Capex tracker
A1: Tool type | B1: Soft tool | C1: Soft tool EC | D1: Hard tool | E1: Hard tool EC | G1: 45706
A2: Product category | B2: RCS POD | C2: RCS DEVICE | D2: MODI | E2: HP | F2: MO
A3: Project | B3: Product Category | C3: Part Name | D3: Part No. | E3: Supplier | F3: Year | G3: Month | H3: Stage | I3: Data Submit Date | J3: Cavity | K3: Tooling Capacity Per Month | L3: Total Capacity Per Month | M3: Tooling life | N3: Tool type | O3: Kick off date | P3: Tool Unit cost | Q3: Q'ty | R3: Total Tool cost | S3: Requested by Whom | T3: Approval Status | U3: Payment Status | V3: Remark
A4: VEGA | B4: =VLOOKUP(A4,Sheet1!A:B,2,0) -> MODI | C4: Mouth Piece | D4: 310493191000 | E4: JEE | F4: 2023 | G4: 3 | H4: MP | I4: 45590 | J4: 32 | K4: 1261807.7 | L4: =K4*Q4 -> 8832653.6 | M4: 1000000 | N4: Hard tool | O4: 45012 | P4: 680000 | Q4: 7 | R4: =P4*Q4 -> 4760000 | S4: Srikanth Naule | T4: Approved | U4: Yes
A5: VEGA | B5: =VLOOKUP(A5,Sheet1!A:B,2,0) -> MODI | C5: Top Plastic Bracket | D5: 310493192000 | E5: JEE | F5: 2023 | G5: 3 | H5: MP | I5: 45590 | J5: 48 | K5: 4447872 | L5: =K5*Q5 -> 22239360 | M5: 1000000 | N5: Hard tool | O5: 45012 | P5: 690000 | Q5: 5 | R5: =P5*Q5 -> 3450000 | S5: Srikanth Naule | T5: Approved | U5: Yes
A6: VEGA | B6: =VLOOKUP(A6,Sheet1!A:B,2,0) -> MODI | C6: Bottom Plastic Bracket | D6: 310493193000 | E6: JEE | F6: 2023 | G6: 3 | H6: MP | I6: 45590 | J6: 48 | K6: 2703873.6 | L6: =K6*Q6 -> 13519368 | M6: 1000000 | N6: Hard tool | O6: 45012 | P6: 748000 | Q6: 5 | R6: =P6*Q6 -> 3740000 | S6: Srikanth Naule | T6: Approved | U6: Yes
A7: VEGA | B7: =VLOOKUP(A7,Sheet1!A:B,2,0) -> MODI | C7: Bottom cap | D7: 310493194000 | E7: JEE | F7: 2023 | G7: 3 | H7: MP | I7: 45590 | J7: 48 | K7: 3706560 | L7: =K7*Q7 -> 18532800 | M7: 1000000 | N7: Hard tool | O7: 45012 | P7: 690000 | Q7: 5 | R7: =P7*Q7 -> 3450000 | S7: Srikanth Naule | T7: Approved | U7: Yes
A8: VEGA | B8: =VLOOKUP(A8,Sheet1!A:B,2,0) -> MODI | C8: Air Flow slider | D8: 310493195000 | E8: JEE | F8: 2023 | G8: 3 | H8: MP | I8: 45590 | J8: 48 | K8: 3801600 | L8: =K8*Q8 -> 19008000 | M8: 1000000 | N8: Hard tool | O8: 45012 | P8: 680000 | Q8: 5 | R8: =P8*Q8 -> 3400000 | S8: Srikanth Naule | T8: Approved | U8: Yes
A9: KUMA E-Box NZ | B9: =VLOOKUP(A9,Sheet1!A:B,2,0) -> RCS DEVICE | C9: Top cover | D9: 130040670021260 | E9: JEE | F9: 2024 | G9: 1 | H9: MP | I9: 45590 | J9: 4 | K9: 211822 | L9: =K9*Q9 -> 211822 | M9: 300000 | N9: Soft tool | O9: 45231 | P9: 160000 | Q9: 1 | R9: =P9*Q9 -> 160000 | S9: Chris | T9: Approved | U9: Yes
A10: KUMA E-Box NZ | B10: =VLOOKUP(A10,Sheet1!A:B,2,0) -> RCS DEVICE | C10: Bottom cover | D10: 130040670021261 | E10: JEE | F10: 2024 | G10: 1 | H10: MP | I10: 45590 | J10: 4 | K10: 211822 | L10: =K10*Q10 -> 211822 | M10: 300000 | N10: Soft tool | O10: 45231 | P10: 180000 | Q10: 1 | R10: =P10*Q10 -> 180000 | S10: Chris | T10: Approved | U10: Yes
A11: KUMA E-Box NZ | B11: =VLOOKUP(A11,Sheet1!A:B,2,0) -> RCS DEVICE | C11: Button | D11: 130040670021263 | E11: JEE | F11: 2024 | G11: 1 | H11: MP | I11: 45590 | J11: 4 | K11: 296530 | L11: =K11*Q11 -> 296530 | M11: 300000 | N11: Soft tool | O11: 45231 | P11: 140000 | Q11: 1 | R11: =P11*Q11 -> 140000 | S11: Chris | T11: Approved | U11: Yes
A12: KUMA E-Box NZ | B12: =VLOOKUP(A12,Sheet1!A:B,2,0) -> RCS DEVICE | C12: PCB holder | D12: 130040670021262 | E12: JEE | F12: 2024 | G12: 1 | H12: MP | I12: 45590 | J12: 4 | K12: 296530 | L12: =K12*Q12 -> 296530 | M12: 300000 | N12: Soft tool | O12: 45231 | P12: 180000 | Q12: 1 | R12: =P12*Q12 -> 180000 | S12: Chris | T12: Approved | U12: Yes
A13: KUMA E-Pen 1.0 ROW | B13: =VLOOKUP(A13,Sheet1!A:B,2,0) -> RCS DEVICE | C13: Battery tube | D13: 120020670031773 | E13: JEE | F13: 2024 | G13: 6 | H13: MP | I13: 45590 | J13: 8 | K13: 356448 | L13: =K13*Q13 -> 356448 | M13: 1000000 | N13: Hard tool | O13: 45383 | P13: 280000 | Q13: 1 | R13: =P13*Q13 -> 280000 | S13: Chris | T13: Approved | U13: No
A14: KUMA E-Pen 1.0 ROW | B14: =VLOOKUP(A14,Sheet1!A:B,2,0) -> RCS DEVICE | C14: Bottom cap | D14: 130020670031775 | E14: JEE | F14: 2024 | G14: 6 | H14: MP | I14: 45590 | J14: 16 | K14: 750432 | L14: =K14*Q14 -> 750432 | M14: 1000000 | N14: Hard tool | O14: 45383 | P14: 460000 | Q14: 1 | R14: =P14*Q14 -> 460000 | S14: Chris | T14: Approved | U14: No
A15: KUMA E-Pen 1.0 ROW | B15: =VLOOKUP(A15,Sheet1!A:B,2,0) -> RCS DEVICE | C15: Holder | D15: 130020670031776 | E15: JEE | F15: 2024 | G15: 6 | H15: MP | I15: 45590 | J15: 16 | K15: 893952 | L15: =K15*Q15 -> 893952 | M15: 1000000 | N15: Hard tool | O15: 45383 | P15: 420000 | Q15: 1 | R15: =P15*Q15 -> 420000 | S15: Chris | T15: Approved | U15: No
... A17: KUMA E-Pen 1.0 ROW | B17: =VLOOKUP(A17,Sheet1!A:B,2,0) -> RCS DEVICE | C17: Light guide | D17: 130020670035243 | E17: JEE | F17: 2024 | G17: 6 | H17: MP | I17: 45590 | J17: 16 | K17: 903168 | L17: =K17*Q17 -> 903168 | M17: 1000000 | N17: Hard tool | O17: 45383 | P17: 400000 | Q17: 1 | R17: =P17*Q17 -> 400000 | S17: Chris | T17: Approved | U17: No
A18: Alto Pod | B18: =VLOOKUP(A18,Sheet1!A:B,2,0) -> RCS POD | C18: Cartomizer tube | D18: 130010390000214 | E18: JEE | F18: 2022 | G18: 6 | H18: MP | I18: 45590 | J18: 16 | K18: 1185600 | L18: =K18*Q18 -> 23712000 | M18: 1000000 | N18: Hard tool | O18: 44713 | P18: =7.15*173199.447270021 -> 1238376 | Q18: 20 | R18: =P18*Q18 -> 24767521 | S18: Smoore | T18: Approved | U18: Yes
A19: Alto Pod | B19: =VLOOKUP(A19,Sheet1!A:B,2,0) -> RCS POD | C19: Heating holder | D19: 130010390000215 | E19: JEE | F19: 2022 | G19: 6 | H19: MP | I19: 45590 | J19: 32 | K19: 2695680 | L19: =K19*Q19 -> 21565440 | M19: 1000000 | N19: Hard tool | O19: 44713 | P19: =7.15*179728.993498461 -> 1285062.3 | Q19: 8 | R19: =P19*Q19 -> 10280498 | S19: Smoore | T19: Approved | U19: Yes
A20: Alto Pod | B20: =VLOOKUP(A20,Sheet1!A:B,2,0) -> RCS POD | C20: Heater top cover | D20: 130010390000216 | E20: JEE | F20: 2022 | G20: 6 | H20: MP | I20: 45590 | J20: 32 | K20: 2695680 | L20: =K20*Q20 -> 21565440 | M20: 1000000 | N20: Hard tool | O20: 44713 | P20: =7.15*180678.150274652 -> 1291848.8 | Q20: 8 | R20: =P20*Q20 -> 10334790 | S20: Smoore | T20: Approved | U20: Yes
A21: Alto Pod | B21: =VLOOKUP(A21,Sheet1!A:B,2,0) -> RCS POD | C21: Cartomizer holder tap | D21: 130010390000221 | E21: JEE | F21: 2022 | G21: 6 | H21: MP | I21: 45590 | J21: 32 | K21: 2526368 | L21: =K21*Q21 -> 20210944 | M21: 1000000 | N21: Hard tool | O21: 44713 | P21: =7.15*(585819/6.4305) -> 651365.5 | Q21: 8 | R21: =P21*Q21 -> 5210924 | S21: Smoore | T21: Approved | U21: Yes
A22: Prismatic Pod | B22: =VLOOKUP(A22,Sheet1!A:B,2,0) -> RCS POD | C22: Cartomizer tube | D22: 130010390000214 | E22: JEE | F22: 2023 | G22: 6 | H22: MP | I22: 45590 | J22: 16 | K22: 1185600 | L22: =K22*Q22 -> 1185600 | M22: 1000000 | N22: Hard tool | O22: 45078 | P22: =5424750.84955752-(2800000*30%) -> 4584750.8 | Q22: 1 | R22: =5424750.84955752-(2800000*30%) -> 4584750.8 | S22: Chris | T22: Approved | U22: No | V22: Indonesia
A23: Prismatic Pod | B23: =VLOOKUP(A23,Sheet1!A:B,2,0) -> RCS POD | C23: Cartomizer tube | D23: 130010390000214 | E23: JEE | F23: 2023 | G23: 6 | H23: MP | I23: 45590 | J23: 16 | K23: 1185600 | L23: =K23*Q23 -> 1185600 | M23: 1000000 | N23: Hard tool | O23: 45078 | P23: =5893456.35840708-(2800000*70%) -> 3933456.4 | Q23: 1 | R23: =5893456.35840708-(2800000*70%) -> 3933456.4 | S23: Chris | T23: Approved | U23: No | V23: Indonesia
A24: Prismatic Pod | B24: =VLOOKUP(A24,Sheet1!A:B,2,0) -> RCS POD | C24: Cartomizer tube | D24: 130010390000214 | E24: JEE | F24: 2023 | G24: 6 | H24: MP | I24: 45590 | J24: 16 | K24: 1185600 | L24: =K24*Q24 -> 1185600 | M24: 1000000 | N24: Soft tool | O24: 44927 | P24: 98000 | Q24: 1 | R24: =P24*Q24 -> 98000 | S24: Chris | T24: Approved | U24: No | V24: China
A25: Hyper Pro 2P | B25: =VLOOKUP(A25,Sheet1!A:B,2,0) -> HP | C25: Botton cover | D25: 22150202014 | E25: JEE | F25: 2023 | G25: 1 | H25: MP | I25: 45590 | J25: 16 | K25: 860860 | L25: =K25*Q25 -> 860860 | M25: 1000000 | N25: Hard tool | O25: 44927 | P25: 105000 | Q25: 1 | R25: =P25*Q25 -> 105000 | S25: Chris | T25: Approved | U25: Yes | V25: China
A26: Hyper Pro 2P | B26: =VLOOKUP(A26,Sheet1!A:B,2,0) -> HP | C26: Cleanout door | D26: 22150202015 | E26: JEE | F26: 2023 | G26: 1 | H26: MP | I26: 45590 | J26: 16 | K26: 531960 | L26: =K26*Q26 -> 531960 | M26: 1000000 | N26: Hard tool | O26: 44927 | P26: 376000 | Q26: 1 | R26: =P26*Q26 -> 376000 | S26: Chris | T26: Approved | U26: Yes | V26: China
A27: Hyper Pro 2P | B27: =VLOOKUP(A27,Sheet1!A:B,2,0) -> HP | C27: Button | D27: 22150202010 | E27: JEE | F27: 2023 | G27: 1 | H27: MP | I27: 45590 | J27: 16 | K27: 994136 | L27: =K27*Q27 -> 994136 | M27: 1000000 | N27: Hard tool | O27: 44927 | P27: 98350 | Q27: 1 | R27: =P27*Q27 -> 98350 | S27: Chris | T27: Approved | U27: Yes | V27: China
A28: Hyper Pro 2P | B28: =VLOOKUP(A28,Sheet1!A:B,2,0) -> HP | C28: Crown Support | D28: 22150202008 | E28: JEE | F28: 2023 | G28: 1 | H28: MP | I28: 45590 | J28: 16 | K28: 1129700 | L28: =K28*Q28 -> 1129700 | M28: 1000000 | N28: Hard tool | O28: 44927 | P28: 110600 | Q28: 1 | R28: =P28*Q28 -> 110600 | S28: Chris | T28: Approved | U28: Yes | V28: China
A29: Hyper Pro 2P | B29: =VLOOKUP(A29,Sheet1!A:B,2,0) -> HP | C29: Connector frame | D29: 22150202017 | E29: JEE | F29: 2023 | G29: 1 | H29: MP | I29: 45590 | J29: 16 | K29: 1141140 | L29: =K29*Q29 -> 1141140 | M29: 1000000 | N29: Hard tool | O29: 44927 | P29: 98000 | Q29: 1 | R29: =P29*Q29 -> 98000 | S29: Chris | T29: Approved | U29: Yes | V29: China
A30: Hyper Pro 2P | B30: =VLOOKUP(A30,Sheet1!A:B,2,0) -> HP | C30: Spin Wheel | D30: 22150202009 | E30: JEE | F30: 2023 | G30: 1 | H30: MP | I30: 45590 | J30: 16 | K30: 988416 | L30: =K30*Q30 -> 988416 | M30: 1000000 | N30: Hard tool | O30: 44927 | P30: 98000 | Q30: 1 | R30: =P30*Q30 -> 98000 | S30: Chris | T30: Approved | U30: Yes | V30: China
A31: Hyper Pro 2P | B31: =VLOOKUP(A31,Sheet1!A:B,2,0) -> HP | C31: Display bracket | D31: 22150202021 | E31: JEE | F31: 2023 | G31: 1 | H31: MP | I31: 45590 | J31: 16 | K31: 1251978 | L31: =K31*Q31 -> 1251978 | M31: 1000000 | N31: Hard tool | O31: 44927 | P31: 200100 | Q31: 1 | R31: =P31*Q31 -> 200100 | S31: Chris | T31: Approved | U31: Yes | V31: China
A32: Hyper Pro 2P | B32: =VLOOKUP(A32,Sheet1!A:B,2,0) -> HP | C32: PCBA Bracket | D32: 22150202018 | E32: JEE | F32: 2023 | G32: 1 | H32: MP | I32: 45590 | J32: 16 | K32: 1065064 | L32: =K32*Q32 -> 1065064 | M32: 1000000 | N32: Hard tool | O32: 44927 | P32: 98000 | Q32: 1 | R32: =P32*Q32 -> 98000 | S32: Chris | T32: Approved | U32: Yes | V32: China
A33: Hyper Pro 2P | B33: =VLOOKUP(A33,Sheet1!A:B,2,0) -> HP | C33: Shut Door | D33: 22150202007 | E33: JEE | F33: 2023 | G33: 1 | H33: MP | I33: 45590 | J33: 16 | K33: 1129700 | L33: =K33*Q33 -> 1129700 | M33: 1000000 | N33: Hard tool | O33: 44927 | P33: 130350 | Q33: 1 | R33: =P33*Q33 -> 130350 | S33: Chris | T33: Approved | U33: Yes | V33: China
A34: Hyper Core | B34: =VLOOKUP(A34,Sheet1!A:B,2,0) -> HP | C34: Crown Support | D34: 23590202001 | E34: JEE | F34: 2023 | G34: 1 | H34: MP | I34: 45590 | J34: 16 | K34: 50284 | L34: =K34*Q34 -> 50284 | M34: 1000000 | N34: Hard tool | O34: 44927 | P34: 98000 | Q34: 1 | R34: =P34*Q34 -> 98000 | S34: Chris | T34: Approved | U34: Yes | V34: China
A35: Hyper Core | B35: =VLOOKUP(A35,Sheet1!A:B,2,0) -> HP | C35: Connector frame | D35: 23480202015 | E35: JEE | F35: 2023 | G35: 1 | H35: MP | I35: 45590 | J35: 16 | K35: 1251978 | L35: =K35*Q35 -> 1251978 | M35: 1000000 | N35: Hard tool | O35: 44927 | P35: 188000 | Q35: 1 | R35: =P35*Q35 -> 188000 | S35: Chris | T35: Approved | U35: Yes | V35: China
A36: Hyper Core | B36: =VLOOKUP(A36,Sheet1!A:B,2,0) -> HP | C36: Battery carrier | D36: 23480202012 | E36: JEE | F36: 2023 | G36: 1 | H36: MP | I36: 45590 | J36: 4 | K36: 260832 | L36: =K36*Q36 -> 521664 | M36: 1000000 | N36: Hard tool | O36: 44927 | P36: 320000 | Q36: 2 | R36: =P36*Q36 -> 640000 | S36: Chris | T36: Approved | U36: No | V36: China
... A40: Hyper Core | B40: =VLOOKUP(A40,Sheet1!A:B,2,0) -> HP | C40: Light guide | D40: 23480202018 | E40: JEE | F40: 2023 | G40: 1 | H40: MP | I40: 45590 | J40: 16 | K40: 665808 | L40: =K40*Q40 -> 665808 | M40: 1000000 | N40: Hard tool | O40: 44927 | P40: 452729 | Q40: 1 | R40: =P40*Q40 -> 452729 | S40: Chris | T40: Approved | U40: No | V40: China
A41: Hyper Pro 2P | B41: =VLOOKUP(A41,Sheet1!A:B,2,0) -> HP | C41: Crown Support | D41: 22150202008 | E41: JEE | F41: 2023 | G41: 10 | H41: MP | I41: 45590 | L41: =K41*Q41 -> 0 | N41: Hard tool EC | O41: 45210 | P41: 12600 | Q41: 1 | R41: =P41*Q41 -> 12600 | S41: Chris | T41: Approved | U41: No | V41: China
A42: Hyper Core | B42: =VLOOKUP(A42,Sheet1!A:B,2,0) -> HP | C42: Light guide | D42: 23480202018 | E42: JEE | F42: 2023 | G42: 10 | H42: MP | I42: 45590 | L42: =K42*Q42 -> 0 | N42: Hard tool EC | O42: 45220 | P42: 53870 | Q42: 1 | R42: =P42*Q42 -> 53870 | S42: Chris | T42: Approved | U42: No | V42: China
A43: Hyper Core | B43: =VLOOKUP(A43,Sheet1!A:B,2,0) -> HP | C43: Shutter Door Support | D43: 23480202005 | E43: JEE | F43: 2023 | G43: 10 | H43: MP | I43: 45590 | L43: =K43*Q43 -> 0 | N43: Hard tool EC | O43: 45223 | P43: 35296 | Q43: 1 | R43: =P43*Q43 -> 35296 | S43: Chris | T43: Approved | U43: No | V43: China
A44: Hyper Core | B44: =VLOOKUP(A44,Sheet1!A:B,2,0) -> HP | C44: Button | D44: 23480202017 | E44: JEE | F44: 2023 | G44: 10 | H44: MP | I44: 45590 | L44: =K44*Q44 -> 0 | N44: Hard tool EC | O44: 45209 | P44: 207000 | Q44: 1 | R44: =P44*Q44 -> 207000 | S44: Chris | T44: Approved | U44: No | V44: China
A45: Hyper Core | B45: =VLOOKUP(A45,Sheet1!A:B,2,0) -> HP | C45: Button | D45: 23480202017 | E45: JEE | F45: 2023 | G45: 10 | H45: MP | I45: 45590 | L45: =K45*Q45 -> 0 | N45: Hard tool EC | O45: 45220 | P45: 35513 | Q45: 1 | R45: =P45*Q45 -> 35513 | S45: Chris | T45: Approved | U45: No | V45: China
A46: Hyper Core | B46: =VLOOKUP(A46,Sheet1!A:B,2,0) -> HP | C46: Light guide | D46: 23480202018 | E46: JEE | F46: 2023 | G46: 11 | H46: MP | I46: 45590 | L46: =K46*Q46 -> 0 | N46: Hard tool EC | O46: 45254 | P46: 10859 | Q46: 1 | R46: =P46*Q46 -> 10859 | S46: Chris | T46: Approved | U46: No | V46: China
A47: Hyper Core | B47: =VLOOKUP(A47,Sheet1!A:B,2,0) -> HP | C47: Button | D47: 23480202017 | E47: JEE | F47: 2023 | G47: 11 | H47: MP | I47: 45590 | L47: =K47*Q47 -> 0 | N47: Hard tool EC | O47: 45254 | P47: 26171 | Q47: 1 | R47: =P47*Q47 -> 26171 | S47: Chris | T47: Approved | U47: No | V47: China
A48: Hyper Pro | B48: HP | C48: Connect frame | D48: 22150202017 | E48: JEE | F48: 2023 | G48: 6 | H48: POC | I48: 45590 | N48: Soft tool EC | O48: 45078 | P48: 6415 | Q48: 1 | R48: =P48*Q48 -> 6415 | S48: Chris | T48: Approved | U48: Yes
A49: Hyper Pro | B49: HP | C49: Connect frame | D49: 22150202017 | E49: JEE | F49: 2023 | G49: 6 | H49: POC | I49: 45590 | N49: Soft tool EC | O49: 45078 | P49: 3088 | Q49: 1 | R49: =P49*Q49 -> 3088 | S49: Chris | T49: Approved | U49: Yes
A50: Hyper Pro | B50: HP | C50: Connect frame | D50: 22150202017 | E50: JEE | F50: 2023 | G50: 6 | H50: POC | I50: 45590 | N50: Soft tool EC | O50: 45078 | P50: 10183 | Q50: 1 | R50: =P50*Q50 -> 10183 | S50: Chris | T50: Approved | U50: Yes
A51: Hyper Pro | B51: HP | C51: Display bracket | D51: 22150202021 | E51: JEE | F51: 2023 | G51: 6 | H51: POC | I51: 45590 | N51: Soft tool EC | O51: 45078 | P51: 9977 | Q51: 1 | R51: =P51*Q51 -> 9977 | S51: Chris | T51: Approved | U51: Yes
A52: Hyper Pro | B52: HP | C52: Spin wheel | D52: 22150202009 | E52: JEE | F52: 2023 | G52: 6 | H52: POC | I52: 45590 | N52: Soft tool EC | O52: 45078 | P52: 9245 | Q52: 1 | R52: =P52*Q52 -> 9245 | S52: Chris | T52: Approved | U52: Yes
A53: Hyper Pro | B53: HP | C53: Botton cover | D53: 22150202014 | E53: JEE | F53: 2023 | G53: 6 | H53: POC | I53: 45590 | N53: Soft tool EC | O53: 45078 | P53: 6998 | Q53: 1 | R53: =P53*Q53 -> 6998 | S53: Chris | T53: Approved | U53: Yes
A54: Hyper Pro | B54: HP | C54: Cleanout door | D54: 22150202015 | E54: JEE | F54: 2023 | G54: 6 | H54: POC | I54: 45590 | N54: Soft tool EC | O54: 45078 | P54: 13970 | Q54: 1 | R54: =P54*Q54 -> 13970 | S54: Chris | T54: Approved | U54: Yes
A55: Hyper Pro | B55: HP | C55: shut door | D55: 22150202007 | E55: JEE | F55: 2023 | G55: 6 | H55: POC | I55: 45590 | N55: Soft tool EC | O55: 45078 | P55: 11686 | Q55: 1 | R55: =P55*Q55 -> 11686 | S55: Chris | T55: Approved | U55: Yes
A56: Hyper Core | B56: HP | C56: Button bracket | D56: 23480202011 | E56: JEE | F56: 2023 | G56: 7 | H56: POC | I56: 45590 | N56: Soft tool EC | O56: 45108 | P56: 9201 | Q56: 1 | R56: =P56*Q56 -> 9201 | S56: Chris | T56: Approved | U56: Yes
A57: Hyper Core | B57: HP | C57: Button Bracket | D57: 23480202011 | E57: JEE | F57: 2023 | G57: 7 | H57: POC | I57: 45590 | N57: Soft tool EC | O57: 45108 | P57: 20444 | Q57: 1 | R57: =P57*Q57 -> 20444 | S57: Chris | T57: Approved | U57: Yes
A58: Hyper Pro | B58: HP | C58: Button | D58: 22150202010 | E58: JEE | F58: 2023 | G58: 7 | H58: POC | I58: 45590 | N58: Soft tool EC | O58: 45108 | P58: 6869 | Q58: 1 | R58: =P58*Q58 -> 6869 | S58: Chris | T58: Approved | U58: Yes
A59: Hyper Pro | B59: HP | C59: Connect frame | D59: 22150202017 | E59: JEE | F59: 2023 | G59: 7 | H59: POC | I59: 45590 | N59: Soft tool EC | O59: 45108 | P59: 32659 | Q59: 1 | R59: =P59*Q59 -> 32659 | S59: Chris | T59: Approved | U59: Yes
... A92: Hyper Core | B92: HP | C92: Display bracket | D92: 23480202010 | E92: JEE | F92: 2023 | G92: 8 | H92: POC | I92: 45590 | N92: Soft tool EC | O92: 45139 | P92: 138000 | Q92: 1 | R92: =P92*Q92 -> 138000 | S92: Chris | T92: Approved | U92: Yes
A93: Hyper Core | B93: =VLOOKUP(A93,Sheet1!A:B,2,0) -> HP | C93: Button | D93: 23480202017 | E93: JEE | F93: 2023 | G93: 3 | H93: POC | I93: 45590 | L93: =K93*Q93 -> 0 | N93: Soft tool EC | O93: 45376 | P93: 8471.1 | Q93: 1 | R93: =P93*Q93 -> 8471.1 | S93: Chris | T93: Approved | U93: Yes | V93: China
A94: Hyper Core | B94: =VLOOKUP(A94,Sheet1!A:B,2,0) -> HP | C94: Shutter Door Support | D94: 23480202005 | E94: JEE | F94: 2023 | G94: 3 | H94: POC | I94: 45590 | L94: =K94*Q94 -> 0 | N94: Soft tool EC | O94: 45376 | P94: 21437 | Q94: 1 | R94: =P94*Q94 -> 21437 | S94: Chris | T94: Approved | U94: Yes | V94: China
A95: Hyper Core | B95: =VLOOKUP(A95,Sheet1!A:B,2,0) -> HP | C95: Battery carrier | D95: 23480202012 | E95: JEE | F95: 2023 | G95: 3 | H95: POC | I95: 45590 | L95: =K95*Q95 -> 0 | N95: Soft tool EC | O95: 45376 | P95: 8396.215 | Q95: 1 | R95: =P95*Q95 -> 8396.215 | S95: Chris | T95: Approved | U95: Yes | V95: China
A96: Hyper Core | B96: =VLOOKUP(A96,Sheet1!A:B,2,0) -> HP | C96: Battery carrier | D96: 23480202012 | E96: JEE | F96: 2023 | G96: 3 | H96: POC | I96: 45590 | L96: =K96*Q96 -> 0 | N96: Soft tool EC | O96: 45376 | P96: 43769.9 | Q96: 1 | R96: =P96*Q96 -> 43769.9 | S96: Chris | T96: Approved | U96: Yes | V96: China
A97: Hyper Core | B97: =VLOOKUP(A97,Sheet1!A:B,2,0) -> HP | C97: Button Bracket | D97: 23480202011 | E97: JEE | F97: 2023 | G97: 3 | H97: POC | I97: 45590 | L97: =K97*Q97 -> 0 | N97: Soft tool EC | O97: 45376 | P97: 10892.07 | Q97: 1 | R97: =P97*Q97 -> 10892.07 | S97: Chris | T97: Approved | U97: Yes | V97: China
A98: Hyper Core | B98: =VLOOKUP(A98,Sheet1!A:B,2,0) -> HP | C98: Light guide | D98: 23480202018 | E98: JEE | F98: 2023 | G98: 3 | H98: POC | I98: 45590 | L98: =K98*Q98 -> 0 | N98: Soft tool EC | O98: 45376 | P98: 41897.01 | Q98: 1 | R98: =P98*Q98 -> 41897.01 | S98: Chris | T98: Approved | U98: Yes | V98: China
A99: Artemis 1P | B99: =VLOOKUP(A99,Sheet1!A:B,2,0) -> HP | C99: Housing | D99: 0600201003 | E99: JEE | F99: 2023 | G99: 5 | H99: POP | I99: 45590 | J99: 1 | K99: 10000 | L99: =K99*Q99 -> 10000 | M99: 50000 | N99: Soft tool | O99: 45422 | P99: 672500 | Q99: 1 | R99: =P99*Q99 -> 672500 | S99: Chris | T99: Approved | U99: No
A100: Artemis 1P | B100: =VLOOKUP(A100,Sheet1!A:B,2,0) -> HP | C100: MAIN CHASISS | D100: 0600202009 | E100: JEE | F100: 2023 | G100: 5 | H100: POP | I100: 45590 | J100: 1 | K100: 580882.37 | L100: =K100*Q100 -> 580882.37 | M100: 500000 | N100: Soft tool | O100: 45422 | P100: 302500 | Q100: 1 | R100: =P100*Q100 -> 302500 | S100: Chris | T100: Approved | U100: No
A101: Artemis 1P | B101: =VLOOKUP(A101,Sheet1!A:B,2,0) -> HP | C101: Top cover | D101: 0600201010 | E101: JEE | F101: 2023 | G101: 5 | H101: POP | I101: 45590 | J101: 1 | K101: 10000 | L101: =K101*Q101 -> 10000 | M101: 500000 | N101: Soft tool | O101: 45422 | P101: 55400 | Q101: 1 | R101: =P101*Q101 -> 55400 | S101: Chris | T101: Approved | U101: No
A102: Artemis 2P | B102: =VLOOKUP(A102,Sheet1!A:B,2,0) -> HP | C102: Slider bracket | D102: 0620201006 | E102: JEE | F102: 2023 | G102: 5 | H102: POP | I102: 45590 | J102: 1 | K102: 10000 | L102: =K102*Q102 -> 10000 | M102: 500000 | N102: Soft tool | O102: 45422 | P102: 39200 | Q102: 1 | R102: =P102*Q102 -> 39200 | S102: Chris | T102: Approved | U102: No
A103: Artemis 2P | B103: =VLOOKUP(A103,Sheet1!A:B,2,0) -> HP | C103: Heat transferring tube | D103: 06002010034 | E103: JEE | F103: 2023 | G103: 5 | H103: POP | I103: 45590 | J103: 1 | K103: 10000 | L103: =K103*Q103 -> 10000 | M103: 50000 | N103: Soft tool | O103: 45422 | P103: 144981 | Q103: 1 | R103: =P103*Q103 -> 144981 | S103: Chris | T103: Approved | U103: No
A104: Artemis 2P | B104: =VLOOKUP(A104,Sheet1!A:B,2,0) -> HP | C104: Slider bracket | D104: 0620201006 | E104: JEE | F104: 2023 | G104: 5 | H104: POP | I104: 45590 | J104: 1 | K104: 10000 | L104: =K104*Q104 -> 10000 | M104: 50000 | N104: Soft tool | O104: 45422 | P104: 12500 | Q104: 1 | R104: =P104*Q104 -> 12500 | S104: Chris | T104: Approved | U104: No
A105: Artemis 2P | B105: =VLOOKUP(A105,Sheet1!A:B,2,0) -> HP | C105: Heat transferring tube | D105: 06002010034 | E105: JEE | F105: 2023 | G105: 5 | H105: POP | I105: 45590 | J105: 1 | K105: 10000 | L105: =K105*Q105 -> 10000 | M105: 50000 | N105: Soft tool | O105: 45422 | P105: 20500 | Q105: 1 | R105: =P105*Q105 -> 20500 | S105: Chris | T105: Approved | U105: No
A106: Artemis 2P | B106: =VLOOKUP(A106,Sheet1!A:B,2,0) -> HP | C106: cap pogo pin | D106: 0620201009 | E106: JEE | F106: 2023 | G106: 5 | H106: POP | I106: 45590 | J106: 1 | K106: 10000 | L106: =K106*Q106 -> 10000 | M106: 50000 | N106: Soft tool | O106: 45422 | P106: 63000 | Q106: 1 | R106: =P106*Q106 -> 63000 | S106: Chris | T106: Approved | U106: No
A107: Artemis 2P | B107: =VLOOKUP(A107,Sheet1!A:B,2,0) -> HP | C107: SLIDER RAIL | D107: 06202021007 | E107: JEE | F107: 2023 | G107: 5 | H107: POP | I107: 45590 | J107: 1 | K107: 10000 | L107: =K107*Q107 -> 10000 | M107: 50000 | N107: Soft tool | O107: 45422 | P107: 135260 | Q107: 1 | R107: =P107*Q107 -> 135260 | S107: Chris | T107: Approved | U107: No
A108: Artemis 1P | B108: =VLOOKUP(A108,Sheet1!A:B,2,0) -> HP | C108: HOUSING | D108: 0600201003 | E108: JEE | F108: 2023 | G108: 5 | H108: POP | I108: 45590 | L108: =K108*Q108 -> 0 | N108: Soft tool | O108: 45422 | P108: 33452.212 | Q108: 1 | R108: =P108*Q108 -> 33452.212 | S108: Chris | T108: Approved | U108: No
A109: Artemis 1P | B109: =VLOOKUP(A109,Sheet1!A:B,2,0) -> HP | C109: MAIN_CHASISS | D109: 0600202009 | E109: JEE | F109: 2023 | G109: 5 | H109: POP | I109: 45590 | L109: =K109*Q109 -> 0 | N109: Soft tool | O109: 45422 | P109: 89692.735 | Q109: 1 | R109: =P109*Q109 -> 89692.735 | S109: Chris | T109: Approved | U109: No
A110: Artemis 1P | B110: =VLOOKUP(A110,Sheet1!A:B,2,0) -> HP | C110: TOP_COVER | D110: 0600201010 | E110: JEE | F110: 2023 | G110: 5 | H110: POP | I110: 45590 | L110: =K110*Q110 -> 0 | N110: Soft tool | O110: 45422 | P110: 3451.3274 | Q110: 1 | R110: =P110*Q110 -> 3451.3274 | S110: Chris | T110: Approved | U110: No
A111: Artemis 1P | B111: =VLOOKUP(A111,Sheet1!A:B,2,0) -> HP | C111: HEATING PIN LSR SUB | D111: 0600204088 | E111: JEE | F111: 2023 | G111: 5 | H111: POP | I111: 45590 | L111: =K111*Q111 -> 0 | N111: Soft tool | O111: 45422 | P111: 20000 | Q111: 1 | R111: =P111*Q111 -> 20000 | S111: Chris | T111: Approved | U111: No
A112: Artemis 1P | B112: =VLOOKUP(A112,Sheet1!A:B,2,0) -> HP | C112: HEATING PIN LSR SUB | D112: 0600204088 | E112: JEE | F112: 2023 | G112: 5 | H112: POP | I112: 45590 | L112: =K112*Q112 -> 0 | N112: Soft tool | O112: 45422 | P112: 6650 | Q112: 1 | R112: =P112*Q112 -> 6650 | S112: Chris | T112: Approved | U112: No
A113: Artemis 1P | B113: =VLOOKUP(A113,Sheet1!A:B,2,0) -> HP | C113: HEATING PIN LSR SUB | D113: 0600204088 | E113: JEE | F113: 2023 | G113: 5 | H113: POP | I113: 45590 | L113: =K113*Q113 -> 0 | N113: Soft tool | O113: 45422 | P113: 38480 | Q113: 1 | R113: =P113*Q113 -> 38480 | S113: Chris | T113: Approved | U113: No
A114: Alto Pod | B114: =VLOOKUP(A114,Sheet1!A:B,2,0) -> RCS POD | C114: Cartomizer tube | D114: 130010390000214 | E114: JEE | F114: 2024 | G114: 11 | H114: MP | I114: 45608 | J114: 16 | K114: 1185600 | L114: 13041600 | M114: 1000000 | N114: Hard tool | O114: 45598 | P114: =7.15*93440.47 -> 668099.36 | Q114: 11 | R114: =P114*Q114 -> 7349093 | S114: Candy | T114: Approved | U114: No
A115: Alto Pod | B115: =VLOOKUP(A115,Sheet1!A:B,2,0) -> RCS POD | C115: Heating holder | D115: 130010390000214 | E115: JEE | F115: 2024 | G115: 11 | H115: MP | I115: 45608 | J115: 32 | K115: 2695680 | L115: 13478400 | M115: 1000000 | N115: Hard tool | O115: 45598 | P115: =7.15*102652.91 -> 733968.31 | Q115: 5 | R115: =P115*Q115 -> 3669841.5 | S115: Candy | T115: Approved | U115: No
A116: Alto Pod | B116: =VLOOKUP(A116,Sheet1!A:B,2,0) -> RCS POD | C116: Heater top cover | D116: 130010390000214 | E116: JEE | F116: 2024 | G116: 11 | H116: MP | I116: 45608 | J116: 32 | K116: 2695680 | L116: 13478400 | M116: 1000000 | N116: Hard tool | O116: 45598 | P116: =7.15*102652.91 -> 733968.31 | Q116: 5 | R116: =P116*Q116 -> 3669841.5 | S116: Candy | T116: Approved | U116: No
A117: Alto Pod | B117: =VLOOKUP(A117,Sheet1!A:B,2,0) -> RCS POD | C117: Cartomizer holder tap | D117: 130010390000214 | E117: JEE | F117: 2024 | G117: 11 | H117: MP | I117: 45608 | J117: 32 | K117: 2526368 | L117: 12631840 | M117: 1000000 | N117: Hard tool | O117: 45598 | P117: =7.15*69751.33 -> 498722.01 | Q117: 5 | R117: =P117*Q117 -> 2493610 | S117: Candy | T117: Approved | U117: No
A118: Box 800 Full 2.0 | B118: MODI | C118: protective shell | D118: 120040670018926 | E118: JEE | F118: 2024 | G118: 1 | H118: MP | I118: 45706 | J118: 1 | K118: 11108448 | L118: 44433792 | M118: 60000000 | N118: Hard tool | O118: 45294 | P118: 3500 | Q118: 4 | R118: =P118*Q118 -> 14000 | S118: Chris | T118: Approved | U118: No
A119: Box 5000 Full 2.0 | B119: MODI | C119: protective shell | D119: 120040670025620 | E119: JEE | F119: 2024 | G119: 1 | H119: MP | I119: 45706 | J119: 1 | K119: 1834560 | L119: 3669120 | M119: 2000000 | N119: Hard tool | O119: 45294 | P119: 0 | Q119: 2 | R119: =P119*Q119 -> 0 | S119: Chris | T119: Approved | U119: No | V119: JEE agree no tooling cost to BAT for 3K/5K
A120: Pen 800 Full 2.0 | B120: MODI | C120: protective shell | D120: 120040670017654 | E120: JEE | F120: 2024 | G120: 9 | H120: MP | I120: 45706 | J120: 1 | K120: 1851408 | L120: 11108448 | M120: 120000000 | N120: Hard tool | O120: 45538 | P120: 18500 | Q120: 6 | R120: =P120*Q120 -> 111000 | S120: Chris | T120: Approved | U120: No
A121: Alto Device | B121: RCS DEVICE | C121: Battery holder | D121: 130020390000222 | E121: JEE | F121: 2020 | G121: 1 | H121: MP | I121: 45706 | J121: 9 | K121: 812968 | L121: 812968 | M121: 1000000 | N121: Hard tool | O121: 43831 | P121: 600000 | Q121: 1 | R121: 600000 | S121: smoore | T121: Approved | U121: Yes
A122: Adonis 1P | B122: HP | C122: Housing | D122: 240000090201004 | E122: JEE | F122: 2024 | G122: 9 | H122: MP | I122: 45706 | J122: 1 | K122: 200000 | L122: 200000 | M122: 1000000 | N122: Hard tool | O122: 45627 | P122: 776500 | Q122: 1 | R122: 776500 | S122: Srikanth Naule | T122: Not Approved | U122: No | V122: Metal parts ，Metal tool& fixtures
A123: Adonis 1P | B123: HP | C123: Top cover | D123: 240000090201003 | E123: JEE | F123: 2024 | G123: 9 | H123: MP | I123: 45706 | J123: 1 | K123: 200000 | L123: 200000 | M123: 1000000 | N123: Hard tool | O123: 45627 | P123: 441700 | Q123: 1 | R123: 441700 | S123: Srikanth Naule | T123: Not Approved | U123: No | V123: Metal parts ，Metal tool& fixtures
A124: Adonis 1P | B124: HP | C124: Slider bracket | D124: 240000090201001 | E124: JEE | F124: 2024 | G124: 9 | H124: MP | I124: 45706 | J124: 1 | K124: 200000 | L124: 200000 | M124: 1000000 | N124: Hard tool | O124: 45627 | P124: 51500 | Q124: 1 | R124: 51500 | S124: Srikanth Naule | T124: Not Approved | U124: No | V124: Metal parts ，Metal tool& fixtures
A125: Adonis 1P | B125: HP | C125: Slider cover | D125: 240000090201002 | E125: JEE | F125: 2024 | G125: 9 | H125: MP | I125: 45706 | J125: 1 | K125: 200000 | L125: 200000 | M125: 1000000 | N125: Hard tool | O125: 45627 | P125: 26500 | Q125: 1 | R125: 26500 | S125: Srikanth Naule | T125: Not Approved | U125: No | V125: Metal parts ，Metal tool& fixtures
A126: Adonis 1P | B126: HP | C126: Housing | D126: 240000090201004 | E126: JEE | F126: 2024 | G126: 9 | H126: POC | I126: 45706 | J126: 1 | K126: 1000 | L126: 2000 | M126: 1000000 | N126: Soft tool | O126: 45536 | P126: 3276 | Q126: 2 | R126: 6552 | S126: Srikanth Naule | T126: Not Approved | U126: No | V126: NPI COST
A127: Adonis 1P | B127: HP | C127: Housing | D127: 240000090201004 | E127: JEE | F127: 2024 | G127: 9 | H127: POC | I127: 45706 | J127: 1 | K127: 1000 | L127: 1000 | M127: 1000000 | N127: Soft tool | O127: 45536 | P127: 4914 | Q127: 1 | R127: 4914 | S127: Srikanth Naule | T127: Not Approved | U127: No | V127: NPI COST
A128: Adonis 1P | B128: HP | C128: Housing | D128: 240000090201004 | E128: JEE | F128: 2024 | G128: 9 | H128: POC | I128: 45706 | J128: 1 | K128: 1000 | L128: 1000 | M128: 1000000 | N128: Soft tool | O128: 45536 | P128: 13260 | Q128: 1 | R128: 13260 | S128: Srikanth Naule | T128: Not Approved | U128: No | V128: NPI COST
A129: Adonis 1P | B129: HP | C129: Housing | D129: 240000090201004 | E129: JEE | F129: 2024 | G129: 9 | H129: POC | I129: 45706 | J129: 1 | K129: 1000 | L129: 7000 | M129: 1000000 | N129: Soft tool | O129: 45536 | P129: 1105 | Q129: 7 | R129: 7735 | S129: Srikanth Naule | T129: Not Approved | U129: No | V129: NPI COST
A130: Adonis 1P | B130: HP | C130: Housing | D130: 240000090201004 | E130: JEE | F130: 2024 | G130: 9 | H130: POC | I130: 45706 | J130: 1 | K130: 1000 | L130: 2000 | M130: 1000000 | N130: Soft tool | O130: 45536 | P130: 331.5 | Q130: 2 | R130: 663 | S130: Srikanth Naule | T130: Not Approved | U130: No | V130: NPI COST
A131: Adonis 1P | B131: HP | C131: Housing | D131: 240000090201004 | E131: JEE | F131: 2024 | G131: 9 | H131: POC | I131: 45706 | J131: 1 | K131: 1000 | L131: 1000 | M131: 1000000 | N131: Soft tool | O131: 45536 | P131: 13000 | Q131: 1 | R131: 13000 | S131: Srikanth Naule | T131: Not Approved | U131: No | V131: NPI COST
A132: Adonis 1P | B132: HP | C132: Housing | D132: 240000090201004 | E132: JEE | F132: 2024 | G132: 9 | H132: POC | I132: 45706 | J132: 1 | K132: 1000 | L132: 2000 | M132: 1000000 | N132: Soft tool | O132: 45536 | P132: 2000 | Q132: 2 | R132: 4000 | S132: Srikanth Naule | T132: Not Approved | U132: No | V132: NPI COST
A133: Adonis 1P | B133: HP | C133: Housing | D133: 240000090201004 | E133: JEE | F133: 2024 | G133: 9 | H133: POC | I133: 45706 | J133: 1 | K133: 1000 | L133: 58000 | M133: 1000000 | N133: Soft tool | O133: 45536 | P133: 3150 | Q133: 58 | R133: 182700 | S133: Srikanth Naule | T133: Not Approved | U133: No | V133: NPI COST
A134: Adonis 1P | B134: HP | C134: Housing | D134: 240000090201004 | E134: JEE | F134: 2024 | G134: 9 | H134: POC | I134: 45706 | J134: 1 | K134: 1000 | L134: 5000 | M134: 1000000 | N134: Soft tool | O134: 45536 | P134: 1275 | Q134: 5 | R134: 6375 | S134: Srikanth Naule | T134: Not Approved | U134: No | V134: NPI COST
A135: Adonis 1P | B135: HP | C135: Housing | D135: 240000090201004 | E135: JEE | F135: 2024 | G135: 9 | H135: POC | I135: 45706 | J135: 1 | K135: 1000 | L135: 4000 | M135: 1000000 | N135: Soft tool | O135: 45536 | P135: 3150 | Q135: 4 | R135: 12600 | S135: Srikanth Naule | T135: Not Approved | U135: No | V135: NPI COST
A136: Adonis 1P | B136: HP | C136: Housing | D136: 240000090201004 | E136: JEE | F136: 2024 | G136: 9 | H136: POC | I136: 45706 | J136: 1 | K136: 1000 | L136: 1000 | M136: 1000000 | N136: Soft tool | O136: 45536 | P136: 1275 | Q136: 1 | R136: 1275 | S136: Srikanth Naule | T136: Not Approved | U136: No | V136: NPI COST
...

Sheet Sheet1
A1: Project | B1: Product category
A2: Vega | B2: MODI | C2: Commodity | D2: Approval Status | E2: Payment Status | F2: Stage | G2: Tool type | H2: CMF Type | I2: Year | J2: Month | L2: Requested by Who | O2: Product Category
A3: Box 8000 1.0 | B3: MODI | C3: Plastic | D3: Approved | E3: Yes | F3: POP | G3: Soft tool | H3: Painting | I3: 2022 | J3: 1 | L3: Chris | O3: RCS POD
A4: DP1500 | B4: MODI | C4: Metal | D4: Not Approved | E4: No | F4: POA | G4: Soft tool EC | H4: Anodizing | I4: 2023 | J4: 2 | L4: Candy | O4: RCS DEVICE
A5: Pen 800 Default 2.0 | B5: MODI | C5: Silicone | F5: POC | G5: Hard tool | H5: Printing | I5: 2024 | J5: 3 | L5: Charlie | O5: MODI
A6: Pen 800 Full 2.0 | B6: MODI | C6: Die-cut | F6: DP-SP | G6: Hard tool EC | H6: Others | I6: 2025 | J6: 4 | O6: HP
A7: Box 800 Default 2.0 | B7: MODI | C7: Magnet | F7: MP | G7: Others | I7: 2026 | J7: 5 | O7: MO
A8: Box 800 Full 2.0 | B8: MODI | C8: Others | I8: 2027 | J8: 6
A9: Box 3000 Full 2.0 | B9: MODI | I9: 2028 | J9: 7
A10: Box 5000 Full 2.0 | B10: MODI | I10: 2029 | J10: 8
A11: Sensa 5K | B11: MODI | I11: 2030 | J11: 9
A12: Box 8000 Full 2.0 | B12: MODI | I12: 2031 | J12: 10
A13: Alto Pod | B13: RCS POD | I13: 2032 | J13: 11
A14: ePod/epod2 cartridge | B14: RCS POD | I14: 2033 | J14: 12
A15: Prismatic Pod | B15: RCS POD | C15: before | D15: after | I15: 2034
A16: Hyper Pro 2P | B16: HP | C16: Hyper Pro 2P | D16: X3 2P
A17: Hyper Core | B17: HP | C17: Hyper Core | D17: X3 Core
A18: Hyper Pro | B18: HP | C18: Hyper Pro | D18: X3 1P
A19: Artemis 1P | B19: HP
A20: Artemis 2P | B20: HP
A21: Artemis BRUSH | B21: HP
A22: Artemis 1.1 CORE | B22: HP
A23: Artemis 1.1 PRO | B23: HP
A24: Clyde POD | B24: HP
A25: Clyde RCS DEVICE | B25: HP
A26: Bacchus | B26: HP
A27: Adonis 1P | B27: HP
A28: Adonis 2P | B28: HP
A29: 1K BOX ESG | B29: MODI
A30: 1K BOX SEMI | B30: MODI
... A42: ePod 3+ | B42: RCS POD
A43: ePod2 Catridges
A44: ePod2 device(Wave1) | B44: RCS DEVICE
A45: ePod2+ device | B45: RCS DEVICE
A46: ePod 3 Device | B46: RCS DEVICE
A47: ePod 3 descope
A48: ePod 3+ Device | B48: RCS DEVICE
A49: KUMA E-Box NZ | B49: RCS DEVICE
A50: KUMA E-Box ROW | B50: RCS DEVICE
A51: KUMA E-Pen 1.0 ROW | B51: RCS DEVICE
A52: US Aquila | B52: RCS DEVICE
A53: MIMOSA 1.0 | B53: RCS DEVICE
A54: MIMOSA 1.0 US | B54: RCS DEVICE
A55: HESTIA XL US (Smart) 2ml / 2.4ml | B55: RCS POD
A56: HESTIA 1.1 (non smart) | B56: RCS POD
A57: HESTIA 1.1 (smart) | B57: RCS POD
A58: KUMA-E 2.0 Pen | B58: RCS DEVICE
A59: KUMA-E 2.0 BOX | B59: RCS DEVICE
... A64: MIMOSA MAX | B64: RCS DEVICE

Sheet Capex summary Dec 2024
B3: Column Labels
B4: Hard tool | C4: Hard tool EC | D4: Soft tool | E4: Soft tool EC | F4: Grand Total
A5: Sum of Total Tool cost | B5: 1.0124147e+08 | C5: 381309 | D5: 3479218.3 | E5: 2259022.3 | F5: 1.0736102e+08
