Workbook
Name _1_0: #REF!
Name _111: #REF!
Name _2_00: #REF!
Name _3_000: #REF!
Name A: #REF!
Name aa: #REF!
Name aaa: #REF!
Name act_cur_pl: #REF!
Name act_sum_pl: #REF!
Name ACT_SumPL: #REF!
Name B: #REF!
Name Backliner_grade: #REF!
Name Backliner_grammage: #REF!
Name BRL: #REF!
Name bud_cur_pl: #REF!
Name bud_sum_pl: #REF!
Name CHF: #REF!
Name CNY: #REF!
Name d: #REF!
Name D07CUR: #REF!
Name D07SUM: #REF!
Name D09SUM: #REF!
Name DOSASIA: #REF!
Name DOSEUR: #REF!
Name DVOL: #REF!
Name f: #REF!
Name Flute: #REF!
Name Fluting_grade: #REF!
Name Fluting_grammage: #REF!
Name Gluing_type: #REF!
Name HBS08CUR: #REF!
Name HBS08SUM: #REF!
Name Ink_type: #REF!
Name INR: #REF!
Name IROR: #REF!
Name JPY: #REF!
Name k53454556: #REF!
Name KAZ: #REF!
Name KRW: #REF!
Name lmthcode: #REF!
Name ly_cur_bal: #REF!
Name ly_cur_pl: #REF!
Name ly_sum_pl: #REF!
Name M_days: #REF!
Name M_days_LY: #REF!
Name mthcode: #REF!
Name mthcodes: #REF!
Name MXN: #REF!
Name precentage_run: #REF!
Name Producing_unit: #REF!
Name Run: #REF!
Name SEK: #REF!
Name SEKCNY: #REF!
Name SEKEUR: #REF!
Name Selling_unit: #REF!
Name set_up: #REF!
Name Set_up_per_job: #REF!
Name ssss: #REF!
Name TaxTV: 10%
Name TaxXL: 5%

Sheet Gap Analysis update
I1: 0 | J1: =J23-'[1]MoDi Initiatives'!G3 -> 0 | K1: =K23-'[1]MoDi Initiatives'!H3 -> 0 | L1: =L23-'[1]MoDi Initiatives'!I3 -> 0 | M1: =M23-'[1]MoDi Initiatives'!J3 -> 0 | N1: =N23-'[1]MoDi Initiatives'!K3 -> 0 | O1: =O23-'[1]MoDi Initiatives'!L3 -> 0.0097544596 | P1: =P23-'[1]MoDi Initiatives'!M3 -> 0.017418977 | Q1: =Q23-'[1]MoDi Initiatives'!N3 -> 0.036927896 | ... Y1: =Y23-'[1]MoDi Initiatives'!V3 -> 0.051298867 | AA1: =AA23-'[1]MoDi Initiatives'!F29 -> 0 | AB1: =AB23-'[1]MoDi Initiatives'!G29 -> 0 | AC1: =AC23-'[1]MoDi Initiatives'!H29 -> 0.00017467878 | AD1: =AD23-'[1]MoDi Initiatives'!I29 -> 0.00017467878 | AE1: =AE23-'[1]MoDi Initiatives'!J29 -> 0.00017467878 | AF1: =AF23-'[1]MoDi Initiatives'!K29 -> 0.00017467878 | AG1: =AG23-'[1]MoDi Initiatives'!L29 -> 0.00017467878 | AH1: =AH23-'[1]MoDi Initiatives'!M29 -> 0.00083788518 | ... AQ1: =AQ23-'[1]MoDi Initiatives'!V29 -> 0.0029225349 | BJ1: =BJ5-BJ6-BJ7 -> 0
A2: Base Price: | B2: MD: | C2: Jun'24 | D2: 2 month lag | I2: CoPlan | J2: CoPlan | K2: CoPlan | L2: CoPlan | M2: CoPlan | N2: CoPlan | O2: CoPlan | P2: CoPlan | Q2: CoPlan | R2: CoPlan | S2: CoPlan | T2: CoPlan | U2: CoPlan | V2: CoPlan | W2: CoPlan | X2: CoPlan | Y2: CoPlan | AA2: SOP2 | AB2: SOP2 | AC2: SOP2 | AD2: SOP2 | AE2: SOP2 | AF2: SOP2 | AG2: SOP2 | AH2: SOP2 | AI2: SOP2 | AJ2: SOP2 | AK2: SOP2 | AL2: SOP2 | AM2: SOP2 | AN2: SOP2 | AO2: SOP2 | AP2: SOP2 | AQ2: SOP2 | AS2: Gap | AT2: Gap | AU2: Gap | AV2: Gap | AW2: Gap | AX2: Gap | AY2: Gap | AZ2: Gap | BA2: Gap | BB2: Gap | BC2: Gap | BD2: Gap | BE2: Gap | BF2: Gap | BG2: Gap | BH2: Gap | BI2: Gap | BK2: Gap remark | BL2: Gap remark | BM2: Gap remark | BN2: Gap remark | BO2: Gap remark | BP2: Gap remark | BQ2: Gap remark | BR2: Gap remark | BS2: Gap remark | BT2: Gap remark | BU2: Gap remark | BV2: Gap remark | BW2: Gap remark | BX2: Gap remark | BY2: Gap remark | BZ2: Gap remark | CA2: Gap remark
B3: Hestia: | C3: Aug'24 | D3: 4 month lag | I3: Actual | J3: Actual | K3: Actual | L3: Actual | M3: Actual | N3: Actual | O3: Actual | P3: Actual | Q3: Actual | R3: Plan | S3: Plan | T3: Plan | U3: Plan | V3: Plan | W3: Plan | X3: Plan | Y3: Plan | AA3: Actual | AB3: Actual | AC3: Actual | AD3: Actual | AE3: Actual | AF3: Actual | AG3: Actual | AH3: Actual | AI3: Actual | AJ3: Plan | AK3: Plan | AL3: Plan | AM3: Plan | AN3: Plan | AO3: Plan | AP3: Plan | AQ3: Plan | AS3: Actual | AT3: Actual | AU3: Actual | AV3: Actual | AW3: Actual | AX3: Actual | AY3: Actual | AZ3: Actual | BA3: Actual | BB3: Plan | BC3: Plan | BD3: Plan | BE3: Plan | BF3: Plan | BG3: Plan | BH3: Plan | BI3: Plan | BK3: Actual | BL3: Actual | BM3: Actual | BN3: Actual | BO3: Actual | BP3: Actual | BQ3: Actual | BR3: Actual | BS3: Actual | BT3: Plan | BU3: Plan | BV3: Plan | BW3: Plan | BX3: Plan | BY3: Plan | BZ3: Plan | CA3: Plan
A4: Product | C4: Gap(till Feb'25) | D4: Gap (Mar'25 to Oct'25) | E4: Gap (Till year end) | F4: Gap Remark (Till Feb'25) | G4: Gap Remark(Till Oct'25) | I4: 45444 | J4: 45474 | K4: 45505 | L4: 45536 | M4: 45566 | N4: 45597 | O4: 45627 | P4: 45658 | Q4: 45689 | R4: 45717 | S4: 45748 | T4: 45778 | U4: 45809 | V4: 45839 | W4: 45870 | X4: 45901 | Y4: 45931 | AA4: 45444 | AB4: 45474 | AC4: 45505 | AD4: 45536 | AE4: 45566 | AF4: 45597 | AG4: 45627 | AH4: 45658 | AI4: 45689 | AJ4: 45717 | AK4: 45748 | AL4: 45778 | AM4: 45809 | AN4: 45839 | AO4: 45870 | AP4: 45901 | AQ4: 45931 | AS4: 45444 | AT4: 45474 | AU4: 45505 | AV4: 45536 | AW4: 45566 | AX4: 45597 | AY4: 45627 | AZ4: 45658 | BA4: 45689 | BB4: 45717 | BC4: 45748 | BD4: 45778 | BE4: 45809 | BF4: 45839 | BG4: 45870 | BH4: 45901 | BI4: 45931 | BK4: 45444 | BL4: 45474 | BM4: 45505 | BN4: 45536 | BO4: 45566 | BP4: 45597 | BQ4: 45627 | BR4: 45658 | BS4: 45689 | BT4: 45717 | BU4: 45748 | BV4: 45778 | BW4: 45809 | BX4: 45839 | BY4: 45870 | BZ4: 45901 | CA4: 45931
A5: PEN 800 Default 2.0 | B5: FCA: | C5: =AI5-Q5 -> 0.0056189584 | D5: =AQ5-Y5-C5 -> 0.033265152 | E5: =AQ5-Y5 -> 0.038884111 | I5: 0.95700927 | J5: =+I5+J6+J7 -> 0.9488551 | K5: =+J5+K6+K7 -> 0.9362433 | L5: =+K5+L6+L7 -> 0.9362433 | M5: =+L5+M6+M7 -> 0.92857879 | N5: =+M5+N6+N7 -> 0.9443825 | O5: =+N5+O6+O7 -> 0.9443825 | P5: =+O5+P6+P7 -> 0.91660502 | Q5: =+P5+Q6+Q7 -> 0.91660502 | ... Y5: =+X5+Y6+Y7 -> 0.89251035 | AA5: ='[1]MoDi Initiatives'!F325 -> 0.95700927 | AB5: =+AA5+AB6+AB7 -> 0.94188556 | AC5: =+AB5+AC6+AC7 -> 0.94749609 | AD5: =+AC5+AD6+AD7 -> 0.93974533 | AE5: =+AD5+AE6+AE7 -> 0.93974533 | AF5: =+AE5+AF6+AF7 -> 0.93680826 | AG5: =+AF5+AG6+AG7 -> 0.93889052 | AH5: =+AG5+AH6+AH7 -> 0.93844868 | AI5: =+AH5+AI6+AI7 -> 0.92222398 | ... AR5: =+AQ5+AR6+AR7 -> #VALUE! | AS5: =I5-AA5 -> 0 | AT5: =AB5-J5 -> -0.0069695382 | AU5: =AC5-K5 -> 0.011252787 | AV5: =AD5-L5 -> 0.0035020291 | AW5: =AE5-M5 -> 0.011166547 | AX5: =AF5-N5 -> -0.007574236 | AY5: =AG5-O5 -> -0.0054919749 | AZ5: =AH5-P5 -> 0.021843653 | BA5: =AI5-Q5 -> 0.0056189584 | ... BI5: =AQ5-Y5 -> 0.038884111
A6: PEN 800 Default 2.0 | B6: Saving: | C6: =SUM(AT6:BA6) -> 0.021422672 | D6: =SUM(BB6:BI6) -> 0.016186954 | E6: =+D6+C6 -> 0.037609626 | J6: =SUBTOTAL(9,J8:J13) -> -0.008154177 | K6: =SUBTOTAL(9,K8:K13) -> -0.012611794 | L6: =SUBTOTAL(9,L8:L13) -> 0 | M6: =SUBTOTAL(9,M8:M13) -> -0.0076645176 | N6: =SUBTOTAL(9,N8:N13) -> 0 | O6: =SUBTOTAL(9,O8:O13) -> 0 | P6: =SUBTOTAL(9,P8:P13) -> -0.027777476 | Q6: =SUBTOTAL(9,Q8:Q13) -> 0 | ... Y6: =SUBTOTAL(9,Y8:Y13) -> 0 | AB6: =SUBTOTAL(9,AB8:AB13) -> -0.015123715 | AC6: =SUBTOTAL(9,AC8:AC13) -> 0.0056105315 | AD6: =SUBTOTAL(9,AD8:AD13) -> -0.007750758 | AE6: =SUBTOTAL(9,AE8:AE13) -> 0 | AF6: =SUBTOTAL(9,AF8:AF13) -> -0.0029370693 | AG6: =SUBTOTAL(9,AG8:AG13) -> 0.0020822611 | AH6: =SUBTOTAL(9,AH8:AH13) -> -0.00044184767 | AI6: =SUBTOTAL(9,AI8:AI13) -> -0.016224695 | ... AQ6: =SUBTOTAL(9,AQ8:AQ13) -> 0 | AS6: =I6-AA6 -> 0 | AT6: =AB6-J6 -> -0.0069695382 | AU6: =AC6-K6 -> 0.018222325 | AV6: =AD6-L6 -> -0.007750758 | AW6: =AE6-M6 -> 0.0076645176 | AX6: =AF6-N6 -> -0.0029370693 | AY6: =AG6-O6 -> 0.0020822611 | AZ6: =AH6-P6 -> 0.027335628 | BA6: =AI6-Q6 -> -0.016224695 | ... BI6: =AQ6-Y6 -> 0
A7: PEN 800 Default 2.0 | B7: Inflation | C7: =SUM(AT7:BA7) -> -0.015803713 | D7: =SUM(BB7:BI7) -> 0.017078198 | E7: =+D7+C7 -> 0.0012744848 | G7: Inflation need to postpone: 1. Thimble; 2. DL. 3. Others to cancel. | J7: =SUMIFS('MoDi Initiatives'!H:H,'MoDi Initiatives'!$C:$C,'Gap Analysis update'!$B7,'MoDi Initiatives'!$A:$A,'Gap Analysis update'!$A7,'MoDi Initiatives'!$B:$B,'Gap Analysis update'!J$2) -> 0 | K7: =SUMIFS('MoDi Initiatives'!I:I,'MoDi Initiatives'!$C:$C,'Gap Analysis update'!$B7,'MoDi Initiatives'!$A:$A,'Gap Analysis update'!$A7,'MoDi Initiatives'!$B:$B,'Gap Analysis update'!K$2) -> 0 | L7: =SUMIFS('MoDi Initiatives'!J:J,'MoDi Initiatives'!$C:$C,'Gap Analysis update'!$B7,'MoDi Initiatives'!$A:$A,'Gap Analysis update'!$A7,'MoDi Initiatives'!$B:$B,'Gap Analysis update'!L$2) -> 0 | M7: =SUMIFS('MoDi Initiatives'!K:K,'MoDi Initiatives'!$C:$C,'Gap Analysis update'!$B7,'MoDi Initiatives'!$A:$A,'Gap Analysis update'!$A7,'MoDi Initiatives'!$B:$B,'Gap Analysis update'!M$2) -> 0 | N7: =SUMIFS('MoDi Initiatives'!L:L,'MoDi Initiatives'!$C:$C,'Gap Analysis update'!$B7,'MoDi Initiatives'!$A:$A,'Gap Analysis update'!$A7,'MoDi Initiatives'!$B:$B,'Gap Analysis update'!N$2) -> 0.015803713 | O7: =SUMIFS('MoDi Initiatives'!M:M,'MoDi Initiatives'!$C:$C,'Gap Analysis update'!$B7,'MoDi Initiatives'!$A:$A,'Gap Analysis update'!$A7,'MoDi Initiatives'!$B:$B,'Gap Analysis update'!O$2) -> 0 | P7: =SUMIFS('MoDi Initiatives'!N:N,'MoDi Initiatives'!$C:$C,'Gap Analysis update'!$B7,'MoDi Initiatives'!$A:$A,'Gap Analysis update'!$A7,'MoDi Initiatives'!$B:$B,'Gap Analysis update'!P$2) -> 0 | Q7: =SUMIFS('MoDi Initiatives'!O:O,'MoDi Initiatives'!$C:$C,'Gap Analysis update'!$B7,'MoDi Initiatives'!$A:$A,'Gap Analysis update'!$A7,'MoDi Initiatives'!$B:$B,'Gap Analysis update'!Q$2) -> 0 | R7: =SUMIFS('MoDi Initiatives'!P:P,'MoDi Initiatives'!$C:$C,'Gap Analysis update'!$B7,'MoDi Initiatives'!$A:$A,'Gap Analysis update'!$A7,'MoDi Initiatives'!$B:$B,'Gap Analysis update'!R$2) -> 0 | S7: =SUMIFS('MoDi Initiatives'!Q:Q,'MoDi Initiatives'!$C:$C,'Gap Analysis update'!$B7,'MoDi Initiatives'!$A:$A,'Gap Analysis update'!$A7,'MoDi Initiatives'!$B:$B,'Gap Analysis update'!S$2) -> 0 | T7: =SUMIFS('MoDi Initiatives'!R:R,'MoDi Initiatives'!$C:$C,'Gap Analysis update'!$B7,'MoDi Initiatives'!$A:$A,'Gap Analysis update'!$A7,'MoDi Initiatives'!$B:$B,'Gap Analysis update'!T$2) -> 0 | U7: =SUMIFS('MoDi Initiatives'!S:S,'MoDi Initiatives'!$C:$C,'Gap Analysis update'!$B7,'MoDi Initiatives'!$A:$A,'Gap Analysis update'!$A7,'MoDi Initiatives'!$B:$B,'Gap Analysis update'!U$2) -> 0 | V7: =SUMIFS('MoDi Initiatives'!T:T,'MoDi Initiatives'!$C:$C,'Gap Analysis update'!$B7,'MoDi Initiatives'!$A:$A,'Gap Analysis update'!$A7,'MoDi Initiatives'!$B:$B,'Gap Analysis update'!V$2) -> 0 | W7: =SUMIFS('MoDi Initiatives'!U:U,'MoDi Initiatives'!$C:$C,'Gap Analysis update'!$B7,'MoDi Initiatives'!$A:$A,'Gap Analysis update'!$A7,'MoDi Initiatives'!$B:$B,'Gap Analysis update'!W$2) -> 0 | X7: =SUMIFS('MoDi Initiatives'!V:V,'MoDi Initiatives'!$C:$C,'Gap Analysis update'!$B7,'MoDi Initiatives'!$A:$A,'Gap Analysis update'!$A7,'MoDi Initiatives'!$B:$B,'Gap Analysis update'!X$2) -> 0 | Y7: =SUMIFS('MoDi Initiatives'!W:W,'MoDi Initiatives'!$C:$C,'Gap Analysis update'!$B7,'MoDi Initiatives'!$A:$A,'Gap Analysis update'!$A7,'MoDi Initiatives'!$B:$B,'Gap Analysis update'!Y$2) -> 0 | AB7: =SUMIFS('MoDi Initiatives'!H:H,'MoDi Initiatives'!$C:$C,'Gap Analysis update'!$B7,'MoDi Initiatives'!$A:$A,'Gap Analysis update'!$A7,'MoDi Initiatives'!$B:$B,'Gap Analysis update'!AB$2) -> 0 | AC7: =SUMIFS('MoDi Initiatives'!I:I,'MoDi Initiatives'!$C:$C,'Gap Analysis update'!$B7,'MoDi Initiatives'!$A:$A,'Gap Analysis update'!$A7,'MoDi Initiatives'!$B:$B,'Gap Analysis update'!AC$2) -> 0 | AD7: =SUMIFS('MoDi Initiatives'!J:J,'MoDi Initiatives'!$C:$C,'Gap Analysis update'!$B7,'MoDi Initiatives'!$A:$A,'Gap Analysis update'!$A7,'MoDi Initiatives'!$B:$B,'Gap Analysis update'!AD$2) -> 0 | AE7: =SUMIFS('MoDi Initiatives'!K:K,'MoDi Initiatives'!$C:$C,'Gap Analysis update'!$B7,'MoDi Initiatives'!$A:$A,'Gap Analysis update'!$A7,'MoDi Initiatives'!$B:$B,'Gap Analysis update'!AE$2) -> 0 | AF7: =SUMIFS('MoDi Initiatives'!L:L,'MoDi Initiatives'!$C:$C,'Gap Analysis update'!$B7,'MoDi Initiatives'!$A:$A,'Gap Analysis update'!$A7,'MoDi Initiatives'!$B:$B,'Gap Analysis update'!AF$2) -> 0 | AG7: =SUMIFS('MoDi Initiatives'!M:M,'MoDi Initiatives'!$C:$C,'Gap Analysis update'!$B7,'MoDi Initiatives'!$A:$A,'Gap Analysis update'!$A7,'MoDi Initiatives'!$B:$B,'Gap Analysis update'!AG$2) -> 0 | AH7: =SUMIFS('MoDi Initiatives'!N:N,'MoDi Initiatives'!$C:$C,'Gap Analysis update'!$B7,'MoDi Initiatives'!$A:$A,'Gap Analysis update'!$A7,'MoDi Initiatives'!$B:$B,'Gap Analysis update'!AH$2) -> 0 | AI7: =SUMIFS('MoDi Initiatives'!O:O,'MoDi Initiatives'!$C:$C,'Gap Analysis update'!$B7,'MoDi Initiatives'!$A:$A,'Gap Analysis update'!$A7,'MoDi Initiatives'!$B:$B,'Gap Analysis update'!AI$2) -> 0 | AJ7: =SUMIFS('MoDi Initiatives'!P:P,'MoDi Initiatives'!$C:$C,'Gap Analysis update'!$B7,'MoDi Initiatives'!$A:$A,'Gap Analysis update'!$A7,'MoDi Initiatives'!$B:$B,'Gap Analysis update'!AJ$2) -> 0 | AK7: =SUMIFS('MoDi Initiatives'!Q:Q,'MoDi Initiatives'!$C:$C,'Gap Analysis update'!$B7,'MoDi Initiatives'!$A:$A,'Gap Analysis update'!$A7,'MoDi Initiatives'!$B:$B,'Gap Analysis update'!AK$2) -> 0.013589329 | AL7: =SUMIFS('MoDi Initiatives'!R:R,'MoDi Initiatives'!$C:$C,'Gap Analysis update'!$B7,'MoDi Initiatives'!$A:$A,'Gap Analysis update'!$A7,'MoDi Initiatives'!$B:$B,'Gap Analysis update'!AL$2) -> 0 | AM7: =SUMIFS('MoDi Initiatives'!S:S,'MoDi Initiatives'!$C:$C,'Gap Analysis update'!$B7,'MoDi Initiatives'!$A:$A,'Gap Analysis update'!$A7,'MoDi Initiatives'!$B:$B,'Gap Analysis update'!AM$2) -> 0.0034888693 | AN7: =SUMIFS('MoDi Initiatives'!T:T,'MoDi Initiatives'!$C:$C,'Gap Analysis update'!$B7,'MoDi Initiatives'!$A:$A,'Gap Analysis update'!$A7,'MoDi Initiatives'!$B:$B,'Gap Analysis update'!AN$2) -> 0 | AO7: =SUMIFS('MoDi Initiatives'!U:U,'MoDi Initiatives'!$C:$C,'Gap Analysis update'!$B7,'MoDi Initiatives'!$A:$A,'Gap Analysis update'!$A7,'MoDi Initiatives'!$B:$B,'Gap Analysis update'!AO$2) -> 0 | AP7: =SUMIFS('MoDi Initiatives'!V:V,'MoDi Initiatives'!$C:$C,'Gap Analysis update'!$B7,'MoDi Initiatives'!$A:$A,'Gap Analysis update'!$A7,'MoDi Initiatives'!$B:$B,'Gap Analysis update'!AP$2) -> 0 | AQ7: =SUMIFS('MoDi Initiatives'!W:W,'MoDi Initiatives'!$C:$C,'Gap Analysis update'!$B7,'MoDi Initiatives'!$A:$A,'Gap Analysis update'!$A7,'MoDi Initiatives'!$B:$B,'Gap Analysis update'!AQ$2) -> 0 | AR7: =SUMIFS('[1]MoDi Initiatives'!W:W,'[1]MoDi Initiatives'!$B:$B,'Gap Analysis update'!AR$2,'[1]MoDi Initiatives'!$A:$A,'Gap Analysis update'!$A7,'[1]MoDi Initiatives'!$C:$C,"Inflation") -> #VALUE! | AS7: =I7-AA7 -> 0 | AT7: =AB7-J7 -> 0 | AU7: =AC7-K7 -> 0 | AV7: =AD7-L7 -> 0 | AW7: =AE7-M7 -> 0 | AX7: =AF7-N7 -> -0.015803713 | AY7: =AG7-O7 -> 0 | AZ7: =AH7-P7 -> 0 | BA7: =AI7-Q7 -> 0 | ... BI7: =AQ7-Y7 -> 0
A8: PEN 800 Default 2.0 | B8: Mechanical Parts | C8: =SUM(AS8:BA8) -> 0 | D8: =SUM(BB8:BI8) -> 0 | E8: =D8+C8 -> 0 | F8: Gap: 3.23P: 1. COE : Gap 2.84P; 1) Target: -3.91P. 1) Achieve: -1.06p 2) Gap:2.84P. Reason: 1) Coplan SOP6 Stretch: 2.93p, only finish 0.09p(thimble, TFK Protective shell) Action: find opp of 2.84p. 2. Extra stretch-finance: 0.38p gap; (to align with Finance) | J8: =SUMIFS('MoDi Initiatives'!H:H,'MoDi Initiatives'!$E:$E,'Gap Analysis update'!$B8,'MoDi Initiatives'!$A:$A,'Gap Analysis update'!$A8,'MoDi Initiatives'!$B:$B,'Gap Analysis update'!J$2)-SUMIFS('MoDi Initiatives'!H:H,'MoDi Initiatives'!$E:$E,'Gap Analysis update'!$B8,'MoDi Initiatives'!$A:$A,'Gap Analysis update'!$A8,'MoDi Initiatives'!$C:$C,'Gap Analysis update'!$B$7,'MoDi Initiatives'!$B:$B,'Gap Analysis update'!J$2) -> 0 | K8: =SUMIFS('MoDi Initiatives'!I:I,'MoDi Initiatives'!$E:$E,'Gap Analysis update'!$B8,'MoDi Initiatives'!$A:$A,'Gap Analysis update'!$A8,'MoDi Initiatives'!$B:$B,'Gap Analysis update'!K$2)-SUMIFS('MoDi Initiatives'!I:I,'MoDi Initiatives'!$E:$E,'Gap Analysis update'!$B8,'MoDi Initiatives'!$A:$A,'Gap Analysis update'!$A8,'MoDi Initiatives'!$C:$C,'Gap Analysis update'!$B$7,'MoDi Initiatives'!$B:$B,'Gap Analysis update'!K$2) -> 0 | L8: =SUMIFS('MoDi Initiatives'!J:J,'MoDi Initiatives'!$E:$E,'Gap Analysis update'!$B8,'MoDi Initiatives'!$A:$A,'Gap Analysis update'!$A8,'MoDi Initiatives'!$B:$B,'Gap Analysis update'!L$2)-SUMIFS('MoDi Initiatives'!J:J,'MoDi Initiatives'!$E:$E,'Gap Analysis update'!$B8,'MoDi Initiatives'!$A:$A,'Gap Analysis update'!$A8,'MoDi Initiatives'!$C:$C,'Gap Analysis update'!$B$7,'MoDi Initiatives'!$B:$B,'Gap Analysis update'!L$2) -> 0 | M8: =SUMIFS('MoDi Initiatives'!K:K,'MoDi Initiatives'!$E:$E,'Gap Analysis update'!$B8,'MoDi Initiatives'!$A:$A,'Gap Analysis update'!$A8,'MoDi Initiatives'!$B:$B,'Gap Analysis update'!M$2)-SUMIFS('MoDi Initiatives'!K:K,'MoDi Initiatives'!$E:$E,'Gap Analysis update'!$B8,'MoDi Initiatives'!$A:$A,'Gap Analysis update'!$A8,'MoDi Initiatives'!$C:$C,'Gap Analysis update'!$B$7,'MoDi Initiatives'!$B:$B,'Gap Analysis update'!M$2) -> 0 | N8: =SUMIFS('MoDi Initiatives'!L:L,'MoDi Initiatives'!$E:$E,'Gap Analysis update'!$B8,'MoDi Initiatives'!$A:$A,'Gap Analysis update'!$A8,'MoDi Initiatives'!$B:$B,'Gap Analysis update'!N$2)-SUMIFS('MoDi Initiatives'!L:L,'MoDi Initiatives'!$E:$E,'Gap Analysis update'!$B8,'MoDi Initiatives'!$A:$A,'Gap Analysis update'!$A8,'MoDi Initiatives'!$C:$C,'Gap Analysis update'!$B$7,'MoDi Initiatives'!$B:$B,'Gap Analysis update'!N$2) -> 0 | O8: =SUMIFS('MoDi Initiatives'!M:M,'MoDi Initiatives'!$E:$E,'Gap Analysis update'!$B8,'MoDi Initiatives'!$A:$A,'Gap Analysis update'!$A8,'MoDi Initiatives'!$B:$B,'Gap Analysis update'!O$2)-SUMIFS('MoDi Initiatives'!M:M,'MoDi Initiatives'!$E:$E,'Gap Analysis update'!$B8,'MoDi Initiatives'!$A:$A,'Gap Analysis update'!$A8,'MoDi Initiatives'!$C:$C,'Gap Analysis update'!$B$7,'MoDi Initiatives'!$B:$B,'Gap Analysis update'!O$2) -> 0 | P8: =SUMIFS('MoDi Initiatives'!N:N,'MoDi Initiatives'!$E:$E,'Gap Analysis update'!$B8,'MoDi Initiatives'!$A:$A,'Gap Analysis update'!$A8,'MoDi Initiatives'!$B:$B,'Gap Analysis update'!P$2)-SUMIFS('MoDi Initiatives'!N:N,'MoDi Initiatives'!$E:$E,'Gap Analysis update'!$B8,'MoDi Initiatives'!$A:$A,'Gap Analysis update'!$A8,'MoDi Initiatives'!$C:$C,'Gap Analysis update'!$B$7,'MoDi Initiatives'!$B:$B,'Gap Analysis update'!P$2) -> 0 | Q8: =SUMIFS('MoDi Initiatives'!O:O,'MoDi Initiatives'!$E:$E,'Gap Analysis update'!$B8,'MoDi Initiatives'!$A:$A,'Gap Analysis update'!$A8,'MoDi Initiatives'!$B:$B,'Gap Analysis update'!Q$2)-SUMIFS('MoDi Initiatives'!O:O,'MoDi Initiatives'!$E:$E,'Gap Analysis update'!$B8,'MoDi Initiatives'!$A:$A,'Gap Analysis update'!$A8,'MoDi Initiatives'!$C:$C,'Gap Analysis update'!$B$7,'MoDi Initiatives'!$B:$B,'Gap Analysis update'!Q$2) -> 0 | R8: =SUMIFS('MoDi Initiatives'!P:P,'MoDi Initiatives'!$E:$E,'Gap Analysis update'!$B8,'MoDi Initiatives'!$A:$A,'Gap Analysis update'!$A8,'MoDi Initiatives'!$B:$B,'Gap Analysis update'!R$2)-SUMIFS('MoDi Initiatives'!P:P,'MoDi Initiatives'!$E:$E,'Gap Analysis update'!$B8,'MoDi Initiatives'!$A:$A,'Gap Analysis update'!$A8,'MoDi Initiatives'!$C:$C,'Gap Analysis update'!$B$7,'MoDi Initiatives'!$B:$B,'Gap Analysis update'!R$2) -> 0 | S8: =SUMIFS('MoDi Initiatives'!Q:Q,'MoDi Initiatives'!$E:$E,'Gap Analysis update'!$B8,'MoDi Initiatives'!$A:$A,'Gap Analysis update'!$A8,'MoDi Initiatives'!$B:$B,'Gap Analysis update'!S$2)-SUMIFS('MoDi Initiatives'!Q:Q,'MoDi Initiatives'!$E:$E,'Gap Analysis update'!$B8,'MoDi Initiatives'!$A:$A,'Gap Analysis update'!$A8,'MoDi Initiatives'!$C:$C,'Gap Analysis update'!$B$7,'MoDi Initiatives'!$B:$B,'Gap Analysis update'!S$2) -> 0 | T8: =SUMIFS('MoDi Initiatives'!R:R,'MoDi Initiatives'!$E:$E,'Gap Analysis update'!$B8,'MoDi Initiatives'!$A:$A,'Gap Analysis update'!$A8,'MoDi Initiatives'!$B:$B,'Gap Analysis update'!T$2)-SUMIFS('MoDi Initiatives'!R:R,'MoDi Initiatives'!$E:$E,'Gap Analysis update'!$B8,'MoDi Initiatives'!$A:$A,'Gap Analysis update'!$A8,'MoDi Initiatives'!$C:$C,'Gap Analysis update'!$B$7,'MoDi Initiatives'!$B:$B,'Gap Analysis update'!T$2) -> 0 | U8: =SUMIFS('MoDi Initiatives'!S:S,'MoDi Initiatives'!$E:$E,'Gap Analysis update'!$B8,'MoDi Initiatives'!$A:$A,'Gap Analysis update'!$A8,'MoDi Initiatives'!$B:$B,'Gap Analysis update'!U$2)-SUMIFS('MoDi Initiatives'!S:S,'MoDi Initiatives'!$E:$E,'Gap Analysis update'!$B8,'MoDi Initiatives'!$A:$A,'Gap Analysis update'!$A8,'MoDi Initiatives'!$C:$C,'Gap Analysis update'!$B$7,'MoDi Initiatives'!$B:$B,'Gap Analysis update'!U$2) -> 0 | V8: =SUMIFS('MoDi Initiatives'!T:T,'MoDi Initiatives'!$E:$E,'Gap Analysis update'!$B8,'MoDi Initiatives'!$A:$A,'Gap Analysis update'!$A8,'MoDi Initiatives'!$B:$B,'Gap Analysis update'!V$2)-SUMIFS('MoDi Initiatives'!T:T,'MoDi Initiatives'!$E:$E,'Gap Analysis update'!$B8,'MoDi Initiatives'!$A:$A,'Gap Analysis update'!$A8,'MoDi Initiatives'!$C:$C,'Gap Analysis update'!$B$7,'MoDi Initiatives'!$B:$B,'Gap Analysis update'!V$2) -> 0 | W8: =SUMIFS('MoDi Initiatives'!U:U,'MoDi Initiatives'!$E:$E,'Gap Analysis update'!$B8,'MoDi Initiatives'!$A:$A,'Gap Analysis update'!$A8,'MoDi Initiatives'!$B:$B,'Gap Analysis update'!W$2)-SUMIFS('MoDi Initiatives'!U:U,'MoDi Initiatives'!$E:$E,'Gap Analysis update'!$B8,'MoDi Initiatives'!$A:$A,'Gap Analysis update'!$A8,'MoDi Initiatives'!$C:$C,'Gap Analysis update'!$B$7,'MoDi Initiatives'!$B:$B,'Gap Analysis update'!W$2) -> 0 | X8: =SUMIFS('MoDi Initiatives'!V:V,'MoDi Initiatives'!$E:$E,'Gap Analysis update'!$B8,'MoDi Initiatives'!$A:$A,'Gap Analysis update'!$A8,'MoDi Initiatives'!$B:$B,'Gap Analysis update'!X$2)-SUMIFS('MoDi Initiatives'!V:V,'MoDi Initiatives'!$E:$E,'Gap Analysis update'!$B8,'MoDi Initiatives'!$A:$A,'Gap Analysis update'!$A8,'MoDi Initiatives'!$C:$C,'Gap Analysis update'!$B$7,'MoDi Initiatives'!$B:$B,'Gap Analysis update'!X$2) -> 0 | Y8: =SUMIFS('MoDi Initiatives'!W:W,'MoDi Initiatives'!$E:$E,'Gap Analysis update'!$B8,'MoDi Initiatives'!$A:$A,'Gap Analysis update'!$A8,'MoDi Initiatives'!$B:$B,'Gap Analysis update'!Y$2)-SUMIFS('MoDi Initiatives'!W:W,'MoDi Initiatives'!$E:$E,'Gap Analysis update'!$B8,'MoDi Initiatives'!$A:$A,'Gap Analysis update'!$A8,'MoDi Initiatives'!$C:$C,'Gap Analysis update'!$B$7,'MoDi Initiatives'!$B:$B,'Gap Analysis update'!Y$2) -> 0 | AB8: =SUMIFS('MoDi Initiatives'!H:H,'MoDi Initiatives'!$E:$E,'Gap Analysis update'!$B8,'MoDi Initiatives'!$A:$A,'Gap Analysis update'!$A8,'MoDi Initiatives'!$B:$B,'Gap Analysis update'!AB$2)-SUMIFS('MoDi Initiatives'!H:H,'MoDi Initiatives'!$E:$E,'Gap Analysis update'!$B8,'MoDi Initiatives'!$A:$A,'Gap Analysis update'!$A8,'MoDi Initiatives'!$B:$B,'Gap Analysis update'!AB$2,'MoDi Initiatives'!$C:$C,'Gap Analysis update'!$B$7) -> 0 | AC8: =SUMIFS('MoDi Initiatives'!I:I,'MoDi Initiatives'!$E:$E,'Gap Analysis update'!$B8,'MoDi Initiatives'!$A:$A,'Gap Analysis update'!$A8,'MoDi Initiatives'!$B:$B,'Gap Analysis update'!AC$2)-SUMIFS('MoDi Initiatives'!I:I,'MoDi Initiatives'!$E:$E,'Gap Analysis update'!$B8,'MoDi Initiatives'!$A:$A,'Gap Analysis update'!$A8,'MoDi Initiatives'!$B:$B,'Gap Analysis update'!AC$2,'MoDi Initiatives'!$C:$C,'Gap Analysis update'!$B$7) -> 0 | AD8: =SUMIFS('MoDi Initiatives'!J:J,'MoDi Initiatives'!$E:$E,'Gap Analysis update'!$B8,'MoDi Initiatives'!$A:$A,'Gap Analysis update'!$A8,'MoDi Initiatives'!$B:$B,'Gap Analysis update'!AD$2)-SUMIFS('MoDi Initiatives'!J:J,'MoDi Initiatives'!$E:$E,'Gap Analysis update'!$B8,'MoDi Initiatives'!$A:$A,'Gap Analysis update'!$A8,'MoDi Initiatives'!$B:$B,'Gap Analysis update'!AD$2,'MoDi Initiatives'!$C:$C,'Gap Analysis update'!$B$7) -> 0 | AE8: =SUMIFS('MoDi Initiatives'!K:K,'MoDi Initiatives'!$E:$E,'Gap Analysis update'!$B8,'MoDi Initiatives'!$A:$A,'Gap Analysis update'!$A8,'MoDi Initiatives'!$B:$B,'Gap Analysis update'!AE$2)-SUMIFS('MoDi Initiatives'!K:K,'MoDi Initiatives'!$E:$E,'Gap Analysis update'!$B8,'MoDi Initiatives'!$A:$A,'Gap Analysis update'!$A8,'MoDi Initiatives'!$B:$B,'Gap Analysis update'!AE$2,'MoDi Initiatives'!$C:$C,'Gap Analysis update'!$B$7) -> 0 | AF8: =SUMIFS('MoDi Initiatives'!L:L,'MoDi Initiatives'!$E:$E,'Gap Analysis update'!$B8,'MoDi Initiatives'!$A:$A,'Gap Analysis update'!$A8,'MoDi Initiatives'!$B:$B,'Gap Analysis update'!AF$2)-SUMIFS('MoDi Initiatives'!L:L,'MoDi Initiatives'!$E:$E,'Gap Analysis update'!$B8,'MoDi Initiatives'!$A:$A,'Gap Analysis update'!$A8,'MoDi Initiatives'!$B:$B,'Gap Analysis update'!AF$2,'MoDi Initiatives'!$C:$C,'Gap Analysis update'!$B$7) -> 0 | AG8: =SUMIFS('MoDi Initiatives'!M:M,'MoDi Initiatives'!$E:$E,'Gap Analysis update'!$B8,'MoDi Initiatives'!$A:$A,'Gap Analysis update'!$A8,'MoDi Initiatives'!$B:$B,'Gap Analysis update'!AG$2)-SUMIFS('MoDi Initiatives'!M:M,'MoDi Initiatives'!$E:$E,'Gap Analysis update'!$B8,'MoDi Initiatives'!$A:$A,'Gap Analysis update'!$A8,'MoDi Initiatives'!$B:$B,'Gap Analysis update'!AG$2,'MoDi Initiatives'!$C:$C,'Gap Analysis update'!$B$7) -> 0 | AH8: =SUMIFS('MoDi Initiatives'!N:N,'MoDi Initiatives'!$E:$E,'Gap Analysis update'!$B8,'MoDi Initiatives'!$A:$A,'Gap Analysis update'!$A8,'MoDi Initiatives'!$B:$B,'Gap Analysis update'!AH$2)-SUMIFS('MoDi Initiatives'!N:N,'MoDi Initiatives'!$E:$E,'Gap Analysis update'!$B8,'MoDi Initiatives'!$A:$A,'Gap Analysis update'!$A8,'MoDi Initiatives'!$B:$B,'Gap Analysis update'!AH$2,'MoDi Initiatives'!$C:$C,'Gap Analysis update'!$B$7) -> 0 | AI8: =SUMIFS('MoDi Initiatives'!O:O,'MoDi Initiatives'!$E:$E,'Gap Analysis update'!$B8,'MoDi Initiatives'!$A:$A,'Gap Analysis update'!$A8,'MoDi Initiatives'!$B:$B,'Gap Analysis update'!AI$2)-SUMIFS('MoDi Initiatives'!O:O,'MoDi Initiatives'!$E:$E,'Gap Analysis update'!$B8,'MoDi Initiatives'!$A:$A,'Gap Analysis update'!$A8,'MoDi Initiatives'!$B:$B,'Gap Analysis update'!AI$2,'MoDi Initiatives'!$C:$C,'Gap Analysis update'!$B$7) -> 0 | AJ8: =SUMIFS('MoDi Initiatives'!P:P,'MoDi Initiatives'!$E:$E,'Gap Analysis update'!$B8,'MoDi Initiatives'!$A:$A,'Gap Analysis update'!$A8,'MoDi Initiatives'!$B:$B,'Gap Analysis update'!AJ$2)-SUMIFS('MoDi Initiatives'!P:P,'MoDi Initiatives'!$E:$E,'Gap Analysis update'!$B8,'MoDi Initiatives'!$A:$A,'Gap Analysis update'!$A8,'MoDi Initiatives'!$B:$B,'Gap Analysis update'!AJ$2,'MoDi Initiatives'!$C:$C,'Gap Analysis update'!$B$7) -> 0 | AK8: =SUMIFS('MoDi Initiatives'!Q:Q,'MoDi Initiatives'!$E:$E,'Gap Analysis update'!$B8,'MoDi Initiatives'!$A:$A,'Gap Analysis update'!$A8,'MoDi Initiatives'!$B:$B,'Gap Analysis update'!AK$2)-SUMIFS('MoDi Initiatives'!Q:Q,'MoDi Initiatives'!$E:$E,'Gap Analysis update'!$B8,'MoDi Initiatives'!$A:$A,'Gap Analysis update'!$A8,'MoDi Initiatives'!$B:$B,'Gap Analysis update'!AK$2,'MoDi Initiatives'!$C:$C,'Gap Analysis update'!$B$7) -> 0 | AL8: =SUMIFS('MoDi Initiatives'!R:R,'MoDi Initiatives'!$E:$E,'Gap Analysis update'!$B8,'MoDi Initiatives'!$A:$A,'Gap Analysis update'!$A8,'MoDi Initiatives'!$B:$B,'Gap Analysis update'!AL$2)-SUMIFS('MoDi Initiatives'!R:R,'MoDi Initiatives'!$E:$E,'Gap Analysis update'!$B8,'MoDi Initiatives'!$A:$A,'Gap Analysis update'!$A8,'MoDi Initiatives'!$B:$B,'Gap Analysis update'!AL$2,'MoDi Initiatives'!$C:$C,'Gap Analysis update'!$B$7) -> 0 | AM8: =SUMIFS('MoDi Initiatives'!S:S,'MoDi Initiatives'!$E:$E,'Gap Analysis update'!$B8,'MoDi Initiatives'!$A:$A,'Gap Analysis update'!$A8,'MoDi Initiatives'!$B:$B,'Gap Analysis update'!AM$2)-SUMIFS('MoDi Initiatives'!S:S,'MoDi Initiatives'!$E:$E,'Gap Analysis update'!$B8,'MoDi Initiatives'!$A:$A,'Gap Analysis update'!$A8,'MoDi Initiatives'!$B:$B,'Gap Analysis update'!AM$2,'MoDi Initiatives'!$C:$C,'Gap Analysis update'!$B$7) -> 0 | AN8: =SUMIFS('MoDi Initiatives'!T:T,'MoDi Initiatives'!$E:$E,'Gap Analysis update'!$B8,'MoDi Initiatives'!$A:$A,'Gap Analysis update'!$A8,'MoDi Initiatives'!$B:$B,'Gap Analysis update'!AN$2)-SUMIFS('MoDi Initiatives'!T:T,'MoDi Initiatives'!$E:$E,'Gap Analysis update'!$B8,'MoDi Initiatives'!$A:$A,'Gap Analysis update'!$A8,'MoDi Initiatives'!$B:$B,'Gap Analysis update'!AN$2,'MoDi Initiatives'!$C:$C,'Gap Analysis update'!$B$7) -> 0 | AO8: =SUMIFS('MoDi Initiatives'!U:U,'MoDi Initiatives'!$E:$E,'Gap Analysis update'!$B8,'MoDi Initiatives'!$A:$A,'Gap Analysis update'!$A8,'MoDi Initiatives'!$B:$B,'Gap Analysis update'!AO$2)-SUMIFS('MoDi Initiatives'!U:U,'MoDi Initiatives'!$E:$E,'Gap Analysis update'!$B8,'MoDi Initiatives'!$A:$A,'Gap Analysis update'!$A8,'MoDi Initiatives'!$B:$B,'Gap Analysis update'!AO$2,'MoDi Initiatives'!$C:$C,'Gap Analysis update'!$B$7) -> 0 | AP8: =SUMIFS('MoDi Initiatives'!V:V,'MoDi Initiatives'!$E:$E,'Gap Analysis update'!$B8,'MoDi Initiatives'!$A:$A,'Gap Analysis update'!$A8,'MoDi Initiatives'!$B:$B,'Gap Analysis update'!AP$2)-SUMIFS('MoDi Initiatives'!V:V,'MoDi Initiatives'!$E:$E,'Gap Analysis update'!$B8,'MoDi Initiatives'!$A:$A,'Gap Analysis update'!$A8,'MoDi Initiatives'!$B:$B,'Gap Analysis update'!AP$2,'MoDi Initiatives'!$C:$C,'Gap Analysis update'!$B$7) -> 0 | AQ8: =SUMIFS('MoDi Initiatives'!W:W,'MoDi Initiatives'!$E:$E,'Gap Analysis update'!$B8,'MoDi Initiatives'!$A:$A,'Gap Analysis update'!$A8,'MoDi Initiatives'!$B:$B,'Gap Analysis update'!AQ$2)-SUMIFS('MoDi Initiatives'!W:W,'MoDi Initiatives'!$E:$E,'Gap Analysis update'!$B8,'MoDi Initiatives'!$A:$A,'Gap Analysis update'!$A8,'MoDi Initiatives'!$B:$B,'Gap Analysis update'!AQ$2,'MoDi Initiatives'!$C:$C,'Gap Analysis update'!$B$7) -> 0 | AR8: =SUMIFS('[1]MoDi Initiatives'!$G:$G,'[1]MoDi Initiatives'!$A:$A,'Gap Analysis update'!$A8,'[1]MoDi Initiatives'!$B:$B,"SOP1",'[1]MoDi Initiatives'!$E:$E,'Gap Analysis update'!$B8) -> #VALUE! | AT8: =AB8-J8 -> 0 | AU8: =AC8-K8 -> 0 | AV8: =AD8-L8 -> 0 | AW8: =AE8-M8 -> 0 | AX8: =AF8-N8 -> 0 | AY8: =AG8-O8 -> 0 | AZ8: =AH8-P8 -> 0 | BA8: =AI8-Q8 -> 0 | ... BI8: =AQ8-Y8 -> 0 | BM8: Fengyi wraping cost down 0.02p | BN8: Wrap sticker + SS tube vertical integration | BO8: Wrap sticker + SS tube vertical integration | BQ8: Inflation | BR8: Stretch | BS8: 1. Stretch -0.0038; 2. Thimble cost down: -0.0004 | BT8: 1. Stretch: -0.0195p 2.TFK Protective shell cost down | BU8: Thimble inflation
A9: PEN 800 Default 2.0 | B9: Electronics | C9: =SUM(AS9:BA9) -> 0.013012979 | D9: =SUM(BB9:BI9) -> 0.0044576168 | E9: =D9+C9 -> 0.017470596 | F9: Gap:1.3P (COE): 1. Battery: Target: -2.06p, realized -2.37p, -0.31p exceed. (July'24: 0.05p gap less; Jan'25 0.36p better) 2.PCBA: gap 1.53p. (coplan should in Full only, wrong set in Default.) 3. Airflow controller: Gap:0.08p. Target -1.26p in Aug, Realized -1.18p (Jul/Aug/Nov/Jan). Reason: not 100% allocate to TMY but keep duel source with Toll for quality/supply chain risk. Action: find opp to close the gap. | G9: Highlight: battery -0.68p target cost down in Jul'25, actual nego price to monitor. (Jan'25 exceeds target) | J9: =SUMIFS('MoDi Initiatives'!H:H,'MoDi Initiatives'!$E:$E,'Gap Analysis update'!$B9,'MoDi Initiatives'!$A:$A,'Gap Analysis update'!$A9,'MoDi Initiatives'!$B:$B,'Gap Analysis update'!J$2)-SUMIFS('MoDi Initiatives'!H:H,'MoDi Initiatives'!$E:$E,'Gap Analysis update'!$B9,'MoDi Initiatives'!$A:$A,'Gap Analysis update'!$A9,'MoDi Initiatives'!$C:$C,'Gap Analysis update'!$B$7,'MoDi Initiatives'!$B:$B,'Gap Analysis update'!J$2) -> -0.008154177 | K9: =SUMIFS('MoDi Initiatives'!I:I,'MoDi Initiatives'!$E:$E,'Gap Analysis update'!$B9,'MoDi Initiatives'!$A:$A,'Gap Analysis update'!$A9,'MoDi Initiatives'!$B:$B,'Gap Analysis update'!K$2)-SUMIFS('MoDi Initiatives'!I:I,'MoDi Initiatives'!$E:$E,'Gap Analysis update'!$B9,'MoDi Initiatives'!$A:$A,'Gap Analysis update'!$A9,'MoDi Initiatives'!$C:$C,'Gap Analysis update'!$B$7,'MoDi Initiatives'!$B:$B,'Gap Analysis update'!K$2) -> -0.012611794 | L9: =SUMIFS('MoDi Initiatives'!J:J,'MoDi Initiatives'!$E:$E,'Gap Analysis update'!$B9,'MoDi Initiatives'!$A:$A,'Gap Analysis update'!$A9,'MoDi Initiatives'!$B:$B,'Gap Analysis update'!L$2)-SUMIFS('MoDi Initiatives'!J:J,'MoDi Initiatives'!$E:$E,'Gap Analysis update'!$B9,'MoDi Initiatives'!$A:$A,'Gap Analysis update'!$A9,'MoDi Initiatives'!$C:$C,'Gap Analysis update'!$B$7,'MoDi Initiatives'!$B:$B,'Gap Analysis update'!L$2) -> 0 | M9: =SUMIFS('MoDi Initiatives'!K:K,'MoDi Initiatives'!$E:$E,'Gap Analysis update'!$B9,'MoDi Initiatives'!$A:$A,'Gap Analysis update'!$A9,'MoDi Initiatives'!$B:$B,'Gap Analysis update'!M$2)-SUMIFS('MoDi Initiatives'!K:K,'MoDi Initiatives'!$E:$E,'Gap Analysis update'!$B9,'MoDi Initiatives'!$A:$A,'Gap Analysis update'!$A9,'MoDi Initiatives'!$C:$C,'Gap Analysis update'!$B$7,'MoDi Initiatives'!$B:$B,'Gap Analysis update'!M$2) -> 0 | N9: =SUMIFS('MoDi Initiatives'!L:L,'MoDi Initiatives'!$E:$E,'Gap Analysis update'!$B9,'MoDi Initiatives'!$A:$A,'Gap Analysis update'!$A9,'MoDi Initiatives'!$B:$B,'Gap Analysis update'!N$2)-SUMIFS('MoDi Initiatives'!L:L,'MoDi Initiatives'!$E:$E,'Gap Analysis update'!$B9,'MoDi Initiatives'!$A:$A,'Gap Analysis update'!$A9,'MoDi Initiatives'!$C:$C,'Gap Analysis update'!$B$7,'MoDi Initiatives'!$B:$B,'Gap Analysis update'!N$2) -> 0 | O9: =SUMIFS('MoDi Initiatives'!M:M,'MoDi Initiatives'!$E:$E,'Gap Analysis update'!$B9,'MoDi Initiatives'!$A:$A,'Gap Analysis update'!$A9,'MoDi Initiatives'!$B:$B,'Gap Analysis update'!O$2)-SUMIFS('MoDi Initiatives'!M:M,'MoDi Initiatives'!$E:$E,'Gap Analysis update'!$B9,'MoDi Initiatives'!$A:$A,'Gap Analysis update'!$A9,'MoDi Initiatives'!$C:$C,'Gap Analysis update'!$B$7,'MoDi Initiatives'!$B:$B,'Gap Analysis update'!O$2) -> 0 | P9: =SUMIFS('MoDi Initiatives'!N:N,'MoDi Initiatives'!$E:$E,'Gap Analysis update'!$B9,'MoDi Initiatives'!$A:$A,'Gap Analysis update'!$A9,'MoDi Initiatives'!$B:$B,'Gap Analysis update'!P$2)-SUMIFS('MoDi Initiatives'!N:N,'MoDi Initiatives'!$E:$E,'Gap Analysis update'!$B9,'MoDi Initiatives'!$A:$A,'Gap Analysis update'!$A9,'MoDi Initiatives'!$C:$C,'Gap Analysis update'!$B$7,'MoDi Initiatives'!$B:$B,'Gap Analysis update'!P$2) -> -0.027777476 | Q9: =SUMIFS('MoDi Initiatives'!O:O,'MoDi Initiatives'!$E:$E,'Gap Analysis update'!$B9,'MoDi Initiatives'!$A:$A,'Gap Analysis update'!$A9,'MoDi Initiatives'!$B:$B,'Gap Analysis update'!Q$2)-SUMIFS('MoDi Initiatives'!O:O,'MoDi Initiatives'!$E:$E,'Gap Analysis update'!$B9,'MoDi Initiatives'!$A:$A,'Gap Analysis update'!$A9,'MoDi Initiatives'!$C:$C,'Gap Analysis update'!$B$7,'MoDi Initiatives'!$B:$B,'Gap Analysis update'!Q$2) -> 0 | R9: =SUMIFS('MoDi Initiatives'!P:P,'MoDi Initiatives'!$E:$E,'Gap Analysis update'!$B9,'MoDi Initiatives'!$A:$A,'Gap Analysis update'!$A9,'MoDi Initiatives'!$B:$B,'Gap Analysis update'!R$2)-SUMIFS('MoDi Initiatives'!P:P,'MoDi Initiatives'!$E:$E,'Gap Analysis update'!$B9,'MoDi Initiatives'!$A:$A,'Gap Analysis update'!$A9,'MoDi Initiatives'!$C:$C,'Gap Analysis update'!$B$7,'MoDi Initiatives'!$B:$B,'Gap Analysis update'!R$2) -> 0 | S9: =SUMIFS('MoDi Initiatives'!Q:Q,'MoDi Initiatives'!$E:$E,'Gap Analysis update'!$B9,'MoDi Initiatives'!$A:$A,'Gap Analysis update'!$A9,'MoDi Initiatives'!$B:$B,'Gap Analysis update'!S$2)-SUMIFS('MoDi Initiatives'!Q:Q,'MoDi Initiatives'!$E:$E,'Gap Analysis update'!$B9,'MoDi Initiatives'!$A:$A,'Gap Analysis update'!$A9,'MoDi Initiatives'!$C:$C,'Gap Analysis update'!$B$7,'MoDi Initiatives'!$B:$B,'Gap Analysis update'!S$2) -> 0 | T9: =SUMIFS('MoDi Initiatives'!R:R,'MoDi Initiatives'!$E:$E,'Gap Analysis update'!$B9,'MoDi Initiatives'!$A:$A,'Gap Analysis update'!$A9,'MoDi Initiatives'!$B:$B,'Gap Analysis update'!T$2)-SUMIFS('MoDi Initiatives'!R:R,'MoDi Initiatives'!$E:$E,'Gap Analysis update'!$B9,'MoDi Initiatives'!$A:$A,'Gap Analysis update'!$A9,'MoDi Initiatives'!$C:$C,'Gap Analysis update'!$B$7,'MoDi Initiatives'!$B:$B,'Gap Analysis update'!T$2) -> 0 | U9: =SUMIFS('MoDi Initiatives'!S:S,'MoDi Initiatives'!$E:$E,'Gap Analysis update'!$B9,'MoDi Initiatives'!$A:$A,'Gap Analysis update'!$A9,'MoDi Initiatives'!$B:$B,'Gap Analysis update'!U$2)-SUMIFS('MoDi Initiatives'!S:S,'MoDi Initiatives'!$E:$E,'Gap Analysis update'!$B9,'MoDi Initiatives'!$A:$A,'Gap Analysis update'!$A9,'MoDi Initiatives'!$C:$C,'Gap Analysis update'!$B$7,'MoDi Initiatives'!$B:$B,'Gap Analysis update'!U$2) -> 0 | V9: =SUMIFS('MoDi Initiatives'!T:T,'MoDi Initiatives'!$E:$E,'Gap Analysis update'!$B9,'MoDi Initiatives'!$A:$A,'Gap Analysis update'!$A9,'MoDi Initiatives'!$B:$B,'Gap Analysis update'!V$2)-SUMIFS('MoDi Initiatives'!T:T,'MoDi Initiatives'!$E:$E,'Gap Analysis update'!$B9,'MoDi Initiatives'!$A:$A,'Gap Analysis update'!$A9,'MoDi Initiatives'!$C:$C,'Gap Analysis update'!$B$7,'MoDi Initiatives'!$B:$B,'Gap Analysis update'!V$2) -> -0.0068495087 | W9: =SUMIFS('MoDi Initiatives'!U:U,'MoDi Initiatives'!$E:$E,'Gap Analysis update'!$B9,'MoDi Initiatives'!$A:$A,'Gap Analysis update'!$A9,'MoDi Initiatives'!$B:$B,'Gap Analysis update'!W$2)-SUMIFS('MoDi Initiatives'!U:U,'MoDi Initiatives'!$E:$E,'Gap Analysis update'!$B9,'MoDi Initiatives'!$A:$A,'Gap Analysis update'!$A9,'MoDi Initiatives'!$C:$C,'Gap Analysis update'!$B$7,'MoDi Initiatives'!$B:$B,'Gap Analysis update'!W$2) -> 0 | X9: =SUMIFS('MoDi Initiatives'!V:V,'MoDi Initiatives'!$E:$E,'Gap Analysis update'!$B9,'MoDi Initiatives'!$A:$A,'Gap Analysis update'!$A9,'MoDi Initiatives'!$B:$B,'Gap Analysis update'!X$2)-SUMIFS('MoDi Initiatives'!V:V,'MoDi Initiatives'!$E:$E,'Gap Analysis update'!$B9,'MoDi Initiatives'!$A:$A,'Gap Analysis update'!$A9,'MoDi Initiatives'!$C:$C,'Gap Analysis update'!$B$7,'MoDi Initiatives'!$B:$B,'Gap Analysis update'!X$2) -> 0 | Y9: =SUMIFS('MoDi Initiatives'!W:W,'MoDi Initiatives'!$E:$E,'Gap Analysis update'!$B9,'MoDi Initiatives'!$A:$A,'Gap Analysis update'!$A9,'MoDi Initiatives'!$B:$B,'Gap Analysis update'!Y$2)-SUMIFS('MoDi Initiatives'!W:W,'MoDi Initiatives'!$E:$E,'Gap Analysis update'!$B9,'MoDi Initiatives'!$A:$A,'Gap Analysis update'!$A9,'MoDi Initiatives'!$C:$C,'Gap Analysis update'!$B$7,'MoDi Initiatives'!$B:$B,'Gap Analysis update'!Y$2) -> 0 | AB9: =SUMIFS('MoDi Initiatives'!H:H,'MoDi Initiatives'!$E:$E,'Gap Analysis update'!$B9,'MoDi Initiatives'!$A:$A,'Gap Analysis update'!$A9,'MoDi Initiatives'!$B:$B,'Gap Analysis update'!AB$2)-SUMIFS('MoDi Initiatives'!H:H,'MoDi Initiatives'!$E:$E,'Gap Analysis update'!$B9,'MoDi Initiatives'!$A:$A,'Gap Analysis update'!$A9,'MoDi Initiatives'!$B:$B,'Gap Analysis update'!AB$2,'MoDi Initiatives'!$C:$C,'Gap Analysis update'!$B$7) -> -0.015003686 | AC9: =SUMIFS('MoDi Initiatives'!I:I,'MoDi Initiatives'!$E:$E,'Gap Analysis update'!$B9,'MoDi Initiatives'!$A:$A,'Gap Analysis update'!$A9,'MoDi Initiatives'!$B:$B,'Gap Analysis update'!AC$2)-SUMIFS('MoDi Initiatives'!I:I,'MoDi Initiatives'!$E:$E,'Gap Analysis update'!$B9,'MoDi Initiatives'!$A:$A,'Gap Analysis update'!$A9,'MoDi Initiatives'!$B:$B,'Gap Analysis update'!AC$2,'MoDi Initiatives'!$C:$C,'Gap Analysis update'!$B$7) -> -0.0010872236 | AD9: =SUMIFS('MoDi Initiatives'!J:J,'MoDi Initiatives'!$E:$E,'Gap Analysis update'!$B9,'MoDi Initiatives'!$A:$A,'Gap Analysis update'!$A9,'MoDi Initiatives'!$B:$B,'Gap Analysis update'!AD$2)-SUMIFS('MoDi Initiatives'!J:J,'MoDi Initiatives'!$E:$E,'Gap Analysis update'!$B9,'MoDi Initiatives'!$A:$A,'Gap Analysis update'!$A9,'MoDi Initiatives'!$B:$B,'Gap Analysis update'!AD$2,'MoDi Initiatives'!$C:$C,'Gap Analysis update'!$B$7) -> 0 | AE9: =SUMIFS('MoDi Initiatives'!K:K,'MoDi Initiatives'!$E:$E,'Gap Analysis update'!$B9,'MoDi Initiatives'!$A:$A,'Gap Analysis update'!$A9,'MoDi Initiatives'!$B:$B,'Gap Analysis update'!AE$2)-SUMIFS('MoDi Initiatives'!K:K,'MoDi Initiatives'!$E:$E,'Gap Analysis update'!$B9,'MoDi Initiatives'!$A:$A,'Gap Analysis update'!$A9,'MoDi Initiatives'!$B:$B,'Gap Analysis update'!AE$2,'MoDi Initiatives'!$C:$C,'Gap Analysis update'!$B$7) -> 0 | AF9: =SUMIFS('MoDi Initiatives'!L:L,'MoDi Initiatives'!$E:$E,'Gap Analysis update'!$B9,'MoDi Initiatives'!$A:$A,'Gap Analysis update'!$A9,'MoDi Initiatives'!$B:$B,'Gap Analysis update'!AF$2)-SUMIFS('MoDi Initiatives'!L:L,'MoDi Initiatives'!$E:$E,'Gap Analysis update'!$B9,'MoDi Initiatives'!$A:$A,'Gap Analysis update'!$A9,'MoDi Initiatives'!$B:$B,'Gap Analysis update'!AF$2,'MoDi Initiatives'!$C:$C,'Gap Analysis update'!$B$7) -> -0.0029137592 | AG9: =SUMIFS('MoDi Initiatives'!M:M,'MoDi Initiatives'!$E:$E,'Gap Analysis update'!$B9,'MoDi Initiatives'!$A:$A,'Gap Analysis update'!$A9,'MoDi Initiatives'!$B:$B,'Gap Analysis update'!AG$2)-SUMIFS('MoDi Initiatives'!M:M,'MoDi Initiatives'!$E:$E,'Gap Analysis update'!$B9,'MoDi Initiatives'!$A:$A,'Gap Analysis update'!$A9,'MoDi Initiatives'!$B:$B,'Gap Analysis update'!AG$2,'MoDi Initiatives'!$C:$C,'Gap Analysis update'!$B$7) -> 0 | AH9: =SUMIFS('MoDi Initiatives'!N:N,'MoDi Initiatives'!$E:$E,'Gap Analysis update'!$B9,'MoDi Initiatives'!$A:$A,'Gap Analysis update'!$A9,'MoDi Initiatives'!$B:$B,'Gap Analysis update'!AH$2)-SUMIFS('MoDi Initiatives'!N:N,'MoDi Initiatives'!$E:$E,'Gap Analysis update'!$B9,'MoDi Initiatives'!$A:$A,'Gap Analysis update'!$A9,'MoDi Initiatives'!$B:$B,'Gap Analysis update'!AH$2,'MoDi Initiatives'!$C:$C,'Gap Analysis update'!$B$7) -> -0.00043488944 | AI9: =SUMIFS('MoDi Initiatives'!O:O,'MoDi Initiatives'!$E:$E,'Gap Analysis update'!$B9,'MoDi Initiatives'!$A:$A,'Gap Analysis update'!$A9,'MoDi Initiatives'!$B:$B,'Gap Analysis update'!AI$2)-SUMIFS('MoDi Initiatives'!O:O,'MoDi Initiatives'!$E:$E,'Gap Analysis update'!$B9,'MoDi Initiatives'!$A:$A,'Gap Analysis update'!$A9,'MoDi Initiatives'!$B:$B,'Gap Analysis update'!AI$2,'MoDi Initiatives'!$C:$C,'Gap Analysis update'!$B$7) -> -0.016090909 | AJ9: =SUMIFS('MoDi Initiatives'!P:P,'MoDi Initiatives'!$E:$E,'Gap Analysis update'!$B9,'MoDi Initiatives'!$A:$A,'Gap Analysis update'!$A9,'MoDi Initiatives'!$B:$B,'Gap Analysis update'!AJ$2)-SUMIFS('MoDi Initiatives'!P:P,'MoDi Initiatives'!$E:$E,'Gap Analysis update'!$B9,'MoDi Initiatives'!$A:$A,'Gap Analysis update'!$A9,'MoDi Initiatives'!$B:$B,'Gap Analysis update'!AJ$2,'MoDi Initiatives'!$C:$C,'Gap Analysis update'!$B$7) -> 0 | AK9: =SUMIFS('MoDi Initiatives'!Q:Q,'MoDi Initiatives'!$E:$E,'Gap Analysis update'!$B9,'MoDi Initiatives'!$A:$A,'Gap Analysis update'!$A9,'MoDi Initiatives'!$B:$B,'Gap Analysis update'!AK$2)-SUMIFS('MoDi Initiatives'!Q:Q,'MoDi Initiatives'!$E:$E,'Gap Analysis update'!$B9,'MoDi Initiatives'!$A:$A,'Gap Analysis update'!$A9,'MoDi Initiatives'!$B:$B,'Gap Analysis update'!AK$2,'MoDi Initiatives'!$C:$C,'Gap Analysis update'!$B$7) -> 0 | AL9: =SUMIFS('MoDi Initiatives'!R:R,'MoDi Initiatives'!$E:$E,'Gap Analysis update'!$B9,'MoDi Initiatives'!$A:$A,'Gap Analysis update'!$A9,'MoDi Initiatives'!$B:$B,'Gap Analysis update'!AL$2)-SUMIFS('MoDi Initiatives'!R:R,'MoDi Initiatives'!$E:$E,'Gap Analysis update'!$B9,'MoDi Initiatives'!$A:$A,'Gap Analysis update'!$A9,'MoDi Initiatives'!$B:$B,'Gap Analysis update'!AL$2,'MoDi Initiatives'!$C:$C,'Gap Analysis update'!$B$7) -> 0 | AM9: =SUMIFS('MoDi Initiatives'!S:S,'MoDi Initiatives'!$E:$E,'Gap Analysis update'!$B9,'MoDi Initiatives'!$A:$A,'Gap Analysis update'!$A9,'MoDi Initiatives'!$B:$B,'Gap Analysis update'!AM$2)-SUMIFS('MoDi Initiatives'!S:S,'MoDi Initiatives'!$E:$E,'Gap Analysis update'!$B9,'MoDi Initiatives'!$A:$A,'Gap Analysis update'!$A9,'MoDi Initiatives'!$B:$B,'Gap Analysis update'!AM$2,'MoDi Initiatives'!$C:$C,'Gap Analysis update'!$B$7) -> 0 | AN9: =SUMIFS('MoDi Initiatives'!T:T,'MoDi Initiatives'!$E:$E,'Gap Analysis update'!$B9,'MoDi Initiatives'!$A:$A,'Gap Analysis update'!$A9,'MoDi Initiatives'!$B:$B,'Gap Analysis update'!AN$2)-SUMIFS('MoDi Initiatives'!T:T,'MoDi Initiatives'!$E:$E,'Gap Analysis update'!$B9,'MoDi Initiatives'!$A:$A,'Gap Analysis update'!$A9,'MoDi Initiatives'!$B:$B,'Gap Analysis update'!AN$2,'MoDi Initiatives'!$C:$C,'Gap Analysis update'!$B$7) -> -0.0023918919 | AO9: =SUMIFS('MoDi Initiatives'!U:U,'MoDi Initiatives'!$E:$E,'Gap Analysis update'!$B9,'MoDi Initiatives'!$A:$A,'Gap Analysis update'!$A9,'MoDi Initiatives'!$B:$B,'Gap Analysis update'!AO$2)-SUMIFS('MoDi Initiatives'!U:U,'MoDi Initiatives'!$E:$E,'Gap Analysis update'!$B9,'MoDi Initiatives'!$A:$A,'Gap Analysis update'!$A9,'MoDi Initiatives'!$B:$B,'Gap Analysis update'!AO$2,'MoDi Initiatives'!$C:$C,'Gap Analysis update'!$B$7) -> 0 | AP9: =SUMIFS('MoDi Initiatives'!V:V,'MoDi Initiatives'!$E:$E,'Gap Analysis update'!$B9,'MoDi Initiatives'!$A:$A,'Gap Analysis update'!$A9,'MoDi Initiatives'!$B:$B,'Gap Analysis update'!AP$2)-SUMIFS('MoDi Initiatives'!V:V,'MoDi Initiatives'!$E:$E,'Gap Analysis update'!$B9,'MoDi Initiatives'!$A:$A,'Gap Analysis update'!$A9,'MoDi Initiatives'!$B:$B,'Gap Analysis update'!AP$2,'MoDi Initiatives'!$C:$C,'Gap Analysis update'!$B$7) -> 0 | AQ9: =SUMIFS('MoDi Initiatives'!W:W,'MoDi Initiatives'!$E:$E,'Gap Analysis update'!$B9,'MoDi Initiatives'!$A:$A,'Gap Analysis update'!$A9,'MoDi Initiatives'!$B:$B,'Gap Analysis update'!AQ$2)-SUMIFS('MoDi Initiatives'!W:W,'MoDi Initiatives'!$E:$E,'Gap Analysis update'!$B9,'MoDi Initiatives'!$A:$A,'Gap Analysis update'!$A9,'MoDi Initiatives'!$B:$B,'Gap Analysis update'!AQ$2,'MoDi Initiatives'!$C:$C,'Gap Analysis update'!$B$7) -> 0 | AT9: =AB9-J9 -> -0.0068495087 | AU9: =AC9-K9 -> 0.01152457 | AV9: =AD9-L9 -> 0 | AW9: =AE9-M9 -> 0 | AX9: =AF9-N9 -> -0.0029137592 | AY9: =AG9-O9 -> 0 | AZ9: =AH9-P9 -> 0.027342586 | BA9: =AI9-Q9 -> -0.016090909 | ... BI9: =AQ9-Y9 -> 0 | BM9: 1. Battery: coplan -0.82p vs actual -0.76p; 2. Airflow controller: actual -0.74p | BN9: 1. Airflow controller: coplan -1.26p vs actual -0.11p | BQ9: 1. Coplan: Inflation 0.74p; 2. Airflow controller: -0.29p; | BS9: 1. Coplan PCBA:-1.53P(No PCBA in Default); 2. Coplan Battery -1.25p;(Delay to Feb due to inventory) | BT9: Battery actual -1.61p.(0.36p better) | BU9: Inflation delay (Could be removed) | BY9: Battery Q3'25 Cost down(Corrected in SOP2 to 0.36p for actual)
A10: PEN 800 Default 2.0 | B10: Packaging | C10: =SUM(AS10:BA10) -> 0.0020822611 | D10: =SUM(BB10:BI10) -> 0.0021077423 | E10: =D10+C10 -> 0.0041900034 | F10: Gap: 0.21p; Unplanned Design change from EM: Flow wrap change from blank to pre-print in Dec. | G10: Gap: 0.21p; Unplan Design change from EM: Flow wrap change Non-ESG material to ESG in Apr'25.(Under validation) | J10: =SUMIFS('MoDi Initiatives'!H:H,'MoDi Initiatives'!$E:$E,'Gap Analysis update'!$B10,'MoDi Initiatives'!$A:$A,'Gap Analysis update'!$A10,'MoDi Initiatives'!$B:$B,'Gap Analysis update'!J$2)-SUMIFS('MoDi Initiatives'!H:H,'MoDi Initiatives'!$E:$E,'Gap Analysis update'!$B10,'MoDi Initiatives'!$A:$A,'Gap Analysis update'!$A10,'MoDi Initiatives'!$C:$C,'Gap Analysis update'!$B$7,'MoDi Initiatives'!$B:$B,'Gap Analysis update'!J$2) -> 0 | K10: =SUMIFS('MoDi Initiatives'!I:I,'MoDi Initiatives'!$E:$E,'Gap Analysis update'!$B10,'MoDi Initiatives'!$A:$A,'Gap Analysis update'!$A10,'MoDi Initiatives'!$B:$B,'Gap Analysis update'!K$2)-SUMIFS('MoDi Initiatives'!I:I,'MoDi Initiatives'!$E:$E,'Gap Analysis update'!$B10,'MoDi Initiatives'!$A:$A,'Gap Analysis update'!$A10,'MoDi Initiatives'!$C:$C,'Gap Analysis update'!$B$7,'MoDi Initiatives'!$B:$B,'Gap Analysis update'!K$2) -> 0 | L10: =SUMIFS('MoDi Initiatives'!J:J,'MoDi Initiatives'!$E:$E,'Gap Analysis update'!$B10,'MoDi Initiatives'!$A:$A,'Gap Analysis update'!$A10,'MoDi Initiatives'!$B:$B,'Gap Analysis update'!L$2)-SUMIFS('MoDi Initiatives'!J:J,'MoDi Initiatives'!$E:$E,'Gap Analysis update'!$B10,'MoDi Initiatives'!$A:$A,'Gap Analysis update'!$A10,'MoDi Initiatives'!$C:$C,'Gap Analysis update'!$B$7,'MoDi Initiatives'!$B:$B,'Gap Analysis update'!L$2) -> 0 | M10: =SUMIFS('MoDi Initiatives'!K:K,'MoDi Initiatives'!$E:$E,'Gap Analysis update'!$B10,'MoDi Initiatives'!$A:$A,'Gap Analysis update'!$A10,'MoDi Initiatives'!$B:$B,'Gap Analysis update'!M$2)-SUMIFS('MoDi Initiatives'!K:K,'MoDi Initiatives'!$E:$E,'Gap Analysis update'!$B10,'MoDi Initiatives'!$A:$A,'Gap Analysis update'!$A10,'MoDi Initiatives'!$C:$C,'Gap Analysis update'!$B$7,'MoDi Initiatives'!$B:$B,'Gap Analysis update'!M$2) -> 0 | N10: =SUMIFS('MoDi Initiatives'!L:L,'MoDi Initiatives'!$E:$E,'Gap Analysis update'!$B10,'MoDi Initiatives'!$A:$A,'Gap Analysis update'!$A10,'MoDi Initiatives'!$B:$B,'Gap Analysis update'!N$2)-SUMIFS('MoDi Initiatives'!L:L,'MoDi Initiatives'!$E:$E,'Gap Analysis update'!$B10,'MoDi Initiatives'!$A:$A,'Gap Analysis update'!$A10,'MoDi Initiatives'!$C:$C,'Gap Analysis update'!$B$7,'MoDi Initiatives'!$B:$B,'Gap Analysis update'!N$2) -> 0 | O10: =SUMIFS('MoDi Initiatives'!M:M,'MoDi Initiatives'!$E:$E,'Gap Analysis update'!$B10,'MoDi Initiatives'!$A:$A,'Gap Analysis update'!$A10,'MoDi Initiatives'!$B:$B,'Gap Analysis update'!O$2)-SUMIFS('MoDi Initiatives'!M:M,'MoDi Initiatives'!$E:$E,'Gap Analysis update'!$B10,'MoDi Initiatives'!$A:$A,'Gap Analysis update'!$A10,'MoDi Initiatives'!$C:$C,'Gap Analysis update'!$B$7,'MoDi Initiatives'!$B:$B,'Gap Analysis update'!O$2) -> 0 | P10: =SUMIFS('MoDi Initiatives'!N:N,'MoDi Initiatives'!$E:$E,'Gap Analysis update'!$B10,'MoDi Initiatives'!$A:$A,'Gap Analysis update'!$A10,'MoDi Initiatives'!$B:$B,'Gap Analysis update'!P$2)-SUMIFS('MoDi Initiatives'!N:N,'MoDi Initiatives'!$E:$E,'Gap Analysis update'!$B10,'MoDi Initiatives'!$A:$A,'Gap Analysis update'!$A10,'MoDi Initiatives'!$C:$C,'Gap Analysis update'!$B$7,'MoDi Initiatives'!$B:$B,'Gap Analysis update'!P$2) -> 0 | Q10: =SUMIFS('MoDi Initiatives'!O:O,'MoDi Initiatives'!$E:$E,'Gap Analysis update'!$B10,'MoDi Initiatives'!$A:$A,'Gap Analysis update'!$A10,'MoDi Initiatives'!$B:$B,'Gap Analysis update'!Q$2)-SUMIFS('MoDi Initiatives'!O:O,'MoDi Initiatives'!$E:$E,'Gap Analysis update'!$B10,'MoDi Initiatives'!$A:$A,'Gap Analysis update'!$A10,'MoDi Initiatives'!$C:$C,'Gap Analysis update'!$B$7,'MoDi Initiatives'!$B:$B,'Gap Analysis update'!Q$2) -> 0 | R10: =SUMIFS('MoDi Initiatives'!P:P,'MoDi Initiatives'!$E:$E,'Gap Analysis update'!$B10,'MoDi Initiatives'!$A:$A,'Gap Analysis update'!$A10,'MoDi Initiatives'!$B:$B,'Gap Analysis update'!R$2)-SUMIFS('MoDi Initiatives'!P:P,'MoDi Initiatives'!$E:$E,'Gap Analysis update'!$B10,'MoDi Initiatives'!$A:$A,'Gap Analysis update'!$A10,'MoDi Initiatives'!$C:$C,'Gap Analysis update'!$B$7,'MoDi Initiatives'!$B:$B,'Gap Analysis update'!R$2) -> 0 | S10: =SUMIFS('MoDi Initiatives'!Q:Q,'MoDi Initiatives'!$E:$E,'Gap Analysis update'!$B10,'MoDi Initiatives'!$A:$A,'Gap Analysis update'!$A10,'MoDi Initiatives'!$B:$B,'Gap Analysis update'!S$2)-SUMIFS('MoDi Initiatives'!Q:Q,'MoDi Initiatives'!$E:$E,'Gap Analysis update'!$B10,'MoDi Initiatives'!$A:$A,'Gap Analysis update'!$A10,'MoDi Initiatives'!$C:$C,'Gap Analysis update'!$B$7,'MoDi Initiatives'!$B:$B,'Gap Analysis update'!S$2) -> 0 | T10: =SUMIFS('MoDi Initiatives'!R:R,'MoDi Initiatives'!$E:$E,'Gap Analysis update'!$B10,'MoDi Initiatives'!$A:$A,'Gap Analysis update'!$A10,'MoDi Initiatives'!$B:$B,'Gap Analysis update'!T$2)-SUMIFS('MoDi Initiatives'!R:R,'MoDi Initiatives'!$E:$E,'Gap Analysis update'!$B10,'MoDi Initiatives'!$A:$A,'Gap Analysis update'!$A10,'MoDi Initiatives'!$C:$C,'Gap Analysis update'!$B$7,'MoDi Initiatives'!$B:$B,'Gap Analysis update'!T$2) -> 0 | U10: =SUMIFS('MoDi Initiatives'!S:S,'MoDi Initiatives'!$E:$E,'Gap Analysis update'!$B10,'MoDi Initiatives'!$A:$A,'Gap Analysis update'!$A10,'MoDi Initiatives'!$B:$B,'Gap Analysis update'!U$2)-SUMIFS('MoDi Initiatives'!S:S,'MoDi Initiatives'!$E:$E,'Gap Analysis update'!$B10,'MoDi Initiatives'!$A:$A,'Gap Analysis update'!$A10,'MoDi Initiatives'!$C:$C,'Gap Analysis update'!$B$7,'MoDi Initiatives'!$B:$B,'Gap Analysis update'!U$2) -> 0 | V10: =SUMIFS('MoDi Initiatives'!T:T,'MoDi Initiatives'!$E:$E,'Gap Analysis update'!$B10,'MoDi Initiatives'!$A:$A,'Gap Analysis update'!$A10,'MoDi Initiatives'!$B:$B,'Gap Analysis update'!V$2)-SUMIFS('MoDi Initiatives'!T:T,'MoDi Initiatives'!$E:$E,'Gap Analysis update'!$B10,'MoDi Initiatives'!$A:$A,'Gap Analysis update'!$A10,'MoDi Initiatives'!$C:$C,'Gap Analysis update'!$B$7,'MoDi Initiatives'!$B:$B,'Gap Analysis update'!V$2) -> 0 | W10: =SUMIFS('MoDi Initiatives'!U:U,'MoDi Initiatives'!$E:$E,'Gap Analysis update'!$B10,'MoDi Initiatives'!$A:$A,'Gap Analysis update'!$A10,'MoDi Initiatives'!$B:$B,'Gap Analysis update'!W$2)-SUMIFS('MoDi Initiatives'!U:U,'MoDi Initiatives'!$E:$E,'Gap Analysis update'!$B10,'MoDi Initiatives'!$A:$A,'Gap Analysis update'!$A10,'MoDi Initiatives'!$C:$C,'Gap Analysis update'!$B$7,'MoDi Initiatives'!$B:$B,'Gap Analysis update'!W$2) -> 0 | X10: =SUMIFS('MoDi Initiatives'!V:V,'MoDi Initiatives'!$E:$E,'Gap Analysis update'!$B10,'MoDi Initiatives'!$A:$A,'Gap Analysis update'!$A10,'MoDi Initiatives'!$B:$B,'Gap Analysis update'!X$2)-SUMIFS('MoDi Initiatives'!V:V,'MoDi Initiatives'!$E:$E,'Gap Analysis update'!$B10,'MoDi Initiatives'!$A:$A,'Gap Analysis update'!$A10,'MoDi Initiatives'!$C:$C,'Gap Analysis update'!$B$7,'MoDi Initiatives'!$B:$B,'Gap Analysis update'!X$2) -> 0 | Y10: =SUMIFS('MoDi Initiatives'!W:W,'MoDi Initiatives'!$E:$E,'Gap Analysis update'!$B10,'MoDi Initiatives'!$A:$A,'Gap Analysis update'!$A10,'MoDi Initiatives'!$B:$B,'Gap Analysis update'!Y$2)-SUMIFS('MoDi Initiatives'!W:W,'MoDi Initiatives'!$E:$E,'Gap Analysis update'!$B10,'MoDi Initiatives'!$A:$A,'Gap Analysis update'!$A10,'MoDi Initiatives'!$C:$C,'Gap Analysis update'!$B$7,'MoDi Initiatives'!$B:$B,'Gap Analysis update'!Y$2) -> 0 | AB10: =SUMIFS('MoDi Initiatives'!H:H,'MoDi Initiatives'!$E:$E,'Gap Analysis update'!$B10,'MoDi Initiatives'!$A:$A,'Gap Analysis update'!$A10,'MoDi Initiatives'!$B:$B,'Gap Analysis update'!AB$2)-SUMIFS('MoDi Initiatives'!H:H,'MoDi Initiatives'!$E:$E,'Gap Analysis update'!$B10,'MoDi Initiatives'!$A:$A,'Gap Analysis update'!$A10,'MoDi Initiatives'!$B:$B,'Gap Analysis update'!AB$2,'MoDi Initiatives'!$C:$C,'Gap Analysis update'!$B$7) -> 0 | AC10: =SUMIFS('MoDi Initiatives'!I:I,'MoDi Initiatives'!$E:$E,'Gap Analysis update'!$B10,'MoDi Initiatives'!$A:$A,'Gap Analysis update'!$A10,'MoDi Initiatives'!$B:$B,'Gap Analysis update'!AC$2)-SUMIFS('MoDi Initiatives'!I:I,'MoDi Initiatives'!$E:$E,'Gap Analysis update'!$B10,'MoDi Initiatives'!$A:$A,'Gap Analysis update'!$A10,'MoDi Initiatives'!$B:$B,'Gap Analysis update'!AC$2,'MoDi Initiatives'!$C:$C,'Gap Analysis update'!$B$7) -> 0 | AD10: =SUMIFS('MoDi Initiatives'!J:J,'MoDi Initiatives'!$E:$E,'Gap Analysis update'!$B10,'MoDi Initiatives'!$A:$A,'Gap Analysis update'!$A10,'MoDi Initiatives'!$B:$B,'Gap Analysis update'!AD$2)-SUMIFS('MoDi Initiatives'!J:J,'MoDi Initiatives'!$E:$E,'Gap Analysis update'!$B10,'MoDi Initiatives'!$A:$A,'Gap Analysis update'!$A10,'MoDi Initiatives'!$B:$B,'Gap Analysis update'!AD$2,'MoDi Initiatives'!$C:$C,'Gap Analysis update'!$B$7) -> 0 | AE10: =SUMIFS('MoDi Initiatives'!K:K,'MoDi Initiatives'!$E:$E,'Gap Analysis update'!$B10,'MoDi Initiatives'!$A:$A,'Gap Analysis update'!$A10,'MoDi Initiatives'!$B:$B,'Gap Analysis update'!AE$2)-SUMIFS('MoDi Initiatives'!K:K,'MoDi Initiatives'!$E:$E,'Gap Analysis update'!$B10,'MoDi Initiatives'!$A:$A,'Gap Analysis update'!$A10,'MoDi Initiatives'!$B:$B,'Gap Analysis update'!AE$2,'MoDi Initiatives'!$C:$C,'Gap Analysis update'!$B$7) -> 0 | AF10: =SUMIFS('MoDi Initiatives'!L:L,'MoDi Initiatives'!$E:$E,'Gap Analysis update'!$B10,'MoDi Initiatives'!$A:$A,'Gap Analysis update'!$A10,'MoDi Initiatives'!$B:$B,'Gap Analysis update'!AF$2)-SUMIFS('MoDi Initiatives'!L:L,'MoDi Initiatives'!$E:$E,'Gap Analysis update'!$B10,'MoDi Initiatives'!$A:$A,'Gap Analysis update'!$A10,'MoDi Initiatives'!$B:$B,'Gap Analysis update'!AF$2,'MoDi Initiatives'!$C:$C,'Gap Analysis update'!$B$7) -> 0 | AG10: =SUMIFS('MoDi Initiatives'!M:M,'MoDi Initiatives'!$E:$E,'Gap Analysis update'!$B10,'MoDi Initiatives'!$A:$A,'Gap Analysis update'!$A10,'MoDi Initiatives'!$B:$B,'Gap Analysis update'!AG$2)-SUMIFS('MoDi Initiatives'!M:M,'MoDi Initiatives'!$E:$E,'Gap Analysis update'!$B10,'MoDi Initiatives'!$A:$A,'Gap Analysis update'!$A10,'MoDi Initiatives'!$B:$B,'Gap Analysis update'!AG$2,'MoDi Initiatives'!$C:$C,'Gap Analysis update'!$B$7) -> 0.0020822611 | AH10: =SUMIFS('MoDi Initiatives'!N:N,'MoDi Initiatives'!$E:$E,'Gap Analysis update'!$B10,'MoDi Initiatives'!$A:$A,'Gap Analysis update'!$A10,'MoDi Initiatives'!$B:$B,'Gap Analysis update'!AH$2)-SUMIFS('MoDi Initiatives'!N:N,'MoDi Initiatives'!$E:$E,'Gap Analysis update'!$B10,'MoDi Initiatives'!$A:$A,'Gap Analysis update'!$A10,'MoDi Initiatives'!$B:$B,'Gap Analysis update'!AH$2,'MoDi Initiatives'!$C:$C,'Gap Analysis update'!$B$7) -> 0 | AI10: =SUMIFS('MoDi Initiatives'!O:O,'MoDi Initiatives'!$E:$E,'Gap Analysis update'!$B10,'MoDi Initiatives'!$A:$A,'Gap Analysis update'!$A10,'MoDi Initiatives'!$B:$B,'Gap Analysis update'!AI$2)-SUMIFS('MoDi Initiatives'!O:O,'MoDi Initiatives'!$E:$E,'Gap Analysis update'!$B10,'MoDi Initiatives'!$A:$A,'Gap Analysis update'!$A10,'MoDi Initiatives'!$B:$B,'Gap Analysis update'!AI$2,'MoDi Initiatives'!$C:$C,'Gap Analysis update'!$B$7) -> 0 | AJ10: =SUMIFS('MoDi Initiatives'!P:P,'MoDi Initiatives'!$E:$E,'Gap Analysis update'!$B10,'MoDi Initiatives'!$A:$A,'Gap Analysis update'!$A10,'MoDi Initiatives'!$B:$B,'Gap Analysis update'!AJ$2)-SUMIFS('MoDi Initiatives'!P:P,'MoDi Initiatives'!$E:$E,'Gap Analysis update'!$B10,'MoDi Initiatives'!$A:$A,'Gap Analysis update'!$A10,'MoDi Initiatives'!$B:$B,'Gap Analysis update'!AJ$2,'MoDi Initiatives'!$C:$C,'Gap Analysis update'!$B$7) -> 0 | AK10: =SUMIFS('MoDi Initiatives'!Q:Q,'MoDi Initiatives'!$E:$E,'Gap Analysis update'!$B10,'MoDi Initiatives'!$A:$A,'Gap Analysis update'!$A10,'MoDi Initiatives'!$B:$B,'Gap Analysis update'!AK$2)-SUMIFS('MoDi Initiatives'!Q:Q,'MoDi Initiatives'!$E:$E,'Gap Analysis update'!$B10,'MoDi Initiatives'!$A:$A,'Gap Analysis update'!$A10,'MoDi Initiatives'!$B:$B,'Gap Analysis update'!AK$2,'MoDi Initiatives'!$C:$C,'Gap Analysis update'!$B$7) -> 0.0021077423 | AL10: =SUMIFS('MoDi Initiatives'!R:R,'MoDi Initiatives'!$E:$E,'Gap Analysis update'!$B10,'MoDi Initiatives'!$A:$A,'Gap Analysis update'!$A10,'MoDi Initiatives'!$B:$B,'Gap Analysis update'!AL$2)-SUMIFS('MoDi Initiatives'!R:R,'MoDi Initiatives'!$E:$E,'Gap Analysis update'!$B10,'MoDi Initiatives'!$A:$A,'Gap Analysis update'!$A10,'MoDi Initiatives'!$B:$B,'Gap Analysis update'!AL$2,'MoDi Initiatives'!$C:$C,'Gap Analysis update'!$B$7) -> 0 | AM10: =SUMIFS('MoDi Initiatives'!S:S,'MoDi Initiatives'!$E:$E,'Gap Analysis update'!$B10,'MoDi Initiatives'!$A:$A,'Gap Analysis update'!$A10,'MoDi Initiatives'!$B:$B,'Gap Analysis update'!AM$2)-SUMIFS('MoDi Initiatives'!S:S,'MoDi Initiatives'!$E:$E,'Gap Analysis update'!$B10,'MoDi Initiatives'!$A:$A,'Gap Analysis update'!$A10,'MoDi Initiatives'!$B:$B,'Gap Analysis update'!AM$2,'MoDi Initiatives'!$C:$C,'Gap Analysis update'!$B$7) -> 0 | AN10: =SUMIFS('MoDi Initiatives'!T:T,'MoDi Initiatives'!$E:$E,'Gap Analysis update'!$B10,'MoDi Initiatives'!$A:$A,'Gap Analysis update'!$A10,'MoDi Initiatives'!$B:$B,'Gap Analysis update'!AN$2)-SUMIFS('MoDi Initiatives'!T:T,'MoDi Initiatives'!$E:$E,'Gap Analysis update'!$B10,'MoDi Initiatives'!$A:$A,'Gap Analysis update'!$A10,'MoDi Initiatives'!$B:$B,'Gap Analysis update'!AN$2,'MoDi Initiatives'!$C:$C,'Gap Analysis update'!$B$7) -> 0 | AO10: =SUMIFS('MoDi Initiatives'!U:U,'MoDi Initiatives'!$E:$E,'Gap Analysis update'!$B10,'MoDi Initiatives'!$A:$A,'Gap Analysis update'!$A10,'MoDi Initiatives'!$B:$B,'Gap Analysis update'!AO$2)-SUMIFS('MoDi Initiatives'!U:U,'MoDi Initiatives'!$E:$E,'Gap Analysis update'!$B10,'MoDi Initiatives'!$A:$A,'Gap Analysis update'!$A10,'MoDi Initiatives'!$B:$B,'Gap Analysis update'!AO$2,'MoDi Initiatives'!$C:$C,'Gap Analysis update'!$B$7) -> 0 | AP10: =SUMIFS('MoDi Initiatives'!V:V,'MoDi Initiatives'!$E:$E,'Gap Analysis update'!$B10,'MoDi Initiatives'!$A:$A,'Gap Analysis update'!$A10,'MoDi Initiatives'!$B:$B,'Gap Analysis update'!AP$2)-SUMIFS('MoDi Initiatives'!V:V,'MoDi Initiatives'!$E:$E,'Gap Analysis update'!$B10,'MoDi Initiatives'!$A:$A,'Gap Analysis update'!$A10,'MoDi Initiatives'!$B:$B,'Gap Analysis update'!AP$2,'MoDi Initiatives'!$C:$C,'Gap Analysis update'!$B$7) -> 0 | AQ10: =SUMIFS('MoDi Initiatives'!W:W,'MoDi Initiatives'!$E:$E,'Gap Analysis update'!$B10,'MoDi Initiatives'!$A:$A,'Gap Analysis update'!$A10,'MoDi Initiatives'!$B:$B,'Gap Analysis update'!AQ$2)-SUMIFS('MoDi Initiatives'!W:W,'MoDi Initiatives'!$E:$E,'Gap Analysis update'!$B10,'MoDi Initiatives'!$A:$A,'Gap Analysis update'!$A10,'MoDi Initiatives'!$B:$B,'Gap Analysis update'!AQ$2,'MoDi Initiatives'!$C:$C,'Gap Analysis update'!$B$7) -> 0 | AT10: =AB10-J10 -> 0 | AU10: =AC10-K10 -> 0 | AV10: =AD10-L10 -> 0 | AW10: =AE10-M10 -> 0 | AX10: =AF10-N10 -> 0 | AY10: =AG10-O10 -> 0.0020822611 | AZ10: =AH10-P10 -> 0 | BA10: =AI10-Q10 -> 0 | ... BI10: =AQ10-Y10 -> 0 | BQ10: Inflation | BR10: Design change from EM: Flow Wrap (NON-ESG) Change from blank to printing | BU10: Inflation delay | BV10: Design change from EM: Flow wrap change from Pre-print Non-ESG to ESG preprint
A11: PEN 800 Default 2.0 | B11: E-liquid | C11: =SUM(AS11:BA11) -> 0 | D11: =SUM(BB11:BI11) -> 0 | E11: =D11+C11 -> 0 | F11: Gap: 0.25p; 1.Extra stretch-finance: 0.29p gap; 2. Liquid cost down from FX: -0.04P. Action: Flavor Nego down finished, to push US for liquid down(Kil). | J11: =SUMIFS('MoDi Initiatives'!H:H,'MoDi Initiatives'!$E:$E,'Gap Analysis update'!$B11,'MoDi Initiatives'!$A:$A,'Gap Analysis update'!$A11,'MoDi Initiatives'!$B:$B,'Gap Analysis update'!J$2)-SUMIFS('MoDi Initiatives'!H:H,'MoDi Initiatives'!$E:$E,'Gap Analysis update'!$B11,'MoDi Initiatives'!$A:$A,'Gap Analysis update'!$A11,'MoDi Initiatives'!$C:$C,'Gap Analysis update'!$B$7,'MoDi Initiatives'!$B:$B,'Gap Analysis update'!J$2) -> 0 | K11: =SUMIFS('MoDi Initiatives'!I:I,'MoDi Initiatives'!$E:$E,'Gap Analysis update'!$B11,'MoDi Initiatives'!$A:$A,'Gap Analysis update'!$A11,'MoDi Initiatives'!$B:$B,'Gap Analysis update'!K$2)-SUMIFS('MoDi Initiatives'!I:I,'MoDi Initiatives'!$E:$E,'Gap Analysis update'!$B11,'MoDi Initiatives'!$A:$A,'Gap Analysis update'!$A11,'MoDi Initiatives'!$C:$C,'Gap Analysis update'!$B$7,'MoDi Initiatives'!$B:$B,'Gap Analysis update'!K$2) -> 0 | L11: =SUMIFS('MoDi Initiatives'!J:J,'MoDi Initiatives'!$E:$E,'Gap Analysis update'!$B11,'MoDi Initiatives'!$A:$A,'Gap Analysis update'!$A11,'MoDi Initiatives'!$B:$B,'Gap Analysis update'!L$2)-SUMIFS('MoDi Initiatives'!J:J,'MoDi Initiatives'!$E:$E,'Gap Analysis update'!$B11,'MoDi Initiatives'!$A:$A,'Gap Analysis update'!$A11,'MoDi Initiatives'!$C:$C,'Gap Analysis update'!$B$7,'MoDi Initiatives'!$B:$B,'Gap Analysis update'!L$2) -> 0 | M11: =SUMIFS('MoDi Initiatives'!K:K,'MoDi Initiatives'!$E:$E,'Gap Analysis update'!$B11,'MoDi Initiatives'!$A:$A,'Gap Analysis update'!$A11,'MoDi Initiatives'!$B:$B,'Gap Analysis update'!M$2)-SUMIFS('MoDi Initiatives'!K:K,'MoDi Initiatives'!$E:$E,'Gap Analysis update'!$B11,'MoDi Initiatives'!$A:$A,'Gap Analysis update'!$A11,'MoDi Initiatives'!$C:$C,'Gap Analysis update'!$B$7,'MoDi Initiatives'!$B:$B,'Gap Analysis update'!M$2) -> 0 | N11: =SUMIFS('MoDi Initiatives'!L:L,'MoDi Initiatives'!$E:$E,'Gap Analysis update'!$B11,'MoDi Initiatives'!$A:$A,'Gap Analysis update'!$A11,'MoDi Initiatives'!$B:$B,'Gap Analysis update'!N$2)-SUMIFS('MoDi Initiatives'!L:L,'MoDi Initiatives'!$E:$E,'Gap Analysis update'!$B11,'MoDi Initiatives'!$A:$A,'Gap Analysis update'!$A11,'MoDi Initiatives'!$C:$C,'Gap Analysis update'!$B$7,'MoDi Initiatives'!$B:$B,'Gap Analysis update'!N$2) -> 0 | O11: =SUMIFS('MoDi Initiatives'!M:M,'MoDi Initiatives'!$E:$E,'Gap Analysis update'!$B11,'MoDi Initiatives'!$A:$A,'Gap Analysis update'!$A11,'MoDi Initiatives'!$B:$B,'Gap Analysis update'!O$2)-SUMIFS('MoDi Initiatives'!M:M,'MoDi Initiatives'!$E:$E,'Gap Analysis update'!$B11,'MoDi Initiatives'!$A:$A,'Gap Analysis update'!$A11,'MoDi Initiatives'!$C:$C,'Gap Analysis update'!$B$7,'MoDi Initiatives'!$B:$B,'Gap Analysis update'!O$2) -> 0 | P11: =SUMIFS('MoDi Initiatives'!N:N,'MoDi Initiatives'!$E:$E,'Gap Analysis update'!$B11,'MoDi Initiatives'!$A:$A,'Gap Analysis update'!$A11,'MoDi Initiatives'!$B:$B,'Gap Analysis update'!P$2)-SUMIFS('MoDi Initiatives'!N:N,'MoDi Initiatives'!$E:$E,'Gap Analysis update'!$B11,'MoDi Initiatives'!$A:$A,'Gap Analysis update'!$A11,'MoDi Initiatives'!$C:$C,'Gap Analysis update'!$B$7,'MoDi Initiatives'!$B:$B,'Gap Analysis update'!P$2) -> 0 | Q11: =SUMIFS('MoDi Initiatives'!O:O,'MoDi Initiatives'!$E:$E,'Gap Analysis update'!$B11,'MoDi Initiatives'!$A:$A,'Gap Analysis update'!$A11,'MoDi Initiatives'!$B:$B,'Gap Analysis update'!Q$2)-SUMIFS('MoDi Initiatives'!O:O,'MoDi Initiatives'!$E:$E,'Gap Analysis update'!$B11,'MoDi Initiatives'!$A:$A,'Gap Analysis update'!$A11,'MoDi Initiatives'!$C:$C,'Gap Analysis update'!$B$7,'MoDi Initiatives'!$B:$B,'Gap Analysis update'!Q$2) -> 0 | R11: =SUMIFS('MoDi Initiatives'!P:P,'MoDi Initiatives'!$E:$E,'Gap Analysis update'!$B11,'MoDi Initiatives'!$A:$A,'Gap Analysis update'!$A11,'MoDi Initiatives'!$B:$B,'Gap Analysis update'!R$2)-SUMIFS('MoDi Initiatives'!P:P,'MoDi Initiatives'!$E:$E,'Gap Analysis update'!$B11,'MoDi Initiatives'!$A:$A,'Gap Analysis update'!$A11,'MoDi Initiatives'!$C:$C,'Gap Analysis update'!$B$7,'MoDi Initiatives'!$B:$B,'Gap Analysis update'!R$2) -> 0 | S11: =SUMIFS('MoDi Initiatives'!Q:Q,'MoDi Initiatives'!$E:$E,'Gap Analysis update'!$B11,'MoDi Initiatives'!$A:$A,'Gap Analysis update'!$A11,'MoDi Initiatives'!$B:$B,'Gap Analysis update'!S$2)-SUMIFS('MoDi Initiatives'!Q:Q,'MoDi Initiatives'!$E:$E,'Gap Analysis update'!$B11,'MoDi Initiatives'!$A:$A,'Gap Analysis update'!$A11,'MoDi Initiatives'!$C:$C,'Gap Analysis update'!$B$7,'MoDi Initiatives'!$B:$B,'Gap Analysis update'!S$2) -> 0 | T11: =SUMIFS('MoDi Initiatives'!R:R,'MoDi Initiatives'!$E:$E,'Gap Analysis update'!$B11,'MoDi Initiatives'!$A:$A,'Gap Analysis update'!$A11,'MoDi Initiatives'!$B:$B,'Gap Analysis update'!T$2)-SUMIFS('MoDi Initiatives'!R:R,'MoDi Initiatives'!$E:$E,'Gap Analysis update'!$B11,'MoDi Initiatives'!$A:$A,'Gap Analysis update'!$A11,'MoDi Initiatives'!$C:$C,'Gap Analysis update'!$B$7,'MoDi Initiatives'!$B:$B,'Gap Analysis update'!T$2) -> 0 | U11: =SUMIFS('MoDi Initiatives'!S:S,'MoDi Initiatives'!$E:$E,'Gap Analysis update'!$B11,'MoDi Initiatives'!$A:$A,'Gap Analysis update'!$A11,'MoDi Initiatives'!$B:$B,'Gap Analysis update'!U$2)-SUMIFS('MoDi Initiatives'!S:S,'MoDi Initiatives'!$E:$E,'Gap Analysis update'!$B11,'MoDi Initiatives'!$A:$A,'Gap Analysis update'!$A11,'MoDi Initiatives'!$C:$C,'Gap Analysis update'!$B$7,'MoDi Initiatives'!$B:$B,'Gap Analysis update'!U$2) -> 0 | V11: =SUMIFS('MoDi Initiatives'!T:T,'MoDi Initiatives'!$E:$E,'Gap Analysis update'!$B11,'MoDi Initiatives'!$A:$A,'Gap Analysis update'!$A11,'MoDi Initiatives'!$B:$B,'Gap Analysis update'!V$2)-SUMIFS('MoDi Initiatives'!T:T,'MoDi Initiatives'!$E:$E,'Gap Analysis update'!$B11,'MoDi Initiatives'!$A:$A,'Gap Analysis update'!$A11,'MoDi Initiatives'!$C:$C,'Gap Analysis update'!$B$7,'MoDi Initiatives'!$B:$B,'Gap Analysis update'!V$2) -> 0 | W11: =SUMIFS('MoDi Initiatives'!U:U,'MoDi Initiatives'!$E:$E,'Gap Analysis update'!$B11,'MoDi Initiatives'!$A:$A,'Gap Analysis update'!$A11,'MoDi Initiatives'!$B:$B,'Gap Analysis update'!W$2)-SUMIFS('MoDi Initiatives'!U:U,'MoDi Initiatives'!$E:$E,'Gap Analysis update'!$B11,'MoDi Initiatives'!$A:$A,'Gap Analysis update'!$A11,'MoDi Initiatives'!$C:$C,'Gap Analysis update'!$B$7,'MoDi Initiatives'!$B:$B,'Gap Analysis update'!W$2) -> 0 | X11: =SUMIFS('MoDi Initiatives'!V:V,'MoDi Initiatives'!$E:$E,'Gap Analysis update'!$B11,'MoDi Initiatives'!$A:$A,'Gap Analysis update'!$A11,'MoDi Initiatives'!$B:$B,'Gap Analysis update'!X$2)-SUMIFS('MoDi Initiatives'!V:V,'MoDi Initiatives'!$E:$E,'Gap Analysis update'!$B11,'MoDi Initiatives'!$A:$A,'Gap Analysis update'!$A11,'MoDi Initiatives'!$C:$C,'Gap Analysis update'!$B$7,'MoDi Initiatives'!$B:$B,'Gap Analysis update'!X$2) -> 0 | Y11: =SUMIFS('MoDi Initiatives'!W:W,'MoDi Initiatives'!$E:$E,'Gap Analysis update'!$B11,'MoDi Initiatives'!$A:$A,'Gap Analysis update'!$A11,'MoDi Initiatives'!$B:$B,'Gap Analysis update'!Y$2)-SUMIFS('MoDi Initiatives'!W:W,'MoDi Initiatives'!$E:$E,'Gap Analysis update'!$B11,'MoDi Initiatives'!$A:$A,'Gap Analysis update'!$A11,'MoDi Initiatives'!$C:$C,'Gap Analysis update'!$B$7,'MoDi Initiatives'!$B:$B,'Gap Analysis update'!Y$2) -> 0 | AB11: =SUMIFS('MoDi Initiatives'!H:H,'MoDi Initiatives'!$E:$E,'Gap Analysis update'!$B11,'MoDi Initiatives'!$A:$A,'Gap Analysis update'!$A11,'MoDi Initiatives'!$B:$B,'Gap Analysis update'!AB$2)-SUMIFS('MoDi Initiatives'!H:H,'MoDi Initiatives'!$E:$E,'Gap Analysis update'!$B11,'MoDi Initiatives'!$A:$A,'Gap Analysis update'!$A11,'MoDi Initiatives'!$B:$B,'Gap Analysis update'!AB$2,'MoDi Initiatives'!$C:$C,'Gap Analysis update'!$B$7) -> 0 | AC11: =SUMIFS('MoDi Initiatives'!I:I,'MoDi Initiatives'!$E:$E,'Gap Analysis update'!$B11,'MoDi Initiatives'!$A:$A,'Gap Analysis update'!$A11,'MoDi Initiatives'!$B:$B,'Gap Analysis update'!AC$2)-SUMIFS('MoDi Initiatives'!I:I,'MoDi Initiatives'!$E:$E,'Gap Analysis update'!$B11,'MoDi Initiatives'!$A:$A,'Gap Analysis update'!$A11,'MoDi Initiatives'!$B:$B,'Gap Analysis update'!AC$2,'MoDi Initiatives'!$C:$C,'Gap Analysis update'!$B$7) -> 0 | AD11: =SUMIFS('MoDi Initiatives'!J:J,'MoDi Initiatives'!$E:$E,'Gap Analysis update'!$B11,'MoDi Initiatives'!$A:$A,'Gap Analysis update'!$A11,'MoDi Initiatives'!$B:$B,'Gap Analysis update'!AD$2)-SUMIFS('MoDi Initiatives'!J:J,'MoDi Initiatives'!$E:$E,'Gap Analysis update'!$B11,'MoDi Initiatives'!$A:$A,'Gap Analysis update'!$A11,'MoDi Initiatives'!$B:$B,'Gap Analysis update'!AD$2,'MoDi Initiatives'!$C:$C,'Gap Analysis update'!$B$7) -> 0 | AE11: =SUMIFS('MoDi Initiatives'!K:K,'MoDi Initiatives'!$E:$E,'Gap Analysis update'!$B11,'MoDi Initiatives'!$A:$A,'Gap Analysis update'!$A11,'MoDi Initiatives'!$B:$B,'Gap Analysis update'!AE$2)-SUMIFS('MoDi Initiatives'!K:K,'MoDi Initiatives'!$E:$E,'Gap Analysis update'!$B11,'MoDi Initiatives'!$A:$A,'Gap Analysis update'!$A11,'MoDi Initiatives'!$B:$B,'Gap Analysis update'!AE$2,'MoDi Initiatives'!$C:$C,'Gap Analysis update'!$B$7) -> 0 | AF11: =SUMIFS('MoDi Initiatives'!L:L,'MoDi Initiatives'!$E:$E,'Gap Analysis update'!$B11,'MoDi Initiatives'!$A:$A,'Gap Analysis update'!$A11,'MoDi Initiatives'!$B:$B,'Gap Analysis update'!AF$2)-SUMIFS('MoDi Initiatives'!L:L,'MoDi Initiatives'!$E:$E,'Gap Analysis update'!$B11,'MoDi Initiatives'!$A:$A,'Gap Analysis update'!$A11,'MoDi Initiatives'!$B:$B,'Gap Analysis update'!AF$2,'MoDi Initiatives'!$C:$C,'Gap Analysis update'!$B$7) -> 0 | AG11: =SUMIFS('MoDi Initiatives'!M:M,'MoDi Initiatives'!$E:$E,'Gap Analysis update'!$B11,'MoDi Initiatives'!$A:$A,'Gap Analysis update'!$A11,'MoDi Initiatives'!$B:$B,'Gap Analysis update'!AG$2)-SUMIFS('MoDi Initiatives'!M:M,'MoDi Initiatives'!$E:$E,'Gap Analysis update'!$B11,'MoDi Initiatives'!$A:$A,'Gap Analysis update'!$A11,'MoDi Initiatives'!$B:$B,'Gap Analysis update'!AG$2,'MoDi Initiatives'!$C:$C,'Gap Analysis update'!$B$7) -> 0 | AH11: =SUMIFS('MoDi Initiatives'!N:N,'MoDi Initiatives'!$E:$E,'Gap Analysis update'!$B11,'MoDi Initiatives'!$A:$A,'Gap Analysis update'!$A11,'MoDi Initiatives'!$B:$B,'Gap Analysis update'!AH$2)-SUMIFS('MoDi Initiatives'!N:N,'MoDi Initiatives'!$E:$E,'Gap Analysis update'!$B11,'MoDi Initiatives'!$A:$A,'Gap Analysis update'!$A11,'MoDi Initiatives'!$B:$B,'Gap Analysis update'!AH$2,'MoDi Initiatives'!$C:$C,'Gap Analysis update'!$B$7) -> 0 | AI11: =SUMIFS('MoDi Initiatives'!O:O,'MoDi Initiatives'!$E:$E,'Gap Analysis update'!$B11,'MoDi Initiatives'!$A:$A,'Gap Analysis update'!$A11,'MoDi Initiatives'!$B:$B,'Gap Analysis update'!AI$2)-SUMIFS('MoDi Initiatives'!O:O,'MoDi Initiatives'!$E:$E,'Gap Analysis update'!$B11,'MoDi Initiatives'!$A:$A,'Gap Analysis update'!$A11,'MoDi Initiatives'!$B:$B,'Gap Analysis update'!AI$2,'MoDi Initiatives'!$C:$C,'Gap Analysis update'!$B$7) -> 0 | AJ11: =SUMIFS('MoDi Initiatives'!P:P,'MoDi Initiatives'!$E:$E,'Gap Analysis update'!$B11,'MoDi Initiatives'!$A:$A,'Gap Analysis update'!$A11,'MoDi Initiatives'!$B:$B,'Gap Analysis update'!AJ$2)-SUMIFS('MoDi Initiatives'!P:P,'MoDi Initiatives'!$E:$E,'Gap Analysis update'!$B11,'MoDi Initiatives'!$A:$A,'Gap Analysis update'!$A11,'MoDi Initiatives'!$B:$B,'Gap Analysis update'!AJ$2,'MoDi Initiatives'!$C:$C,'Gap Analysis update'!$B$7) -> 0 | AK11: =SUMIFS('MoDi Initiatives'!Q:Q,'MoDi Initiatives'!$E:$E,'Gap Analysis update'!$B11,'MoDi Initiatives'!$A:$A,'Gap Analysis update'!$A11,'MoDi Initiatives'!$B:$B,'Gap Analysis update'!AK$2)-SUMIFS('MoDi Initiatives'!Q:Q,'MoDi Initiatives'!$E:$E,'Gap Analysis update'!$B11,'MoDi Initiatives'!$A:$A,'Gap Analysis update'!$A11,'MoDi Initiatives'!$B:$B,'Gap Analysis update'!AK$2,'MoDi Initiatives'!$C:$C,'Gap Analysis update'!$B$7) -> 0 | AL11: =SUMIFS('MoDi Initiatives'!R:R,'MoDi Initiatives'!$E:$E,'Gap Analysis update'!$B11,'MoDi Initiatives'!$A:$A,'Gap Analysis update'!$A11,'MoDi Initiatives'!$B:$B,'Gap Analysis update'!AL$2)-SUMIFS('MoDi Initiatives'!R:R,'MoDi Initiatives'!$E:$E,'Gap Analysis update'!$B11,'MoDi Initiatives'!$A:$A,'Gap Analysis update'!$A11,'MoDi Initiatives'!$B:$B,'Gap Analysis update'!AL$2,'MoDi Initiatives'!$C:$C,'Gap Analysis update'!$B$7) -> 0 | AM11: =SUMIFS('MoDi Initiatives'!S:S,'MoDi Initiatives'!$E:$E,'Gap Analysis update'!$B11,'MoDi Initiatives'!$A:$A,'Gap Analysis update'!$A11,'MoDi Initiatives'!$B:$B,'Gap Analysis update'!AM$2)-SUMIFS('MoDi Initiatives'!S:S,'MoDi Initiatives'!$E:$E,'Gap Analysis update'!$B11,'MoDi Initiatives'!$A:$A,'Gap Analysis update'!$A11,'MoDi Initiatives'!$B:$B,'Gap Analysis update'!AM$2,'MoDi Initiatives'!$C:$C,'Gap Analysis update'!$B$7) -> 0 | AN11: =SUMIFS('MoDi Initiatives'!T:T,'MoDi Initiatives'!$E:$E,'Gap Analysis update'!$B11,'MoDi Initiatives'!$A:$A,'Gap Analysis update'!$A11,'MoDi Initiatives'!$B:$B,'Gap Analysis update'!AN$2)-SUMIFS('MoDi Initiatives'!T:T,'MoDi Initiatives'!$E:$E,'Gap Analysis update'!$B11,'MoDi Initiatives'!$A:$A,'Gap Analysis update'!$A11,'MoDi Initiatives'!$B:$B,'Gap Analysis update'!AN$2,'MoDi Initiatives'!$C:$C,'Gap Analysis update'!$B$7) -> 0 | AO11: =SUMIFS('MoDi Initiatives'!U:U,'MoDi Initiatives'!$E:$E,'Gap Analysis update'!$B11,'MoDi Initiatives'!$A:$A,'Gap Analysis update'!$A11,'MoDi Initiatives'!$B:$B,'Gap Analysis update'!AO$2)-SUMIFS('MoDi Initiatives'!U:U,'MoDi Initiatives'!$E:$E,'Gap Analysis update'!$B11,'MoDi Initiatives'!$A:$A,'Gap Analysis update'!$A11,'MoDi Initiatives'!$B:$B,'Gap Analysis update'!AO$2,'MoDi Initiatives'!$C:$C,'Gap Analysis update'!$B$7) -> 0 | AP11: =SUMIFS('MoDi Initiatives'!V:V,'MoDi Initiatives'!$E:$E,'Gap Analysis update'!$B11,'MoDi Initiatives'!$A:$A,'Gap Analysis update'!$A11,'MoDi Initiatives'!$B:$B,'Gap Analysis update'!AP$2)-SUMIFS('MoDi Initiatives'!V:V,'MoDi Initiatives'!$E:$E,'Gap Analysis update'!$B11,'MoDi Initiatives'!$A:$A,'Gap Analysis update'!$A11,'MoDi Initiatives'!$B:$B,'Gap Analysis update'!AP$2,'MoDi Initiatives'!$C:$C,'Gap Analysis update'!$B$7) -> 0 | AQ11: =SUMIFS('MoDi Initiatives'!W:W,'MoDi Initiatives'!$E:$E,'Gap Analysis update'!$B11,'MoDi Initiatives'!$A:$A,'Gap Analysis update'!$A11,'MoDi Initiatives'!$B:$B,'Gap Analysis update'!AQ$2)-SUMIFS('MoDi Initiatives'!W:W,'MoDi Initiatives'!$E:$E,'Gap Analysis update'!$B11,'MoDi Initiatives'!$A:$A,'Gap Analysis update'!$A11,'MoDi Initiatives'!$B:$B,'Gap Analysis update'!AQ$2,'MoDi Initiatives'!$C:$C,'Gap Analysis update'!$B$7) -> 0 | AT11: =AB11-J11 -> 0 | AU11: =AC11-K11 -> 0 | AV11: =AD11-L11 -> 0 | AW11: =AE11-M11 -> 0 | AX11: =AF11-N11 -> 0 | AY11: =AG11-O11 -> 0 | AZ11: =AH11-P11 -> 0 | BA11: =AI11-Q11 -> 0 | ... BI11: =AQ11-Y11 -> 0 | BO11: Liquid price down with FX update | BQ11: Inflation | BS11: Liquid stretch | BT11: Liquid price down with FX update | BU11: Inflation
A12: PEN 800 Default 2.0 | B12: Core Technology | C12: =SUM(AS12:BA12) -> 5.3952384e-05 | D12: =SUM(BB12:BI12) -> 0 | E12: =D12+C12 -> 5.3952384e-05 | F12: Gap: 0.01p Slight gap from FX. | G12: Action: pull in Heater cost down -0.76p from Jun'25 to Jan'25 to balance the gap from Assy stretch. (T1) | J12: =SUMIFS('MoDi Initiatives'!H:H,'MoDi Initiatives'!$E:$E,'Gap Analysis update'!$B12,'MoDi Initiatives'!$A:$A,'Gap Analysis update'!$A12,'MoDi Initiatives'!$B:$B,'Gap Analysis update'!J$2)-SUMIFS('MoDi Initiatives'!H:H,'MoDi Initiatives'!$E:$E,'Gap Analysis update'!$B12,'MoDi Initiatives'!$A:$A,'Gap Analysis update'!$A12,'MoDi Initiatives'!$C:$C,'Gap Analysis update'!$B$7,'MoDi Initiatives'!$B:$B,'Gap Analysis update'!J$2) -> 0 | K12: =SUMIFS('MoDi Initiatives'!I:I,'MoDi Initiatives'!$E:$E,'Gap Analysis update'!$B12,'MoDi Initiatives'!$A:$A,'Gap Analysis update'!$A12,'MoDi Initiatives'!$B:$B,'Gap Analysis update'!K$2)-SUMIFS('MoDi Initiatives'!I:I,'MoDi Initiatives'!$E:$E,'Gap Analysis update'!$B12,'MoDi Initiatives'!$A:$A,'Gap Analysis update'!$A12,'MoDi Initiatives'!$C:$C,'Gap Analysis update'!$B$7,'MoDi Initiatives'!$B:$B,'Gap Analysis update'!K$2) -> 0 | L12: =SUMIFS('MoDi Initiatives'!J:J,'MoDi Initiatives'!$E:$E,'Gap Analysis update'!$B12,'MoDi Initiatives'!$A:$A,'Gap Analysis update'!$A12,'MoDi Initiatives'!$B:$B,'Gap Analysis update'!L$2)-SUMIFS('MoDi Initiatives'!J:J,'MoDi Initiatives'!$E:$E,'Gap Analysis update'!$B12,'MoDi Initiatives'!$A:$A,'Gap Analysis update'!$A12,'MoDi Initiatives'!$C:$C,'Gap Analysis update'!$B$7,'MoDi Initiatives'!$B:$B,'Gap Analysis update'!L$2) -> 0 | M12: =SUMIFS('MoDi Initiatives'!K:K,'MoDi Initiatives'!$E:$E,'Gap Analysis update'!$B12,'MoDi Initiatives'!$A:$A,'Gap Analysis update'!$A12,'MoDi Initiatives'!$B:$B,'Gap Analysis update'!M$2)-SUMIFS('MoDi Initiatives'!K:K,'MoDi Initiatives'!$E:$E,'Gap Analysis update'!$B12,'MoDi Initiatives'!$A:$A,'Gap Analysis update'!$A12,'MoDi Initiatives'!$C:$C,'Gap Analysis update'!$B$7,'MoDi Initiatives'!$B:$B,'Gap Analysis update'!M$2) -> -0.0076645176 | N12: =SUMIFS('MoDi Initiatives'!L:L,'MoDi Initiatives'!$E:$E,'Gap Analysis update'!$B12,'MoDi Initiatives'!$A:$A,'Gap Analysis update'!$A12,'MoDi Initiatives'!$B:$B,'Gap Analysis update'!N$2)-SUMIFS('MoDi Initiatives'!L:L,'MoDi Initiatives'!$E:$E,'Gap Analysis update'!$B12,'MoDi Initiatives'!$A:$A,'Gap Analysis update'!$A12,'MoDi Initiatives'!$C:$C,'Gap Analysis update'!$B$7,'MoDi Initiatives'!$B:$B,'Gap Analysis update'!N$2) -> 0 | O12: =SUMIFS('MoDi Initiatives'!M:M,'MoDi Initiatives'!$E:$E,'Gap Analysis update'!$B12,'MoDi Initiatives'!$A:$A,'Gap Analysis update'!$A12,'MoDi Initiatives'!$B:$B,'Gap Analysis update'!O$2)-SUMIFS('MoDi Initiatives'!M:M,'MoDi Initiatives'!$E:$E,'Gap Analysis update'!$B12,'MoDi Initiatives'!$A:$A,'Gap Analysis update'!$A12,'MoDi Initiatives'!$C:$C,'Gap Analysis update'!$B$7,'MoDi Initiatives'!$B:$B,'Gap Analysis update'!O$2) -> 0 | P12: =SUMIFS('MoDi Initiatives'!N:N,'MoDi Initiatives'!$E:$E,'Gap Analysis update'!$B12,'MoDi Initiatives'!$A:$A,'Gap Analysis update'!$A12,'MoDi Initiatives'!$B:$B,'Gap Analysis update'!P$2)-SUMIFS('MoDi Initiatives'!N:N,'MoDi Initiatives'!$E:$E,'Gap Analysis update'!$B12,'MoDi Initiatives'!$A:$A,'Gap Analysis update'!$A12,'MoDi Initiatives'!$C:$C,'Gap Analysis update'!$B$7,'MoDi Initiatives'!$B:$B,'Gap Analysis update'!P$2) -> 0 | Q12: =SUMIFS('MoDi Initiatives'!O:O,'MoDi Initiatives'!$E:$E,'Gap Analysis update'!$B12,'MoDi Initiatives'!$A:$A,'Gap Analysis update'!$A12,'MoDi Initiatives'!$B:$B,'Gap Analysis update'!Q$2)-SUMIFS('MoDi Initiatives'!O:O,'MoDi Initiatives'!$E:$E,'Gap Analysis update'!$B12,'MoDi Initiatives'!$A:$A,'Gap Analysis update'!$A12,'MoDi Initiatives'!$C:$C,'Gap Analysis update'!$B$7,'MoDi Initiatives'!$B:$B,'Gap Analysis update'!Q$2) -> 0 | R12: =SUMIFS('MoDi Initiatives'!P:P,'MoDi Initiatives'!$E:$E,'Gap Analysis update'!$B12,'MoDi Initiatives'!$A:$A,'Gap Analysis update'!$A12,'MoDi Initiatives'!$B:$B,'Gap Analysis update'!R$2)-SUMIFS('MoDi Initiatives'!P:P,'MoDi Initiatives'!$E:$E,'Gap Analysis update'!$B12,'MoDi Initiatives'!$A:$A,'Gap Analysis update'!$A12,'MoDi Initiatives'!$C:$C,'Gap Analysis update'!$B$7,'MoDi Initiatives'!$B:$B,'Gap Analysis update'!R$2) -> 0 | S12: =SUMIFS('MoDi Initiatives'!Q:Q,'MoDi Initiatives'!$E:$E,'Gap Analysis update'!$B12,'MoDi Initiatives'!$A:$A,'Gap Analysis update'!$A12,'MoDi Initiatives'!$B:$B,'Gap Analysis update'!S$2)-SUMIFS('MoDi Initiatives'!Q:Q,'MoDi Initiatives'!$E:$E,'Gap Analysis update'!$B12,'MoDi Initiatives'!$A:$A,'Gap Analysis update'!$A12,'MoDi Initiatives'!$C:$C,'Gap Analysis update'!$B$7,'MoDi Initiatives'!$B:$B,'Gap Analysis update'!S$2) -> 0 | T12: =SUMIFS('MoDi Initiatives'!R:R,'MoDi Initiatives'!$E:$E,'Gap Analysis update'!$B12,'MoDi Initiatives'!$A:$A,'Gap Analysis update'!$A12,'MoDi Initiatives'!$B:$B,'Gap Analysis update'!T$2)-SUMIFS('MoDi Initiatives'!R:R,'MoDi Initiatives'!$E:$E,'Gap Analysis update'!$B12,'MoDi Initiatives'!$A:$A,'Gap Analysis update'!$A12,'MoDi Initiatives'!$C:$C,'Gap Analysis update'!$B$7,'MoDi Initiatives'!$B:$B,'Gap Analysis update'!T$2) -> -0.0076645176 | U12: =SUMIFS('MoDi Initiatives'!S:S,'MoDi Initiatives'!$E:$E,'Gap Analysis update'!$B12,'MoDi Initiatives'!$A:$A,'Gap Analysis update'!$A12,'MoDi Initiatives'!$B:$B,'Gap Analysis update'!U$2)-SUMIFS('MoDi Initiatives'!S:S,'MoDi Initiatives'!$E:$E,'Gap Analysis update'!$B12,'MoDi Initiatives'!$A:$A,'Gap Analysis update'!$A12,'MoDi Initiatives'!$C:$C,'Gap Analysis update'!$B$7,'MoDi Initiatives'!$B:$B,'Gap Analysis update'!U$2) -> 0 | V12: =SUMIFS('MoDi Initiatives'!T:T,'MoDi Initiatives'!$E:$E,'Gap Analysis update'!$B12,'MoDi Initiatives'!$A:$A,'Gap Analysis update'!$A12,'MoDi Initiatives'!$B:$B,'Gap Analysis update'!V$2)-SUMIFS('MoDi Initiatives'!T:T,'MoDi Initiatives'!$E:$E,'Gap Analysis update'!$B12,'MoDi Initiatives'!$A:$A,'Gap Analysis update'!$A12,'MoDi Initiatives'!$C:$C,'Gap Analysis update'!$B$7,'MoDi Initiatives'!$B:$B,'Gap Analysis update'!V$2) -> 0 | W12: =SUMIFS('MoDi Initiatives'!U:U,'MoDi Initiatives'!$E:$E,'Gap Analysis update'!$B12,'MoDi Initiatives'!$A:$A,'Gap Analysis update'!$A12,'MoDi Initiatives'!$B:$B,'Gap Analysis update'!W$2)-SUMIFS('MoDi Initiatives'!U:U,'MoDi Initiatives'!$E:$E,'Gap Analysis update'!$B12,'MoDi Initiatives'!$A:$A,'Gap Analysis update'!$A12,'MoDi Initiatives'!$C:$C,'Gap Analysis update'!$B$7,'MoDi Initiatives'!$B:$B,'Gap Analysis update'!W$2) -> 0 | X12: =SUMIFS('MoDi Initiatives'!V:V,'MoDi Initiatives'!$E:$E,'Gap Analysis update'!$B12,'MoDi Initiatives'!$A:$A,'Gap Analysis update'!$A12,'MoDi Initiatives'!$B:$B,'Gap Analysis update'!X$2)-SUMIFS('MoDi Initiatives'!V:V,'MoDi Initiatives'!$E:$E,'Gap Analysis update'!$B12,'MoDi Initiatives'!$A:$A,'Gap Analysis update'!$A12,'MoDi Initiatives'!$C:$C,'Gap Analysis update'!$B$7,'MoDi Initiatives'!$B:$B,'Gap Analysis update'!X$2) -> 0 | Y12: =SUMIFS('MoDi Initiatives'!W:W,'MoDi Initiatives'!$E:$E,'Gap Analysis update'!$B12,'MoDi Initiatives'!$A:$A,'Gap Analysis update'!$A12,'MoDi Initiatives'!$B:$B,'Gap Analysis update'!Y$2)-SUMIFS('MoDi Initiatives'!W:W,'MoDi Initiatives'!$E:$E,'Gap Analysis update'!$B12,'MoDi Initiatives'!$A:$A,'Gap Analysis update'!$A12,'MoDi Initiatives'!$C:$C,'Gap Analysis update'!$B$7,'MoDi Initiatives'!$B:$B,'Gap Analysis update'!Y$2) -> 0 | AB12: =SUMIFS('MoDi Initiatives'!H:H,'MoDi Initiatives'!$E:$E,'Gap Analysis update'!$B12,'MoDi Initiatives'!$A:$A,'Gap Analysis update'!$A12,'MoDi Initiatives'!$B:$B,'Gap Analysis update'!AB$2)-SUMIFS('MoDi Initiatives'!H:H,'MoDi Initiatives'!$E:$E,'Gap Analysis update'!$B12,'MoDi Initiatives'!$A:$A,'Gap Analysis update'!$A12,'MoDi Initiatives'!$B:$B,'Gap Analysis update'!AB$2,'MoDi Initiatives'!$C:$C,'Gap Analysis update'!$B$7) -> 0 | AC12: =SUMIFS('MoDi Initiatives'!I:I,'MoDi Initiatives'!$E:$E,'Gap Analysis update'!$B12,'MoDi Initiatives'!$A:$A,'Gap Analysis update'!$A12,'MoDi Initiatives'!$B:$B,'Gap Analysis update'!AC$2)-SUMIFS('MoDi Initiatives'!I:I,'MoDi Initiatives'!$E:$E,'Gap Analysis update'!$B12,'MoDi Initiatives'!$A:$A,'Gap Analysis update'!$A12,'MoDi Initiatives'!$B:$B,'Gap Analysis update'!AC$2,'MoDi Initiatives'!$C:$C,'Gap Analysis update'!$B$7) -> 0 | AD12: =SUMIFS('MoDi Initiatives'!J:J,'MoDi Initiatives'!$E:$E,'Gap Analysis update'!$B12,'MoDi Initiatives'!$A:$A,'Gap Analysis update'!$A12,'MoDi Initiatives'!$B:$B,'Gap Analysis update'!AD$2)-SUMIFS('MoDi Initiatives'!J:J,'MoDi Initiatives'!$E:$E,'Gap Analysis update'!$B12,'MoDi Initiatives'!$A:$A,'Gap Analysis update'!$A12,'MoDi Initiatives'!$B:$B,'Gap Analysis update'!AD$2,'MoDi Initiatives'!$C:$C,'Gap Analysis update'!$B$7) -> -0.0076105652 | AE12: =SUMIFS('MoDi Initiatives'!K:K,'MoDi Initiatives'!$E:$E,'Gap Analysis update'!$B12,'MoDi Initiatives'!$A:$A,'Gap Analysis update'!$A12,'MoDi Initiatives'!$B:$B,'Gap Analysis update'!AE$2)-SUMIFS('MoDi Initiatives'!K:K,'MoDi Initiatives'!$E:$E,'Gap Analysis update'!$B12,'MoDi Initiatives'!$A:$A,'Gap Analysis update'!$A12,'MoDi Initiatives'!$B:$B,'Gap Analysis update'!AE$2,'MoDi Initiatives'!$C:$C,'Gap Analysis update'!$B$7) -> 0 | AF12: =SUMIFS('MoDi Initiatives'!L:L,'MoDi Initiatives'!$E:$E,'Gap Analysis update'!$B12,'MoDi Initiatives'!$A:$A,'Gap Analysis update'!$A12,'MoDi Initiatives'!$B:$B,'Gap Analysis update'!AF$2)-SUMIFS('MoDi Initiatives'!L:L,'MoDi Initiatives'!$E:$E,'Gap Analysis update'!$B12,'MoDi Initiatives'!$A:$A,'Gap Analysis update'!$A12,'MoDi Initiatives'!$B:$B,'Gap Analysis update'!AF$2,'MoDi Initiatives'!$C:$C,'Gap Analysis update'!$B$7) -> 0 | AG12: =SUMIFS('MoDi Initiatives'!M:M,'MoDi Initiatives'!$E:$E,'Gap Analysis update'!$B12,'MoDi Initiatives'!$A:$A,'Gap Analysis update'!$A12,'MoDi Initiatives'!$B:$B,'Gap Analysis update'!AG$2)-SUMIFS('MoDi Initiatives'!M:M,'MoDi Initiatives'!$E:$E,'Gap Analysis update'!$B12,'MoDi Initiatives'!$A:$A,'Gap Analysis update'!$A12,'MoDi Initiatives'!$B:$B,'Gap Analysis update'!AG$2,'MoDi Initiatives'!$C:$C,'Gap Analysis update'!$B$7) -> 0 | AH12: =SUMIFS('MoDi Initiatives'!N:N,'MoDi Initiatives'!$E:$E,'Gap Analysis update'!$B12,'MoDi Initiatives'!$A:$A,'Gap Analysis update'!$A12,'MoDi Initiatives'!$B:$B,'Gap Analysis update'!AH$2)-SUMIFS('MoDi Initiatives'!N:N,'MoDi Initiatives'!$E:$E,'Gap Analysis update'!$B12,'MoDi Initiatives'!$A:$A,'Gap Analysis update'!$A12,'MoDi Initiatives'!$B:$B,'Gap Analysis update'!AH$2,'MoDi Initiatives'!$C:$C,'Gap Analysis update'!$B$7) -> 0 | AI12: =SUMIFS('MoDi Initiatives'!O:O,'MoDi Initiatives'!$E:$E,'Gap Analysis update'!$B12,'MoDi Initiatives'!$A:$A,'Gap Analysis update'!$A12,'MoDi Initiatives'!$B:$B,'Gap Analysis update'!AI$2)-SUMIFS('MoDi Initiatives'!O:O,'MoDi Initiatives'!$E:$E,'Gap Analysis update'!$B12,'MoDi Initiatives'!$A:$A,'Gap Analysis update'!$A12,'MoDi Initiatives'!$B:$B,'Gap Analysis update'!AI$2,'MoDi Initiatives'!$C:$C,'Gap Analysis update'!$B$7) -> 0 | AJ12: =SUMIFS('MoDi Initiatives'!P:P,'MoDi Initiatives'!$E:$E,'Gap Analysis update'!$B12,'MoDi Initiatives'!$A:$A,'Gap Analysis update'!$A12,'MoDi Initiatives'!$B:$B,'Gap Analysis update'!AJ$2)-SUMIFS('MoDi Initiatives'!P:P,'MoDi Initiatives'!$E:$E,'Gap Analysis update'!$B12,'MoDi Initiatives'!$A:$A,'Gap Analysis update'!$A12,'MoDi Initiatives'!$B:$B,'Gap Analysis update'!AJ$2,'MoDi Initiatives'!$C:$C,'Gap Analysis update'!$B$7) -> 0 | AK12: =SUMIFS('MoDi Initiatives'!Q:Q,'MoDi Initiatives'!$E:$E,'Gap Analysis update'!$B12,'MoDi Initiatives'!$A:$A,'Gap Analysis update'!$A12,'MoDi Initiatives'!$B:$B,'Gap Analysis update'!AK$2)-SUMIFS('MoDi Initiatives'!Q:Q,'MoDi Initiatives'!$E:$E,'Gap Analysis update'!$B12,'MoDi Initiatives'!$A:$A,'Gap Analysis update'!$A12,'MoDi Initiatives'!$B:$B,'Gap Analysis update'!AK$2,'MoDi Initiatives'!$C:$C,'Gap Analysis update'!$B$7) -> 0 | AL12: =SUMIFS('MoDi Initiatives'!R:R,'MoDi Initiatives'!$E:$E,'Gap Analysis update'!$B12,'MoDi Initiatives'!$A:$A,'Gap Analysis update'!$A12,'MoDi Initiatives'!$B:$B,'Gap Analysis update'!AL$2)-SUMIFS('MoDi Initiatives'!R:R,'MoDi Initiatives'!$E:$E,'Gap Analysis update'!$B12,'MoDi Initiatives'!$A:$A,'Gap Analysis update'!$A12,'MoDi Initiatives'!$B:$B,'Gap Analysis update'!AL$2,'MoDi Initiatives'!$C:$C,'Gap Analysis update'!$B$7) -> -0.0076645176 | AM12: =SUMIFS('MoDi Initiatives'!S:S,'MoDi Initiatives'!$E:$E,'Gap Analysis update'!$B12,'MoDi Initiatives'!$A:$A,'Gap Analysis update'!$A12,'MoDi Initiatives'!$B:$B,'Gap Analysis update'!AM$2)-SUMIFS('MoDi Initiatives'!S:S,'MoDi Initiatives'!$E:$E,'Gap Analysis update'!$B12,'MoDi Initiatives'!$A:$A,'Gap Analysis update'!$A12,'MoDi Initiatives'!$B:$B,'Gap Analysis update'!AM$2,'MoDi Initiatives'!$C:$C,'Gap Analysis update'!$B$7) -> 0 | AN12: =SUMIFS('MoDi Initiatives'!T:T,'MoDi Initiatives'!$E:$E,'Gap Analysis update'!$B12,'MoDi Initiatives'!$A:$A,'Gap Analysis update'!$A12,'MoDi Initiatives'!$B:$B,'Gap Analysis update'!AN$2)-SUMIFS('MoDi Initiatives'!T:T,'MoDi Initiatives'!$E:$E,'Gap Analysis update'!$B12,'MoDi Initiatives'!$A:$A,'Gap Analysis update'!$A12,'MoDi Initiatives'!$B:$B,'Gap Analysis update'!AN$2,'MoDi Initiatives'!$C:$C,'Gap Analysis update'!$B$7) -> 0 | AO12: =SUMIFS('MoDi Initiatives'!U:U,'MoDi Initiatives'!$E:$E,'Gap Analysis update'!$B12,'MoDi Initiatives'!$A:$A,'Gap Analysis update'!$A12,'MoDi Initiatives'!$B:$B,'Gap Analysis update'!AO$2)-SUMIFS('MoDi Initiatives'!U:U,'MoDi Initiatives'!$E:$E,'Gap Analysis update'!$B12,'MoDi Initiatives'!$A:$A,'Gap Analysis update'!$A12,'MoDi Initiatives'!$B:$B,'Gap Analysis update'!AO$2,'MoDi Initiatives'!$C:$C,'Gap Analysis update'!$B$7) -> 0 | AP12: =SUMIFS('MoDi Initiatives'!V:V,'MoDi Initiatives'!$E:$E,'Gap Analysis update'!$B12,'MoDi Initiatives'!$A:$A,'Gap Analysis update'!$A12,'MoDi Initiatives'!$B:$B,'Gap Analysis update'!AP$2)-SUMIFS('MoDi Initiatives'!V:V,'MoDi Initiatives'!$E:$E,'Gap Analysis update'!$B12,'MoDi Initiatives'!$A:$A,'Gap Analysis update'!$A12,'MoDi Initiatives'!$B:$B,'Gap Analysis update'!AP$2,'MoDi Initiatives'!$C:$C,'Gap Analysis update'!$B$7) -> 0 | AQ12: =SUMIFS('MoDi Initiatives'!W:W,'MoDi Initiatives'!$E:$E,'Gap Analysis update'!$B12,'MoDi Initiatives'!$A:$A,'Gap Analysis update'!$A12,'MoDi Initiatives'!$B:$B,'Gap Analysis update'!AQ$2)-SUMIFS('MoDi Initiatives'!W:W,'MoDi Initiatives'!$E:$E,'Gap Analysis update'!$B12,'MoDi Initiatives'!$A:$A,'Gap Analysis update'!$A12,'MoDi Initiatives'!$B:$B,'Gap Analysis update'!AQ$2,'MoDi Initiatives'!$C:$C,'Gap Analysis update'!$B$7) -> 0 | AT12: =AB12-J12 -> 0 | AU12: =AC12-K12 -> 0 | AV12: =AD12-L12 -> -0.0076105652 | AW12: =AE12-M12 -> 0.0076645176 | AX12: =AF12-N12 -> 0 | AY12: =AG12-O12 -> 0 | AZ12: =AH12-P12 -> 0 | BA12: =AI12-Q12 -> 0 | ... BI12: =AQ12-Y12 -> 0 | BO12: Heater wave 3 | BP12: Heater wave 3 | BW12: Heater wave 4 | BX12: Heater wave 4
A13: PEN 800 Default 2.0 | B13: Assembly | C13: =SUM(AS13:BA13) -> 0.0062734789 | D13: =SUM(BB13:BI13) -> 0.0096215953 | E13: =D13+C13 -> 0.015895074 | F13: Gap: -0.04p.(exceed) TML reduce from BOM cost improvement. | G13: Gap: 0.96p; 1. Extra Stretch-finance: 0.96p gap in Mar'25. (T1) | J13: =SUMIFS('MoDi Initiatives'!H:H,'MoDi Initiatives'!$E:$E,'Gap Analysis update'!$B13,'MoDi Initiatives'!$A:$A,'Gap Analysis update'!$A13,'MoDi Initiatives'!$B:$B,'Gap Analysis update'!J$2)-SUMIFS('MoDi Initiatives'!H:H,'MoDi Initiatives'!$E:$E,'Gap Analysis update'!$B13,'MoDi Initiatives'!$A:$A,'Gap Analysis update'!$A13,'MoDi Initiatives'!$C:$C,'Gap Analysis update'!$B$7,'MoDi Initiatives'!$B:$B,'Gap Analysis update'!J$2) -> 0 | K13: =SUMIFS('MoDi Initiatives'!I:I,'MoDi Initiatives'!$E:$E,'Gap Analysis update'!$B13,'MoDi Initiatives'!$A:$A,'Gap Analysis update'!$A13,'MoDi Initiatives'!$B:$B,'Gap Analysis update'!K$2)-SUMIFS('MoDi Initiatives'!I:I,'MoDi Initiatives'!$E:$E,'Gap Analysis update'!$B13,'MoDi Initiatives'!$A:$A,'Gap Analysis update'!$A13,'MoDi Initiatives'!$C:$C,'Gap Analysis update'!$B$7,'MoDi Initiatives'!$B:$B,'Gap Analysis update'!K$2) -> 0 | L13: =SUMIFS('MoDi Initiatives'!J:J,'MoDi Initiatives'!$E:$E,'Gap Analysis update'!$B13,'MoDi Initiatives'!$A:$A,'Gap Analysis update'!$A13,'MoDi Initiatives'!$B:$B,'Gap Analysis update'!L$2)-SUMIFS('MoDi Initiatives'!J:J,'MoDi Initiatives'!$E:$E,'Gap Analysis update'!$B13,'MoDi Initiatives'!$A:$A,'Gap Analysis update'!$A13,'MoDi Initiatives'!$C:$C,'Gap Analysis update'!$B$7,'MoDi Initiatives'!$B:$B,'Gap Analysis update'!L$2) -> 0 | M13: =SUMIFS('MoDi Initiatives'!K:K,'MoDi Initiatives'!$E:$E,'Gap Analysis update'!$B13,'MoDi Initiatives'!$A:$A,'Gap Analysis update'!$A13,'MoDi Initiatives'!$B:$B,'Gap Analysis update'!M$2)-SUMIFS('MoDi Initiatives'!K:K,'MoDi Initiatives'!$E:$E,'Gap Analysis update'!$B13,'MoDi Initiatives'!$A:$A,'Gap Analysis update'!$A13,'MoDi Initiatives'!$C:$C,'Gap Analysis update'!$B$7,'MoDi Initiatives'!$B:$B,'Gap Analysis update'!M$2) -> 0 | N13: =SUMIFS('MoDi Initiatives'!L:L,'MoDi Initiatives'!$E:$E,'Gap Analysis update'!$B13,'MoDi Initiatives'!$A:$A,'Gap Analysis update'!$A13,'MoDi Initiatives'!$B:$B,'Gap Analysis update'!N$2)-SUMIFS('MoDi Initiatives'!L:L,'MoDi Initiatives'!$E:$E,'Gap Analysis update'!$B13,'MoDi Initiatives'!$A:$A,'Gap Analysis update'!$A13,'MoDi Initiatives'!$C:$C,'Gap Analysis update'!$B$7,'MoDi Initiatives'!$B:$B,'Gap Analysis update'!N$2) -> 0 | O13: =SUMIFS('MoDi Initiatives'!M:M,'MoDi Initiatives'!$E:$E,'Gap Analysis update'!$B13,'MoDi Initiatives'!$A:$A,'Gap Analysis update'!$A13,'MoDi Initiatives'!$B:$B,'Gap Analysis update'!O$2)-SUMIFS('MoDi Initiatives'!M:M,'MoDi Initiatives'!$E:$E,'Gap Analysis update'!$B13,'MoDi Initiatives'!$A:$A,'Gap Analysis update'!$A13,'MoDi Initiatives'!$C:$C,'Gap Analysis update'!$B$7,'MoDi Initiatives'!$B:$B,'Gap Analysis update'!O$2) -> 0 | P13: =SUMIFS('MoDi Initiatives'!N:N,'MoDi Initiatives'!$E:$E,'Gap Analysis update'!$B13,'MoDi Initiatives'!$A:$A,'Gap Analysis update'!$A13,'MoDi Initiatives'!$B:$B,'Gap Analysis update'!P$2)-SUMIFS('MoDi Initiatives'!N:N,'MoDi Initiatives'!$E:$E,'Gap Analysis update'!$B13,'MoDi Initiatives'!$A:$A,'Gap Analysis update'!$A13,'MoDi Initiatives'!$C:$C,'Gap Analysis update'!$B$7,'MoDi Initiatives'!$B:$B,'Gap Analysis update'!P$2) -> 0 | Q13: =SUMIFS('MoDi Initiatives'!O:O,'MoDi Initiatives'!$E:$E,'Gap Analysis update'!$B13,'MoDi Initiatives'!$A:$A,'Gap Analysis update'!$A13,'MoDi Initiatives'!$B:$B,'Gap Analysis update'!Q$2)-SUMIFS('MoDi Initiatives'!O:O,'MoDi Initiatives'!$E:$E,'Gap Analysis update'!$B13,'MoDi Initiatives'!$A:$A,'Gap Analysis update'!$A13,'MoDi Initiatives'!$C:$C,'Gap Analysis update'!$B$7,'MoDi Initiatives'!$B:$B,'Gap Analysis update'!Q$2) -> 0 | R13: =SUMIFS('MoDi Initiatives'!P:P,'MoDi Initiatives'!$E:$E,'Gap Analysis update'!$B13,'MoDi Initiatives'!$A:$A,'Gap Analysis update'!$A13,'MoDi Initiatives'!$B:$B,'Gap Analysis update'!R$2)-SUMIFS('MoDi Initiatives'!P:P,'MoDi Initiatives'!$E:$E,'Gap Analysis update'!$B13,'MoDi Initiatives'!$A:$A,'Gap Analysis update'!$A13,'MoDi Initiatives'!$C:$C,'Gap Analysis update'!$B$7,'MoDi Initiatives'!$B:$B,'Gap Analysis update'!R$2) -> -0.009580647 | S13: =SUMIFS('MoDi Initiatives'!Q:Q,'MoDi Initiatives'!$E:$E,'Gap Analysis update'!$B13,'MoDi Initiatives'!$A:$A,'Gap Analysis update'!$A13,'MoDi Initiatives'!$B:$B,'Gap Analysis update'!S$2)-SUMIFS('MoDi Initiatives'!Q:Q,'MoDi Initiatives'!$E:$E,'Gap Analysis update'!$B13,'MoDi Initiatives'!$A:$A,'Gap Analysis update'!$A13,'MoDi Initiatives'!$C:$C,'Gap Analysis update'!$B$7,'MoDi Initiatives'!$B:$B,'Gap Analysis update'!S$2) -> 0 | T13: =SUMIFS('MoDi Initiatives'!R:R,'MoDi Initiatives'!$E:$E,'Gap Analysis update'!$B13,'MoDi Initiatives'!$A:$A,'Gap Analysis update'!$A13,'MoDi Initiatives'!$B:$B,'Gap Analysis update'!T$2)-SUMIFS('MoDi Initiatives'!R:R,'MoDi Initiatives'!$E:$E,'Gap Analysis update'!$B13,'MoDi Initiatives'!$A:$A,'Gap Analysis update'!$A13,'MoDi Initiatives'!$C:$C,'Gap Analysis update'!$B$7,'MoDi Initiatives'!$B:$B,'Gap Analysis update'!T$2) -> 0 | U13: =SUMIFS('MoDi Initiatives'!S:S,'MoDi Initiatives'!$E:$E,'Gap Analysis update'!$B13,'MoDi Initiatives'!$A:$A,'Gap Analysis update'!$A13,'MoDi Initiatives'!$B:$B,'Gap Analysis update'!U$2)-SUMIFS('MoDi Initiatives'!S:S,'MoDi Initiatives'!$E:$E,'Gap Analysis update'!$B13,'MoDi Initiatives'!$A:$A,'Gap Analysis update'!$A13,'MoDi Initiatives'!$C:$C,'Gap Analysis update'!$B$7,'MoDi Initiatives'!$B:$B,'Gap Analysis update'!U$2) -> 0 | V13: =SUMIFS('MoDi Initiatives'!T:T,'MoDi Initiatives'!$E:$E,'Gap Analysis update'!$B13,'MoDi Initiatives'!$A:$A,'Gap Analysis update'!$A13,'MoDi Initiatives'!$B:$B,'Gap Analysis update'!V$2)-SUMIFS('MoDi Initiatives'!T:T,'MoDi Initiatives'!$E:$E,'Gap Analysis update'!$B13,'MoDi Initiatives'!$A:$A,'Gap Analysis update'!$A13,'MoDi Initiatives'!$C:$C,'Gap Analysis update'!$B$7,'MoDi Initiatives'!$B:$B,'Gap Analysis update'!V$2) -> 0 | W13: =SUMIFS('MoDi Initiatives'!U:U,'MoDi Initiatives'!$E:$E,'Gap Analysis update'!$B13,'MoDi Initiatives'!$A:$A,'Gap Analysis update'!$A13,'MoDi Initiatives'!$B:$B,'Gap Analysis update'!W$2)-SUMIFS('MoDi Initiatives'!U:U,'MoDi Initiatives'!$E:$E,'Gap Analysis update'!$B13,'MoDi Initiatives'!$A:$A,'Gap Analysis update'!$A13,'MoDi Initiatives'!$C:$C,'Gap Analysis update'!$B$7,'MoDi Initiatives'!$B:$B,'Gap Analysis update'!W$2) -> 0 | X13: =SUMIFS('MoDi Initiatives'!V:V,'MoDi Initiatives'!$E:$E,'Gap Analysis update'!$B13,'MoDi Initiatives'!$A:$A,'Gap Analysis update'!$A13,'MoDi Initiatives'!$B:$B,'Gap Analysis update'!X$2)-SUMIFS('MoDi Initiatives'!V:V,'MoDi Initiatives'!$E:$E,'Gap Analysis update'!$B13,'MoDi Initiatives'!$A:$A,'Gap Analysis update'!$A13,'MoDi Initiatives'!$C:$C,'Gap Analysis update'!$B$7,'MoDi Initiatives'!$B:$B,'Gap Analysis update'!X$2) -> 0 | Y13: =SUMIFS('MoDi Initiatives'!W:W,'MoDi Initiatives'!$E:$E,'Gap Analysis update'!$B13,'MoDi Initiatives'!$A:$A,'Gap Analysis update'!$A13,'MoDi Initiatives'!$B:$B,'Gap Analysis update'!Y$2)-SUMIFS('MoDi Initiatives'!W:W,'MoDi Initiatives'!$E:$E,'Gap Analysis update'!$B13,'MoDi Initiatives'!$A:$A,'Gap Analysis update'!$A13,'MoDi Initiatives'!$C:$C,'Gap Analysis update'!$B$7,'MoDi Initiatives'!$B:$B,'Gap Analysis update'!Y$2) -> 0 | AB13: =SUMIFS('MoDi Initiatives'!H:H,'MoDi Initiatives'!$E:$E,'Gap Analysis update'!$B13,'MoDi Initiatives'!$A:$A,'Gap Analysis update'!$A13,'MoDi Initiatives'!$B:$B,'Gap Analysis update'!AB$2)-SUMIFS('MoDi Initiatives'!H:H,'MoDi Initiatives'!$E:$E,'Gap Analysis update'!$B13,'MoDi Initiatives'!$A:$A,'Gap Analysis update'!$A13,'MoDi Initiatives'!$B:$B,'Gap Analysis update'!AB$2,'MoDi Initiatives'!$C:$C,'Gap Analysis update'!$B$7) -> -0.00012002949 | AC13: =SUMIFS('MoDi Initiatives'!I:I,'MoDi Initiatives'!$E:$E,'Gap Analysis update'!$B13,'MoDi Initiatives'!$A:$A,'Gap Analysis update'!$A13,'MoDi Initiatives'!$B:$B,'Gap Analysis update'!AC$2)-SUMIFS('MoDi Initiatives'!I:I,'MoDi Initiatives'!$E:$E,'Gap Analysis update'!$B13,'MoDi Initiatives'!$A:$A,'Gap Analysis update'!$A13,'MoDi Initiatives'!$B:$B,'Gap Analysis update'!AC$2,'MoDi Initiatives'!$C:$C,'Gap Analysis update'!$B$7) -> 0.0066977551 | AD13: =SUMIFS('MoDi Initiatives'!J:J,'MoDi Initiatives'!$E:$E,'Gap Analysis update'!$B13,'MoDi Initiatives'!$A:$A,'Gap Analysis update'!$A13,'MoDi Initiatives'!$B:$B,'Gap Analysis update'!AD$2)-SUMIFS('MoDi Initiatives'!J:J,'MoDi Initiatives'!$E:$E,'Gap Analysis update'!$B13,'MoDi Initiatives'!$A:$A,'Gap Analysis update'!$A13,'MoDi Initiatives'!$B:$B,'Gap Analysis update'!AD$2,'MoDi Initiatives'!$C:$C,'Gap Analysis update'!$B$7) -> -0.00014019283 | AE13: =SUMIFS('MoDi Initiatives'!K:K,'MoDi Initiatives'!$E:$E,'Gap Analysis update'!$B13,'MoDi Initiatives'!$A:$A,'Gap Analysis update'!$A13,'MoDi Initiatives'!$B:$B,'Gap Analysis update'!AE$2)-SUMIFS('MoDi Initiatives'!K:K,'MoDi Initiatives'!$E:$E,'Gap Analysis update'!$B13,'MoDi Initiatives'!$A:$A,'Gap Analysis update'!$A13,'MoDi Initiatives'!$B:$B,'Gap Analysis update'!AE$2,'MoDi Initiatives'!$C:$C,'Gap Analysis update'!$B$7) -> 0 | AF13: =SUMIFS('MoDi Initiatives'!L:L,'MoDi Initiatives'!$E:$E,'Gap Analysis update'!$B13,'MoDi Initiatives'!$A:$A,'Gap Analysis update'!$A13,'MoDi Initiatives'!$B:$B,'Gap Analysis update'!AF$2)-SUMIFS('MoDi Initiatives'!L:L,'MoDi Initiatives'!$E:$E,'Gap Analysis update'!$B13,'MoDi Initiatives'!$A:$A,'Gap Analysis update'!$A13,'MoDi Initiatives'!$B:$B,'Gap Analysis update'!AF$2,'MoDi Initiatives'!$C:$C,'Gap Analysis update'!$B$7) -> -2.3310074e-05 | AG13: =SUMIFS('MoDi Initiatives'!M:M,'MoDi Initiatives'!$E:$E,'Gap Analysis update'!$B13,'MoDi Initiatives'!$A:$A,'Gap Analysis update'!$A13,'MoDi Initiatives'!$B:$B,'Gap Analysis update'!AG$2)-SUMIFS('MoDi Initiatives'!M:M,'MoDi Initiatives'!$E:$E,'Gap Analysis update'!$B13,'MoDi Initiatives'!$A:$A,'Gap Analysis update'!$A13,'MoDi Initiatives'!$B:$B,'Gap Analysis update'!AG$2,'MoDi Initiatives'!$C:$C,'Gap Analysis update'!$B$7) -> 0 | AH13: =SUMIFS('MoDi Initiatives'!N:N,'MoDi Initiatives'!$E:$E,'Gap Analysis update'!$B13,'MoDi Initiatives'!$A:$A,'Gap Analysis update'!$A13,'MoDi Initiatives'!$B:$B,'Gap Analysis update'!AH$2)-SUMIFS('MoDi Initiatives'!N:N,'MoDi Initiatives'!$E:$E,'Gap Analysis update'!$B13,'MoDi Initiatives'!$A:$A,'Gap Analysis update'!$A13,'MoDi Initiatives'!$B:$B,'Gap Analysis update'!AH$2,'MoDi Initiatives'!$C:$C,'Gap Analysis update'!$B$7) -> -6.958231e-06 | AI13: =SUMIFS('MoDi Initiatives'!O:O,'MoDi Initiatives'!$E:$E,'Gap Analysis update'!$B13,'MoDi Initiatives'!$A:$A,'Gap Analysis update'!$A13,'MoDi Initiatives'!$B:$B,'Gap Analysis update'!AI$2)-SUMIFS('MoDi Initiatives'!O:O,'MoDi Initiatives'!$E:$E,'Gap Analysis update'!$B13,'MoDi Initiatives'!$A:$A,'Gap Analysis update'!$A13,'MoDi Initiatives'!$B:$B,'Gap Analysis update'!AI$2,'MoDi Initiatives'!$C:$C,'Gap Analysis update'!$B$7) -> -0.00013378556 | AJ13: =SUMIFS('MoDi Initiatives'!P:P,'MoDi Initiatives'!$E:$E,'Gap Analysis update'!$B13,'MoDi Initiatives'!$A:$A,'Gap Analysis update'!$A13,'MoDi Initiatives'!$B:$B,'Gap Analysis update'!AJ$2)-SUMIFS('MoDi Initiatives'!P:P,'MoDi Initiatives'!$E:$E,'Gap Analysis update'!$B13,'MoDi Initiatives'!$A:$A,'Gap Analysis update'!$A13,'MoDi Initiatives'!$B:$B,'Gap Analysis update'!AJ$2,'MoDi Initiatives'!$C:$C,'Gap Analysis update'!$B$7) -> 4.0948348e-05 | AK13: =SUMIFS('MoDi Initiatives'!Q:Q,'MoDi Initiatives'!$E:$E,'Gap Analysis update'!$B13,'MoDi Initiatives'!$A:$A,'Gap Analysis update'!$A13,'MoDi Initiatives'!$B:$B,'Gap Analysis update'!AK$2)-SUMIFS('MoDi Initiatives'!Q:Q,'MoDi Initiatives'!$E:$E,'Gap Analysis update'!$B13,'MoDi Initiatives'!$A:$A,'Gap Analysis update'!$A13,'MoDi Initiatives'!$B:$B,'Gap Analysis update'!AK$2,'MoDi Initiatives'!$C:$C,'Gap Analysis update'!$B$7) -> 0 | AL13: =SUMIFS('MoDi Initiatives'!R:R,'MoDi Initiatives'!$E:$E,'Gap Analysis update'!$B13,'MoDi Initiatives'!$A:$A,'Gap Analysis update'!$A13,'MoDi Initiatives'!$B:$B,'Gap Analysis update'!AL$2)-SUMIFS('MoDi Initiatives'!R:R,'MoDi Initiatives'!$E:$E,'Gap Analysis update'!$B13,'MoDi Initiatives'!$A:$A,'Gap Analysis update'!$A13,'MoDi Initiatives'!$B:$B,'Gap Analysis update'!AL$2,'MoDi Initiatives'!$C:$C,'Gap Analysis update'!$B$7) -> 0 | AM13: =SUMIFS('MoDi Initiatives'!S:S,'MoDi Initiatives'!$E:$E,'Gap Analysis update'!$B13,'MoDi Initiatives'!$A:$A,'Gap Analysis update'!$A13,'MoDi Initiatives'!$B:$B,'Gap Analysis update'!AM$2)-SUMIFS('MoDi Initiatives'!S:S,'MoDi Initiatives'!$E:$E,'Gap Analysis update'!$B13,'MoDi Initiatives'!$A:$A,'Gap Analysis update'!$A13,'MoDi Initiatives'!$B:$B,'Gap Analysis update'!AM$2,'MoDi Initiatives'!$C:$C,'Gap Analysis update'!$B$7) -> 0 | AN13: =SUMIFS('MoDi Initiatives'!T:T,'MoDi Initiatives'!$E:$E,'Gap Analysis update'!$B13,'MoDi Initiatives'!$A:$A,'Gap Analysis update'!$A13,'MoDi Initiatives'!$B:$B,'Gap Analysis update'!AN$2)-SUMIFS('MoDi Initiatives'!T:T,'MoDi Initiatives'!$E:$E,'Gap Analysis update'!$B13,'MoDi Initiatives'!$A:$A,'Gap Analysis update'!$A13,'MoDi Initiatives'!$B:$B,'Gap Analysis update'!AN$2,'MoDi Initiatives'!$C:$C,'Gap Analysis update'!$B$7) -> 0 | AO13: =SUMIFS('MoDi Initiatives'!U:U,'MoDi Initiatives'!$E:$E,'Gap Analysis update'!$B13,'MoDi Initiatives'!$A:$A,'Gap Analysis update'!$A13,'MoDi Initiatives'!$B:$B,'Gap Analysis update'!AO$2)-SUMIFS('MoDi Initiatives'!U:U,'MoDi Initiatives'!$E:$E,'Gap Analysis update'!$B13,'MoDi Initiatives'!$A:$A,'Gap Analysis update'!$A13,'MoDi Initiatives'!$B:$B,'Gap Analysis update'!AO$2,'MoDi Initiatives'!$C:$C,'Gap Analysis update'!$B$7) -> 0 | AP13: =SUMIFS('MoDi Initiatives'!V:V,'MoDi Initiatives'!$E:$E,'Gap Analysis update'!$B13,'MoDi Initiatives'!$A:$A,'Gap Analysis update'!$A13,'MoDi Initiatives'!$B:$B,'Gap Analysis update'!AP$2)-SUMIFS('MoDi Initiatives'!V:V,'MoDi Initiatives'!$E:$E,'Gap Analysis update'!$B13,'MoDi Initiatives'!$A:$A,'Gap Analysis update'!$A13,'MoDi Initiatives'!$B:$B,'Gap Analysis update'!AP$2,'MoDi Initiatives'!$C:$C,'Gap Analysis update'!$B$7) -> 0 | AQ13: =SUMIFS('MoDi Initiatives'!W:W,'MoDi Initiatives'!$E:$E,'Gap Analysis update'!$B13,'MoDi Initiatives'!$A:$A,'Gap Analysis update'!$A13,'MoDi Initiatives'!$B:$B,'Gap Analysis update'!AQ$2)-SUMIFS('MoDi Initiatives'!W:W,'MoDi Initiatives'!$E:$E,'Gap Analysis update'!$B13,'MoDi Initiatives'!$A:$A,'Gap Analysis update'!$A13,'MoDi Initiatives'!$B:$B,'Gap Analysis update'!AQ$2,'MoDi Initiatives'!$C:$C,'Gap Analysis update'!$B$7) -> 0 | AT13: =AB13-J13 -> -0.00012002949 | AU13: =AC13-K13 -> 0.0066977551 | AV13: =AD13-L13 -> -0.00014019283 | AW13: =AE13-M13 -> 0 | AX13: =AF13-N13 -> -2.3310074e-05 | AY13: =AG13-O13 -> 0 | AZ13: =AH13-P13 -> -6.958231e-06 | BA13: =AI13-Q13 -> -0.00013378556 | ... BI13: =AQ13-Y13 -> 0 | BM13: TML Improvement(1%->0.8%) | BN13: TML | BO13: TML | BQ13: Inflation | BS13: TML | BT13: TML | BU13: 1. Stretch -0.96p(coplan); 2. Inflation DL0.99P.(Actual)
A14: PEN 800 Full 2.0 | B14: FCA: | C14: =AI14-Q14 -> -0.026655779 | D14: =AQ14-Y14-C14 -> 0.0055331314 | E14: =D14+C14 -> -0.021122648 | I14: 1.2813039 | J14: =+I14+J15+J16 -> 1.2731498 | K14: =+J14+K15+K16 -> 1.2731498 | L14: =+K14+L15+L16 -> 1.2731498 | M14: =+L14+M15+M16 -> 1.2654852 | N14: =+M14+N15+N16 -> 1.2886566 | O14: =+N14+O15+O16 -> 1.2886566 | P14: =+O14+P15+P16 -> 1.2608791 | Q14: =+P14+Q15+Q16 -> 1.2608791 | ... Y14: =+X14+Y15+Y16 -> 1.2463651 | AA14: ='[1]MoDi Initiatives'!F393 -> 1.2813039 | AB14: =+AA14+AB15+AB16 -> 1.2736523 | AC14: =+AB14+AC15+AC16 -> 1.2736509 | AD14: =+AC14+AD15+AD16 -> 1.2659015 | AE14: =+AD14+AE15+AE16 -> 1.2659015 | AF14: =+AE14+AF15+AF16 -> 1.2659015 | AG14: =+AF14+AG15+AG16 -> 1.2636001 | AH14: =+AG14+AH15+AH16 -> 1.2504486 | AI14: =+AH14+AI15+AI16 -> 1.2342233 | ... AR14: =+AQ14+AR15+AR16 -> #VALUE! | AS14: =I14-AA14 -> 0 | AT14: =AB14-J14 -> 0.00050253214 | AU14: =AC14-K14 -> 0.00050113471 | AV14: =AD14-L14 -> -0.0072482259 | AW14: =AE14-M14 -> 0.0004162917 | AX14: =AF14-N14 -> -0.022755039 | AY14: =AG14-O14 -> -0.025056464 | AZ14: =AH14-P14 -> -0.010430475 | BA14: =AI14-Q14 -> -0.026655779 | ... BI14: =AQ14-Y14 -> -0.021122648
A15: PEN 800 Full 2.0 | B15: Saving: | C15: =SUM(AT15:BA15) -> -0.0034844479 | D15: =SUM(BB15:BI15) -> -0.019648 | E15: =D15+C15 -> -0.023132448 | J15: =SUBTOTAL(9,J17:J22) -> -0.008154177 | K15: =SUBTOTAL(9,K17:K22) -> 0 | L15: =SUBTOTAL(9,L17:L22) -> 0 | M15: =SUBTOTAL(9,M17:M22) -> -0.0076645176 | N15: =SUBTOTAL(9,N17:N22) -> 0 | O15: =SUBTOTAL(9,O17:O22) -> 0 | P15: =SUBTOTAL(9,P17:P22) -> -0.027777476 | Q15: =SUBTOTAL(9,Q17:Q22) -> 0 | ... Y15: =SUBTOTAL(9,Y17:Y22) -> 0 | AB15: =SUBTOTAL(9,AB17:AB22) -> -0.0076516449 | AC15: =SUBTOTAL(9,AC17:AC22) -> -1.3974302e-06 | AD15: =SUBTOTAL(9,AD17:AD22) -> -0.0077493606 | AE15: =SUBTOTAL(9,AE17:AE22) -> 0 | AF15: =SUBTOTAL(9,AF17:AF22) -> 0 | AG15: =SUBTOTAL(9,AG17:AG22) -> -0.0023014245 | AH15: =SUBTOTAL(9,AH17:AH22) -> -0.013151487 | AI15: =SUBTOTAL(9,AI17:AI22) -> -0.016225304 | ... AQ15: =SUBTOTAL(9,AQ17:AQ22) -> 0 | AS15: =I15-AA15 -> 0 | AT15: =AB15-J15 -> 0.00050253214 | AU15: =AC15-K15 -> -1.3974302e-06 | AV15: =AD15-L15 -> -0.0077493606 | AW15: =AE15-M15 -> 0.0076645176 | AX15: =AF15-N15 -> 0 | AY15: =AG15-O15 -> -0.0023014245 | AZ15: =AH15-P15 -> 0.014625989 | BA15: =AI15-Q15 -> -0.016225304 | ... BI15: =AQ15-Y15 -> 0
A16: PEN 800 Full 2.0 | B16: Inflation | C16: =SUM(AT16:BA16) -> -0.023171331 | D16: =SUM(BB16:BI16) -> 0.025181132 | E16: =D16+C16 -> 0.0020098005 | G16: Inflation need to postpone: 1. Thimble; 2. DL. 3. Others to cancel. | J16: =SUMIFS('MoDi Initiatives'!H:H,'MoDi Initiatives'!$C:$C,'Gap Analysis update'!$B16,'MoDi Initiatives'!$A:$A,'Gap Analysis update'!$A16,'MoDi Initiatives'!$B:$B,'Gap Analysis update'!J$2) -> 0 | K16: =SUMIFS('MoDi Initiatives'!I:I,'MoDi Initiatives'!$C:$C,'Gap Analysis update'!$B16,'MoDi Initiatives'!$A:$A,'Gap Analysis update'!$A16,'MoDi Initiatives'!$B:$B,'Gap Analysis update'!K$2) -> 0 | L16: =SUMIFS('MoDi Initiatives'!J:J,'MoDi Initiatives'!$C:$C,'Gap Analysis update'!$B16,'MoDi Initiatives'!$A:$A,'Gap Analysis update'!$A16,'MoDi Initiatives'!$B:$B,'Gap Analysis update'!L$2) -> 0 | M16: =SUMIFS('MoDi Initiatives'!K:K,'MoDi Initiatives'!$C:$C,'Gap Analysis update'!$B16,'MoDi Initiatives'!$A:$A,'Gap Analysis update'!$A16,'MoDi Initiatives'!$B:$B,'Gap Analysis update'!M$2) -> 0 | N16: =SUMIFS('MoDi Initiatives'!L:L,'MoDi Initiatives'!$C:$C,'Gap Analysis update'!$B16,'MoDi Initiatives'!$A:$A,'Gap Analysis update'!$A16,'MoDi Initiatives'!$B:$B,'Gap Analysis update'!N$2) -> 0.023171331 | O16: =SUMIFS('MoDi Initiatives'!M:M,'MoDi Initiatives'!$C:$C,'Gap Analysis update'!$B16,'MoDi Initiatives'!$A:$A,'Gap Analysis update'!$A16,'MoDi Initiatives'!$B:$B,'Gap Analysis update'!O$2) -> 0 | P16: =SUMIFS('MoDi Initiatives'!N:N,'MoDi Initiatives'!$C:$C,'Gap Analysis update'!$B16,'MoDi Initiatives'!$A:$A,'Gap Analysis update'!$A16,'MoDi Initiatives'!$B:$B,'Gap Analysis update'!P$2) -> 0 | Q16: =SUMIFS('MoDi Initiatives'!O:O,'MoDi Initiatives'!$C:$C,'Gap Analysis update'!$B16,'MoDi Initiatives'!$A:$A,'Gap Analysis update'!$A16,'MoDi Initiatives'!$B:$B,'Gap Analysis update'!Q$2) -> 0 | R16: =SUMIFS('MoDi Initiatives'!P:P,'MoDi Initiatives'!$C:$C,'Gap Analysis update'!$B16,'MoDi Initiatives'!$A:$A,'Gap Analysis update'!$A16,'MoDi Initiatives'!$B:$B,'Gap Analysis update'!R$2) -> 0 | S16: =SUMIFS('MoDi Initiatives'!Q:Q,'MoDi Initiatives'!$C:$C,'Gap Analysis update'!$B16,'MoDi Initiatives'!$A:$A,'Gap Analysis update'!$A16,'MoDi Initiatives'!$B:$B,'Gap Analysis update'!S$2) -> 0 | T16: =SUMIFS('MoDi Initiatives'!R:R,'MoDi Initiatives'!$C:$C,'Gap Analysis update'!$B16,'MoDi Initiatives'!$A:$A,'Gap Analysis update'!$A16,'MoDi Initiatives'!$B:$B,'Gap Analysis update'!T$2) -> 0 | U16: =SUMIFS('MoDi Initiatives'!S:S,'MoDi Initiatives'!$C:$C,'Gap Analysis update'!$B16,'MoDi Initiatives'!$A:$A,'Gap Analysis update'!$A16,'MoDi Initiatives'!$B:$B,'Gap Analysis update'!U$2) -> 0 | V16: =SUMIFS('MoDi Initiatives'!T:T,'MoDi Initiatives'!$C:$C,'Gap Analysis update'!$B16,'MoDi Initiatives'!$A:$A,'Gap Analysis update'!$A16,'MoDi Initiatives'!$B:$B,'Gap Analysis update'!V$2) -> 0 | W16: =SUMIFS('MoDi Initiatives'!U:U,'MoDi Initiatives'!$C:$C,'Gap Analysis update'!$B16,'MoDi Initiatives'!$A:$A,'Gap Analysis update'!$A16,'MoDi Initiatives'!$B:$B,'Gap Analysis update'!W$2) -> 0 | X16: =SUMIFS('MoDi Initiatives'!V:V,'MoDi Initiatives'!$C:$C,'Gap Analysis update'!$B16,'MoDi Initiatives'!$A:$A,'Gap Analysis update'!$A16,'MoDi Initiatives'!$B:$B,'Gap Analysis update'!X$2) -> 0 | Y16: =SUMIFS('MoDi Initiatives'!W:W,'MoDi Initiatives'!$C:$C,'Gap Analysis update'!$B16,'MoDi Initiatives'!$A:$A,'Gap Analysis update'!$A16,'MoDi Initiatives'!$B:$B,'Gap Analysis update'!Y$2) -> 0 | AB16: =SUMIFS('MoDi Initiatives'!H:H,'MoDi Initiatives'!$C:$C,'Gap Analysis update'!$B16,'MoDi Initiatives'!$A:$A,'Gap Analysis update'!$A16,'MoDi Initiatives'!$B:$B,'Gap Analysis update'!AB$2) -> 0 | AC16: =SUMIFS('MoDi Initiatives'!I:I,'MoDi Initiatives'!$C:$C,'Gap Analysis update'!$B16,'MoDi Initiatives'!$A:$A,'Gap Analysis update'!$A16,'MoDi Initiatives'!$B:$B,'Gap Analysis update'!AC$2) -> 0 | AD16: =SUMIFS('MoDi Initiatives'!J:J,'MoDi Initiatives'!$C:$C,'Gap Analysis update'!$B16,'MoDi Initiatives'!$A:$A,'Gap Analysis update'!$A16,'MoDi Initiatives'!$B:$B,'Gap Analysis update'!AD$2) -> 0 | AE16: =SUMIFS('MoDi Initiatives'!K:K,'MoDi Initiatives'!$C:$C,'Gap Analysis update'!$B16,'MoDi Initiatives'!$A:$A,'Gap Analysis update'!$A16,'MoDi Initiatives'!$B:$B,'Gap Analysis update'!AE$2) -> 0 | AF16: =SUMIFS('MoDi Initiatives'!L:L,'MoDi Initiatives'!$C:$C,'Gap Analysis update'!$B16,'MoDi Initiatives'!$A:$A,'Gap Analysis update'!$A16,'MoDi Initiatives'!$B:$B,'Gap Analysis update'!AF$2) -> 0 | AG16: =SUMIFS('MoDi Initiatives'!M:M,'MoDi Initiatives'!$C:$C,'Gap Analysis update'!$B16,'MoDi Initiatives'!$A:$A,'Gap Analysis update'!$A16,'MoDi Initiatives'!$B:$B,'Gap Analysis update'!AG$2) -> 0 | AH16: =SUMIFS('MoDi Initiatives'!N:N,'MoDi Initiatives'!$C:$C,'Gap Analysis update'!$B16,'MoDi Initiatives'!$A:$A,'Gap Analysis update'!$A16,'MoDi Initiatives'!$B:$B,'Gap Analysis update'!AH$2) -> 0 | AI16: =SUMIFS('MoDi Initiatives'!O:O,'MoDi Initiatives'!$C:$C,'Gap Analysis update'!$B16,'MoDi Initiatives'!$A:$A,'Gap Analysis update'!$A16,'MoDi Initiatives'!$B:$B,'Gap Analysis update'!AI$2) -> 0 | AJ16: =SUMIFS('MoDi Initiatives'!P:P,'MoDi Initiatives'!$C:$C,'Gap Analysis update'!$B16,'MoDi Initiatives'!$A:$A,'Gap Analysis update'!$A16,'MoDi Initiatives'!$B:$B,'Gap Analysis update'!AJ$2) -> 0 | AK16: =SUMIFS('MoDi Initiatives'!Q:Q,'MoDi Initiatives'!$C:$C,'Gap Analysis update'!$B16,'MoDi Initiatives'!$A:$A,'Gap Analysis update'!$A16,'MoDi Initiatives'!$B:$B,'Gap Analysis update'!AK$2) -> 0.020370042 | AL16: =SUMIFS('MoDi Initiatives'!R:R,'MoDi Initiatives'!$C:$C,'Gap Analysis update'!$B16,'MoDi Initiatives'!$A:$A,'Gap Analysis update'!$A16,'MoDi Initiatives'!$B:$B,'Gap Analysis update'!AL$2) -> 0 | AM16: =SUMIFS('MoDi Initiatives'!S:S,'MoDi Initiatives'!$C:$C,'Gap Analysis update'!$B16,'MoDi Initiatives'!$A:$A,'Gap Analysis update'!$A16,'MoDi Initiatives'!$B:$B,'Gap Analysis update'!AM$2) -> 0.0048110893 | AN16: =SUMIFS('MoDi Initiatives'!T:T,'MoDi Initiatives'!$C:$C,'Gap Analysis update'!$B16,'MoDi Initiatives'!$A:$A,'Gap Analysis update'!$A16,'MoDi Initiatives'!$B:$B,'Gap Analysis update'!AN$2) -> 0 | AO16: =SUMIFS('MoDi Initiatives'!U:U,'MoDi Initiatives'!$C:$C,'Gap Analysis update'!$B16,'MoDi Initiatives'!$A:$A,'Gap Analysis update'!$A16,'MoDi Initiatives'!$B:$B,'Gap Analysis update'!AO$2) -> 0 | AP16: =SUMIFS('MoDi Initiatives'!V:V,'MoDi Initiatives'!$C:$C,'Gap Analysis update'!$B16,'MoDi Initiatives'!$A:$A,'Gap Analysis update'!$A16,'MoDi Initiatives'!$B:$B,'Gap Analysis update'!AP$2) -> 0 | AQ16: =SUMIFS('MoDi Initiatives'!W:W,'MoDi Initiatives'!$C:$C,'Gap Analysis update'!$B16,'MoDi Initiatives'!$A:$A,'Gap Analysis update'!$A16,'MoDi Initiatives'!$B:$B,'Gap Analysis update'!AQ$2) -> 0 | AR16: =SUMIFS('[1]MoDi Initiatives'!W:W,'[1]MoDi Initiatives'!$B:$B,'Gap Analysis update'!AR$2,'[1]MoDi Initiatives'!$A:$A,'Gap Analysis update'!$A16,'[1]MoDi Initiatives'!$C:$C,"Inflation") -> #VALUE! | AS16: =I16-AA16 -> 0 | AT16: =AB16-J16 -> 0 | AU16: =AC16-K16 -> 0 | AV16: =AD16-L16 -> 0 | AW16: =AE16-M16 -> 0 | AX16: =AF16-N16 -> -0.023171331 | AY16: =AG16-O16 -> 0 | AZ16: =AH16-P16 -> 0 | BA16: =AI16-Q16 -> 0 | ... BI16: =AQ16-Y16 -> 0
A17: PEN 800 Full 2.0 | B17: Mechanical Parts | C17: =SUM(AS17:BA17) -> 0 | D17: =SUM(BB17:BI17) -> 0 | E17: =D17+C17 -> 0 | F17: Gap: 3.12P: 1. COE : Gap 3.12P; 1) Target: -3.91P.(-2.93p stretch & -0.98p VSM) 1) Achieve: -0.78p 2) Gap:3.12P. Reason: 1) 0.25P from duel source with lower cavity. 2) Other VSM -0.05P exceeds. 3) Coplan SOP6 Stretch: 2.93p => not realize. Action: find opp to close gap. | J17: =SUMIFS('MoDi Initiatives'!H:H,'MoDi Initiatives'!$E:$E,'Gap Analysis update'!$B17,'MoDi Initiatives'!$A:$A,'Gap Analysis update'!$A17,'MoDi Initiatives'!$B:$B,'Gap Analysis update'!J$2)-SUMIFS('MoDi Initiatives'!H:H,'MoDi Initiatives'!$E:$E,'Gap Analysis update'!$B17,'MoDi Initiatives'!$A:$A,'Gap Analysis update'!$A17,'MoDi Initiatives'!$C:$C,'Gap Analysis update'!$B$7,'MoDi Initiatives'!$B:$B,'Gap Analysis update'!J$2) -> 0 | K17: =SUMIFS('MoDi Initiatives'!I:I,'MoDi Initiatives'!$E:$E,'Gap Analysis update'!$B17,'MoDi Initiatives'!$A:$A,'Gap Analysis update'!$A17,'MoDi Initiatives'!$B:$B,'Gap Analysis update'!K$2)-SUMIFS('MoDi Initiatives'!I:I,'MoDi Initiatives'!$E:$E,'Gap Analysis update'!$B17,'MoDi Initiatives'!$A:$A,'Gap Analysis update'!$A17,'MoDi Initiatives'!$C:$C,'Gap Analysis update'!$B$7,'MoDi Initiatives'!$B:$B,'Gap Analysis update'!K$2) -> 0 | L17: =SUMIFS('MoDi Initiatives'!J:J,'MoDi Initiatives'!$E:$E,'Gap Analysis update'!$B17,'MoDi Initiatives'!$A:$A,'Gap Analysis update'!$A17,'MoDi Initiatives'!$B:$B,'Gap Analysis update'!L$2)-SUMIFS('MoDi Initiatives'!J:J,'MoDi Initiatives'!$E:$E,'Gap Analysis update'!$B17,'MoDi Initiatives'!$A:$A,'Gap Analysis update'!$A17,'MoDi Initiatives'!$C:$C,'Gap Analysis update'!$B$7,'MoDi Initiatives'!$B:$B,'Gap Analysis update'!L$2) -> 0 | M17: =SUMIFS('MoDi Initiatives'!K:K,'MoDi Initiatives'!$E:$E,'Gap Analysis update'!$B17,'MoDi Initiatives'!$A:$A,'Gap Analysis update'!$A17,'MoDi Initiatives'!$B:$B,'Gap Analysis update'!M$2)-SUMIFS('MoDi Initiatives'!K:K,'MoDi Initiatives'!$E:$E,'Gap Analysis update'!$B17,'MoDi Initiatives'!$A:$A,'Gap Analysis update'!$A17,'MoDi Initiatives'!$C:$C,'Gap Analysis update'!$B$7,'MoDi Initiatives'!$B:$B,'Gap Analysis update'!M$2) -> 0 | N17: =SUMIFS('MoDi Initiatives'!L:L,'MoDi Initiatives'!$E:$E,'Gap Analysis update'!$B17,'MoDi Initiatives'!$A:$A,'Gap Analysis update'!$A17,'MoDi Initiatives'!$B:$B,'Gap Analysis update'!N$2)-SUMIFS('MoDi Initiatives'!L:L,'MoDi Initiatives'!$E:$E,'Gap Analysis update'!$B17,'MoDi Initiatives'!$A:$A,'Gap Analysis update'!$A17,'MoDi Initiatives'!$C:$C,'Gap Analysis update'!$B$7,'MoDi Initiatives'!$B:$B,'Gap Analysis update'!N$2) -> 0 | O17: =SUMIFS('MoDi Initiatives'!M:M,'MoDi Initiatives'!$E:$E,'Gap Analysis update'!$B17,'MoDi Initiatives'!$A:$A,'Gap Analysis update'!$A17,'MoDi Initiatives'!$B:$B,'Gap Analysis update'!O$2)-SUMIFS('MoDi Initiatives'!M:M,'MoDi Initiatives'!$E:$E,'Gap Analysis update'!$B17,'MoDi Initiatives'!$A:$A,'Gap Analysis update'!$A17,'MoDi Initiatives'!$C:$C,'Gap Analysis update'!$B$7,'MoDi Initiatives'!$B:$B,'Gap Analysis update'!O$2) -> 0 | P17: =SUMIFS('MoDi Initiatives'!N:N,'MoDi Initiatives'!$E:$E,'Gap Analysis update'!$B17,'MoDi Initiatives'!$A:$A,'Gap Analysis update'!$A17,'MoDi Initiatives'!$B:$B,'Gap Analysis update'!P$2)-SUMIFS('MoDi Initiatives'!N:N,'MoDi Initiatives'!$E:$E,'Gap Analysis update'!$B17,'MoDi Initiatives'!$A:$A,'Gap Analysis update'!$A17,'MoDi Initiatives'!$C:$C,'Gap Analysis update'!$B$7,'MoDi Initiatives'!$B:$B,'Gap Analysis update'!P$2) -> 0 | Q17: =SUMIFS('MoDi Initiatives'!O:O,'MoDi Initiatives'!$E:$E,'Gap Analysis update'!$B17,'MoDi Initiatives'!$A:$A,'Gap Analysis update'!$A17,'MoDi Initiatives'!$B:$B,'Gap Analysis update'!Q$2)-SUMIFS('MoDi Initiatives'!O:O,'MoDi Initiatives'!$E:$E,'Gap Analysis update'!$B17,'MoDi Initiatives'!$A:$A,'Gap Analysis update'!$A17,'MoDi Initiatives'!$C:$C,'Gap Analysis update'!$B$7,'MoDi Initiatives'!$B:$B,'Gap Analysis update'!Q$2) -> 0 | R17: =SUMIFS('MoDi Initiatives'!P:P,'MoDi Initiatives'!$E:$E,'Gap Analysis update'!$B17,'MoDi Initiatives'!$A:$A,'Gap Analysis update'!$A17,'MoDi Initiatives'!$B:$B,'Gap Analysis update'!R$2)-SUMIFS('MoDi Initiatives'!P:P,'MoDi Initiatives'!$E:$E,'Gap Analysis update'!$B17,'MoDi Initiatives'!$A:$A,'Gap Analysis update'!$A17,'MoDi Initiatives'!$C:$C,'Gap Analysis update'!$B$7,'MoDi Initiatives'!$B:$B,'Gap Analysis update'!R$2) -> 0 | S17: =SUMIFS('MoDi Initiatives'!Q:Q,'MoDi Initiatives'!$E:$E,'Gap Analysis update'!$B17,'MoDi Initiatives'!$A:$A,'Gap Analysis update'!$A17,'MoDi Initiatives'!$B:$B,'Gap Analysis update'!S$2)-SUMIFS('MoDi Initiatives'!Q:Q,'MoDi Initiatives'!$E:$E,'Gap Analysis update'!$B17,'MoDi Initiatives'!$A:$A,'Gap Analysis update'!$A17,'MoDi Initiatives'!$C:$C,'Gap Analysis update'!$B$7,'MoDi Initiatives'!$B:$B,'Gap Analysis update'!S$2) -> 0 | T17: =SUMIFS('MoDi Initiatives'!R:R,'MoDi Initiatives'!$E:$E,'Gap Analysis update'!$B17,'MoDi Initiatives'!$A:$A,'Gap Analysis update'!$A17,'MoDi Initiatives'!$B:$B,'Gap Analysis update'!T$2)-SUMIFS('MoDi Initiatives'!R:R,'MoDi Initiatives'!$E:$E,'Gap Analysis update'!$B17,'MoDi Initiatives'!$A:$A,'Gap Analysis update'!$A17,'MoDi Initiatives'!$C:$C,'Gap Analysis update'!$B$7,'MoDi Initiatives'!$B:$B,'Gap Analysis update'!T$2) -> 0 | U17: =SUMIFS('MoDi Initiatives'!S:S,'MoDi Initiatives'!$E:$E,'Gap Analysis update'!$B17,'MoDi Initiatives'!$A:$A,'Gap Analysis update'!$A17,'MoDi Initiatives'!$B:$B,'Gap Analysis update'!U$2)-SUMIFS('MoDi Initiatives'!S:S,'MoDi Initiatives'!$E:$E,'Gap Analysis update'!$B17,'MoDi Initiatives'!$A:$A,'Gap Analysis update'!$A17,'MoDi Initiatives'!$C:$C,'Gap Analysis update'!$B$7,'MoDi Initiatives'!$B:$B,'Gap Analysis update'!U$2) -> 0 | V17: =SUMIFS('MoDi Initiatives'!T:T,'MoDi Initiatives'!$E:$E,'Gap Analysis update'!$B17,'MoDi Initiatives'!$A:$A,'Gap Analysis update'!$A17,'MoDi Initiatives'!$B:$B,'Gap Analysis update'!V$2)-SUMIFS('MoDi Initiatives'!T:T,'MoDi Initiatives'!$E:$E,'Gap Analysis update'!$B17,'MoDi Initiatives'!$A:$A,'Gap Analysis update'!$A17,'MoDi Initiatives'!$C:$C,'Gap Analysis update'!$B$7,'MoDi Initiatives'!$B:$B,'Gap Analysis update'!V$2) -> 0 | W17: =SUMIFS('MoDi Initiatives'!U:U,'MoDi Initiatives'!$E:$E,'Gap Analysis update'!$B17,'MoDi Initiatives'!$A:$A,'Gap Analysis update'!$A17,'MoDi Initiatives'!$B:$B,'Gap Analysis update'!W$2)-SUMIFS('MoDi Initiatives'!U:U,'MoDi Initiatives'!$E:$E,'Gap Analysis update'!$B17,'MoDi Initiatives'!$A:$A,'Gap Analysis update'!$A17,'MoDi Initiatives'!$C:$C,'Gap Analysis update'!$B$7,'MoDi Initiatives'!$B:$B,'Gap Analysis update'!W$2) -> 0 | X17: =SUMIFS('MoDi Initiatives'!V:V,'MoDi Initiatives'!$E:$E,'Gap Analysis update'!$B17,'MoDi Initiatives'!$A:$A,'Gap Analysis update'!$A17,'MoDi Initiatives'!$B:$B,'Gap Analysis update'!X$2)-SUMIFS('MoDi Initiatives'!V:V,'MoDi Initiatives'!$E:$E,'Gap Analysis update'!$B17,'MoDi Initiatives'!$A:$A,'Gap Analysis update'!$A17,'MoDi Initiatives'!$C:$C,'Gap Analysis update'!$B$7,'MoDi Initiatives'!$B:$B,'Gap Analysis update'!X$2) -> 0 | Y17: =SUMIFS('MoDi Initiatives'!W:W,'MoDi Initiatives'!$E:$E,'Gap Analysis update'!$B17,'MoDi Initiatives'!$A:$A,'Gap Analysis update'!$A17,'MoDi Initiatives'!$B:$B,'Gap Analysis update'!Y$2)-SUMIFS('MoDi Initiatives'!W:W,'MoDi Initiatives'!$E:$E,'Gap Analysis update'!$B17,'MoDi Initiatives'!$A:$A,'Gap Analysis update'!$A17,'MoDi Initiatives'!$C:$C,'Gap Analysis update'!$B$7,'MoDi Initiatives'!$B:$B,'Gap Analysis update'!Y$2) -> 0 | AB17: =SUMIFS('MoDi Initiatives'!H:H,'MoDi Initiatives'!$E:$E,'Gap Analysis update'!$B17,'MoDi Initiatives'!$A:$A,'Gap Analysis update'!$A17,'MoDi Initiatives'!$B:$B,'Gap Analysis update'!AB$2)-SUMIFS('MoDi Initiatives'!H:H,'MoDi Initiatives'!$E:$E,'Gap Analysis update'!$B17,'MoDi Initiatives'!$A:$A,'Gap Analysis update'!$A17,'MoDi Initiatives'!$B:$B,'Gap Analysis update'!AB$2,'MoDi Initiatives'!$C:$C,'Gap Analysis update'!$B$7) -> 0 | AC17: =SUMIFS('MoDi Initiatives'!I:I,'MoDi Initiatives'!$E:$E,'Gap Analysis update'!$B17,'MoDi Initiatives'!$A:$A,'Gap Analysis update'!$A17,'MoDi Initiatives'!$B:$B,'Gap Analysis update'!AC$2)-SUMIFS('MoDi Initiatives'!I:I,'MoDi Initiatives'!$E:$E,'Gap Analysis update'!$B17,'MoDi Initiatives'!$A:$A,'Gap Analysis update'!$A17,'MoDi Initiatives'!$B:$B,'Gap Analysis update'!AC$2,'MoDi Initiatives'!$C:$C,'Gap Analysis update'!$B$7) -> 0 | AD17: =SUMIFS('MoDi Initiatives'!J:J,'MoDi Initiatives'!$E:$E,'Gap Analysis update'!$B17,'MoDi Initiatives'!$A:$A,'Gap Analysis update'!$A17,'MoDi Initiatives'!$B:$B,'Gap Analysis update'!AD$2)-SUMIFS('MoDi Initiatives'!J:J,'MoDi Initiatives'!$E:$E,'Gap Analysis update'!$B17,'MoDi Initiatives'!$A:$A,'Gap Analysis update'!$A17,'MoDi Initiatives'!$B:$B,'Gap Analysis update'!AD$2,'MoDi Initiatives'!$C:$C,'Gap Analysis update'!$B$7) -> 0 | AE17: =SUMIFS('MoDi Initiatives'!K:K,'MoDi Initiatives'!$E:$E,'Gap Analysis update'!$B17,'MoDi Initiatives'!$A:$A,'Gap Analysis update'!$A17,'MoDi Initiatives'!$B:$B,'Gap Analysis update'!AE$2)-SUMIFS('MoDi Initiatives'!K:K,'MoDi Initiatives'!$E:$E,'Gap Analysis update'!$B17,'MoDi Initiatives'!$A:$A,'Gap Analysis update'!$A17,'MoDi Initiatives'!$B:$B,'Gap Analysis update'!AE$2,'MoDi Initiatives'!$C:$C,'Gap Analysis update'!$B$7) -> 0 | AF17: =SUMIFS('MoDi Initiatives'!L:L,'MoDi Initiatives'!$E:$E,'Gap Analysis update'!$B17,'MoDi Initiatives'!$A:$A,'Gap Analysis update'!$A17,'MoDi Initiatives'!$B:$B,'Gap Analysis update'!AF$2)-SUMIFS('MoDi Initiatives'!L:L,'MoDi Initiatives'!$E:$E,'Gap Analysis update'!$B17,'MoDi Initiatives'!$A:$A,'Gap Analysis update'!$A17,'MoDi Initiatives'!$B:$B,'Gap Analysis update'!AF$2,'MoDi Initiatives'!$C:$C,'Gap Analysis update'!$B$7) -> 0 | AG17: =SUMIFS('MoDi Initiatives'!M:M,'MoDi Initiatives'!$E:$E,'Gap Analysis update'!$B17,'MoDi Initiatives'!$A:$A,'Gap Analysis update'!$A17,'MoDi Initiatives'!$B:$B,'Gap Analysis update'!AG$2)-SUMIFS('MoDi Initiatives'!M:M,'MoDi Initiatives'!$E:$E,'Gap Analysis update'!$B17,'MoDi Initiatives'!$A:$A,'Gap Analysis update'!$A17,'MoDi Initiatives'!$B:$B,'Gap Analysis update'!AG$2,'MoDi Initiatives'!$C:$C,'Gap Analysis update'!$B$7) -> 0 | AH17: =SUMIFS('MoDi Initiatives'!N:N,'MoDi Initiatives'!$E:$E,'Gap Analysis update'!$B17,'MoDi Initiatives'!$A:$A,'Gap Analysis update'!$A17,'MoDi Initiatives'!$B:$B,'Gap Analysis update'!AH$2)-SUMIFS('MoDi Initiatives'!N:N,'MoDi Initiatives'!$E:$E,'Gap Analysis update'!$B17,'MoDi Initiatives'!$A:$A,'Gap Analysis update'!$A17,'MoDi Initiatives'!$B:$B,'Gap Analysis update'!AH$2,'MoDi Initiatives'!$C:$C,'Gap Analysis update'!$B$7) -> 0 | AI17: =SUMIFS('MoDi Initiatives'!O:O,'MoDi Initiatives'!$E:$E,'Gap Analysis update'!$B17,'MoDi Initiatives'!$A:$A,'Gap Analysis update'!$A17,'MoDi Initiatives'!$B:$B,'Gap Analysis update'!AI$2)-SUMIFS('MoDi Initiatives'!O:O,'MoDi Initiatives'!$E:$E,'Gap Analysis update'!$B17,'MoDi Initiatives'!$A:$A,'Gap Analysis update'!$A17,'MoDi Initiatives'!$B:$B,'Gap Analysis update'!AI$2,'MoDi Initiatives'!$C:$C,'Gap Analysis update'!$B$7) -> 0 | AJ17: =SUMIFS('MoDi Initiatives'!P:P,'MoDi Initiatives'!$E:$E,'Gap Analysis update'!$B17,'MoDi Initiatives'!$A:$A,'Gap Analysis update'!$A17,'MoDi Initiatives'!$B:$B,'Gap Analysis update'!AJ$2)-SUMIFS('MoDi Initiatives'!P:P,'MoDi Initiatives'!$E:$E,'Gap Analysis update'!$B17,'MoDi Initiatives'!$A:$A,'Gap Analysis update'!$A17,'MoDi Initiatives'!$B:$B,'Gap Analysis update'!AJ$2,'MoDi Initiatives'!$C:$C,'Gap Analysis update'!$B$7) -> 0 | AK17: =SUMIFS('MoDi Initiatives'!Q:Q,'MoDi Initiatives'!$E:$E,'Gap Analysis update'!$B17,'MoDi Initiatives'!$A:$A,'Gap Analysis update'!$A17,'MoDi Initiatives'!$B:$B,'Gap Analysis update'!AK$2)-SUMIFS('MoDi Initiatives'!Q:Q,'MoDi Initiatives'!$E:$E,'Gap Analysis update'!$B17,'MoDi Initiatives'!$A:$A,'Gap Analysis update'!$A17,'MoDi Initiatives'!$B:$B,'Gap Analysis update'!AK$2,'MoDi Initiatives'!$C:$C,'Gap Analysis update'!$B$7) -> 0 | AL17: =SUMIFS('MoDi Initiatives'!R:R,'MoDi Initiatives'!$E:$E,'Gap Analysis update'!$B17,'MoDi Initiatives'!$A:$A,'Gap Analysis update'!$A17,'MoDi Initiatives'!$B:$B,'Gap Analysis update'!AL$2)-SUMIFS('MoDi Initiatives'!R:R,'MoDi Initiatives'!$E:$E,'Gap Analysis update'!$B17,'MoDi Initiatives'!$A:$A,'Gap Analysis update'!$A17,'MoDi Initiatives'!$B:$B,'Gap Analysis update'!AL$2,'MoDi Initiatives'!$C:$C,'Gap Analysis update'!$B$7) -> 0 | AM17: =SUMIFS('MoDi Initiatives'!S:S,'MoDi Initiatives'!$E:$E,'Gap Analysis update'!$B17,'MoDi Initiatives'!$A:$A,'Gap Analysis update'!$A17,'MoDi Initiatives'!$B:$B,'Gap Analysis update'!AM$2)-SUMIFS('MoDi Initiatives'!S:S,'MoDi Initiatives'!$E:$E,'Gap Analysis update'!$B17,'MoDi Initiatives'!$A:$A,'Gap Analysis update'!$A17,'MoDi Initiatives'!$B:$B,'Gap Analysis update'!AM$2,'MoDi Initiatives'!$C:$C,'Gap Analysis update'!$B$7) -> 0 | AN17: =SUMIFS('MoDi Initiatives'!T:T,'MoDi Initiatives'!$E:$E,'Gap Analysis update'!$B17,'MoDi Initiatives'!$A:$A,'Gap Analysis update'!$A17,'MoDi Initiatives'!$B:$B,'Gap Analysis update'!AN$2)-SUMIFS('MoDi Initiatives'!T:T,'MoDi Initiatives'!$E:$E,'Gap Analysis update'!$B17,'MoDi Initiatives'!$A:$A,'Gap Analysis update'!$A17,'MoDi Initiatives'!$B:$B,'Gap Analysis update'!AN$2,'MoDi Initiatives'!$C:$C,'Gap Analysis update'!$B$7) -> 0 | AO17: =SUMIFS('MoDi Initiatives'!U:U,'MoDi Initiatives'!$E:$E,'Gap Analysis update'!$B17,'MoDi Initiatives'!$A:$A,'Gap Analysis update'!$A17,'MoDi Initiatives'!$B:$B,'Gap Analysis update'!AO$2)-SUMIFS('MoDi Initiatives'!U:U,'MoDi Initiatives'!$E:$E,'Gap Analysis update'!$B17,'MoDi Initiatives'!$A:$A,'Gap Analysis update'!$A17,'MoDi Initiatives'!$B:$B,'Gap Analysis update'!AO$2,'MoDi Initiatives'!$C:$C,'Gap Analysis update'!$B$7) -> 0 | AP17: =SUMIFS('MoDi Initiatives'!V:V,'MoDi Initiatives'!$E:$E,'Gap Analysis update'!$B17,'MoDi Initiatives'!$A:$A,'Gap Analysis update'!$A17,'MoDi Initiatives'!$B:$B,'Gap Analysis update'!AP$2)-SUMIFS('MoDi Initiatives'!V:V,'MoDi Initiatives'!$E:$E,'Gap Analysis update'!$B17,'MoDi Initiatives'!$A:$A,'Gap Analysis update'!$A17,'MoDi Initiatives'!$B:$B,'Gap Analysis update'!AP$2,'MoDi Initiatives'!$C:$C,'Gap Analysis update'!$B$7) -> 0 | AQ17: =SUMIFS('MoDi Initiatives'!W:W,'MoDi Initiatives'!$E:$E,'Gap Analysis update'!$B17,'MoDi Initiatives'!$A:$A,'Gap Analysis update'!$A17,'MoDi Initiatives'!$B:$B,'Gap Analysis update'!AQ$2)-SUMIFS('MoDi Initiatives'!W:W,'MoDi Initiatives'!$E:$E,'Gap Analysis update'!$B17,'MoDi Initiatives'!$A:$A,'Gap Analysis update'!$A17,'MoDi Initiatives'!$B:$B,'Gap Analysis update'!AQ$2,'MoDi Initiatives'!$C:$C,'Gap Analysis update'!$B$7) -> 0 | AT17: =AB17-J17 -> 0 | AU17: =AC17-K17 -> 0 | AV17: =AD17-L17 -> 0 | AW17: =AE17-M17 -> 0 | AX17: =AF17-N17 -> 0 | AY17: =AG17-O17 -> 0 | AZ17: =AH17-P17 -> 0 | BA17: =AI17-Q17 -> 0 | ... BI17: =AQ17-Y17 -> 0 | BL17: 1. Coplan:Fengyi wrapping: -0.02p; 2. Pen full duel source button: 0.25p(actual) | BM17: Protective shell cost down | BN17: Protective shell cost down | BP17: Inflation | BQ17: Stretch | BR17: TK plastic cost saving | BS17: 1. Stretch 1.95p; 2. TFK&MGC cost down-0.05p | BT17: Inflation
A18: PEN 800 Full 2.0 | B18: Electronics | C18: =SUM(AS18:BA18) -> -0.00081650492 | D18: =SUM(BB18:BI18) -> -0.021777025 | E18: =D18+C18 -> -0.02259353 | F18: Gap: -0.08P (Exceed): 1. Battery: Target: -2.06p, realized -2.37p, -0.31p exceed. (July'24: 0.05p gap less; Jan'25 0.36p better) 2. PCBA: gap 0.23p in Jan'25. Action: find opp to close PCBA Gap. | G18: Highlight: battery -0.68p target cost down in Jul'25, actual nego price to monitor. (Jan'25 exceeds target) | J18: =SUMIFS('MoDi Initiatives'!H:H,'MoDi Initiatives'!$E:$E,'Gap Analysis update'!$B18,'MoDi Initiatives'!$A:$A,'Gap Analysis update'!$A18,'MoDi Initiatives'!$B:$B,'Gap Analysis update'!J$2)-SUMIFS('MoDi Initiatives'!H:H,'MoDi Initiatives'!$E:$E,'Gap Analysis update'!$B18,'MoDi Initiatives'!$A:$A,'Gap Analysis update'!$A18,'MoDi Initiatives'!$C:$C,'Gap Analysis update'!$B$7,'MoDi Initiatives'!$B:$B,'Gap Analysis update'!J$2) -> -0.008154177 | K18: =SUMIFS('MoDi Initiatives'!I:I,'MoDi Initiatives'!$E:$E,'Gap Analysis update'!$B18,'MoDi Initiatives'!$A:$A,'Gap Analysis update'!$A18,'MoDi Initiatives'!$B:$B,'Gap Analysis update'!K$2)-SUMIFS('MoDi Initiatives'!I:I,'MoDi Initiatives'!$E:$E,'Gap Analysis update'!$B18,'MoDi Initiatives'!$A:$A,'Gap Analysis update'!$A18,'MoDi Initiatives'!$C:$C,'Gap Analysis update'!$B$7,'MoDi Initiatives'!$B:$B,'Gap Analysis update'!K$2) -> 0 | L18: =SUMIFS('MoDi Initiatives'!J:J,'MoDi Initiatives'!$E:$E,'Gap Analysis update'!$B18,'MoDi Initiatives'!$A:$A,'Gap Analysis update'!$A18,'MoDi Initiatives'!$B:$B,'Gap Analysis update'!L$2)-SUMIFS('MoDi Initiatives'!J:J,'MoDi Initiatives'!$E:$E,'Gap Analysis update'!$B18,'MoDi Initiatives'!$A:$A,'Gap Analysis update'!$A18,'MoDi Initiatives'!$C:$C,'Gap Analysis update'!$B$7,'MoDi Initiatives'!$B:$B,'Gap Analysis update'!L$2) -> 0 | M18: =SUMIFS('MoDi Initiatives'!K:K,'MoDi Initiatives'!$E:$E,'Gap Analysis update'!$B18,'MoDi Initiatives'!$A:$A,'Gap Analysis update'!$A18,'MoDi Initiatives'!$B:$B,'Gap Analysis update'!M$2)-SUMIFS('MoDi Initiatives'!K:K,'MoDi Initiatives'!$E:$E,'Gap Analysis update'!$B18,'MoDi Initiatives'!$A:$A,'Gap Analysis update'!$A18,'MoDi Initiatives'!$C:$C,'Gap Analysis update'!$B$7,'MoDi Initiatives'!$B:$B,'Gap Analysis update'!M$2) -> 0 | N18: =SUMIFS('MoDi Initiatives'!L:L,'MoDi Initiatives'!$E:$E,'Gap Analysis update'!$B18,'MoDi Initiatives'!$A:$A,'Gap Analysis update'!$A18,'MoDi Initiatives'!$B:$B,'Gap Analysis update'!N$2)-SUMIFS('MoDi Initiatives'!L:L,'MoDi Initiatives'!$E:$E,'Gap Analysis update'!$B18,'MoDi Initiatives'!$A:$A,'Gap Analysis update'!$A18,'MoDi Initiatives'!$C:$C,'Gap Analysis update'!$B$7,'MoDi Initiatives'!$B:$B,'Gap Analysis update'!N$2) -> 0 | O18: =SUMIFS('MoDi Initiatives'!M:M,'MoDi Initiatives'!$E:$E,'Gap Analysis update'!$B18,'MoDi Initiatives'!$A:$A,'Gap Analysis update'!$A18,'MoDi Initiatives'!$B:$B,'Gap Analysis update'!O$2)-SUMIFS('MoDi Initiatives'!M:M,'MoDi Initiatives'!$E:$E,'Gap Analysis update'!$B18,'MoDi Initiatives'!$A:$A,'Gap Analysis update'!$A18,'MoDi Initiatives'!$C:$C,'Gap Analysis update'!$B$7,'MoDi Initiatives'!$B:$B,'Gap Analysis update'!O$2) -> 0 | P18: =SUMIFS('MoDi Initiatives'!N:N,'MoDi Initiatives'!$E:$E,'Gap Analysis update'!$B18,'MoDi Initiatives'!$A:$A,'Gap Analysis update'!$A18,'MoDi Initiatives'!$B:$B,'Gap Analysis update'!P$2)-SUMIFS('MoDi Initiatives'!N:N,'MoDi Initiatives'!$E:$E,'Gap Analysis update'!$B18,'MoDi Initiatives'!$A:$A,'Gap Analysis update'!$A18,'MoDi Initiatives'!$C:$C,'Gap Analysis update'!$B$7,'MoDi Initiatives'!$B:$B,'Gap Analysis update'!P$2) -> -0.027777476 | Q18: =SUMIFS('MoDi Initiatives'!O:O,'MoDi Initiatives'!$E:$E,'Gap Analysis update'!$B18,'MoDi Initiatives'!$A:$A,'Gap Analysis update'!$A18,'MoDi Initiatives'!$B:$B,'Gap Analysis update'!Q$2)-SUMIFS('MoDi Initiatives'!O:O,'MoDi Initiatives'!$E:$E,'Gap Analysis update'!$B18,'MoDi Initiatives'!$A:$A,'Gap Analysis update'!$A18,'MoDi Initiatives'!$C:$C,'Gap Analysis update'!$B$7,'MoDi Initiatives'!$B:$B,'Gap Analysis update'!Q$2) -> 0 | R18: =SUMIFS('MoDi Initiatives'!P:P,'MoDi Initiatives'!$E:$E,'Gap Analysis update'!$B18,'MoDi Initiatives'!$A:$A,'Gap Analysis update'!$A18,'MoDi Initiatives'!$B:$B,'Gap Analysis update'!R$2)-SUMIFS('MoDi Initiatives'!P:P,'MoDi Initiatives'!$E:$E,'Gap Analysis update'!$B18,'MoDi Initiatives'!$A:$A,'Gap Analysis update'!$A18,'MoDi Initiatives'!$C:$C,'Gap Analysis update'!$B$7,'MoDi Initiatives'!$B:$B,'Gap Analysis update'!R$2) -> 0 | S18: =SUMIFS('MoDi Initiatives'!Q:Q,'MoDi Initiatives'!$E:$E,'Gap Analysis update'!$B18,'MoDi Initiatives'!$A:$A,'Gap Analysis update'!$A18,'MoDi Initiatives'!$B:$B,'Gap Analysis update'!S$2)-SUMIFS('MoDi Initiatives'!Q:Q,'MoDi Initiatives'!$E:$E,'Gap Analysis update'!$B18,'MoDi Initiatives'!$A:$A,'Gap Analysis update'!$A18,'MoDi Initiatives'!$C:$C,'Gap Analysis update'!$B$7,'MoDi Initiatives'!$B:$B,'Gap Analysis update'!S$2) -> 0 | T18: =SUMIFS('MoDi Initiatives'!R:R,'MoDi Initiatives'!$E:$E,'Gap Analysis update'!$B18,'MoDi Initiatives'!$A:$A,'Gap Analysis update'!$A18,'MoDi Initiatives'!$B:$B,'Gap Analysis update'!T$2)-SUMIFS('MoDi Initiatives'!R:R,'MoDi Initiatives'!$E:$E,'Gap Analysis update'!$B18,'MoDi Initiatives'!$A:$A,'Gap Analysis update'!$A18,'MoDi Initiatives'!$C:$C,'Gap Analysis update'!$B$7,'MoDi Initiatives'!$B:$B,'Gap Analysis update'!T$2) -> 0 | U18: =SUMIFS('MoDi Initiatives'!S:S,'MoDi Initiatives'!$E:$E,'Gap Analysis update'!$B18,'MoDi Initiatives'!$A:$A,'Gap Analysis update'!$A18,'MoDi Initiatives'!$B:$B,'Gap Analysis update'!U$2)-SUMIFS('MoDi Initiatives'!S:S,'MoDi Initiatives'!$E:$E,'Gap Analysis update'!$B18,'MoDi Initiatives'!$A:$A,'Gap Analysis update'!$A18,'MoDi Initiatives'!$C:$C,'Gap Analysis update'!$B$7,'MoDi Initiatives'!$B:$B,'Gap Analysis update'!U$2) -> 0 | V18: =SUMIFS('MoDi Initiatives'!T:T,'MoDi Initiatives'!$E:$E,'Gap Analysis update'!$B18,'MoDi Initiatives'!$A:$A,'Gap Analysis update'!$A18,'MoDi Initiatives'!$B:$B,'Gap Analysis update'!V$2)-SUMIFS('MoDi Initiatives'!T:T,'MoDi Initiatives'!$E:$E,'Gap Analysis update'!$B18,'MoDi Initiatives'!$A:$A,'Gap Analysis update'!$A18,'MoDi Initiatives'!$C:$C,'Gap Analysis update'!$B$7,'MoDi Initiatives'!$B:$B,'Gap Analysis update'!V$2) -> -0.0068495087 | W18: =SUMIFS('MoDi Initiatives'!U:U,'MoDi Initiatives'!$E:$E,'Gap Analysis update'!$B18,'MoDi Initiatives'!$A:$A,'Gap Analysis update'!$A18,'MoDi Initiatives'!$B:$B,'Gap Analysis update'!W$2)-SUMIFS('MoDi Initiatives'!U:U,'MoDi Initiatives'!$E:$E,'Gap Analysis update'!$B18,'MoDi Initiatives'!$A:$A,'Gap Analysis update'!$A18,'MoDi Initiatives'!$C:$C,'Gap Analysis update'!$B$7,'MoDi Initiatives'!$B:$B,'Gap Analysis update'!W$2) -> 0 | X18: =SUMIFS('MoDi Initiatives'!V:V,'MoDi Initiatives'!$E:$E,'Gap Analysis update'!$B18,'MoDi Initiatives'!$A:$A,'Gap Analysis update'!$A18,'MoDi Initiatives'!$B:$B,'Gap Analysis update'!X$2)-SUMIFS('MoDi Initiatives'!V:V,'MoDi Initiatives'!$E:$E,'Gap Analysis update'!$B18,'MoDi Initiatives'!$A:$A,'Gap Analysis update'!$A18,'MoDi Initiatives'!$C:$C,'Gap Analysis update'!$B$7,'MoDi Initiatives'!$B:$B,'Gap Analysis update'!X$2) -> 0 | Y18: =SUMIFS('MoDi Initiatives'!W:W,'MoDi Initiatives'!$E:$E,'Gap Analysis update'!$B18,'MoDi Initiatives'!$A:$A,'Gap Analysis update'!$A18,'MoDi Initiatives'!$B:$B,'Gap Analysis update'!Y$2)-SUMIFS('MoDi Initiatives'!W:W,'MoDi Initiatives'!$E:$E,'Gap Analysis update'!$B18,'MoDi Initiatives'!$A:$A,'Gap Analysis update'!$A18,'MoDi Initiatives'!$C:$C,'Gap Analysis update'!$B$7,'MoDi Initiatives'!$B:$B,'Gap Analysis update'!Y$2) -> 0 | AB18: =SUMIFS('MoDi Initiatives'!H:H,'MoDi Initiatives'!$E:$E,'Gap Analysis update'!$B18,'MoDi Initiatives'!$A:$A,'Gap Analysis update'!$A18,'MoDi Initiatives'!$B:$B,'Gap Analysis update'!AB$2)-SUMIFS('MoDi Initiatives'!H:H,'MoDi Initiatives'!$E:$E,'Gap Analysis update'!$B18,'MoDi Initiatives'!$A:$A,'Gap Analysis update'!$A18,'MoDi Initiatives'!$B:$B,'Gap Analysis update'!AB$2,'MoDi Initiatives'!$C:$C,'Gap Analysis update'!$B$7) -> -0.0076105652 | AC18: =SUMIFS('MoDi Initiatives'!I:I,'MoDi Initiatives'!$E:$E,'Gap Analysis update'!$B18,'MoDi Initiatives'!$A:$A,'Gap Analysis update'!$A18,'MoDi Initiatives'!$B:$B,'Gap Analysis update'!AC$2)-SUMIFS('MoDi Initiatives'!I:I,'MoDi Initiatives'!$E:$E,'Gap Analysis update'!$B18,'MoDi Initiatives'!$A:$A,'Gap Analysis update'!$A18,'MoDi Initiatives'!$B:$B,'Gap Analysis update'!AC$2,'MoDi Initiatives'!$C:$C,'Gap Analysis update'!$B$7) -> 0 | AD18: =SUMIFS('MoDi Initiatives'!J:J,'MoDi Initiatives'!$E:$E,'Gap Analysis update'!$B18,'MoDi Initiatives'!$A:$A,'Gap Analysis update'!$A18,'MoDi Initiatives'!$B:$B,'Gap Analysis update'!AD$2)-SUMIFS('MoDi Initiatives'!J:J,'MoDi Initiatives'!$E:$E,'Gap Analysis update'!$B18,'MoDi Initiatives'!$A:$A,'Gap Analysis update'!$A18,'MoDi Initiatives'!$B:$B,'Gap Analysis update'!AD$2,'MoDi Initiatives'!$C:$C,'Gap Analysis update'!$B$7) -> 0 | AE18: =SUMIFS('MoDi Initiatives'!K:K,'MoDi Initiatives'!$E:$E,'Gap Analysis update'!$B18,'MoDi Initiatives'!$A:$A,'Gap Analysis update'!$A18,'MoDi Initiatives'!$B:$B,'Gap Analysis update'!AE$2)-SUMIFS('MoDi Initiatives'!K:K,'MoDi Initiatives'!$E:$E,'Gap Analysis update'!$B18,'MoDi Initiatives'!$A:$A,'Gap Analysis update'!$A18,'MoDi Initiatives'!$B:$B,'Gap Analysis update'!AE$2,'MoDi Initiatives'!$C:$C,'Gap Analysis update'!$B$7) -> 0 | AF18: =SUMIFS('MoDi Initiatives'!L:L,'MoDi Initiatives'!$E:$E,'Gap Analysis update'!$B18,'MoDi Initiatives'!$A:$A,'Gap Analysis update'!$A18,'MoDi Initiatives'!$B:$B,'Gap Analysis update'!AF$2)-SUMIFS('MoDi Initiatives'!L:L,'MoDi Initiatives'!$E:$E,'Gap Analysis update'!$B18,'MoDi Initiatives'!$A:$A,'Gap Analysis update'!$A18,'MoDi Initiatives'!$B:$B,'Gap Analysis update'!AF$2,'MoDi Initiatives'!$C:$C,'Gap Analysis update'!$B$7) -> 0 | AG18: =SUMIFS('MoDi Initiatives'!M:M,'MoDi Initiatives'!$E:$E,'Gap Analysis update'!$B18,'MoDi Initiatives'!$A:$A,'Gap Analysis update'!$A18,'MoDi Initiatives'!$B:$B,'Gap Analysis update'!AG$2)-SUMIFS('MoDi Initiatives'!M:M,'MoDi Initiatives'!$E:$E,'Gap Analysis update'!$B18,'MoDi Initiatives'!$A:$A,'Gap Analysis update'!$A18,'MoDi Initiatives'!$B:$B,'Gap Analysis update'!AG$2,'MoDi Initiatives'!$C:$C,'Gap Analysis update'!$B$7) -> 0 | AH18: =SUMIFS('MoDi Initiatives'!N:N,'MoDi Initiatives'!$E:$E,'Gap Analysis update'!$B18,'MoDi Initiatives'!$A:$A,'Gap Analysis update'!$A18,'MoDi Initiatives'!$B:$B,'Gap Analysis update'!AH$2)-SUMIFS('MoDi Initiatives'!N:N,'MoDi Initiatives'!$E:$E,'Gap Analysis update'!$B18,'MoDi Initiatives'!$A:$A,'Gap Analysis update'!$A18,'MoDi Initiatives'!$B:$B,'Gap Analysis update'!AH$2,'MoDi Initiatives'!$C:$C,'Gap Analysis update'!$B$7) -> -0.013046683 | AI18: =SUMIFS('MoDi Initiatives'!O:O,'MoDi Initiatives'!$E:$E,'Gap Analysis update'!$B18,'MoDi Initiatives'!$A:$A,'Gap Analysis update'!$A18,'MoDi Initiatives'!$B:$B,'Gap Analysis update'!AI$2)-SUMIFS('MoDi Initiatives'!O:O,'MoDi Initiatives'!$E:$E,'Gap Analysis update'!$B18,'MoDi Initiatives'!$A:$A,'Gap Analysis update'!$A18,'MoDi Initiatives'!$B:$B,'Gap Analysis update'!AI$2,'MoDi Initiatives'!$C:$C,'Gap Analysis update'!$B$7) -> -0.016090909 | AJ18: =SUMIFS('MoDi Initiatives'!P:P,'MoDi Initiatives'!$E:$E,'Gap Analysis update'!$B18,'MoDi Initiatives'!$A:$A,'Gap Analysis update'!$A18,'MoDi Initiatives'!$B:$B,'Gap Analysis update'!AJ$2)-SUMIFS('MoDi Initiatives'!P:P,'MoDi Initiatives'!$E:$E,'Gap Analysis update'!$B18,'MoDi Initiatives'!$A:$A,'Gap Analysis update'!$A18,'MoDi Initiatives'!$B:$B,'Gap Analysis update'!AJ$2,'MoDi Initiatives'!$C:$C,'Gap Analysis update'!$B$7) -> 0 | AK18: =SUMIFS('MoDi Initiatives'!Q:Q,'MoDi Initiatives'!$E:$E,'Gap Analysis update'!$B18,'MoDi Initiatives'!$A:$A,'Gap Analysis update'!$A18,'MoDi Initiatives'!$B:$B,'Gap Analysis update'!AK$2)-SUMIFS('MoDi Initiatives'!Q:Q,'MoDi Initiatives'!$E:$E,'Gap Analysis update'!$B18,'MoDi Initiatives'!$A:$A,'Gap Analysis update'!$A18,'MoDi Initiatives'!$B:$B,'Gap Analysis update'!AK$2,'MoDi Initiatives'!$C:$C,'Gap Analysis update'!$B$7) -> 0 | AL18: =SUMIFS('MoDi Initiatives'!R:R,'MoDi Initiatives'!$E:$E,'Gap Analysis update'!$B18,'MoDi Initiatives'!$A:$A,'Gap Analysis update'!$A18,'MoDi Initiatives'!$B:$B,'Gap Analysis update'!AL$2)-SUMIFS('MoDi Initiatives'!R:R,'MoDi Initiatives'!$E:$E,'Gap Analysis update'!$B18,'MoDi Initiatives'!$A:$A,'Gap Analysis update'!$A18,'MoDi Initiatives'!$B:$B,'Gap Analysis update'!AL$2,'MoDi Initiatives'!$C:$C,'Gap Analysis update'!$B$7) -> 0 | AM18: =SUMIFS('MoDi Initiatives'!S:S,'MoDi Initiatives'!$E:$E,'Gap Analysis update'!$B18,'MoDi Initiatives'!$A:$A,'Gap Analysis update'!$A18,'MoDi Initiatives'!$B:$B,'Gap Analysis update'!AM$2)-SUMIFS('MoDi Initiatives'!S:S,'MoDi Initiatives'!$E:$E,'Gap Analysis update'!$B18,'MoDi Initiatives'!$A:$A,'Gap Analysis update'!$A18,'MoDi Initiatives'!$B:$B,'Gap Analysis update'!AM$2,'MoDi Initiatives'!$C:$C,'Gap Analysis update'!$B$7) -> -0.026234642 | AN18: =SUMIFS('MoDi Initiatives'!T:T,'MoDi Initiatives'!$E:$E,'Gap Analysis update'!$B18,'MoDi Initiatives'!$A:$A,'Gap Analysis update'!$A18,'MoDi Initiatives'!$B:$B,'Gap Analysis update'!AN$2)-SUMIFS('MoDi Initiatives'!T:T,'MoDi Initiatives'!$E:$E,'Gap Analysis update'!$B18,'MoDi Initiatives'!$A:$A,'Gap Analysis update'!$A18,'MoDi Initiatives'!$B:$B,'Gap Analysis update'!AN$2,'MoDi Initiatives'!$C:$C,'Gap Analysis update'!$B$7) -> -0.0023918919 | AO18: =SUMIFS('MoDi Initiatives'!U:U,'MoDi Initiatives'!$E:$E,'Gap Analysis update'!$B18,'MoDi Initiatives'!$A:$A,'Gap Analysis update'!$A18,'MoDi Initiatives'!$B:$B,'Gap Analysis update'!AO$2)-SUMIFS('MoDi Initiatives'!U:U,'MoDi Initiatives'!$E:$E,'Gap Analysis update'!$B18,'MoDi Initiatives'!$A:$A,'Gap Analysis update'!$A18,'MoDi Initiatives'!$B:$B,'Gap Analysis update'!AO$2,'MoDi Initiatives'!$C:$C,'Gap Analysis update'!$B$7) -> 0 | AP18: =SUMIFS('MoDi Initiatives'!V:V,'MoDi Initiatives'!$E:$E,'Gap Analysis update'!$B18,'MoDi Initiatives'!$A:$A,'Gap Analysis update'!$A18,'MoDi Initiatives'!$B:$B,'Gap Analysis update'!AP$2)-SUMIFS('MoDi Initiatives'!V:V,'MoDi Initiatives'!$E:$E,'Gap Analysis update'!$B18,'MoDi Initiatives'!$A:$A,'Gap Analysis update'!$A18,'MoDi Initiatives'!$B:$B,'Gap Analysis update'!AP$2,'MoDi Initiatives'!$C:$C,'Gap Analysis update'!$B$7) -> 0 | AQ18: =SUMIFS('MoDi Initiatives'!W:W,'MoDi Initiatives'!$E:$E,'Gap Analysis update'!$B18,'MoDi Initiatives'!$A:$A,'Gap Analysis update'!$A18,'MoDi Initiatives'!$B:$B,'Gap Analysis update'!AQ$2)-SUMIFS('MoDi Initiatives'!W:W,'MoDi Initiatives'!$E:$E,'Gap Analysis update'!$B18,'MoDi Initiatives'!$A:$A,'Gap Analysis update'!$A18,'MoDi Initiatives'!$B:$B,'Gap Analysis update'!AQ$2,'MoDi Initiatives'!$C:$C,'Gap Analysis update'!$B$7) -> 0 | AT18: =AB18-J18 -> 0.0005436118 | AU18: =AC18-K18 -> 0 | AV18: =AD18-L18 -> 0 | AW18: =AE18-M18 -> 0 | AX18: =AF18-N18 -> 0 | AY18: =AG18-O18 -> 0 | AZ18: =AH18-P18 -> 0.014730793 | BA18: =AI18-Q18 -> -0.016090909 | ... BI18: =AQ18-Y18 -> 0 | BL18: 1. Battery: coplan -0.82p vs actual -0.76p; | BP18: Inflation | BR18: 1. Coplan PCBA:-1.53P vs Actual -1.3p; 0.22p gap. 2. Coplan Battery -1.25p;(Delay to Feb due to inventory) | BS18: Battery actual -1.61p.(0.36p better) | BT18: Inflation | BX18: Battery Q3'25 Cost down(Corrected in SOP2 to 0.36p for actual)
A19: PEN 800 Full 2.0 | B19: Packaging | C19: =SUM(AS19:BA19) -> -0.0022831592 | D19: =SUM(BB19:BI19) -> 0.0021077423 | E19: =D19+C19 -> -0.00017541687 | F19: Unplanned Design change from EM: Flow wrap change from blank to pre-print in Dec. + Remove bottom sticker. | G19: Gap: 0.21p; Design change from EM: Flow wrap: -0.02p. | J19: =SUMIFS('MoDi Initiatives'!H:H,'MoDi Initiatives'!$E:$E,'Gap Analysis update'!$B19,'MoDi Initiatives'!$A:$A,'Gap Analysis update'!$A19,'MoDi Initiatives'!$B:$B,'Gap Analysis update'!J$2)-SUMIFS('MoDi Initiatives'!H:H,'MoDi Initiatives'!$E:$E,'Gap Analysis update'!$B19,'MoDi Initiatives'!$A:$A,'Gap Analysis update'!$A19,'MoDi Initiatives'!$C:$C,'Gap Analysis update'!$B$7,'MoDi Initiatives'!$B:$B,'Gap Analysis update'!J$2) -> 0 | K19: =SUMIFS('MoDi Initiatives'!I:I,'MoDi Initiatives'!$E:$E,'Gap Analysis update'!$B19,'MoDi Initiatives'!$A:$A,'Gap Analysis update'!$A19,'MoDi Initiatives'!$B:$B,'Gap Analysis update'!K$2)-SUMIFS('MoDi Initiatives'!I:I,'MoDi Initiatives'!$E:$E,'Gap Analysis update'!$B19,'MoDi Initiatives'!$A:$A,'Gap Analysis update'!$A19,'MoDi Initiatives'!$C:$C,'Gap Analysis update'!$B$7,'MoDi Initiatives'!$B:$B,'Gap Analysis update'!K$2) -> 0 | L19: =SUMIFS('MoDi Initiatives'!J:J,'MoDi Initiatives'!$E:$E,'Gap Analysis update'!$B19,'MoDi Initiatives'!$A:$A,'Gap Analysis update'!$A19,'MoDi Initiatives'!$B:$B,'Gap Analysis update'!L$2)-SUMIFS('MoDi Initiatives'!J:J,'MoDi Initiatives'!$E:$E,'Gap Analysis update'!$B19,'MoDi Initiatives'!$A:$A,'Gap Analysis update'!$A19,'MoDi Initiatives'!$C:$C,'Gap Analysis update'!$B$7,'MoDi Initiatives'!$B:$B,'Gap Analysis update'!L$2) -> 0 | M19: =SUMIFS('MoDi Initiatives'!K:K,'MoDi Initiatives'!$E:$E,'Gap Analysis update'!$B19,'MoDi Initiatives'!$A:$A,'Gap Analysis update'!$A19,'MoDi Initiatives'!$B:$B,'Gap Analysis update'!M$2)-SUMIFS('MoDi Initiatives'!K:K,'MoDi Initiatives'!$E:$E,'Gap Analysis update'!$B19,'MoDi Initiatives'!$A:$A,'Gap Analysis update'!$A19,'MoDi Initiatives'!$C:$C,'Gap Analysis update'!$B$7,'MoDi Initiatives'!$B:$B,'Gap Analysis update'!M$2) -> 0 | N19: =SUMIFS('MoDi Initiatives'!L:L,'MoDi Initiatives'!$E:$E,'Gap Analysis update'!$B19,'MoDi Initiatives'!$A:$A,'Gap Analysis update'!$A19,'MoDi Initiatives'!$B:$B,'Gap Analysis update'!N$2)-SUMIFS('MoDi Initiatives'!L:L,'MoDi Initiatives'!$E:$E,'Gap Analysis update'!$B19,'MoDi Initiatives'!$A:$A,'Gap Analysis update'!$A19,'MoDi Initiatives'!$C:$C,'Gap Analysis update'!$B$7,'MoDi Initiatives'!$B:$B,'Gap Analysis update'!N$2) -> 0 | O19: =SUMIFS('MoDi Initiatives'!M:M,'MoDi Initiatives'!$E:$E,'Gap Analysis update'!$B19,'MoDi Initiatives'!$A:$A,'Gap Analysis update'!$A19,'MoDi Initiatives'!$B:$B,'Gap Analysis update'!O$2)-SUMIFS('MoDi Initiatives'!M:M,'MoDi Initiatives'!$E:$E,'Gap Analysis update'!$B19,'MoDi Initiatives'!$A:$A,'Gap Analysis update'!$A19,'MoDi Initiatives'!$C:$C,'Gap Analysis update'!$B$7,'MoDi Initiatives'!$B:$B,'Gap Analysis update'!O$2) -> 0 | P19: =SUMIFS('MoDi Initiatives'!N:N,'MoDi Initiatives'!$E:$E,'Gap Analysis update'!$B19,'MoDi Initiatives'!$A:$A,'Gap Analysis update'!$A19,'MoDi Initiatives'!$B:$B,'Gap Analysis update'!P$2)-SUMIFS('MoDi Initiatives'!N:N,'MoDi Initiatives'!$E:$E,'Gap Analysis update'!$B19,'MoDi Initiatives'!$A:$A,'Gap Analysis update'!$A19,'MoDi Initiatives'!$C:$C,'Gap Analysis update'!$B$7,'MoDi Initiatives'!$B:$B,'Gap Analysis update'!P$2) -> 0 | Q19: =SUMIFS('MoDi Initiatives'!O:O,'MoDi Initiatives'!$E:$E,'Gap Analysis update'!$B19,'MoDi Initiatives'!$A:$A,'Gap Analysis update'!$A19,'MoDi Initiatives'!$B:$B,'Gap Analysis update'!Q$2)-SUMIFS('MoDi Initiatives'!O:O,'MoDi Initiatives'!$E:$E,'Gap Analysis update'!$B19,'MoDi Initiatives'!$A:$A,'Gap Analysis update'!$A19,'MoDi Initiatives'!$C:$C,'Gap Analysis update'!$B$7,'MoDi Initiatives'!$B:$B,'Gap Analysis update'!Q$2) -> 0 | R19: =SUMIFS('MoDi Initiatives'!P:P,'MoDi Initiatives'!$E:$E,'Gap Analysis update'!$B19,'MoDi Initiatives'!$A:$A,'Gap Analysis update'!$A19,'MoDi Initiatives'!$B:$B,'Gap Analysis update'!R$2)-SUMIFS('MoDi Initiatives'!P:P,'MoDi Initiatives'!$E:$E,'Gap Analysis update'!$B19,'MoDi Initiatives'!$A:$A,'Gap Analysis update'!$A19,'MoDi Initiatives'!$C:$C,'Gap Analysis update'!$B$7,'MoDi Initiatives'!$B:$B,'Gap Analysis update'!R$2) -> 0 | S19: =SUMIFS('MoDi Initiatives'!Q:Q,'MoDi Initiatives'!$E:$E,'Gap Analysis update'!$B19,'MoDi Initiatives'!$A:$A,'Gap Analysis update'!$A19,'MoDi Initiatives'!$B:$B,'Gap Analysis update'!S$2)-SUMIFS('MoDi Initiatives'!Q:Q,'MoDi Initiatives'!$E:$E,'Gap Analysis update'!$B19,'MoDi Initiatives'!$A:$A,'Gap Analysis update'!$A19,'MoDi Initiatives'!$C:$C,'Gap Analysis update'!$B$7,'MoDi Initiatives'!$B:$B,'Gap Analysis update'!S$2) -> 0 | T19: =SUMIFS('MoDi Initiatives'!R:R,'MoDi Initiatives'!$E:$E,'Gap Analysis update'!$B19,'MoDi Initiatives'!$A:$A,'Gap Analysis update'!$A19,'MoDi Initiatives'!$B:$B,'Gap Analysis update'!T$2)-SUMIFS('MoDi Initiatives'!R:R,'MoDi Initiatives'!$E:$E,'Gap Analysis update'!$B19,'MoDi Initiatives'!$A:$A,'Gap Analysis update'!$A19,'MoDi Initiatives'!$C:$C,'Gap Analysis update'!$B$7,'MoDi Initiatives'!$B:$B,'Gap Analysis update'!T$2) -> 0 | U19: =SUMIFS('MoDi Initiatives'!S:S,'MoDi Initiatives'!$E:$E,'Gap Analysis update'!$B19,'MoDi Initiatives'!$A:$A,'Gap Analysis update'!$A19,'MoDi Initiatives'!$B:$B,'Gap Analysis update'!U$2)-SUMIFS('MoDi Initiatives'!S:S,'MoDi Initiatives'!$E:$E,'Gap Analysis update'!$B19,'MoDi Initiatives'!$A:$A,'Gap Analysis update'!$A19,'MoDi Initiatives'!$C:$C,'Gap Analysis update'!$B$7,'MoDi Initiatives'!$B:$B,'Gap Analysis update'!U$2) -> 0 | V19: =SUMIFS('MoDi Initiatives'!T:T,'MoDi Initiatives'!$E:$E,'Gap Analysis update'!$B19,'MoDi Initiatives'!$A:$A,'Gap Analysis update'!$A19,'MoDi Initiatives'!$B:$B,'Gap Analysis update'!V$2)-SUMIFS('MoDi Initiatives'!T:T,'MoDi Initiatives'!$E:$E,'Gap Analysis update'!$B19,'MoDi Initiatives'!$A:$A,'Gap Analysis update'!$A19,'MoDi Initiatives'!$C:$C,'Gap Analysis update'!$B$7,'MoDi Initiatives'!$B:$B,'Gap Analysis update'!V$2) -> 0 | W19: =SUMIFS('MoDi Initiatives'!U:U,'MoDi Initiatives'!$E:$E,'Gap Analysis update'!$B19,'MoDi Initiatives'!$A:$A,'Gap Analysis update'!$A19,'MoDi Initiatives'!$B:$B,'Gap Analysis update'!W$2)-SUMIFS('MoDi Initiatives'!U:U,'MoDi Initiatives'!$E:$E,'Gap Analysis update'!$B19,'MoDi Initiatives'!$A:$A,'Gap Analysis update'!$A19,'MoDi Initiatives'!$C:$C,'Gap Analysis update'!$B$7,'MoDi Initiatives'!$B:$B,'Gap Analysis update'!W$2) -> 0 | X19: =SUMIFS('MoDi Initiatives'!V:V,'MoDi Initiatives'!$E:$E,'Gap Analysis update'!$B19,'MoDi Initiatives'!$A:$A,'Gap Analysis update'!$A19,'MoDi Initiatives'!$B:$B,'Gap Analysis update'!X$2)-SUMIFS('MoDi Initiatives'!V:V,'MoDi Initiatives'!$E:$E,'Gap Analysis update'!$B19,'MoDi Initiatives'!$A:$A,'Gap Analysis update'!$A19,'MoDi Initiatives'!$C:$C,'Gap Analysis update'!$B$7,'MoDi Initiatives'!$B:$B,'Gap Analysis update'!X$2) -> 0 | Y19: =SUMIFS('MoDi Initiatives'!W:W,'MoDi Initiatives'!$E:$E,'Gap Analysis update'!$B19,'MoDi Initiatives'!$A:$A,'Gap Analysis update'!$A19,'MoDi Initiatives'!$B:$B,'Gap Analysis update'!Y$2)-SUMIFS('MoDi Initiatives'!W:W,'MoDi Initiatives'!$E:$E,'Gap Analysis update'!$B19,'MoDi Initiatives'!$A:$A,'Gap Analysis update'!$A19,'MoDi Initiatives'!$C:$C,'Gap Analysis update'!$B$7,'MoDi Initiatives'!$B:$B,'Gap Analysis update'!Y$2) -> 0 | AB19: =SUMIFS('MoDi Initiatives'!H:H,'MoDi Initiatives'!$E:$E,'Gap Analysis update'!$B19,'MoDi Initiatives'!$A:$A,'Gap Analysis update'!$A19,'MoDi Initiatives'!$B:$B,'Gap Analysis update'!AB$2)-SUMIFS('MoDi Initiatives'!H:H,'MoDi Initiatives'!$E:$E,'Gap Analysis update'!$B19,'MoDi Initiatives'!$A:$A,'Gap Analysis update'!$A19,'MoDi Initiatives'!$B:$B,'Gap Analysis update'!AB$2,'MoDi Initiatives'!$C:$C,'Gap Analysis update'!$B$7) -> 0 | AC19: =SUMIFS('MoDi Initiatives'!I:I,'MoDi Initiatives'!$E:$E,'Gap Analysis update'!$B19,'MoDi Initiatives'!$A:$A,'Gap Analysis update'!$A19,'MoDi Initiatives'!$B:$B,'Gap Analysis update'!AC$2)-SUMIFS('MoDi Initiatives'!I:I,'MoDi Initiatives'!$E:$E,'Gap Analysis update'!$B19,'MoDi Initiatives'!$A:$A,'Gap Analysis update'!$A19,'MoDi Initiatives'!$B:$B,'Gap Analysis update'!AC$2,'MoDi Initiatives'!$C:$C,'Gap Analysis update'!$B$7) -> 0 | AD19: =SUMIFS('MoDi Initiatives'!J:J,'MoDi Initiatives'!$E:$E,'Gap Analysis update'!$B19,'MoDi Initiatives'!$A:$A,'Gap Analysis update'!$A19,'MoDi Initiatives'!$B:$B,'Gap Analysis update'!AD$2)-SUMIFS('MoDi Initiatives'!J:J,'MoDi Initiatives'!$E:$E,'Gap Analysis update'!$B19,'MoDi Initiatives'!$A:$A,'Gap Analysis update'!$A19,'MoDi Initiatives'!$B:$B,'Gap Analysis update'!AD$2,'MoDi Initiatives'!$C:$C,'Gap Analysis update'!$B$7) -> 0 | AE19: =SUMIFS('MoDi Initiatives'!K:K,'MoDi Initiatives'!$E:$E,'Gap Analysis update'!$B19,'MoDi Initiatives'!$A:$A,'Gap Analysis update'!$A19,'MoDi Initiatives'!$B:$B,'Gap Analysis update'!AE$2)-SUMIFS('MoDi Initiatives'!K:K,'MoDi Initiatives'!$E:$E,'Gap Analysis update'!$B19,'MoDi Initiatives'!$A:$A,'Gap Analysis update'!$A19,'MoDi Initiatives'!$B:$B,'Gap Analysis update'!AE$2,'MoDi Initiatives'!$C:$C,'Gap Analysis update'!$B$7) -> 0 | AF19: =SUMIFS('MoDi Initiatives'!L:L,'MoDi Initiatives'!$E:$E,'Gap Analysis update'!$B19,'MoDi Initiatives'!$A:$A,'Gap Analysis update'!$A19,'MoDi Initiatives'!$B:$B,'Gap Analysis update'!AF$2)-SUMIFS('MoDi Initiatives'!L:L,'MoDi Initiatives'!$E:$E,'Gap Analysis update'!$B19,'MoDi Initiatives'!$A:$A,'Gap Analysis update'!$A19,'MoDi Initiatives'!$B:$B,'Gap Analysis update'!AF$2,'MoDi Initiatives'!$C:$C,'Gap Analysis update'!$B$7) -> 0 | AG19: =SUMIFS('MoDi Initiatives'!M:M,'MoDi Initiatives'!$E:$E,'Gap Analysis update'!$B19,'MoDi Initiatives'!$A:$A,'Gap Analysis update'!$A19,'MoDi Initiatives'!$B:$B,'Gap Analysis update'!AG$2)-SUMIFS('MoDi Initiatives'!M:M,'MoDi Initiatives'!$E:$E,'Gap Analysis update'!$B19,'MoDi Initiatives'!$A:$A,'Gap Analysis update'!$A19,'MoDi Initiatives'!$B:$B,'Gap Analysis update'!AG$2,'MoDi Initiatives'!$C:$C,'Gap Analysis update'!$B$7) -> -0.0022831592 | AH19: =SUMIFS('MoDi Initiatives'!N:N,'MoDi Initiatives'!$E:$E,'Gap Analysis update'!$B19,'MoDi Initiatives'!$A:$A,'Gap Analysis update'!$A19,'MoDi Initiatives'!$B:$B,'Gap Analysis update'!AH$2)-SUMIFS('MoDi Initiatives'!N:N,'MoDi Initiatives'!$E:$E,'Gap Analysis update'!$B19,'MoDi Initiatives'!$A:$A,'Gap Analysis update'!$A19,'MoDi Initiatives'!$B:$B,'Gap Analysis update'!AH$2,'MoDi Initiatives'!$C:$C,'Gap Analysis update'!$B$7) -> 0 | AI19: =SUMIFS('MoDi Initiatives'!O:O,'MoDi Initiatives'!$E:$E,'Gap Analysis update'!$B19,'MoDi Initiatives'!$A:$A,'Gap Analysis update'!$A19,'MoDi Initiatives'!$B:$B,'Gap Analysis update'!AI$2)-SUMIFS('MoDi Initiatives'!O:O,'MoDi Initiatives'!$E:$E,'Gap Analysis update'!$B19,'MoDi Initiatives'!$A:$A,'Gap Analysis update'!$A19,'MoDi Initiatives'!$B:$B,'Gap Analysis update'!AI$2,'MoDi Initiatives'!$C:$C,'Gap Analysis update'!$B$7) -> 0 | AJ19: =SUMIFS('MoDi Initiatives'!P:P,'MoDi Initiatives'!$E:$E,'Gap Analysis update'!$B19,'MoDi Initiatives'!$A:$A,'Gap Analysis update'!$A19,'MoDi Initiatives'!$B:$B,'Gap Analysis update'!AJ$2)-SUMIFS('MoDi Initiatives'!P:P,'MoDi Initiatives'!$E:$E,'Gap Analysis update'!$B19,'MoDi Initiatives'!$A:$A,'Gap Analysis update'!$A19,'MoDi Initiatives'!$B:$B,'Gap Analysis update'!AJ$2,'MoDi Initiatives'!$C:$C,'Gap Analysis update'!$B$7) -> 0 | AK19: =SUMIFS('MoDi Initiatives'!Q:Q,'MoDi Initiatives'!$E:$E,'Gap Analysis update'!$B19,'MoDi Initiatives'!$A:$A,'Gap Analysis update'!$A19,'MoDi Initiatives'!$B:$B,'Gap Analysis update'!AK$2)-SUMIFS('MoDi Initiatives'!Q:Q,'MoDi Initiatives'!$E:$E,'Gap Analysis update'!$B19,'MoDi Initiatives'!$A:$A,'Gap Analysis update'!$A19,'MoDi Initiatives'!$B:$B,'Gap Analysis update'!AK$2,'MoDi Initiatives'!$C:$C,'Gap Analysis update'!$B$7) -> 0.0021077423 | AL19: =SUMIFS('MoDi Initiatives'!R:R,'MoDi Initiatives'!$E:$E,'Gap Analysis update'!$B19,'MoDi Initiatives'!$A:$A,'Gap Analysis update'!$A19,'MoDi Initiatives'!$B:$B,'Gap Analysis update'!AL$2)-SUMIFS('MoDi Initiatives'!R:R,'MoDi Initiatives'!$E:$E,'Gap Analysis update'!$B19,'MoDi Initiatives'!$A:$A,'Gap Analysis update'!$A19,'MoDi Initiatives'!$B:$B,'Gap Analysis update'!AL$2,'MoDi Initiatives'!$C:$C,'Gap Analysis update'!$B$7) -> 0 | AM19: =SUMIFS('MoDi Initiatives'!S:S,'MoDi Initiatives'!$E:$E,'Gap Analysis update'!$B19,'MoDi Initiatives'!$A:$A,'Gap Analysis update'!$A19,'MoDi Initiatives'!$B:$B,'Gap Analysis update'!AM$2)-SUMIFS('MoDi Initiatives'!S:S,'MoDi Initiatives'!$E:$E,'Gap Analysis update'!$B19,'MoDi Initiatives'!$A:$A,'Gap Analysis update'!$A19,'MoDi Initiatives'!$B:$B,'Gap Analysis update'!AM$2,'MoDi Initiatives'!$C:$C,'Gap Analysis update'!$B$7) -> 0 | AN19: =SUMIFS('MoDi Initiatives'!T:T,'MoDi Initiatives'!$E:$E,'Gap Analysis update'!$B19,'MoDi Initiatives'!$A:$A,'Gap Analysis update'!$A19,'MoDi Initiatives'!$B:$B,'Gap Analysis update'!AN$2)-SUMIFS('MoDi Initiatives'!T:T,'MoDi Initiatives'!$E:$E,'Gap Analysis update'!$B19,'MoDi Initiatives'!$A:$A,'Gap Analysis update'!$A19,'MoDi Initiatives'!$B:$B,'Gap Analysis update'!AN$2,'MoDi Initiatives'!$C:$C,'Gap Analysis update'!$B$7) -> 0 | AO19: =SUMIFS('MoDi Initiatives'!U:U,'MoDi Initiatives'!$E:$E,'Gap Analysis update'!$B19,'MoDi Initiatives'!$A:$A,'Gap Analysis update'!$A19,'MoDi Initiatives'!$B:$B,'Gap Analysis update'!AO$2)-SUMIFS('MoDi Initiatives'!U:U,'MoDi Initiatives'!$E:$E,'Gap Analysis update'!$B19,'MoDi Initiatives'!$A:$A,'Gap Analysis update'!$A19,'MoDi Initiatives'!$B:$B,'Gap Analysis update'!AO$2,'MoDi Initiatives'!$C:$C,'Gap Analysis update'!$B$7) -> 0 | AP19: =SUMIFS('MoDi Initiatives'!V:V,'MoDi Initiatives'!$E:$E,'Gap Analysis update'!$B19,'MoDi Initiatives'!$A:$A,'Gap Analysis update'!$A19,'MoDi Initiatives'!$B:$B,'Gap Analysis update'!AP$2)-SUMIFS('MoDi Initiatives'!V:V,'MoDi Initiatives'!$E:$E,'Gap Analysis update'!$B19,'MoDi Initiatives'!$A:$A,'Gap Analysis update'!$A19,'MoDi Initiatives'!$B:$B,'Gap Analysis update'!AP$2,'MoDi Initiatives'!$C:$C,'Gap Analysis update'!$B$7) -> 0 | AQ19: =SUMIFS('MoDi Initiatives'!W:W,'MoDi Initiatives'!$E:$E,'Gap Analysis update'!$B19,'MoDi Initiatives'!$A:$A,'Gap Analysis update'!$A19,'MoDi Initiatives'!$B:$B,'Gap Analysis update'!AQ$2)-SUMIFS('MoDi Initiatives'!W:W,'MoDi Initiatives'!$E:$E,'Gap Analysis update'!$B19,'MoDi Initiatives'!$A:$A,'Gap Analysis update'!$A19,'MoDi Initiatives'!$B:$B,'Gap Analysis update'!AQ$2,'MoDi Initiatives'!$C:$C,'Gap Analysis update'!$B$7) -> 0 | AT19: =AB19-J19 -> 0 | AU19: =AC19-K19 -> 0 | AV19: =AD19-L19 -> 0 | AW19: =AE19-M19 -> 0 | AX19: =AF19-N19 -> 0 | AY19: =AG19-O19 -> -0.0022831592 | AZ19: =AH19-P19 -> 0 | BA19: =AI19-Q19 -> 0 | ... BI19: =AQ19-Y19 -> 0 | BN19: Protective shell(ZRP Wrapping sticker） | BP19: Inflation | BQ19: Design change from EM: Flow wrap pre-print + Bottom sticker removal | BR19: 2. Coplan Battery -1.25p;(Delay to Feb due to inventory) | BT19: Inflation | BU19: Design change from EM: Flow wrap change to ESG
A20: PEN 800 Full 2.0 | B20: E-liquid | C20: =SUM(AS20:BA20) -> 0 | D20: =SUM(BB20:BI20) -> 0 | E20: =D20+C20 -> 0 | F20: Gap: 0.25p; 1.Extra stretch-finance: 0.29p gap; 2. Liquid cost down from FX: -0.04P. Action: Flavor Nego down finished, to push US for liquid down(Kil). | J20: =SUMIFS('MoDi Initiatives'!H:H,'MoDi Initiatives'!$E:$E,'Gap Analysis update'!$B20,'MoDi Initiatives'!$A:$A,'Gap Analysis update'!$A20,'MoDi Initiatives'!$B:$B,'Gap Analysis update'!J$2)-SUMIFS('MoDi Initiatives'!H:H,'MoDi Initiatives'!$E:$E,'Gap Analysis update'!$B20,'MoDi Initiatives'!$A:$A,'Gap Analysis update'!$A20,'MoDi Initiatives'!$C:$C,'Gap Analysis update'!$B$7,'MoDi Initiatives'!$B:$B,'Gap Analysis update'!J$2) -> 0 | K20: =SUMIFS('MoDi Initiatives'!I:I,'MoDi Initiatives'!$E:$E,'Gap Analysis update'!$B20,'MoDi Initiatives'!$A:$A,'Gap Analysis update'!$A20,'MoDi Initiatives'!$B:$B,'Gap Analysis update'!K$2)-SUMIFS('MoDi Initiatives'!I:I,'MoDi Initiatives'!$E:$E,'Gap Analysis update'!$B20,'MoDi Initiatives'!$A:$A,'Gap Analysis update'!$A20,'MoDi Initiatives'!$C:$C,'Gap Analysis update'!$B$7,'MoDi Initiatives'!$B:$B,'Gap Analysis update'!K$2) -> 0 | L20: =SUMIFS('MoDi Initiatives'!J:J,'MoDi Initiatives'!$E:$E,'Gap Analysis update'!$B20,'MoDi Initiatives'!$A:$A,'Gap Analysis update'!$A20,'MoDi Initiatives'!$B:$B,'Gap Analysis update'!L$2)-SUMIFS('MoDi Initiatives'!J:J,'MoDi Initiatives'!$E:$E,'Gap Analysis update'!$B20,'MoDi Initiatives'!$A:$A,'Gap Analysis update'!$A20,'MoDi Initiatives'!$C:$C,'Gap Analysis update'!$B$7,'MoDi Initiatives'!$B:$B,'Gap Analysis update'!L$2) -> 0 | M20: =SUMIFS('MoDi Initiatives'!K:K,'MoDi Initiatives'!$E:$E,'Gap Analysis update'!$B20,'MoDi Initiatives'!$A:$A,'Gap Analysis update'!$A20,'MoDi Initiatives'!$B:$B,'Gap Analysis update'!M$2)-SUMIFS('MoDi Initiatives'!K:K,'MoDi Initiatives'!$E:$E,'Gap Analysis update'!$B20,'MoDi Initiatives'!$A:$A,'Gap Analysis update'!$A20,'MoDi Initiatives'!$C:$C,'Gap Analysis update'!$B$7,'MoDi Initiatives'!$B:$B,'Gap Analysis update'!M$2) -> 0 | N20: =SUMIFS('MoDi Initiatives'!L:L,'MoDi Initiatives'!$E:$E,'Gap Analysis update'!$B20,'MoDi Initiatives'!$A:$A,'Gap Analysis update'!$A20,'MoDi Initiatives'!$B:$B,'Gap Analysis update'!N$2)-SUMIFS('MoDi Initiatives'!L:L,'MoDi Initiatives'!$E:$E,'Gap Analysis update'!$B20,'MoDi Initiatives'!$A:$A,'Gap Analysis update'!$A20,'MoDi Initiatives'!$C:$C,'Gap Analysis update'!$B$7,'MoDi Initiatives'!$B:$B,'Gap Analysis update'!N$2) -> 0 | O20: =SUMIFS('MoDi Initiatives'!M:M,'MoDi Initiatives'!$E:$E,'Gap Analysis update'!$B20,'MoDi Initiatives'!$A:$A,'Gap Analysis update'!$A20,'MoDi Initiatives'!$B:$B,'Gap Analysis update'!O$2)-SUMIFS('MoDi Initiatives'!M:M,'MoDi Initiatives'!$E:$E,'Gap Analysis update'!$B20,'MoDi Initiatives'!$A:$A,'Gap Analysis update'!$A20,'MoDi Initiatives'!$C:$C,'Gap Analysis update'!$B$7,'MoDi Initiatives'!$B:$B,'Gap Analysis update'!O$2) -> 0 | P20: =SUMIFS('MoDi Initiatives'!N:N,'MoDi Initiatives'!$E:$E,'Gap Analysis update'!$B20,'MoDi Initiatives'!$A:$A,'Gap Analysis update'!$A20,'MoDi Initiatives'!$B:$B,'Gap Analysis update'!P$2)-SUMIFS('MoDi Initiatives'!N:N,'MoDi Initiatives'!$E:$E,'Gap Analysis update'!$B20,'MoDi Initiatives'!$A:$A,'Gap Analysis update'!$A20,'MoDi Initiatives'!$C:$C,'Gap Analysis update'!$B$7,'MoDi Initiatives'!$B:$B,'Gap Analysis update'!P$2) -> 0 | Q20: =SUMIFS('MoDi Initiatives'!O:O,'MoDi Initiatives'!$E:$E,'Gap Analysis update'!$B20,'MoDi Initiatives'!$A:$A,'Gap Analysis update'!$A20,'MoDi Initiatives'!$B:$B,'Gap Analysis update'!Q$2)-SUMIFS('MoDi Initiatives'!O:O,'MoDi Initiatives'!$E:$E,'Gap Analysis update'!$B20,'MoDi Initiatives'!$A:$A,'Gap Analysis update'!$A20,'MoDi Initiatives'!$C:$C,'Gap Analysis update'!$B$7,'MoDi Initiatives'!$B:$B,'Gap Analysis update'!Q$2) -> 0 | R20: =SUMIFS('MoDi Initiatives'!P:P,'MoDi Initiatives'!$E:$E,'Gap Analysis update'!$B20,'MoDi Initiatives'!$A:$A,'Gap Analysis update'!$A20,'MoDi Initiatives'!$B:$B,'Gap Analysis update'!R$2)-SUMIFS('MoDi Initiatives'!P:P,'MoDi Initiatives'!$E:$E,'Gap Analysis update'!$B20,'MoDi Initiatives'!$A:$A,'Gap Analysis update'!$A20,'MoDi Initiatives'!$C:$C,'Gap Analysis update'!$B$7,'MoDi Initiatives'!$B:$B,'Gap Analysis update'!R$2) -> 0 | S20: =SUMIFS('MoDi Initiatives'!Q:Q,'MoDi Initiatives'!$E:$E,'Gap Analysis update'!$B20,'MoDi Initiatives'!$A:$A,'Gap Analysis update'!$A20,'MoDi Initiatives'!$B:$B,'Gap Analysis update'!S$2)-SUMIFS('MoDi Initiatives'!Q:Q,'MoDi Initiatives'!$E:$E,'Gap Analysis update'!$B20,'MoDi Initiatives'!$A:$A,'Gap Analysis update'!$A20,'MoDi Initiatives'!$C:$C,'Gap Analysis update'!$B$7,'MoDi Initiatives'!$B:$B,'Gap Analysis update'!S$2) -> 0 | T20: =SUMIFS('MoDi Initiatives'!R:R,'MoDi Initiatives'!$E:$E,'Gap Analysis update'!$B20,'MoDi Initiatives'!$A:$A,'Gap Analysis update'!$A20,'MoDi Initiatives'!$B:$B,'Gap Analysis update'!T$2)-SUMIFS('MoDi Initiatives'!R:R,'MoDi Initiatives'!$E:$E,'Gap Analysis update'!$B20,'MoDi Initiatives'!$A:$A,'Gap Analysis update'!$A20,'MoDi Initiatives'!$C:$C,'Gap Analysis update'!$B$7,'MoDi Initiatives'!$B:$B,'Gap Analysis update'!T$2) -> 0 | U20: =SUMIFS('MoDi Initiatives'!S:S,'MoDi Initiatives'!$E:$E,'Gap Analysis update'!$B20,'MoDi Initiatives'!$A:$A,'Gap Analysis update'!$A20,'MoDi Initiatives'!$B:$B,'Gap Analysis update'!U$2)-SUMIFS('MoDi Initiatives'!S:S,'MoDi Initiatives'!$E:$E,'Gap Analysis update'!$B20,'MoDi Initiatives'!$A:$A,'Gap Analysis update'!$A20,'MoDi Initiatives'!$C:$C,'Gap Analysis update'!$B$7,'MoDi Initiatives'!$B:$B,'Gap Analysis update'!U$2) -> 0 | V20: =SUMIFS('MoDi Initiatives'!T:T,'MoDi Initiatives'!$E:$E,'Gap Analysis update'!$B20,'MoDi Initiatives'!$A:$A,'Gap Analysis update'!$A20,'MoDi Initiatives'!$B:$B,'Gap Analysis update'!V$2)-SUMIFS('MoDi Initiatives'!T:T,'MoDi Initiatives'!$E:$E,'Gap Analysis update'!$B20,'MoDi Initiatives'!$A:$A,'Gap Analysis update'!$A20,'MoDi Initiatives'!$C:$C,'Gap Analysis update'!$B$7,'MoDi Initiatives'!$B:$B,'Gap Analysis update'!V$2) -> 0 | W20: =SUMIFS('MoDi Initiatives'!U:U,'MoDi Initiatives'!$E:$E,'Gap Analysis update'!$B20,'MoDi Initiatives'!$A:$A,'Gap Analysis update'!$A20,'MoDi Initiatives'!$B:$B,'Gap Analysis update'!W$2)-SUMIFS('MoDi Initiatives'!U:U,'MoDi Initiatives'!$E:$E,'Gap Analysis update'!$B20,'MoDi Initiatives'!$A:$A,'Gap Analysis update'!$A20,'MoDi Initiatives'!$C:$C,'Gap Analysis update'!$B$7,'MoDi Initiatives'!$B:$B,'Gap Analysis update'!W$2) -> 0 | X20: =SUMIFS('MoDi Initiatives'!V:V,'MoDi Initiatives'!$E:$E,'Gap Analysis update'!$B20,'MoDi Initiatives'!$A:$A,'Gap Analysis update'!$A20,'MoDi Initiatives'!$B:$B,'Gap Analysis update'!X$2)-SUMIFS('MoDi Initiatives'!V:V,'MoDi Initiatives'!$E:$E,'Gap Analysis update'!$B20,'MoDi Initiatives'!$A:$A,'Gap Analysis update'!$A20,'MoDi Initiatives'!$C:$C,'Gap Analysis update'!$B$7,'MoDi Initiatives'!$B:$B,'Gap Analysis update'!X$2) -> 0 | Y20: =SUMIFS('MoDi Initiatives'!W:W,'MoDi Initiatives'!$E:$E,'Gap Analysis update'!$B20,'MoDi Initiatives'!$A:$A,'Gap Analysis update'!$A20,'MoDi Initiatives'!$B:$B,'Gap Analysis update'!Y$2)-SUMIFS('MoDi Initiatives'!W:W,'MoDi Initiatives'!$E:$E,'Gap Analysis update'!$B20,'MoDi Initiatives'!$A:$A,'Gap Analysis update'!$A20,'MoDi Initiatives'!$C:$C,'Gap Analysis update'!$B$7,'MoDi Initiatives'!$B:$B,'Gap Analysis update'!Y$2) -> 0 | AB20: =SUMIFS('MoDi Initiatives'!H:H,'MoDi Initiatives'!$E:$E,'Gap Analysis update'!$B20,'MoDi Initiatives'!$A:$A,'Gap Analysis update'!$A20,'MoDi Initiatives'!$B:$B,'Gap Analysis update'!AB$2)-SUMIFS('MoDi Initiatives'!H:H,'MoDi Initiatives'!$E:$E,'Gap Analysis update'!$B20,'MoDi Initiatives'!$A:$A,'Gap Analysis update'!$A20,'MoDi Initiatives'!$B:$B,'Gap Analysis update'!AB$2,'MoDi Initiatives'!$C:$C,'Gap Analysis update'!$B$7) -> 0 | AC20: =SUMIFS('MoDi Initiatives'!I:I,'MoDi Initiatives'!$E:$E,'Gap Analysis update'!$B20,'MoDi Initiatives'!$A:$A,'Gap Analysis update'!$A20,'MoDi Initiatives'!$B:$B,'Gap Analysis update'!AC$2)-SUMIFS('MoDi Initiatives'!I:I,'MoDi Initiatives'!$E:$E,'Gap Analysis update'!$B20,'MoDi Initiatives'!$A:$A,'Gap Analysis update'!$A20,'MoDi Initiatives'!$B:$B,'Gap Analysis update'!AC$2,'MoDi Initiatives'!$C:$C,'Gap Analysis update'!$B$7) -> 0 | AD20: =SUMIFS('MoDi Initiatives'!J:J,'MoDi Initiatives'!$E:$E,'Gap Analysis update'!$B20,'MoDi Initiatives'!$A:$A,'Gap Analysis update'!$A20,'MoDi Initiatives'!$B:$B,'Gap Analysis update'!AD$2)-SUMIFS('MoDi Initiatives'!J:J,'MoDi Initiatives'!$E:$E,'Gap Analysis update'!$B20,'MoDi Initiatives'!$A:$A,'Gap Analysis update'!$A20,'MoDi Initiatives'!$B:$B,'Gap Analysis update'!AD$2,'MoDi Initiatives'!$C:$C,'Gap Analysis update'!$B$7) -> 0 | AE20: =SUMIFS('MoDi Initiatives'!K:K,'MoDi Initiatives'!$E:$E,'Gap Analysis update'!$B20,'MoDi Initiatives'!$A:$A,'Gap Analysis update'!$A20,'MoDi Initiatives'!$B:$B,'Gap Analysis update'!AE$2)-SUMIFS('MoDi Initiatives'!K:K,'MoDi Initiatives'!$E:$E,'Gap Analysis update'!$B20,'MoDi Initiatives'!$A:$A,'Gap Analysis update'!$A20,'MoDi Initiatives'!$B:$B,'Gap Analysis update'!AE$2,'MoDi Initiatives'!$C:$C,'Gap Analysis update'!$B$7) -> 0 | AF20: =SUMIFS('MoDi Initiatives'!L:L,'MoDi Initiatives'!$E:$E,'Gap Analysis update'!$B20,'MoDi Initiatives'!$A:$A,'Gap Analysis update'!$A20,'MoDi Initiatives'!$B:$B,'Gap Analysis update'!AF$2)-SUMIFS('MoDi Initiatives'!L:L,'MoDi Initiatives'!$E:$E,'Gap Analysis update'!$B20,'MoDi Initiatives'!$A:$A,'Gap Analysis update'!$A20,'MoDi Initiatives'!$B:$B,'Gap Analysis update'!AF$2,'MoDi Initiatives'!$C:$C,'Gap Analysis update'!$B$7) -> 0 | AG20: =SUMIFS('MoDi Initiatives'!M:M,'MoDi Initiatives'!$E:$E,'Gap Analysis update'!$B20,'MoDi Initiatives'!$A:$A,'Gap Analysis update'!$A20,'MoDi Initiatives'!$B:$B,'Gap Analysis update'!AG$2)-SUMIFS('MoDi Initiatives'!M:M,'MoDi Initiatives'!$E:$E,'Gap Analysis update'!$B20,'MoDi Initiatives'!$A:$A,'Gap Analysis update'!$A20,'MoDi Initiatives'!$B:$B,'Gap Analysis update'!AG$2,'MoDi Initiatives'!$C:$C,'Gap Analysis update'!$B$7) -> 0 | AH20: =SUMIFS('MoDi Initiatives'!N:N,'MoDi Initiatives'!$E:$E,'Gap Analysis update'!$B20,'MoDi Initiatives'!$A:$A,'Gap Analysis update'!$A20,'MoDi Initiatives'!$B:$B,'Gap Analysis update'!AH$2)-SUMIFS('MoDi Initiatives'!N:N,'MoDi Initiatives'!$E:$E,'Gap Analysis update'!$B20,'MoDi Initiatives'!$A:$A,'Gap Analysis update'!$A20,'MoDi Initiatives'!$B:$B,'Gap Analysis update'!AH$2,'MoDi Initiatives'!$C:$C,'Gap Analysis update'!$B$7) -> 0 | AI20: =SUMIFS('MoDi Initiatives'!O:O,'MoDi Initiatives'!$E:$E,'Gap Analysis update'!$B20,'MoDi Initiatives'!$A:$A,'Gap Analysis update'!$A20,'MoDi Initiatives'!$B:$B,'Gap Analysis update'!AI$2)-SUMIFS('MoDi Initiatives'!O:O,'MoDi Initiatives'!$E:$E,'Gap Analysis update'!$B20,'MoDi Initiatives'!$A:$A,'Gap Analysis update'!$A20,'MoDi Initiatives'!$B:$B,'Gap Analysis update'!AI$2,'MoDi Initiatives'!$C:$C,'Gap Analysis update'!$B$7) -> 0 | AJ20: =SUMIFS('MoDi Initiatives'!P:P,'MoDi Initiatives'!$E:$E,'Gap Analysis update'!$B20,'MoDi Initiatives'!$A:$A,'Gap Analysis update'!$A20,'MoDi Initiatives'!$B:$B,'Gap Analysis update'!AJ$2)-SUMIFS('MoDi Initiatives'!P:P,'MoDi Initiatives'!$E:$E,'Gap Analysis update'!$B20,'MoDi Initiatives'!$A:$A,'Gap Analysis update'!$A20,'MoDi Initiatives'!$B:$B,'Gap Analysis update'!AJ$2,'MoDi Initiatives'!$C:$C,'Gap Analysis update'!$B$7) -> 0 | AK20: =SUMIFS('MoDi Initiatives'!Q:Q,'MoDi Initiatives'!$E:$E,'Gap Analysis update'!$B20,'MoDi Initiatives'!$A:$A,'Gap Analysis update'!$A20,'MoDi Initiatives'!$B:$B,'Gap Analysis update'!AK$2)-SUMIFS('MoDi Initiatives'!Q:Q,'MoDi Initiatives'!$E:$E,'Gap Analysis update'!$B20,'MoDi Initiatives'!$A:$A,'Gap Analysis update'!$A20,'MoDi Initiatives'!$B:$B,'Gap Analysis update'!AK$2,'MoDi Initiatives'!$C:$C,'Gap Analysis update'!$B$7) -> 0 | AL20: =SUMIFS('MoDi Initiatives'!R:R,'MoDi Initiatives'!$E:$E,'Gap Analysis update'!$B20,'MoDi Initiatives'!$A:$A,'Gap Analysis update'!$A20,'MoDi Initiatives'!$B:$B,'Gap Analysis update'!AL$2)-SUMIFS('MoDi Initiatives'!R:R,'MoDi Initiatives'!$E:$E,'Gap Analysis update'!$B20,'MoDi Initiatives'!$A:$A,'Gap Analysis update'!$A20,'MoDi Initiatives'!$B:$B,'Gap Analysis update'!AL$2,'MoDi Initiatives'!$C:$C,'Gap Analysis update'!$B$7) -> 0 | AM20: =SUMIFS('MoDi Initiatives'!S:S,'MoDi Initiatives'!$E:$E,'Gap Analysis update'!$B20,'MoDi Initiatives'!$A:$A,'Gap Analysis update'!$A20,'MoDi Initiatives'!$B:$B,'Gap Analysis update'!AM$2)-SUMIFS('MoDi Initiatives'!S:S,'MoDi Initiatives'!$E:$E,'Gap Analysis update'!$B20,'MoDi Initiatives'!$A:$A,'Gap Analysis update'!$A20,'MoDi Initiatives'!$B:$B,'Gap Analysis update'!AM$2,'MoDi Initiatives'!$C:$C,'Gap Analysis update'!$B$7) -> 0 | AN20: =SUMIFS('MoDi Initiatives'!T:T,'MoDi Initiatives'!$E:$E,'Gap Analysis update'!$B20,'MoDi Initiatives'!$A:$A,'Gap Analysis update'!$A20,'MoDi Initiatives'!$B:$B,'Gap Analysis update'!AN$2)-SUMIFS('MoDi Initiatives'!T:T,'MoDi Initiatives'!$E:$E,'Gap Analysis update'!$B20,'MoDi Initiatives'!$A:$A,'Gap Analysis update'!$A20,'MoDi Initiatives'!$B:$B,'Gap Analysis update'!AN$2,'MoDi Initiatives'!$C:$C,'Gap Analysis update'!$B$7) -> 0 | AO20: =SUMIFS('MoDi Initiatives'!U:U,'MoDi Initiatives'!$E:$E,'Gap Analysis update'!$B20,'MoDi Initiatives'!$A:$A,'Gap Analysis update'!$A20,'MoDi Initiatives'!$B:$B,'Gap Analysis update'!AO$2)-SUMIFS('MoDi Initiatives'!U:U,'MoDi Initiatives'!$E:$E,'Gap Analysis update'!$B20,'MoDi Initiatives'!$A:$A,'Gap Analysis update'!$A20,'MoDi Initiatives'!$B:$B,'Gap Analysis update'!AO$2,'MoDi Initiatives'!$C:$C,'Gap Analysis update'!$B$7) -> 0 | AP20: =SUMIFS('MoDi Initiatives'!V:V,'MoDi Initiatives'!$E:$E,'Gap Analysis update'!$B20,'MoDi Initiatives'!$A:$A,'Gap Analysis update'!$A20,'MoDi Initiatives'!$B:$B,'Gap Analysis update'!AP$2)-SUMIFS('MoDi Initiatives'!V:V,'MoDi Initiatives'!$E:$E,'Gap Analysis update'!$B20,'MoDi Initiatives'!$A:$A,'Gap Analysis update'!$A20,'MoDi Initiatives'!$B:$B,'Gap Analysis update'!AP$2,'MoDi Initiatives'!$C:$C,'Gap Analysis update'!$B$7) -> 0 | AQ20: =SUMIFS('MoDi Initiatives'!W:W,'MoDi Initiatives'!$E:$E,'Gap Analysis update'!$B20,'MoDi Initiatives'!$A:$A,'Gap Analysis update'!$A20,'MoDi Initiatives'!$B:$B,'Gap Analysis update'!AQ$2)-SUMIFS('MoDi Initiatives'!W:W,'MoDi Initiatives'!$E:$E,'Gap Analysis update'!$B20,'MoDi Initiatives'!$A:$A,'Gap Analysis update'!$A20,'MoDi Initiatives'!$B:$B,'Gap Analysis update'!AQ$2,'MoDi Initiatives'!$C:$C,'Gap Analysis update'!$B$7) -> 0 | AT20: =AB20-J20 -> 0 | AU20: =AC20-K20 -> 0 | AV20: =AD20-L20 -> 0 | AW20: =AE20-M20 -> 0 | AX20: =AF20-N20 -> 0 | AY20: =AG20-O20 -> 0 | AZ20: =AH20-P20 -> 0 | BA20: =AI20-Q20 -> 0 | ... BI20: =AQ20-Y20 -> 0 | BM20: Liquid price down with FX update | BP20: Inflation | BR20: Liquid stretch | BS20: Liquid price down with FX update | BT20: Inflation
A21: PEN 800 Full 2.0 | B21: Core Technology | C21: =SUM(AS21:BA21) -> 5.3952384e-05 | D21: =SUM(BB21:BI21) -> 0 | E21: =D21+C21 -> 5.3952384e-05 | F21: Gap: 0.01p Slight gap from FX. | G21: Action: pull in Heater cost down -0.76p from Jun'25 to Jan'25 to balance the gap from Assy stretch. (T1) | J21: =SUMIFS('MoDi Initiatives'!H:H,'MoDi Initiatives'!$E:$E,'Gap Analysis update'!$B21,'MoDi Initiatives'!$A:$A,'Gap Analysis update'!$A21,'MoDi Initiatives'!$B:$B,'Gap Analysis update'!J$2)-SUMIFS('MoDi Initiatives'!H:H,'MoDi Initiatives'!$E:$E,'Gap Analysis update'!$B21,'MoDi Initiatives'!$A:$A,'Gap Analysis update'!$A21,'MoDi Initiatives'!$C:$C,'Gap Analysis update'!$B$7,'MoDi Initiatives'!$B:$B,'Gap Analysis update'!J$2) -> 0 | K21: =SUMIFS('MoDi Initiatives'!I:I,'MoDi Initiatives'!$E:$E,'Gap Analysis update'!$B21,'MoDi Initiatives'!$A:$A,'Gap Analysis update'!$A21,'MoDi Initiatives'!$B:$B,'Gap Analysis update'!K$2)-SUMIFS('MoDi Initiatives'!I:I,'MoDi Initiatives'!$E:$E,'Gap Analysis update'!$B21,'MoDi Initiatives'!$A:$A,'Gap Analysis update'!$A21,'MoDi Initiatives'!$C:$C,'Gap Analysis update'!$B$7,'MoDi Initiatives'!$B:$B,'Gap Analysis update'!K$2) -> 0 | L21: =SUMIFS('MoDi Initiatives'!J:J,'MoDi Initiatives'!$E:$E,'Gap Analysis update'!$B21,'MoDi Initiatives'!$A:$A,'Gap Analysis update'!$A21,'MoDi Initiatives'!$B:$B,'Gap Analysis update'!L$2)-SUMIFS('MoDi Initiatives'!J:J,'MoDi Initiatives'!$E:$E,'Gap Analysis update'!$B21,'MoDi Initiatives'!$A:$A,'Gap Analysis update'!$A21,'MoDi Initiatives'!$C:$C,'Gap Analysis update'!$B$7,'MoDi Initiatives'!$B:$B,'Gap Analysis update'!L$2) -> 0 | M21: =SUMIFS('MoDi Initiatives'!K:K,'MoDi Initiatives'!$E:$E,'Gap Analysis update'!$B21,'MoDi Initiatives'!$A:$A,'Gap Analysis update'!$A21,'MoDi Initiatives'!$B:$B,'Gap Analysis update'!M$2)-SUMIFS('MoDi Initiatives'!K:K,'MoDi Initiatives'!$E:$E,'Gap Analysis update'!$B21,'MoDi Initiatives'!$A:$A,'Gap Analysis update'!$A21,'MoDi Initiatives'!$C:$C,'Gap Analysis update'!$B$7,'MoDi Initiatives'!$B:$B,'Gap Analysis update'!M$2) -> -0.0076645176 | N21: =SUMIFS('MoDi Initiatives'!L:L,'MoDi Initiatives'!$E:$E,'Gap Analysis update'!$B21,'MoDi Initiatives'!$A:$A,'Gap Analysis update'!$A21,'MoDi Initiatives'!$B:$B,'Gap Analysis update'!N$2)-SUMIFS('MoDi Initiatives'!L:L,'MoDi Initiatives'!$E:$E,'Gap Analysis update'!$B21,'MoDi Initiatives'!$A:$A,'Gap Analysis update'!$A21,'MoDi Initiatives'!$C:$C,'Gap Analysis update'!$B$7,'MoDi Initiatives'!$B:$B,'Gap Analysis update'!N$2) -> 0 | O21: =SUMIFS('MoDi Initiatives'!M:M,'MoDi Initiatives'!$E:$E,'Gap Analysis update'!$B21,'MoDi Initiatives'!$A:$A,'Gap Analysis update'!$A21,'MoDi Initiatives'!$B:$B,'Gap Analysis update'!O$2)-SUMIFS('MoDi Initiatives'!M:M,'MoDi Initiatives'!$E:$E,'Gap Analysis update'!$B21,'MoDi Initiatives'!$A:$A,'Gap Analysis update'!$A21,'MoDi Initiatives'!$C:$C,'Gap Analysis update'!$B$7,'MoDi Initiatives'!$B:$B,'Gap Analysis update'!O$2) -> 0 | P21: =SUMIFS('MoDi Initiatives'!N:N,'MoDi Initiatives'!$E:$E,'Gap Analysis update'!$B21,'MoDi Initiatives'!$A:$A,'Gap Analysis update'!$A21,'MoDi Initiatives'!$B:$B,'Gap Analysis update'!P$2)-SUMIFS('MoDi Initiatives'!N:N,'MoDi Initiatives'!$E:$E,'Gap Analysis update'!$B21,'MoDi Initiatives'!$A:$A,'Gap Analysis update'!$A21,'MoDi Initiatives'!$C:$C,'Gap Analysis update'!$B$7,'MoDi Initiatives'!$B:$B,'Gap Analysis update'!P$2) -> 0 | Q21: =SUMIFS('MoDi Initiatives'!O:O,'MoDi Initiatives'!$E:$E,'Gap Analysis update'!$B21,'MoDi Initiatives'!$A:$A,'Gap Analysis update'!$A21,'MoDi Initiatives'!$B:$B,'Gap Analysis update'!Q$2)-SUMIFS('MoDi Initiatives'!O:O,'MoDi Initiatives'!$E:$E,'Gap Analysis update'!$B21,'MoDi Initiatives'!$A:$A,'Gap Analysis update'!$A21,'MoDi Initiatives'!$C:$C,'Gap Analysis update'!$B$7,'MoDi Initiatives'!$B:$B,'Gap Analysis update'!Q$2) -> 0 | R21: =SUMIFS('MoDi Initiatives'!P:P,'MoDi Initiatives'!$E:$E,'Gap Analysis update'!$B21,'MoDi Initiatives'!$A:$A,'Gap Analysis update'!$A21,'MoDi Initiatives'!$B:$B,'Gap Analysis update'!R$2)-SUMIFS('MoDi Initiatives'!P:P,'MoDi Initiatives'!$E:$E,'Gap Analysis update'!$B21,'MoDi Initiatives'!$A:$A,'Gap Analysis update'!$A21,'MoDi Initiatives'!$C:$C,'Gap Analysis update'!$B$7,'MoDi Initiatives'!$B:$B,'Gap Analysis update'!R$2) -> 0 | S21: =SUMIFS('MoDi Initiatives'!Q:Q,'MoDi Initiatives'!$E:$E,'Gap Analysis update'!$B21,'MoDi Initiatives'!$A:$A,'Gap Analysis update'!$A21,'MoDi Initiatives'!$B:$B,'Gap Analysis update'!S$2)-SUMIFS('MoDi Initiatives'!Q:Q,'MoDi Initiatives'!$E:$E,'Gap Analysis update'!$B21,'MoDi Initiatives'!$A:$A,'Gap Analysis update'!$A21,'MoDi Initiatives'!$C:$C,'Gap Analysis update'!$B$7,'MoDi Initiatives'!$B:$B,'Gap Analysis update'!S$2) -> 0 | T21: =SUMIFS('MoDi Initiatives'!R:R,'MoDi Initiatives'!$E:$E,'Gap Analysis update'!$B21,'MoDi Initiatives'!$A:$A,'Gap Analysis update'!$A21,'MoDi Initiatives'!$B:$B,'Gap Analysis update'!T$2)-SUMIFS('MoDi Initiatives'!R:R,'MoDi Initiatives'!$E:$E,'Gap Analysis update'!$B21,'MoDi Initiatives'!$A:$A,'Gap Analysis update'!$A21,'MoDi Initiatives'!$C:$C,'Gap Analysis update'!$B$7,'MoDi Initiatives'!$B:$B,'Gap Analysis update'!T$2) -> 0 | U21: =SUMIFS('MoDi Initiatives'!S:S,'MoDi Initiatives'!$E:$E,'Gap Analysis update'!$B21,'MoDi Initiatives'!$A:$A,'Gap Analysis update'!$A21,'MoDi Initiatives'!$B:$B,'Gap Analysis update'!U$2)-SUMIFS('MoDi Initiatives'!S:S,'MoDi Initiatives'!$E:$E,'Gap Analysis update'!$B21,'MoDi Initiatives'!$A:$A,'Gap Analysis update'!$A21,'MoDi Initiatives'!$C:$C,'Gap Analysis update'!$B$7,'MoDi Initiatives'!$B:$B,'Gap Analysis update'!U$2) -> -0.0076645176 | V21: =SUMIFS('MoDi Initiatives'!T:T,'MoDi Initiatives'!$E:$E,'Gap Analysis update'!$B21,'MoDi Initiatives'!$A:$A,'Gap Analysis update'!$A21,'MoDi Initiatives'!$B:$B,'Gap Analysis update'!V$2)-SUMIFS('MoDi Initiatives'!T:T,'MoDi Initiatives'!$E:$E,'Gap Analysis update'!$B21,'MoDi Initiatives'!$A:$A,'Gap Analysis update'!$A21,'MoDi Initiatives'!$C:$C,'Gap Analysis update'!$B$7,'MoDi Initiatives'!$B:$B,'Gap Analysis update'!V$2) -> 0 | W21: =SUMIFS('MoDi Initiatives'!U:U,'MoDi Initiatives'!$E:$E,'Gap Analysis update'!$B21,'MoDi Initiatives'!$A:$A,'Gap Analysis update'!$A21,'MoDi Initiatives'!$B:$B,'Gap Analysis update'!W$2)-SUMIFS('MoDi Initiatives'!U:U,'MoDi Initiatives'!$E:$E,'Gap Analysis update'!$B21,'MoDi Initiatives'!$A:$A,'Gap Analysis update'!$A21,'MoDi Initiatives'!$C:$C,'Gap Analysis update'!$B$7,'MoDi Initiatives'!$B:$B,'Gap Analysis update'!W$2) -> 0 | X21: =SUMIFS('MoDi Initiatives'!V:V,'MoDi Initiatives'!$E:$E,'Gap Analysis update'!$B21,'MoDi Initiatives'!$A:$A,'Gap Analysis update'!$A21,'MoDi Initiatives'!$B:$B,'Gap Analysis update'!X$2)-SUMIFS('MoDi Initiatives'!V:V,'MoDi Initiatives'!$E:$E,'Gap Analysis update'!$B21,'MoDi Initiatives'!$A:$A,'Gap Analysis update'!$A21,'MoDi Initiatives'!$C:$C,'Gap Analysis update'!$B$7,'MoDi Initiatives'!$B:$B,'Gap Analysis update'!X$2) -> 0 | Y21: =SUMIFS('MoDi Initiatives'!W:W,'MoDi Initiatives'!$E:$E,'Gap Analysis update'!$B21,'MoDi Initiatives'!$A:$A,'Gap Analysis update'!$A21,'MoDi Initiatives'!$B:$B,'Gap Analysis update'!Y$2)-SUMIFS('MoDi Initiatives'!W:W,'MoDi Initiatives'!$E:$E,'Gap Analysis update'!$B21,'MoDi Initiatives'!$A:$A,'Gap Analysis update'!$A21,'MoDi Initiatives'!$C:$C,'Gap Analysis update'!$B$7,'MoDi Initiatives'!$B:$B,'Gap Analysis update'!Y$2) -> 0 | AB21: =SUMIFS('MoDi Initiatives'!H:H,'MoDi Initiatives'!$E:$E,'Gap Analysis update'!$B21,'MoDi Initiatives'!$A:$A,'Gap Analysis update'!$A21,'MoDi Initiatives'!$B:$B,'Gap Analysis update'!AB$2)-SUMIFS('MoDi Initiatives'!H:H,'MoDi Initiatives'!$E:$E,'Gap Analysis update'!$B21,'MoDi Initiatives'!$A:$A,'Gap Analysis update'!$A21,'MoDi Initiatives'!$B:$B,'Gap Analysis update'!AB$2,'MoDi Initiatives'!$C:$C,'Gap Analysis update'!$B$7) -> 0 | AC21: =SUMIFS('MoDi Initiatives'!I:I,'MoDi Initiatives'!$E:$E,'Gap Analysis update'!$B21,'MoDi Initiatives'!$A:$A,'Gap Analysis update'!$A21,'MoDi Initiatives'!$B:$B,'Gap Analysis update'!AC$2)-SUMIFS('MoDi Initiatives'!I:I,'MoDi Initiatives'!$E:$E,'Gap Analysis update'!$B21,'MoDi Initiatives'!$A:$A,'Gap Analysis update'!$A21,'MoDi Initiatives'!$B:$B,'Gap Analysis update'!AC$2,'MoDi Initiatives'!$C:$C,'Gap Analysis update'!$B$7) -> 0 | AD21: =SUMIFS('MoDi Initiatives'!J:J,'MoDi Initiatives'!$E:$E,'Gap Analysis update'!$B21,'MoDi Initiatives'!$A:$A,'Gap Analysis update'!$A21,'MoDi Initiatives'!$B:$B,'Gap Analysis update'!AD$2)-SUMIFS('MoDi Initiatives'!J:J,'MoDi Initiatives'!$E:$E,'Gap Analysis update'!$B21,'MoDi Initiatives'!$A:$A,'Gap Analysis update'!$A21,'MoDi Initiatives'!$B:$B,'Gap Analysis update'!AD$2,'MoDi Initiatives'!$C:$C,'Gap Analysis update'!$B$7) -> -0.0076105652 | AE21: =SUMIFS('MoDi Initiatives'!K:K,'MoDi Initiatives'!$E:$E,'Gap Analysis update'!$B21,'MoDi Initiatives'!$A:$A,'Gap Analysis update'!$A21,'MoDi Initiatives'!$B:$B,'Gap Analysis update'!AE$2)-SUMIFS('MoDi Initiatives'!K:K,'MoDi Initiatives'!$E:$E,'Gap Analysis update'!$B21,'MoDi Initiatives'!$A:$A,'Gap Analysis update'!$A21,'MoDi Initiatives'!$B:$B,'Gap Analysis update'!AE$2,'MoDi Initiatives'!$C:$C,'Gap Analysis update'!$B$7) -> 0 | AF21: =SUMIFS('MoDi Initiatives'!L:L,'MoDi Initiatives'!$E:$E,'Gap Analysis update'!$B21,'MoDi Initiatives'!$A:$A,'Gap Analysis update'!$A21,'MoDi Initiatives'!$B:$B,'Gap Analysis update'!AF$2)-SUMIFS('MoDi Initiatives'!L:L,'MoDi Initiatives'!$E:$E,'Gap Analysis update'!$B21,'MoDi Initiatives'!$A:$A,'Gap Analysis update'!$A21,'MoDi Initiatives'!$B:$B,'Gap Analysis update'!AF$2,'MoDi Initiatives'!$C:$C,'Gap Analysis update'!$B$7) -> 0 | AG21: =SUMIFS('MoDi Initiatives'!M:M,'MoDi Initiatives'!$E:$E,'Gap Analysis update'!$B21,'MoDi Initiatives'!$A:$A,'Gap Analysis update'!$A21,'MoDi Initiatives'!$B:$B,'Gap Analysis update'!AG$2)-SUMIFS('MoDi Initiatives'!M:M,'MoDi Initiatives'!$E:$E,'Gap Analysis update'!$B21,'MoDi Initiatives'!$A:$A,'Gap Analysis update'!$A21,'MoDi Initiatives'!$B:$B,'Gap Analysis update'!AG$2,'MoDi Initiatives'!$C:$C,'Gap Analysis update'!$B$7) -> 0 | AH21: =SUMIFS('MoDi Initiatives'!N:N,'MoDi Initiatives'!$E:$E,'Gap Analysis update'!$B21,'MoDi Initiatives'!$A:$A,'Gap Analysis update'!$A21,'MoDi Initiatives'!$B:$B,'Gap Analysis update'!AH$2)-SUMIFS('MoDi Initiatives'!N:N,'MoDi Initiatives'!$E:$E,'Gap Analysis update'!$B21,'MoDi Initiatives'!$A:$A,'Gap Analysis update'!$A21,'MoDi Initiatives'!$B:$B,'Gap Analysis update'!AH$2,'MoDi Initiatives'!$C:$C,'Gap Analysis update'!$B$7) -> 0 | AI21: =SUMIFS('MoDi Initiatives'!O:O,'MoDi Initiatives'!$E:$E,'Gap Analysis update'!$B21,'MoDi Initiatives'!$A:$A,'Gap Analysis update'!$A21,'MoDi Initiatives'!$B:$B,'Gap Analysis update'!AI$2)-SUMIFS('MoDi Initiatives'!O:O,'MoDi Initiatives'!$E:$E,'Gap Analysis update'!$B21,'MoDi Initiatives'!$A:$A,'Gap Analysis update'!$A21,'MoDi Initiatives'!$B:$B,'Gap Analysis update'!AI$2,'MoDi Initiatives'!$C:$C,'Gap Analysis update'!$B$7) -> 0 | AJ21: =SUMIFS('MoDi Initiatives'!P:P,'MoDi Initiatives'!$E:$E,'Gap Analysis update'!$B21,'MoDi Initiatives'!$A:$A,'Gap Analysis update'!$A21,'MoDi Initiatives'!$B:$B,'Gap Analysis update'!AJ$2)-SUMIFS('MoDi Initiatives'!P:P,'MoDi Initiatives'!$E:$E,'Gap Analysis update'!$B21,'MoDi Initiatives'!$A:$A,'Gap Analysis update'!$A21,'MoDi Initiatives'!$B:$B,'Gap Analysis update'!AJ$2,'MoDi Initiatives'!$C:$C,'Gap Analysis update'!$B$7) -> 0 | AK21: =SUMIFS('MoDi Initiatives'!Q:Q,'MoDi Initiatives'!$E:$E,'Gap Analysis update'!$B21,'MoDi Initiatives'!$A:$A,'Gap Analysis update'!$A21,'MoDi Initiatives'!$B:$B,'Gap Analysis update'!AK$2)-SUMIFS('MoDi Initiatives'!Q:Q,'MoDi Initiatives'!$E:$E,'Gap Analysis update'!$B21,'MoDi Initiatives'!$A:$A,'Gap Analysis update'!$A21,'MoDi Initiatives'!$B:$B,'Gap Analysis update'!AK$2,'MoDi Initiatives'!$C:$C,'Gap Analysis update'!$B$7) -> 0 | AL21: =SUMIFS('MoDi Initiatives'!R:R,'MoDi Initiatives'!$E:$E,'Gap Analysis update'!$B21,'MoDi Initiatives'!$A:$A,'Gap Analysis update'!$A21,'MoDi Initiatives'!$B:$B,'Gap Analysis update'!AL$2)-SUMIFS('MoDi Initiatives'!R:R,'MoDi Initiatives'!$E:$E,'Gap Analysis update'!$B21,'MoDi Initiatives'!$A:$A,'Gap Analysis update'!$A21,'MoDi Initiatives'!$B:$B,'Gap Analysis update'!AL$2,'MoDi Initiatives'!$C:$C,'Gap Analysis update'!$B$7) -> -0.0076645176 | AM21: =SUMIFS('MoDi Initiatives'!S:S,'MoDi Initiatives'!$E:$E,'Gap Analysis update'!$B21,'MoDi Initiatives'!$A:$A,'Gap Analysis update'!$A21,'MoDi Initiatives'!$B:$B,'Gap Analysis update'!AM$2)-SUMIFS('MoDi Initiatives'!S:S,'MoDi Initiatives'!$E:$E,'Gap Analysis update'!$B21,'MoDi Initiatives'!$A:$A,'Gap Analysis update'!$A21,'MoDi Initiatives'!$B:$B,'Gap Analysis update'!AM$2,'MoDi Initiatives'!$C:$C,'Gap Analysis update'!$B$7) -> 0 | AN21: =SUMIFS('MoDi Initiatives'!T:T,'MoDi Initiatives'!$E:$E,'Gap Analysis update'!$B21,'MoDi Initiatives'!$A:$A,'Gap Analysis update'!$A21,'MoDi Initiatives'!$B:$B,'Gap Analysis update'!AN$2)-SUMIFS('MoDi Initiatives'!T:T,'MoDi Initiatives'!$E:$E,'Gap Analysis update'!$B21,'MoDi Initiatives'!$A:$A,'Gap Analysis update'!$A21,'MoDi Initiatives'!$B:$B,'Gap Analysis update'!AN$2,'MoDi Initiatives'!$C:$C,'Gap Analysis update'!$B$7) -> 0 | AO21: =SUMIFS('MoDi Initiatives'!U:U,'MoDi Initiatives'!$E:$E,'Gap Analysis update'!$B21,'MoDi Initiatives'!$A:$A,'Gap Analysis update'!$A21,'MoDi Initiatives'!$B:$B,'Gap Analysis update'!AO$2)-SUMIFS('MoDi Initiatives'!U:U,'MoDi Initiatives'!$E:$E,'Gap Analysis update'!$B21,'MoDi Initiatives'!$A:$A,'Gap Analysis update'!$A21,'MoDi Initiatives'!$B:$B,'Gap Analysis update'!AO$2,'MoDi Initiatives'!$C:$C,'Gap Analysis update'!$B$7) -> 0 | AP21: =SUMIFS('MoDi Initiatives'!V:V,'MoDi Initiatives'!$E:$E,'Gap Analysis update'!$B21,'MoDi Initiatives'!$A:$A,'Gap Analysis update'!$A21,'MoDi Initiatives'!$B:$B,'Gap Analysis update'!AP$2)-SUMIFS('MoDi Initiatives'!V:V,'MoDi Initiatives'!$E:$E,'Gap Analysis update'!$B21,'MoDi Initiatives'!$A:$A,'Gap Analysis update'!$A21,'MoDi Initiatives'!$B:$B,'Gap Analysis update'!AP$2,'MoDi Initiatives'!$C:$C,'Gap Analysis update'!$B$7) -> 0 | AQ21: =SUMIFS('MoDi Initiatives'!W:W,'MoDi Initiatives'!$E:$E,'Gap Analysis update'!$B21,'MoDi Initiatives'!$A:$A,'Gap Analysis update'!$A21,'MoDi Initiatives'!$B:$B,'Gap Analysis update'!AQ$2)-SUMIFS('MoDi Initiatives'!W:W,'MoDi Initiatives'!$E:$E,'Gap Analysis update'!$B21,'MoDi Initiatives'!$A:$A,'Gap Analysis update'!$A21,'MoDi Initiatives'!$B:$B,'Gap Analysis update'!AQ$2,'MoDi Initiatives'!$C:$C,'Gap Analysis update'!$B$7) -> 0 | AT21: =AB21-J21 -> 0 | AU21: =AC21-K21 -> 0 | AV21: =AD21-L21 -> -0.0076105652 | AW21: =AE21-M21 -> 0.0076645176 | AX21: =AF21-N21 -> 0 | AY21: =AG21-O21 -> 0 | AZ21: =AH21-P21 -> 0 | BA21: =AI21-Q21 -> 0 | ... BI21: =AQ21-Y21 -> 0
