Workbook
Name \A: #REF!
Name \A: #REF!
Name \C: #REF!
Name \C: #REF!
Name \D: #REF!
Name \D: #REF!
Name \W: #REF!
Name \W: #REF!
Name _: #REF!
Name _: #REF!
Name __: #REF!
Name __: #REF!
Name ___: #REF!
Name ___: #REF!
Name ______0: #REF!
Name ______0: #REF!
Name ______0___0: #REF!
Name ______0___0: #REF!
Name ______4: "$"
Name ______5: "$"
Name ______6: "$"
Name __m72: {"傳各位表單.xls","Sheet1"}
Name __m72: {"傳各位表單.xls","Sheet1"}
Name __m72_1: {"傳各位表單.xls","Sheet1"}
Name __m72_1: {"傳各位表單.xls","Sheet1"}
Name __m72_2: {"傳各位表單.xls","Sheet1"}
Name __m72_2: {"傳各位表單.xls","Sheet1"}
Name __m72_3: {"傳各位表單.xls","Sheet1"}
Name __m72_3: {"傳各位表單.xls","Sheet1"}
Name __m72_4: {"傳各位表單.xls","Sheet1"}
Name __m72_4: {"傳各位表單.xls","Sheet1"}
Name _017: #REF!
Name _017: #REF!
Name _024: #REF!
Name _024: #REF!
Name _039: #REF!
Name _039: #REF!
Name _1.: #REF!
Name _1.: #REF!
Name _1_0: #REF!
Name _1_0: #REF!
Name _17__cycle_time: #REF!
Name _17__cycle_time: #REF!
Name _1A: #REF!
Name _1A: #REF!
Name _2_00: #REF!
Name _2_00: #REF!
Name _20__cycle_time: #REF!
Name _20__cycle_time: #REF!
Name _2C_: #REF!
Name _2C_: #REF!
Name _3_000: #REF!
Name _3_000: #REF!
Name _3D: #REF!
Name _3D: #REF!
Name _4W: #REF!
Name _4W: #REF!
Name _AB12: #REF!
Name _AB12: #REF!
Name _RMX1: #REF!

Sheet Pivot
B2: Liabilities Dashboard
B3: Summary
F5: Values
B6: Project | C6: Description Item | D6: Start Date | E6: End Date | F6: Sum of Investment (GBP) | G6: Sum of Balance (GBP) Nov'24
B7: Alto | C7: Addendum No.10 - Indonesia | D7: 44682 | F7: 33083222 | G7: 20218013
C8: Addendum No.10 - Indonesia Total | F8: 33083222 | G8: 20218013
C9: Alto Blister Reduction Capex | D9: 45588 | F9: 712555.8 | G9: 655272.72
C10: Alto Blister Reduction Capex Total | F10: 712555.8 | G10: 655272.72
C11: Alto Pod Investment fee for Inkjet printing | D11: 45344 | F11: 1624734.3
C12: Alto Pod Investment fee for Inkjet printing Total | F12: 1624734.3
C13: Alto tooling | D13: 44857 | F13: 7011014.5 | G13: 0
C14: Alto tooling Total | F14: 7011014.5 | G14: 0
C15: Alto tooling(IM tooling for 2p cost reduction) | D15: 44980 | F15: 4099802.5 | G15: 0
C16: Alto tooling(IM tooling for 2p cost reduction) Total | F16: 4099802.5 | G16: 0
C17: Device to Indo Equipment move cost | D17: 45345 | F17: 522701.32 | G17: 313714.88
C18: Device to Indo Equipment move cost Total | F18: 522701.32 | G18: 313714.88
C19: Prismastic China project capex | D19: - | F19: 177315.67
C20: Prismastic China project capex Total | F20: 177315.67
B21: Alto Total | F21: 47231346 | G21: 21187001
B22: Alto & Hestia & Epod | F22: 57899223 | G22: 17249276
B23: Aquila-US | F23: 168020.31 | G23: 168020.31
B24: BOX 1K | F24: 445583.44 | G24: 293264.27
B25: DP 1500 | F25: 850699.38 | G25: 172500.96
B26: epod 2 Device | F26: 61960.751 | G26: 0
B27: Epod 3 | F27: 92759.557 | G27: 0
B28: epod 3 Device | F28: 172492.38 | G28: 127582.86
B29: Epod 3+ | F29: 153994.03 | G29: 0
B30: epod 3+ Device | F30: 217261.05 | G30: 206107.17
B31: Epod&Modi | F31: 81025.598 | G31: 37497.213
B32: ePod2 POD | F32: 2669816.1 | G32: 0
... B37: Kuma | F37: 1239135.6 | G37: 1095337.6
B38: Kuma | F38: 0
B39: Kuma E 2.0 | F39: 1010585.6 | G39: 1010585.6
B40: Kuma E 2.0 Box | F40: 66034.728 | G40: 66034.728
B41: Kuma E 2.0 Pen NZ | F41: 81241.212 | G41: 81241.212
B42: Kuma E Max | F42: 78619.796 | G42: 78619.796
B43: Mimosa 1.0 | F43: 1177357 | G43: 1177357
B44: Mimosa Smart Box PB88 | F44: 192713.82 | G44: 192713.82
B45: Modi | F45: 327949.16 | G45: 309519.5
B46: Modi 2.0 | F46: 7928735.4 | G46: 6770218.6
B47: Prismatic Pod | F47: 977777.79 | G47: 974239.5
B48: Sensa | F48: 785493.73 | G48: 772153.73
B49: VEGA | F49: 8085896.2 | G49: 5603772.9
B50: Grand Total | F50: 1.4675389e+08 | G50: 65914254

Sheet By Project -Feb 2025
Q1: CNY | R1: GBP
C2: Investment/Liabilities Dashboard | Q2: =34746341 -> 34746341 | R2: =Q2/8.812 -> 3943070.9
C3: New Categories - Vapour | Q3: 24216741 | R3: =Q3/8.812 -> 2748154.9
R4: =SUM(R2:R3) -> 6691225.8
A5: USD-GBP | B5: 1.27818
A6: RMB-GBP | B6: 9.19774 | AS6: SC update
AA7: Tooling Capex | AB7: Tooling Capex | AC7: Tooling Capex | AD7: Tooling Capex | AE7: Actual Shipment Qty | AT7: Forecast (pls link tab'Summary') | BH7: BAT Demand Waterfall
A9: # | B9: Unique Ref Number | C9: Project | D9: Project Description | E9: Portfolio | F9: Platform | G9: Location | H9: Type | I9: Portfolio1 | J9: Tier | K9: Supplier | L9: Contracting Entity | M9: Start Date | N9: End Date | O9: Investment Quotation | P9: Investment Currency | Q9: Investment (GBP) | R9: Committed PO Volume | S9: Amortization per Unit | T9: Payment Type | U9: Amortization _x000D_ per Unit (GBP) | V9: Cumulative Vol. (from start date) | W9: % Finished | X9: Balance(Feb'25) | Y9: Balance1 | Z9: Status | AA9: % Finished | AB9: Total Paid Investment Currency | AC9: Balance2 | AD9: Remaining Vol required | AE9: Y2021 | AF9: Y2022 | AG9: Y2023 | AH9: 45292 | AI9: 45323 | AJ9: 45352 | AK9: 45383 | AL9: 45413 | AM9: 45444 | AN9: 45474 | AO9: 45505 | AP9: 45536 | AQ9: 45566 | AR9: 45597 | AS9: 45627 | AT9: 45658 | AU9: 45689 | AV9: 45717 | AW9: 45748 | AX9: 45778 | AY9: 45809 | AZ9: 45839 | BA9: 45870 | BB9: 45901 | BC9: 45931 | BD9: 45962 | BE9: 45992 | BF9: YTG 2025 | BH9: T2 Product | BI9: Version | BJ9: Customer | BK9: SOP Date | BL9: Product | BM9: 2021 | BN9: 2022 | BO9: 2023 | BP9: 2024 | BQ9: 44197 | BR9: 44228 | BS9: 44256 | BT9: 44287 | BU9: 44317 | BV9: 44348 | BW9: 44378 | BX9: 44409 | BY9: 44440 | BZ9: 44470 | CA9: 44501 | CB9: 44531 | CD9: 44562 | CE9: 44593 | CF9: 44621 | CG9: 44652 | CH9: 44682 | CI9: 44713 | CJ9: 44743 | CK9: 44774 | CL9: 44805 | CM9: 44835 | CN9: 44866 | CO9: 44896 | CP9: 44927 | CQ9: 44958 | CR9: 44986 | CS9: 45017 | CT9: 45047 | CU9: 45078 | CV9: 45108 | CW9: 45139 | CX9: 45170 | CY9: 45200 | CZ9: 45231 | DA9: 45261 | DB9: 45292 | DC9: 45323 | DD9: 45352 | DE9: 45383 | DF9: 45413 | DG9: 45444 | DH9: 45474 | DI9: 45505 | DJ9: 45536 | DK9: 45566 | DL9: 45597 | DM9: 45627 | DN9: 45658 | DO9: 45689 | DP9: 45717 | DQ9: 45748 | DR9: 45778 | DS9: 45809 | DT9: 45839 | DU9: 45870 | DV9: 45901 | DW9: 45931 | DX9: 45962 | DY9: 45992
A10: 1 | B10: RF001_Alto &ePod | C10: Alto & ePod | D10: APA - Automation Production Agreement | E10: Pod | F10: Pod | G10: Indo | H10: Pod Automation (initial Investment) | I10: RCS | J10: T1 | K10: Smoore T1 | L10: Reynolds | M10: 44197 | N10: 46722 | O10: 72000000 | P10: USD | Q10: =IF(P10="RMB",O10/$B$6,IF(P10="GBP",O10,O10/$B$5)) -> 56330094 | R10: 2570000000 | S10: Volume | T10: By Volume | U10: =IF(T10="By Unit", IF(P10="RMB",S10/$B$6,IF(P10="GBP",S10,S10/$B$5)),T10) -> By Volume | V10: =SUM(AE10:AU10) -> 1940686118 | W10: =IF($T10="By Volume",V10/$R10,V10*$U10/$Q10) -> 0.75513079 | X10: =IFERROR($Q10*(1-W10),"") -> 13793506 | Y10: =IF(X10>0,X10,0) -> 13793506 | Z10: Under Amortization | AD10: =IF(U10="By Volume",(1-W10)*R10,X10/U10) -> 629313882 | AE10: 523716080 | AF10: 471530346 | AG10: 404870290 | AH10: 34094250 | AI10: 27982380 | AJ10: 35881250 | AK10: 33715264 | AL10: 49761762 | AM10: 49968522 | AN10: 46294918 | AO10: 57860634 | AP10: 36903554 | AQ10: 32308514 | AR10: 34612990 | AS10: 28195840 | AT10: ='By Project -Feb 2025'!DN10+'By Project -Feb 2025'!DN11+'By Project -Feb 2025'!DN22+'By Project -Feb 2025'!DN34+'By Project -Feb 2025'!DN59+'By Project -Feb 2025'!DN62 -> 48220474 | AU10: ='By Project -Feb 2025'!DO10+'By Project -Feb 2025'!DO11+'By Project -Feb 2025'!DO22+'By Project -Feb 2025'!DO34+'By Project -Feb 2025'!DO59+'By Project -Feb 2025'!DO62 -> 24769050 | AV10: ='By Project -Feb 2025'!DP10+'By Project -Feb 2025'!DP11+'By Project -Feb 2025'!DP22+'By Project -Feb 2025'!DP34+'By Project -Feb 2025'!DP59+'By Project -Feb 2025'!DP62 -> 67126382 | AW10: ='By Project -Feb 2025'!DQ10+'By Project -Feb 2025'!DQ11+'By Project -Feb 2025'!DQ22+'By Project -Feb 2025'!DQ34+'By Project -Feb 2025'!DQ59+'By Project -Feb 2025'!DQ62 -> 61797920 | AX10: ='By Project -Feb 2025'!DR10+'By Project -Feb 2025'!DR11+'By Project -Feb 2025'!DR22+'By Project -Feb 2025'!DR34+'By Project -Feb 2025'!DR59+'By Project -Feb 2025'!DR62 -> 42129688 | AY10: ='By Project -Feb 2025'!DS10+'By Project -Feb 2025'!DS11+'By Project -Feb 2025'!DS22+'By Project -Feb 2025'!DS34+'By Project -Feb 2025'!DS59+'By Project -Feb 2025'!DS62 -> 42064888 | AZ10: ='By Project -Feb 2025'!DT10+'By Project -Feb 2025'!DT11+'By Project -Feb 2025'!DT22+'By Project -Feb 2025'!DT34+'By Project -Feb 2025'!DT59+'By Project -Feb 2025'!DT62 -> 45832074 | BA10: ='By Project -Feb 2025'!DU10+'By Project -Feb 2025'!DU11+'By Project -Feb 2025'!DU22+'By Project -Feb 2025'!DU34+'By Project -Feb 2025'!DU59+'By Project -Feb 2025'!DU62 -> 50460345 | ... BE10: ='By Project -Feb 2025'!DY10+'By Project -Feb 2025'!DY11+'By Project -Feb 2025'!DY22+'By Project -Feb 2025'!DY34+'By Project -Feb 2025'!DY59+'By Project -Feb 2025'!DY62 -> 46771803 | BF10: =SUM(AV10:BE10) -> 4.9956899e+08 | BH10: epod2 pod | BI10: SOP01.0 | BJ10: BAT | BK10: 45698 | BL10: ePod2 Cartridges | BM10: 150444920 | BN10: 202559713 | BO10: 91785440 | BP10: 12656900 | BQ10: 9366300 | BR10: 5088060 | BS10: 10606320 | BT10: 9598860 | BU10: 14671980 | BV10: 14349580 | BW10: 12979220 | BX10: 15256580 | BY10: 15964420 | BZ10: 12569000 | CA10: 15497160 | CB10: 14497440 | CD10: 15559440 | CE10: 12012360 | CF10: 18465130 | CG10: 19798430 | CH10: 20944920 | CI10: 17632262 | CJ10: 15720521 | CK10: 13104480 | CL10: 29618660 | CM10: 11285460 | CN10: 13803750 | CO10: 14614300 | CP10: 8764100 | CQ10: 8606700 | CR10: 16334000 | CS10: 12069960 | CT10: 7439980 | CU10: 7699880 | CV10: 3856460 | CW10: 4664000 | CX10: 6591860 | CY10: 4137070 | CZ10: 7758370 | DA10: 3863060 | DB10: 4132280 | DC10: 2737600 | DD10: 3241380 | DE10: 839240 | DF10: 607680 | DG10: 543780 | DH10: 136620 | DI10: 20160 | DJ10: 20160 | DK10: 0 | DL10: 216720 | DM10: 161280 | DN10: 0 | DO10: 15120 | DP10: 20160 | DQ10: 65520 | DR10: 0 | DS10: 0 | DT10: 0 | DU10: 0 | DV10: 0 | DW10: 0 | DX10: 0 | DY10: 0 | EA10: APA - Automation Production Agreement
A11: 2 | B11: RF002_Alto | C11: Alto | D11: Addendum No.10 - Indonesia | E11: Pod | F11: Pod | G11: Indo | H11: Indo Facility | I11: RCS | J11: T1 | K11: Smoore T1 | L11: Reynolds | M11: 44682 | N11: 46722 | O11: 41140309 | P11: USD | Q11: =IF(P11="RMB",O11/$B$6,IF(P11="GBP",O11,O11/$B$5)) -> 32186632 | R11: 2340000000 | S11: 0.0152 | T11: By Unit | U11: =IF(T11="By Unit", IF(P11="RMB",S11/$B$6,IF(P11="GBP",S11,S11/$B$5)),T11) -> 0.011891909 | V11: =SUM(AE11:AU11) -> 750520050 | W11: =((328822613*0.0321)+(V11-328822613)*S11)/O11 -> 0.41236945 | X11: =IFERROR(Q11*(1-W11),"") -> 18913848 | Y11: =IF(X11>0,X11,0) -> 18913848 | Z11: Under Amortization | AD11: =IF(U11="By Volume",(1-W11)*R11,X11/U11) -> 1.5904804e+09 | AF11: 195500900 | AG11: 255515000 | AH11: 22785000 | AI11: 22092200 | AJ11: 25589000 | AK11: 18498600 | AL11: 30742700 | AM11: 18494250 | AN11: 25532300 | AO11: 28932600 | AP11: 11088600 | AQ11: 14612550 | AR11: 17543850 | AS11: 18060400 | AT11: =DN59+DN62 -> 29540200 | AU11: =DO59+DO62 -> 15991900 | AV11: =DP59+DP62 -> 46417950 | AW11: =DQ59+DQ62 -> 39955200 | AX11: =DR59+DR62 -> 25506950 | AY11: =DS59+DS62 -> 21583600 | AZ11: =DT59+DT62 -> 27502550 | BA11: =DU59+DU62 -> 22651600 | ... BE11: =DY59+DY62 -> 25626000 | BF11: =SUM(AV11:BE11) -> 276304400 | BH11: ePod 3 Pod | BI11: SOP01.0 | BJ11: BAT | BK11: 45698 | BL11: ePod3 Cartridges | BM11: 0 | BN11: 0 | BO11: 49538050 | BP11: 52288270 | CD11: 0 | CE11: 0 | CF11: 0 | CG11: 0 | CH11: 0 | CI11: 0 | CJ11: 0 | CK11: 0 | CL11: 0 | CM11: 0 | CN11: 0 | CO11: 0 | CP11: 0 | CQ11: 0 | CR11: 136620 | CS11: 1201500 | CT11: 2856870 | CU11: 5365530 | CV11: 6736500 | CW11: 6646410 | CX11: 9393120 | CY11: 8034750 | CZ11: 6721830 | DA11: 2444920 | DB11: 7133770 | DC11: 3013380 | DD11: 6978870 | DE11: 4888410 | DF11: 4624920 | DG11: 6254730 | DH11: 5871600 | DI11: 5959710 | DJ11: 5151780 | DK11: 2354220 | DL11: 56880 | DM11: 0 | DN11: 196560 | DO11: 0 | DP11: 0 | DQ11: 0 | DR11: 0 | DS11: 0 | DT11: 0 | DU11: 0 | DV11: 0 | DW11: 0 | DX11: 0 | DY11: 0 | EA11: APA - Automation Production Agreement
A12: 4 | B12: RF003_Alto | C12: Alto | D12: Alto Pod Investment fee for Inkjet printing | E12: Pod | F12: Pod | G12: Indo | H12: Asset - Others | I12: RCS | J12: T1 | K12: Smoore T1 | L12: Reynolds | M12: 45344 | N12: - | O12: 2020422.1 | P12: USD | Q12: =IF(P12="RMB",O12/$B$6,IF(P12="GBP",O12,O12/$B$5)) -> 1580702.4 | R12: 0 | S12: n/a | U12: =IF(T12="By Unit", IF(P12="RMB",S12/$B$6,IF(P12="GBP",S12,S12/$B$5)),T12) -> 0 | V12: =SUM(AE12:AS12) -> 0 | W12: =1-X12/Q12 -> 1 | X12: 0 | Y12: 0 | Z12: Paid-off | BF12: =SUM(AV12:BE12) -> 0 | BH12: Hestia 1.0 | BI12: SOP01.0 | BJ12: BAT | BK12: 45698 | BL12: Hestia | BM12: 0 | BN12: 0 | BO12: 0 | BP12: 119534880 | CD12: 0 | CE12: 0 | CF12: 0 | CG12: 0 | CH12: 0 | CI12: 0 | CJ12: 0 | CK12: 0 | CL12: 0 | CM12: 0 | CN12: 0 | CO12: 0 | CP12: 0 | CQ12: 0 | CR12: 0 | CS12: 0 | CT12: 0 | CU12: 0 | CV12: 0 | CW12: 0 | CX12: 0 | CY12: 0 | CZ12: 0 | DA12: 0 | DB12: 0 | DC12: 0 | DD12: 0 | DE12: 4141170 | DF12: 10303470 | DG12: 18112860 | DH12: 12666060 | DI12: 17188320 | DJ12: 15151590 | DK12: 12838860 | DL12: 13199850 | DM12: 15932700 | DN12: 17350470 | DO12: 7948260 | DP12: 19106540 | DQ12: 20397590 | DR12: 14871760 | DS12: 18739530 | DT12: 17118810 | DU12: 26215830 | DV12: 23149370 | DW12: 21619420 | DX12: 27275260 | DY12: 19757020 | EA12: Hestia 1.0 Automation Lines Modification (Modified from ePod3 to Hestia1.0) (1-4 line)
A13: 5 | B13: RF004_Alto | C13: Alto | D13: Device to Indo Equipment move cost | E13: RCS | F13: Vuse Device( US Alto) | G13: Indo | H13: Asset - RCS Device line | I13: RCS | J13: T1 | K13: Smoore T1 | L13: Reynolds | M13: 45345 | N13: 46722 | O13: 650000 | P13: USD | Q13: =IF(P13="RMB",O13/$B$6,IF(P13="GBP",O13,O13/$B$5)) -> 508535.57 | R13: 20000000 | S13: 0.032288552 | T13: By Unit | U13: =IF(T13="By Unit", IF(P13="RMB",S13/$B$6,IF(P13="GBP",S13,S13/$B$5)),T13) -> 0.02526135 | V13: =SUM(AE13:AU13) -> 11689500 | W13: =IF(T13="By Volume",V13/R13,V13*U13/Q13) -> 0.58067235 | X13: =IFERROR(Q13*(1-W13),"") -> 213243.03 | Y13: =IF(X13>0,X13,0) -> 213243.03 | Z13: Under Amortization | AD13: =IF(U13="By Volume",(1-W13)*R13,X13/U13) -> 8441474 | AI13: 816200 | AJ13: 663600 | AK13: 138600 | AL13: 662000 | AM13: 213750 | AN13: 845900 | AO13: 950400 | AP13: 1489800 | AQ13: 1329750 | AR13: 886650 | AS13: 1550250 | AT13: ='By Project -Feb 2025'!DN57+'By Project -Feb 2025'!DN58 -> 1243800 | AU13: ='By Project -Feb 2025'!DO57+'By Project -Feb 2025'!DO58 -> 898800 | AV13: ='By Project -Feb 2025'!DP57+'By Project -Feb 2025'!DP58 -> 924150 | AW13: ='By Project -Feb 2025'!DQ57+'By Project -Feb 2025'!DQ58 -> 466200 | AX13: ='By Project -Feb 2025'!DR57+'By Project -Feb 2025'!DR58 -> 1068350 | AY13: ='By Project -Feb 2025'!DS57+'By Project -Feb 2025'!DS58 -> 721000 | AZ13: ='By Project -Feb 2025'!DT57+'By Project -Feb 2025'!DT58 -> 869750 | BA13: ='By Project -Feb 2025'!DU57+'By Project -Feb 2025'!DU58 -> 750400 | ... BE13: ='By Project -Feb 2025'!DY57+'By Project -Feb 2025'!DY58 -> 802200 | BF13: =SUM(AV13:BE13) -> 8017400 | BH13: Hestia 1.1 | BI13: SOP01.0 | BJ13: BAT | BK13: 45698 | BL13: Hestia 1.1 | BM13: 0 | BN13: 0 | BO13: 0 | BP13: 0 | DB13: 0 | DC13: 0 | DD13: 0 | DE13: 0 | DF13: 0 | DG13: 0 | DH13: 0 | DI13: 0 | DJ13: 0 | DK13: 0 | DL13: 0 | DM13: 0 | DN13: 0 | DO13: 0 | DP13: 0 | DQ13: 0 | DR13: 0 | DS13: 0 | DT13: 0 | DU13: 0 | DV13: 0 | DW13: 0 | DX13: 0 | DY13: 0
A14: 6 | B14: RF005_Alto | C14: Alto | D14: Alto Blister Reduction Capex | E14: Pod | F14: Pod | G14: Indo | H14: Asset - Others | I14: RCS | J14: T1 | K14: Smoore T1 | L14: Reynolds | M14: 45597 | N14: 46722 | O14: 886091.64 | P14: USD | Q14: =IF(P14="RMB",O14/$B$6,IF(P14="GBP",O14,O14/$B$5)) -> 693244.8 | R14: 400000000 | S14: =O14/R14 -> 0.0022152291 | T14: By Unit | U14: =IF(T14="By Unit", IF(P14="RMB",S14/$B$6,IF(P14="GBP",S14,S14/$B$5)),T14) -> 0.001733112 | V14: =SUM(AE14:AU14) -> 76591800 | W14: =IF(T14="By Volume",V14/R14,V14*U14/Q14) -> 0.1914795 | X14: =IFERROR(Q14*(1-W14),"") -> 560502.63 | Y14: =IF(X14>0,X14,0) -> 560502.63 | Z14: Under Amortization | AD14: =IF(U14="By Volume",(1-W14)*R14,X14/U14) -> 3.234082e+08 | AR14: 16056000 | AS14: 13005000 | AT14: 30684600 | AU14: 16846200 | AV14: ='By Project -Feb 2025'!DP59*98% -> 45442551 | AW14: ='By Project -Feb 2025'!DQ59*98% -> 39156096 | AX14: ='By Project -Feb 2025'!DR59*98% -> 24996811 | AY14: ='By Project -Feb 2025'!DS59*98% -> 21151928 | AZ14: ='By Project -Feb 2025'!DT59*98% -> 26787859 | BA14: ='By Project -Feb 2025'!DU59*98% -> 22033928 | BB14: ='By Project -Feb 2025'!DV59*98% -> 20502139 | BC14: ='By Project -Feb 2025'!DW59*98% -> 24815952 | ... BE14: ='By Project -Feb 2025'!DY59*98% -> 24784200 | BF14: =SUM(AV14:BE14) -> 269216584 | BH14: Hestia 1.1 Premium | BI14: SOP01.0 | BJ14: BAT | BK14: 45698 | BL14: Hestia 1.1 Premium | BM14: 0 | BN14: 0 | BO14: 0 | BP14: 0 | DB14: 0 | DC14: 0 | DD14: 0 | DE14: 0 | DF14: 0 | DG14: 0 | DH14: 0 | DI14: 0 | DJ14: 0 | DK14: 0 | DL14: 0 | DM14: 0 | DN14: 0 | DO14: 29970 | DP14: 576000 | DQ14: 811150 | DR14: 1104660 | DS14: 817540 | DT14: 476460 | DU14: 606300 | DV14: 610230 | DW14: 481710 | DX14: 582030 | DY14: 613260
A15: 7 | B15: RF006_Alto | C15: Prismatic Pod | D15: Prismastic China project capex | E15: Pod | F15: Pod | G15: Indo | H15: Asset - Others | I15: RCS | J15: T1 | K15: Smoore T1 | L15: Reynolds | M15: - | N15: - | O15: 1562511 | P15: RMB | Q15: =IF(P15="RMB",O15/$B$6,IF(P15="GBP",O15,O15/$B$5)) -> 169879.88 | S15: Volume | T15: By Volume | U15: =IF(T15="By Unit", IF(P15="RMB",S15/$B$6,IF(P15="GBP",S15,S15/$B$5)),T15) -> By Volume | W15: =1-X15/Q15 -> 1 | X15: 0 | Y15: 0 | Z15: Paid-off | BF15: =SUM(AV15:BE15) -> 0 | BH15: KUMA E-Box ROW | BI15: SOP01.0 | BJ15: BAT | BK15: 45698 | BL15: Kuma 1K | BM15: 0 | BN15: 0 | BO15: 0 | BP15: 4452220 | CD15: 0 | CE15: 0 | CF15: 0 | CG15: 0 | CH15: 0 | CI15: 0 | CJ15: 0 | CK15: 0 | CL15: 0 | CM15: 0 | CN15: 0 | CO15: 0 | CP15: 0 | CQ15: 0 | CR15: 0 | CS15: 0 | CT15: 0 | CU15: 0 | CV15: 0 | CW15: 0 | CX15: 0 | CY15: 0 | CZ15: 0 | DA15: 0 | DB15: 0 | DC15: 0 | DD15: 0 | DE15: 146304 | DF15: 793652 | DG15: 1209610 | DH15: 417742 | DI15: 338164 | DJ15: 665900 | DK15: 479376 | DL15: 184320 | DM15: 217152 | DN15: 522432 | DO15: 149760 | DP15: 207792 | DQ15: 87840 | DR15: 66240 | DS15: 111600 | DT15: 65520 | DU15: 60480 | DV15: 40320 | DW15: 40320 | DX15: 65520 | DY15: 35280 | EA15: KUMA E-ROW Ultra Sonic Machine
A16: 8 | B16: RF007_Epod&Modi | C16: Epod&Modi | D16: Tax Stamp(Pod2+ePod3 Czech,Germany,Poland&Italy) | E16: RCS | F16: Vuse device(ROW) | G16: CN | H16: Asset - Others | I16: RCS | J16: T1 | K16: Smoore T1 | L16: NVT | M16: 45261 | N16: 46722 | O16: 714000 | P16: RMB | Q16: =IF(P16="RMB",O16/$B$6,IF(P16="GBP",O16,O16/$B$5)) -> 77627.765 | R16: 8572763 | S16: 0.083287034 | T16: By Unit | U16: =IF(T16="By Unit", IF(P16="RMB",S16/$B$6,IF(P16="GBP",S16,S16/$B$5)),T16) -> 0.0090551629 | V16: =SUM(AE16:AU16) -> 4614480 | W16: =IF(T16="By Volume",V16/R16,V16*U16/Q16) -> 0.5382722 | X16: =IFERROR(Q16*(1-W16),"") -> 35842.897 | Y16: =IF(X16>0,X16,0) -> 35842.897 | Z16: Under Amortization | AD16: =IF(U16="By Volume",(1-W16)*R16,X16/U16) -> 3958283 | AG16: 25920 | AH16: 322380 | AI16: 336240 | AJ16: 1478340 | AK16: 229680 | AL16: 1008810 | AM16: 993150 | AO16: 36540 | AP16: 178380 | AQ16: 5040 | AT16: 0 | AU16: 0 | AV16: 0 | AW16: 0 | AX16: 0 | AY16: 0 | AZ16: 0 | BA16: 0 | BB16: 0 | BC16: 0 | BD16: 0 | BE16: 0 | BF16: =SUM(AV16:BE16) -> 0 | BH16: KUMA E-Box NZ | BI16: SOP01.0 | BJ16: BAT | BK16: 45698 | BL16: Kuma 950 | BM16: 0 | BN16: 0 | BO16: 0 | BP16: 622560 | CD16: 0 | CE16: 0 | CF16: 0 | CG16: 0 | CH16: 0 | CI16: 0 | CJ16: 0 | CK16: 0 | CL16: 0 | CM16: 0 | CN16: 0 | CO16: 0 | CP16: 0 | CQ16: 0 | CR16: 0 | CS16: 0 | CT16: 0 | CU16: 0 | CV16: 0 | CW16: 0 | CX16: 0 | CY16: 0 | CZ16: 0 | DA16: 0 | DB16: 0 | DC16: 150000 | DD16: 115200 | DE16: 24000 | DF16: 0 | DG16: 222480 | DH16: 45360 | DI16: 65520 | DJ16: 0 | DK16: 0 | DL16: 0 | DM16: 0 | DN16: 0 | DO16: 0 | DP16: 0 | DQ16: 0 | DR16: 0 | DS16: 0 | DT16: 0 | DU16: 0 | DV16: 0 | DW16: 0 | DX16: 0 | DY16: 0
A17: 9 | B17: RF008_Modi2.0 | C17: Modi 2.0 | D17: Automation Flexible Line for Modi 2.0 Platform 1K PEN Default/Full and 1k BOX Full | E17: MD | F17: MD 2.0 | G17: CN | H17: Asset - Modi Line | I17: MoDi | J17: T1 | K17: Smoore T1 | L17: NVT | M17: 45505 | N17: 46235 | O17: 4912380 | P17: RMB | Q17: =IF(P17="RMB",O17/$B$6,IF(P17="GBP",O17,O17/$B$5)) -> 534085.55 | R17: =Q17/0.007 -> 76297935 | S17: =0.007*8.81203 -> 0.06168421 | T17: By Unit | U17: =IF(T17="By Unit", IF(P17="RMB",S17/$B$6,IF(P17="GBP",S17,S17/$B$5)),T17) -> 0.0067064529 | V17: =SUM(AE17:AU17) -> 23870660 | W17: =IF(T17="By Volume",V17/R17,V17*U17/Q17) -> 0.29974123 | X17: =IFERROR(Q17*(1-W17),"") -> 373998.09 | Y17: =IF(X17>0,X17,0) -> 373998.09 | Z17: Under Amortization | AD17: =IF(U17="By Volume",(1-W17)*R17,X17/U17) -> 55766900 | AP17: 705120 | AQ17: 8166540 | AR17: 7083240 | AS17: 2347320 | AT17: ='By Project -Feb 2025'!DN44+'By Project -Feb 2025'!DN45+'By Project -Feb 2025'!DN46 -> 3342680 | AU17: ='By Project -Feb 2025'!DO44+'By Project -Feb 2025'!DO45+'By Project -Feb 2025'!DO46 -> 2225760 | AV17: ='By Project -Feb 2025'!DP44+'By Project -Feb 2025'!DP45+'By Project -Feb 2025'!DP46 -> 5941992 | AW17: ='By Project -Feb 2025'!DQ44+'By Project -Feb 2025'!DQ45+'By Project -Feb 2025'!DQ46 -> 5851740 | AX17: ='By Project -Feb 2025'!DR44+'By Project -Feb 2025'!DR45+'By Project -Feb 2025'!DR46 -> 3951300 | AY17: ='By Project -Feb 2025'!DS44+'By Project -Feb 2025'!DS45+'By Project -Feb 2025'!DS46 -> 4293600 | AZ17: ='By Project -Feb 2025'!DT44+'By Project -Feb 2025'!DT45+'By Project -Feb 2025'!DT46 -> 3621000 | BA17: ='By Project -Feb 2025'!DU44+'By Project -Feb 2025'!DU45+'By Project -Feb 2025'!DU46 -> 5416620 | ... BE17: ='By Project -Feb 2025'!DY44+'By Project -Feb 2025'!DY45+'By Project -Feb 2025'!DY46 -> 5507580 | BF17: =SUM(AV17:BE17) -> 53381412 | BH17: Kuma Box 2.0 | BI17: SOP01.0 | BJ17: BAT | BK17: 45698 | BL17: Kuma Box 2.0 | BP17: 0 | DB17: 0 | DC17: 0 | DD17: 0 | DE17: 0 | DF17: 0 | DG17: 0 | DH17: 0 | DI17: 0 | DJ17: 0 | DK17: 0 | DL17: 0 | DM17: 0 | DN17: 0 | DO17: 0 | DP17: 0 | DQ17: 155360 | DR17: 294600 | DS17: 250560 | DT17: 142560 | DU17: 289405.95 | DV17: 173563.25 | DW17: 172374.76 | DX17: 244507.11 | DY17: 191572.99
A18: 10 | B18: RF009_Hestia1.0 | C18: Hestia 1.0 | D18: Hestia 1.0 Automation Lines Modification (Modified from ePod3 to Hestia1.0) (1-4 line) | E18: Pod | F18: Pod | G18: CN | H18: Pod Automation (Line Upgrade) | I18: RCS | J18: T1 | K18: Smoore T1 | L18: NVT | M18: 45406 | N18: 46113 | O18: 34746341 | P18: RMB | Q18: =IF(P18="RMB",O18/$B$6,IF(P18="GBP",O18,O18/$B$5)) -> 3777704.2 | R18: 246400000 | S18: =O18/R18 -> 0.14101599 | T18: By Unit | U18: =IF(T18="By Unit", IF(P18="RMB",S18/$B$6,IF(P18="GBP",S18,S18/$B$5)),T18) -> 0.015331592 | V18: =SUM(AE18:AU18) -> 139845360 | W18: =IF(T18="By Volume",V18/R18,V18*U18/Q18) -> 0.56755422 | X18: =IFERROR(Q18*(1-W18),"") -> 1633652.2 | Y18: =IF(X18>0,X18,0) -> 1633652.2 | Z18: Under Amortization | AD18: =IF(U18="By Volume",(1-W18)*R18,X18/U18) -> 1.0655464e+08 | AK18: 4374450 | AL18: 10070190 | AM18: 20708100 | AN18: 10070820 | AO18: 17188320 | AP18: 15151590 | AQ18: 12838860 | AR18: 15197040 | AS18: 8947260 | AT18: ='By Project -Feb 2025'!DN12 -> 17350470 | AU18: ='By Project -Feb 2025'!DO12 -> 7948260 | AV18: ='By Project -Feb 2025'!DP12 -> 19106540 | AW18: ='By Project -Feb 2025'!DQ12 -> 20397590 | AX18: ='By Project -Feb 2025'!DR12 -> 14871760 | AY18: ='By Project -Feb 2025'!DS12 -> 18739530 | AZ18: ='By Project -Feb 2025'!DT12 -> 17118810 | BA18: ='By Project -Feb 2025'!DU12 -> 26215830 | ... BE18: ='By Project -Feb 2025'!DY12 -> 19757020 | BF18: =SUM(AV18:BE18) -> 208251130 | BH18: KUMA E-Pen 1.0 ROW | BI18: SOP01.0 | BJ18: BAT | BK18: 45698 | BL18: Kuma Pen 1K | BM18: 0 | BN18: 0 | BO18: 0 | BP18: 1741320 | CD18: 0 | CE18: 0 | CF18: 0 | CG18: 0 | CH18: 0 | CI18: 0 | CJ18: 0 | CK18: 0 | CL18: 0 | CM18: 0 | CN18: 0 | CO18: 0 | CP18: 0 | CQ18: 0 | CR18: 0 | CS18: 0 | CT18: 0 | CU18: 0 | CV18: 0 | CW18: 0 | CX18: 0 | CY18: 0 | CZ18: 0 | DA18: 0 | DB18: 0 | DC18: 0 | DD18: 0 | DE18: 0 | DF18: 0 | DG18: 0 | DH18: 39600 | DI18: 31860 | DJ18: 532440 | DK18: 709740 | DL18: 275220 | DM18: 152460 | DN18: 0 | DO18: 0 | DP18: 0 | DQ18: 0 | DR18: 0 | DS18: 0 | DT18: 0 | DU18: 0 | DV18: 0 | DW18: 0 | DX18: 0 | DY18: 0 | EA18: KUMA E-Pen Laser welding machine & Kuma E-Pen 1.0 air tightness test machine
A19: 11 | B19: RF010_Hestia1.0 | C19: Hestia 1.0 | D19: Hestia1.0 Manual line capex | E19: Pod | F19: Pod | G19: CN | H19: Asset - Others | I19: RCS | J19: T1 | K19: Smoore T1 | L19: NVT | M19: 45406 | N19: 45505 | O19: - | P19: RMB | Q19: 0 | R19: 0 | S19: 0.036 | T19: By Unit | U19: =IF(T19="By Unit", IF(P19="RMB",S19/$B$6,IF(P19="GBP",S19,S19/$B$5)),T19) -> 0.003914005 | V19: 0 | W19: =IFERROR(IF(T19="By Volume",V19/R19,V19*U19/Q19),0) -> 0 | X19: =IFERROR(Q19*(1-W19),"") -> 0 | Y19: 0 | Z19: Not Applicable | BF19: =SUM(AV19:BE19) -> 0 | BH19: Kuma Pen 2.0 | BI19: SOP01.0 | BJ19: BAT | BK19: 45698 | BL19: Kuma Pen 2.0 | BM19: 0 | BN19: 0 | BO19: 0 | BP19: 107460 | CD19: 0 | CE19: 0 | CF19: 0 | CG19: 0 | CH19: 0 | CI19: 0 | CJ19: 0 | CK19: 0 | CL19: 0 | CM19: 0 | CN19: 0 | CO19: 0 | CP19: 0 | CQ19: 0 | CR19: 0 | CS19: 0 | CT19: 0 | CU19: 0 | CV19: 0 | CW19: 0 | CX19: 0 | CY19: 0 | CZ19: 0 | DA19: 0 | DB19: 0 | DC19: 0 | DD19: 0 | DE19: 0 | DF19: 0 | DG19: 0 | DH19: 0 | DI19: 0 | DJ19: 0 | DK19: 0 | DL19: 50040 | DM19: 57420 | DN19: 25200 | DO19: 440 | DP19: 171720 | DQ19: 208800 | DR19: 170818 | DS19: 382597.62 | DT19: 356973.74 | DU19: 489469.07 | DV19: 481795.02 | DW19: 459653.18 | DX19: 540842.01 | DY19: 405790.38
A20: 12 | B20: RF011_ePod2Pod | C20: ePod2 Pod | D20: ePod Packer - Included in Hestia | E20: Pod | F20: Pod | G20: CN | H20: Automation - Packing | I20: RCS | J20: T1 | K20: Smoore T1 | L20: NVT | M20: 44197 | N20: 46357 | O20: 2660000 | P20: USD | Q20: =IF(P20="RMB",O20/$B$6,IF(P20="GBP",O20,O20/$B$5)) -> 2081084 | R20: 175000000 | S20: Volume | T20: By Volume | U20: =IF(T20="By Unit", IF(P20="RMB",S20/$B$6,IF(P20="GBP",S20,S20/$B$5)),T20) -> By Volume | V20: =SUM(AE20:AU20) -> 144866505 | W20: 1 | X20: =IFERROR(Q20*(1-W20),"") -> 0 | Y20: =IF(X20>0,X20,0) -> 0 | Z20: Paid-off | AD20: =IF(U20="By Volume",(1-W20)*R20,X20/U20) -> 0 | AE20: 845920 | AF20: 72773897 | AG20: 63660929 | AH20: 5439052 | AI20: 806095 | AJ20: 321239 | AK20: 481119 | AL20: 497616 | AM20: 40638 | AT20: 0 | BF20: =SUM(AV20:BE20) -> 0 | BH20: KUMA E-Pen 1.0 ROW | BI20: SOP01.0 | BJ20: BAT | BK20: 45698 | BL20: Kuma Pen 950 | BM20: 0 | BN20: 0 | BO20: 0 | BP20: 3020760 | CD20: 0 | CE20: 0 | CF20: 0 | CG20: 0 | CH20: 0 | CI20: 0 | CJ20: 0 | CK20: 0 | CL20: 0 | CM20: 0 | CN20: 0 | CO20: 0 | CP20: 0 | CQ20: 0 | CR20: 0 | CS20: 0 | CT20: 0 | CU20: 0 | CV20: 0 | CW20: 0 | CX20: 0 | CY20: 0 | CZ20: 0 | DA20: 0 | DB20: 0 | DC20: 0 | DD20: 0 | DE20: 0 | DF20: 0 | DG20: 0 | DH20: 0 | DI20: 862920 | DJ20: 623880 | DK20: 567720 | DL20: 660240 | DM20: 306000 | DN20: 574020 | DO20: 633600 | DP20: 626220 | DQ20: 116460 | DR20: 114660 | DS20: 179460 | DT20: 169200 | DU20: 147260 | DV20: 143160 | DW20: 128580 | DX20: 116680 | DY20: 142880 | EA20: KUMA E-Pen Laser welding machine & Kuma E-Pen 1.0 air tightness test machine
A21: 13 | B21: RF012_ePod3Pod | C21: ePod3 Pod | D21: ePod 3 Automation Modification Capex Amortization (1P) Modified from ePod2 to ePod3 | E21: Pod | F21: Pod | G21: CN | H21: Pod Automation (Line Upgrade) | I21: RCS | J21: T1 | K21: Smoore T1 | L21: NVT | M21: 44980 | N21: 45689 | O21: 1503259 | P21: RMB | Q21: =IF(P21="RMB",O21/$B$6,IF(P21="GBP",O21,O21/$B$5)) -> 163437.87 | R21: =6430000*4/(0.01*8.87287) -> 2.8987239e+08 | S21: 0.0887284 | T21: By Unit | U21: =IF(T21="By Unit", IF(P21="RMB",S21/$B$6,IF(P21="GBP",S21,S21/$B$5)),T21) -> 0.0096467611 | V21: =Q21/U21 -> 16942253 | W21: =IF(T21="By Volume",V21/R21,V21*U21/Q21) -> 1 | X21: =IFERROR(Q21*(1-W21),"")*0 -> 0 | Y21: 0 | Z21: Amortization Completed | AG21: 12285257 | AH21: 1074798 | AI21: 65733 | AJ21: 894985 | AK21: 906260 | AL21: 1097616 | AM21: 617546 | AN21: 612910 | AO21: 277678 | AP21: 193824 | BF21: =SUM(AV21:BE21) -> 0 | BI21: SOP01.0 | BJ21: BAT | BK21: 45698 | BL21: Kuma Pen NZ | BP21: 0 | DB21: 0 | DC21: 0 | DD21: 0 | DE21: 0 | DF21: 0 | DG21: 0 | DH21: 0 | DI21: 0 | DJ21: 0 | DK21: 0 | DL21: 0 | DM21: 0 | DN21: 0 | DO21: 0 | DP21: 0 | DQ21: 0 | DR21: 0 | DS21: 0 | DT21: 0 | DU21: 0 | DV21: 0 | DW21: 0 | DX21: 0 | DY21: 0
A22: 14 | B22: RF013_Kuma | C22: Kuma 1.0 | D22: KUMA E-ROW Ultra Sonic Machine | E22: RCS | F22: Vuse device(ROW) | G22: CN | H22: Asset - RCS Device line | I22: RCS | J22: T1 | K22: Smoore T1 | L22: NVT | M22: 45383 | N22: 46113 | O22: 640000 | P22: RMB | Q22: =IF(P22="RMB",O22/$B$6,IF(P22="GBP",O22,O22/$B$5)) -> 69582.31 | R22: =O22/S22 -> 11034483 | S22: 0.058 | T22: By Unit | U22: =IF(T22="By Unit", IF(P22="RMB",S22/$B$6,IF(P22="GBP",S22,S22/$B$5)),T22) -> 0.0063058969 | V22: =SUM(AE22:AU22) -> 5022892 | W22: =IF(T22="By Volume",V22/R22,V22*U22/Q22) -> 0.45519959 | X22: =IFERROR(Q22*(1-W22),"") -> 37908.471 | Y22: =IF(X22>0,X22,0) -> 37908.471 | Z22: Under Amortization | AD22: =IF(U22="By Volume",(1-W22)*R22,X22/U22) -> 6011590.8 | AK22: 146304 | AL22: 793652 | AM22: 1209610 | AN22: 417742 | AO22: 338164 | AP22: 665900 | AQ22: 479376 | AR22: 160272 | AS22: 139680 | AT22: ='By Project -Feb 2025'!DN15 -> 522432 | AU22: ='By Project -Feb 2025'!DO15 -> 149760 | AV22: ='By Project -Feb 2025'!DP15 -> 207792 | AW22: ='By Project -Feb 2025'!DQ15 -> 87840 | AX22: ='By Project -Feb 2025'!DR15 -> 66240 | AY22: ='By Project -Feb 2025'!DS15 -> 111600 | AZ22: ='By Project -Feb 2025'!DT15 -> 65520 | BA22: ='By Project -Feb 2025'!DU15 -> 60480 | ... BE22: ='By Project -Feb 2025'!DY15 -> 35280 | BF22: =SUM(AV22:BE22) -> 780912 | BH22: Hestia total（include Kuma） | BI22: SOP01.0 | BJ22: BAT | BK22: 45698 | BL22: Hestia total（include Kuma） | BM22: 0 | BN22: 0 | BO22: 0 | BP22: 128856640 | BQ22: 0 | BR22: 0 | BS22: 0 | BT22: 0 | BU22: 0 | BV22: 0 | BW22: 0 | BX22: 0 | BY22: 0 | BZ22: 0 | CA22: 0 | CB22: 0 | CD22: 0 | CE22: 0 | CF22: 0 | CG22: 0 | CH22: 0 | CI22: 0 | CJ22: 0 | CK22: 0 | CL22: 0 | CM22: 0 | CN22: 0 | CO22: 0 | CP22: 0 | CQ22: 0 | CR22: 0 | CS22: 0 | CT22: 0 | CU22: 0 | CV22: 0 | CW22: 0 | CX22: 0 | CY22: 0 | CZ22: 0 | DA22: 0 | DB22: 0 | DC22: 0 | DD22: 0 | DE22: 4287474 | DF22: 11097122 | DG22: 19322470 | DH22: 13123402 | DI22: 18421264 | DJ22: 16973810 | DK22: 14595696 | DL22: 14369670 | DM22: 16665732 | DN22: 18472122 | DO22: 8762030 | DP22: 20688272 | DQ22: 21777200 | DR22: 16622738 | DS22: 20481288 | DT22: 18329524 | DU22: 27808745 | DV22: 24598438 | DW22: 22902058 | DX22: 28824839 | DY22: 21145803 | EA22: APA - Automation Production Agreement
A23: 15 | B23: RF014_Kuma | C23: Kuma 1.0 | D23: KUMA E-Pen Laser welding machine & Kuma E-Pen 1.0 air tightness test machine | E23: RCS | F23: Vuse device(ROW) | G23: CN | H23: Asset - RCS Device line | I23: RCS | J23: T1 | K23: Smoore T1 | L23: NVT | M23: 45505 | N23: 46235 | O23: =708000+72300 -> 780300 | P23: RMB | Q23: =IF(P23="RMB",O23/$B$6,IF(P23="GBP",O23,O23/$B$5)) -> 84836.058 | S23: 0.094674863 | T23: By Unit | U23: =IF(T23="By Unit", IF(P23="RMB",S23/$B$6,IF(P23="GBP",S23,S23/$B$5)),T23) -> 0.010293275 | V23: =SUM(AE23:AU23) -> 5979960 | W23: =IF(T23="By Volume",V23/R23,V23*U23/Q23) -> 0.7255567 | X23: =IFERROR(Q23*(1-W23),"")*0 -> 0 | Y23: 0 | Z23: Under Amortization | AD23: =IF(U23="By Volume",(1-W23)*R23,X23/U23) -> 0 | AN23: 39600 | AO23: 894780 | AP23: 1156320 | AQ23: 1277460 | AR23: 950580 | AS23: 453600 | AT23: ='By Project -Feb 2025'!DN18+'By Project -Feb 2025'!DN20 -> 574020 | AU23: ='By Project -Feb 2025'!DO18+'By Project -Feb 2025'!DO20 -> 633600 | AV23: ='By Project -Feb 2025'!DP18+'By Project -Feb 2025'!DP20 -> 626220 | AW23: ='By Project -Feb 2025'!DQ18+'By Project -Feb 2025'!DQ20 -> 116460 | AX23: ='By Project -Feb 2025'!DR18+'By Project -Feb 2025'!DR20 -> 114660 | AY23: ='By Project -Feb 2025'!DS18+'By Project -Feb 2025'!DS20 -> 179460 | AZ23: ='By Project -Feb 2025'!DT18+'By Project -Feb 2025'!DT20 -> 169200 | BA23: ='By Project -Feb 2025'!DU18+'By Project -Feb 2025'!DU20 -> 147260 | ... BE23: ='By Project -Feb 2025'!DY18+'By Project -Feb 2025'!DY20 -> 142880 | BF23: =SUM(AV23:BE23) -> 1884560 | BH23: Mimosa | BI23: SOP01.0 | BJ23: BAT | BK23: 45698 | BL23: Mimosa | BM23: 0 | BN23: 0 | BO23: 0 | BP23: 0 | CD23: 0 | CE23: 0 | CF23: 0 | CG23: 0 | CH23: 0 | CI23: 0 | CJ23: 0 | CK23: 0 | CL23: 0 | CM23: 0 | CN23: 0 | CO23: 0 | CP23: 0 | CQ23: 0 | CR23: 0 | CS23: 0 | CT23: 0 | CU23: 0 | CV23: 0 | CW23: 0 | CX23: 0 | CY23: 0 | CZ23: 0 | DA23: 0 | DB23: 0 | DC23: 0 | DD23: 0 | DE23: 0 | DF23: 0 | DG23: 0 | DH23: 0 | DI23: 0 | DJ23: 0 | DK23: 0 | DL23: 0 | DM23: 0 | DN23: 0 | DO23: 3744 | DP23: 72000 | DQ23: 153000 | DR23: 99000 | DS23: 18000 | DT23: 36336 | DU23: 56016 | DV23: 38736 | DW23: 46032 | DX23: 44928 | DY23: 43776
A24: 16 | B24: RF015_Modi&RCS | C24: Modi & RCS | D24: CCD&Tax Stamp Machine MD2.0 1K PEN Default Czech/Germany/Poland/Italy/BUL (Machines can be cross-used by both Modi & RCS) | E24: MD | F24: MD 2.0 | G24: CN | H24: Asset - Others | I24: Modi | J24: T1 | K24: Smoore T1 | L24: NVT | M24: 45505 | N24: 46966 | O24: 1210000 | P24: RMB | Q24: =IF(P24="RMB",O24/$B$6,IF(P24="GBP",O24,O24/$B$5)) -> 131554.06 | R24: 29491560 | S24: 0.041028688 | T24: By Unit | U24: =IF(T24="By Unit", IF(P24="RMB",S24/$B$6,IF(P24="GBP",S24,S24/$B$5)),T24) -> 0.0044607357 | V24: =SUM(AE24:AU24) -> 9825420 | W24: =IF(T24="By Volume",V24/R24,V24*U24/Q24) -> 0.3331604 | X24: =IFERROR(Q24*(1-W24),"") -> 87725.454 | Y24: =IF(X24>0,X24,0) -> 87725.454 | Z24: Under Amortization | AD24: =IF(U24="By Volume",(1-W24)*R24,X24/U24) -> 19666140 | AP24: 36060 | AQ24: 4722360 | AR24: 3286440 | AS24: 398760 | AT24: 1150380 | AU24: 231420 | AV24: 1771920 | AW24: 3593400 | AX24: 1748640 | AY24: 752880 | AZ24: 1156800 | BA24: 1870560 | BB24: 1795920 | BC24: 2130480 | BD24: 3526800 | BE24: 2150400 | BF24: =SUM(AV24:BE24) -> 20497800 | BH24: ePod 2 Device(Wave 1) | BI24: SOP01.0 | BJ24: BAT | BK24: 45698 | BL24: ePod2 | BM24: 6919526 | BN24: 6734445 | BO24: 973700 | BP24: 301000 | BQ24: 355400 | BR24: 376900 | BS24: 329800 | BT24: 514000 | BU24: 392100 | BV24: 672345 | BW24: 790600 | BX24: 581700 | BY24: 493100 | BZ24: 766581 | CA24: 791000 | CB24: 856000 | CD24: 617400 | CE24: 565400 | CF24: 918400 | CG24: 1007400 | CH24: 723600 | CI24: 752700 | CJ24: 589200 | CK24: 591300 | CL24: 636055 | CM24: 45000 | CN24: 163790 | CO24: 124200 | CP24: 95000 | CQ24: 309300 | CR24: 98600 | CS24: 18000 | CT24: 41000 | CU24: 16000 | CV24: 30000 | CW24: 43800 | CX24: 72900 | CY24: 75600 | CZ24: 48400 | DA24: 125100 | DB24: 19300 | DC24: 72900 | DD24: 30200 | DE24: 21700 | DF24: 24900 | DG24: 19800 | DH24: 0 | DI24: 0 | DJ24: 0 | DK24: 69000 | DL24: 43200 | DM24: 0 | DN24: 0 | DO24: 0 | DP24: 0 | DQ24: 0 | DR24: 0 | DS24: 0 | DT24: 0 | DU24: 0 | DV24: 0 | DW24: 0 | DX24: 0 | DY24: 0
A25: 17 | B25: RF016_Sensa | C25: Sensa | D25: Sensa Manual Line Capex | E25: MD | F25: MD 2.0 | G25: CN | H25: Asset - Others | I25: Modi | J25: T1 | K25: Smoore T1 | L25: NVT | M25: 45474 | N25: 45992 | O25: 903370.28 | P25: RMB | Q25: =IF(P25="RMB",O25/$B$6,IF(P25="GBP",O25,O25/$B$5)) -> 98216.549 | R25: 8895000 | S25: =0.0115*8.81203 -> 0.10133834 | T25: By Unit | U25: =IF(T25="By Unit", IF(P25="RMB",S25/$B$6,IF(P25="GBP",S25,S25/$B$5)),T25) -> 0.011017744 | V25: =SUM(AE25:AU25) -> 0 | W25: =IF(T25="By Volume",V25/R25,V25*U25/Q25) -> 0 | X25: =IFERROR(Q25*(1-W25),"") -> 98216.549 | Y25: =IF(X25>0,X25,0) -> 98216.549 | Z25: Under Amortization | AD25: =IF(U25="By Volume",(1-W25)*R25,X25/U25) -> 8914397.4 | BF25: =SUM(AV25:BE25) -> 0 | BI25: SOP12.1 | BJ25: BAT | BK25: 0 | BL25: ePod2 | BM25: 6503406 | BN25: 7074939 | BO25: 0 | BP25: 0 | BQ25: 355400 | BR25: 376900 | BS25: 329800 | BT25: 514000 | BU25: 392100 | BV25: 672345 | BW25: 790600 | BX25: 581700 | BY25: 493100 | BZ25: 766581 | CA25: 695680 | CB25: 535200 | CD25: 845094 | CE25: 464000 | CF25: 918400 | CG25: 1206700 | CH25: 786300 | CI25: 752700 | CJ25: 589200 | CK25: 543500 | CL25: 636055 | CM25: 45000 | CN25: 163790 | CO25: 124200 | CP25: 0 | CQ25: 0 | CR25: 0 | CS25: 0 | CT25: 0 | CU25: 0 | CV25: 0 | CW25: 0 | CX25: 0 | CY25: 0 | CZ25: 0 | DA25: 0 | DB25: 0 | DC25: 0 | DD25: 0 | DE25: 0 | DF25: 0 | DG25: 0 | DH25: 0 | DI25: 0 | DJ25: 0 | DK25: 0 | DL25: 0 | DM25: 0 | DN25: 0 | DO25: 0 | DP25: 0 | DQ25: 0 | DR25: 0 | DS25: 0 | DT25: 0 | DU25: 0 | DV25: 0 | DW25: 0 | DX25: 0 | DY25: 0
A26: 18 | B26: RF017_Sensa | C26: Sensa | D26: Sensa Semi-Auto Line Capex | E26: MD | F26: MD 2.0 | G26: CN | H26: Asset - Modi Line | I26: Modi | J26: T1 | K26: Smoore T1 | L26: NVT | M26: 45536 | N26: 45992 | O26: 6018424 | P26: RMB | Q26: =IF(P26="RMB",O26/$B$6,IF(P26="GBP",O26,O26/$B$5)) -> 654337.26 | R26: 12960000 | S26: =0.0527*8.81203 -> 0.46439398 | T26: By Unit | U26: =IF(T26="By Unit", IF(P26="RMB",S26/$B$6,IF(P26="GBP",S26,S26/$B$5)),T26) -> 0.05049001 | V26: =SUM(AE26:AU26) -> 0 | W26: =IF(T26="By Volume",V26/R26,V26*U26/Q26) -> 0 | X26: =IFERROR(Q26*(1-W26),"") -> 654337.26 | Y26: =IF(X26>0,X26,0) -> 654337.26 | Z26: Under Amortization | AD26: =IF(U26="By Volume",(1-W26)*R26,X26/U26) -> 12959737 | BF26: =SUM(AV26:BE26) -> 0 | BI26: 0 | BJ26: BAT | BK26: 0 | BL26: ePod2 | BM26: 6503406 | BN26: 6529023 | BO26: 0 | BP26: 0 | BQ26: 355400 | BR26: 376900 | BS26: 329800 | BT26: 514000 | BU26: 392100 | BV26: 672345 | BW26: 790600 | BX26: 581700 | BY26: 493100 | BZ26: 766581 | CA26: 695680 | CB26: 535200 | CD26: 845094 | CE26: 464000 | CF26: 884050 | CG26: 1206700 | CH26: 484575 | CI26: 935984 | CJ26: 432680 | CK26: 306895 | CL26: 636055 | CM26: 45000 | CN26: 163790 | CO26: 124200 | CP26: 0 | CQ26: 0 | CR26: 0 | CS26: 0 | CT26: 0 | CU26: 0 | CV26: 0 | CW26: 0 | CX26: 0 | CY26: 0 | CZ26: 0 | DA26: 0 | DB26: 0 | DC26: 0 | DD26: 0 | DE26: 0 | DF26: 0 | DG26: 0 | DH26: 0 | DI26: 0 | DJ26: 0 | DK26: 0 | DL26: 0 | DM26: 0 | DN26: 0 | DO26: 0 | DP26: 0 | DQ26: 0 | DR26: 0 | DS26: 0 | DT26: 0 | DU26: 0 | DV26: 0 | DW26: 0 | DX26: 0 | DY26: 0
A27: 19 | B27: RF018_Modi | C27: Modi | D27: T&T longterm solution cost Amortize at Uzbekistan TX500 and DP1500（UZB—乌兹别克斯坦） | E27: MD | F27: MD1.0 | G27: CN | H27: Asset - Others | I27: Modi | J27: T1 | K27: Smoore T1 | L27: NVT | M27: 44986 | N27: 46447 | O27: 1363867.4 | P27: RMB | Q27: =IF(P27="RMB",O27/$B$6,IF(P27="GBP",O27,O27/$B$5)) -> 148282.88 | R27: 4682003 | S27: =O27/R27 -> 0.29129998 | T27: By Unit | U27: =IF(T27="By Unit", IF(P27="RMB",S27/$B$6,IF(P27="GBP",S27,S27/$B$5)),T27) -> 0.031670821 | V27: =SUM(AE27:AU27) -> 552000 | W27: =IF(T27="By Volume",V27/R27,V27*U27/Q27) -> 0.11789826 | X27: =IFERROR(Q27*(1-W27),"") -> 130800.59 | Y27: =IF(X27>0,X27,0) -> 130800.59 | Z27: Under Amortization | AD27: =IF(U27="By Volume",(1-W27)*R27,X27/U27) -> 4130003 | AG27: 549000 | AH27: 3000 | AT27: 0 | AU27: 0 | AV27: 0 | AW27: 0 | AX27: 0 | AY27: 0 | AZ27: 0 | BA27: 0 | BB27: 0 | BC27: 0 | BD27: 0 | BE27: 0 | BF27: =SUM(AV27:BE27) -> 0 | BI27: 0 | BJ27: BAT | BK27: SOP7-2022/8/2 | BL27: ETMI | BM27: 45200 | BN27: 21040 | BO27: 32160 | BP27: 0 | BR27: 17760 | BT27: 14320 | BV27: 4400 | BW27: 8720 | CD27: 6000 | CF27: 3000 | CG27: 0 | CH27: 4000 | CI27: 0 | CJ27: 5040 | CK27: 3000 | CL27: 0 | CM27: 0 | CN27: 0 | CO27: 0 | CP27: 0 | CQ27: 3000 | CR27: 5040 | CS27: 0 | CT27: 3000 | CU27: 5040 | CV27: 0 | CW27: 0 | CX27: 8040 | CY27: 0 | CZ27: 0 | DA27: 8040
A28: 20 | B28: RF019_Modi | C28: Modi | D28: KZ MODI testing / support for T&T Amortize at KAZ TX500 and DP1500（KZ—哈萨克斯坦） | E28: MD | F28: MD1.0 | G28: CN | H28: Asset - Others | I28: Modi | J28: T1 | K28: Smoore T1 | L28: NVT | M28: 45108 | N28: 46569 | O28: 130573.98 | P28: RMB | Q28: =IF(P28="RMB",O28/$B$6,IF(P28="GBP",O28,O28/$B$5)) -> 14196.311 | R28: 1020000 | S28: =O28/R28 -> 0.12801371 | T28: By Unit | U28: =IF(T28="By Unit", IF(P28="RMB",S28/$B$6,IF(P28="GBP",S28,S28/$B$5)),T28) -> 0.013917952 | V28: =SUM(AE28:AU28) -> 0 | W28: =IF(T28="By Volume",V28/R28,V28*U28/Q28) -> 0 | X28: =IFERROR(Q28*(1-W28),"") -> 14196.311 | Y28: =IF(X28>0,X28,0) -> 14196.311 | Z28: Under Amortization | AD28: =IF(U28="By Volume",(1-W28)*R28,X28/U28) -> 1020000 | AT28: 0 | AU28: 0 | AV28: 0 | AW28: 0 | AX28: 0 | AY28: 0 | AZ28: 0 | BA28: 0 | BB28: 0 | BC28: 0 | BD28: 0 | BE28: 0 | BF28: =SUM(AV28:BE28) -> 0 | BI28: SOP7-2022/8/2 | BJ28: BAT | BK28: 44805 | BL28: Atomiser | BM28: 511000 | BN28: 40500 | BO28: 0 | BP28: 0 | BR28: 181500 | BT28: 77000 | BV28: 85000 | BW28: 167500 | CD28: 3000 | CF28: 0 | CG28: 0 | CI28: 0 | CJ28: 12500 | CK28: 0 | CL28: 0 | CM28: 12500 | CN28: 12500
A29: 21 | B29: RF020_Modi | C29: Modi | D29: T&T Interim programme of Azerbaijan Amortize at Azerbaijan 1k/3k/5k product（AZB—阿塞拜疆） | E29: MD | F29: MD1.0 | G29: CN | H29: Asset - Others | I29: Modi | J29: T1 | K29: Smoore T1 | L29: NVT | M29: 45017 | N29: 46478 | O29: 95728.992 | P29: RMB | Q29: =IF(P29="RMB",O29/$B$6,IF(P29="GBP",O29,O29/$B$5)) -> 10407.882 | T29: By Unit | U29: =IF(T29="By Unit", IF(P29="RMB",S29/$B$6,IF(P29="GBP",S29,S29/$B$5)),T29) -> 0 | V29: =SUM(AE29:AU29) -> 4680 | W29: =IF(T29="By Volume",V29/R29,V29*U29/Q29) -> 0 | X29: =IFERROR(Q29*(1-W29),"") -> 10407.882 | Y29: =IF(X29>0,X29,0) -> 10407.882 | Z29: Under Amortization | AT29: 0 | AU29: 4680 | AV29: 72000 | AW29: 0 | AX29: 0 | AY29: 0 | AZ29: 0 | BA29: 0 | BB29: 0 | BC29: 0 | BD29: 0 | BE29: 0 | BF29: =SUM(AV29:BE29) -> 72000 | BI29: 44805 | BJ29: BAT | BK29: SOP10-12/6 236M | BL29: ePod2+ | BM29: 0 | BN29: 1724245.5 | BO29: 650254.5 | BP29: 0 | CD29: 135000 | CE29: 135000 | CF29: 136696.5 | CG29: 108378 | CH29: 181110 | CI29: 121848 | CJ29: 156642 | CK29: 131443.5 | CL29: 186801 | CM29: 203887.5 | CN29: 157320 | CO29: 70119 | CP29: 75019.5 | CQ29: 79714.5 | CR29: 164461.5 | CS29: 165529.5 | CT29: 165529.5
A30: 22 | B30: RF021_Modi | C30: Modi | D30: T&T for Pre-Dispatch Advice --add extra function（UZB—乌兹别克斯坦 KZ—哈萨克斯坦） | E30: MD | F30: MD1.0 | G30: CN | H30: Asset - Others | I30: Modi | J30: T1 | K30: Smoore T1 | L30: NVT | M30: 45017 | N30: 46478 | O30: 706075.2 | P30: RMB | Q30: =IF(P30="RMB",O30/$B$6,IF(P30="GBP",O30,O30/$B$5)) -> 76766.162 | T30: By Unit | U30: =IF(T30="By Unit", IF(P30="RMB",S30/$B$6,IF(P30="GBP",S30,S30/$B$5)),T30) -> 0 | V30: =SUM(AE30:AU30) -> 0 | W30: =IF(T30="By Volume",V30/R30,V30*U30/Q30) -> 0 | X30: =IFERROR(Q30*(1-W30),"") -> 76766.162 | Y30: =IF(X30>0,X30,0) -> 76766.162 | Z30: Under Amortization | AT30: 0 | AU30: 0 | AV30: 0 | AW30: 0 | AX30: 0 | AY30: 0 | AZ30: 0 | BA30: 0 | BB30: 0 | BC30: 0 | BD30: 0 | BE30: 0 | BF30: =SUM(AV30:BE30) -> 0 | BI30: SOP10-12/6 236M | BJ30: BAT | BK30: 2023/1/31Core | BL30: ePod2+ | BM30: 0 | BN30: 1541050 | BO30: 235000 | BP30: 0 | CD30: 0 | CE30: 64549 | CF30: 127048 | CG30: 181303 | CH30: 24200 | CI30: 254800 | CJ30: 211000 | CK30: 214000 | CL30: 215000 | CM30: 81000 | CN30: 48150 | CO30: 120000 | CP30: 175000 | CQ30: 60000 | CR30: 0 | CS30: 0 | CT30: 0 | CU30: 0 | CV30: 0 | CW30: 0 | CX30: 0 | CY30: 0 | CZ30: 0 | DA30: 0
A31: 23 | B31: RF022_Modi | C31: Modi | D31: KZ MODI testing / support for T&T Amortize at BOX3K&5K KAZ&UZB market（KZ—哈萨克斯坦） | E31: MD | F31: MD1.0 | G31: CN | H31: Asset - Others | I31: Modi | J31: T1 | K31: Smoore T1 | L31: NVT | M31: 45108 | N31: 46569 | O31: 46448.488 | P31: RMB | Q31: =IF(P31="RMB",O31/$B$6,IF(P31="GBP",O31,O31/$B$5)) -> 5049.9892 | R31: 3976000 | S31: 0.011682215 | T31: By Unit | U31: =IF(T31="By Unit", IF(P31="RMB",S31/$B$6,IF(P31="GBP",S31,S31/$B$5)),T31) -> 0.001270118 | V31: =SUM(AE31:AU31) -> 137400 | W31: =IF(T31="By Volume",V31/R31,V31*U31/Q31) -> 0.034557344 | X31: =IFERROR(Q31*(1-W31),"") -> 4875.475 | Y31: =IF(X31>0,X31,0) -> 4875.475 | Z31: Under Amortization | AD31: =IF(U31="By Volume",(1-W31)*R31,X31/U31) -> 3838600 | AG31: 116160 | AH31: 15840 | AK31: 5400 | AT31: 0 | AU31: 0 | AV31: 0 | AW31: 0 | AX31: 0 | AY31: 0 | AZ31: 0 | BA31: 0 | BB31: 0 | BC31: 0 | BD31: 0 | BE31: 0 | BF31: =SUM(AV31:BE31) -> 0 | BI31: SOP2 | BJ31: BAT | BK31: 2023/1/31-Core+Sensitivity | BL31: ePod2+ | BM31: 0 | BN31: 1650011 | BO31: 235000 | BP31: 0 | BQ31: 0 | BR31: 0 | BS31: 0 | BT31: 0 | BU31: 0 | BV31: 0 | BW31: 0 | BX31: 0 | BY31: 0 | BZ31: 0 | CA31: 0 | CB31: 0 | CD31: 0 | CE31: 80000 | CF31: 148648 | CG31: 181303 | CH31: 24200 | CI31: 326710 | CJ31: 211000 | CK31: 214000 | CL31: 215000 | CM31: 81000 | CN31: 48150 | CO31: 120000 | CP31: 175000 | CQ31: 60000 | CR31: 0 | CS31: 0 | CT31: 0 | CU31: 0 | CV31: 0 | CW31: 0 | CX31: 0 | CY31: 0 | CZ31: 0 | DA31: 0
A32: 24 | B32: RF023_Modi | C32: Modi | D32: AZB T&T longterm solution cost for TX500&DP1500&BOX1K&3K&5K for AZB Market（AZB—阿塞拜疆） | E32: MD | F32: MD1.0 | G32: CN | H32: Asset - Others | I32: Modi | J32: T1 | K32: Smoore T1 | L32: NVT | M32: 45017 | N32: 46478 | O32: 466929.08 | P32: RMB | Q32: =IF(P32="RMB",O32/$B$6,IF(P32="GBP",O32,O32/$B$5)) -> 50765.632 | T32: By Unit | U32: =IF(T32="By Unit", IF(P32="RMB",S32/$B$6,IF(P32="GBP",S32,S32/$B$5)),T32) -> 0 | V32: =SUM(AE32:AU32) -> 4680 | W32: =IF(T32="By Volume",V32/R32,V32*U32/Q32) -> 0 | X32: =IFERROR(Q32*(1-W32),"") -> 50765.632 | Y32: =IF(X32>0,X32,0) -> 50765.632 | Z32: Under Amortization | AT32: 0 | AU32: 4680 | AV32: 72000 | AW32: 0 | AX32: 0 | AY32: 0 | AZ32: 0 | BA32: 0 | BB32: 0 | BC32: 0 | BD32: 0 | BE32: 0 | BF32: =SUM(AV32:BE32) -> 72000 | BI32: 2023/1/31-Core+Sensitivity | BJ32: BAT | BK32: 2023/1/31-PO+Production | BL32: ePod2+ | BM32: 0 | BN32: 1542297 | BO32: 235000 | BP32: 0 | CE32: 69349 | CF32: 148648 | CG32: 160000 | CH32: 20000 | CI32: 326710 | CJ32: 139440 | CK32: 214000 | CL32: 215000 | CM32: 81000 | CN32: 48150 | CO32: 120000 | CP32: 175000 | CQ32: 60000 | CR32: 0 | CS32: 0 | CT32: 0 | CU32: 0 | CV32: 0 | CW32: 0 | CX32: 0 | CY32: 0 | CZ32: 0 | DA32: 0
A33: 25 | B33: RF024_Modi | C33: Modi | D33: Custom development BAT CMO INEXTRACK GS1 Novarator removal CR for AZB regulation（AZB—阿塞拜疆） | E33: MD | F33: MD1.0 | G33: CN | H33: Asset - Others | I33: Modi | J33: T1 | K33: Smoore T1 | L33: NVT | M33: 45108 | N33: 46569 | O33: 80274.71 | P33: RMB | Q33: =IF(P33="RMB",O33/$B$6,IF(P33="GBP",O33,O33/$B$5)) -> 8727.6559 | T33: By Unit | U33: =IF(T33="By Unit", IF(P33="RMB",S33/$B$6,IF(P33="GBP",S33,S33/$B$5)),T33) -> 0 | V33: =SUM(AE33:AU33) -> 4680 | W33: =IF(T33="By Volume",V33/R33,V33*U33/Q33) -> 0 | X33: =IFERROR(Q33*(1-W33),"") -> 8727.6559 | Y33: =IF(X33>0,X33,0) -> 8727.6559 | Z33: Under Amortization | AT33: 0 | AU33: 4680 | AV33: 72000 | AW33: 0 | AX33: 0 | AY33: 0 | AZ33: 0 | BA33: 0 | BB33: 0 | BC33: 0 | BD33: 0 | BE33: 0 | BF33: =SUM(AV33:BE33) -> 72000 | BH33: ePod 3+ Device | BI33: SOP01.0 | BJ33: BAT | BK33: 45698 | BL33: ePod3+ | BM33: 0 | BN33: 0 | BO33: 283400 | BP33: 540400 | CD33: 0 | CE33: 0 | CF33: 0 | CG33: 0 | CH33: 0 | CI33: 0 | CJ33: 0 | CK33: 0 | CL33: 0 | CM33: 0 | CN33: 0 | CO33: 0 | CP33: 0 | CQ33: 0 | CR33: 0 | CS33: 0 | CT33: 61500 | CU33: 95000 | CV33: 0 | CW33: 0 | CX33: 54300 | CY33: 29900 | CZ33: 3600 | DA33: 39100 | DB33: 101800 | DC33: 40000 | DD33: 56600 | DE33: 163900 | DF33: 57700 | DG33: 37200 | DH33: 4000 | DI33: 12200 | DJ33: 38200 | DK33: 20800 | DL33: 0 | DM33: 8000 | DN33: 27600 | DO33: 17000 | DP33: 11000 | DQ33: 18200 | DR33: 14400 | DS33: 32400 | DT33: 12300 | DU33: 17300 | DV33: 28200 | DW33: 21100 | DX33: 24800 | DY33: 24800
A34: 27 | B34: RF025_Hestia1.1 | C34: Hestia 1.0 | D34: epod2 to Hestia1.1 non-smart | E34: RCS | F34: Pod | G34: CN | H34: Pod Automation (Line Upgrade) | I34: RCS | J34: T1 | K34: Smoore T1 | L34: NVT | O34: 5756300 | P34: RMB | Q34: =IF(P34="RMB",O34/$B$6,IF(P34="GBP",O34,O34/$B$5)) -> 625838.52 | T34: By Unit | U34: =IF(T34="By Unit", IF(P34="RMB",S34/$B$6,IF(P34="GBP",S34,S34/$B$5)),T34) -> 0 | W34: =IF(T34="By Volume",V34/R34,V34*U34/Q34) -> 0 | X34: =IFERROR(Q34*(1-W34),"") -> 625838.52 | Y34: 0 | Z34: Project Cancelled | BF34: =SUM(AV34:BE34) -> 0 | BH34: Epod Starter Kit | BI34: SOP01.0 | BJ34: BAT | BK34: 45698 | BL34: Starter Kit | BM34: 0 | BN34: 0 | BO34: 319800 | BP34: 617536 | CD34: 0 | CE34: 0 | CF34: 0 | CG34: 0 | CH34: 0 | CI34: 0 | CJ34: 0 | CK34: 0 | CL34: 0 | CM34: 0 | CN34: 0 | CO34: 0 | CP34: 0 | CQ34: 0 | CR34: 0 | CS34: 0 | CT34: 0 | CU34: 0 | CV34: 0 | CW34: 0 | CX34: 0 | CY34: 0 | CZ34: 110800 | DA34: 209000 | DB34: 43200 | DC34: 7200 | DD34: 10800 | DE34: 147920 | DF34: 44600 | DG34: 19440 | DH34: 295576 | DI34: 28640 | DJ34: 20160 | DK34: 0 | DL34: 0 | DM34: 0 | DN34: 11592 | DO34: 0 | DP34: 0 | DQ34: 0 | DR34: 0 | DS34: 0 | DT34: 0 | DU34: 0 | DV34: 0 | DW34: 0 | DX34: 0 | DY34: 0 | EA34: APA - Automation Production Agreement
A35: 26 | B35: RF026_Hestia1.1 | C35: Hestia 1.1 | D35: epod2 to Hestia1.1 smart | E35: RCS | F35: Pod | G35: CN | H35: Pod Automation (Line Upgrade) | I35: RCS | J35: T1 | K35: Smoore T1 | L35: NVT | M35: 45777 | N35: 46507 | O35: 12518185 | P35: RMB | Q35: =IF(P35="RMB",O35/$B$6,IF(P35="GBP",O35,O35/$B$5)) -> 1361006.6 | R35: TBC | S35: TBC | T35: By Unit | U35: =IF(T35="By Unit", IF(P35="RMB",S35/$B$6,IF(P35="GBP",S35,S35/$B$5)),T35) -> #VALUE! | W35: =IFERROR(IF(T35="By Volume",V35/R35,V35*U35/Q35),0) -> 0 | X35: =IFERROR(Q35*(1-W35),"") -> 1361006.6 | Y35: 0 | Z35: NPD | BF35: =SUM(AV35:BE35) -> 0 | BH35: ePod 3 Device | BI35: SOP01.0 | BJ35: BAT | BK35: 45698 | BL35: ePod3 descope | BM35: 0 | BN35: 0 | BO35: 2085900 | BP35: 1135900 | CD35: 0 | CE35: 0 | CF35: 0 | CG35: 0 | CH35: 0 | CI35: 0 | CJ35: 0 | CK35: 0 | CL35: 0 | CM35: 0 | CN35: 0 | CO35: 0 | CP35: 0 | CQ35: 0 | CR35: 21600 | CS35: 227600 | CT35: 447400 | CU35: 285400 | CV35: 200900 | CW35: 353700 | CX35: 307000 | CY35: 121200 | CZ35: 77500 | DA35: 43600 | DB35: 46800 | DC35: 29400 | DD35: 229500 | DE35: 111600 | DF35: 154900 | DG35: 79300 | DH35: 21600 | DI35: 105200 | DJ35: 52400 | DK35: 91800 | DL35: 75600 | DM35: 137800 | DN35: 77900 | DO35: 36900 | DP35: 51000 | DQ35: 42100 | DR35: 32600 | DS35: 49400 | DT35: 40000 | DU35: 48800 | DV35: 48400 | DW35: 34700 | DX35: 23800 | DY35: 25200
A36: 28 | B36: RF027_Hestia1.0 | C36: Hestia 1.0 | D36: epod2 to Hestia1.0 (5th line) | E36: RCS | F36: Pod | G36: CN | H36: Pod Automation (Line Upgrade) | I36: RCS | J36: T1 | K36: Smoore T1 | L36: NVT | M36: TBC | N36: TBC | O36: 6590000 | P36: RMB | Q36: =IF(P36="RMB",O36/$B$6,IF(P36="GBP",O36,O36/$B$5)) -> 716480.35 | T36: By Unit | U36: =IF(T36="By Unit", IF(P36="RMB",S36/$B$6,IF(P36="GBP",S36,S36/$B$5)),T36) -> 0 | W36: =IF(T36="By Volume",V36/R36,V36*U36/Q36) -> 0 | X36: =IFERROR(Q36*(1-W36),"") -> 716480.35 | Y36: 0 | Z36: NPD | BF36: =SUM(AV36:BE36) -> 0 | BH36: TX500 | BI36: SOP12.1 | BJ36: BAT | BK36: 45635 | BL36: TX500 | BM36: 0 | BN36: 81177917 | BO36: 45566346 | BP36: 12000 | BQ36: 0 | BR36: 0 | BS36: 0 | BT36: 0 | BU36: 0 | BV36: 0 | BW36: 0 | BX36: 0 | BY36: 0 | BZ36: 0 | CA36: 0 | CB36: 0 | CD36: 0 | CE36: 0 | CF36: 0 | CG36: 932000 | CH36: 2904000 | CI36: 6345360 | CJ36: 12084000 | CK36: 12364000 | CL36: 14666000 | CM36: 7120798 | CN36: 16391759 | CO36: 8370000 | CP36: 7091800 | CQ36: 7861600 | CR36: 8626600 | CS36: 11847400 | CT36: 4344600 | CU36: 2568000 | CV36: 972000 | CW36: 905946 | CX36: 912200 | CY36: 252000 | CZ36: 48000 | DA36: 136200 | DB36: 12000 | DC36: 0 | DD36: 0 | DE36: 0 | DF36: 0 | DG36: 0 | DH36: 0 | DI36: 0 | DJ36: 0 | DK36: 0 | DL36: 0 | DM36: 0 | DN36: 0 | DO36: 0 | DP36: 0 | DQ36: 0 | DR36: 0 | DS36: 0 | DT36: 0 | DU36: 0 | DV36: 0 | DW36: 0 | DX36: 0 | DY36: 0
A37: 29 | B37: RF028_Kuma | C37: Kuma E 2.0 Pen | D37: semi-auto for Kuma E 2.0 Pen | E37: RCS | F37: Device | G37: CN | H37: Asset - RCS Device line | I37: RCS | J37: T1 | K37: Smoore T1 | L37: NVT | M37: 45747 | N37: 46477 | O37: 2126778 | P37: RMB | Q37: =IF(P37="RMB",O37/$B$6,IF(P37="GBP",O37,O37/$B$5)) -> 231228.32 | R37: 5400000 | S37: 0.3938 | T37: By Unit | U37: =IF(T37="By Unit", IF(P37="RMB",S37/$B$6,IF(P37="GBP",S37,S37/$B$5)),T37) -> 0.042814865 | V37: =SUM(AV37:AV37) -> 171720 | W37: =IF(T37="By Volume",V37/R37,V37*U37/Q37) -> 0.031796142 | X37: =IFERROR(Q37*(1-W37),"") -> 223876.15 | Y37: 0 | Z37: Under Amortization | AD37: =IF(U37="By Volume",(1-W37)*R37,X37/U37) -> 5228935.2 | AT37: =DN19 -> 25200 | AU37: =DO19 -> 440 | AV37: =DP19 -> 171720 | AW37: =DQ19 -> 208800 | AX37: =DR19 -> 170818 | AY37: =DS19 -> 382597.62 | AZ37: =DT19 -> 356973.74 | BA37: =DU19 -> 489469.07 | ... BE37: =DY19 -> 405790.38 | BF37: =SUM(AV37:BE37) -> 3668459 | BI37: SOP12.1 | BJ37: BAT | BK37: 0 | BL37: TX500 | BM37: 0 | BN37: 81177917 | BO37: 0 | BP37: 0 | CG37: 932000 | CH37: 2904000 | CI37: 6345360 | CJ37: 12084000 | CK37: 12364000 | CL37: 14666000 | CM37: 7120798 | CN37: 16391759 | CO37: 8370000 | CP37: 0 | CQ37: 0 | CR37: 0 | CS37: 0 | CT37: 0 | CU37: 0 | CV37: 0 | CW37: 0 | CX37: 0 | CY37: 0 | CZ37: 0 | DA37: 0 | DB37: 0 | DC37: 0 | DD37: 0 | DE37: 0 | DF37: 0 | DG37: 0 | DH37: 0 | DI37: 0 | DJ37: 0 | DK37: 0 | DL37: 0 | DM37: 0 | DN37: 0 | DO37: 0 | DP37: 0 | DQ37: 0 | DR37: 0 | DS37: 0 | DT37: 0 | DU37: 0 | DV37: 0 | DW37: 0 | DX37: 0 | DY37: 0
A38: 30 | B38: RF029_Kuma | C38: Kuma E 2.0 Box | D38: semi-auto for Kuma E 2.0 Box | E38: RCS | F38: Device | G38: CN | H38: Asset - RCS Device line | I38: RCS | J38: T1 | K38: Smoore T1 | L38: NVT | M38: 45761 | N38: 46491 | O38: 1682778 | P38: RMB | Q38: =IF(P38="RMB",O38/$B$6,IF(P38="GBP",O38,O38/$B$5)) -> 182955.6 | R38: 5400000 | S38: 0.3084 | T38: By Unit | U38: =IF(T38="By Unit", IF(P38="RMB",S38/$B$6,IF(P38="GBP",S38,S38/$B$5)),T38) -> 0.033529976 | W38: =IF(T38="By Volume",V38/R38,V38*U38/Q38) -> 0 | X38: =IFERROR(Q38*(1-W38),"") -> 182955.6 | Y38: 0 | Z38: NPD | BF38: =SUM(AV38:BE38) -> 0 | BI38: 0 | BJ38: BAT | BK38: 0 | BL38: TX500 | BM38: 0 | BN38: 78480075 | BO38: 0 | BP38: 0 | CF38: 0 | CG38: 932000 | CH38: 2904000 | CI38: 6344000 | CJ38: 10214553 | CK38: 11960620 | CL38: 14242345 | CM38: 7120798 | CN38: 16391759 | CO38: 8370000 | CP38: 0 | CQ38: 0 | CR38: 0 | CS38: 0 | CT38: 0 | CU38: 0 | CV38: 0 | CW38: 0 | CX38: 0 | CY38: 0 | CZ38: 0 | DA38: 0 | DB38: 0 | DC38: 0 | DD38: 0 | DE38: 0 | DF38: 0 | DG38: 0 | DH38: 0 | DI38: 0 | DJ38: 0 | DK38: 0 | DL38: 0 | DM38: 0 | DN38: 0 | DO38: 0 | DP38: 0 | DQ38: 0 | DR38: 0 | DS38: 0 | DT38: 0 | DU38: 0 | DV38: 0 | DW38: 0 | DX38: 0 | DY38: 0
A39: 31 | B39: RF030_Mimosa | C39: Mimosa | D39: semi-auto for Mimosa1.0 + 2 Glue Machine | E39: RCS | F39: Device | G39: CN | H39: Asset - RCS Device line | I39: RCS | J39: T1 | K39: Smoore T1 | L39: NVT | M39: 45689 | N39: 46411 | O39: 4352000 | P39: RMB | Q39: =IF(P39="RMB",O39/$B$6,IF(P39="GBP",O39,O39/$B$5)) -> 473159.71 | R39: 4800000 | S39: 0.91 | T39: By Unit | U39: =IF(T39="By Unit", IF(P39="RMB",S39/$B$6,IF(P39="GBP",S39,S39/$B$5)),T39) -> 0.098937348 | V39: =SUM(AU39) -> 3744 | W39: =IF(T39="By Volume",V39/R39,V39*U39/Q39) -> 0.00078286765 | X39: =IFERROR(Q39*(1-W39),"") -> 472789.29 | Y39: 0 | Z39: Under Amortization | AD39: =IF(U39="By Volume",(1-W39)*R39,X39/U39) -> 4778673.6 | AT39: 0 | AU39: 3744 | AV39: 72000 | AW39: 153000 | AX39: 99000 | AY39: 18000 | AZ39: 36336 | BA39: 56016 | BB39: 38736 | BC39: 46032 | BD39: 44928 | BE39: 43776 | BF39: =SUM(AV39:BE39) -> 607824 | BH39: DP1500 | BI39: 0 | BJ39: BAT | BK39: 45635 | BL39: DP1500 | BM39: 0 | BN39: 5012030 | BO39: 13033000 | BP39: 3795000 | BQ39: 0 | BR39: 0 | BS39: 0 | BT39: 0 | BU39: 0 | BV39: 0 | BW39: 0 | BX39: 0 | BY39: 0 | BZ39: 0 | CA39: 0 | CB39: 0 | CD39: 0 | CE39: 0 | CF39: 0 | CG39: 0 | CH39: 0 | CI39: 0 | CJ39: 0 | CK39: 0 | CL39: 0 | CM39: 0 | CN39: 1812030 | CO39: 3200000 | CP39: 1984000 | CQ39: 576000 | CR39: 1716000 | CS39: 1409000 | CT39: 636000 | CU39: 1406600 | CV39: 1608000 | CW39: 840000 | CX39: 1418400 | CY39: 647000 | CZ39: 420000 | DA39: 372000 | DB39: 204000 | DC39: 279000 | DD39: 324000 | DE39: 984000 | DF39: 276000 | DG39: 862000 | DH39: 60000 | DI39: 264000 | DJ39: 242000 | DK39: 180000 | DL39: 24000 | DM39: 96000 | DN39: 96000 | DO39: 0 | DP39: 0 | DQ39: 0 | DR39: 0 | DS39: 0 | DT39: 0 | DU39: 0 | DV39: 0 | DW39: 0 | DX39: 0 | DY39: 0
A40: 32 | B40: RF031_Hestia1.0 | C40: Hestia 1.0 | D40: Tax stamp and CCD capex amortization | E40: RCS | F40: Pod | G40: CN | H40: Asset - Others | I40: RCS | J40: T1 | K40: Smoore T1 | L40: NVT | M40: 45566 | N40: 48122 | O40: 760000 | P40: RMB | Q40: =IF(P40="RMB",O40/$B$6,IF(P40="GBP",O40,O40/$B$5)) -> 82628.994 | S40: 0.028896174 | T40: By Unit | U40: =IF(T40="By Unit", IF(P40="RMB",S40/$B$6,IF(P40="GBP",S40,S40/$B$5)),T40) -> 0.0031416602 | V40: =SUM(AE40:AU40) -> 5988600 | W40: =IF(T40="By Volume",V40/R40,V40*U40/Q40) -> 0.22769425 | X40: =IFERROR(Q40*(1-W40),"") -> 63814.847 | Y40: =IF(X40>0,X40,0) -> 63814.847 | Z40: Under Amortization | AD40: =IF(U40="By Volume",(1-W40)*R40,X40/U40) -> 20312460 | AR40: 252540 | AS40: 208440 | AT40: 2761020 | AU40: 2766600 | AV40: 3869820 | AW40: =1762020+2693340 -> 4455360 | AX40: 2013300 | AY40: 2991600 | AZ40: 2957040 | BA40: 3942180 | BB40: 3335760 | BC40: 3791340 | BD40: 5151240 | BE40: 3408300 | BF40: =SUM(AV40:BE40) -> 35915940 | BI40: SOP12.1 | BJ40: BAT | BK40: 2022/2/3-Core+Sensitivity | BL40: DP1500 | BM40: 0 | BN40: 5012030 | BO40: 0 | BP40: 0 | CF40: 0 | CK40: 0 | CL40: 0 | CN40: 1812030 | CO40: 3200000 | CP40: 0 | CQ40: 0 | CR40: 0 | CS40: 0 | CT40: 0 | CU40: 0 | CV40: 0 | CW40: 0 | CX40: 0 | CY40: 0 | CZ40: 0 | DA40: 0 | DB40: 0 | DC40: 0 | DD40: 0 | DE40: 0 | DF40: 0 | DG40: 0 | DH40: 0 | DI40: 0 | DJ40: 0 | DK40: 0 | DL40: 0 | DM40: 0 | DN40: 0 | DO40: 0 | DP40: 0 | DQ40: 0 | DR40: 0 | DS40: 0 | DT40: 0 | DU40: 0 | DV40: 0 | DW40: 0 | DX40: 0 | DY40: 0
A41: 33 | B41: RF032_Alto | C41: Alto | D41: Alto tooling(IM tooling for 2p cost reduction) | E41: Pod | F41: Pod | G41: Indo | H41: Tooling | I41: RCS | J41: T2 | K41: Smoore T2 | L41: Reynolds | M41: 44980 | N41: 46722 | O41: 5098268.4 | P41: USD | Q41: =IF(P41="RMB",O41/$B$6,IF(P41="GBP",O41,O41/$B$5)) -> 3988693.6 | R41: 480000000 | S41: 0.0106 | T41: By Unit | U41: =IF(T41="By Unit", IF(P41="RMB",S41/$B$6,IF(P41="GBP",S41,S41/$B$5)),T41) -> 0.0082930417 | V41: =SUM(AE41:AU41) -> 523629650 | W41: =IF(T41="By Volume",V41/R41,V41*U41/Q41) -> 1.0886979 | X41: 0 | Y41: 0 | Z41: Amortization Completed | AG41: 224601000 | AH41: 22785000 | AI41: 22092200 | AJ41: 25589000 | AK41: 18498600 | AL41: 30742700 | AM41: 18494250 | AN41: 25532300 | AO41: 28932600 | AP41: 11088600 | AQ41: 14612550 | AR41: 17543850 | AS41: 18060400 | AT41: ='By Project -Feb 2025'!DN59 -> 29540200 | AU41: ='By Project -Feb 2025'!DO59 -> 15516400 | AV41: ='By Project -Feb 2025'!DP59 -> 46369950 | AW41: ='By Project -Feb 2025'!DQ59 -> 39955200 | AX41: ='By Project -Feb 2025'!DR59 -> 25506950 | AY41: ='By Project -Feb 2025'!DS59 -> 21583600 | AZ41: ='By Project -Feb 2025'!DT59 -> 27334550 | BA41: ='By Project -Feb 2025'!DU59 -> 22483600 | ... BE41: ='By Project -Feb 2025'!DY59 -> 25290000 | BF41: =SUM(AV41:BE41) -> 274710800 | BI41: 2022/2/3-Core+Sensitivity | BJ41: BAT | BK41: 2022/2/3-PO+Production | BL41: DP1500 | BM41: 0 | BN41: 5012030 | BO41: 0 | BP41: 0 | CF41: 0 | CK41: 0 | CL41: 0 | CN41: 1812030 | CO41: 3200000 | CP41: 0 | CQ41: 0 | CR41: 0 | CS41: 0 | CT41: 0 | CU41: 0 | CV41: 0 | CW41: 0 | CX41: 0 | CY41: 0 | CZ41: 0 | DA41: 0 | DB41: 0 | DC41: 0 | DD41: 0 | DE41: 0 | DF41: 0 | DG41: 0 | DH41: 0 | DI41: 0 | DJ41: 0 | DK41: 0 | DL41: 0 | DM41: 0 | DN41: 0 | DO41: 0 | DP41: 0 | DQ41: 0 | DR41: 0 | DS41: 0 | DT41: 0 | DU41: 0 | DV41: 0 | DW41: 0 | DX41: 0 | DY41: 0
A42: 34 | B42: RF033_ePod2Pod | C42: ePod2 POD | D42: ePod2 POD | E42: Pod | F42: Pod | G42: CN | H42: Tooling | I42: RCS | J42: T2 | K42: Smoore T2 | L42: NVT | M42: 44986 | N42: 45657 | O42: 23526500 | P42: RMB | Q42: =IF(P42="RMB",O42/$B$6,IF(P42="GBP",O42,O42/$B$5)) -> 2557856.6 | S42: 0.1048 | T42: By Unit | U42: =IF(T42="By Unit", IF(P42="RMB",S42/$B$6,IF(P42="GBP",S42,S42/$B$5)),T42) -> 0.011394103 | V42: =SUM(AE42:AU42) -> 2.4058794e+08 | W42: =IF(T42="By Volume",V42/R42,V42*U42/Q42) -> 1.0717113 | X42: =IFERROR(Q42*(1-W42),"")*0 -> 0 | Y42: 0 | Z42: Amortization Completed | AE42: 2.4058794e+08 | BF42: =SUM(AV42:BE42) -> 0 | BH42: Box 800 1.0 | BI42: 2022/2/3-PO+Production | BJ42: BAT | BK42: 45635 | BL42: Modi Box 1K | BM42: 0 | BN42: 0 | BO42: 35856000 | BP42: 7897176 | CD42: 0 | CE42: 0 | CF42: 0 | CG42: 0 | CH42: 0 | CI42: 0 | CJ42: 0 | CK42: 0 | CL42: 0 | CM42: 0 | CN42: 0 | CO42: 0 | CP42: 0 | CQ42: 0 | CR42: 0 | CS42: 1208800 | CT42: 3315200 | CU42: 3036000 | CV42: 3184800 | CW42: 4384600 | CX42: 4778600 | CY42: 6900000 | CZ42: 7176000 | DA42: 1872000 | DB42: 2317344 | DC42: 915144 | DD42: 2029776 | DE42: 1251648 | DF42: 647600 | DG42: 387088 | DH42: 216480 | DI42: 108000 | DJ42: 24096 | DK42: 0 | DL42: 0 | DM42: 0 | DN42: 0 | DO42: 0 | DP42: 0 | DQ42: 0 | DR42: 0 | DS42: 0 | DT42: 0 | DU42: 0 | DV42: 0 | DW42: 0 | DX42: 0 | DY42: 0
A43: 35 | B43: RF034_epod2Device | C43: epod 2 Device | D43: ePod2 Device - Wave 1-B design | E43: RCS | F43: Vuse device(ROW) | G43: CN | H43: Tooling | I43: RCS | J43: T2 | K43: Smoore T2 | L43: NVT | M43: 44228 | N43: 45657 | O43: 546000 | P43: RMB | Q43: =IF(P43="RMB",O43/$B$6,IF(P43="GBP",O43,O43/$B$5)) -> 59362.409 | S43: NO SHIPMENT | U43: =IF(T43="By Unit", IF(P43="RMB",S43/$B$6,IF(P43="GBP",S43,S43/$B$5)),T43) -> 0 | W43: =IF(T43="By Volume",V43/R43,V43*U43/Q43) -> 0 | X43: =IFERROR(Q43*(1-W43),"")*0 -> 0 | Y43: 0 | Z43: Amortization Completed | BF43: =SUM(AV43:BE43) -> 0 | BH43: Box 800 Default 2.0 | BI43: SOP12.1 | BJ43: BAT | BK43: 45635 | BL43: Box 1K Default | BM43: 0 | BN43: 0 | BO43: 0 | BP43: 9427392 | CD43: 0 | CE43: 0 | CF43: 0 | CG43: 0 | CH43: 0 | CI43: 0 | CJ43: 0 | CK43: 0 | CL43: 0 | CM43: 0 | CN43: 0 | CO43: 0 | CP43: 0 | CQ43: 0 | CR43: 0 | CS43: 0 | CT43: 0 | CU43: 0 | CV43: 0 | CW43: 0 | CX43: 0 | CY43: 0 | CZ43: 0 | DA43: 0 | DB43: 0 | DC43: 0 | DD43: 0 | DE43: 36000 | DF43: 1370520 | DG43: 1201056 | DH43: 1603776 | DI43: 2123328 | DJ43: 1403904 | DK43: 677400 | DL43: 819168 | DM43: 192240 | DN43: 319992 | DO43: 419400 | DP43: 478200 | DQ43: 342768 | DR43: 336444 | DS43: 439644 | DT43: 412488 | DU43: 453144 | DV43: 397368 | DW43: 467268 | DX43: 585648 | DY43: 567660
A44: 36 | B44: RF035_epod2+Device | C44: ePod2+ Device | D44: ePod2+ Device | E44: RCS | F44: Vuse device(ROW) | G44: CN | H44: Tooling | I44: RCS | J44: T2 | K44: Smoore T2 | L44: NVT | M44: 44593 | N44: 45657 | O44: 1550800 | P44: RMB | Q44: =IF(P44="RMB",O44/$B$6,IF(P44="GBP",O44,O44/$B$5)) -> 168606.64 | S44: 0.7016 | T44: By Unit | U44: =IF(T44="By Unit", IF(P44="RMB",S44/$B$6,IF(P44="GBP",S44,S44/$B$5)),T44) -> 0.076279608 | V44: =SUM(AE44:AU44) -> 235000 | W44: =IF(T44="By Volume",V44/R44,V44*U44/Q44) -> 0.10631674 | X44: =IFERROR(Q44*(1-W44),"")*0 -> 0 | Y44: 0 | Z44: Amortization Completed | AG44: 235000 | BF44: =SUM(AV44:BE44) -> 0 | BH44: Box 800 Full 2.0 | BI44: SOP12.1 | BJ44: BAT | BK44: 45635 | BL44: Box 1K Full | BM44: 0 | BN44: 0 | BO44: 0 | BP44: 8217000 | CD44: 0 | CE44: 0 | CF44: 0 | CG44: 0 | CH44: 0 | CI44: 0 | CJ44: 0 | CK44: 0 | CL44: 0 | CM44: 0 | CN44: 0 | CO44: 0 | CP44: 0 | CQ44: 0 | CR44: 0 | CS44: 0 | CT44: 0 | CU44: 0 | CV44: 0 | CW44: 0 | CX44: 0 | CY44: 0 | CZ44: 0 | DA44: 0 | DB44: 0 | DC44: 0 | DD44: 0 | DE44: 0 | DF44: 1250040 | DG44: 460440 | DH44: 515880 | DI44: 1704000 | DJ44: 1204920 | DK44: 1007160 | DL44: 1175760 | DM44: 898800 | DN44: 360480 | DO44: 287040 | DP44: 634200 | DQ44: 602640 | DR44: 667320 | DS44: 430860 | DT44: 437880 | DU44: 553680 | DV44: 630180 | DW44: 607620 | DX44: 1053000 | DY44: 533700 | EA44: Automation Flexible Line for Modi 2.0 Platform 1K PEN Default/Full and 1k BOX Full
A45: 37 | B45: RF036_Hestia1.0 | C45: Hestia 1.0 | D45: epod 3 pod Tooling, Included in Hestia Carryover | E45: Pod | F45: Pod | G45: CN | H45: Tooling | I45: RCS | J45: T2 | K45: Smoore T2 | L45: NVT | M45: 45008 | N45: 46357 | O45: -9120225 | P45: RMB | Q45: =IF(P45="RMB",O45/$B$6,IF(P45="GBP",O45,O45/$B$5)) -> -991572.39 | R45: 0 | T45: By Unit | U45: =IF(T45="By Unit", IF(P45="RMB",S45/$B$6,IF(P45="GBP",S45,S45/$B$5)),T45) -> 0 | V45: 0 | W45: =IF(T45="By Volume",V45/R45,(#REF!+S45*SUM(AQ45:AS45))/O45) -> #REF! | X45: =IFERROR(Q45*(1-W45),"")*0 -> #VALUE! | Y45: 0 | Z45: Amortization Completed | AG45: 12285257 | AH45: 1074798 | AI45: 65733 | AJ45: 894985 | AK45: 906260 | AL45: 1097616 | AM45: 617546 | AN45: 612910 | AO45: 277678 | AP45: 193824 | BF45: =SUM(AV45:BE45) -> 0 | BH45: Pen 800 Default 2.0 | BI45: SOP12.1 | BJ45: BAT | BK45: 45635 | BL45: Pen 1K Default | BM45: 0 | BN45: 0 | BO45: 0 | BP45: 42631420 | CD45: 0 | CE45: 0 | CF45: 0 | CG45: 0 | CH45: 0 | CI45: 0 | CJ45: 0 | CK45: 0 | CL45: 0 | CM45: 0 | CN45: 0 | CO45: 0 | CP45: 0 | CQ45: 0 | CR45: 0 | CS45: 0 | CT45: 0 | CU45: 0 | CV45: 0 | CW45: 0 | CX45: 0 | CY45: 0 | CZ45: 0 | DA45: 0 | DB45: 0 | DC45: 0 | DD45: 0 | DE45: 1827840 | DF45: 2503920 | DG45: 3935280 | DH45: 4244880 | DI45: 7573320 | DJ45: 6301360 | DK45: 7331100 | DL45: 5685240 | DM45: 3228480 | DN45: 2687720 | DO45: 1733640 | DP45: 4945392 | DQ45: 4747500 | DR45: 2770380 | DS45: 3233940 | DT45: 2643120 | DU45: 4075260 | DV45: 4091460 | DW45: 5045760 | DX45: 5955000 | DY45: 4381320 | EA45: Automation Flexible Line for Modi 2.0 Platform 1K PEN Default/Full and 1k BOX Full
A46: 38 | B46: RF037_epod3Device | C46: epod 3 Device | D46: epod 3 device tooling, To be Included in ePod 4+ no risk to flag yet. | E46: RCS | F46: Vuse device(ROW) | G46: CN | H46: Tooling | I46: RCS | J46: T2 | K46: Smoore T2 | L46: NVT | M46: 44986 | N46: 45627 | O46: 1520008 | P46: RMB | Q46: =IF(P46="RMB",O46/$B$6,IF(P46="GBP",O46,O46/$B$5)) -> 165258.86 | R46: 0 | S46: 0.1006 | T46: By Unit | U46: =IF(T46="By Unit", IF(P46="RMB",S46/$B$6,IF(P46="GBP",S46,S46/$B$5)),T46) -> 0.010937469 | V46: =SUM(AE46:AS46) -> 3169100 | W46: =1-X46/Q46 -> 1 | X46: 0 | Y46: 0 | Z46: Paid-off | AG46: 2085900 | AH46: 46800 | AI46: 29400 | AJ46: 229500 | AK46: 111600 | AL46: 154900 | AM46: 79300 | AN46: 21600 | AO46: 105200 | AP46: 52400 | AQ46: 91800 | AR46: 75600 | AS46: 85100 | AT46: 89492 | AU46: ='By Project -Feb 2025'!DO35 -> 36900 | AV46: ='By Project -Feb 2025'!DP35 -> 51000 | AW46: ='By Project -Feb 2025'!DQ35 -> 42100 | AX46: ='By Project -Feb 2025'!DR35 -> 32600 | AY46: ='By Project -Feb 2025'!DS35 -> 49400 | AZ46: ='By Project -Feb 2025'!DT35 -> 40000 | BA46: ='By Project -Feb 2025'!DU35 -> 48800 | BB46: ='By Project -Feb 2025'!DV35 -> 48400 | ... BE46: ='By Project -Feb 2025'!DY35 -> 25200 | BF46: =SUM(AV46:BE46) -> 396000 | BH46: Pen 800 Full 2.0 | BI46: SOP12.1 | BJ46: BAT | BK46: 45635 | BL46: Pen 1K Full | BM46: 0 | BN46: 0 | BO46: 0 | BP46: 5635920 | CD46: 0 | CE46: 0 | CF46: 0 | CG46: 0 | CH46: 0 | CI46: 0 | CJ46: 0 | CK46: 0 | CL46: 0 | CM46: 0 | CN46: 0 | CO46: 0 | CP46: 0 | CQ46: 0 | CR46: 0 | CS46: 0 | CT46: 0 | CU46: 0 | CV46: 0 | CW46: 0 | CX46: 0 | CY46: 0 | CZ46: 0 | DA46: 0 | DB46: 0 | DC46: 0 | DD46: 0 | DE46: 0 | DF46: 324000 | DG46: 132000 | DH46: 1704000 | DI46: 36000 | DJ46: 0 | DK46: 1163340 | DL46: 954900 | DM46: 1321680 | DN46: 294480 | DO46: 205080 | DP46: 362400 | DQ46: 501600 | DR46: 513600 | DS46: 628800 | DT46: 540000 | DU46: 787680 | DV46: 527520 | DW46: 320880 | DX46: 566160 | DY46: 592560 | EA46: Automation Flexible Line for Modi 2.0 Platform 1K PEN Default/Full and 1k BOX Full
A47: 39 | B47: RF038_epod3+Device | C47: epod 3+ Device | D47: epod 3+ device tooling, To be Included in ePod 4+ no risk to flag yet. | E47: RCS | F47: Vuse device(ROW) | G47: CN | H47: Tooling | I47: RCS | J47: T2 | K47: Smoore T2 | L47: NVT | M47: 45047 | N47: 45627 | O47: 1914510.9 | P47: RMB | Q47: =IF(P47="RMB",O47/$B$6,IF(P47="GBP",O47,O47/$B$5)) -> 208150.14 | R47: 0 | S47: 0.1155 | T47: By Unit | U47: =IF(T47="By Unit", IF(P47="RMB",S47/$B$6,IF(P47="GBP",S47,S47/$B$5)),T47) -> 0.012557433 | V47: =SUM(AE47:AS47) -> 823800 | W47: =1-X47/Q47 -> 1 | X47: 0 | Y47: 0 | Z47: Paid-off | AG47: 283400 | AH47: 101800 | AI47: 40000 | AJ47: 56600 | AK47: 163900 | AL47: 57700 | AM47: 37200 | AN47: 4000 | AO47: 12200 | AP47: 38200 | AQ47: 20800 | AS47: 8000 | AT47: ='By Project -Feb 2025'!DN33 -> 27600 | AU47: ='By Project -Feb 2025'!DO33 -> 17000 | AV47: ='By Project -Feb 2025'!DP33 -> 11000 | AW47: ='By Project -Feb 2025'!DQ33 -> 18200 | AX47: ='By Project -Feb 2025'!DR33 -> 14400 | AY47: ='By Project -Feb 2025'!DS33 -> 32400 | AZ47: ='By Project -Feb 2025'!DT33 -> 12300 | BA47: ='By Project -Feb 2025'!DU33 -> 17300 | ... BE47: ='By Project -Feb 2025'!DY33 -> 24800 | BF47: =SUM(AV47:BE47) -> 204500 | BH47: Box 3000 1.0 | BI47: SOP12.1 | BJ47: BAT | BK47: 45635 | BL47: Modi Box 3K | BM47: 0 | BN47: 0 | BO47: 3435120 | BP47: 4143840 | CD47: 0 | CE47: 0 | CF47: 0 | CG47: 0 | CH47: 0 | CI47: 0 | CJ47: 0 | CK47: 0 | CL47: 0 | CM47: 0 | CN47: 0 | CO47: 0 | CP47: 0 | CQ47: 0 | CR47: 0 | CS47: 0 | CT47: 0 | CU47: 0 | CV47: 120000 | CW47: 734400 | CX47: 1005600 | CY47: 921240 | CZ47: 404880 | DA47: 249000 | DB47: 384000 | DC47: 434760 | DD47: 672000 | DE47: 1116000 | DF47: 270000 | DG47: 1159080 | DH47: 96000 | DI47: 12000 | DJ47: 0 | DK47: 0 | DL47: 0 | DM47: 0 | DN47: 0 | DO47: 0 | DP47: 0 | DQ47: 0 | DR47: 0 | DS47: 0 | DT47: 0 | DU47: 0 | DV47: 0 | DW47: 0 | DX47: 0 | DY47: 0
A48: 40 | B48: RF039_Hestia1.0 | C48: Hestia 1.0 | D48: Hestia 1.0 New Tooling + ePod3 Pod Tooling included | E48: Pod | F48: Pod | G48: CN | H48: Tooling | I48: RCS | J48: T2 | K48: Smoore T2 | L48: NVT | M48: 45383 | N48: 46113 | O48: 29153936 | P48: RMB | Q48: =IF(P48="RMB",O48/$B$6,IF(P48="GBP",O48,O48/$B$5)) -> 3169684.7 | R48: =Q48/U48 -> 2.8980055e+08 | S48: 0.1006 | T48: By Unit | U48: =IF(T48="By Unit", IF(P48="RMB",S48/$B$6,IF(P48="GBP",S48,S48/$B$5)),T48) -> 0.010937469 | V48: =R48*W48 -> 1.6223235e+08 | W48: =AA48 -> 0.55980689 | X48: =IFERROR(Q48*(1-W48),"") -> 1395273.4 | Y48: =IF(X48>0,X48,0) -> 1395273.4 | Z48: Under Amortization | AA48: =(IFERROR(SUMIFS('ME Capex '!Z:Z,'ME Capex '!$A:$A,'By Project -Feb 2025'!$D48),0))/O48 -> 0.55980689 | AB48: =IFERROR(SUMIFS('ME Capex '!Z:Z,'ME Capex '!$A:$A,'By Project -Feb 2025'!$D48),0) -> 16320574 | AC48: =IFERROR(Q48*(1-AA48),"") -> 1395273.4 | AD48: =IF(U48="By Volume",(1-W48)*R48,X48/U48) -> 1.2756821e+08 | AK48: 4374450 | AL48: 10070190 | AM48: 20708100 | AN48: 10070820 | AO48: 17188320 | AP48: 15151590 | AQ48: 12838860 | AR48: 15197040 | AS48: 8947260 | AT48: 17350470 | AU48: ='By Project -Feb 2025'!DO12 -> 7948260 | AV48: ='By Project -Feb 2025'!DP12 -> 19106540 | AW48: ='By Project -Feb 2025'!DQ12 -> 20397590 | AX48: ='By Project -Feb 2025'!DR12 -> 14871760 | AY48: ='By Project -Feb 2025'!DS12 -> 18739530 | AZ48: ='By Project -Feb 2025'!DT12 -> 17118810 | BA48: ='By Project -Feb 2025'!DU12 -> 26215830 | BB48: ='By Project -Feb 2025'!DV12 -> 23149370 | ... BE48: ='By Project -Feb 2025'!DY12 -> 19757020 | BF48: =SUM(AV48:BE48) -> 208251130 | BI48: SOP12.1 | BK48: 0 | BL48: Box 3K Default | BO48: 0 | BP48: 0 | CP48: 0 | CQ48: 0 | CR48: 0 | CS48: 0 | CT48: 0 | CU48: 0 | CV48: 0 | CW48: 0 | CX48: 0 | CY48: 0 | CZ48: 0 | DA48: 0 | DB48: 0 | DC48: 0 | DD48: 0 | DE48: 0 | DF48: 0 | DG48: 0 | DH48: 0 | DI48: 0 | DJ48: 0 | DK48: 0 | DL48: 0 | DM48: 0 | DN48: 0 | DO48: 0 | DP48: 0 | DQ48: 0 | DR48: 0 | DS48: 0 | DT48: 0 | DU48: 0 | DV48: 0 | DW48: 0 | DX48: 0 | DY48: 0
A49: 41 | B49: RF040_Kuma | C49: Kuma | D49: KUMA E BOX NZ | E49: RCS | F49: Vuse device(ROW) | G49: CN | H49: Tooling | I49: RCS | J49: T2 | K49: Smoore T2 | L49: NVT | M49: 45383 | N49: N/A | O49: No Hard tool investment | P49: RMB | Q49: 0 | S49: 0 | U49: =IF(T49="By Unit", IF(P49="RMB",S49/$B$6,IF(P49="GBP",S49,S49/$B$5)),T49) -> 0 | W49: =IFERROR(IF(T49="By Volume",V49/R49,V49*U49/Q49),0) -> 0 | X49: =IFERROR(Q49*(1-W49),"") -> 0 | Y49: 0 | Z49: Not Applicable | BF49: =SUM(AV49:BE49) -> 0 | BH49: Box 3000 Full 2.0 | BI49: SOP01.4 | BJ49: BAT | BK49: 45698 | BL49: Box 3K Full | BM49: 0 | BN49: 0 | BO49: 0 | BP49: 1367880 | CD49: 0 | CE49: 0 | CF49: 0 | CG49: 0 | CH49: 0 | CI49: 0 | CJ49: 0 | CK49: 0 | CL49: 0 | CM49: 0 | CN49: 0 | CO49: 0 | CP49: 0 | CQ49: 0 | CR49: 0 | CS49: 0 | CT49: 0 | CU49: 0 | CV49: 0 | CW49: 0 | CX49: 0 | CY49: 0 | CZ49: 0 | DA49: 0 | DB49: 0 | DC49: 0 | DD49: 0 | DE49: 0 | DF49: 0 | DG49: 0 | DH49: 0 | DI49: 0 | DJ49: 0 | DK49: 845000 | DL49: 510880 | DM49: 12000 | DN49: 24120 | DO49: 208032 | DP49: 96000 | DQ49: 36096 | DR49: 271824 | DS49: 490848 | DT49: 338460 | DU49: 457272 | DV49: 374784 | DW49: 307656 | DX49: 456444 | DY49: 447432
A50: 42 | B50: RF041_Kuma | C50: Kuma | D50: KUMA E BOX ROW | E50: RCS | F50: Vuse device(ROW) | G50: CN | H50: Tooling | I50: RCS | J50: T2 | K50: Smoore T2 | L50: NVT | M50: 45383 | N50: 46113 | O50: 3274500 | P50: RMB | Q50: =IF(P50="RMB",O50/$B$6,IF(P50="GBP",O50,O50/$B$5)) -> 356011.37 | R50: =Q50/U50 -> 20963508 | S50: 0.1562 | T50: By Unit | U50: =IF(T50="By Unit", IF(P50="RMB",S50/$B$6,IF(P50="GBP",S50,S50/$B$5)),T50) -> 0.016982433 | V50: =R50*W50 -> 4554317.4 | W50: =AA50 -> 0.21724977 | X50: =IFERROR(Q50*(1-W50),"") -> 278667.98 | Y50: =IF(X50>0,X50,0) -> 278667.98 | Z50: Under Amortization | AA50: =(IFERROR(SUMIFS('ME Capex '!Z:Z,'ME Capex '!$A:$A,'By Project -Feb 2025'!$D50),0))/O50 -> 0.21724977 | AB50: =IFERROR(SUMIFS('ME Capex '!Z:Z,'ME Capex '!$A:$A,'By Project -Feb 2025'!$D50),0) -> 711384.37 | AC50: =IFERROR(Q50*(1-AA50),"") -> 278667.98 | AD50: =IF(U50="By Volume",(1-W50)*R50,X50/U50) -> 16409191 | AK50: 146304 | AL50: 793652 | AM50: 1209610 | AN50: 417742 | AO50: 338164 | AP50: 665900 | AQ50: 479376 | AR50: 160272 | AS50: 139680 | AT50: ='By Project -Feb 2025'!DN15 -> 522432 | AU50: ='By Project -Feb 2025'!DO15 -> 149760 | AV50: ='By Project -Feb 2025'!DP15 -> 207792 | AW50: ='By Project -Feb 2025'!DQ15 -> 87840 | AX50: ='By Project -Feb 2025'!DR15 -> 66240 | AY50: ='By Project -Feb 2025'!DS15 -> 111600 | AZ50: ='By Project -Feb 2025'!DT15 -> 65520 | BA50: ='By Project -Feb 2025'!DU15 -> 60480 | ... BE50: ='By Project -Feb 2025'!DY15 -> 35280 | BF50: =SUM(AV50:BE50) -> 780912 | BH50: Box 5000 1.0 | BI50: SOP1.4 | BJ50: BAT | BK50: 45719 | BL50: Modi Box 5K | BM50: 0 | BN50: 0 | BO50: 4156720 | BP50: 2563880 | CD50: 0 | CE50: 0 | CF50: 0 | CG50: 0 | CH50: 0 | CI50: 0 | CJ50: 0 | CK50: 0 | CL50: 0 | CM50: 0 | CN50: 0 | CO50: 0 | CP50: 0 | CQ50: 0 | CR50: 0 | CS50: 0 | CT50: 264000 | CU50: 504000 | CV50: 672000 | CW50: 180000 | CX50: 911520 | CY50: 981240 | CZ50: 314160 | DA50: 329800 | DB50: 522200 | DC50: 440400 | DD50: 240600 | DE50: 233880 | DF50: 232800 | DG50: 368160 | DH50: 95640 | DI50: 342600 | DJ50: 70920 | DK50: 0 | DL50: 16680 | DM50: 0 | DN50: 0 | DO50: 4680 | DP50: 72000 | DQ50: 0 | DR50: 0 | DS50: 0 | DT50: 0 | DU50: 0 | DV50: 0 | DW50: 0 | DX50: 0 | DY50: 0
A51: 43 | B51: RF042_Kuma | C51: Kuma | D51: KUMA E-ROW E Pen 1.0 | E51: RCS | F51: Vuse device(ROW) | G51: CN | H51: Tooling | I51: RCS | J51: T2 | K51: Smoore T2 | L51: NVT | M51: 45383 | N51: 46113 | O51: 5236765 | P51: RMB | Q51: =IF(P51="RMB",O51/$B$6,IF(P51="GBP",O51,O51/$B$5)) -> 569353.45 | R51: =Q51/U51 -> 22928043 | S51: 0.2284 | T51: By Unit | U51: =IF(T51="By Unit", IF(P51="RMB",S51/$B$6,IF(P51="GBP",S51,S51/$B$5)),T51) -> 0.024832187 | V51: =R51*W51 -> 5167622.3 | W51: =AA51 -> 0.22538436 | X51: =IFERROR(Q51*(1-W51),"") -> 441030.09 | Y51: =IF(X51>0,X51,0) -> 441030.09 | Z51: Under Amortization | AA51: =(IFERROR(SUMIFS('ME Capex '!Z:Z,'ME Capex '!$A:$A,'By Project -Feb 2025'!$D51),0))/O51 -> 0.22538436 | AB51: =IFERROR(SUMIFS('ME Capex '!Z:Z,'ME Capex '!$A:$A,'By Project -Feb 2025'!$D51),0) -> 1180284.9 | AC51: =IFERROR(Q51*(1-AA51),"") -> 441030.09 | AD51: =IF(U51="By Volume",(1-W51)*R51,X51/U51) -> 17760421 | AN51: 39600 | AO51: 894780 | AP51: 1411740 | AQ51: 1022040 | AR51: 950580 | AS51: 453600 | AT51: ='By Project -Feb 2025'!DN18+'By Project -Feb 2025'!DN20 -> 574020 | AU51: ='By Project -Feb 2025'!DO18+'By Project -Feb 2025'!DO20 -> 633600 | AV51: ='By Project -Feb 2025'!DP18+'By Project -Feb 2025'!DP20 -> 626220 | AW51: ='By Project -Feb 2025'!DQ18+'By Project -Feb 2025'!DQ20 -> 116460 | AX51: ='By Project -Feb 2025'!DR18+'By Project -Feb 2025'!DR20 -> 114660 | AY51: ='By Project -Feb 2025'!DS18+'By Project -Feb 2025'!DS20 -> 179460 | AZ51: ='By Project -Feb 2025'!DT18+'By Project -Feb 2025'!DT20 -> 169200 | BA51: ='By Project -Feb 2025'!DU18+'By Project -Feb 2025'!DU20 -> 147260 | ... BE51: ='By Project -Feb 2025'!DY18+'By Project -Feb 2025'!DY20 -> 142880 | BF51: =SUM(AV51:BE51) -> 1884560 | BI51: SOP12.1 | BK51: 0 | BL51: Box 5K Default | BO51: 0 | BP51: 0 | CP51: 0 | CQ51: 0 | CR51: 0 | CS51: 0 | CT51: 0 | CU51: 0 | CV51: 0 | CW51: 0 | CX51: 0 | CY51: 0 | CZ51: 0 | DA51: 0 | DB51: 0 | DC51: 0 | DD51: 0 | DE51: 0 | DF51: 0 | DG51: 0 | DH51: 0 | DI51: 0 | DJ51: 0 | DK51: 0 | DL51: 0 | DM51: 0 | DN51: 0 | DO51: 0 | DP51: 0 | DQ51: 0 | DR51: 0 | DS51: 0 | DT51: 0 | DU51: 0 | DV51: 0 | DW51: 0 | DX51: 0 | DY51: 0
A52: 44 | B52: RF043_Modi2.0 | C52: Modi 2.0 | D52: Vuse Go 2.0 1K Pen Default | E52: MD | F52: MD 2.0 | G52: CN | H52: Tooling | I52: Modi | J52: T2 | K52: Smoore T2 | L52: NVT | M52: 45383 | N52: 45992 | O52: 12241217 | P52: RMB | Q52: =IF(P52="RMB",O52/$B$6,IF(P52="GBP",O52,O52/$B$5)) -> 1330894 | R52: =Q52/U52 -> 1.5918357e+08 | S52: 0.0769 | T52: By Unit | U52: =IF(T52="By Unit", IF(P52="RMB",S52/$B$6,IF(P52="GBP",S52,S52/$B$5)),T52) -> 0.0083607495 | V52: =R52*W52 -> 59995175 | W52: =AA52 -> 0.376893 | X52: =IFERROR(Q52*(1-W52),"") -> 829289.35 | Y52: =IF(X52>0,X52,0) -> 829289.35 | Z52: Under Amortization | AA52: =(IFERROR(SUMIFS('ME Capex '!Z:Z,'ME Capex '!$A:$A,'By Project -Feb 2025'!$D52),0))/O52 -> 0.376893 | AB52: =IFERROR(SUMIFS('ME Capex '!Z:Z,'ME Capex '!$A:$A,'By Project -Feb 2025'!$D52),0) -> 4613629 | AC52: =IFERROR(Q52*(1-AA52),"") -> 829289.35 | AD52: =IF(U52="By Volume",(1-W52)*R52,X52/U52) -> 99188399 | AK52: 1827840 | AL52: 2873520 | AM52: 3565680 | AN52: 4244880 | AO52: 7812840 | AP52: 6241840 | AQ52: 7151100 | AR52: 5812200 | AS52: 1591120 | AT52: ='By Project -Feb 2025'!DN45 -> 2687720 | AU52: ='By Project -Feb 2025'!DO45 -> 1733640 | AV52: ='By Project -Feb 2025'!DP45 -> 4945392 | AW52: ='By Project -Feb 2025'!DQ45 -> 4747500 | AX52: ='By Project -Feb 2025'!DR45 -> 2770380 | AY52: ='By Project -Feb 2025'!DS45 -> 3233940 | AZ52: ='By Project -Feb 2025'!DT45 -> 2643120 | BA52: ='By Project -Feb 2025'!DU45 -> 4075260 | ... BE52: ='By Project -Feb 2025'!DY45 -> 4381320 | BF52: =SUM(AV52:BE52) -> 41889132 | BH52: Box 5000 Full 2.0 | BI52: SOP01.4 | BJ52: BAT | BK52: 45698 | BL52: Box 5K Full | BM52: 0 | BN52: 0 | BO52: 0 | BP52: 7129464 | CD52: 0 | CE52: 0 | CF52: 0 | CG52: 0 | CH52: 0 | CI52: 0 | CJ52: 0 | CK52: 0 | CL52: 0 | CM52: 0 | CN52: 0 | CO52: 0 | CP52: 0 | CQ52: 0 | CR52: 0 | CS52: 0 | CT52: 0 | CU52: 0 | CV52: 0 | CW52: 0 | CX52: 0 | CY52: 0 | CZ52: 0 | DA52: 0 | DB52: 0 | DC52: 0 | DD52: 0 | DE52: 0 | DF52: 436512 | DG52: 404112 | DH52: 1191168 | DI52: 1163760 | DJ52: 1310808 | DK52: 1000560 | DL52: 430488 | DM52: 1192056 | DN52: 446688 | DO52: 303144 | DP52: 214656 | DQ52: 173640 | DR52: 239520 | DS52: 149400 | DT52: 143040 | DU52: 214080 | DV52: 220560 | DW52: 206880 | DX52: 368880 | DY52: 167040
A53: 45 | B53: RF044_Modi2.0 | C53: Modi 2.0 | D53: Vuse Go 2.0 1K Box Default | E53: MD | F53: MD 2.0 | G53: CN | H53: Tooling | I53: Modi | J53: T2 | K53: Smoore T2 | L53: NVT | M53: 45383 | N53: 45992 | O53: 10952560 | P53: RMB | Q53: =IF(P53="RMB",O53/$B$6,IF(P53="GBP",O53,O53/$B$5)) -> 1190788.2 | R53: =Q53/U53 -> 1.2306248e+08 | S53: 0.089 | T53: By Unit | U53: =IF(T53="By Unit", IF(P53="RMB",S53/$B$6,IF(P53="GBP",S53,S53/$B$5)),T53) -> 0.00967629 | V53: =R53*W53 -> 21367955 | W53: =AA53 -> 0.17363501 | X53: =IFERROR(Q53*(1-W53),"") -> 984025.69 | Y53: =IF(X53>0,X53,0) -> 984025.69 | Z53: Under Amortization | AA53: =(IFERROR(SUMIFS('ME Capex '!Z:Z,'ME Capex '!$A:$A,'By Project -Feb 2025'!$D53),0))/O53 -> 0.17363501 | AB53: =IFERROR(SUMIFS('ME Capex '!Z:Z,'ME Capex '!$A:$A,'By Project -Feb 2025'!$D53),0) -> 1901748 | AC53: =IFERROR(Q53*(1-AA53),"") -> 984025.69 | AD53: =IF(U53="By Volume",(1-W53)*R53,X53/U53) -> 1.0169452e+08 | AK53: 36000 | AL53: 1370520 | AM53: 1201056 | AN53: 1603776 | AO53: 2195328 | AP53: 1331904 | AQ53: 701400 | AR53: 795168 | AS53: 144000 | AT53: ='By Project -Feb 2025'!DN43 -> 319992 | AU53: ='By Project -Feb 2025'!DO43 -> 419400 | AV53: ='By Project -Feb 2025'!DP43 -> 478200 | AW53: ='By Project -Feb 2025'!DQ43 -> 342768 | AX53: ='By Project -Feb 2025'!DR43 -> 336444 | AY53: ='By Project -Feb 2025'!DS43 -> 439644 | AZ53: ='By Project -Feb 2025'!DT43 -> 412488 | BA53: ='By Project -Feb 2025'!DU43 -> 453144 | ... BE53: ='By Project -Feb 2025'!DY43 -> 567660 | BF53: =SUM(AV53:BE53) -> 4480632 | BH53: Box 8000 1.0 | BI53: SOP1.4 | BJ53: BAT | BK53: 45719 | BL53: Modi Box 8K | BM53: 0 | BN53: 0 | BO53: 0 | BP53: 965280 | CD53: 0 | CE53: 0 | CF53: 0 | CG53: 0 | CH53: 0 | CI53: 0 | CJ53: 0 | CK53: 0 | CL53: 0 | CM53: 0 | CN53: 0 | CO53: 0 | CP53: 0 | CQ53: 0 | CR53: 0 | CS53: 0 | CT53: 0 | CU53: 0 | CV53: 0 | CW53: 0 | CX53: 0 | CY53: 0 | CZ53: 0 | DA53: 0 | DB53: 360000 | DC53: 0 | DD53: 108000 | DE53: 0 | DF53: 108000 | DG53: 12000 | DH53: 0 | DI53: 20040 | DJ53: 48600 | DK53: 17280 | DL53: 133440 | DM53: 157920 | DN53: 102000 | DO53: 14040 | DP53: 0 | DQ53: 0 | DR53: 0 | DS53: 0 | DT53: 0 | DU53: 0 | DV53: 0 | DW53: 0 | DX53: 0 | DY53: 0
A54: 46 | B54: RF045_Modi2.0 | C54: Modi 2.0 | D54: Vuse Go 2.0 1K Box Full | E54: MD | F54: MD 2.0 | G54: CN | H54: Tooling | I54: MoDi | J54: T2 | K54: Smoore T2 | L54: NVT | M54: 45383 | N54: 45992 | O54: 6088018 | P54: RMB | Q54: =IF(P54="RMB",O54/$B$6,IF(P54="GBP",O54,O54/$B$5)) -> 661903.69 | R54: =Q54/U54 -> 37122061 | S54: 0.164 | T54: By Unit | U54: =IF(T54="By Unit", IF(P54="RMB",S54/$B$6,IF(P54="GBP",S54,S54/$B$5)),T54) -> 0.017830467 | V54: =R54*W54 -> 9388125.2 | W54: =AA54 -> 0.25289881 | X54: =IFERROR(Q54*(1-W54),"") -> 494509.03 | Y54: =IF(X54>0,X54,0) -> 494509.03 | Z54: Under Amortization | AA54: =(IFERROR(SUMIFS('ME Capex '!Z:Z,'ME Capex '!$A:$A,'By Project -Feb 2025'!$D54),0))/O54 -> 0.25289881 | AB54: =IFERROR(SUMIFS('ME Capex '!Z:Z,'ME Capex '!$A:$A,'By Project -Feb 2025'!$D54),0) -> 1539652.5 | AC54: =IFERROR(Q54*(1-AA54),"") -> 494509.03 | AD54: =IF(U54="By Volume",(1-W54)*R54,X54/U54) -> 27733936 | AL54: 1250040 | AM54: 460440 | AN54: 515880 | AO54: 1815960 | AP54: 1092960 | AQ54: 1043160 | AR54: 1111560 | AS54: 789000 | AT54: ='By Project -Feb 2025'!DN44 -> 360480 | AU54: ='By Project -Feb 2025'!DO44 -> 287040 | AV54: ='By Project -Feb 2025'!DP44 -> 634200 | AW54: ='By Project -Feb 2025'!DQ44 -> 602640 | AX54: ='By Project -Feb 2025'!DR44 -> 667320 | AY54: ='By Project -Feb 2025'!DS44 -> 430860 | AZ54: ='By Project -Feb 2025'!DT44 -> 437880 | BA54: ='By Project -Feb 2025'!DU44 -> 553680 | ... BE54: ='By Project -Feb 2025'!DY44 -> 533700 | BF54: =SUM(AV54:BE54) -> 6151080 | BI54: SOP12.1 | BJ54: RJR | BK54: 45600 | BL54: Alto Cartridges-CN | BM54: 370859400 | BN54: 97779600 | BO54: 0 | BP54: 0 | BQ54: 28587600 | BR54: 8263800 | BS54: 31741200 | BT54: 33382800 | BU54: 33210000 | BV54: 33397200 | BW54: 37684800 | BX54: 34875000 | BY54: 35804400 | BZ54: 26860800 | CA54: 28072800 | CB54: 38979000 | CD54: 23313600 | CE54: 11452500 | CF54: 19874700 | CG54: 23241600 | CH54: 18414000 | CI54: 1483200
A55: 47 | B55: RF046_Modi2.0 | C55: Modi 2.0 | D55: Vuse Go 2.0 1K Pen Full | E55: MD | F55: MD 2.0 | G55: CN | H55: Tooling | I55: MoDi | J55: T2 | K55: Smoore T2 | L55: NVT | M55: 45383 | N55: 45992 | O55: 1864192.9 | P55: RMB | Q55: =IF(P55="RMB",O55/$B$6,IF(P55="GBP",O55,O55/$B$5)) -> 202679.45 | R55: =Q55/U55 -> 17245078 | S55: 0.1081 | T55: By Unit | U55: =IF(T55="By Unit", IF(P55="RMB",S55/$B$6,IF(P55="GBP",S55,S55/$B$5)),T55) -> 0.011752887 | V55: =R55*W55 -> 2842503.2 | W55: =AA55 -> 0.16482983 | X55: =IFERROR(Q55*(1-W55),"") -> 169271.83 | Y55: =IF(X55>0,X55,0) -> 169271.83 | Z55: Under Amortization | AA55: =(IFERROR(SUMIFS('ME Capex '!Z:Z,'ME Capex '!$A:$A,'By Project -Feb 2025'!$D55),0))/O55 -> 0.16482983 | AB55: =IFERROR(SUMIFS('ME Capex '!Z:Z,'ME Capex '!$A:$A,'By Project -Feb 2025'!$D55),0) -> 307274.6 | AC55: =IFERROR(Q55*(1-AA55),"") -> 169271.83 | AD55: =IF(U55="By Volume",(1-W55)*R55,X55/U55) -> 14402575 | AL55: 324000 | AM55: 132000 | AN55: 1704000 | AO55: 36000 | AQ55: 1183440 | AR55: 934800 | AS55: 49680 | AT55: ='By Project -Feb 2025'!DN46 -> 294480 | AU55: ='By Project -Feb 2025'!DO46 -> 205080 | AV55: ='By Project -Feb 2025'!DP46 -> 362400 | AW55: ='By Project -Feb 2025'!DQ46 -> 501600 | AX55: ='By Project -Feb 2025'!DR46 -> 513600 | AY55: ='By Project -Feb 2025'!DS46 -> 628800 | AZ55: ='By Project -Feb 2025'!DT46 -> 540000 | BA55: ='By Project -Feb 2025'!DU46 -> 787680 | ... BE55: ='By Project -Feb 2025'!DY46 -> 592560 | BF55: =SUM(AV55:BE55) -> 5341200 | BH55: Box 8000 Full 2.0 | BI55: SOP01.4 | BJ55: BAT | BK55: 45698 | BL55: Box 8K Full | BM55: 0 | BN55: 0 | BO55: 0 | BP55: 384000 | CD55: 0 | CE55: 0 | CF55: 0 | CG55: 0 | CH55: 0 | CI55: 0 | CJ55: 0 | CK55: 0 | CL55: 0 | CM55: 0 | CN55: 0 | CO55: 0 | CP55: 0 | CQ55: 0 | CR55: 0 | CS55: 0 | CT55: 0 | CU55: 0 | CV55: 0 | CW55: 0 | CX55: 0 | CY55: 0 | CZ55: 0 | DA55: 0 | DB55: 0 | DC55: 0 | DD55: 0 | DE55: 0 | DF55: 0 | DG55: 0 | DH55: 0 | DI55: 0 | DJ55: 0 | DK55: 0 | DL55: 348000 | DM55: 36000 | DN55: 84960 | DO55: 4080 | DP55: 116280 | DQ55: 77520 | DR55: 206280 | DS55: 65640 | DT55: 77040 | DU55: 80160 | DV55: 76680 | DW55: 83520 | DX55: 143520 | DY55: 71520 | BAH55: ''''''''' | BAJ55: ''''''''''''''''''''''''''''''''''''''' | BAK55: ''''''''''''''''''''''''''''''''''''''''''''''''''''''''''''''''''''''''''''''''''''''''''''''''''''''''''''''''''''''''''''''''''''''''''''''''''''''''''''''''''''''''''''''''''''''''''''''''''''''''''''''''''''''''''''''''''''''''''''''''''''''''''''''''''''''''''''''''''''''''''''''''''''''''''''''''''''''''''''''''''''''''''''''''''''''''''''''''''''''''''''''''''''''''''''''''''''''''''''''''''''''''''''''''''''''''''''''''''''''''''''''''''''''''''''''''''''''''''''''''''''''''''''''''''''''''''''''''''''''''''''''''''''''''''''''''''''''''''''''''''''''''''''''''''''''''''''''''''''''''''''''''''''''''''''''''''''''''''''''''''''''''''''''''''''''''''''''''''''''''''''''''''''''''''''''''''''''''''''''''''''''''''''''''''''''''''''''''''''''''''''''''''''''''''''''''''''''''''''''''''''''''''''''''''''''''''''''''''''''''''''''''''''''''''''''''''''''''''''''''''''''''''''''''''''''''''''''''''''''''''''''''''''''''''''''''''''''''''''''''''''''''''''''''''''''''''''''''''''''''''''''''''''''''''''''''''''''''''''''''''''''''''''''''''''''''''''''''''''''''''''''''''''''''''''''''''''''''''''''''''''''''''''''''''''''''''''''''''''''''''''''''''''''''''''''''''''''''''''''''''''''''''''''''''''''''''''''''''''''''''''''''''''''''''''''''''''''''''''''''''''''''''''''''''''''''''''''''''''''''''''''''''''''''''''''''''''''''''''''''''''''''''''''''''
A56: 48 | B56: RF047_DP1500 | C56: DP 1500 | D56: DP 1500 tooling | E56: MD | F56: MD 1.0 | G56: CN | H56: Tooling | I56: Modi | J56: T2 | K56: Smoore T2 | L56: NVT | M56: 44743 | N56: 45559 | O56: 7496388.4 | P56: RMB | Q56: =IF(P56="RMB",O56/$B$6,IF(P56="GBP",O56,O56/$B$5)) -> 815025.04 | R56: =SUM(AE56:AR56) -> 20964000 | S56: =Q56/R56 -> 0.038877363 | T56: By Unit | U56: =IF(T56="By Unit", IF(P56="RMB",S56/$B$6,IF(P56="GBP",S56,S56/$B$5)),T56) -> 0.0042268387 | W56: =1-X56/Q56 -> 1 | X56: 0 | Y56: 0 | Z56: Paid-off | AF56: 4508000 | AG56: 12961000 | AH56: 303000 | AI56: 180000 | AJ56: 324000 | AK56: 984000 | AL56: 912000 | AM56: 226000 | AN56: 60000 | AO56: 288000 | AP56: 218000 | BF56: =SUM(AV56:BE56) -> 0 | BH56: Alto Cartridges-IND | BI56: SOP1.4 | BJ56: RJR | BK56: 45719 | BL56: Alto Cartridges-IND | BM56: 0 | BN56: 168097600 | BO56: 255515000 | BP56: 240955000 | BQ56: 0 | BR56: 0 | BS56: 0 | BT56: 0 | BU56: 0 | BV56: 0 | BW56: 0 | BX56: 0 | BY56: 0 | BZ56: 0 | CA56: 0 | CB56: 0 | CD56: 0 | CE56: 0 | CF56: 0 | CG56: 0 | CH56: 1500000 | CI56: 8525800 | CJ56: 20464600 | CK56: 29343800 | CL56: 27249800 | CM56: 20437500 | CN56: 27980700 | CO56: 32595400 | CP56: 30914000 | CQ56: 31018300 | CR56: 27736300 | CS56: 20107700 | CT56: 25062300 | CU56: 25527600 | CV56: 23250400 | CW56: 13933400 | CX56: 8697000 | CY56: 3530100 | CZ56: 24994500 | DA56: 20743400 | DB56: 18696800 | DC56: 26612200 | DD56: 24709600 | DE56: 15849900 | DF56: 31753100 | DG56: 18403700 | DH56: 25102700 | DI56: 27982200 | DJ56: 9598800 | DK56: 13374000 | DL56: 15867000 | DM56: 13005000 | DN56: 28556.8 | DO56: 14936.8 | DP56: 45748.2 | DQ56: 39757.8 | DR56: 24774.6 | DS56: 21123 | DT56: 26758.8 | DU56: 21960 | DV56: 20235.6 | DW56: 24805.8 | DX56: 19515.6 | DY56: 24748.2
A57: 49 | B57: RF048_Box1k | C57: BOX 1K | D57: BOX 1000 | E57: MD | F57: MD 1.0 | G57: CN | H57: Tooling | I57: MoDi | J57: T2 | K57: Smoore T2 | L57: NVT | M57: 45170 | N57: 45559 | O57: 3926494.7 | P57: RMB | Q57: =IF(P57="RMB",O57/$B$6,IF(P57="GBP",O57,O57/$B$5)) -> 426897.77 | R57: =SUM(AE57:AR57) -> 16873296 | S57: =Q57/R57 -> 0.0253002 | T57: By Unit | U57: =IF(T57="By Unit", IF(P57="RMB",S57/$B$6,IF(P57="GBP",S57,S57/$B$5)),T57) -> 0.0027506975 | W57: =1-X57/Q57 -> 1 | X57: 0 | Y57: 0 | Z57: Paid-off | AG57: 9072000 | AH57: 2569344 | AI57: 651264 | AJ57: 1993776 | AK57: 1203648 | AL57: 647600 | AM57: 411280 | AN57: 192288 | AO57: 108000 | AP57: 24096 | BF57: =SUM(AV57:BE57) -> 0 | BH57: Alto Device | BI57: SOP1.4 | BJ57: RJR | BK57: 45719 | BL57: Alto Device | BM57: 14653350 | BN57: 17110575 | BO57: 5737450 | BP57: 2190800 | BQ57: 1981200 | BR57: 309000 | BS57: 1156200 | BT57: 1657200 | BU57: 1011000 | BV57: 1050000 | BW57: 789600 | BX57: 744000 | BY57: 1297800 | BZ57: 1524150 | CA57: 1623600 | CB57: 1509600 | CD57: 1485600 | CE57: 660000 | CF57: 1605865 | CG57: 1854200 | CH57: 1775000 | CI57: 2027900 | CJ57: 1732450 | CK57: 1542350 | CL57: 681200 | CM57: 933600 | CN57: 1074410 | CO57: 1738000 | CP57: 1056750 | CQ57: 1672800 | CR57: 2378700 | CS57: 116850 | CT57: 29600 | CU57: 174650 | CV57: 226900 | CW57: 81200 | CX57: 0 | CY57: 0 | CZ57: 0 | DA57: 0 | DB57: 0 | DC57: 292500 | DD57: 301700 | DE57: 290600 | DF57: 431700 | DG57: 123200 | DH57: 416300 | DI57: 0 | DJ57: 0 | DK57: 91200 | DL57: 117600 | DM57: 126000 | DN57: 260400 | DO57: 319200 | DP57: 302400 | DQ57: 268800 | DR57: 336000 | DS57: 260400 | DT57: 294000 | DU57: 226800 | DV57: 327600 | DW57: 256200 | DX57: 201600 | DY57: 260400 | EA57: Device to Indo Equipment move cost
A58: 50 | B58: RF049_Modi2.0 | C58: Modi 2.0 | D58: Vuse Go 2.0 5K Box Full(Include Sensa) | E58: MD | F58: MD 2.0 | G58: CN | H58: Tooling | I58: Modi | J58: T2 | K58: Smoore T2 | L58: NVT | M58: 45413 | N58: 45992 | O58: 16853984 | P58: RMB | Q58: =IF(P58="RMB",O58/$B$6,IF(P58="GBP",O58,O58/$B$5)) -> 1832404.9 | R58: =Q58/U58 -> 73598184 | S58: 0.229 | T58: By Unit | U58: =IF(T58="By Unit", IF(P58="RMB",S58/$B$6,IF(P58="GBP",S58,S58/$B$5)),T58) -> 0.02489742 | V58: =R58*W58 -> 7754199.1 | W58: =AA58 -> 0.10535857 | X58: =IFERROR(Q58*(1-W58),"") -> 1639345.4 | Y58: =IF(X58>0,X58,0) -> 1639345.4 | Z58: Under Amortization | AA58: =(IFERROR(SUMIFS('ME Capex '!Z:Z,'ME Capex '!$A:$A,'By Project -Feb 2025'!$D58),0))/O58 -> 0.10535857 | AB58: =IFERROR(SUMIFS('ME Capex '!Z:Z,'ME Capex '!$A:$A,'By Project -Feb 2025'!$D58),0) -> 1775711.6 | AC58: =IFERROR(Q58*(1-AA58),"") -> 1639345.4 | AD58: =IF(U58="By Volume",(1-W58)*R58,X58/U58) -> 65843985 | AL58: 1257720 | AM58: 1734480 | AN58: 1765872 | AO58: 1740168 | AP58: 1307520 | AQ58: 1000560 | AR58: 593352 | AS58: 398280 | AT58: ='By Project -Feb 2025'!DN52 -> 446688 | AU58: ='By Project -Feb 2025'!DO52 -> 303144 | AV58: ='By Project -Feb 2025'!DP52 -> 214656 | AW58: ='By Project -Feb 2025'!DQ52 -> 173640 | AX58: ='By Project -Feb 2025'!DR52 -> 239520 | AY58: ='By Project -Feb 2025'!DS52 -> 149400 | AZ58: ='By Project -Feb 2025'!DT52 -> 143040 | BA58: ='By Project -Feb 2025'!DU52 -> 214080 | ... BE58: ='By Project -Feb 2025'!DY52 -> 167040 | BF58: =SUM(AV58:BE58) -> 2097696 | BH58: Alto bundle kit | BI58: SOP1.4 | BJ58: RJR | BK58: 45719 | BL58: Alto bundle kit | BM58: 0 | BN58: 0 | BO58: 7777400 | BP58: 8478450 | BQ58: 0 | BR58: 0 | BS58: 0 | BT58: 0 | BU58: 0 | BV58: 0 | BW58: 0 | BX58: 0 | BY58: 0 | BZ58: 0 | CA58: 0 | CB58: 0 | CD58: 0 | CE58: 0 | CF58: 0 | CG58: 0 | CH58: 0 | CI58: 0 | CJ58: 0 | CK58: 0 | CL58: 0 | CM58: 0 | CN58: 0 | CO58: 0 | CP58: 509000 | CQ58: 538250 | CR58: 0 | CS58: 1135100 | CT58: 701600 | CU58: 231550 | CV58: 1056000 | CW58: 644200 | CX58: 253600 | CY58: 471000 | CZ58: 829900 | DA58: 1407200 | DB58: 1122000 | DC58: 121500 | DD58: 351700 | DE58: 381400 | DF58: 109300 | DG58: 90550 | DH58: 429600 | DI58: 950400 | DJ58: 1489800 | DK58: 1238550 | DL58: 769050 | DM58: 1424600 | DN58: 983400 | DO58: 579600 | DP58: 621750 | DQ58: 197400 | DR58: 732350 | DS58: 460600 | DT58: 575750 | DU58: 523600 | DV58: 684950 | DW58: 516600 | DX58: 428400 | DY58: 541800 | EA58: Device to Indo Equipment move cost
A59: 51 | B59: RF050_Modi2.0 | C59: Modi 2.0 | D59: Vuse Go 2.0 8K Box Full | E59: MD | F59: MD 2.0 | G59: CN | H59: Tooling | I59: MoDi | J59: T2 | K59: Smoore T2 | L59: NVT | M59: 45505 | N59: 45992 | O59: 2482288.7 | P59: RMB | Q59: =IF(P59="RMB",O59/$B$6,IF(P59="GBP",O59,O59/$B$5)) -> 269880.28 | R59: =Q59/U59 -> 10074224 | S59: 0.2464 | T59: By Unit | U59: =IF(T59="By Unit", IF(P59="RMB",S59/$B$6,IF(P59="GBP",S59,S59/$B$5)),T59) -> 0.02678919 | V59: =R59*W59 -> 144834.25 | W59: =AA59 -> 0.014376716 | X59: =IFERROR(Q59*(1-W59),"") -> 266000.29 | Y59: =IF(X59>0,X59,0) -> 266000.29 | Z59: Under Amortization | AA59: =(IFERROR(SUMIFS('ME Capex '!Z:Z,'ME Capex '!$A:$A,'By Project -Feb 2025'!$D59),0))/O59 -> 0.014376716 | AB59: =IFERROR(SUMIFS('ME Capex '!Z:Z,'ME Capex '!$A:$A,'By Project -Feb 2025'!$D59),0) -> 35687.16 | AC59: =IFERROR(Q59*(1-AA59),"") -> 266000.29 | AD59: =IF(U59="By Volume",(1-W59)*R59,X59/U59) -> 9929389.3 | AQ59: 312000 | AR59: 36000 | AS59: 8160 | AT59: ='By Project -Feb 2025'!DN55 -> 84960 | AU59: ='By Project -Feb 2025'!DO55 -> 4080 | AV59: ='By Project -Feb 2025'!DP55 -> 116280 | AW59: ='By Project -Feb 2025'!DQ55 -> 77520 | AX59: ='By Project -Feb 2025'!DR55 -> 206280 | AY59: ='By Project -Feb 2025'!DS55 -> 65640 | AZ59: ='By Project -Feb 2025'!DT55 -> 77040 | BA59: ='By Project -Feb 2025'!DU55 -> 80160 | ... BE59: ='By Project -Feb 2025'!DY55 -> 71520 | BF59: =SUM(AV59:BE59) -> 998160 | BH59: Alto Pods total (cartridge +bundle kit pod) | BI59: SOP1.4 | BJ59: RJR | BK59: 45635 | BL59: Alto Pods total (cartridge +bundle kit pod) | BM59: 370859400 | BN59: 265877200 | BO59: 263292400 | BP59: 249433450 | DB59: 19818800 | DC59: 26733700 | DD59: 25061300 | DE59: 16231300 | DF59: 31862400 | DG59: 18494250 | DH59: 25532300 | DI59: 28932600 | DJ59: 11088600 | DK59: 14612550 | DL59: 16636050 | DM59: 14429600 | DN59: 29540200 | DO59: 15516400 | DP59: 46369950 | DQ59: 39955200 | DR59: 25506950 | DS59: 21583600 | DT59: 27334550 | DU59: 22483600 | DV59: 20920550 | DW59: 25322400 | DX59: 19944000 | DY59: 25290000 | EA59: APA - Automation Production Agreement | EB59: Addendum No.10 - Indonesia | EC59: Alto Blister Reduction Capex
A60: 52 | B60: RF051_Modi2.0 | C60: Modi 2.0 | D60: Vuse Go 2.0 3K Box Full | E60: MD | F60: MD 2.0 | G60: CN | H60: Tooling | I60: Modi | J60: T2 | K60: Smoore T2 | L60: NVT | M60: 45536 | N60: 45992 | O60: 11061510 | P60: RMB | Q60: =IF(P60="RMB",O60/$B$6,IF(P60="GBP",O60,O60/$B$5)) -> 1202633.5 | R60: =Q60/U60 -> 46089626 | S60: 0.24 | T60: By Unit | U60: =IF(T60="By Unit", IF(P60="RMB",S60/$B$6,IF(P60="GBP",S60,S60/$B$5)),T60) -> 0.026093366 | V60: =R60*W60 -> 3100789 | W60: =AA60 -> 0.067277374 | X60: =IFERROR(Q60*(1-W60),"") -> 1121723.5 | Y60: =IF(X60>0,X60,0) -> 1121723.5 | Z60: Under Amortization | AA60: =(IFERROR(SUMIFS('ME Capex '!Z:Z,'ME Capex '!$A:$A,'By Project -Feb 2025'!$D60),0))/O60 -> 0.067277374 | AB60: =IFERROR(SUMIFS('ME Capex '!Z:Z,'ME Capex '!$A:$A,'By Project -Feb 2025'!$D60),0) -> 744189.37 | AC60: =IFERROR(Q60*(1-AA60),"") -> 1121723.5 | AD60: =IF(U60="By Volume",(1-W60)*R60,X60/U60) -> 42988837 | AQ60: 845000 | AR60: 522880 | AT60: ='By Project -Feb 2025'!DN49 -> 24120 | AU60: ='By Project -Feb 2025'!DO49 -> 208032 | AV60: ='By Project -Feb 2025'!DP49 -> 96000 | AW60: ='By Project -Feb 2025'!DQ49 -> 36096 | AX60: ='By Project -Feb 2025'!DR49 -> 271824 | AY60: ='By Project -Feb 2025'!DS49 -> 490848 | AZ60: ='By Project -Feb 2025'!DT49 -> 338460 | BA60: ='By Project -Feb 2025'!DU49 -> 457272 | ... BE60: ='By Project -Feb 2025'!DY49 -> 447432 | BF60: =SUM(AV60:BE60) -> 3276816 | BH60: Prismatic Taste Kit | BI60: SOP1.4 | BJ60: RJR | BK60: 45719 | BL60: Prismatic Taste Kit | BM60: 0 | BN60: 0 | BO60: 0 | BP60: 2910050 | CD60: 0 | CE60: 0 | CF60: 0 | CG60: 0 | CH60: 0 | CI60: 0 | CJ60: 0 | CK60: 0 | CL60: 0 | CM60: 0 | CN60: 0 | CO60: 0 | CP60: 0 | CQ60: 0 | CR60: 0 | CS60: 0 | CT60: 0 | CU60: 0 | CV60: 0 | CW60: 0 | CX60: 0 | CY60: 0 | CZ60: 0 | DA60: 0 | DB60: 0 | DC60: 0 | DD60: 0 | DE60: 450000 | DF60: 351000 | DG60: 392600 | DH60: 196500 | DI60: 337500 | DJ60: 171000 | DK60: 434800 | DL60: 375050 | DM60: 201600 | DN60: 0 | DO60: 189000 | DP60: 24000 | DQ60: 0 | DR60: 0 | DS60: 0 | DT60: 84000 | DU60: 84000 | DV60: 105000 | DW60: 180600 | DX60: 151200 | DY60: 168000
A61: 53 | B61: RF052_epod3pod | C61: ePod3 Pod | D61: ePod3 Pod tooling | E61: Pod | F61: Pod | G61: CN | H61: Tooling | I61: RCS | J61: T2 | K61: Smoore T2 | L61: NVT | M61: 44986 | N61: 45627 | O61: 16213779 | P61: RMB | Q61: =IF(P61="RMB",O61/$B$6,IF(P61="GBP",O61,O61/$B$5)) -> 1762800.3 | T61: By Unit | U61: =IF(T61="By Unit", IF(P61="RMB",S61/$B$6,IF(P61="GBP",S61,S61/$B$5)),T61) -> 0 | V61: =SUM(AE61:AS61) -> 18026607 | W61: =1-X61/Q61 -> 1 | X61: 0 | Y61: 0 | Z61: Paid-off | AG61: 12285257 | AH61: 1074798 | AI61: 65733 | AJ61: 894985 | AK61: 906260 | AL61: 1097616 | AM61: 617546 | AN61: 612910 | AO61: 277678 | AP61: 193824 | AT61: 0 | BF61: =SUM(AV61:BE61) -> 0 | BH61: Prismatic Pod | BI61: SOP1.4 | BJ61: RJR | BK61: 45719 | BL61: Prismatic Pods | BM61: 0 | BN61: 0 | BO61: 0 | BP61: 19002900 | CD61: 0 | CE61: 0 | CF61: 0 | CG61: 0 | CH61: 0 | CI61: 0 | CJ61: 0 | CK61: 0 | CL61: 0 | CM61: 0 | CN61: 0 | CO61: 0 | CP61: 0 | CQ61: 0 | CR61: 0 | CS61: 0 | CT61: 0 | CU61: 0 | CV61: 0 | CW61: 0 | CX61: 0 | CY61: 0 | CZ61: 0 | DA61: 0 | DB61: 0 | DC61: 0 | DD61: 0 | DE61: 3211800 | DF61: 2988300 | DG61: 1850100 | DH61: 3589500 | DI61: 3864300 | DJ61: 3416400 | DK61: 0 | DL61: 82500 | DM61: 0 | DN61: 0 | DO61: 97500 | DP61: 0 | DQ61: 0 | DR61: 0 | DS61: 0 | DT61: 0 | DU61: 0 | DV61: 0 | DW61: 0 | DX61: 0 | DY61: 0
A62: 54 | B62: RF053_Alto | C62: Alto | D62: Alto tooling | E62: RCS | F62: Pod | G62: Indo | H62: Tooling | I62: RCS | J62: T2 | K62: Smoore T2 | L62: Reynolds | M62: 44857 | N62: N/A | O62: 8718477 | P62: USD | Q62: =IF(P62="RMB",O62/$B$6,IF(P62="GBP",O62,O62/$B$5)) -> 6821008.8 | S62: 0.016248973 | T62: By Unit | U62: =IF(T62="By Unit", IF(P62="RMB",S62/$B$6,IF(P62="GBP",S62,S62/$B$5)),T62) -> 0.012712586 | V62: =SUM(AE62:AU62) -> 750044550 | W62: =IF(T62="By Volume",V62/R62,V62*U62/Q62) -> 1.3978879 | X62: =IFERROR(Q62*(1-W62),"")*0 -> 0 | Y62: 0 | Z62: Amortization Completed | AF62: 195500900 | AG62: 255515000 | AH62: 22785000 | AI62: 22092200 | AJ62: 25589000 | AK62: 18498600 | AL62: 30742700 | AM62: 18494250 | AN62: 25532300 | AO62: 28932600 | AP62: 11088600 | AQ62: 14612550 | AR62: 17543850 | AS62: 18060400 | AT62: ='By Project -Feb 2025'!DN59 -> 29540200 | AU62: ='By Project -Feb 2025'!DO59 -> 15516400 | AV62: ='By Project -Feb 2025'!DP59 -> 46369950 | AW62: ='By Project -Feb 2025'!DQ59 -> 39955200 | AX62: ='By Project -Feb 2025'!DR59 -> 25506950 | AY62: ='By Project -Feb 2025'!DS59 -> 21583600 | AZ62: ='By Project -Feb 2025'!DT59 -> 27334550 | BA62: ='By Project -Feb 2025'!DU59 -> 22483600 | ... BE62: ='By Project -Feb 2025'!DY59 -> 25290000 | BF62: =SUM(AV62:BE62) -> 274710800 | BH62: Prismatic Pods total(cartridge+Taste kit） | BI62: SOP1.4 | BJ62: RJR | BK62: 45719 | BL62: Prismatic Pods total(cartridge+Taste kit） | BM62: 0 | BN62: 0 | BO62: 0 | BP62: 24823000 | DB62: 0 | DC62: 0 | DD62: 0 | DE62: 4111800 | DF62: 3690300 | DG62: 2635300 | DH62: 3982500 | DI62: 4539300 | DJ62: 3758400 | DK62: 869600 | DL62: 832600 | DM62: 403200 | DN62: 0 | DO62: 475500 | DP62: 48000 | DQ62: 0 | DR62: 0 | DS62: 0 | DT62: 168000 | DU62: 168000 | DV62: 210000 | DW62: 361200 | DX62: 302400 | DY62: 336000 | EA62: APA - Automation Production Agreement | EB62: Addendum No.10 - Indonesia
A63: 55 | B63: RF054_Hestia1.1 | C63: Hestia 1.1 | D63: Hestia 1.1 tooling NON-smart unique+ECN | E63: RCS | F63: Pod | G63: CN | H63: Tooling | I63: RCS | J63: T2 | K63: Smoore T2 | L63: NVT | M63: 45777 | N63: 46507 | O63: 2009900 | P63: RMB | Q63: =IF(P63="RMB",O63/$B$6,IF(P63="GBP",O63,O63/$B$5)) -> 218521.07 | R63: 0 | T63: By Unit | U63: =IF(T63="By Unit", IF(P63="RMB",S63/$B$6,IF(P63="GBP",S63,S63/$B$5)),T63) -> 0 | W63: =IF(T63="By Volume",V63/R63,V63*U63/Q63) -> 0 | X63: =IFERROR(Q63*(1-W63),"") -> 218521.07 | Y63: 0 | Z63: NPD | BF63: =SUM(AV63:BE63) -> 0 | BH63: Sensa 5K | BI63: RJR FC_0206 | BJ63: RJR | BK63: 45694 | BL63: Alto 5K Full | BM63: 0 | BN63: 0 | BO63: 0 | BP63: 3299400 | CD63: 0 | CE63: 0 | CF63: 0 | CG63: 0 | CH63: 0 | CI63: 0 | CJ63: 0 | CK63: 0 | CL63: 0 | CM63: 0 | CN63: 0 | CO63: 0 | CP63: 0 | CQ63: 0 | CR63: 0 | CS63: 0 | CT63: 0 | CU63: 0 | CV63: 0 | CW63: 0 | CX63: 0 | CY63: 0 | CZ63: 0 | DA63: 0 | DB63: 0 | DC63: 0 | DD63: 0 | DE63: 0 | DF63: 728760 | DG63: 1410720 | DH63: 434160 | DI63: 376920 | DJ63: 348840 | DK63: 0 | DL63: 0 | DM63: 0 | DN63: 0 | DO63: 0 | DP63: 0 | DQ63: 0 | DR63: 0 | DS63: 0 | DT63: 0 | DU63: 0 | DV63: 0 | DW63: 0 | DX63: 0 | DY63: 0
A64: 56 | B64: RF055_Hestia1.1 | C64: Hestia 1.1 | D64: Hestia 1.1 tooling initial smart and commont parts | E64: RCS | F64: Pod | G64: CN | H64: Tooling | I64: RCS | J64: T2 | K64: Smoore T2 | L64: NVT | M64: 45777 | N64: 46507 | O64: 10069487 | P64: RMB | Q64: =IF(P64="RMB",O64/$B$6,IF(P64="GBP",O64,O64/$B$5)) -> 1094778.4 | S64: 0.1939 | T64: By Unit | U64: =IF(T64="By Unit", IF(P64="RMB",S64/$B$6,IF(P64="GBP",S64,S64/$B$5)),T64) -> 0.021081266 | W64: =IF(T64="By Volume",V64/R64,V64*U64/Q64) -> 0 | X64: =IFERROR(Q64*(1-W64),"") -> 1094778.4 | Y64: 0 | Z64: NPD | AT64: 0 | AU64: ='By Project -Feb 2025'!DO14 -> 29970 | AV64: ='By Project -Feb 2025'!DP14 -> 576000 | AW64: ='By Project -Feb 2025'!DQ14 -> 811150 | AX64: ='By Project -Feb 2025'!DR14 -> 1104660 | AY64: ='By Project -Feb 2025'!DS14 -> 817540 | AZ64: ='By Project -Feb 2025'!DT14 -> 476460 | BA64: ='By Project -Feb 2025'!DU14 -> 606300 | BB64: ='By Project -Feb 2025'!DV14 -> 610230 | ... BE64: ='By Project -Feb 2025'!DY14 -> 613260 | BF64: =SUM(AV64:BE64) -> 6679340 | BI64: SOP12.1 | BM64: 521304320 | BN64: 468436913 | BO64: 397158290 | BP64: 469298356 | BQ64: 9366300 | BR64: 5088060 | BS64: 10606320 | BT64: 9598860 | BU64: 14671980 | BV64: 14349580 | BW64: 12979220 | BX64: 15256580 | BY64: 15964420 | BZ64: 12569000 | CA64: 15497160 | CB64: 14497440 | CD64: 15559440 | CE64: 12012360 | CF64: 18465130 | CG64: 19798430 | CH64: 23406028 | CI64: 26965023 | CJ64: 37630703 | CK64: 43853585 | CL64: 58256164 | CM64: 32802598 | CN64: 42920800 | CO64: 48233339 | CP64: 41323124 | CQ64: 41261193 | CR64: 45338256 | CS64: 35612524 | CT64: 37187474 | CU64: 39990544 | CV64: 36028066 | CW64: 27053480 | CX64: 26089463 | CY64: 17352266 | CZ64: 41595510 | DA64: 29854630 | DB64: 31128050 | DC64: 32641880 | DD64: 35407550 | DE64: 30530144 | DF64: 51927022 | DG64: 47492450 | DH64: 48987358 | DI64: 57967194 | DJ64: 37012910 | DK64: 32432066 | DL64: 32111920 | DM64: 31659812 | DN64: 49325134 | DO64: 24094072 | DP64: 33634028 | DQ64: 34681186 | DR64: 30539856 | DS64: 34099475 | DT64: 36698503 | DU64: 35034668 | DV64: 32811629 | DW64: 35888193 | DX64: 32888857 | DY64: 33677829
A65: 57 | B65: RF056_Hestia1.1 | C65: Hestia 1.1 | D65: Hestia 1.1 tooling incremental | E65: RCS | F65: Pod | G65: CN | H65: Tooling | I65: RCS | J65: T2 | K65: Smoore T2 | L65: NVT | M65: 45777 | N65: 46507 | P65: RMB | Q65: =IF(P65="RMB",O65/$B$6,IF(P65="GBP",O65,O65/$B$5)) -> 0 | T65: By Unit | U65: =IF(T65="By Unit", IF(P65="RMB",S65/$B$6,IF(P65="GBP",S65,S65/$B$5)),T65) -> 0 | W65: =IF(T65="By Volume",V65/R65,V65*U65/Q65) -> #DIV/0! | X65: =IFERROR(Q65*(1-W65),0) -> 0 | Y65: 0 | Z65: NPD | AU65: ='By Project -Feb 2025'!DO14 -> 29970 | AV65: ='By Project -Feb 2025'!DP14 -> 576000 | AW65: ='By Project -Feb 2025'!DQ14 -> 811150 | AX65: ='By Project -Feb 2025'!DR14 -> 1104660 | AY65: ='By Project -Feb 2025'!DS14 -> 817540 | AZ65: ='By Project -Feb 2025'!DT14 -> 476460 | BA65: ='By Project -Feb 2025'!DU14 -> 606300 | BB65: ='By Project -Feb 2025'!DV14 -> 610230 | ... BE65: ='By Project -Feb 2025'!DY14 -> 613260 | BF65: =SUM(AV65:BE65) -> 6679340 | BI65: Cartridges Total | BM65: 0 | BN65: 86189947 | BO65: 102047186 | BP65: 97469652 | BQ65: 0 | BR65: 0 | BS65: 0 | BT65: 0 | BU65: 0 | BV65: 0 | BW65: 0 | BX65: 0 | BY65: 0 | BZ65: 0 | CA65: 0 | CB65: 0 | CD65: 0 | CE65: 0 | CF65: 0 | CG65: 932000 | CH65: 2904000 | CI65: 6345360 | CJ65: 12084000 | CK65: 12364000 | CL65: 14666000 | CM65: 7120798 | CN65: 18203789 | CO65: 11570000 | CP65: 9075800 | CQ65: 8437600 | CR65: 10342600 | CS65: 14465200 | CT65: 8559800 | CU65: 7514600 | CV65: 6556800 | CW65: 7044946 | CX65: 9026320 | CY65: 9701480 | CZ65: 8363040 | DA65: 2959000 | DB65: 3799544 | DC65: 2069304 | DD65: 3374376 | DE65: 5449368 | DF65: 8148152 | DG65: 10331936 | DH65: 10161984 | DI65: 13723968 | DJ65: 10955448 | DK65: 12221840 | DL65: 10098556 | DM65: 7135176 | DN65: 4385016 | DO65: 3352744 | DP65: 3298140 | DQ65: 5150200 | DR65: 5252844 | DS65: 7607097 | DT65: 6144799 | DU65: 7092410 | DV65: 6236532 | DW65: 6095646 | DX65: 7886988 | DY65: 6036936
A66: 58 | B66: RF057_KumaE2.0 | C66: Kuma E 2.0 | D66: Kuma E 2.0 Pen tooling initial | E66: RCS | F66: Vuse device(ROW) | G66: CN | H66: Tooling | I66: RCS | J66: T2 | K66: Smoore T2 | L66: NVT | M66: 45620 | N66: 46350 | O66: 7732809 | P66: RMB | Q66: =IF(P66="RMB",O66/$B$6,IF(P66="GBP",O66,O66/$B$5)) -> 840729.24 | S66: 0.2015 | T66: By Unit | U66: =IF(T66="By Unit", IF(P66="RMB",S66/$B$6,IF(P66="GBP",S66,S66/$B$5)),T66) -> 0.021907556 | W66: =IF(T66="By Volume",V66/R66,V66*U66/Q66) -> 0 | X66: =IFERROR(Q66*(1-W66),"") -> 840729.24 | Y66: 0 | Z66: NPD | BF66: =SUM(AV66:BE66) -> 0 | BI66: Disposable Total | BM66: 21928601 | BN66: 25418470 | BO66: 9400250 | BP66: 16174136 | BQ66: 2336600 | BR66: 685900 | BS66: 1486000 | BT66: 2171200 | BU66: 1403100 | BV66: 1722345 | BW66: 1580200 | BX66: 1325700 | BY66: 1790900 | BZ66: 2290731 | CA66: 2414600 | CB66: 2365600 | CD66: 2103000 | CE66: 1225400 | CF66: 2524265 | CG66: 2861600 | CH66: 2498600 | CI66: 2780600 | CJ66: 2321650 | CK66: 2133650 | CL66: 1317255 | CM66: 978600 | CN66: 1238200 | CO66: 1862200 | CP66: 1660750 | CQ66: 2520350 | CR66: 2498900 | CS66: 1497550 | CT66: 1281100 | CU66: 802600 | CV66: 1513800 | CW66: 1122900 | CX66: 687800 | CY66: 697700 | CZ66: 1070200 | DA66: 1824000 | DB66: 1333100 | DC66: 563500 | DD66: 980500 | DE66: 1567120 | DF66: 1174100 | DG66: 762090 | DH66: 1363576 | DI66: 1433940 | DJ66: 1771560 | DK66: 1946150 | DL66: 1380500 | DM66: 1898000 | DN66: 1628186 | DO66: 1005872 | DP66: 719520 | DQ66: 959628 | DR66: 751372 | DS66: 758202 | DT66: 943514 | DU66: 907316 | DV66: 858682 | DW66: 1061394 | DX66: 884696 | DY66: 1075695
A67: 59 | B67: RF058_KumaE2.0 | C67: Kuma E 2.0 | D67: Kuma E 2.0 Pen tooling incremental | E67: RCS | F67: Vuse device(ROW) | G67: CN | H67: Tooling | I67: RCS | J67: T2 | K67: Smoore T2 | L67: NVT | M67: 45620 | N67: 46350 | O67: 0 | P67: RMB | Q67: =IF(P67="RMB",O67/$B$6,IF(P67="GBP",O67,O67/$B$5)) -> 0 | T67: By Unit | U67: =IF(T67="By Unit", IF(P67="RMB",S67/$B$6,IF(P67="GBP",S67,S67/$B$5)),T67) -> 0 | W67: =IF(T67="By Volume",V67/R67,V67*U67/Q67) -> #DIV/0! | X67: =IFERROR(Q67*(1-W67),0) -> 0 | Y67: 0 | Z67: NPD | BF67: =SUM(AV67:BE67) -> 0
A68: 60 | B68: RF059_Mimosa1.0 | C68: Mimosa | D68: Mimosa 1.0 tooling initial | E68: RCS | F68: Vuse device(ROW) | G68: CN | H68: Tooling | I68: RCS | J68: T2 | K68: Smoore T2 | L68: NVT | M68: 45689 | N68: 46411 | O68: 10157605 | P68: RMB | Q68: =IF(P68="RMB",O68/$B$6,IF(P68="GBP",O68,O68/$B$5)) -> 1104358.8 | R68: =Q68/U68 -> 5098687.4 | S68: 1.9922 | T68: By Unit | U68: =IF(T68="By Unit", IF(P68="RMB",S68/$B$6,IF(P68="GBP",S68,S68/$B$5)),T68) -> 0.21659669 | V68: =R68*W68 -> 82859.771 | W68: =AA68 -> 0.016251197 | X68: =IFERROR(Q68*(1-W68),"") -> 1086411.6 | Y68: 0 | Z68: Under Amortization | AA68: =(IFERROR(SUMIFS('ME Capex '!Z:Z,'ME Capex '!$A:$A,'By Project -Feb 2025'!$D68),0))/O68 -> 0.016251197 | AB68: =IFERROR(SUMIFS('ME Capex '!Z:Z,'ME Capex '!$A:$A,'By Project -Feb 2025'!$D68),0) -> 165073.24 | AC68: =IFERROR(Q68*(1-AA68),"") -> 1086411.6 | AD68: =IF(U68="By Volume",(1-W68)*R68,X68/U68) -> 5015827.6 | AT68: 0 | AU68: 3744 | AV68: 72000 | AW68: 153000 | AX68: 99000 | AY68: 18000 | AZ68: 36336 | BA68: 56016 | BB68: 38736 | BC68: 46032 | BD68: 44928 | BE68: 43776 | BF68: =SUM(AV68:BE68) -> 607824
A69: 61 | B69: RF060_Mimosa1.0 | C69: Mimosa | D69: Mimosa 1.0 tooling incremental | E69: RCS | F69: Vuse device(ROW) | G69: CN | H69: Tooling | I69: RCS | J69: T2 | K69: Smoore T2 | L69: NVT | M69: 45689 | N69: 46411 | O69: 217300 | P69: RMB | Q69: =IF(P69="RMB",O69/$B$6,IF(P69="GBP",O69,O69/$B$5)) -> 23625.369 | T69: By Unit | U69: =IF(T69="By Unit", IF(P69="RMB",S69/$B$6,IF(P69="GBP",S69,S69/$B$5)),T69) -> 0 | V69: =R69*W69 -> 0 | W69: =AA69 -> 0 | X69: =IFERROR(Q69*(1-W69),"") -> 23625.369 | Y69: 0 | Z69: Under Amortization | AA69: =(IFERROR(SUMIFS('ME Capex '!Z:Z,'ME Capex '!$A:$A,'By Project -Feb 2025'!$D69),0))/O69 -> 0 | AB69: =IFERROR(SUMIFS('ME Capex '!Z:Z,'ME Capex '!$A:$A,'By Project -Feb 2025'!$D69),0) -> 0 | AC69: =IFERROR(Q69*(1-AA69),"") -> 23625.369 | AT69: 0 | AU69: 3744 | AV69: 72000 | AW69: 153000 | AX69: 99000 | AY69: 18000 | AZ69: 36336 | BA69: 56016 | BB69: 38736 | BC69: 46032 | BD69: 44928 | BE69: 43776 | BF69: =SUM(AV69:BE69) -> 607824
A70: 62 | B70: RF061_PrismaticPod | C70: Prismatic Pod | D70: China | E70: RCS | F70: Pod | G70: CN | H70: N/A | I70: RCS | J70: T2 | K70: Smoore T2 | L70: NVT | M70: 45352 | N70: 46082 | O70: 98000 | P70: RMB | Q70: =IF(P70="RMB",O70/$B$6,IF(P70="GBP",O70,O70/$B$5)) -> 10654.791 | S70: 0.0030625 | T70: By Unit | U70: =IF(T70="By Unit", IF(P70="RMB",S70/$B$6,IF(P70="GBP",S70,S70/$B$5)),T70) -> 0.00033296223 | W70: =IF(T70="By Volume",V70/R70,V70*U70/Q70) -> 0 | X70: 0 | Y70: 0 | Z70: Paid-off | AV70: 106560 | BF70: =SUM(AV70:BE70) -> 106560
A71: 63 | B71: RF062_PrismaticPod | C71: Prismatic Pod | D71: Prismatic Pod Indo Black | E71: RCS | F71: Pod | G71: Indo | H71: N/A | I71: RCS | J71: T2 | K71: Smoore T2 | L71: NVT | M71: 45839 | N71: 46569 | O71: 4584750.8 | P71: RMB | Q71: =IF(P71="RMB",O71/$B$6,IF(P71="GBP",O71,O71/$B$5)) -> 498464.93 | R71: 54607346 | S71: =O71/R71 -> 0.0839585 | T71: By Unit | U71: =IF(T71="By Unit", IF(P71="RMB",S71/$B$6,IF(P71="GBP",S71,S71/$B$5)),T71) -> 0.0091281663 | V71: 162200 | W71: =IF(T71="By Volume",V71/R71,V71*U71/Q71) -> 0.0029702964 | X71: =IFERROR(Q71*(1-W71),"") -> 496984.34 | Y71: 0 | Z71: NPD | BF71: =SUM(AV71:BE71) -> 0
A72: 64 | B72: RF063_PrismaticPod | C72: Prismatic Pod | D72: Prismatic Pod Indo white | E72: RCS | F72: Pod | G72: Indo | H72: N/A | I72: RCS | J72: T2 | K72: Smoore T2 | L72: NVT | M72: 45839 | N72: 46569 | O72: 3933456.4 | P72: RMB | Q72: =IF(P72="RMB",O72/$B$6,IF(P72="GBP",O72,O72/$B$5)) -> 427654.66 | R72: 54607346 | S72: =O72/R72 -> 0.072031634 | T72: By Unit | U72: =IF(T72="By Unit", IF(P72="RMB",S72/$B$6,IF(P72="GBP",S72,S72/$B$5)),T72) -> 0.0078314493 | V72: 162200 | W72: =IF(T72="By Volume",V72/R72,V72*U72/Q72) -> 0.0029702964 | X72: =IFERROR(Q72*(1-W72),"") -> 426384.4 | Y72: 0 | Z72: NPD | BF72: =SUM(AV72:BE72) -> 0
A73: 65 | B73: RF064_MimosaSmart | C73: Mimosa | D73: Mimosa 1.0 - PCBA Tooling | E73: RCS | F73: Vuse device(ROW) | G73: CN | H73: Tooling | I73: RCS | J73: T2 | K73: BYD T2 | L73: NVT | M73: 45778 | N73: 46143 | O73: 1359200 | P73: RMB | Q73: =IF(P73="RMB",O73/$B$6,IF(P73="GBP",O73,O73/$B$5)) -> 147775.43 | R73: 1000000 | S73: =O73/R73 -> 1.3592 | T73: By Unit | U73: =IF(T73="By Unit", IF(P73="RMB",S73/$B$6,IF(P73="GBP",S73,S73/$B$5)),T73) -> 0.14777543 | V73: =R73*W73 -> 0 | W73: =AA73 -> 0 | X73: =IFERROR(Q73*(1-W73),"") -> 147775.43 | Y73: 0 | Z73: Under Amortization | AA73: =(IFERROR(SUMIFS('ME Capex '!Z:Z,'ME Capex '!$A:$A,'By Project -Feb 2025'!$D73),0))/O73 -> 0 | AB73: =IFERROR(SUMIFS('ME Capex '!Z:Z,'ME Capex '!$A:$A,'By Project -Feb 2025'!$D73),0) -> 0 | AC73: =IFERROR(Q73*(1-AA73),"") -> 147775.43 | AD73: =IF(U73="By Volume",(1-W73)*R73,X73/U73) -> 1000000 | AT73: 0 | AU73: 3744 | AV73: 72000 | AW73: 153000 | AX73: 99000 | AY73: 18000 | AZ73: 36336 | BA73: 56016 | BB73: 38736 | BC73: 46032 | BD73: 44928 | BE73: 43776 | BF73: =SUM(AV73:BE73) -> 607824
A74: 66 | B74: RF065_Epod3 | C74: Epod 3 | D74: Epod 3 - PCBA Tooling | E74: RCS | F74: Vuse device(ROW) | G74: CN | H74: Tooling | I74: RCS | J74: T2 | K74: BYD T2 | L74: NVT | M74: NA | N74: NA | O74: 817400 | P74: RMB | Q74: =IF(P74="RMB",O74/$B$6,IF(P74="GBP",O74,O74/$B$5)) -> 88869.657 | R74: NA | S74: NA | T74: By Unit | U74: =IF(T74="By Unit", IF(P74="RMB",S74/$B$6,IF(P74="GBP",S74,S74/$B$5)),T74) -> #VALUE! | V74: =SUM(AE74:AU74) -> 89492 | W74: 1 | X74: 0 | Y74: 0 | Z74: Amortization Completed | AT74: 89492 | BF74: =SUM(AV74:BE74) -> 0
A75: 67 | B75: RF066_Epod3+ | C75: Epod 3+ | D75: Epod 3+ - PCBA Tooling | E75: RCS | F75: Vuse device(ROW) | G75: CN | H75: Tooling | I75: RCS | J75: T2 | K75: BYD T2 | L75: NVT | M75: NA | N75: NA | O75: 1357000 | P75: RMB | Q75: =IF(P75="RMB",O75/$B$6,IF(P75="GBP",O75,O75/$B$5)) -> 147536.24 | R75: NA | S75: NA | T75: By Unit | U75: =IF(T75="By Unit", IF(P75="RMB",S75/$B$6,IF(P75="GBP",S75,S75/$B$5)),T75) -> #VALUE! | V75: =SUM(AE75:AU75) -> 27600 | W75: 1 | X75: 0 | Y75: 0 | Z75: Amortization Completed | AT75: 27600 | BF75: =SUM(AV75:BE75) -> 0
A76: 68 | B76: RF067_Hestia1.1 | C76: Hestia 1.1 | D76: Hestia 1.1 - PCBA Tooling | E76: Pod | F76: Pod | G76: CN | I76: RCS | J76: T2 | K76: BYD T2 | L76: NVT | M76: 45777 | N76: 46507 | O76: 212750 | P76: RMB | Q76: =IF(P76="RMB",O76/$B$6,IF(P76="GBP",O76,O76/$B$5)) -> 23130.682 | R76: 4000000 | S76: =O76/R76 -> 0.0531875 | T76: By Unit | U76: =IF(T76="By Unit", IF(P76="RMB",S76/$B$6,IF(P76="GBP",S76,S76/$B$5)),T76) -> 0.0057826705 | W76: =IF(T76="By Volume",V76/R76,V76*U76/Q76) -> 0 | X76: =IFERROR(Q76*(1-W76),"") -> 23130.682 | Y76: 0 | Z76: NPD | AT76: 0 | AU76: ='By Project -Feb 2025'!DO14 -> 29970 | AV76: ='By Project -Feb 2025'!DP14 -> 576000 | AW76: ='By Project -Feb 2025'!DQ14 -> 811150 | AX76: ='By Project -Feb 2025'!DR14 -> 1104660 | AY76: ='By Project -Feb 2025'!DS14 -> 817540 | AZ76: ='By Project -Feb 2025'!DT14 -> 476460 | BA76: ='By Project -Feb 2025'!DU14 -> 606300 | BB76: ='By Project -Feb 2025'!DV14 -> 610230 | ... BE76: ='By Project -Feb 2025'!DY14 -> 613260 | BF76: =SUM(AV76:BE76) -> 6679340
A77: 69 | B77: RF068_KumaE2.0PenNZ | C77: Kuma E 2.0 Pen NZ | D77: Kuma E 2.0 Pen NZ - PCBA Tooling | E77: RCS | F77: Vuse device(ROW) | G77: CN | H77: Tooling | I77: RCS | J77: T2 | K77: BYD T2 | L77: NVT | M77: 45604 | N77: 46334 | O77: 715900 | P77: RMB | Q77: =IF(P77="RMB",O77/$B$6,IF(P77="GBP",O77,O77/$B$5)) -> 77834.338 | R77: 4000000 | S77: =O77/R77 -> 0.178975 | T77: By Unit | U77: =IF(T77="By Unit", IF(P77="RMB",S77/$B$6,IF(P77="GBP",S77,S77/$B$5)),T77) -> 0.019458584 | V77: =R77*W77 -> 0 | W77: =AA77 -> 0 | X77: =IFERROR(Q77*(1-W77),"") -> 77834.338 | Y77: 0 | Z77: Under Amortization | AA77: =(IFERROR(SUMIFS('ME Capex '!Z:Z,'ME Capex '!$A:$A,'By Project -Feb 2025'!$D77),0))/O77 -> 0 | AB77: =IFERROR(SUMIFS('ME Capex '!Z:Z,'ME Capex '!$A:$A,'By Project -Feb 2025'!$D77),0) -> 0 | AC77: =IFERROR(Q77*(1-AA77),"") -> 77834.338 | AD77: =IF(U77="By Volume",(1-W77)*R77,X77/U77) -> 4000000 | BF77: =SUM(AV77:BE77) -> 0
A78: 70 | B78: RF069_KumaE2.0Box | C78: Kuma E 2.0 Box | D78: Kuma E 2.0 Box - PCBA Tooling | E78: RCS | F78: Vuse device(ROW) | G78: CN | H78: Tooling | I78: RCS | J78: T2 | K78: BYD T2 | L78: NVT | M78: 45761 | N78: 46491 | O78: 824300 | P78: RMB | Q78: =IF(P78="RMB",O78/$B$6,IF(P78="GBP",O78,O78/$B$5)) -> 89619.841 | R78: 3000000 | S78: =O78/R78 -> 0.27476667 | T78: By Unit | U78: =IF(T78="By Unit", IF(P78="RMB",S78/$B$6,IF(P78="GBP",S78,S78/$B$5)),T78) -> 0.02987328 | W78: =IF(T78="By Volume",V78/R78,V78*U78/Q78) -> 0 | X78: =IFERROR(Q78*(1-W78),"") -> 89619.841 | Y78: 0 | Z78: NPD | BF78: =SUM(AV78:BE78) -> 0
A79: 71 | B79: RF070_KumaEMax | C79: Kuma E Max | D79: Kuma E Max - PCBA Tooling | E79: RCS | F79: Vuse device(ROW) | G79: CN | H79: Tooling | I79: RCS | J79: T2 | K79: BYD T2 | L79: NVT | M79: TBC | N79: TBC | O79: 692800 | P79: RMB | Q79: =IF(P79="RMB",O79/$B$6,IF(P79="GBP",O79,O79/$B$5)) -> 75322.851 | R79: 4000000 | S79: =O79/R79 -> 0.1732 | T79: By Unit | U79: =IF(T79="By Unit", IF(P79="RMB",S79/$B$6,IF(P79="GBP",S79,S79/$B$5)),T79) -> 0.018830713 | W79: =IF(T79="By Volume",V79/R79,V79*U79/Q79) -> 0 | X79: =IFERROR(Q79*(1-W79),"") -> 75322.851 | Y79: 0 | Z79: NPD | BF79: =SUM(AV79:BE79) -> 0
A80: 72 | B80: RF071_Aquila-US | C80: Aquila-US | D80: Aquila-US - PCBA Tooling | E80: RCS | F80: Vuse Device( US Alto) | G80: CN | H80: Tooling | I80: RCS | J80: T2 | K80: BYD T2 | L80: NVT | M80: TBC | N80: TBC | O80: 1480600 | P80: RMB | Q80: =IF(P80="RMB",O80/$B$6,IF(P80="GBP",O80,O80/$B$5)) -> 160974.33 | R80: 4000000 | S80: =O80/R80 -> 0.37015 | T80: By Unit | U80: =IF(T80="By Unit", IF(P80="RMB",S80/$B$6,IF(P80="GBP",S80,S80/$B$5)),T80) -> 0.040243582 | W80: =IF(T80="By Volume",V80/R80,V80*U80/Q80) -> 0 | X80: =IFERROR(Q80*(1-W80),"") -> 160974.33 | Y80: 0 | Z80: NPD | BF80: =SUM(AV80:BE80) -> 0
A81: 73 | B81: RF072_PrismaticPod | C81: Prismatic Pod | D81: Indo POD T1 transfer Capex | E81: RCS | F81: Pod | G81: Indo | H81: N/A | I81: RCS | J81: T1 | K81: Smoore T1 | L81: Reynolds | M81: 45839 | N81: 46569 | O81: 1714020.5 | P81: RMB | Q81: =IF(P81="RMB",O81/$B$6,IF(P81="GBP",O81,O81/$B$5)) -> 186352.35 | R81: 54607346 | S81: =O81/R81 -> 0.031388093 | T81: By Unit | U81: =IF(T81="By Unit", IF(P81="RMB",S81/$B$6,IF(P81="GBP",S81,S81/$B$5)),T81) -> 0.0034125876 | V81: 162200 | W81: =IF(T81="By Volume",V81/R81,V81*U81/Q81) -> 0.0029702964 | X81: =IFERROR(Q81*(1-W81),"") -> 185798.83 | Y81: 0 | Z81: NPD | BF81: =SUM(AV81:BE81) -> 0
A82: 74 | B82: RF073_Hestia1.0 | C82: Hestia 1.0 | D82: ePod 2 to Hestia1.0 / ePod compatible line (6th line) | E82: RCS | F82: Pod | G82: CN | H82: Pod Automation | I82: RCS | J82: T1 | K82: Smoore T1 | L82: NVT | M82: TBC | N82: TBC | O82: 13323188 | P82: RMB | Q82: =IF(P82="RMB",O82/$B$6,IF(P82="GBP",O82,O82/$B$5)) -> 1448528.4 | T82: By Unit | U82: =IF(T82="By Unit", IF(P82="RMB",S82/$B$6,IF(P82="GBP",S82,S82/$B$5)),T82) -> 0 | W82: =IF(T82="By Volume",V82/R82,V82*U82/Q82) -> 0 | X82: =IFERROR(Q82*(1-W82),"") -> 1448528.4 | Z82: NPD | BF82: =SUM(AV82:BE82) -> 0
A83: 76 | C83: Kuma E 2.0 Box | D83: Kuma E 2.0 Box Tooling | E83: RCS | F83: Device | G83: CN | H83: Tooling | I83: RCS | J83: T2 | K83: Smoore T2 | L83: NVT | M83: 45761 | N83: 46491 | O83: 4711062.4 | P83: RMB | Q83: =IF(P83="RMB",O83/$B$6,IF(P83="GBP",O83,O83/$B$5)) -> 512197.82 | S83: 0.3225 | T83: By Unit | Z83: NPD
A84: 77 | C84: Prismatic Kit | D84: Primsmatic Kit VAT/qualification cost | E84: RCS | F84: Pod | G84: Indo | H84: N/A | I84: RCS | J84: T1 | K84: Smoore T1 | L84: Reynolds | M84: 45839 | N84: 46569 | O84: 116400 | P84: USD | Q84: =IF(P84="RMB",O84/$B$6,IF(P84="GBP",O84,O84/$B$5)) -> 91066.986 | R84: 2400000 | S84: =O84/R84 -> 0.0485 | T84: By Unit | U84: =IF(T84="By Unit", IF(P84="RMB",S84/$B$6,IF(P84="GBP",S84,S84/$B$5)),T84) -> 0.037944577 | W84: =IF(T84="By Volume",V84/R84,V84*U84/Q84) -> 0 | X84: =IFERROR(Q84*(1-W84),"") -> 91066.986 | Y84: 0 | Z84: NPD
C85: Kuma E 2.0 Pen ROW | D85: Kuma E 2.0 Pen ROW - PCBA Tooling | E85: RCS | F85: Device | G85: CN | H85: Tooling | I85: RCS | J85: T2 | K85: BYD T2 | L85: NVT | M85: 45778 | N85: 46508 | O85: 1668455.6 | P85: RMB | Q85: =IF(P85="RMB",O85/$B$6,IF(P85="GBP",O85,O85/$B$5)) -> 181398.43 | R85: 3000000 | S85: =O85/R85 -> 0.55615187 | T85: By Unit | U85: =IF(T85="By Unit", IF(P85="RMB",S85/$B$6,IF(P85="GBP",S85,S85/$B$5)),T85) -> 0.060466143 | W85: 0 | Y85: 0
C86: VEGA | D86: Automation CFU Line (ACCRUED) | E86: MD | H86: Asset | I86: MoDi | J86: T1 | K86: CFU T1 | L86: NVT | M86: 45139 | N86: 45566 | O86: 31179700 | P86: RMB | Q86: =IF(P86="RMB",O86/$B$6,IF(P86="GBP",O86,O86/$B$5)) -> 3389930.6 | R86: 40000000 | S86: 0 | T86: By Unit | U86: =IF(T86="By Unit", IF(P86="RMB",S86/$B$6,IF(P86="GBP",S86,S86/$B$5)),T86) -> 0 | W86: =1-X86/Q86 -> 1 | X86: 0 | Y86: 0 | Z86: Paid-off
C87: VEGA | D87: Tax Stamp | E87: MD | H87: Asset - Tax Stamp | I87: Modi | J87: T1 | K87: CFU T1 | L87: NVT | M87: 45231 | N87: 45474 | O87: 340000 | P87: RMB | Q87: =IF(P87="RMB",O87/$B$6,IF(P87="GBP",O87,O87/$B$5)) -> 36965.602 | R87: 2000000 | S87: 0.17 | T87: By Unit | U87: =IF(T87="By Unit", IF(P87="RMB",S87/$B$6,IF(P87="GBP",S87,S87/$B$5)),T87) -> 0.018482801 | W87: 1 | X87: 0 | Y87: 0 | Z87: Amortization Completed
C88: VEGA | D88: VEGA tooling | E88: MD | H88: Tooling | I88: MoDi | J88: T2 | K88: CFU T2 | L88: NVT | M88: 45017 | N88: 45566 | O88: 39733460 | P88: RMB | Q88: =IF(P88="RMB",O88/$B$6,IF(P88="GBP",O88,O88/$B$5)) -> 4319915.5 | S88: 0.1792 | T88: By Unit | U88: =IF(T88="By Unit", IF(P88="RMB",S88/$B$6,IF(P88="GBP",S88,S88/$B$5)),T88) -> 0.019483047 | W88: =1-X88/Q88 -> 1 | X88: 0 | Y88: 0 | Z88: Paid-off
C89: Kuma E Max | D89: Kuma E Max Tooling | E89: RCS | F89: Vuse device(ROW) | G89: CN | H89: Tooling | I89: RCS | J89: T2 | K89: Smoore T2 | L89: NVT | Z89: NPD
N98: `
X108: {=DP59+AV11+BG18:BH18+BG18:BH18} -> 92787900 | Y108: #VALUE!

Sheet ME Capex 
A1: Project | B1: Project | C1: Product Category | D1: Part Name | E1: Part No. | F1: Supplier | G1: Commonality | H1: Commodity | I1: Year | J1: Month | K1: Data Submit Date | L1: Split | M1: Unit price w/o amortization | N1: Unit Price with Amortization | O1: Amortization Cost | P1: Blended Amortization Cost | Q1: Usage in BOM | R1: BOM cost | S1: Shipped Volume | T1: Cum Shipped Volume | U1: Total Capex Cost | V1: Remaining Capex Cost (RMB) | W1: Remaining Capex Cost (GBP) | X1: TOTAL VOLUME TO PAY INESTMENT OFF | Z1: Total PAID
A2: KUMA E-ROW E Pen 1.0 | B2: KUMA E-Pen 1.0 ROW | C2: RCS DEVICE | D2: Battery tube | E2: 130040670046310 | F2: BYD | H2: Plastic | I2: 2024 | J2: 7 | K2: 45602 | L2: 1 | M2: 1.8255822 | N2: 1.8908572 | O2: 0.065275 | P2: 0.065275 | Q2: 1 | R2: 1.8255822 | S2: 122830 | T2: 122830 | U2: 1566600 | V2: 1558582.3 | W2: =V2/$AB$1 -> #DIV/0! | Z2: =O2*S2 -> 8017.7282
A3: KUMA E-ROW E Pen 1.0 | B3: KUMA E-Pen 1.0 ROW | C3: RCS DEVICE | D3: Bottom cap | E3: 130020670034027 | F3: BYD | H3: Plastic | I3: 2024 | J3: 7 | K3: 45602 | L3: 1 | M3: 0.61681485 | N3: 0.67358985 | O3: 0.056775 | P3: 0.056775 | Q3: 1 | R3: 0.61681485 | S3: 191796 | T3: 191796 | U3: 1135500 | V3: 1124610.8 | W3: =V3/$AB$1 -> #DIV/0! | Z3: =O3*S3 -> 10889.218
A4: KUMA E-ROW E Pen 1.0 | B4: KUMA E-Pen 1.0 ROW | C4: RCS DEVICE | D4: Holder | E4: 130020670031776 | F4: BYD | H4: Plastic | I4: 2024 | J4: 7 | K4: 45587 | L4: 1 | M4: 0.33182378 | N4: 0.35401128 | O4: 0.0221875 | P4: 0.0221875 | Q4: 1 | R4: 0.33182378 | S4: 100000 | T4: 100000 | U4: 355000 | V4: 352781.25 | W4: =V4/$AB$1 -> #DIV/0! | Z4: =O4*S4 -> 2218.75
A5: KUMA E-ROW E Pen 1.0 | B5: KUMA E-Pen 1.0 ROW | C5: RCS DEVICE | D5: Button | E5: 130020670033987 | F5: BYD | H5: Plastic | I5: 2024 | J5: 7 | K5: 45602 | L5: 1 | M5: 0.21890549 | N5: 0.22521799 | O5: 0.0063125 | P5: 0.0063125 | Q5: 1 | R5: 0.21890549 | S5: 128340 | T5: 128340 | U5: 103700 | V5: 102889.85 | W5: =V5/$AB$1 -> #DIV/0! | Z5: =O5*S5 -> 810.14625
A6: KUMA E-ROW E Pen 1.0 | B6: KUMA E-Pen 1.0 ROW | C6: RCS DEVICE | D6: Light guide | E6: 130020670035243 | F6: BYD | H6: Plastic | I6: 2024 | J6: 7 | K6: 45587 | L6: 1 | M6: 0.22380863 | N6: 0.22974613 | O6: 0.0059375 | P6: 0.0059375 | Q6: 1 | R6: 0.22380863 | S6: 114000 | T6: 114000 | U6: 95000 | V6: 94323.125 | W6: =V6/$AB$1 -> #DIV/0! | Z6: =O6*S6 -> 676.875
A7: Vuse Go 2.0 8K Box Full | B7: Box 8000 Full 2.0 | C7: MODI | D7: Plastic plug | E7: 130040670043029 | F7: BYD | H7: Plastic | I7: 2024 | J7: 8 | K7: 45587 | L7: 1 | M7: 0.166529 | N7: 0.173779 | O7: 0.00725 | P7: 0.00725 | Q7: 1 | R7: 0.166529 | S7: 203700 | T7: 203700 | U7: 236698 | V7: 235221.17 | W7: =V7/$AB$1 -> #DIV/0! | Z7: =O7*S7 -> 1476.825 | AC7: =SUMPRODUCT(O2:O6044,S2:S6044) -> 1.8854176e+08
A8: KUMA E-ROW E Pen 1.0 | B8: KUMA E-Pen 1.0 ROW | C8: RCS DEVICE | D8: Battery tube | E8: 130040670046310 | F8: BYD | H8: Plastic | I8: 2024 | J8: 8 | K8: 45602 | L8: 1 | M8: 1.8255822 | N8: 1.8908572 | O8: 0.065275 | P8: 0.065275 | Q8: 1 | R8: 1.8255822 | S8: 1172068 | T8: 1294898 | U8: 1566600 | V8: 1482075.5 | W8: =V8/$AB$1 -> #DIV/0! | Z8: =O8*S8 -> 76506.739
A9: KUMA E-ROW E Pen 1.0 | B9: KUMA E-Pen 1.0 ROW | C9: RCS DEVICE | D9: Bottom cap | E9: 130020670034027 | F9: BYD | H9: Plastic | I9: 2024 | J9: 8 | K9: 45602 | L9: 1 | M9: 0.61681485 | N9: 0.67358985 | O9: 0.056775 | P9: 0.056775 | Q9: 1 | R9: 0.61681485 | S9: 1021763 | T9: 1213559 | U9: 1135500 | V9: 1066600.2 | W9: =V9/$AB$1 -> #DIV/0! | Z9: =O9*S9 -> 58010.594
A10: KUMA E-ROW E Pen 1.0 | B10: KUMA E-Pen 1.0 ROW | C10: RCS DEVICE | D10: Holder | E10: 130020670031776 | F10: BYD | H10: Plastic | I10: 2024 | J10: 8 | K10: 45587 | L10: 1 | M10: 0.33182378 | N10: 0.35401128 | O10: 0.0221875 | P10: 0.0221875 | Q10: 1 | R10: 0.33182378 | S10: 700920 | T10: 800920 | U10: 355000 | V10: 337229.59 | W10: =V10/$AB$1 -> #DIV/0! | Z10: =O10*S10 -> 15551.663
A11: KUMA E-ROW E Pen 1.0 | B11: KUMA E-Pen 1.0 ROW | C11: RCS DEVICE | D11: Button | E11: 130020670033987 | F11: BYD | H11: Plastic | I11: 2024 | J11: 8 | K11: 45602 | L11: 1 | M11: 0.21890549 | N11: 0.22521799 | O11: 0.0063125 | P11: 0.0063125 | Q11: 1 | R11: 0.21890549 | S11: 822170 | T11: 950510 | U11: 103700 | V11: 97699.906 | W11: =V11/$AB$1 -> #DIV/0! | Z11: =O11*S11 -> 5189.9481
A12: KUMA E-ROW E Pen 1.0 | B12: KUMA E-Pen 1.0 ROW | C12: RCS DEVICE | D12: Light guide | E12: 130020670035243 | F12: BYD | H12: Plastic | I12: 2024 | J12: 8 | K12: 45587 | L12: 1 | M12: 0.22380863 | N12: 0.22974613 | O12: 0.0059375 | P12: 0.0059375 | Q12: 1 | R12: 0.22380863 | S12: 596466 | T12: 710466 | U12: 95000 | V12: 90781.608 | W12: =V12/$AB$1 -> #DIV/0! | Z12: =O12*S12 -> 3541.5169
A13: KUMA E-ROW E Pen 1.0 | B13: KUMA E-Pen 1.0 ROW | C13: RCS DEVICE | D13: Battery tube | E13: 130040670046310 | F13: BYD | H13: Plastic | I13: 2024 | J13: 9 | K13: 45602 | L13: 1 | M13: 1.8255822 | N13: 1.8908572 | O13: 0.065275 | P13: 0.065275 | Q13: 1 | R13: 1.8255822 | S13: 1112751 | T13: 2407649 | U13: 1566600 | V13: 1409440.7 | W13: =V13/$AB$1 -> #DIV/0! | Z13: =O13*S13 -> 72634.822
A14: KUMA E-ROW E Pen 1.0 | B14: KUMA E-Pen 1.0 ROW | C14: RCS DEVICE | D14: Bottom cap | E14: 130020670034027 | F14: BYD | H14: Plastic | I14: 2024 | J14: 9 | K14: 45602 | L14: 1 | M14: 0.61681485 | N14: 0.67358985 | O14: 0.056775 | P14: 0.056775 | Q14: 1 | R14: 0.61681485 | S14: 1111735 | T14: 2325294 | U14: 1135500 | V14: 1003481.4 | W14: =V14/$AB$1 -> #DIV/0! | Z14: =O14*S14 -> 63118.755
A15: KUMA E-ROW E Pen 1.0 | B15: KUMA E-Pen 1.0 ROW | C15: RCS DEVICE | D15: Holder | E15: 130020670031776 | F15: BYD | H15: Plastic | I15: 2024 | J15: 9 | K15: 45587 | L15: 1 | M15: 0.33182378 | N15: 0.35401128 | O15: 0.0221875 | P15: 0.0221875 | Q15: 1 | R15: 0.33182378 | S15: 405500 | T15: 1206420 | U15: 355000 | V15: 328232.56 | W15: =V15/$AB$1 -> #DIV/0! | Z15: =O15*S15 -> 8997.0312
A16: KUMA E-ROW E Pen 1.0 | B16: KUMA E-Pen 1.0 ROW | C16: RCS DEVICE | D16: Button | E16: 130020670033987 | F16: BYD | H16: Plastic | I16: 2024 | J16: 9 | K16: 45602 | L16: 1 | M16: 0.21890549 | N16: 0.22521799 | O16: 0.0063125 | P16: 0.0063125 | Q16: 1 | R16: 0.21890549 | S16: 742396 | T16: 1692906 | U16: 103700 | V16: 93013.531 | W16: =V16/$AB$1 -> #DIV/0! | Z16: =O16*S16 -> 4686.3747
A17: KUMA E-ROW E Pen 1.0 | B17: KUMA E-Pen 1.0 ROW | C17: RCS DEVICE | D17: Light guide | E17: 130020670035243 | F17: BYD | H17: Plastic | I17: 2024 | J17: 9 | K17: 45587 | L17: 1 | M17: 0.22380863 | N17: 0.22974613 | O17: 0.0059375 | P17: 0.0059375 | Q17: 1 | R17: 0.22380863 | S17: 395900 | T17: 1106366 | U17: 95000 | V17: 88430.952 | W17: =V17/$AB$1 -> #DIV/0! | Z17: =O17*S17 -> 2350.6562
A18: Vuse Go 2.0 8K Box Full | B18: Box 8000 Full 2.0 | C18: MODI | D18: Plastic plug | E18: 130040670043029 | F18: BYD | H18: Plastic | I18: 2024 | J18: 9 | K18: 45587 | L18: 1 | M18: 0.166529 | N18: 0.173779 | O18: 0.00725 | P18: 0.00725 | Q18: 1 | R18: 0.166529 | S18: 152593 | T18: 356293 | U18: 236698 | V18: 234114.88 | W18: =V18/$AB$1 -> #DIV/0! | Z18: =O18*S18 -> 1106.2992
B19: X3 1P | C19: HP | D19: SUSCEPTOR | E19: 22150201001 | F19: BYD | G19: X3 pro 2P/X3 pro 1P/X3 core | H19: Metal | I19: 2023 | J19: 11 | K19: 45600 | L19: 0.6 | M19: 2.62 | N19: 2.69 | O19: 0.07 | P19: 0.042 | Q19: 1 | R19: 2.62 | S19: 268000 | T19: 268000 | U19: 330000 | V19: 308935 | W19: =V19/$AB$1 -> #DIV/0! | Z19: =O19*S19 -> 18760
B20: X3 1P | C20: HP | D20: BOTTOM_COVER | E20: 22150202014 | F20: BYD | G20: X3 pro 2P/X3 pro 1P/X3 core | H20: Plastic | I20: 2023 | J20: 11 | K20: 45600 | L20: 0.6 | M20: 2.01 | N20: 2.08 | O20: 0.07 | P20: 0.042 | Q20: 1 | R20: 2.01 | S20: 134784 | T20: 134784 | U20: 280000 | V20: 271018 | W20: =V20/$AB$1 -> #DIV/0! | Z20: =O20*S20 -> 9434.88
B21: X3 1P | C21: HP | D21: CLEANOUT_DOOR | E21: 22150202015 | F21: BYD | G21: X3 pro 2P/X3 pro 1P/X3 core | H21: Plastic | I21: 2023 | J21: 11 | K21: 45600 | L21: 0.4 | M21: 1.55 | N21: 1.68 | O21: 0.13 | P21: 0.052 | Q21: 1 | R21: 1.55 | S21: 134784 | T21: 134784 | U21: 525000 | V21: 508152 | W21: =V21/$AB$1 -> #DIV/0! | Z21: =O21*S21 -> 17521.92
B22: X3 2P | C22: HP | D22: SHUTTER_DOOR_SUPPORT | E22: 22150202006 | F22: BYD | G22: X3 Pro 2P | H22: Plastic | I22: 2023 | J22: 11 | K22: 45600 | L22: 0.5 | M22: 0.77 | N22: 0.92 | O22: 0.15 | P22: 0.075 | Q22: 1 | R22: 0.77 | S22: 300127 | T22: 300127 | U22: 260000 | V22: 213540 | W22: =V22/$AB$1 -> #DIV/0! | Z22: =O22*S22 -> 45019.05
B23: X3 2P | C23: HP | D23: FRONT_COVER | E23: 22150201009-A- 22150201009-E | F23: BYD | G23: X3 Pro 2P | H23: Metal | I23: 2023 | J23: 11 | K23: 45600 | L23: 1 | M23: 19.22 | N23: 20.02 | O23: 0.8 | P23: 0.8 | Q23: 1 | R23: 19.22 | S23: 224640 | T23: 224640 | U23: 1865000 | V23: 1685288 | W23: =V23/$AB$1 -> #DIV/0! | Z23: =O23*S23 -> 179712
B24: X3 2P | C24: HP | D24: REAR_COVER | E24: 22150201015-A- 22150201015-E | F24: BYD | G24: X3 Pro 2P | H24: Metal | I24: 2023 | J24: 11 | K24: 45600 | L24: 0.6 | M24: 37.81 | N24: 38.85 | O24: 1.04 | P24: 0.624 | Q24: 1 | R24: 37.81 | S24: 196298 | T24: 196298 | U24: 1040000 | V24: 835850 | W24: =V24/$AB$1 -> #DIV/0! | Z24: =O24*S24 -> 204149.92
B25: X3 1P | C25: HP | D25: BATTERY_CARRIER | E25: 22150202011 | F25: BYD | G25: X3 Pro 2P/X3 Pro 1P | H25: Plastic | I25: 2023 | J25: 11 | K25: 45600 | L25: 0 | M25: 0.61 | N25: 0.79 | O25: 0.18 | P25: 0 | Q25: 1 | R25: 0.61 | S25: 78966 | T25: - | U25: 510000 | V25: 510000 | W25: =V25/$AB$1 -> #DIV/0! | Z25: =O25*S25 -> 14213.88
B26: X3 1P | C26: HP | D26: DISPLAY_BRACKET | E26: 22150202021 | F26: BYD | G26: X3 Pro 2P/X3 Pro 1P | H26: Plastic | I26: 2023 | J26: 11 | K26: 45600 | L26: 0.4 | M26: 2.44 | N26: 2.48 | O26: 0.05 | P26: 0.02 | Q26: 1 | R26: 2.44 | S26: 89856 | T26: 89856 | U26: 220000 | V26: 215894 | W26: =V26/$AB$1 -> #DIV/0! | Z26: =O26*S26 -> 4492.8
B27: X3 1P | C27: HP | D27: BOTTOM_SUPPORT | E27: 22150202019 | F27: BYD | G27: X3 Pro 2P/X3 Pro 1P | H27: Plastic | I27: 2023 | J27: 11 | K27: 45600 | L27: 0.5 | M27: 0.65 | N27: 0.85 | O27: 0.2 | P27: 0.1 | Q27: 1 | R27: 0.65 | S27: 183058 | T27: 183058 | U27: 520000 | V27: 483755 | W27: =V27/$AB$1 -> #DIV/0! | Z27: =O27*S27 -> 36611.6
B28: X3 1P | C28: HP | D28: CROWN_SUPPORT | E28: 23590202001 | F28: BYD | G28: X3 Pro 1P/X3 Core | H28: Plastic | I28: 2023 | J28: 11 | K28: 45600 | L28: 0.5 | M28: 0.15 | N28: 0.19 | O28: 0.04 | P28: 0.02 | Q28: 1 | R28: 0.15 | S28: 0 | T28: 0 | U28: 140000 | V28: 140000 | W28: =V28/$AB$1 -> #DIV/0! | Z28: =O28*S28 -> 0
B29: X3 CORE | C29: HP | D29: MAIN_BODY | E29: 23480201007 | F29: BYD | G29: X3 Core | H29: Metal | I29: 2023 | J29: 11 | K29: 45600 | L29: 0.5 | M29: 24.32 | N29: 24.83 | O29: 0.51 | P29: 0.255 | Q29: 1 | R29: 24.32 | S29: 0 | T29: 0 | U29: 1790000 | V29: 1790000 | W29: =V29/$AB$1 -> #DIV/0! | Z29: =O29*S29 -> 0
B30: X3 CORE | C30: HP | D30: SHUTTER_DOOR_SUPP | E30: 23480202005 | F30: BYD | G30: X3 Pro 1P/X3 Core | H30: Plastic | I30: 2023 | J30: 11 | K30: 45600 | L30: 0.4 | M30: 0.72 | N30: 0.91 | O30: 0.19 | P30: 0.076 | Q30: 1 | R30: 0.72 | S30: 0 | T30: 0 | U30: 780000 | V30: 780000 | W30: =V30/$AB$1 -> #DIV/0! | Z30: =O30*S30 -> 0
B31: X3 CORE | C31: HP | D31: BATTERY_CARRIER | E31: 23480202012 | F31: BYD | G31: X3 Core | H31: Plastic | I31: 2023 | J31: 11 | K31: 45600 | L31: 0.6 | M31: 0.72 | N31: 0.8 | O31: 0.08 | P31: 0.048 | Q31: 1 | R31: 0.72 | S31: 0 | T31: 0 | U31: 765000 | V31: 765000 | W31: =V31/$AB$1 -> #DIV/0! | Z31: =O31*S31 -> 0
B32: X3 CORE | C32: HP | D32: CONNECTOR_FRAME | E32: 23480202015 | F32: BYD | G32: X3 Pro 1P/X3 Core | H32: Plastic | I32: 2023 | J32: 11 | K32: 45600 | L32: 0.6 | M32: 0.14 | N32: 0.16 | O32: 0.02 | P32: 0.012 | Q32: 1 | R32: 0.14 | S32: 0 | T32: 0 | U32: 150000 | V32: 150000 | W32: =V32/$AB$1 -> #DIV/0! | Z32: =O32*S32 -> 0
B33: X3 CORE | C33: HP | D33: BUTTON | E33: 23480202017 | F33: BYD | G33: X3 Core | H33: Plastic | I33: 2023 | J33: 11 | K33: 45600 | L33: 0.5 | M33: 1.06 | N33: 1.18 | O33: 0.11 | P33: 0.055 | Q33: 1 | R33: 1.06 | S33: 0 | T33: 0 | U33: 335000 | V33: 335000 | W33: =V33/$AB$1 -> #DIV/0! | Z33: =O33*S33 -> 0
B34: X3 CORE | C34: HP | D34: BUTTON_BRACKET | E34: 23480202011 | F34: BYD | G34: X3 Core | H34: Plastic | I34: 2023 | J34: 11 | K34: 45600 | L34: 0.5 | M34: 0.25 | N34: 0.34 | O34: 0.09 | P34: 0.045 | Q34: 1 | R34: 0.25 | S34: 0 | T34: 0 | U34: 260000 | V34: 260000 | W34: =V34/$AB$1 -> #DIV/0! | Z34: =O34*S34 -> 0
B35: X3 CORE | C35: HP | D35: LIGHT GUIDE | E35: 23480202018 | F35: BYD | G35: X3 Core | H35: Plastic | I35: 2023 | J35: 11 | K35: 45600 | L35: 0.8 | M35: 0.41 | N35: 0.5 | O35: 0.09 | P35: 0.072 | Q35: 1 | R35: 0.41 | S35: 0 | T35: 0 | U35: 310000 | V35: 310000 | W35: =V35/$AB$1 -> #DIV/0! | Z35: =O35*S35 -> 0
B36: X3 1P | C36: HP | D36: MAIN_BODY | E36: 23590201002 | F36: BYD | G36: X3 Pro 1P | H36: Metal | I36: 2023 | J36: 11 | K36: 45600 | L36: 0.5 | M36: 25.4 | N36: 27.3 | O36: 1.9 | P36: 0.95 | Q36: 1 | R36: 25.4 | S36: 0 | T36: 0 | U36: 1330000 | V36: 1330000 | W36: =V36/$AB$1 -> #DIV/0! | Z36: =O36*S36 -> 0
B37: X3 1P | C37: HP | D37: HEATER_UPPER_HOLDER | E37: 22150202001 | F37: BYD | G37: X3 pro 2P/X3 pro 1P/X3 core | H37: Plastic | I37: 2023 | J37: 11 | K37: 45600 | L37: 0.5 | M37: 0.7 | N37: 0.7 | O37: 0 | P37: 0 | Q37: 1 | R37: 0.7 | S37: 346710 | T37: 346710 | U37: ¥- | V37: 0 | W37: =V37/$AB$1 -> #DIV/0! | Z37: =O37*S37 -> 0
B38: X3 1P | C38: HP | D38: DOUBLE_COIL_SUPPORT | E38: 22150202002 | F38: BYD | G38: X3 pro 2P/X3 pro 1P/X3 core | H38: Plastic | I38: 2023 | J38: 11 | K38: 45600 | L38: 0.5 | M38: 1.41 | N38: 1.41 | O38: 0 | P38: 0 | Q38: 1 | R38: 1.41 | S38: 325600 | T38: 325600 | U38: ¥- | V38: 0 | W38: =V38/$AB$1 -> #DIV/0! | Z38: =O38*S38 -> 0
B39: X3 1P | C39: HP | D39: BOT_HOLDER_ASSY | E39: 22150202003-2 | F39: BYD | G39: X3 pro 2P/X3 pro 1P/X3 core | H39: Plastic | I39: 2023 | J39: 11 | K39: 45600 | L39: 0.5 | M39: 2.14 | N39: 2.14 | P39: 0 | Q39: 1 | R39: 2.14 | S39: 241668 | T39: 241668 | U39: ¥- | V39: 0 | W39: =V39/$AB$1 -> #DIV/0! | Z39: =O39*S39 -> 0
B40: X3 1P | C40: HP | D40: EXPANSION_CHAMBER | E40: 22150202004-2 | F40: BYD | G40: X3 pro 2P/X3 pro 1P/X3 core | H40: Plastic | I40: 2023 | J40: 11 | K40: 45600 | L40: 0.5 | M40: 1.5 | N40: 1.5 | P40: 0 | Q40: 1 | R40: 1.5 | S40: 112320 | T40: 112320 | U40: ¥- | V40: 0 | W40: =V40/$AB$1 -> #DIV/0! | Z40: =O40*S40 -> 0
B41: X3 1P | C41: HP | D41: SHUTTER_DOOR | E41: 22150202007 | F41: BYD | G41: X3 pro 2P/X3 pro 1P/X3 core | H41: Plastic | I41: 2023 | J41: 11 | K41: 45600 | L41: 0.5 | M41: 0.13 | N41: 0.13 | P41: 0 | Q41: 1 | R41: 0.13 | S41: 112320 | T41: 112320 | U41: ¥- | V41: 0 | W41: =V41/$AB$1 -> #DIV/0! | Z41: =O41*S41 -> 0
B42: X3 1P | C42: HP | D42: GND_SPRING_USB | E42: 22150201018 | F42: BYD | G42: X3 pro 2P/X3 pro 1P/X3 core | H42: Metal | I42: 2023 | J42: 11 | K42: 45600 | L42: 0.5 | M42: 0.2 | N42: 0.2 | P42: 0 | Q42: 1 | R42: 0.2 | S42: 112320 | T42: 112320 | U42: ¥- | V42: 0 | W42: =V42/$AB$1 -> #DIV/0! | Z42: =O42*S42 -> 0
B43: X3 2P | C43: HP | D43: CROWN_SUPPORT | E43: 22150202008 | F43: BYD | G43: X3 Pro 2P | H43: Plastic | I43: 2023 | J43: 11 | K43: 45600 | L43: 0.5 | M43: 0.17 | N43: 0.17 | P43: 0 | Q43: 1 | R43: 0.17 | S43: 112320 | T43: 112320 | U43: ¥- | V43: 0 | W43: =V43/$AB$1 -> #DIV/0! | Z43: =O43*S43 -> 0
B44: X3 1P | C44: HP | D44: SPIN_WHEEL | E44: 22150202009 | F44: BYD | G44: X3 pro 2P/X3 pro 1P/X3 core | H44: Plastic | I44: 2023 | J44: 11 | K44: 45600 | L44: 0.5 | M44: 0.13 | N44: 0.13 | P44: 0 | Q44: 1 | R44: 0.13 | S44: 112320 | T44: 112320 | U44: ¥- | V44: 0 | W44: =V44/$AB$1 -> #DIV/0! | Z44: =O44*S44 -> 0
B45: X3 1P | C45: HP | D45: PCBA_BRACKET | E45: 22150202018 | F45: BYD | G45: X3 pro 2P/X3 pro 1P/X3 core | H45: Plastic | I45: 2023 | J45: 11 | K45: 45600 | L45: 0.6 | M45: 0.16 | N45: 0.16 | P45: 0 | Q45: 1 | R45: 0.16 | S45: 112320 | T45: 112320 | U45: ¥- | V45: 0 | W45: =V45/$AB$1 -> #DIV/0! | Z45: =O45*S45 -> 0
B46: X3 1P | C46: HP | D46: BOT_THIMBLE | E46: 22150201002 | F46: BYD | G46: X3 pro 2P/X3 pro 1P/X3 core | H46: Metal | I46: 2023 | J46: 11 | K46: 45600 | L46: 0.5 | M46: 0.25 | N46: 0.25 | P46: 0 | Q46: 1 | R46: 0.25 | S46: 112320 | T46: 112320 | U46: ¥- | V46: 0 | W46: =V46/$AB$1 -> #DIV/0! | Z46: =O46*S46 -> 0
B47: X3 1P | C47: HP | D47: TOP_SPIN_PART | E47: 23480201005 | F47: BYD | G47: X3 Pro 1P/X3 Core | H47: Metal | I47: 2023 | J47: 11 | K47: 45600 | L47: 0.5 | M47: 9.31 | N47: 9.31 | P47: 0 | Q47: 1 | R47: 9.31 | S47: 0 | T47: 0 | U47: ¥- | V47: 0 | W47: =V47/$AB$1 -> #DIV/0! | Z47: =O47*S47 -> 0
B48: X3 1P | C48: HP | D48: TOP_COVER_METAL | E48: 23590201001 | F48: BYD | G48: X3 Pro 1P/X3 Core | H48: Metal | I48: 2023 | J48: 11 | K48: 45600 | L48: 0.6 | M48: 7.97 | N48: 7.97 | P48: 0 | Q48: 1 | R48: 7.97 | S48: 0 | T48: 0 | U48: ¥- | V48: 0 | W48: =V48/$AB$1 -> #DIV/0! | Z48: =O48*S48 -> 0
B49: X3 1P | C49: HP | D49: BUTTON | E49: 22150202010 | F49: BYD | G49: X3 Pro 2P/X3 Pro 1P | H49: Plastic | I49: 2023 | J49: 11 | K49: 45600 | L49: 0.6 | M49: 0.79 | N49: 0.79 | P49: 0 | Q49: 1 | R49: 0.79 | S49: 134784 | T49: 134784 | U49: ¥- | V49: 0 | W49: =V49/$AB$1 -> #DIV/0! | Z49: =O49*S49 -> 0
B50: X3 1P | C50: HP | D50: BUTTON_RUBBER | E50: 22150203002 | F50: BYD | G50: X3 Pro 2P/X3 Pro 1P | H50: Plastic | I50: 2023 | J50: 11 | K50: 45600 | L50: 0.6 | M50: 0.12 | N50: 0.12 | P50: 0 | Q50: 1 | R50: 0.12 | S50: 171200 | T50: 171200 | U50: ¥- | V50: 0 | W50: =V50/$AB$1 -> #DIV/0! | Z50: =O50*S50 -> 0
... B54: X3 2P | C54: HP | D54: TOP_SPIN_PART | E54: 22150201006-A- 22150201006-E | F54: BYD | G54: X3 Pro 2P | H54: Metal | I54: 2023 | J54: 11 | K54: 45600 | L54: 0.6 | M54: 10.7 | N54: 10.7 | P54: 0 | Q54: 1 | R54: 10.7 | S54: 134784 | T54: 134784 | U54: ¥- | V54: 0 | W54: =V54/$AB$1 -> #DIV/0! | Z54: =O54*S54 -> 0
B55: X3 1P | C55: HP | D55: SUSCEPTOR | E55: 22150201001 | F55: BYD | G55: X3 pro 2P/X3 pro 1P/X3 core | H55: Metal | I55: 2023 | J55: 12 | K55: 45600 | L55: 0.6 | M55: 2.62 | N55: 2.69 | O55: 0.08 | P55: 0.048 | Q55: 1 | R55: 2.62 | S55: 244800 | T55: 512800 | U55: 330000 | V55: 289694 | W55: =V55/$AB$1 -> #DIV/0! | Z55: =O55*S55 -> 19584
B56: X3 1P | C56: HP | D56: BOTTOM_COVER | E56: 22150202014 | F56: BYD | G56: X3 pro 2P/X3 pro 1P/X3 core | H56: Plastic | I56: 2023 | J56: 12 | K56: 45600 | L56: 0.6 | M56: 2.01 | N56: 2.08 | O56: 0.07 | P56: 0.042 | Q56: 1 | R56: 2.01 | S56: 162432 | T56: 297216 | U56: 280000 | V56: 260194 | W56: =V56/$AB$1 -> #DIV/0! | Z56: =O56*S56 -> 11370.24
B57: X3 1P | C57: HP | D57: CLEANOUT_DOOR | E57: 22150202015 | F57: BYD | G57: X3 pro 2P/X3 pro 1P/X3 core | H57: Plastic | I57: 2023 | J57: 12 | K57: 45600 | L57: 0.4 | M57: 1.55 | N57: 1.68 | O57: 0.13 | P57: 0.052 | Q57: 1 | R57: 1.55 | S57: 162432 | T57: 297216 | U57: 525000 | V57: 487848 | W57: =V57/$AB$1 -> #DIV/0! | Z57: =O57*S57 -> 21116.16
B58: X3 2P | C58: HP | D58: SHUTTER_DOOR_SUPPORT | E58: 22150202006 | F58: BYD | G58: X3 Pro 2P | H58: Plastic | I58: 2023 | J58: 12 | K58: 45600 | L58: 0.5 | M58: 0.77 | N58: 0.92 | O58: 0.15 | P58: 0.075 | Q58: 1 | R58: 0.77 | S58: 103870 | T58: 403997 | U58: 260000 | V58: 197461 | W58: =V58/$AB$1 -> #DIV/0! | Z58: =O58*S58 -> 15580.5
B59: X3 2P | C59: HP | D59: FRONT_COVER | E59: 22150201009-A- 22150201009-E | F59: BYD | G59: X3 Pro 2P | H59: Metal | I59: 2023 | J59: 12 | K59: 45600 | L59: 1 | M59: 19.22 | N59: 20.02 | O59: 0.8 | P59: 0.8 | Q59: 1 | R59: 19.22 | S59: 270720 | T59: 495360 | U59: 1865000 | V59: 1468712 | W59: =V59/$AB$1 -> #DIV/0! | Z59: =O59*S59 -> 216576
B60: X3 2P | C60: HP | D60: REAR_COVER | E60: 22150201015-A- 22150201015-E | F60: BYD | G60: X3 Pro 2P | H60: Metal | I60: 2023 | J60: 12 | K60: 45600 | L60: 0.6 | M60: 37.81 | N60: 38.85 | O60: 1.04 | P60: 0.624 | Q60: 1 | R60: 37.81 | S60: 142850 | T60: 339148 | U60: 1040000 | V60: 687286 | W60: =V60/$AB$1 -> #DIV/0! | Z60: =O60*S60 -> 148564
B61: X3 1P | C61: HP | D61: BATTERY_CARRIER | E61: 22150202011 | F61: BYD | G61: X3 Pro 2P/X3 Pro 1P | H61: Plastic | I61: 2023 | J61: 12 | K61: 45600 | L61: 0 | M61: 0.61 | N61: 0.79 | O61: 0.18 | P61: 0 | Q61: 1 | R61: 0.61 | S61: 78966 | T61: - | U61: 510000 | V61: 510000 | W61: =V61/$AB$1 -> #DIV/0! | Z61: =O61*S61 -> 14213.88
B62: X3 1P | C62: HP | D62: DISPLAY_BRACKET | E62: 22150202021 | F62: BYD | G62: X3 Pro 2P/X3 Pro 1P | H62: Plastic | I62: 2023 | J62: 12 | K62: 45600 | L62: 0.4 | M62: 2.44 | N62: 2.48 | O62: 0.05 | P62: 0.02 | Q62: 1 | R62: 2.44 | S62: 108288 | T62: 198144 | U62: 220000 | V62: 210945 | W62: =V62/$AB$1 -> #DIV/0! | Z62: =O62*S62 -> 5414.4
B63: X3 1P | C63: HP | D63: BOTTOM_SUPPORT | E63: 22150202019 | F63: BYD | G63: X3 Pro 2P/X3 Pro 1P | H63: Plastic | I63: 2023 | J63: 12 | K63: 45600 | L63: 0.5 | M63: 0.65 | N63: 0.85 | O63: 0.2 | P63: 0.1 | Q63: 1 | R63: 0.65 | S63: 203040 | T63: 386098 | U63: 520000 | V63: 443553 | W63: =V63/$AB$1 -> #DIV/0! | Z63: =O63*S63 -> 40608
B64: X3 1P | C64: HP | D64: CROWN_SUPPORT | E64: 23590202001 | F64: BYD | G64: X3 Pro 1P/X3 Core | H64: Plastic | I64: 2023 | J64: 12 | K64: 45600 | L64: 0.5 | M64: 0.15 | N64: 0.19 | O64: 0.04 | P64: 0.02 | Q64: 1 | R64: 0.15 | S64: 0 | T64: 0 | U64: 140000 | V64: 140000 | W64: =V64/$AB$1 -> #DIV/0! | Z64: =O64*S64 -> 0
B65: X3 CORE | C65: HP | D65: MAIN_BODY | E65: 23480201007 | F65: BYD | G65: X3 Core | H65: Metal | I65: 2023 | J65: 12 | K65: 45600 | L65: 0.5 | M65: 24.32 | N65: 24.83 | O65: 0.51 | P65: 0.255 | Q65: 1 | R65: 24.32 | S65: 0 | T65: 0 | U65: 1790000 | V65: 1790000 | W65: =V65/$AB$1 -> #DIV/0! | Z65: =O65*S65 -> 0
B66: X3 CORE | C66: HP | D66: SHUTTER_DOOR_SUPP | E66: 23480202005 | F66: BYD | G66: X3 Pro 1P/X3 Core | H66: Plastic | I66: 2023 | J66: 12 | K66: 45600 | L66: 0.4 | M66: 0.72 | N66: 0.91 | O66: 0.19 | P66: 0.076 | Q66: 1 | R66: 0.72 | S66: 0 | T66: 0 | U66: 780000 | V66: 780000 | W66: =V66/$AB$1 -> #DIV/0! | Z66: =O66*S66 -> 0
B67: X3 CORE | C67: HP | D67: BATTERY_CARRIER | E67: 23480202012 | F67: BYD | G67: X3 Core | H67: Plastic | I67: 2023 | J67: 12 | K67: 45600 | L67: 0.6 | M67: 0.72 | N67: 0.8 | O67: 0.08 | P67: 0.048 | Q67: 1 | R67: 0.72 | S67: 0 | T67: 0 | U67: 765000 | V67: 765000 | W67: =V67/$AB$1 -> #DIV/0! | Z67: =O67*S67 -> 0
B68: X3 CORE | C68: HP | D68: CONNECTOR_FRAME | E68: 23480202015 | F68: BYD | G68: X3 Pro 1P/X3 Core | H68: Plastic | I68: 2023 | J68: 12 | K68: 45600 | L68: 0.6 | M68: 0.14 | N68: 0.16 | O68: 0.02 | P68: 0.012 | Q68: 1 | R68: 0.14 | S68: 0 | T68: 0 | U68: 150000 | V68: 150000 | W68: =V68/$AB$1 -> #DIV/0! | Z68: =O68*S68 -> 0
B69: X3 CORE | C69: HP | D69: BUTTON | E69: 23480202017 | F69: BYD | G69: X3 Core | H69: Plastic | I69: 2023 | J69: 12 | K69: 45600 | L69: 0.5 | M69: 1.06 | N69: 1.18 | O69: 0.11 | P69: 0.055 | Q69: 1 | R69: 1.06 | S69: 0 | T69: 0 | U69: 335000 | V69: 335000 | W69: =V69/$AB$1 -> #DIV/0! | Z69: =O69*S69 -> 0
B70: X3 CORE | C70: HP | D70: BUTTON_BRACKET | E70: 23480202011 | F70: BYD | G70: X3 Core | H70: Plastic | I70: 2023 | J70: 12 | K70: 45600 | L70: 0.5 | M70: 0.25 | N70: 0.34 | O70: 0.09 | P70: 0.045 | Q70: 1 | R70: 0.25 | S70: 0 | T70: 0 | U70: 260000 | V70: 260000 | W70: =V70/$AB$1 -> #DIV/0! | Z70: =O70*S70 -> 0
B71: X3 CORE | C71: HP | D71: LIGHT GUIDE | E71: 23480202018 | F71: BYD | G71: X3 Core | H71: Plastic | I71: 2023 | J71: 12 | K71: 45600 | L71: 0.8 | M71: 0.41 | N71: 0.5 | O71: 0.09 | P71: 0.072 | Q71: 1 | R71: 0.41 | S71: 0 | T71: 0 | U71: 310000 | V71: 310000 | W71: =V71/$AB$1 -> #DIV/0! | Z71: =O71*S71 -> 0
B72: X3 1P | C72: HP | D72: MAIN_BODY | E72: 23590201002 | F72: BYD | G72: X3 Pro 1P | H72: Metal | I72: 2023 | J72: 12 | K72: 45600 | L72: 0.5 | M72: 25.4 | N72: 27.3 | O72: 1.9 | P72: 0.95 | Q72: 1 | R72: 25.4 | S72: 0 | T72: 0 | U72: 1330000 | V72: 1330000 | W72: =V72/$AB$1 -> #DIV/0! | Z72: =O72*S72 -> 0
B73: X3 1P | C73: HP | D73: HEATER_UPPER_HOLDER | E73: 22150202001 | F73: BYD | G73: X3 pro 2P/X3 pro 1P/X3 core | H73: Plastic | I73: 2023 | J73: 12 | K73: 45600 | L73: 0.5 | M73: 0.7 | N73: 0.7 | P73: 0 | Q73: 1 | R73: 0.7 | S73: 145790 | T73: 492500 | U73: ¥- | V73: 0 | W73: =V73/$AB$1 -> #DIV/0! | Z73: =O73*S73 -> 0
B74: X3 1P | C74: HP | D74: DOUBLE_COIL_SUPPORT | E74: 22150202002 | F74: BYD | G74: X3 pro 2P/X3 pro 1P/X3 core | H74: Plastic | I74: 2023 | J74: 12 | K74: 45600 | L74: 0.5 | M74: 1.41 | N74: 1.41 | P74: 0 | Q74: 1 | R74: 1.41 | S74: 204000 | T74: 529600 | U74: ¥- | V74: 0 | W74: =V74/$AB$1 -> #DIV/0! | Z74: =O74*S74 -> 0
B75: X3 1P | C75: HP | D75: BOT_HOLDER_ASSY | E75: 22150202003-2 | F75: BYD | G75: X3 pro 2P/X3 pro 1P/X3 core | H75: Plastic | I75: 2023 | J75: 12 | K75: 45600 | L75: 0.5 | M75: 2.14 | N75: 2.14 | P75: 0 | Q75: 1 | R75: 2.14 | S75: 325957 | T75: 567625 | U75: ¥- | V75: 0 | W75: =V75/$AB$1 -> #DIV/0! | Z75: =O75*S75 -> 0
B76: X3 1P | C76: HP | D76: EXPANSION_CHAMBER | E76: 22150202004-2 | F76: BYD | G76: X3 pro 2P/X3 pro 1P/X3 core | H76: Plastic | I76: 2023 | J76: 12 | K76: 45600 | L76: 0.5 | M76: 1.5 | N76: 1.5 | P76: 0 | Q76: 1 | R76: 1.5 | S76: 135360 | T76: 247680 | U76: ¥- | V76: 0 | W76: =V76/$AB$1 -> #DIV/0! | Z76: =O76*S76 -> 0
B77: X3 1P | C77: HP | D77: SHUTTER_DOOR | E77: 22150202007 | F77: BYD | G77: X3 pro 2P/X3 pro 1P/X3 core | H77: Plastic | I77: 2023 | J77: 12 | K77: 45600 | L77: 0.5 | M77: 0.13 | N77: 0.13 | P77: 0 | Q77: 1 | R77: 0.13 | S77: 135360 | T77: 247680 | U77: ¥- | V77: 0 | W77: =V77/$AB$1 -> #DIV/0! | Z77: =O77*S77 -> 0
B78: X3 1P | C78: HP | D78: GND_SPRING_USB | E78: 22150201018 | F78: BYD | G78: X3 pro 2P/X3 pro 1P/X3 core | H78: Metal | I78: 2023 | J78: 12 | K78: 45600 | L78: 0.5 | M78: 0.2 | N78: 0.2 | P78: 0 | Q78: 1 | R78: 0.2 | S78: 135360 | T78: 247680 | U78: ¥- | V78: 0 | W78: =V78/$AB$1 -> #DIV/0! | Z78: =O78*S78 -> 0
B79: X3 2P | C79: HP | D79: CROWN_SUPPORT | E79: 22150202008 | F79: BYD | G79: X3 Pro 2P | H79: Plastic | I79: 2023 | J79: 12 | K79: 45600 | L79: 0.5 | M79: 0.17 | N79: 0.17 | P79: 0 | Q79: 1 | R79: 0.17 | S79: 135360 | T79: 247680 | U79: ¥- | V79: 0 | W79: =V79/$AB$1 -> #DIV/0! | Z79: =O79*S79 -> 0
B80: X3 1P | C80: HP | D80: SPIN_WHEEL | E80: 22150202009 | F80: BYD | G80: X3 pro 2P/X3 pro 1P/X3 core | H80: Plastic | I80: 2023 | J80: 12 | K80: 45600 | L80: 0.5 | M80: 0.13 | N80: 0.13 | P80: 0 | Q80: 1 | R80: 0.13 | S80: 135360 | T80: 247680 | U80: ¥- | V80: 0 | W80: =V80/$AB$1 -> #DIV/0! | Z80: =O80*S80 -> 0
B81: X3 1P | C81: HP | D81: PCBA_BRACKET | E81: 22150202018 | F81: BYD | G81: X3 pro 2P/X3 pro 1P/X3 core | H81: Plastic | I81: 2023 | J81: 12 | K81: 45600 | L81: 0.6 | M81: 0.16 | N81: 0.16 | P81: 0 | Q81: 1 | R81: 0.16 | S81: 135360 | T81: 247680 | U81: ¥- | V81: 0 | W81: =V81/$AB$1 -> #DIV/0! | Z81: =O81*S81 -> 0
B82: X3 1P | C82: HP | D82: BOT_THIMBLE | E82: 22150201002 | F82: BYD | G82: X3 pro 2P/X3 pro 1P/X3 core | H82: Metal | I82: 2023 | J82: 12 | K82: 45600 | L82: 0.5 | M82: 0.25 | N82: 0.25 | P82: 0 | Q82: 1 | R82: 0.25 | S82: 135360 | T82: 247680 | U82: ¥- | V82: 0 | W82: =V82/$AB$1 -> #DIV/0! | Z82: =O82*S82 -> 0
B83: X3 1P | C83: HP | D83: TOP_SPIN_PART | E83: 23480201005 | F83: BYD | G83: X3 Pro 1P/X3 Core | H83: Metal | I83: 2023 | J83: 12 | K83: 45600 | L83: 0.5 | M83: 9.31 | N83: 9.31 | P83: 0 | Q83: 1 | R83: 9.31 | S83: 0 | T83: 0 | U83: ¥- | V83: 0 | W83: =V83/$AB$1 -> #DIV/0! | Z83: =O83*S83 -> 0
B84: X3 1P | C84: HP | D84: TOP_COVER_METAL | E84: 23590201001 | F84: BYD | G84: X3 Pro 1P/X3 Core | H84: Metal | I84: 2023 | J84: 12 | K84: 45600 | L84: 0.6 | M84: 7.97 | N84: 7.97 | P84: 0 | Q84: 1 | R84: 7.97 | S84: 0 | T84: 0 | U84: ¥- | V84: 0 | W84: =V84/$AB$1 -> #DIV/0! | Z84: =O84*S84 -> 0
... B90: X3 2P | C90: HP | D90: TOP_SPIN_PART | E90: 22150201006-A- 22150201006-E | F90: BYD | G90: X3 Pro 2P | H90: Metal | I90: 2023 | J90: 12 | K90: 45600 | L90: 0.6 | M90: 10.7 | N90: 10.7 | P90: 0 | Q90: 1 | R90: 10.7 | S90: 162432 | T90: 297216 | U90: ¥- | V90: 0 | W90: =V90/$AB$1 -> #DIV/0! | Z90: =O90*S90 -> 0
B91: X3 1P | C91: HP | D91: SUSCEPTOR | E91: 22150201001 | F91: BYD | G91: X3 pro 2P/X3 pro 1P/X3 core | H91: Metal | I91: 2024 | J91: 1 | K91: 45600 | L91: 0.6 | M91: 2.62 | N91: 2.69 | O91: 0.08 | P91: 0.048 | Q91: 1 | R91: 2.62 | S91: 402400 | T91: 915200 | U91: 330000 | V91: 258065 | W91: =V91/$AB$1 -> #DIV/0! | Z91: =O91*S91 -> 32192
B92: X3 1P | C92: HP | D92: BOTTOM_COVER | E92: 22150202014 | F92: BYD | G92: X3 pro 2P/X3 pro 1P/X3 core | H92: Plastic | I92: 2024 | J92: 1 | K92: 45600 | L92: 0.6 | M92: 2.01 | N92: 2.08 | O92: 0.07 | P92: 0.042 | Q92: 1 | R92: 2.01 | S92: 263040 | T92: 560256 | U92: 280000 | V92: 242665 | W92: =V92/$AB$1 -> #DIV/0! | Z92: =O92*S92 -> 18412.8
B93: X3 1P | C93: HP | D93: CLEANOUT_DOOR | E93: 22150202015 | F93: BYD | G93: X3 pro 2P/X3 pro 1P/X3 core | H93: Plastic | I93: 2024 | J93: 1 | K93: 45600 | L93: 0.4 | M93: 1.55 | N93: 1.68 | O93: 0.13 | P93: 0.052 | Q93: 1 | R93: 1.55 | S93: 263040 | T93: 560256 | U93: 525000 | V93: 454968 | W93: =V93/$AB$1 -> #DIV/0! | Z93: =O93*S93 -> 34195.2
B94: X3 2P | C94: HP | D94: SHUTTER_DOOR_SUPPORT | E94: 22150202006 | F94: BYD | G94: X3 Pro 2P | H94: Plastic | I94: 2024 | J94: 1 | K94: 45600 | L94: 0.5 | M94: 0.77 | N94: 0.92 | O94: 0.15 | P94: 0.075 | Q94: 1 | R94: 0.77 | S94: 189050 | T94: 593047 | U94: 260000 | V94: 168196 | W94: =V94/$AB$1 -> #DIV/0! | Z94: =O94*S94 -> 28357.5
B95: X3 2P | C95: HP | D95: FRONT_COVER | E95: 22150201009-A- 22150201009-E | F95: BYD | G95: X3 Pro 2P | H95: Metal | I95: 2024 | J95: 1 | K95: 45600 | L95: 1 | M95: 19.22 | N95: 20.02 | O95: 0.8 | P95: 0.8 | Q95: 1 | R95: 19.22 | S95: 438400 | T95: 933760 | U95: 1865000 | V95: 1117992 | W95: =V95/$AB$1 -> #DIV/0! | Z95: =O95*S95 -> 350720
B96: X3 2P | C96: HP | D96: REAR_COVER | E96: 22150201015-A- 22150201015-E | F96: BYD | G96: X3 Pro 2P | H96: Metal | I96: 2024 | J96: 1 | K96: 45600 | L96: 0.6 | M96: 37.81 | N96: 38.85 | O96: 1.04 | P96: 0.624 | Q96: 1 | R96: 37.81 | S96: 230520 | T96: 569668 | U96: 1040000 | V96: 447545 | W96: =V96/$AB$1 -> #DIV/0! | Z96: =O96*S96 -> 239740.8
B97: X3 1P | C97: HP | D97: BATTERY_CARRIER | E97: 22150202011 | F97: BYD | G97: X3 Pro 2P/X3 Pro 1P | H97: Plastic | I97: 2024 | J97: 1 | K97: 45600 | L97: 0 | M97: 0.61 | N97: 0.79 | O97: 0.18 | P97: 0 | Q97: 1 | R97: 0.61 | S97: 78966 | T97: 78966 | U97: 510000 | V97: 495786 | W97: =V97/$AB$1 -> #DIV/0! | Z97: =O97*S97 -> 14213.88
B98: X3 1P | C98: HP | D98: DISPLAY_BRACKET | E98: 22150202021 | F98: BYD | G98: X3 Pro 2P/X3 Pro 1P | H98: Plastic | I98: 2024 | J98: 1 | K98: 45600 | L98: 0.4 | M98: 2.44 | N98: 2.48 | O98: 0.05 | P98: 0.02 | Q98: 1 | R98: 2.44 | S98: 175360 | T98: 373504 | U98: 220000 | V98: 202931 | W98: =V98/$AB$1 -> #DIV/0! | Z98: =O98*S98 -> 8768
B99: X3 1P | C99: HP | D99: BOTTOM_SUPPORT | E99: 22150202019 | F99: BYD | G99: X3 Pro 2P/X3 Pro 1P | H99: Plastic | I99: 2024 | J99: 1 | K99: 45600 | L99: 0.5 | M99: 0.65 | N99: 0.85 | O99: 0.2 | P99: 0.1 | Q99: 1 | R99: 0.65 | S99: 205762 | T99: 591860 | U99: 520000 | V99: 402812 | W99: =V99/$AB$1 -> #DIV/0! | Z99: =O99*S99 -> 41152.4
B100: X3 1P | C100: HP | D100: CROWN_SUPPORT | E100: 23590202001 | F100: BYD | G100: X3 Pro 1P/X3 Core | H100: Plastic | I100: 2024 | J100: 1 | K100: 45600 | L100: 0.5 | M100: 0.15 | N100: 0.19 | O100: 0.04 | P100: 0.02 | Q100: 1 | R100: 0.15 | S100: 0 | T100: 0 | U100: 140000 | V100: 140000 | W100: =V100/$AB$1 -> #DIV/0! | Z100: =O100*S100 -> 0
B101: X3 CORE | C101: HP | D101: MAIN_BODY | E101: 23480201007 | F101: BYD | G101: X3 Core | H101: Metal | I101: 2024 | J101: 1 | K101: 45600 | L101: 0.5 | M101: 24.32 | N101: 24.83 | O101: 0.51 | P101: 0.255 | Q101: 1 | R101: 24.32 | S101: 0 | T101: 0 | U101: 1790000 | V101: 1790000 | W101: =V101/$AB$1 -> #DIV/0! | Z101: =O101*S101 -> 0
B102: X3 CORE | C102: HP | D102: SHUTTER_DOOR_SUPP | E102: 23480202005 | F102: BYD | G102: X3 Pro 1P/X3 Core | H102: Plastic | I102: 2024 | J102: 1 | K102: 45600 | L102: 0.4 | M102: 0.72 | N102: 0.91 | O102: 0.19 | P102: 0.076 | Q102: 1 | R102: 0.72 | S102: 0 | T102: 0 | U102: 780000 | V102: 780000 | W102: =V102/$AB$1 -> #DIV/0! | Z102: =O102*S102 -> 0
... B108: X3 1P | C108: HP | D108: MAIN_BODY | E108: 23590201002 | F108: BYD | G108: X3 Pro 1P | H108: Metal | I108: 2024 | J108: 1 | K108: 45600 | L108: 0.5 | M108: 25.4 | N108: 27.3 | O108: 1.9 | P108: 0.95 | Q108: 1 | R108: 25.4 | S108: 64361 | T108: 64361 | U108: 1330000 | V108: 1207714 | W108: =V108/$AB$1 -> #DIV/0! | Z108: =O108*S108 -> 122285.9
B109: X3 1P | C109: HP | D109: HEATER_UPPER_HOLDER | E109: 22150202001 | F109: BYD | G109: X3 pro 2P/X3 pro 1P/X3 core | H109: Plastic | I109: 2024 | J109: 1 | K109: 45600 | L109: 0.5 | M109: 0.7 | N109: 0.7 | P109: 0 | Q109: 1 | R109: 0.7 | S109: 604384 | T109: 1096884 | U109: ¥- | V109: 0 | W109: =V109/$AB$1 -> #DIV/0! | Z109: =O109*S109 -> 0
B110: X3 1P | C110: HP | D110: DOUBLE_COIL_SUPPORT | E110: 22150202002 | F110: BYD | G110: X3 pro 2P/X3 pro 1P/X3 core | H110: Plastic | I110: 2024 | J110: 1 | K110: 45600 | L110: 0.5 | M110: 1.41 | N110: 1.41 | P110: 0 | Q110: 1 | R110: 1.41 | S110: 389800 | T110: 919400 | U110: ¥- | V110: 0 | W110: =V110/$AB$1 -> #DIV/0! | Z110: =O110*S110 -> 0
B111: X3 1P | C111: HP | D111: BOT_HOLDER_ASSY | E111: 22150202003-2 | F111: BYD | G111: X3 pro 2P/X3 pro 1P/X3 core | H111: Plastic | I111: 2024 | J111: 1 | K111: 45600 | L111: 0.5 | M111: 2.14 | N111: 2.14 | P111: 0 | Q111: 1 | R111: 2.14 | S111: 401837 | T111: 969462 | U111: ¥- | V111: 0 | W111: =V111/$AB$1 -> #DIV/0! | Z111: =O111*S111 -> 0
B112: X3 1P | C112: HP | D112: EXPANSION_CHAMBER | E112: 22150202004-2 | F112: BYD | G112: X3 pro 2P/X3 pro 1P/X3 core | H112: Plastic | I112: 2024 | J112: 1 | K112: 45600 | L112: 0.5 | M112: 1.5 | N112: 1.5 | P112: 0 | Q112: 1 | R112: 1.5 | S112: 219200 | T112: 466880 | U112: ¥- | V112: 0 | W112: =V112/$AB$1 -> #DIV/0! | Z112: =O112*S112 -> 0
B113: X3 1P | C113: HP | D113: SHUTTER_DOOR | E113: 22150202007 | F113: BYD | G113: X3 pro 2P/X3 pro 1P/X3 core | H113: Plastic | I113: 2024 | J113: 1 | K113: 45600 | L113: 0.5 | M113: 0.13 | N113: 0.13 | P113: 0 | Q113: 1 | R113: 0.13 | S113: 219200 | T113: 466880 | U113: ¥- | V113: 0 | W113: =V113/$AB$1 -> #DIV/0! | Z113: =O113*S113 -> 0
...
