Workbook
Name \A: #REF!
Name \A: #REF!
Name \A: #REF!
Name \C: #REF!
Name \C: #REF!
Name \C: #REF!
Name \D: #REF!
Name \D: #REF!
Name \D: #REF!
Name \W: #REF!
Name \W: #REF!
Name \W: #REF!
Name _: #REF!
Name _: #REF!
Name _: #REF!
Name __: #REF!
Name __: #REF!
Name __: #REF!
Name ___: #REF!
Name ___: #REF!
Name ___: #REF!
Name ______0: #REF!
Name ______0: #REF!
Name ______0: #REF!
Name ______0___0: #REF!
Name ______0___0: #REF!
Name ______0___0: #REF!
Name ______4: "$"
Name ______5: "$"
Name ______6: "$"
Name __m72: {"傳各位表單.xls","Sheet1"}
Name __m72: {"傳各位表單.xls","Sheet1"}
Name __m72: {"傳各位表單.xls","Sheet1"}
Name __m72_1: {"傳各位表單.xls","Sheet1"}
Name __m72_1: {"傳各位表單.xls","Sheet1"}
Name __m72_1: {"傳各位表單.xls","Sheet1"}
Name __m72_2: {"傳各位表單.xls","Sheet1"}
Name __m72_2: {"傳各位表單.xls","Sheet1"}
Name __m72_2: {"傳各位表單.xls","Sheet1"}
Name __m72_3: {"傳各位表單.xls","Sheet1"}
Name __m72_3: {"傳各位表單.xls","Sheet1"}
Name __m72_3: {"傳各位表單.xls","Sheet1"}
Name __m72_4: {"傳各位表單.xls","Sheet1"}
Name __m72_4: {"傳各位表單.xls","Sheet1"}
Name __m72_4: {"傳各位表單.xls","Sheet1"}
Name _017: #REF!
Name _017: #REF!
Name _017: #REF!
Name _024: #REF!
Name _024: #REF!
Name _024: #REF!
Name _039: #REF!
Name _039: #REF!
Name _039: #REF!
Name _1.: #REF!
Name _1.: #REF!
Name _1.: #REF!
Name _1_0: #REF!
Name _1_0: #REF!
Name _1_0: #REF!

Sheet Capex
S1: CNY | T1: GBP
C2: Investment/Liabilities Dashboard | S2: =34746341 -> 34746341 | T2: =S2/8.812 -> 3943070.9
C3: New Categories - Vapour | S3: 24216741 | T3: =S3/8.812 -> 2748154.9
T4: =SUM(T2:T3) -> 6691225.8
A5: USD-GBP | B5: 1.27818
A6: RMB-GBP | B6: 9.19774 | C6: 0.025813404
B7: Prpcurement/Finance
A9: # | B9: Unique Ref Number | C9: Project | D9: Project Description | E9: SC Owner | F9: Procurement Owner | G9: Portfolio | H9: Platform | I9: Location | J9: Type | K9: Portfolio1 | L9: Tier | M9: Supplier | N9: Contracting Entity | O9: Start Date | P9: End Date | Q9: Investment Quotation | R9: Investment Currency | S9: Investment (GBP) | T9: Committed PO Volume | U9: Amortization per Unit | V9: Amortization per Unit (GBP)
A10: 1 | B10: RF001_Alto &ePod | C10: Alto & ePod | D10: APA - Automation Production Agreement | E10: Angie Huang | F10: Reggie Zhu | G10: Pod | H10: Pod | I10: Indo | J10: Pod Automation (initial Investment) | K10: RCS | L10: T1 | M10: Smoore T1 | N10: Reynolds | O10: 44197 | P10: 46722 | Q10: 72000000 | R10: USD | S10: =IF(R10="RMB",Q10/$B$6,IF(R10="GBP",Q10,Q10/$B$5)) -> 56330094 | T10: 2570000000 | U10: Volume
A11: 2 | B11: RF002_Alto | C11: Alto | D11: Addendum No.10 - Indonesia | E11: Angie Huang | F11: Reggie Zhu | G11: Pod | H11: Pod | I11: Indo | J11: Indo Facility | K11: RCS | L11: T1 | M11: Smoore T1 | N11: Reynolds | O11: 44682 | P11: 46722 | Q11: 41140309 | R11: USD | S11: =IF(R11="RMB",Q11/$B$6,IF(R11="GBP",Q11,Q11/$B$5)) -> 32186632 | T11: 2340000000 | U11: 0.0152 | V11: =IF(R11="RMB",U11/$B$6,IF(R11="GBP",U11,U11/$B$5)) -> 0.011891909
A12: 4 | B12: RF003_Alto | C12: Alto | D12: Alto Pod Investment fee for Inkjet printing | E12: Angie Huang | F12: Reggie Zhu | G12: Pod | H12: Pod | I12: Indo | J12: Asset - Others | K12: RCS | L12: T1 | M12: Smoore T1 | N12: Reynolds | O12: 45344 | P12: - | Q12: 2020422.1 | R12: USD | S12: =IF(R12="RMB",Q12/$B$6,IF(R12="GBP",Q12,Q12/$B$5)) -> 1580702.4 | T12: 0 | U12: n/a
A13: 5 | B13: RF004_Alto | C13: Alto | D13: Device to Indo Equipment move cost | E13: Angie Huang | F13: Reggie Zhu | G13: RCS | H13: Vuse Device( US Alto) | I13: Indo | J13: Asset - RCS Device line | K13: RCS | L13: T1 | M13: Smoore T1 | N13: Reynolds | O13: 45345 | P13: 46722 | Q13: 650000 | R13: USD | S13: =IF(R13="RMB",Q13/$B$6,IF(R13="GBP",Q13,Q13/$B$5)) -> 508535.57 | T13: 20000000 | U13: 0.032288552 | V13: =IF(R13="RMB",U13/$B$6,IF(R13="GBP",U13,U13/$B$5)) -> 0.02526135
A14: 6 | B14: RF005_Alto | C14: Alto | D14: Alto Blister Reduction Capex | E14: Angie Huang | F14: Reggie Zhu | G14: Pod | H14: Pod | I14: Indo | J14: Asset - Others | K14: RCS | L14: T1 | M14: Smoore T1 | N14: Reynolds | O14: 45597 | P14: 46722 | Q14: 886091.64 | R14: USD | S14: =IF(R14="RMB",Q14/$B$6,IF(R14="GBP",Q14,Q14/$B$5)) -> 693244.8 | T14: 400000000 | U14: =Q14/T14 -> 0.0022152291 | V14: =IF(R14="RMB",U14/$B$6,IF(R14="GBP",U14,U14/$B$5)) -> 0.001733112
A15: 7 | B15: RF006_Alto | C15: Prismatic Pod | D15: Prismastic China project capex | E15: Angie Huang | F15: Reggie Zhu | G15: Pod | H15: Pod | I15: Indo | J15: Asset - Others | K15: RCS | L15: T1 | M15: Smoore T1 | N15: Reynolds | O15: - | P15: - | Q15: 1562511 | R15: RMB | S15: =IF(R15="RMB",Q15/$B$6,IF(R15="GBP",Q15,Q15/$B$5)) -> 169879.88 | U15: Volume
A16: 8 | B16: RF007_Epod&Modi | C16: Epod&Modi | D16: Tax Stamp(Pod2+ePod3 Czech,Germany,Poland&Italy) | E16: Susie Su | F16: Reggie Zhu | G16: RCS | H16: Vuse device(ROW) | I16: CN | J16: Asset - Others | K16: RCS | L16: T1 | M16: Smoore T1 | N16: NVT | O16: 45261 | P16: 46722 | Q16: 714000 | R16: RMB | S16: =IF(R16="RMB",Q16/$B$6,IF(R16="GBP",Q16,Q16/$B$5)) -> 77627.765 | T16: 8572763 | U16: 0.083287034 | V16: =IF(R16="RMB",U16/$B$6,IF(R16="GBP",U16,U16/$B$5)) -> 0.0090551629
A17: 9 | B17: RF008_Modi2.0 | C17: Modi 2.0 | D17: Automation Flexible Line for Modi 2.0 Platform 1K PEN Default/Full and 1k BOX Full | E17: Allan Liang | F17: Cailine Huang | G17: MD | H17: MD 2.0 | I17: CN | J17: Asset - Modi Line | K17: MoDi | L17: T1 | M17: Smoore T1 | N17: NVT | O17: 45505 | P17: 46235 | Q17: 4912380 | R17: RMB | S17: =IF(R17="RMB",Q17/$B$6,IF(R17="GBP",Q17,Q17/$B$5)) -> 534085.55 | T17: =S17/0.007 -> 76297935 | U17: =0.007*8.81203 -> 0.06168421 | V17: =IF(R17="RMB",U17/$B$6,IF(R17="GBP",U17,U17/$B$5)) -> 0.0067064529
A18: 10 | B18: RF009_Hestia1.0 | C18: Hestia 1.0 | D18: Hestia 1.0 Automation Lines Modification (Modified from ePod3 to Hestia1.0) (1-4 line) | E18: Susie Su | F18: Daisy Cai | G18: Pod | H18: Pod | I18: CN | J18: Pod Automation (Line Upgrade) | K18: RCS | L18: T1 | M18: Smoore T1 | N18: NVT | O18: 45406 | P18: 46113 | Q18: 34746341 | R18: RMB | S18: =IF(R18="RMB",Q18/$B$6,IF(R18="GBP",Q18,Q18/$B$5)) -> 3777704.2 | T18: 246400000 | U18: =Q18/T18 -> 0.14101599 | V18: =IF(R18="RMB",U18/$B$6,IF(R18="GBP",U18,U18/$B$5)) -> 0.015331592
A19: 11 | B19: RF010_Hestia1.0 | C19: Hestia 1.0 | D19: Hestia1.0 Manual line capex | E19: Susie Su | F19: Daisy Cai | G19: Pod | H19: Pod | I19: CN | J19: Asset - Others | K19: RCS | L19: T1 | M19: Smoore T1 | N19: NVT | O19: 45406 | P19: 45505 | Q19: - | R19: RMB | S19: 0 | T19: 0 | U19: 0.036 | V19: =IF(R19="RMB",U19/$B$6,IF(R19="GBP",U19,U19/$B$5)) -> 0.003914005
A20: 12 | B20: RF011_ePod2Pod | C20: ePod2 Pod | D20: ePod Packer - Included in Hestia | E20: Susie Su | F20: Daisy Cai | G20: Pod | H20: Pod | I20: CN | J20: Automation - Packing | K20: RCS | L20: T1 | M20: Smoore T1 | N20: NVT | O20: 44197 | P20: 46357 | Q20: 2660000 | R20: USD | S20: =IF(R20="RMB",Q20/$B$6,IF(R20="GBP",Q20,Q20/$B$5)) -> 2081084 | T20: 175000000 | U20: Volume
A21: 13 | B21: RF012_ePod3Pod | C21: ePod3 Pod | D21: ePod 3 Automation Modification Capex Amortization (1P) Modified from ePod2 to ePod3 | E21: Susie Su | F21: Daisy Cai | G21: Pod | H21: Pod | I21: CN | J21: Pod Automation (Line Upgrade) | K21: RCS | L21: T1 | M21: Smoore T1 | N21: NVT | O21: 44980 | P21: 45689 | Q21: 1503259 | R21: RMB | S21: =IF(R21="RMB",Q21/$B$6,IF(R21="GBP",Q21,Q21/$B$5)) -> 163437.87 | T21: =6430000*4/(0.01*8.87287) -> 2.8987239e+08 | U21: 0.0887284 | V21: =IF(R21="RMB",U21/$B$6,IF(R21="GBP",U21,U21/$B$5)) -> 0.0096467611
A22: 14 | B22: RF013_Kuma | C22: Kuma 1.0 | D22: KUMA E-ROW Ultra Sonic Machine | E22: Lyn Wu | F22: Daisy Cai | G22: RCS | H22: Vuse device(ROW) | I22: CN | J22: Asset - RCS Device line | K22: RCS | L22: T1 | M22: Smoore T1 | N22: NVT | O22: 45383 | P22: 46113 | Q22: 640000 | R22: RMB | S22: =IF(R22="RMB",Q22/$B$6,IF(R22="GBP",Q22,Q22/$B$5)) -> 69582.31 | T22: =Q22/U22 -> 11034483 | U22: 0.058 | V22: =IF(R22="RMB",U22/$B$6,IF(R22="GBP",U22,U22/$B$5)) -> 0.0063058969
A23: 15 | B23: RF014_Kuma | C23: Kuma 1.0 | D23: KUMA E-Pen Laser welding machine & Kuma E-Pen 1.0 air tightness test machine | E23: Lyn Wu | F23: Daisy Cai | G23: RCS | H23: Vuse device(ROW) | I23: CN | J23: Asset - RCS Device line | K23: RCS | L23: T1 | M23: Smoore T1 | N23: NVT | O23: 45505 | P23: 46235 | Q23: =708000+72300 -> 780300 | R23: RMB | S23: =IF(R23="RMB",Q23/$B$6,IF(R23="GBP",Q23,Q23/$B$5)) -> 84836.058 | U23: 0.094674863 | V23: =IF(R23="RMB",U23/$B$6,IF(R23="GBP",U23,U23/$B$5)) -> 0.010293275
A24: 16 | B24: RF015_Modi&RCS | C24: Modi & RCS | D24: CCD&Tax Stamp Machine MD2.0 1K PEN Default Czech/Germany/Poland/Italy/BUL (Machines can be cross-used by both Modi & RCS) | E24: Allan Liang | F24: Cailine Huang | G24: MD | H24: MD 2.0 | I24: CN | J24: Asset - Others | K24: Modi | L24: T1 | M24: Smoore T1 | N24: NVT | O24: 45505 | P24: 46966 | Q24: 1210000 | R24: RMB | S24: =IF(R24="RMB",Q24/$B$6,IF(R24="GBP",Q24,Q24/$B$5)) -> 131554.06 | T24: 29491560 | U24: 0.041028688 | V24: =IF(R24="RMB",U24/$B$6,IF(R24="GBP",U24,U24/$B$5)) -> 0.0044607357
A25: 17 | B25: RF016_Sensa | C25: Sensa | D25: Sensa Manual Line Capex | E25: Frank Lin | F25: Cailine Huang | G25: MD | H25: MD 2.0 | I25: CN | J25: Asset - Others | K25: Modi | L25: T1 | M25: Smoore T1 | N25: NVT | O25: 45474 | P25: 45992 | Q25: 903370.28 | R25: RMB | S25: =IF(R25="RMB",Q25/$B$6,IF(R25="GBP",Q25,Q25/$B$5)) -> 98216.549 | T25: 8895000 | U25: =0.0115*8.81203 -> 0.10133834 | V25: =IF(R25="RMB",U25/$B$6,IF(R25="GBP",U25,U25/$B$5)) -> 0.011017744
A26: 18 | B26: RF017_Sensa | C26: Sensa | D26: Sensa Semi-Auto Line Capex | E26: Frank Lin | F26: Cailine Huang | G26: MD | H26: MD 2.0 | I26: CN | J26: Asset - Modi Line | K26: Modi | L26: T1 | M26: Smoore T1 | N26: NVT | O26: 45536 | P26: 45992 | Q26: 6018424 | R26: RMB | S26: =IF(R26="RMB",Q26/$B$6,IF(R26="GBP",Q26,Q26/$B$5)) -> 654337.26 | T26: 12960000 | U26: =0.0527*8.81203 -> 0.46439398 | V26: =IF(R26="RMB",U26/$B$6,IF(R26="GBP",U26,U26/$B$5)) -> 0.05049001
A27: 19 | B27: RF018_Modi | C27: Modi | D27: T&T longterm solution cost Amortize at Uzbekistan TX500 and DP1500（UZB—乌兹别克斯坦） | E27: Allan Liang | F27: Cailine Huang | G27: MD | H27: MD1.0 | I27: CN | J27: Asset - Others | K27: Modi | L27: T1 | M27: Smoore T1 | N27: NVT | O27: 44986 | P27: 46447 | Q27: 1363867.4 | R27: RMB | S27: =IF(R27="RMB",Q27/$B$6,IF(R27="GBP",Q27,Q27/$B$5)) -> 148282.88 | T27: 4682003 | U27: =Q27/T27 -> 0.29129998 | V27: =IF(R27="RMB",U27/$B$6,IF(R27="GBP",U27,U27/$B$5)) -> 0.031670821
A28: 20 | B28: RF019_Modi | C28: Modi | D28: KZ MODI testing / support for T&T Amortize at KAZ TX500 and DP1500（KZ—哈萨克斯坦） | E28: Allan Liang | F28: Cailine Huang | G28: MD | H28: MD1.0 | I28: CN | J28: Asset - Others | K28: Modi | L28: T1 | M28: Smoore T1 | N28: NVT | O28: 45108 | P28: 46569 | Q28: 130573.98 | R28: RMB | S28: =IF(R28="RMB",Q28/$B$6,IF(R28="GBP",Q28,Q28/$B$5)) -> 14196.311 | T28: 1020000 | U28: =Q28/T28 -> 0.12801371 | V28: =IF(R28="RMB",U28/$B$6,IF(R28="GBP",U28,U28/$B$5)) -> 0.013917952
A29: 21 | B29: RF020_Modi | C29: Modi | D29: T&T Interim programme of Azerbaijan Amortize at Azerbaijan 1k/3k/5k product（AZB—阿塞拜疆） | E29: Allan Liang | F29: Cailine Huang | G29: MD | H29: MD1.0 | I29: CN | J29: Asset - Others | K29: Modi | L29: T1 | M29: Smoore T1 | N29: NVT | O29: 45017 | P29: 46478 | Q29: 95728.992 | R29: RMB | S29: =IF(R29="RMB",Q29/$B$6,IF(R29="GBP",Q29,Q29/$B$5)) -> 10407.882 | V29: =IF(R29="RMB",U29/$B$6,IF(R29="GBP",U29,U29/$B$5)) -> 0
A30: 22 | B30: RF021_Modi | C30: Modi | D30: T&T for Pre-Dispatch Advice --add extra function（UZB—乌兹别克斯坦 KZ—哈萨克斯坦） | E30: Allan Liang | F30: Cailine Huang | G30: MD | H30: MD1.0 | I30: CN | J30: Asset - Others | K30: Modi | L30: T1 | M30: Smoore T1 | N30: NVT | O30: 45017 | P30: 46478 | Q30: 706075.2 | R30: RMB | S30: =IF(R30="RMB",Q30/$B$6,IF(R30="GBP",Q30,Q30/$B$5)) -> 76766.162 | V30: =IF(R30="RMB",U30/$B$6,IF(R30="GBP",U30,U30/$B$5)) -> 0
A31: 23 | B31: RF022_Modi | C31: Modi | D31: KZ MODI testing / support for T&T Amortize at BOX3K&5K KAZ&UZB market（KZ—哈萨克斯坦） | E31: Allan Liang | F31: Cailine Huang | G31: MD | H31: MD1.0 | I31: CN | J31: Asset - Others | K31: Modi | L31: T1 | M31: Smoore T1 | N31: NVT | O31: 45108 | P31: 46569 | Q31: 46448.488 | R31: RMB | S31: =IF(R31="RMB",Q31/$B$6,IF(R31="GBP",Q31,Q31/$B$5)) -> 5049.9892 | T31: 3976000 | U31: 0.011682215 | V31: =IF(R31="RMB",U31/$B$6,IF(R31="GBP",U31,U31/$B$5)) -> 0.001270118
A32: 24 | B32: RF023_Modi | C32: Modi | D32: AZB T&T longterm solution cost for TX500&DP1500&BOX1K&3K&5K for AZB Market（AZB—阿塞拜疆） | E32: Allan Liang | F32: Cailine Huang | G32: MD | H32: MD1.0 | I32: CN | J32: Asset - Others | K32: Modi | L32: T1 | M32: Smoore T1 | N32: NVT | O32: 45017 | P32: 46478 | Q32: 466929.08 | R32: RMB | S32: =IF(R32="RMB",Q32/$B$6,IF(R32="GBP",Q32,Q32/$B$5)) -> 50765.632 | V32: =IF(R32="RMB",U32/$B$6,IF(R32="GBP",U32,U32/$B$5)) -> 0
A33: 25 | B33: RF024_Modi | C33: Modi | D33: Custom development BAT CMO INEXTRACK GS1 Novarator removal CR for AZB regulation（AZB—阿塞拜疆） | E33: Allan Liang | F33: Cailine Huang | G33: MD | H33: MD1.0 | I33: CN | J33: Asset - Others | K33: Modi | L33: T1 | M33: Smoore T1 | N33: NVT | O33: 45108 | P33: 46569 | Q33: 80274.71 | R33: RMB | S33: =IF(R33="RMB",Q33/$B$6,IF(R33="GBP",Q33,Q33/$B$5)) -> 8727.6559 | V33: =IF(R33="RMB",U33/$B$6,IF(R33="GBP",U33,U33/$B$5)) -> 0
A34: 27 | B34: RF025_Hestia1.1 | C34: Hestia 1.0 | D34: epod2 to Hestia1.1 non-smart | E34: Susie Su | F34: Daisy Cai | G34: RCS | H34: Pod | I34: CN | J34: Pod Automation (Line Upgrade) | K34: RCS | L34: T1 | M34: Smoore T1 | N34: NVT | Q34: 5756300 | R34: RMB | S34: =IF(R34="RMB",Q34/$B$6,IF(R34="GBP",Q34,Q34/$B$5)) -> 625838.52 | V34: =IF(R34="RMB",U34/$B$6,IF(R34="GBP",U34,U34/$B$5)) -> 0
A35: 26 | B35: RF026_Hestia1.1 | C35: Hestia 1.1 | D35: epod2 to Hestia1.1 smart | E35: Susie Su | F35: Daisy Cai | G35: RCS | H35: Pod | I35: CN | J35: Pod Automation (Line Upgrade) | K35: RCS | L35: T1 | M35: Smoore T1 | N35: NVT | O35: 45777 | P35: 46507 | Q35: 12518185 | R35: RMB | S35: =IF(R35="RMB",Q35/$B$6,IF(R35="GBP",Q35,Q35/$B$5)) -> 1361006.6 | T35: TBC | U35: TBC
A36: 28 | B36: RF027_Hestia1.0 | C36: Hestia 1.0 | D36: epod2 to Hestia1.0 (5th line) | E36: Susie Su | F36: Daisy Cai | G36: RCS | H36: Pod | I36: CN | J36: Pod Automation (Line Upgrade) | K36: RCS | L36: T1 | M36: Smoore T1 | N36: NVT | O36: TBC | P36: TBC | Q36: 6590000 | R36: RMB | S36: =IF(R36="RMB",Q36/$B$6,IF(R36="GBP",Q36,Q36/$B$5)) -> 716480.35 | V36: =IF(R36="RMB",U36/$B$6,IF(R36="GBP",U36,U36/$B$5)) -> 0
A37: 29 | B37: RF028_Kuma | C37: Kuma E 2.0 Pen | D37: semi-auto for Kuma E 2.0 Pen | E37: Lyn Wu | F37: Daisy Cai | G37: RCS | H37: Device | I37: CN | J37: Asset - RCS Device line | K37: RCS | L37: T1 | M37: Smoore T1 | N37: NVT | O37: 45747 | P37: 46477 | Q37: 2126778 | R37: RMB | S37: =IF(R37="RMB",Q37/$B$6,IF(R37="GBP",Q37,Q37/$B$5)) -> 231228.32 | T37: 5400000 | U37: 0.3938 | V37: =IF(R37="RMB",U37/$B$6,IF(R37="GBP",U37,U37/$B$5)) -> 0.042814865
A38: 30 | B38: RF029_Kuma | C38: Kuma E 2.0 Box | D38: semi-auto for Kuma E 2.0 Box | E38: Lyn Wu | F38: Daisy Cai | G38: RCS | H38: Device | I38: CN | J38: Asset - RCS Device line | K38: RCS | L38: T1 | M38: Smoore T1 | N38: NVT | O38: 45761 | P38: 46491 | Q38: 1682778 | R38: RMB | S38: =IF(R38="RMB",Q38/$B$6,IF(R38="GBP",Q38,Q38/$B$5)) -> 182955.6 | T38: 5400000 | U38: 0.3084 | V38: =IF(R38="RMB",U38/$B$6,IF(R38="GBP",U38,U38/$B$5)) -> 0.033529976
A39: 31 | B39: RF030_Mimosa | C39: Mimosa | D39: semi-auto for Mimosa1.0 + 2 Glue Machine | E39: Allan Liang | F39: Daisy Cai | G39: RCS | H39: Device | I39: CN | J39: Asset - RCS Device line | K39: RCS | L39: T1 | M39: Smoore T1 | N39: NVT | O39: 45689 | P39: 46411 | Q39: 4352000 | R39: RMB | S39: =IF(R39="RMB",Q39/$B$6,IF(R39="GBP",Q39,Q39/$B$5)) -> 473159.71 | T39: 4800000 | U39: 0.91 | V39: =IF(R39="RMB",U39/$B$6,IF(R39="GBP",U39,U39/$B$5)) -> 0.098937348
A40: 32 | B40: RF031_Hestia1.0 | C40: Hestia 1.0 | D40: Tax stamp and CCD capex amortization | E40: Susie Su | F40: Daisy Cai | G40: RCS | H40: Pod | I40: CN | J40: Asset - Others | K40: RCS | L40: T1 | M40: Smoore T1 | N40: NVT | O40: 45566 | P40: 48122 | Q40: 760000 | R40: RMB | S40: =IF(R40="RMB",Q40/$B$6,IF(R40="GBP",Q40,Q40/$B$5)) -> 82628.994 | U40: 0.028896174 | V40: =IF(R40="RMB",U40/$B$6,IF(R40="GBP",U40,U40/$B$5)) -> 0.0031416602
A41: 33 | B41: RF032_Alto | C41: Alto | D41: Alto tooling(IM tooling for 2p cost reduction) | E41: Angie Huang | F41: Candy Zhang | G41: Pod | H41: Pod | I41: Indo | J41: Tooling | K41: RCS | L41: T2 | M41: Smoore T2 | N41: Reynolds | O41: 44980 | P41: 46722 | Q41: 5098268.4 | R41: USD | S41: =IF(R41="RMB",Q41/$B$6,IF(R41="GBP",Q41,Q41/$B$5)) -> 3988693.6 | T41: 480000000 | U41: 0.0106 | V41: =IF(R41="RMB",U41/$B$6,IF(R41="GBP",U41,U41/$B$5)) -> 0.0082930417
A42: 34 | B42: RF033_ePod2Pod | C42: ePod2 POD | D42: ePod2 POD | E42: Susie Su | F42: Candy Zhang | G42: Pod | H42: Pod | I42: CN | J42: Tooling | K42: RCS | L42: T2 | M42: Smoore T2 | N42: NVT | O42: 44986 | P42: 45657 | Q42: 23526500 | R42: RMB | S42: =IF(R42="RMB",Q42/$B$6,IF(R42="GBP",Q42,Q42/$B$5)) -> 2557856.6 | U42: 0.1048 | V42: =IF(R42="RMB",U42/$B$6,IF(R42="GBP",U42,U42/$B$5)) -> 0.011394103
A43: 35 | B43: RF034_epod2Device | C43: epod 2 Device | D43: ePod2 Device - Wave 1-B design | E43: Susie Su | F43: Candy Zhang | G43: RCS | H43: Vuse device(ROW) | I43: CN | J43: Tooling | K43: RCS | L43: T2 | M43: Smoore T2 | N43: NVT | O43: 44228 | P43: 45657 | Q43: 546000 | R43: RMB | S43: =IF(R43="RMB",Q43/$B$6,IF(R43="GBP",Q43,Q43/$B$5)) -> 59362.409 | U43: NO SHIPMENT
A44: 36 | B44: RF035_epod2+Device | C44: ePod2+ Device | D44: ePod2+ Device | E44: Susie Su | F44: Candy Zhang | G44: RCS | H44: Vuse device(ROW) | I44: CN | J44: Tooling | K44: RCS | L44: T2 | M44: Smoore T2 | N44: NVT | O44: 44593 | P44: 45657 | Q44: 1550800 | R44: RMB | S44: =IF(R44="RMB",Q44/$B$6,IF(R44="GBP",Q44,Q44/$B$5)) -> 168606.64 | U44: 0.7016 | V44: =IF(R44="RMB",U44/$B$6,IF(R44="GBP",U44,U44/$B$5)) -> 0.076279608
A45: 37 | B45: RF036_Hestia1.0 | C45: Hestia 1.0 | D45: epod 3 pod Tooling, Included in Hestia Carryover | E45: Susie Su | F45: Candy Zhang | G45: Pod | H45: Pod | I45: CN | J45: Tooling | K45: RCS | L45: T2 | M45: Smoore T2 | N45: NVT | O45: 45008 | P45: 46357 | Q45: -9120225 | R45: RMB | S45: =IF(R45="RMB",Q45/$B$6,IF(R45="GBP",Q45,Q45/$B$5)) -> -991572.39 | T45: 0 | V45: =IF(R45="RMB",U45/$B$6,IF(R45="GBP",U45,U45/$B$5)) -> 0
A46: 38 | B46: RF037_epod3Device | C46: epod 3 Device | D46: epod 3 device tooling, To be Included in ePod 4+ no risk to flag yet. | E46: Susie Su | F46: Candy Zhang | G46: RCS | H46: Vuse device(ROW) | I46: CN | J46: Tooling | K46: RCS | L46: T2 | M46: Smoore T2 | N46: NVT | O46: 44986 | P46: 45627 | Q46: 1520008 | R46: RMB | S46: =IF(R46="RMB",Q46/$B$6,IF(R46="GBP",Q46,Q46/$B$5)) -> 165258.86 | T46: 0 | U46: 0.1006 | V46: =IF(R46="RMB",U46/$B$6,IF(R46="GBP",U46,U46/$B$5)) -> 0.010937469
A47: 39 | B47: RF038_epod3+Device | C47: epod 3+ Device | D47: epod 3+ device tooling, To be Included in ePod 4+ no risk to flag yet. | E47: Susie Su | F47: Candy Zhang | G47: RCS | H47: Vuse device(ROW) | I47: CN | J47: Tooling | K47: RCS | L47: T2 | M47: Smoore T2 | N47: NVT | O47: 45047 | P47: 45627 | Q47: 1914510.9 | R47: RMB | S47: =IF(R47="RMB",Q47/$B$6,IF(R47="GBP",Q47,Q47/$B$5)) -> 208150.14 | T47: 0 | U47: 0.1155 | V47: =IF(R47="RMB",U47/$B$6,IF(R47="GBP",U47,U47/$B$5)) -> 0.012557433
A48: 40 | B48: RF039_Hestia1.0 | C48: Hestia 1.0 | D48: Hestia 1.0 New Tooling + ePod3 Pod Tooling included | E48: Susie Su | F48: Candy Zhang | G48: Pod | H48: Pod | I48: CN | J48: Tooling | K48: RCS | L48: T2 | M48: Smoore T2 | N48: NVT | O48: 45383 | P48: 46113 | Q48: 29153936 | R48: RMB | S48: =IF(R48="RMB",Q48/$B$6,IF(R48="GBP",Q48,Q48/$B$5)) -> 3169684.7 | T48: =S48/#REF! -> #REF! | U48: 0.1006 | V48: =IF(R48="RMB",U48/$B$6,IF(R48="GBP",U48,U48/$B$5)) -> 0.010937469
A49: 41 | B49: RF040_Kuma | C49: Kuma | D49: KUMA E BOX NZ | E49: Lyn Wu | F49: Candy Zhang | G49: RCS | H49: Vuse device(ROW) | I49: CN | J49: Tooling | K49: RCS | L49: T2 | M49: Smoore T2 | N49: NVT | O49: 45383 | P49: N/A | Q49: No Hard tool investment | R49: RMB | S49: 0 | U49: 0 | V49: =IF(R49="RMB",U49/$B$6,IF(R49="GBP",U49,U49/$B$5)) -> 0
A50: 42 | B50: RF041_Kuma | C50: Kuma | D50: KUMA E BOX ROW | E50: Lyn Wu | F50: Candy Zhang | G50: RCS | H50: Vuse device(ROW) | I50: CN | J50: Tooling | K50: RCS | L50: T2 | M50: Smoore T2 | N50: NVT | O50: 45383 | P50: 46113 | Q50: 3274500 | R50: RMB | S50: =IF(R50="RMB",Q50/$B$6,IF(R50="GBP",Q50,Q50/$B$5)) -> 356011.37 | T50: =S50/#REF! -> #REF! | U50: 0.1562 | V50: =IF(R50="RMB",U50/$B$6,IF(R50="GBP",U50,U50/$B$5)) -> 0.016982433
A51: 43 | B51: RF042_Kuma | C51: Kuma | D51: KUMA E-ROW E Pen 1.0 | E51: Lyn Wu | F51: Candy Zhang | G51: RCS | H51: Vuse device(ROW) | I51: CN | J51: Tooling | K51: RCS | L51: T2 | M51: Smoore T2 | N51: NVT | O51: 45383 | P51: 46113 | Q51: 5236765 | R51: RMB | S51: =IF(R51="RMB",Q51/$B$6,IF(R51="GBP",Q51,Q51/$B$5)) -> 569353.45 | T51: =S51/#REF! -> #REF! | U51: 0.2284 | V51: =IF(R51="RMB",U51/$B$6,IF(R51="GBP",U51,U51/$B$5)) -> 0.024832187
A52: 44 | B52: RF043_Modi2.0 | C52: Modi 2.0 | D52: Vuse Go 2.0 1K Pen Default | E52: Allan Liang | F52: Johnny Yu | G52: MD | H52: MD 2.0 | I52: CN | J52: Tooling | K52: Modi | L52: T2 | M52: Smoore T2 | N52: NVT | O52: 45383 | P52: 45992 | Q52: 12241217 | R52: RMB | S52: =IF(R52="RMB",Q52/$B$6,IF(R52="GBP",Q52,Q52/$B$5)) -> 1330894 | T52: =S52/#REF! -> #REF! | U52: 0.0769 | V52: =IF(R52="RMB",U52/$B$6,IF(R52="GBP",U52,U52/$B$5)) -> 0.0083607495
A53: 45 | B53: RF044_Modi2.0 | C53: Modi 2.0 | D53: Vuse Go 2.0 1K Box Default | E53: Allan Liang | F53: Johnny Yu | G53: MD | H53: MD 2.0 | I53: CN | J53: Tooling | K53: Modi | L53: T2 | M53: Smoore T2 | N53: NVT | O53: 45383 | P53: 45992 | Q53: 10952560 | R53: RMB | S53: =IF(R53="RMB",Q53/$B$6,IF(R53="GBP",Q53,Q53/$B$5)) -> 1190788.2 | T53: =S53/#REF! -> #REF! | U53: 0.089 | V53: =IF(R53="RMB",U53/$B$6,IF(R53="GBP",U53,U53/$B$5)) -> 0.00967629
A54: 46 | B54: RF045_Modi2.0 | C54: Modi 2.0 | D54: Vuse Go 2.0 1K Box Full | E54: Allan Liang | F54: Johnny Yu | G54: MD | H54: MD 2.0 | I54: CN | J54: Tooling | K54: MoDi | L54: T2 | M54: Smoore T2 | N54: NVT | O54: 45383 | P54: 45992 | Q54: 6088018 | R54: RMB | S54: =IF(R54="RMB",Q54/$B$6,IF(R54="GBP",Q54,Q54/$B$5)) -> 661903.69 | T54: =S54/#REF! -> #REF! | U54: 0.164 | V54: =IF(R54="RMB",U54/$B$6,IF(R54="GBP",U54,U54/$B$5)) -> 0.017830467
A55: 47 | B55: RF046_Modi2.0 | C55: Modi 2.0 | D55: Vuse Go 2.0 1K Pen Full | E55: Allan Liang | F55: Johnny Yu | G55: MD | H55: MD 2.0 | I55: CN | J55: Tooling | K55: MoDi | L55: T2 | M55: Smoore T2 | N55: NVT | O55: 45383 | P55: 45992 | Q55: 1864192.9 | R55: RMB | S55: =IF(R55="RMB",Q55/$B$6,IF(R55="GBP",Q55,Q55/$B$5)) -> 202679.45 | T55: =S55/#REF! -> #REF! | U55: 0.1081 | V55: =IF(R55="RMB",U55/$B$6,IF(R55="GBP",U55,U55/$B$5)) -> 0.011752887 | AUD55: ''''''''' | AUF55: ''''''''''''''''''''''''''''''''''''''' | AUG55: ''''''''''''''''''''''''''''''''''''''''''''''''''''''''''''''''''''''''''''''''''''''''''''''''''''''''''''''''''''''''''''''''''''''''''''''''''''''''''''''''''''''''''''''''''''''''''''''''''''''''''''''''''''''''''''''''''''''''''''''''''''''''''''''''''''''''''''''''''''''''''''''''''''''''''''''''''''''''''''''''''''''''''''''''''''''''''''''''''''''''''''''''''''''''''''''''''''''''''''''''''''''''''''''''''''''''''''''''''''''''''''''''''''''''''''''''''''''''''''''''''''''''''''''''''''''''''''''''''''''''''''''''''''''''''''''''''''''''''''''''''''''''''''''''''''''''''''''''''''''''''''''''''''''''''''''''''''''''''''''''''''''''''''''''''''''''''''''''''''''''''''''''''''''''''''''''''''''''''''''''''''''''''''''''''''''''''''''''''''''''''''''''''''''''''''''''''''''''''''''''''''''''''''''''''''''''''''''''''''''''''''''''''''''''''''''''''''''''''''''''''''''''''''''''''''''''''''''''''''''''''''''''''''''''''''''''''''''''''''''''''''''''''''''''''''''''''''''''''''''''''''''''''''''''''''''''''''''''''''''''''''''''''''''''''''''''''''''''''''''''''''''''''''''''''''''''''''''''''''''''''''''''''''''''''''''''''''''''''''''''''''''''''''''''''''''''''''''''''''''''''''''''''''''''''''''''''''''''''''''''''''''''''''''''''''''''''''''''''''''''''''''''''''''''''''''''''''''''''''''''''''''''''''''''''''''''''''''''''''''''''''''''''''''''''
A56: 48 | B56: RF047_DP1500 | C56: DP 1500 | D56: DP 1500 tooling | E56: Angie Huang | F56: Daisy Cai | G56: MD | H56: MD 1.0 | I56: CN | J56: Tooling | K56: Modi | L56: T2 | M56: Smoore T2 | N56: NVT | O56: 44743 | P56: 45559 | Q56: 7496388.4 | R56: RMB | S56: =IF(R56="RMB",Q56/$B$6,IF(R56="GBP",Q56,Q56/$B$5)) -> 815025.04 | T56: =SUM(#REF!) -> #REF! | U56: =S56/T56 -> #REF!
A57: 49 | B57: RF048_Box1k | C57: BOX 1K | D57: BOX 1000 | E57: Angie Huang | F57: Daisy Cai | G57: MD | H57: MD 1.0 | I57: CN | J57: Tooling | K57: MoDi | L57: T2 | M57: Smoore T2 | N57: NVT | O57: 45170 | P57: 45559 | Q57: 3926494.7 | R57: RMB | S57: =IF(R57="RMB",Q57/$B$6,IF(R57="GBP",Q57,Q57/$B$5)) -> 426897.77 | T57: =SUM(#REF!) -> #REF! | U57: =S57/T57 -> #REF!
A58: 50 | B58: RF049_Modi2.0 | C58: Modi 2.0 | D58: Vuse Go 2.0 5K Box Full(Include Sensa) | E58: Frank Lin | F58: Johnny Yu | G58: MD | H58: MD 2.0 | I58: CN | J58: Tooling | K58: Modi | L58: T2 | M58: Smoore T2 | N58: NVT | O58: 45413 | P58: 45992 | Q58: 16853984 | R58: RMB | S58: =IF(R58="RMB",Q58/$B$6,IF(R58="GBP",Q58,Q58/$B$5)) -> 1832404.9 | T58: =S58/#REF! -> #REF! | U58: 0.229 | V58: =IF(R58="RMB",U58/$B$6,IF(R58="GBP",U58,U58/$B$5)) -> 0.02489742
A59: 51 | B59: RF050_Modi2.0 | C59: Modi 2.0 | D59: Vuse Go 2.0 8K Box Full | E59: Frank Lin | F59: Johnny Yu | G59: MD | H59: MD 2.0 | I59: CN | J59: Tooling | K59: MoDi | L59: T2 | M59: Smoore T2 | N59: NVT | O59: 45505 | P59: 45992 | Q59: 2482288.7 | R59: RMB | S59: =IF(R59="RMB",Q59/$B$6,IF(R59="GBP",Q59,Q59/$B$5)) -> 269880.28 | T59: =S59/#REF! -> #REF! | U59: 0.2464 | V59: =IF(R59="RMB",U59/$B$6,IF(R59="GBP",U59,U59/$B$5)) -> 0.02678919
A60: 52 | B60: RF051_Modi2.0 | C60: Modi 2.0 | D60: Vuse Go 2.0 3K Box Full | E60: Frank Lin | F60: Johnny Yu | G60: MD | H60: MD 2.0 | I60: CN | J60: Tooling | K60: Modi | L60: T2 | M60: Smoore T2 | N60: NVT | O60: 45536 | P60: 45992 | Q60: 11061510 | R60: RMB | S60: =IF(R60="RMB",Q60/$B$6,IF(R60="GBP",Q60,Q60/$B$5)) -> 1202633.5 | T60: =S60/#REF! -> #REF! | U60: 0.24 | V60: =IF(R60="RMB",U60/$B$6,IF(R60="GBP",U60,U60/$B$5)) -> 0.026093366
A61: 53 | B61: RF052_epod3pod | C61: ePod3 Pod | D61: ePod3 Pod tooling | E61: Susie Su | F61: Candy Zhang | G61: Pod | H61: Pod | I61: CN | J61: Tooling | K61: RCS | L61: T2 | M61: Smoore T2 | N61: NVT | O61: 44986 | P61: 45627 | Q61: 16213779 | R61: RMB | S61: =IF(R61="RMB",Q61/$B$6,IF(R61="GBP",Q61,Q61/$B$5)) -> 1762800.3 | V61: =IF(R61="RMB",U61/$B$6,IF(R61="GBP",U61,U61/$B$5)) -> 0
A62: 54 | B62: RF053_Alto | C62: Alto | D62: Alto tooling | E62: Angie Huang | F62: Candy Zhang | G62: RCS | H62: Pod | I62: Indo | J62: Tooling | K62: RCS | L62: T2 | M62: Smoore T2 | N62: Reynolds | O62: 44857 | P62: N/A | Q62: 8718477 | R62: USD | S62: =IF(R62="RMB",Q62/$B$6,IF(R62="GBP",Q62,Q62/$B$5)) -> 6821008.8 | U62: 0.016248973 | V62: =IF(R62="RMB",U62/$B$6,IF(R62="GBP",U62,U62/$B$5)) -> 0.012712586
A63: 55 | B63: RF054_Hestia1.1 | C63: Hestia 1.1 | D63: Hestia 1.1 tooling NON-smart unique+ECN | E63: Susie Su | F63: Candy Zhang | G63: RCS | H63: Pod | I63: CN | J63: Tooling | K63: RCS | L63: T2 | M63: Smoore T2 | N63: NVT | O63: 45777 | P63: 46507 | Q63: 2009900 | R63: RMB | S63: =IF(R63="RMB",Q63/$B$6,IF(R63="GBP",Q63,Q63/$B$5)) -> 218521.07 | T63: 0 | V63: =IF(R63="RMB",U63/$B$6,IF(R63="GBP",U63,U63/$B$5)) -> 0
A64: 56 | B64: RF055_Hestia1.1 | C64: Hestia 1.1 | D64: Hestia 1.1 tooling initial smart and commont parts | E64: Susie Su | F64: Candy Zhang | G64: RCS | H64: Pod | I64: CN | J64: Tooling | K64: RCS | L64: T2 | M64: Smoore T2 | N64: NVT | O64: 45777 | P64: 46507 | Q64: 10069487 | R64: RMB | S64: =IF(R64="RMB",Q64/$B$6,IF(R64="GBP",Q64,Q64/$B$5)) -> 1094778.4 | U64: 0.1939 | V64: =IF(R64="RMB",U64/$B$6,IF(R64="GBP",U64,U64/$B$5)) -> 0.021081266
A65: 57 | B65: RF056_Hestia1.1 | C65: Hestia 1.1 | D65: Hestia 1.1 tooling incremental | E65: Susie Su | F65: Candy Zhang | G65: RCS | H65: Pod | I65: CN | J65: Tooling | K65: RCS | L65: T2 | M65: Smoore T2 | N65: NVT | O65: 45777 | P65: 46507 | R65: RMB | S65: =IF(R65="RMB",Q65/$B$6,IF(R65="GBP",Q65,Q65/$B$5)) -> 0 | V65: =IF(R65="RMB",U65/$B$6,IF(R65="GBP",U65,U65/$B$5)) -> 0
A66: 58 | B66: RF057_KumaE2.0 | C66: Kuma E 2.0 | D66: Kuma E 2.0 Pen tooling initial | E66: Lyn Wu | F66: Candy Zhang | G66: RCS | H66: Vuse device(ROW) | I66: CN | J66: Tooling | K66: RCS | L66: T2 | M66: Smoore T2 | N66: NVT | O66: 45620 | P66: 46350 | Q66: 7732809 | R66: RMB | S66: =IF(R66="RMB",Q66/$B$6,IF(R66="GBP",Q66,Q66/$B$5)) -> 840729.24 | U66: 0.2015 | V66: =IF(R66="RMB",U66/$B$6,IF(R66="GBP",U66,U66/$B$5)) -> 0.021907556
A67: 59 | B67: RF058_KumaE2.0 | C67: Kuma E 2.0 | D67: Kuma E 2.0 Pen tooling incremental | E67: Lyn Wu | F67: Candy Zhang | G67: RCS | H67: Vuse device(ROW) | I67: CN | J67: Tooling | K67: RCS | L67: T2 | M67: Smoore T2 | N67: NVT | O67: 45620 | P67: 46350 | Q67: 0 | R67: RMB | S67: =IF(R67="RMB",Q67/$B$6,IF(R67="GBP",Q67,Q67/$B$5)) -> 0 | V67: =IF(R67="RMB",U67/$B$6,IF(R67="GBP",U67,U67/$B$5)) -> 0
A68: 60 | B68: RF059_Mimosa1.0 | C68: Mimosa | D68: Mimosa 1.0 tooling initial | E68: Allan Liang | F68: Candy Zhang | G68: RCS | H68: Vuse device(ROW) | I68: CN | J68: Tooling | K68: RCS | L68: T2 | M68: Smoore T2 | N68: NVT | O68: 45689 | P68: 46411 | Q68: 10157605 | R68: RMB | S68: =IF(R68="RMB",Q68/$B$6,IF(R68="GBP",Q68,Q68/$B$5)) -> 1104358.8 | T68: =S68/#REF! -> #REF! | U68: 1.9922 | V68: =IF(R68="RMB",U68/$B$6,IF(R68="GBP",U68,U68/$B$5)) -> 0.21659669
A69: 61 | B69: RF060_Mimosa1.0 | C69: Mimosa | D69: Mimosa 1.0 tooling incremental | E69: Allan Liang | F69: Candy Zhang | G69: RCS | H69: Vuse device(ROW) | I69: CN | J69: Tooling | K69: RCS | L69: T2 | M69: Smoore T2 | N69: NVT | O69: 45689 | P69: 46411 | Q69: 217300 | R69: RMB | S69: =IF(R69="RMB",Q69/$B$6,IF(R69="GBP",Q69,Q69/$B$5)) -> 23625.369 | V69: =IF(R69="RMB",U69/$B$6,IF(R69="GBP",U69,U69/$B$5)) -> 0
A70: 62 | B70: RF061_PrismaticPod | C70: Prismatic Pod | D70: China | E70: Angie Huang | F70: Candy Zhang | G70: RCS | H70: Pod | I70: CN | J70: N/A | K70: RCS | L70: T2 | M70: Smoore T2 | N70: NVT | O70: 45352 | P70: 46082 | Q70: 98000 | R70: RMB | S70: =IF(R70="RMB",Q70/$B$6,IF(R70="GBP",Q70,Q70/$B$5)) -> 10654.791 | U70: 0.0030625 | V70: =IF(R70="RMB",U70/$B$6,IF(R70="GBP",U70,U70/$B$5)) -> 0.00033296223
A71: 63 | B71: RF062_PrismaticPod | C71: Prismatic Pod | D71: Prismatic Pod Indo Black | E71: Angie Huang | F71: Candy Zhang | G71: RCS | H71: Pod | I71: Indo | J71: N/A | K71: RCS | L71: T2 | M71: Smoore T2 | N71: NVT | O71: 45839 | P71: 46569 | Q71: 4584750.8 | R71: RMB | S71: =IF(R71="RMB",Q71/$B$6,IF(R71="GBP",Q71,Q71/$B$5)) -> 498464.93 | T71: 54607346 | U71: =Q71/T71 -> 0.0839585 | V71: =IF(R71="RMB",U71/$B$6,IF(R71="GBP",U71,U71/$B$5)) -> 0.0091281663
A72: 64 | B72: RF063_PrismaticPod | C72: Prismatic Pod | D72: Prismatic Pod Indo white | E72: Angie Huang | F72: Candy Zhang | G72: RCS | H72: Pod | I72: Indo | J72: N/A | K72: RCS | L72: T2 | M72: Smoore T2 | N72: NVT | O72: 45839 | P72: 46569 | Q72: 3933456.4 | R72: RMB | S72: =IF(R72="RMB",Q72/$B$6,IF(R72="GBP",Q72,Q72/$B$5)) -> 427654.66 | T72: 54607346 | U72: =Q72/T72 -> 0.072031634 | V72: =IF(R72="RMB",U72/$B$6,IF(R72="GBP",U72,U72/$B$5)) -> 0.0078314493
A73: 65 | B73: RF064_MimosaSmart | C73: Mimosa | D73: Mimosa 1.0 - PCBA Tooling | E73: Allan Liang | F73: Richard Yang | G73: RCS | H73: Vuse device(ROW) | I73: CN | J73: Tooling | K73: RCS | L73: T2 | M73: BYD T2 | N73: NVT | O73: 45778 | P73: 46143 | Q73: 1359200 | R73: RMB | S73: =IF(R73="RMB",Q73/$B$6,IF(R73="GBP",Q73,Q73/$B$5)) -> 147775.43 | T73: 1000000 | U73: =Q73/T73 -> 1.3592 | V73: =IF(R73="RMB",U73/$B$6,IF(R73="GBP",U73,U73/$B$5)) -> 0.14777543
A74: 66 | B74: RF065_Epod3 | C74: Epod 3 | D74: Epod 3 - PCBA Tooling | E74: Susie Su | F74: Richard Yang | G74: RCS | H74: Vuse device(ROW) | I74: CN | J74: Tooling | K74: RCS | L74: T2 | M74: BYD T2 | N74: NVT | O74: NA | P74: NA | Q74: 817400 | R74: RMB | S74: =IF(R74="RMB",Q74/$B$6,IF(R74="GBP",Q74,Q74/$B$5)) -> 88869.657 | T74: NA | U74: NA
A75: 67 | B75: RF066_Epod3+ | C75: Epod 3+ | D75: Epod 3+ - PCBA Tooling | E75: Susie Su | F75: Richard Yang | G75: RCS | H75: Vuse device(ROW) | I75: CN | J75: Tooling | K75: RCS | L75: T2 | M75: BYD T2 | N75: NVT | O75: NA | P75: NA | Q75: 1357000 | R75: RMB | S75: =IF(R75="RMB",Q75/$B$6,IF(R75="GBP",Q75,Q75/$B$5)) -> 147536.24 | T75: NA | U75: NA
A76: 68 | B76: RF067_Hestia1.1 | C76: Hestia 1.1 | D76: Hestia 1.1 - PCBA Tooling | E76: Susie Su | F76: Richard Yang | G76: Pod | H76: Pod | I76: CN | K76: RCS | L76: T2 | M76: BYD T2 | N76: NVT | O76: 45777 | P76: 46507 | Q76: 212750 | R76: RMB | S76: =IF(R76="RMB",Q76/$B$6,IF(R76="GBP",Q76,Q76/$B$5)) -> 23130.682 | T76: 4000000 | U76: =Q76/T76 -> 0.0531875 | V76: =IF(R76="RMB",U76/$B$6,IF(R76="GBP",U76,U76/$B$5)) -> 0.0057826705
A77: 69 | B77: RF068_KumaE2.0PenNZ | C77: Kuma E 2.0 Pen NZ | D77: Kuma E 2.0 Pen NZ - PCBA Tooling | E77: Lyn Wu | F77: Richard Yang | G77: RCS | H77: Vuse device(ROW) | I77: CN | J77: Tooling | K77: RCS | L77: T2 | M77: BYD T2 | N77: NVT | O77: 45604 | P77: 46334 | Q77: 715900 | R77: RMB | S77: =IF(R77="RMB",Q77/$B$6,IF(R77="GBP",Q77,Q77/$B$5)) -> 77834.338 | T77: 4000000 | U77: =Q77/T77 -> 0.178975 | V77: =IF(R77="RMB",U77/$B$6,IF(R77="GBP",U77,U77/$B$5)) -> 0.019458584
A78: 70 | B78: RF069_KumaE2.0Box | C78: Kuma E 2.0 Box | D78: Kuma E 2.0 Box - PCBA Tooling | E78: Lyn Wu | F78: Richard Yang | G78: RCS | H78: Vuse device(ROW) | I78: CN | J78: Tooling | K78: RCS | L78: T2 | M78: BYD T2 | N78: NVT | O78: 45761 | P78: 46491 | Q78: 824300 | R78: RMB | S78: =IF(R78="RMB",Q78/$B$6,IF(R78="GBP",Q78,Q78/$B$5)) -> 89619.841 | T78: 3000000 | U78: =Q78/T78 -> 0.27476667 | V78: =IF(R78="RMB",U78/$B$6,IF(R78="GBP",U78,U78/$B$5)) -> 0.02987328
A79: 71 | B79: RF070_KumaEMax | C79: Kuma E Max | D79: Kuma E Max - PCBA Tooling | E79: Lyn Wu | F79: Richard Yang | G79: RCS | H79: Vuse device(ROW) | I79: CN | J79: Tooling | K79: RCS | L79: T2 | M79: BYD T2 | N79: NVT | O79: TBC | P79: TBC | Q79: 692800 | R79: RMB | S79: =IF(R79="RMB",Q79/$B$6,IF(R79="GBP",Q79,Q79/$B$5)) -> 75322.851 | T79: 4000000 | U79: =Q79/T79 -> 0.1732 | V79: =IF(R79="RMB",U79/$B$6,IF(R79="GBP",U79,U79/$B$5)) -> 0.018830713
A80: 72 | B80: RF071_Aquila-US | C80: Aquila-US | D80: Aquila-US - PCBA Tooling | E80: Angie Huang | F80: Richard Yang | G80: RCS | H80: Vuse Device( US Alto) | I80: CN | J80: Tooling | K80: RCS | L80: T2 | M80: BYD T2 | N80: NVT | O80: TBC | P80: TBC | Q80: 1480600 | R80: RMB | S80: =IF(R80="RMB",Q80/$B$6,IF(R80="GBP",Q80,Q80/$B$5)) -> 160974.33 | T80: 4000000 | U80: =Q80/T80 -> 0.37015 | V80: =IF(R80="RMB",U80/$B$6,IF(R80="GBP",U80,U80/$B$5)) -> 0.040243582
A81: 73 | B81: RF072_PrismaticPod | C81: Prismatic Pod | D81: Indo POD T1 transfer Capex | E81: Angie Huang | F81: Reggie Zhu | G81: RCS | H81: Pod | I81: Indo | J81: N/A | K81: RCS | L81: T1 | M81: Smoore T1 | N81: Reynolds | O81: 45839 | P81: 46569 | Q81: 1714020.5 | R81: RMB | S81: =IF(R81="RMB",Q81/$B$6,IF(R81="GBP",Q81,Q81/$B$5)) -> 186352.35 | T81: 54607346 | U81: =Q81/T81 -> 0.031388093 | V81: =IF(R81="RMB",U81/$B$6,IF(R81="GBP",U81,U81/$B$5)) -> 0.0034125876
A82: 74 | B82: RF073_Hestia1.0 | C82: Hestia 1.0 | D82: ePod 2 to Hestia1.0 / ePod compatible line (6th line) | F82: Daisy Cai | G82: RCS | H82: Pod | I82: CN | J82: Pod Automation | K82: RCS | L82: T1 | M82: Smoore T1 | N82: NVT | O82: TBC | P82: TBC | Q82: 13323188 | R82: RMB | S82: =IF(R82="RMB",Q82/$B$6,IF(R82="GBP",Q82,Q82/$B$5)) -> 1448528.4 | V82: =IF(R82="RMB",U82/$B$6,IF(R82="GBP",U82,U82/$B$5)) -> 0
A83: 76 | C83: Kuma E 2.0 Box | D83: Kuma E 2.0 Box Tooling | E83: Susie Su | F83: Candy Zhang | G83: RCS | H83: Device | I83: CN | J83: Tooling | K83: RCS | L83: T2 | M83: Smoore T2 | N83: NVT | O83: 45761 | P83: 46491 | Q83: 4711062.4 | R83: RMB | S83: =IF(R83="RMB",Q83/$B$6,IF(R83="GBP",Q83,Q83/$B$5)) -> 512197.82 | U83: 0.3225 | V83: =IF(R83="RMB",U83/$B$6,IF(R83="GBP",U83,U83/$B$5)) -> 0.035062961
A84: 77 | C84: Prismatic Kit | D84: Primsmatic Kit VAT/qualification cost | E84: Angie Huang | F84: Reggie Zhu | G84: RCS | H84: Pod | I84: Indo | J84: N/A | K84: RCS | L84: T1 | M84: Smoore T1 | N84: Reynolds | O84: 45839 | P84: 46569 | Q84: 116400 | R84: USD | S84: =IF(R84="RMB",Q84/$B$6,IF(R84="GBP",Q84,Q84/$B$5)) -> 91066.986 | T84: 2400000 | U84: =Q84/T84 -> 0.0485 | V84: =IF(R84="RMB",U84/$B$6,IF(R84="GBP",U84,U84/$B$5)) -> 0.037944577
C85: Kuma E 2.0 Pen ROW | D85: Kuma E 2.0 Pen ROW - PCBA Tooling | F85: Richard Yang | G85: RCS | H85: Device | I85: CN | J85: Tooling | K85: RCS | L85: T2 | M85: BYD T2 | N85: NVT | O85: 45778 | P85: 46508 | Q85: 1668455.6 | R85: RMB | S85: =IF(R85="RMB",Q85/$B$6,IF(R85="GBP",Q85,Q85/$B$5)) -> 181398.43 | T85: 3000000 | U85: =Q85/T85 -> 0.55615187 | V85: =IF(R85="RMB",U85/$B$6,IF(R85="GBP",U85,U85/$B$5)) -> 0.060466143
C86: VEGA | D86: Automation CFU Line (ACCRUED) | E86: Angie Huang | F86: Daisy Cai | G86: MD | J86: Asset | K86: MoDi | L86: T1 | M86: CFU T1 | N86: NVT | O86: 45139 | P86: 45566 | Q86: 31179700 | R86: RMB | S86: =IF(R86="RMB",Q86/$B$6,IF(R86="GBP",Q86,Q86/$B$5)) -> 3389930.6 | T86: 40000000 | U86: 0 | V86: =IF(R86="RMB",U86/$B$6,IF(R86="GBP",U86,U86/$B$5)) -> 0
C87: VEGA | D87: Tax Stamp | E87: Angie Huang | F87: Daisy Cai | G87: MD | J87: Asset - Tax Stamp | K87: Modi | L87: T1 | M87: CFU T1 | N87: NVT | O87: 45231 | P87: 45474 | Q87: 340000 | R87: RMB | S87: =IF(R87="RMB",Q87/$B$6,IF(R87="GBP",Q87,Q87/$B$5)) -> 36965.602 | T87: 2000000 | U87: 0.17 | V87: =IF(R87="RMB",U87/$B$6,IF(R87="GBP",U87,U87/$B$5)) -> 0.018482801
C88: VEGA | D88: VEGA tooling | E88: Angie Huang | F88: Daisy Cai | G88: MD | J88: Tooling | K88: MoDi | L88: T2 | M88: CFU T2 | N88: NVT | O88: 45017 | P88: 45566 | Q88: 39733460 | R88: RMB | S88: =IF(R88="RMB",Q88/$B$6,IF(R88="GBP",Q88,Q88/$B$5)) -> 4319915.5 | U88: 0.1792 | V88: =IF(R88="RMB",U88/$B$6,IF(R88="GBP",U88,U88/$B$5)) -> 0.019483047
C89: Kuma E Max | D89: Kuma E Max Tooling | E89: Lyn Wu | F89: Richard Yang | G89: RCS | H89: Vuse device(ROW) | I89: CN | J89: Tooling | K89: RCS | L89: T2 | M89: Smoore T2 | N89: NVT
P98: `

Sheet Volume
C2: Investment/Liabilities Dashboard
C3: New Categories - Vapour
A5: USD-GBP | B5: 1.27818
A6: RMB-GBP | B6: 9.19774 | C6: 0.025813404 | S6: SC update
B7: Prpcurement/Finance | E7: Actual Shipment Qty | T7: Forecast (pls link tab'Summary') | AH7: BAT Demand Waterfall
A9: # | B9: Unique Ref Number | C9: Project | D9: Project Description | E9: Y2021 | F9: Y2022 | G9: Y2023 | H9: 45292 | I9: 45323 | J9: 45352 | K9: 45383 | L9: 45413 | M9: 45444 | N9: 45474 | O9: 45505 | P9: 45536 | Q9: 45566 | R9: 45597 | S9: 45627 | T9: 45658 | U9: 45689 | V9: 45717 | W9: 45748 | X9: 45778 | Y9: 45809 | Z9: 45839 | AA9: 45870 | AB9: 45901 | AC9: 45931 | AD9: 45962 | AE9: 45992 | AF9: YTG 2025 | AH9: T2 Product | AI9: Version | AJ9: Customer | AK9: SOP Date | AL9: Product | AM9: 2021 | AN9: 2022 | AO9: 2023 | AP9: 2024 | AQ9: 44197 | AR9: 44228 | AS9: 44256 | AT9: 44287 | AU9: 44317 | AV9: 44348 | AW9: 44378 | AX9: 44409 | AY9: 44440 | AZ9: 44470 | BA9: 44501 | BB9: 44531 | BD9: 44562 | BE9: 44593 | BF9: 44621 | BG9: 44652 | BH9: 44682 | BI9: 44713 | BJ9: 44743 | BK9: 44774 | BL9: 44805 | BM9: 44835 | BN9: 44866 | BO9: 44896 | BP9: 44927 | BQ9: 44958 | BR9: 44986 | BS9: 45017 | BT9: 45047 | BU9: 45078 | BV9: 45108 | BW9: 45139 | BX9: 45170 | BY9: 45200 | BZ9: 45231 | CA9: 45261 | CB9: 45292 | CC9: 45323 | CD9: 45352 | CE9: 45383 | CF9: 45413 | CG9: 45444 | CH9: 45474 | CI9: 45505 | CJ9: 45536 | CK9: 45566 | CL9: 45597 | CM9: 45627 | CN9: 45658 | CO9: 45689 | CP9: 45717 | CQ9: 45748 | CR9: 45778 | CS9: 45809 | CT9: 45839 | CU9: 45870 | CV9: 45901 | CW9: 45931 | CX9: 45962 | CY9: 45992
A10: 1 | B10: RF001_Alto &ePod | C10: Alto & ePod | D10: APA - Automation Production Agreement | E10: 523716080 | F10: 471530346 | G10: 404870290 | H10: 34094250 | I10: 27982380 | J10: 35881250 | K10: 33715264 | L10: 49761762 | M10: 49968522 | N10: 46294918 | O10: 57860634 | P10: 36903554 | Q10: 32308514 | R10: 34612990 | S10: 28195840 | T10: =Volume!CN10+Volume!CN11+Volume!CN22+Volume!CN34+Volume!CN59+Volume!CN62 -> 48220474 | U10: =Volume!CO10+Volume!CO11+Volume!CO22+Volume!CO34+Volume!CO59+Volume!CO62 -> 24769050 | V10: =Volume!CP10+Volume!CP11+Volume!CP22+Volume!CP34+Volume!CP59+Volume!CP62 -> 67126382 | W10: =Volume!CQ10+Volume!CQ11+Volume!CQ22+Volume!CQ34+Volume!CQ59+Volume!CQ62 -> 61797920 | X10: =Volume!CR10+Volume!CR11+Volume!CR22+Volume!CR34+Volume!CR59+Volume!CR62 -> 42129688 | Y10: =Volume!CS10+Volume!CS11+Volume!CS22+Volume!CS34+Volume!CS59+Volume!CS62 -> 42064888 | Z10: =Volume!CT10+Volume!CT11+Volume!CT22+Volume!CT34+Volume!CT59+Volume!CT62 -> 45832074 | AA10: =Volume!CU10+Volume!CU11+Volume!CU22+Volume!CU34+Volume!CU59+Volume!CU62 -> 50460345 | ... AE10: =Volume!CY10+Volume!CY11+Volume!CY22+Volume!CY34+Volume!CY59+Volume!CY62 -> 46771803 | AF10: =SUM(V10:AE10) -> 4.9956899e+08 | AH10: epod2 pod | AI10: SOP01.0 | AJ10: BAT | AK10: 45698 | AL10: ePod2 Cartridges | AM10: 150444920 | AN10: 202559713 | AO10: 91785440 | AP10: 12656900 | AQ10: 9366300 | AR10: 5088060 | AS10: 10606320 | AT10: 9598860 | AU10: 14671980 | AV10: 14349580 | AW10: 12979220 | AX10: 15256580 | AY10: 15964420 | AZ10: 12569000 | BA10: 15497160 | BB10: 14497440 | BD10: 15559440 | BE10: 12012360 | BF10: 18465130 | BG10: 19798430 | BH10: 20944920 | BI10: 17632262 | BJ10: 15720521 | BK10: 13104480 | BL10: 29618660 | BM10: 11285460 | BN10: 13803750 | BO10: 14614300 | BP10: 8764100 | BQ10: 8606700 | BR10: 16334000 | BS10: 12069960 | BT10: 7439980 | BU10: 7699880 | BV10: 3856460 | BW10: 4664000 | BX10: 6591860 | BY10: 4137070 | BZ10: 7758370 | CA10: 3863060 | CB10: 4132280 | CC10: 2737600 | CD10: 3241380 | CE10: 839240 | CF10: 607680 | CG10: 543780 | CH10: 136620 | CI10: 20160 | CJ10: 20160 | CK10: 0 | CL10: 216720 | CM10: 161280 | CN10: 0 | CO10: 15120 | CP10: 20160 | CQ10: 65520 | CR10: 0 | CS10: 0 | CT10: 0 | CU10: 0 | CV10: 0 | CW10: 0 | CX10: 0 | CY10: 0
A11: 2 | B11: RF002_Alto | C11: Alto | D11: Addendum No.10 - Indonesia | F11: 195500900 | G11: 255515000 | H11: 22785000 | I11: 22092200 | J11: 25589000 | K11: 18498600 | L11: 30742700 | M11: 18494250 | N11: 25532300 | O11: 28932600 | P11: 11088600 | Q11: 14612550 | R11: 17543850 | S11: 18060400 | T11: =CN59+CN62 -> 29540200 | U11: =CO59+CO62 -> 15991900 | V11: =CP59+CP62 -> 46417950 | W11: =CQ59+CQ62 -> 39955200 | X11: =CR59+CR62 -> 25506950 | Y11: =CS59+CS62 -> 21583600 | Z11: =CT59+CT62 -> 27502550 | AA11: =CU59+CU62 -> 22651600 | ... AE11: =CY59+CY62 -> 25626000 | AF11: =SUM(V11:AE11) -> 276304400 | AH11: ePod 3 Pod | AI11: SOP01.0 | AJ11: BAT | AK11: 45698 | AL11: ePod3 Cartridges | AM11: 0 | AN11: 0 | AO11: 49538050 | AP11: 52288270 | BD11: 0 | BE11: 0 | BF11: 0 | BG11: 0 | BH11: 0 | BI11: 0 | BJ11: 0 | BK11: 0 | BL11: 0 | BM11: 0 | BN11: 0 | BO11: 0 | BP11: 0 | BQ11: 0 | BR11: 136620 | BS11: 1201500 | BT11: 2856870 | BU11: 5365530 | BV11: 6736500 | BW11: 6646410 | BX11: 9393120 | BY11: 8034750 | BZ11: 6721830 | CA11: 2444920 | CB11: 7133770 | CC11: 3013380 | CD11: 6978870 | CE11: 4888410 | CF11: 4624920 | CG11: 6254730 | CH11: 5871600 | CI11: 5959710 | CJ11: 5151780 | CK11: 2354220 | CL11: 56880 | CM11: 0 | CN11: 196560 | CO11: 0 | CP11: 0 | CQ11: 0 | CR11: 0 | CS11: 0 | CT11: 0 | CU11: 0 | CV11: 0 | CW11: 0 | CX11: 0 | CY11: 0
A12: 4 | B12: RF003_Alto | C12: Alto | D12: Alto Pod Investment fee for Inkjet printing | AF12: =SUM(V12:AE12) -> 0 | AH12: Hestia 1.0 | AI12: SOP01.0 | AJ12: BAT | AK12: 45698 | AL12: Hestia | AM12: 0 | AN12: 0 | AO12: 0 | AP12: 119534880 | BD12: 0 | BE12: 0 | BF12: 0 | BG12: 0 | BH12: 0 | BI12: 0 | BJ12: 0 | BK12: 0 | BL12: 0 | BM12: 0 | BN12: 0 | BO12: 0 | BP12: 0 | BQ12: 0 | BR12: 0 | BS12: 0 | BT12: 0 | BU12: 0 | BV12: 0 | BW12: 0 | BX12: 0 | BY12: 0 | BZ12: 0 | CA12: 0 | CB12: 0 | CC12: 0 | CD12: 0 | CE12: 4141170 | CF12: 10303470 | CG12: 18112860 | CH12: 12666060 | CI12: 17188320 | CJ12: 15151590 | CK12: 12838860 | CL12: 13199850 | CM12: 15932700 | CN12: 17350470 | CO12: 7948260 | CP12: 19106540 | CQ12: 20397590 | CR12: 14871760 | CS12: 18739530 | CT12: 17118810 | CU12: 26215830 | CV12: 23149370 | CW12: 21619420 | CX12: 27275260 | CY12: 19757020
A13: 5 | B13: RF004_Alto | C13: Alto | D13: Device to Indo Equipment move cost | I13: 816200 | J13: 663600 | K13: 138600 | L13: 662000 | M13: 213750 | N13: 845900 | O13: 950400 | P13: 1489800 | Q13: 1329750 | R13: 886650 | S13: 1550250 | T13: =Volume!CN57+Volume!CN58 -> 1243800 | U13: =Volume!CO57+Volume!CO58 -> 898800 | V13: =Volume!CP57+Volume!CP58 -> 924150 | W13: =Volume!CQ57+Volume!CQ58 -> 466200 | X13: =Volume!CR57+Volume!CR58 -> 1068350 | Y13: =Volume!CS57+Volume!CS58 -> 721000 | Z13: =Volume!CT57+Volume!CT58 -> 869750 | AA13: =Volume!CU57+Volume!CU58 -> 750400 | ... AE13: =Volume!CY57+Volume!CY58 -> 802200 | AF13: =SUM(V13:AE13) -> 8017400 | AH13: Hestia 1.1 | AI13: SOP01.0 | AJ13: BAT | AK13: 45698 | AL13: Hestia 1.1 | AM13: 0 | AN13: 0 | AO13: 0 | AP13: 0 | CB13: 0 | CC13: 0 | CD13: 0 | CE13: 0 | CF13: 0 | CG13: 0 | CH13: 0 | CI13: 0 | CJ13: 0 | CK13: 0 | CL13: 0 | CM13: 0 | CN13: 0 | CO13: 0 | CP13: 0 | CQ13: 0 | CR13: 0 | CS13: 0 | CT13: 0 | CU13: 0 | CV13: 0 | CW13: 0 | CX13: 0 | CY13: 0
A14: 6 | B14: RF005_Alto | C14: Alto | D14: Alto Blister Reduction Capex | R14: 16056000 | S14: 13005000 | T14: 30684600 | U14: 16846200 | V14: =Volume!CP59*98% -> 45442551 | W14: =Volume!CQ59*98% -> 39156096 | X14: =Volume!CR59*98% -> 24996811 | Y14: =Volume!CS59*98% -> 21151928 | Z14: =Volume!CT59*98% -> 26787859 | AA14: =Volume!CU59*98% -> 22033928 | AB14: =Volume!CV59*98% -> 20502139 | AC14: =Volume!CW59*98% -> 24815952 | ... AE14: =Volume!CY59*98% -> 24784200 | AF14: =SUM(V14:AE14) -> 269216584 | AH14: Hestia 1.1 Premium | AI14: SOP01.0 | AJ14: BAT | AK14: 45698 | AL14: Hestia 1.1 Premium | AM14: 0 | AN14: 0 | AO14: 0 | AP14: 0 | CB14: 0 | CC14: 0 | CD14: 0 | CE14: 0 | CF14: 0 | CG14: 0 | CH14: 0 | CI14: 0 | CJ14: 0 | CK14: 0 | CL14: 0 | CM14: 0 | CN14: 0 | CO14: 29970 | CP14: 576000 | CQ14: 811150 | CR14: 1104660 | CS14: 817540 | CT14: 476460 | CU14: 606300 | CV14: 610230 | CW14: 481710 | CX14: 582030 | CY14: 613260
A15: 7 | B15: RF006_Alto | C15: Prismatic Pod | D15: Prismastic China project capex | AF15: =SUM(V15:AE15) -> 0 | AH15: KUMA E-Box ROW | AI15: SOP01.0 | AJ15: BAT | AK15: 45698 | AL15: Kuma 1K | AM15: 0 | AN15: 0 | AO15: 0 | AP15: 4452220 | BD15: 0 | BE15: 0 | BF15: 0 | BG15: 0 | BH15: 0 | BI15: 0 | BJ15: 0 | BK15: 0 | BL15: 0 | BM15: 0 | BN15: 0 | BO15: 0 | BP15: 0 | BQ15: 0 | BR15: 0 | BS15: 0 | BT15: 0 | BU15: 0 | BV15: 0 | BW15: 0 | BX15: 0 | BY15: 0 | BZ15: 0 | CA15: 0 | CB15: 0 | CC15: 0 | CD15: 0 | CE15: 146304 | CF15: 793652 | CG15: 1209610 | CH15: 417742 | CI15: 338164 | CJ15: 665900 | CK15: 479376 | CL15: 184320 | CM15: 217152 | CN15: 522432 | CO15: 149760 | CP15: 207792 | CQ15: 87840 | CR15: 66240 | CS15: 111600 | CT15: 65520 | CU15: 60480 | CV15: 40320 | CW15: 40320 | CX15: 65520 | CY15: 35280
A16: 8 | B16: RF007_Epod&Modi | C16: Epod&Modi | D16: Tax Stamp(Pod2+ePod3 Czech,Germany,Poland&Italy) | G16: 25920 | H16: 322380 | I16: 336240 | J16: 1478340 | K16: 229680 | L16: 1008810 | M16: 993150 | O16: 36540 | P16: 178380 | Q16: 5040 | T16: 0 | U16: 0 | V16: 0 | W16: 0 | X16: 0 | Y16: 0 | Z16: 0 | AA16: 0 | AB16: 0 | AC16: 0 | AD16: 0 | AE16: 0 | AF16: =SUM(V16:AE16) -> 0 | AH16: KUMA E-Box NZ | AI16: SOP01.0 | AJ16: BAT | AK16: 45698 | AL16: Kuma 950 | AM16: 0 | AN16: 0 | AO16: 0 | AP16: 622560 | BD16: 0 | BE16: 0 | BF16: 0 | BG16: 0 | BH16: 0 | BI16: 0 | BJ16: 0 | BK16: 0 | BL16: 0 | BM16: 0 | BN16: 0 | BO16: 0 | BP16: 0 | BQ16: 0 | BR16: 0 | BS16: 0 | BT16: 0 | BU16: 0 | BV16: 0 | BW16: 0 | BX16: 0 | BY16: 0 | BZ16: 0 | CA16: 0 | CB16: 0 | CC16: 150000 | CD16: 115200 | CE16: 24000 | CF16: 0 | CG16: 222480 | CH16: 45360 | CI16: 65520 | CJ16: 0 | CK16: 0 | CL16: 0 | CM16: 0 | CN16: 0 | CO16: 0 | CP16: 0 | CQ16: 0 | CR16: 0 | CS16: 0 | CT16: 0 | CU16: 0 | CV16: 0 | CW16: 0 | CX16: 0 | CY16: 0
A17: 9 | B17: RF008_Modi2.0 | C17: Modi 2.0 | D17: Automation Flexible Line for Modi 2.0 Platform 1K PEN Default/Full and 1k BOX Full | P17: 705120 | Q17: 8166540 | R17: 7083240 | S17: 2347320 | T17: =Volume!CN44+Volume!CN45+Volume!CN46 -> 3342680 | U17: =Volume!CO44+Volume!CO45+Volume!CO46 -> 2225760 | V17: =Volume!CP44+Volume!CP45+Volume!CP46 -> 5941992 | W17: =Volume!CQ44+Volume!CQ45+Volume!CQ46 -> 5851740 | X17: =Volume!CR44+Volume!CR45+Volume!CR46 -> 3951300 | Y17: =Volume!CS44+Volume!CS45+Volume!CS46 -> 4293600 | Z17: =Volume!CT44+Volume!CT45+Volume!CT46 -> 3621000 | AA17: =Volume!CU44+Volume!CU45+Volume!CU46 -> 5416620 | ... AE17: =Volume!CY44+Volume!CY45+Volume!CY46 -> 5507580 | AF17: =SUM(V17:AE17) -> 53381412 | AH17: Kuma Box 2.0 | AI17: SOP01.0 | AJ17: BAT | AK17: 45698 | AL17: Kuma Box 2.0 | AP17: 0 | CB17: 0 | CC17: 0 | CD17: 0 | CE17: 0 | CF17: 0 | CG17: 0 | CH17: 0 | CI17: 0 | CJ17: 0 | CK17: 0 | CL17: 0 | CM17: 0 | CN17: 0 | CO17: 0 | CP17: 0 | CQ17: 155360 | CR17: 294600 | CS17: 250560 | CT17: 142560 | CU17: 289405.95 | CV17: 173563.25 | CW17: 172374.76 | CX17: 244507.11 | CY17: 191572.99
A18: 10 | B18: RF009_Hestia1.0 | C18: Hestia 1.0 | D18: Hestia 1.0 Automation Lines Modification (Modified from ePod3 to Hestia1.0) (1-4 line) | K18: 4374450 | L18: 10070190 | M18: 20708100 | N18: 10070820 | O18: 17188320 | P18: 15151590 | Q18: 12838860 | R18: 15197040 | S18: 8947260 | T18: =Volume!CN12 -> 17350470 | U18: =Volume!CO12 -> 7948260 | V18: =Volume!CP12 -> 19106540 | W18: =Volume!CQ12 -> 20397590 | X18: =Volume!CR12 -> 14871760 | Y18: =Volume!CS12 -> 18739530 | Z18: =Volume!CT12 -> 17118810 | AA18: =Volume!CU12 -> 26215830 | ... AE18: =Volume!CY12 -> 19757020 | AF18: =SUM(V18:AE18) -> 208251130 | AH18: KUMA E-Pen 1.0 ROW | AI18: SOP01.0 | AJ18: BAT | AK18: 45698 | AL18: Kuma Pen 1K | AM18: 0 | AN18: 0 | AO18: 0 | AP18: 1741320 | BD18: 0 | BE18: 0 | BF18: 0 | BG18: 0 | BH18: 0 | BI18: 0 | BJ18: 0 | BK18: 0 | BL18: 0 | BM18: 0 | BN18: 0 | BO18: 0 | BP18: 0 | BQ18: 0 | BR18: 0 | BS18: 0 | BT18: 0 | BU18: 0 | BV18: 0 | BW18: 0 | BX18: 0 | BY18: 0 | BZ18: 0 | CA18: 0 | CB18: 0 | CC18: 0 | CD18: 0 | CE18: 0 | CF18: 0 | CG18: 0 | CH18: 39600 | CI18: 31860 | CJ18: 532440 | CK18: 709740 | CL18: 275220 | CM18: 152460 | CN18: 0 | CO18: 0 | CP18: 0 | CQ18: 0 | CR18: 0 | CS18: 0 | CT18: 0 | CU18: 0 | CV18: 0 | CW18: 0 | CX18: 0 | CY18: 0
A19: 11 | B19: RF010_Hestia1.0 | C19: Hestia 1.0 | D19: Hestia1.0 Manual line capex | AF19: =SUM(V19:AE19) -> 0 | AH19: Kuma Pen 2.0 | AI19: SOP01.0 | AJ19: BAT | AK19: 45698 | AL19: Kuma Pen 2.0 | AM19: 0 | AN19: 0 | AO19: 0 | AP19: 107460 | BD19: 0 | BE19: 0 | BF19: 0 | BG19: 0 | BH19: 0 | BI19: 0 | BJ19: 0 | BK19: 0 | BL19: 0 | BM19: 0 | BN19: 0 | BO19: 0 | BP19: 0 | BQ19: 0 | BR19: 0 | BS19: 0 | BT19: 0 | BU19: 0 | BV19: 0 | BW19: 0 | BX19: 0 | BY19: 0 | BZ19: 0 | CA19: 0 | CB19: 0 | CC19: 0 | CD19: 0 | CE19: 0 | CF19: 0 | CG19: 0 | CH19: 0 | CI19: 0 | CJ19: 0 | CK19: 0 | CL19: 50040 | CM19: 57420 | CN19: 25200 | CO19: 440 | CP19: 171720 | CQ19: 208800 | CR19: 170818 | CS19: 382597.62 | CT19: 356973.74 | CU19: 489469.07 | CV19: 481795.02 | CW19: 459653.18 | CX19: 540842.01 | CY19: 405790.38
A20: 12 | B20: RF011_ePod2Pod | C20: ePod2 Pod | D20: ePod Packer - Included in Hestia | E20: 845920 | F20: 72773897 | G20: 63660929 | H20: 5439052 | I20: 806095 | J20: 321239 | K20: 481119 | L20: 497616 | M20: 40638 | T20: 0 | AF20: =SUM(V20:AE20) -> 0 | AH20: KUMA E-Pen 1.0 ROW | AI20: SOP01.0 | AJ20: BAT | AK20: 45698 | AL20: Kuma Pen 950 | AM20: 0 | AN20: 0 | AO20: 0 | AP20: 3020760 | BD20: 0 | BE20: 0 | BF20: 0 | BG20: 0 | BH20: 0 | BI20: 0 | BJ20: 0 | BK20: 0 | BL20: 0 | BM20: 0 | BN20: 0 | BO20: 0 | BP20: 0 | BQ20: 0 | BR20: 0 | BS20: 0 | BT20: 0 | BU20: 0 | BV20: 0 | BW20: 0 | BX20: 0 | BY20: 0 | BZ20: 0 | CA20: 0 | CB20: 0 | CC20: 0 | CD20: 0 | CE20: 0 | CF20: 0 | CG20: 0 | CH20: 0 | CI20: 862920 | CJ20: 623880 | CK20: 567720 | CL20: 660240 | CM20: 306000 | CN20: 574020 | CO20: 633600 | CP20: 626220 | CQ20: 116460 | CR20: 114660 | CS20: 179460 | CT20: 169200 | CU20: 147260 | CV20: 143160 | CW20: 128580 | CX20: 116680 | CY20: 142880
A21: 13 | B21: RF012_ePod3Pod | C21: ePod3 Pod | D21: ePod 3 Automation Modification Capex Amortization (1P) Modified from ePod2 to ePod3 | G21: 12285257 | H21: 1074798 | I21: 65733 | J21: 894985 | K21: 906260 | L21: 1097616 | M21: 617546 | N21: 612910 | O21: 277678 | P21: 193824 | AF21: =SUM(V21:AE21) -> 0 | AI21: SOP01.0 | AJ21: BAT | AK21: 45698 | AL21: Kuma Pen NZ | AP21: 0 | CB21: 0 | CC21: 0 | CD21: 0 | CE21: 0 | CF21: 0 | CG21: 0 | CH21: 0 | CI21: 0 | CJ21: 0 | CK21: 0 | CL21: 0 | CM21: 0 | CN21: 0 | CO21: 0 | CP21: 0 | CQ21: 0 | CR21: 0 | CS21: 0 | CT21: 0 | CU21: 0 | CV21: 0 | CW21: 0 | CX21: 0 | CY21: 0
A22: 14 | B22: RF013_Kuma | C22: Kuma 1.0 | D22: KUMA E-ROW Ultra Sonic Machine | K22: 146304 | L22: 793652 | M22: 1209610 | N22: 417742 | O22: 338164 | P22: 665900 | Q22: 479376 | R22: 160272 | S22: 139680 | T22: =Volume!CN15 -> 522432 | U22: =Volume!CO15 -> 149760 | V22: =Volume!CP15 -> 207792 | W22: =Volume!CQ15 -> 87840 | X22: =Volume!CR15 -> 66240 | Y22: =Volume!CS15 -> 111600 | Z22: =Volume!CT15 -> 65520 | AA22: =Volume!CU15 -> 60480 | ... AE22: =Volume!CY15 -> 35280 | AF22: =SUM(V22:AE22) -> 780912 | AH22: Hestia total（include Kuma） | AI22: SOP01.0 | AJ22: BAT | AK22: 45698 | AL22: Hestia total（include Kuma） | AM22: 0 | AN22: 0 | AO22: 0 | AP22: 128856640 | AQ22: 0 | AR22: 0 | AS22: 0 | AT22: 0 | AU22: 0 | AV22: 0 | AW22: 0 | AX22: 0 | AY22: 0 | AZ22: 0 | BA22: 0 | BB22: 0 | BD22: 0 | BE22: 0 | BF22: 0 | BG22: 0 | BH22: 0 | BI22: 0 | BJ22: 0 | BK22: 0 | BL22: 0 | BM22: 0 | BN22: 0 | BO22: 0 | BP22: 0 | BQ22: 0 | BR22: 0 | BS22: 0 | BT22: 0 | BU22: 0 | BV22: 0 | BW22: 0 | BX22: 0 | BY22: 0 | BZ22: 0 | CA22: 0 | CB22: 0 | CC22: 0 | CD22: 0 | CE22: 4287474 | CF22: 11097122 | CG22: 19322470 | CH22: 13123402 | CI22: 18421264 | CJ22: 16973810 | CK22: 14595696 | CL22: 14369670 | CM22: 16665732 | CN22: 18472122 | CO22: 8762030 | CP22: 20688272 | CQ22: 21777200 | CR22: 16622738 | CS22: 20481288 | CT22: 18329524 | CU22: 27808745 | CV22: 24598438 | CW22: 22902058 | CX22: 28824839 | CY22: 21145803
A23: 15 | B23: RF014_Kuma | C23: Kuma 1.0 | D23: KUMA E-Pen Laser welding machine & Kuma E-Pen 1.0 air tightness test machine | N23: 39600 | O23: 894780 | P23: 1156320 | Q23: 1277460 | R23: 950580 | S23: 453600 | T23: =Volume!CN18+Volume!CN20 -> 574020 | U23: =Volume!CO18+Volume!CO20 -> 633600 | V23: =Volume!CP18+Volume!CP20 -> 626220 | W23: =Volume!CQ18+Volume!CQ20 -> 116460 | X23: =Volume!CR18+Volume!CR20 -> 114660 | Y23: =Volume!CS18+Volume!CS20 -> 179460 | Z23: =Volume!CT18+Volume!CT20 -> 169200 | AA23: =Volume!CU18+Volume!CU20 -> 147260 | ... AE23: =Volume!CY18+Volume!CY20 -> 142880 | AF23: =SUM(V23:AE23) -> 1884560 | AH23: Mimosa | AI23: SOP01.0 | AJ23: BAT | AK23: 45698 | AL23: Mimosa | AM23: 0 | AN23: 0 | AO23: 0 | AP23: 0 | BD23: 0 | BE23: 0 | BF23: 0 | BG23: 0 | BH23: 0 | BI23: 0 | BJ23: 0 | BK23: 0 | BL23: 0 | BM23: 0 | BN23: 0 | BO23: 0 | BP23: 0 | BQ23: 0 | BR23: 0 | BS23: 0 | BT23: 0 | BU23: 0 | BV23: 0 | BW23: 0 | BX23: 0 | BY23: 0 | BZ23: 0 | CA23: 0 | CB23: 0 | CC23: 0 | CD23: 0 | CE23: 0 | CF23: 0 | CG23: 0 | CH23: 0 | CI23: 0 | CJ23: 0 | CK23: 0 | CL23: 0 | CM23: 0 | CN23: 0 | CO23: 3744 | CP23: 72000 | CQ23: 153000 | CR23: 99000 | CS23: 18000 | CT23: 36336 | CU23: 56016 | CV23: 38736 | CW23: 46032 | CX23: 44928 | CY23: 43776
A24: 16 | B24: RF015_Modi&RCS | C24: Modi & RCS | D24: CCD&Tax Stamp Machine MD2.0 1K PEN Default Czech/Germany/Poland/Italy/BUL (Machines can be cross-used by both Modi & RCS) | P24: 36060 | Q24: 4722360 | R24: 3286440 | S24: 398760 | T24: 1150380 | U24: 231420 | V24: 1771920 | W24: 3593400 | X24: 1748640 | Y24: 752880 | Z24: 1156800 | AA24: 1870560 | AB24: 1795920 | AC24: 2130480 | AD24: 3526800 | AE24: 2150400 | AF24: =SUM(V24:AE24) -> 20497800 | AH24: ePod 2 Device(Wave 1) | AI24: SOP01.0 | AJ24: BAT | AK24: 45698 | AL24: ePod2 | AM24: 6919526 | AN24: 6734445 | AO24: 973700 | AP24: 301000 | AQ24: 355400 | AR24: 376900 | AS24: 329800 | AT24: 514000 | AU24: 392100 | AV24: 672345 | AW24: 790600 | AX24: 581700 | AY24: 493100 | AZ24: 766581 | BA24: 791000 | BB24: 856000 | BD24: 617400 | BE24: 565400 | BF24: 918400 | BG24: 1007400 | BH24: 723600 | BI24: 752700 | BJ24: 589200 | BK24: 591300 | BL24: 636055 | BM24: 45000 | BN24: 163790 | BO24: 124200 | BP24: 95000 | BQ24: 309300 | BR24: 98600 | BS24: 18000 | BT24: 41000 | BU24: 16000 | BV24: 30000 | BW24: 43800 | BX24: 72900 | BY24: 75600 | BZ24: 48400 | CA24: 125100 | CB24: 19300 | CC24: 72900 | CD24: 30200 | CE24: 21700 | CF24: 24900 | CG24: 19800 | CH24: 0 | CI24: 0 | CJ24: 0 | CK24: 69000 | CL24: 43200 | CM24: 0 | CN24: 0 | CO24: 0 | CP24: 0 | CQ24: 0 | CR24: 0 | CS24: 0 | CT24: 0 | CU24: 0 | CV24: 0 | CW24: 0 | CX24: 0 | CY24: 0
A25: 17 | B25: RF016_Sensa | C25: Sensa | D25: Sensa Manual Line Capex | AF25: =SUM(V25:AE25) -> 0 | AI25: SOP12.1 | AJ25: BAT | AK25: 0 | AL25: ePod2 | AM25: 6503406 | AN25: 7074939 | AO25: 0 | AP25: 0 | AQ25: 355400 | AR25: 376900 | AS25: 329800 | AT25: 514000 | AU25: 392100 | AV25: 672345 | AW25: 790600 | AX25: 581700 | AY25: 493100 | AZ25: 766581 | BA25: 695680 | BB25: 535200 | BD25: 845094 | BE25: 464000 | BF25: 918400 | BG25: 1206700 | BH25: 786300 | BI25: 752700 | BJ25: 589200 | BK25: 543500 | BL25: 636055 | BM25: 45000 | BN25: 163790 | BO25: 124200 | BP25: 0 | BQ25: 0 | BR25: 0 | BS25: 0 | BT25: 0 | BU25: 0 | BV25: 0 | BW25: 0 | BX25: 0 | BY25: 0 | BZ25: 0 | CA25: 0 | CB25: 0 | CC25: 0 | CD25: 0 | CE25: 0 | CF25: 0 | CG25: 0 | CH25: 0 | CI25: 0 | CJ25: 0 | CK25: 0 | CL25: 0 | CM25: 0 | CN25: 0 | CO25: 0 | CP25: 0 | CQ25: 0 | CR25: 0 | CS25: 0 | CT25: 0 | CU25: 0 | CV25: 0 | CW25: 0 | CX25: 0 | CY25: 0
A26: 18 | B26: RF017_Sensa | C26: Sensa | D26: Sensa Semi-Auto Line Capex | AF26: =SUM(V26:AE26) -> 0 | AI26: 0 | AJ26: BAT | AK26: 0 | AL26: ePod2 | AM26: 6503406 | AN26: 6529023 | AO26: 0 | AP26: 0 | AQ26: 355400 | AR26: 376900 | AS26: 329800 | AT26: 514000 | AU26: 392100 | AV26: 672345 | AW26: 790600 | AX26: 581700 | AY26: 493100 | AZ26: 766581 | BA26: 695680 | BB26: 535200 | BD26: 845094 | BE26: 464000 | BF26: 884050 | BG26: 1206700 | BH26: 484575 | BI26: 935984 | BJ26: 432680 | BK26: 306895 | BL26: 636055 | BM26: 45000 | BN26: 163790 | BO26: 124200 | BP26: 0 | BQ26: 0 | BR26: 0 | BS26: 0 | BT26: 0 | BU26: 0 | BV26: 0 | BW26: 0 | BX26: 0 | BY26: 0 | BZ26: 0 | CA26: 0 | CB26: 0 | CC26: 0 | CD26: 0 | CE26: 0 | CF26: 0 | CG26: 0 | CH26: 0 | CI26: 0 | CJ26: 0 | CK26: 0 | CL26: 0 | CM26: 0 | CN26: 0 | CO26: 0 | CP26: 0 | CQ26: 0 | CR26: 0 | CS26: 0 | CT26: 0 | CU26: 0 | CV26: 0 | CW26: 0 | CX26: 0 | CY26: 0
A27: 19 | B27: RF018_Modi | C27: Modi | D27: T&T longterm solution cost Amortize at Uzbekistan TX500 and DP1500（UZB—乌兹别克斯坦） | G27: 549000 | H27: 3000 | T27: 0 | U27: 0 | V27: 0 | W27: 0 | X27: 0 | Y27: 0 | Z27: 0 | AA27: 0 | AB27: 0 | AC27: 0 | AD27: 0 | AE27: 0 | AF27: =SUM(V27:AE27) -> 0 | AI27: 0 | AJ27: BAT | AK27: SOP7-2022/8/2 | AL27: ETMI | AM27: 45200 | AN27: 21040 | AO27: 32160 | AP27: 0 | AR27: 17760 | AT27: 14320 | AV27: 4400 | AW27: 8720 | BD27: 6000 | BF27: 3000 | BG27: 0 | BH27: 4000 | BI27: 0 | BJ27: 5040 | BK27: 3000 | BL27: 0 | BM27: 0 | BN27: 0 | BO27: 0 | BP27: 0 | BQ27: 3000 | BR27: 5040 | BS27: 0 | BT27: 3000 | BU27: 5040 | BV27: 0 | BW27: 0 | BX27: 8040 | BY27: 0 | BZ27: 0 | CA27: 8040
A28: 20 | B28: RF019_Modi | C28: Modi | D28: KZ MODI testing / support for T&T Amortize at KAZ TX500 and DP1500（KZ—哈萨克斯坦） | T28: 0 | U28: 0 | V28: 0 | W28: 0 | X28: 0 | Y28: 0 | Z28: 0 | AA28: 0 | AB28: 0 | AC28: 0 | AD28: 0 | AE28: 0 | AF28: =SUM(V28:AE28) -> 0 | AI28: SOP7-2022/8/2 | AJ28: BAT | AK28: 44805 | AL28: Atomiser | AM28: 511000 | AN28: 40500 | AO28: 0 | AP28: 0 | AR28: 181500 | AT28: 77000 | AV28: 85000 | AW28: 167500 | BD28: 3000 | BF28: 0 | BG28: 0 | BI28: 0 | BJ28: 12500 | BK28: 0 | BL28: 0 | BM28: 12500 | BN28: 12500
A29: 21 | B29: RF020_Modi | C29: Modi | D29: T&T Interim programme of Azerbaijan Amortize at Azerbaijan 1k/3k/5k product（AZB—阿塞拜疆） | T29: 0 | U29: 4680 | V29: 72000 | W29: 0 | X29: 0 | Y29: 0 | Z29: 0 | AA29: 0 | AB29: 0 | AC29: 0 | AD29: 0 | AE29: 0 | AF29: =SUM(V29:AE29) -> 72000 | AI29: 44805 | AJ29: BAT | AK29: SOP10-12/6 236M | AL29: ePod2+ | AM29: 0 | AN29: 1724245.5 | AO29: 650254.5 | AP29: 0 | BD29: 135000 | BE29: 135000 | BF29: 136696.5 | BG29: 108378 | BH29: 181110 | BI29: 121848 | BJ29: 156642 | BK29: 131443.5 | BL29: 186801 | BM29: 203887.5 | BN29: 157320 | BO29: 70119 | BP29: 75019.5 | BQ29: 79714.5 | BR29: 164461.5 | BS29: 165529.5 | BT29: 165529.5
A30: 22 | B30: RF021_Modi | C30: Modi | D30: T&T for Pre-Dispatch Advice --add extra function（UZB—乌兹别克斯坦 KZ—哈萨克斯坦） | T30: 0 | U30: 0 | V30: 0 | W30: 0 | X30: 0 | Y30: 0 | Z30: 0 | AA30: 0 | AB30: 0 | AC30: 0 | AD30: 0 | AE30: 0 | AF30: =SUM(V30:AE30) -> 0 | AI30: SOP10-12/6 236M | AJ30: BAT | AK30: 2023/1/31Core | AL30: ePod2+ | AM30: 0 | AN30: 1541050 | AO30: 235000 | AP30: 0 | BD30: 0 | BE30: 64549 | BF30: 127048 | BG30: 181303 | BH30: 24200 | BI30: 254800 | BJ30: 211000 | BK30: 214000 | BL30: 215000 | BM30: 81000 | BN30: 48150 | BO30: 120000 | BP30: 175000 | BQ30: 60000 | BR30: 0 | BS30: 0 | BT30: 0 | BU30: 0 | BV30: 0 | BW30: 0 | BX30: 0 | BY30: 0 | BZ30: 0 | CA30: 0
A31: 23 | B31: RF022_Modi | C31: Modi | D31: KZ MODI testing / support for T&T Amortize at BOX3K&5K KAZ&UZB market（KZ—哈萨克斯坦） | G31: 116160 | H31: 15840 | K31: 5400 | T31: 0 | U31: 0 | V31: 0 | W31: 0 | X31: 0 | Y31: 0 | Z31: 0 | AA31: 0 | AB31: 0 | AC31: 0 | AD31: 0 | AE31: 0 | AF31: =SUM(V31:AE31) -> 0 | AI31: SOP2 | AJ31: BAT | AK31: 2023/1/31-Core+Sensitivity | AL31: ePod2+ | AM31: 0 | AN31: 1650011 | AO31: 235000 | AP31: 0 | AQ31: 0 | AR31: 0 | AS31: 0 | AT31: 0 | AU31: 0 | AV31: 0 | AW31: 0 | AX31: 0 | AY31: 0 | AZ31: 0 | BA31: 0 | BB31: 0 | BD31: 0 | BE31: 80000 | BF31: 148648 | BG31: 181303 | BH31: 24200 | BI31: 326710 | BJ31: 211000 | BK31: 214000 | BL31: 215000 | BM31: 81000 | BN31: 48150 | BO31: 120000 | BP31: 175000 | BQ31: 60000 | BR31: 0 | BS31: 0 | BT31: 0 | BU31: 0 | BV31: 0 | BW31: 0 | BX31: 0 | BY31: 0 | BZ31: 0 | CA31: 0
A32: 24 | B32: RF023_Modi | C32: Modi | D32: AZB T&T longterm solution cost for TX500&DP1500&BOX1K&3K&5K for AZB Market（AZB—阿塞拜疆） | T32: 0 | U32: 4680 | V32: 72000 | W32: 0 | X32: 0 | Y32: 0 | Z32: 0 | AA32: 0 | AB32: 0 | AC32: 0 | AD32: 0 | AE32: 0 | AF32: =SUM(V32:AE32) -> 72000 | AI32: 2023/1/31-Core+Sensitivity | AJ32: BAT | AK32: 2023/1/31-PO+Production | AL32: ePod2+ | AM32: 0 | AN32: 1542297 | AO32: 235000 | AP32: 0 | BE32: 69349 | BF32: 148648 | BG32: 160000 | BH32: 20000 | BI32: 326710 | BJ32: 139440 | BK32: 214000 | BL32: 215000 | BM32: 81000 | BN32: 48150 | BO32: 120000 | BP32: 175000 | BQ32: 60000 | BR32: 0 | BS32: 0 | BT32: 0 | BU32: 0 | BV32: 0 | BW32: 0 | BX32: 0 | BY32: 0 | BZ32: 0 | CA32: 0
A33: 25 | B33: RF024_Modi | C33: Modi | D33: Custom development BAT CMO INEXTRACK GS1 Novarator removal CR for AZB regulation（AZB—阿塞拜疆） | T33: 0 | U33: 4680 | V33: 72000 | W33: 0 | X33: 0 | Y33: 0 | Z33: 0 | AA33: 0 | AB33: 0 | AC33: 0 | AD33: 0 | AE33: 0 | AF33: =SUM(V33:AE33) -> 72000 | AH33: ePod 3+ Device | AI33: SOP01.0 | AJ33: BAT | AK33: 45698 | AL33: ePod3+ | AM33: 0 | AN33: 0 | AO33: 283400 | AP33: 540400 | BD33: 0 | BE33: 0 | BF33: 0 | BG33: 0 | BH33: 0 | BI33: 0 | BJ33: 0 | BK33: 0 | BL33: 0 | BM33: 0 | BN33: 0 | BO33: 0 | BP33: 0 | BQ33: 0 | BR33: 0 | BS33: 0 | BT33: 61500 | BU33: 95000 | BV33: 0 | BW33: 0 | BX33: 54300 | BY33: 29900 | BZ33: 3600 | CA33: 39100 | CB33: 101800 | CC33: 40000 | CD33: 56600 | CE33: 163900 | CF33: 57700 | CG33: 37200 | CH33: 4000 | CI33: 12200 | CJ33: 38200 | CK33: 20800 | CL33: 0 | CM33: 8000 | CN33: 27600 | CO33: 17000 | CP33: 11000 | CQ33: 18200 | CR33: 14400 | CS33: 32400 | CT33: 12300 | CU33: 17300 | CV33: 28200 | CW33: 21100 | CX33: 24800 | CY33: 24800
A34: 27 | B34: RF025_Hestia1.1 | C34: Hestia 1.0 | D34: epod2 to Hestia1.1 non-smart | AF34: =SUM(V34:AE34) -> 0 | AH34: Epod Starter Kit | AI34: SOP01.0 | AJ34: BAT | AK34: 45698 | AL34: Starter Kit | AM34: 0 | AN34: 0 | AO34: 319800 | AP34: 617536 | BD34: 0 | BE34: 0 | BF34: 0 | BG34: 0 | BH34: 0 | BI34: 0 | BJ34: 0 | BK34: 0 | BL34: 0 | BM34: 0 | BN34: 0 | BO34: 0 | BP34: 0 | BQ34: 0 | BR34: 0 | BS34: 0 | BT34: 0 | BU34: 0 | BV34: 0 | BW34: 0 | BX34: 0 | BY34: 0 | BZ34: 110800 | CA34: 209000 | CB34: 43200 | CC34: 7200 | CD34: 10800 | CE34: 147920 | CF34: 44600 | CG34: 19440 | CH34: 295576 | CI34: 28640 | CJ34: 20160 | CK34: 0 | CL34: 0 | CM34: 0 | CN34: 11592 | CO34: 0 | CP34: 0 | CQ34: 0 | CR34: 0 | CS34: 0 | CT34: 0 | CU34: 0 | CV34: 0 | CW34: 0 | CX34: 0 | CY34: 0
A35: 26 | B35: RF026_Hestia1.1 | C35: Hestia 1.1 | D35: epod2 to Hestia1.1 smart | AF35: =SUM(V35:AE35) -> 0 | AH35: ePod 3 Device | AI35: SOP01.0 | AJ35: BAT | AK35: 45698 | AL35: ePod3 descope | AM35: 0 | AN35: 0 | AO35: 2085900 | AP35: 1135900 | BD35: 0 | BE35: 0 | BF35: 0 | BG35: 0 | BH35: 0 | BI35: 0 | BJ35: 0 | BK35: 0 | BL35: 0 | BM35: 0 | BN35: 0 | BO35: 0 | BP35: 0 | BQ35: 0 | BR35: 21600 | BS35: 227600 | BT35: 447400 | BU35: 285400 | BV35: 200900 | BW35: 353700 | BX35: 307000 | BY35: 121200 | BZ35: 77500 | CA35: 43600 | CB35: 46800 | CC35: 29400 | CD35: 229500 | CE35: 111600 | CF35: 154900 | CG35: 79300 | CH35: 21600 | CI35: 105200 | CJ35: 52400 | CK35: 91800 | CL35: 75600 | CM35: 137800 | CN35: 77900 | CO35: 36900 | CP35: 51000 | CQ35: 42100 | CR35: 32600 | CS35: 49400 | CT35: 40000 | CU35: 48800 | CV35: 48400 | CW35: 34700 | CX35: 23800 | CY35: 25200
A36: 28 | B36: RF027_Hestia1.0 | C36: Hestia 1.0 | D36: epod2 to Hestia1.0 (5th line) | AF36: =SUM(V36:AE36) -> 0 | AH36: TX500 | AI36: SOP12.1 | AJ36: BAT | AK36: 45635 | AL36: TX500 | AM36: 0 | AN36: 81177917 | AO36: 45566346 | AP36: 12000 | AQ36: 0 | AR36: 0 | AS36: 0 | AT36: 0 | AU36: 0 | AV36: 0 | AW36: 0 | AX36: 0 | AY36: 0 | AZ36: 0 | BA36: 0 | BB36: 0 | BD36: 0 | BE36: 0 | BF36: 0 | BG36: 932000 | BH36: 2904000 | BI36: 6345360 | BJ36: 12084000 | BK36: 12364000 | BL36: 14666000 | BM36: 7120798 | BN36: 16391759 | BO36: 8370000 | BP36: 7091800 | BQ36: 7861600 | BR36: 8626600 | BS36: 11847400 | BT36: 4344600 | BU36: 2568000 | BV36: 972000 | BW36: 905946 | BX36: 912200 | BY36: 252000 | BZ36: 48000 | CA36: 136200 | CB36: 12000 | CC36: 0 | CD36: 0 | CE36: 0 | CF36: 0 | CG36: 0 | CH36: 0 | CI36: 0 | CJ36: 0 | CK36: 0 | CL36: 0 | CM36: 0 | CN36: 0 | CO36: 0 | CP36: 0 | CQ36: 0 | CR36: 0 | CS36: 0 | CT36: 0 | CU36: 0 | CV36: 0 | CW36: 0 | CX36: 0 | CY36: 0
A37: 29 | B37: RF028_Kuma | C37: Kuma E 2.0 Pen | D37: semi-auto for Kuma E 2.0 Pen | T37: =CN19 -> 25200 | U37: =CO19 -> 440 | V37: =CP19 -> 171720 | W37: =CQ19 -> 208800 | X37: =CR19 -> 170818 | Y37: =CS19 -> 382597.62 | Z37: =CT19 -> 356973.74 | AA37: =CU19 -> 489469.07 | ... AE37: =CY19 -> 405790.38 | AF37: =SUM(V37:AE37) -> 3668459 | AI37: SOP12.1 | AJ37: BAT | AK37: 0 | AL37: TX500 | AM37: 0 | AN37: 81177917 | AO37: 0 | AP37: 0 | BG37: 932000 | BH37: 2904000 | BI37: 6345360 | BJ37: 12084000 | BK37: 12364000 | BL37: 14666000 | BM37: 7120798 | BN37: 16391759 | BO37: 8370000 | BP37: 0 | BQ37: 0 | BR37: 0 | BS37: 0 | BT37: 0 | BU37: 0 | BV37: 0 | BW37: 0 | BX37: 0 | BY37: 0 | BZ37: 0 | CA37: 0 | CB37: 0 | CC37: 0 | CD37: 0 | CE37: 0 | CF37: 0 | CG37: 0 | CH37: 0 | CI37: 0 | CJ37: 0 | CK37: 0 | CL37: 0 | CM37: 0 | CN37: 0 | CO37: 0 | CP37: 0 | CQ37: 0 | CR37: 0 | CS37: 0 | CT37: 0 | CU37: 0 | CV37: 0 | CW37: 0 | CX37: 0 | CY37: 0
A38: 30 | B38: RF029_Kuma | C38: Kuma E 2.0 Box | D38: semi-auto for Kuma E 2.0 Box | AF38: =SUM(V38:AE38) -> 0 | AI38: 0 | AJ38: BAT | AK38: 0 | AL38: TX500 | AM38: 0 | AN38: 78480075 | AO38: 0 | AP38: 0 | BF38: 0 | BG38: 932000 | BH38: 2904000 | BI38: 6344000 | BJ38: 10214553 | BK38: 11960620 | BL38: 14242345 | BM38: 7120798 | BN38: 16391759 | BO38: 8370000 | BP38: 0 | BQ38: 0 | BR38: 0 | BS38: 0 | BT38: 0 | BU38: 0 | BV38: 0 | BW38: 0 | BX38: 0 | BY38: 0 | BZ38: 0 | CA38: 0 | CB38: 0 | CC38: 0 | CD38: 0 | CE38: 0 | CF38: 0 | CG38: 0 | CH38: 0 | CI38: 0 | CJ38: 0 | CK38: 0 | CL38: 0 | CM38: 0 | CN38: 0 | CO38: 0 | CP38: 0 | CQ38: 0 | CR38: 0 | CS38: 0 | CT38: 0 | CU38: 0 | CV38: 0 | CW38: 0 | CX38: 0 | CY38: 0
A39: 31 | B39: RF030_Mimosa | C39: Mimosa | D39: semi-auto for Mimosa1.0 + 2 Glue Machine | T39: 0 | U39: 3744 | V39: 72000 | W39: 153000 | X39: 99000 | Y39: 18000 | Z39: 36336 | AA39: 56016 | AB39: 38736 | AC39: 46032 | AD39: 44928 | AE39: 43776 | AF39: =SUM(V39:AE39) -> 607824 | AH39: DP1500 | AI39: 0 | AJ39: BAT | AK39: 45635 | AL39: DP1500 | AM39: 0 | AN39: 5012030 | AO39: 13033000 | AP39: 3795000 | AQ39: 0 | AR39: 0 | AS39: 0 | AT39: 0 | AU39: 0 | AV39: 0 | AW39: 0 | AX39: 0 | AY39: 0 | AZ39: 0 | BA39: 0 | BB39: 0 | BD39: 0 | BE39: 0 | BF39: 0 | BG39: 0 | BH39: 0 | BI39: 0 | BJ39: 0 | BK39: 0 | BL39: 0 | BM39: 0 | BN39: 1812030 | BO39: 3200000 | BP39: 1984000 | BQ39: 576000 | BR39: 1716000 | BS39: 1409000 | BT39: 636000 | BU39: 1406600 | BV39: 1608000 | BW39: 840000 | BX39: 1418400 | BY39: 647000 | BZ39: 420000 | CA39: 372000 | CB39: 204000 | CC39: 279000 | CD39: 324000 | CE39: 984000 | CF39: 276000 | CG39: 862000 | CH39: 60000 | CI39: 264000 | CJ39: 242000 | CK39: 180000 | CL39: 24000 | CM39: 96000 | CN39: 96000 | CO39: 0 | CP39: 0 | CQ39: 0 | CR39: 0 | CS39: 0 | CT39: 0 | CU39: 0 | CV39: 0 | CW39: 0 | CX39: 0 | CY39: 0
A40: 32 | B40: RF031_Hestia1.0 | C40: Hestia 1.0 | D40: Tax stamp and CCD capex amortization | R40: 252540 | S40: 208440 | T40: 2761020 | U40: 2766600 | V40: 3869820 | W40: =1762020+2693340 -> 4455360 | X40: 2013300 | Y40: 2991600 | Z40: 2957040 | AA40: 3942180 | AB40: 3335760 | AC40: 3791340 | AD40: 5151240 | AE40: 3408300 | AF40: =SUM(V40:AE40) -> 35915940 | AI40: SOP12.1 | AJ40: BAT | AK40: 2022/2/3-Core+Sensitivity | AL40: DP1500 | AM40: 0 | AN40: 5012030 | AO40: 0 | AP40: 0 | BF40: 0 | BK40: 0 | BL40: 0 | BN40: 1812030 | BO40: 3200000 | BP40: 0 | BQ40: 0 | BR40: 0 | BS40: 0 | BT40: 0 | BU40: 0 | BV40: 0 | BW40: 0 | BX40: 0 | BY40: 0 | BZ40: 0 | CA40: 0 | CB40: 0 | CC40: 0 | CD40: 0 | CE40: 0 | CF40: 0 | CG40: 0 | CH40: 0 | CI40: 0 | CJ40: 0 | CK40: 0 | CL40: 0 | CM40: 0 | CN40: 0 | CO40: 0 | CP40: 0 | CQ40: 0 | CR40: 0 | CS40: 0 | CT40: 0 | CU40: 0 | CV40: 0 | CW40: 0 | CX40: 0 | CY40: 0
A41: 33 | B41: RF032_Alto | C41: Alto | D41: Alto tooling(IM tooling for 2p cost reduction) | G41: 224601000 | H41: 22785000 | I41: 22092200 | J41: 25589000 | K41: 18498600 | L41: 30742700 | M41: 18494250 | N41: 25532300 | O41: 28932600 | P41: 11088600 | Q41: 14612550 | R41: 17543850 | S41: 18060400 | T41: =Volume!CN59 -> 29540200 | U41: =Volume!CO59 -> 15516400 | V41: =Volume!CP59 -> 46369950 | W41: =Volume!CQ59 -> 39955200 | X41: =Volume!CR59 -> 25506950 | Y41: =Volume!CS59 -> 21583600 | Z41: =Volume!CT59 -> 27334550 | AA41: =Volume!CU59 -> 22483600 | ... AE41: =Volume!CY59 -> 25290000 | AF41: =SUM(V41:AE41) -> 274710800 | AI41: 2022/2/3-Core+Sensitivity | AJ41: BAT | AK41: 2022/2/3-PO+Production | AL41: DP1500 | AM41: 0 | AN41: 5012030 | AO41: 0 | AP41: 0 | BF41: 0 | BK41: 0 | BL41: 0 | BN41: 1812030 | BO41: 3200000 | BP41: 0 | BQ41: 0 | BR41: 0 | BS41: 0 | BT41: 0 | BU41: 0 | BV41: 0 | BW41: 0 | BX41: 0 | BY41: 0 | BZ41: 0 | CA41: 0 | CB41: 0 | CC41: 0 | CD41: 0 | CE41: 0 | CF41: 0 | CG41: 0 | CH41: 0 | CI41: 0 | CJ41: 0 | CK41: 0 | CL41: 0 | CM41: 0 | CN41: 0 | CO41: 0 | CP41: 0 | CQ41: 0 | CR41: 0 | CS41: 0 | CT41: 0 | CU41: 0 | CV41: 0 | CW41: 0 | CX41: 0 | CY41: 0
A42: 34 | B42: RF033_ePod2Pod | C42: ePod2 POD | D42: ePod2 POD | E42: 2.4058794e+08 | AF42: =SUM(V42:AE42) -> 0 | AH42: Box 800 1.0 | AI42: 2022/2/3-PO+Production | AJ42: BAT | AK42: 45635 | AL42: Modi Box 1K | AM42: 0 | AN42: 0 | AO42: 35856000 | AP42: 7897176 | BD42: 0 | BE42: 0 | BF42: 0 | BG42: 0 | BH42: 0 | BI42: 0 | BJ42: 0 | BK42: 0 | BL42: 0 | BM42: 0 | BN42: 0 | BO42: 0 | BP42: 0 | BQ42: 0 | BR42: 0 | BS42: 1208800 | BT42: 3315200 | BU42: 3036000 | BV42: 3184800 | BW42: 4384600 | BX42: 4778600 | BY42: 6900000 | BZ42: 7176000 | CA42: 1872000 | CB42: 2317344 | CC42: 915144 | CD42: 2029776 | CE42: 1251648 | CF42: 647600 | CG42: 387088 | CH42: 216480 | CI42: 108000 | CJ42: 24096 | CK42: 0 | CL42: 0 | CM42: 0 | CN42: 0 | CO42: 0 | CP42: 0 | CQ42: 0 | CR42: 0 | CS42: 0 | CT42: 0 | CU42: 0 | CV42: 0 | CW42: 0 | CX42: 0 | CY42: 0
A43: 35 | B43: RF034_epod2Device | C43: epod 2 Device | D43: ePod2 Device - Wave 1-B design | AF43: =SUM(V43:AE43) -> 0 | AH43: Box 800 Default 2.0 | AI43: SOP12.1 | AJ43: BAT | AK43: 45635 | AL43: Box 1K Default | AM43: 0 | AN43: 0 | AO43: 0 | AP43: 9427392 | BD43: 0 | BE43: 0 | BF43: 0 | BG43: 0 | BH43: 0 | BI43: 0 | BJ43: 0 | BK43: 0 | BL43: 0 | BM43: 0 | BN43: 0 | BO43: 0 | BP43: 0 | BQ43: 0 | BR43: 0 | BS43: 0 | BT43: 0 | BU43: 0 | BV43: 0 | BW43: 0 | BX43: 0 | BY43: 0 | BZ43: 0 | CA43: 0 | CB43: 0 | CC43: 0 | CD43: 0 | CE43: 36000 | CF43: 1370520 | CG43: 1201056 | CH43: 1603776 | CI43: 2123328 | CJ43: 1403904 | CK43: 677400 | CL43: 819168 | CM43: 192240 | CN43: 319992 | CO43: 419400 | CP43: 478200 | CQ43: 342768 | CR43: 336444 | CS43: 439644 | CT43: 412488 | CU43: 453144 | CV43: 397368 | CW43: 467268 | CX43: 585648 | CY43: 567660
A44: 36 | B44: RF035_epod2+Device | C44: ePod2+ Device | D44: ePod2+ Device | G44: 235000 | AF44: =SUM(V44:AE44) -> 0 | AH44: Box 800 Full 2.0 | AI44: SOP12.1 | AJ44: BAT | AK44: 45635 | AL44: Box 1K Full | AM44: 0 | AN44: 0 | AO44: 0 | AP44: 8217000 | BD44: 0 | BE44: 0 | BF44: 0 | BG44: 0 | BH44: 0 | BI44: 0 | BJ44: 0 | BK44: 0 | BL44: 0 | BM44: 0 | BN44: 0 | BO44: 0 | BP44: 0 | BQ44: 0 | BR44: 0 | BS44: 0 | BT44: 0 | BU44: 0 | BV44: 0 | BW44: 0 | BX44: 0 | BY44: 0 | BZ44: 0 | CA44: 0 | CB44: 0 | CC44: 0 | CD44: 0 | CE44: 0 | CF44: 1250040 | CG44: 460440 | CH44: 515880 | CI44: 1704000 | CJ44: 1204920 | CK44: 1007160 | CL44: 1175760 | CM44: 898800 | CN44: 360480 | CO44: 287040 | CP44: 634200 | CQ44: 602640 | CR44: 667320 | CS44: 430860 | CT44: 437880 | CU44: 553680 | CV44: 630180 | CW44: 607620 | CX44: 1053000 | CY44: 533700
A45: 37 | B45: RF036_Hestia1.0 | C45: Hestia 1.0 | D45: epod 3 pod Tooling, Included in Hestia Carryover | G45: 12285257 | H45: 1074798 | I45: 65733 | J45: 894985 | K45: 906260 | L45: 1097616 | M45: 617546 | N45: 612910 | O45: 277678 | P45: 193824 | AF45: =SUM(V45:AE45) -> 0 | AH45: Pen 800 Default 2.0 | AI45: SOP12.1 | AJ45: BAT | AK45: 45635 | AL45: Pen 1K Default | AM45: 0 | AN45: 0 | AO45: 0 | AP45: 42631420 | BD45: 0 | BE45: 0 | BF45: 0 | BG45: 0 | BH45: 0 | BI45: 0 | BJ45: 0 | BK45: 0 | BL45: 0 | BM45: 0 | BN45: 0 | BO45: 0 | BP45: 0 | BQ45: 0 | BR45: 0 | BS45: 0 | BT45: 0 | BU45: 0 | BV45: 0 | BW45: 0 | BX45: 0 | BY45: 0 | BZ45: 0 | CA45: 0 | CB45: 0 | CC45: 0 | CD45: 0 | CE45: 1827840 | CF45: 2503920 | CG45: 3935280 | CH45: 4244880 | CI45: 7573320 | CJ45: 6301360 | CK45: 7331100 | CL45: 5685240 | CM45: 3228480 | CN45: 2687720 | CO45: 1733640 | CP45: 4945392 | CQ45: 4747500 | CR45: 2770380 | CS45: 3233940 | CT45: 2643120 | CU45: 4075260 | CV45: 4091460 | CW45: 5045760 | CX45: 5955000 | CY45: 4381320
A46: 38 | B46: RF037_epod3Device | C46: epod 3 Device | D46: epod 3 device tooling, To be Included in ePod 4+ no risk to flag yet. | G46: 2085900 | H46: 46800 | I46: 29400 | J46: 229500 | K46: 111600 | L46: 154900 | M46: 79300 | N46: 21600 | O46: 105200 | P46: 52400 | Q46: 91800 | R46: 75600 | S46: 85100 | T46: 89492 | U46: =Volume!CO35 -> 36900 | V46: =Volume!CP35 -> 51000 | W46: =Volume!CQ35 -> 42100 | X46: =Volume!CR35 -> 32600 | Y46: =Volume!CS35 -> 49400 | Z46: =Volume!CT35 -> 40000 | AA46: =Volume!CU35 -> 48800 | AB46: =Volume!CV35 -> 48400 | ... AE46: =Volume!CY35 -> 25200 | AF46: =SUM(V46:AE46) -> 396000 | AH46: Pen 800 Full 2.0 | AI46: SOP12.1 | AJ46: BAT | AK46: 45635 | AL46: Pen 1K Full | AM46: 0 | AN46: 0 | AO46: 0 | AP46: 5635920 | BD46: 0 | BE46: 0 | BF46: 0 | BG46: 0 | BH46: 0 | BI46: 0 | BJ46: 0 | BK46: 0 | BL46: 0 | BM46: 0 | BN46: 0 | BO46: 0 | BP46: 0 | BQ46: 0 | BR46: 0 | BS46: 0 | BT46: 0 | BU46: 0 | BV46: 0 | BW46: 0 | BX46: 0 | BY46: 0 | BZ46: 0 | CA46: 0 | CB46: 0 | CC46: 0 | CD46: 0 | CE46: 0 | CF46: 324000 | CG46: 132000 | CH46: 1704000 | CI46: 36000 | CJ46: 0 | CK46: 1163340 | CL46: 954900 | CM46: 1321680 | CN46: 294480 | CO46: 205080 | CP46: 362400 | CQ46: 501600 | CR46: 513600 | CS46: 628800 | CT46: 540000 | CU46: 787680 | CV46: 527520 | CW46: 320880 | CX46: 566160 | CY46: 592560
A47: 39 | B47: RF038_epod3+Device | C47: epod 3+ Device | D47: epod 3+ device tooling, To be Included in ePod 4+ no risk to flag yet. | G47: 283400 | H47: 101800 | I47: 40000 | J47: 56600 | K47: 163900 | L47: 57700 | M47: 37200 | N47: 4000 | O47: 12200 | P47: 38200 | Q47: 20800 | S47: 8000 | T47: =Volume!CN33 -> 27600 | U47: =Volume!CO33 -> 17000 | V47: =Volume!CP33 -> 11000 | W47: =Volume!CQ33 -> 18200 | X47: =Volume!CR33 -> 14400 | Y47: =Volume!CS33 -> 32400 | Z47: =Volume!CT33 -> 12300 | AA47: =Volume!CU33 -> 17300 | ... AE47: =Volume!CY33 -> 24800 | AF47: =SUM(V47:AE47) -> 204500 | AH47: Box 3000 1.0 | AI47: SOP12.1 | AJ47: BAT | AK47: 45635 | AL47: Modi Box 3K | AM47: 0 | AN47: 0 | AO47: 3435120 | AP47: 4143840 | BD47: 0 | BE47: 0 | BF47: 0 | BG47: 0 | BH47: 0 | BI47: 0 | BJ47: 0 | BK47: 0 | BL47: 0 | BM47: 0 | BN47: 0 | BO47: 0 | BP47: 0 | BQ47: 0 | BR47: 0 | BS47: 0 | BT47: 0 | BU47: 0 | BV47: 120000 | BW47: 734400 | BX47: 1005600 | BY47: 921240 | BZ47: 404880 | CA47: 249000 | CB47: 384000 | CC47: 434760 | CD47: 672000 | CE47: 1116000 | CF47: 270000 | CG47: 1159080 | CH47: 96000 | CI47: 12000 | CJ47: 0 | CK47: 0 | CL47: 0 | CM47: 0 | CN47: 0 | CO47: 0 | CP47: 0 | CQ47: 0 | CR47: 0 | CS47: 0 | CT47: 0 | CU47: 0 | CV47: 0 | CW47: 0 | CX47: 0 | CY47: 0
A48: 40 | B48: RF039_Hestia1.0 | C48: Hestia 1.0 | D48: Hestia 1.0 New Tooling + ePod3 Pod Tooling included | K48: 4374450 | L48: 10070190 | M48: 20708100 | N48: 10070820 | O48: 17188320 | P48: 15151590 | Q48: 12838860 | R48: 15197040 | S48: 8947260 | T48: 17350470 | U48: =Volume!CO12 -> 7948260 | V48: =Volume!CP12 -> 19106540 | W48: =Volume!CQ12 -> 20397590 | X48: =Volume!CR12 -> 14871760 | Y48: =Volume!CS12 -> 18739530 | Z48: =Volume!CT12 -> 17118810 | AA48: =Volume!CU12 -> 26215830 | AB48: =Volume!CV12 -> 23149370 | ... AE48: =Volume!CY12 -> 19757020 | AF48: =SUM(V48:AE48) -> 208251130 | AI48: SOP12.1 | AK48: 0 | AL48: Box 3K Default | AO48: 0 | AP48: 0 | BP48: 0 | BQ48: 0 | BR48: 0 | BS48: 0 | BT48: 0 | BU48: 0 | BV48: 0 | BW48: 0 | BX48: 0 | BY48: 0 | BZ48: 0 | CA48: 0 | CB48: 0 | CC48: 0 | CD48: 0 | CE48: 0 | CF48: 0 | CG48: 0 | CH48: 0 | CI48: 0 | CJ48: 0 | CK48: 0 | CL48: 0 | CM48: 0 | CN48: 0 | CO48: 0 | CP48: 0 | CQ48: 0 | CR48: 0 | CS48: 0 | CT48: 0 | CU48: 0 | CV48: 0 | CW48: 0 | CX48: 0 | CY48: 0
A49: 41 | B49: RF040_Kuma | C49: Kuma | D49: KUMA E BOX NZ | AF49: =SUM(V49:AE49) -> 0 | AH49: Box 3000 Full 2.0 | AI49: SOP01.4 | AJ49: BAT | AK49: 45698 | AL49: Box 3K Full | AM49: 0 | AN49: 0 | AO49: 0 | AP49: 1367880 | BD49: 0 | BE49: 0 | BF49: 0 | BG49: 0 | BH49: 0 | BI49: 0 | BJ49: 0 | BK49: 0 | BL49: 0 | BM49: 0 | BN49: 0 | BO49: 0 | BP49: 0 | BQ49: 0 | BR49: 0 | BS49: 0 | BT49: 0 | BU49: 0 | BV49: 0 | BW49: 0 | BX49: 0 | BY49: 0 | BZ49: 0 | CA49: 0 | CB49: 0 | CC49: 0 | CD49: 0 | CE49: 0 | CF49: 0 | CG49: 0 | CH49: 0 | CI49: 0 | CJ49: 0 | CK49: 845000 | CL49: 510880 | CM49: 12000 | CN49: 24120 | CO49: 208032 | CP49: 96000 | CQ49: 36096 | CR49: 271824 | CS49: 490848 | CT49: 338460 | CU49: 457272 | CV49: 374784 | CW49: 307656 | CX49: 456444 | CY49: 447432
A50: 42 | B50: RF041_Kuma | C50: Kuma | D50: KUMA E BOX ROW | K50: 146304 | L50: 793652 | M50: 1209610 | N50: 417742 | O50: 338164 | P50: 665900 | Q50: 479376 | R50: 160272 | S50: 139680 | T50: =Volume!CN15 -> 522432 | U50: =Volume!CO15 -> 149760 | V50: =Volume!CP15 -> 207792 | W50: =Volume!CQ15 -> 87840 | X50: =Volume!CR15 -> 66240 | Y50: =Volume!CS15 -> 111600 | Z50: =Volume!CT15 -> 65520 | AA50: =Volume!CU15 -> 60480 | ... AE50: =Volume!CY15 -> 35280 | AF50: =SUM(V50:AE50) -> 780912 | AH50: Box 5000 1.0 | AI50: SOP1.4 | AJ50: BAT | AK50: 45719 | AL50: Modi Box 5K | AM50: 0 | AN50: 0 | AO50: 4156720 | AP50: 2563880 | BD50: 0 | BE50: 0 | BF50: 0 | BG50: 0 | BH50: 0 | BI50: 0 | BJ50: 0 | BK50: 0 | BL50: 0 | BM50: 0 | BN50: 0 | BO50: 0 | BP50: 0 | BQ50: 0 | BR50: 0 | BS50: 0 | BT50: 264000 | BU50: 504000 | BV50: 672000 | BW50: 180000 | BX50: 911520 | BY50: 981240 | BZ50: 314160 | CA50: 329800 | CB50: 522200 | CC50: 440400 | CD50: 240600 | CE50: 233880 | CF50: 232800 | CG50: 368160 | CH50: 95640 | CI50: 342600 | CJ50: 70920 | CK50: 0 | CL50: 16680 | CM50: 0 | CN50: 0 | CO50: 4680 | CP50: 72000 | CQ50: 0 | CR50: 0 | CS50: 0 | CT50: 0 | CU50: 0 | CV50: 0 | CW50: 0 | CX50: 0 | CY50: 0
A51: 43 | B51: RF042_Kuma | C51: Kuma | D51: KUMA E-ROW E Pen 1.0 | N51: 39600 | O51: 894780 | P51: 1411740 | Q51: 1022040 | R51: 950580 | S51: 453600 | T51: =Volume!CN18+Volume!CN20 -> 574020 | U51: =Volume!CO18+Volume!CO20 -> 633600 | V51: =Volume!CP18+Volume!CP20 -> 626220 | W51: =Volume!CQ18+Volume!CQ20 -> 116460 | X51: =Volume!CR18+Volume!CR20 -> 114660 | Y51: =Volume!CS18+Volume!CS20 -> 179460 | Z51: =Volume!CT18+Volume!CT20 -> 169200 | AA51: =Volume!CU18+Volume!CU20 -> 147260 | ... AE51: =Volume!CY18+Volume!CY20 -> 142880 | AF51: =SUM(V51:AE51) -> 1884560 | AI51: SOP12.1 | AK51: 0 | AL51: Box 5K Default | AO51: 0 | AP51: 0 | BP51: 0 | BQ51: 0 | BR51: 0 | BS51: 0 | BT51: 0 | BU51: 0 | BV51: 0 | BW51: 0 | BX51: 0 | BY51: 0 | BZ51: 0 | CA51: 0 | CB51: 0 | CC51: 0 | CD51: 0 | CE51: 0 | CF51: 0 | CG51: 0 | CH51: 0 | CI51: 0 | CJ51: 0 | CK51: 0 | CL51: 0 | CM51: 0 | CN51: 0 | CO51: 0 | CP51: 0 | CQ51: 0 | CR51: 0 | CS51: 0 | CT51: 0 | CU51: 0 | CV51: 0 | CW51: 0 | CX51: 0 | CY51: 0
A52: 44 | B52: RF043_Modi2.0 | C52: Modi 2.0 | D52: Vuse Go 2.0 1K Pen Default | K52: 1827840 | L52: 2873520 | M52: 3565680 | N52: 4244880 | O52: 7812840 | P52: 6241840 | Q52: 7151100 | R52: 5812200 | S52: 1591120 | T52: =Volume!CN45 -> 2687720 | U52: =Volume!CO45 -> 1733640 | V52: =Volume!CP45 -> 4945392 | W52: =Volume!CQ45 -> 4747500 | X52: =Volume!CR45 -> 2770380 | Y52: =Volume!CS45 -> 3233940 | Z52: =Volume!CT45 -> 2643120 | AA52: =Volume!CU45 -> 4075260 | ... AE52: =Volume!CY45 -> 4381320 | AF52: =SUM(V52:AE52) -> 41889132 | AH52: Box 5000 Full 2.0 | AI52: SOP01.4 | AJ52: BAT | AK52: 45698 | AL52: Box 5K Full | AM52: 0 | AN52: 0 | AO52: 0 | AP52: 7129464 | BD52: 0 | BE52: 0 | BF52: 0 | BG52: 0 | BH52: 0 | BI52: 0 | BJ52: 0 | BK52: 0 | BL52: 0 | BM52: 0 | BN52: 0 | BO52: 0 | BP52: 0 | BQ52: 0 | BR52: 0 | BS52: 0 | BT52: 0 | BU52: 0 | BV52: 0 | BW52: 0 | BX52: 0 | BY52: 0 | BZ52: 0 | CA52: 0 | CB52: 0 | CC52: 0 | CD52: 0 | CE52: 0 | CF52: 436512 | CG52: 404112 | CH52: 1191168 | CI52: 1163760 | CJ52: 1310808 | CK52: 1000560 | CL52: 430488 | CM52: 1192056 | CN52: 446688 | CO52: 303144 | CP52: 214656 | CQ52: 173640 | CR52: 239520 | CS52: 149400 | CT52: 143040 | CU52: 214080 | CV52: 220560 | CW52: 206880 | CX52: 368880 | CY52: 167040
A53: 45 | B53: RF044_Modi2.0 | C53: Modi 2.0 | D53: Vuse Go 2.0 1K Box Default | K53: 36000 | L53: 1370520 | M53: 1201056 | N53: 1603776 | O53: 2195328 | P53: 1331904 | Q53: 701400 | R53: 795168 | S53: 144000 | T53: =Volume!CN43 -> 319992 | U53: =Volume!CO43 -> 419400 | V53: =Volume!CP43 -> 478200 | W53: =Volume!CQ43 -> 342768 | X53: =Volume!CR43 -> 336444 | Y53: =Volume!CS43 -> 439644 | Z53: =Volume!CT43 -> 412488 | AA53: =Volume!CU43 -> 453144 | ... AE53: =Volume!CY43 -> 567660 | AF53: =SUM(V53:AE53) -> 4480632 | AH53: Box 8000 1.0 | AI53: SOP1.4 | AJ53: BAT | AK53: 45719 | AL53: Modi Box 8K | AM53: 0 | AN53: 0 | AO53: 0 | AP53: 965280 | BD53: 0 | BE53: 0 | BF53: 0 | BG53: 0 | BH53: 0 | BI53: 0 | BJ53: 0 | BK53: 0 | BL53: 0 | BM53: 0 | BN53: 0 | BO53: 0 | BP53: 0 | BQ53: 0 | BR53: 0 | BS53: 0 | BT53: 0 | BU53: 0 | BV53: 0 | BW53: 0 | BX53: 0 | BY53: 0 | BZ53: 0 | CA53: 0 | CB53: 360000 | CC53: 0 | CD53: 108000 | CE53: 0 | CF53: 108000 | CG53: 12000 | CH53: 0 | CI53: 20040 | CJ53: 48600 | CK53: 17280 | CL53: 133440 | CM53: 157920 | CN53: 102000 | CO53: 14040 | CP53: 0 | CQ53: 0 | CR53: 0 | CS53: 0 | CT53: 0 | CU53: 0 | CV53: 0 | CW53: 0 | CX53: 0 | CY53: 0
A54: 46 | B54: RF045_Modi2.0 | C54: Modi 2.0 | D54: Vuse Go 2.0 1K Box Full | L54: 1250040 | M54: 460440 | N54: 515880 | O54: 1815960 | P54: 1092960 | Q54: 1043160 | R54: 1111560 | S54: 789000 | T54: =Volume!CN44 -> 360480 | U54: =Volume!CO44 -> 287040 | V54: =Volume!CP44 -> 634200 | W54: =Volume!CQ44 -> 602640 | X54: =Volume!CR44 -> 667320 | Y54: =Volume!CS44 -> 430860 | Z54: =Volume!CT44 -> 437880 | AA54: =Volume!CU44 -> 553680 | ... AE54: =Volume!CY44 -> 533700 | AF54: =SUM(V54:AE54) -> 6151080 | AI54: SOP12.1 | AJ54: RJR | AK54: 45600 | AL54: Alto Cartridges-CN | AM54: 370859400 | AN54: 97779600 | AO54: 0 | AP54: 0 | AQ54: 28587600 | AR54: 8263800 | AS54: 31741200 | AT54: 33382800 | AU54: 33210000 | AV54: 33397200 | AW54: 37684800 | AX54: 34875000 | AY54: 35804400 | AZ54: 26860800 | BA54: 28072800 | BB54: 38979000 | BD54: 23313600 | BE54: 11452500 | BF54: 19874700 | BG54: 23241600 | BH54: 18414000 | BI54: 1483200
A55: 47 | B55: RF046_Modi2.0 | C55: Modi 2.0 | D55: Vuse Go 2.0 1K Pen Full | L55: 324000 | M55: 132000 | N55: 1704000 | O55: 36000 | Q55: 1183440 | R55: 934800 | S55: 49680 | T55: =Volume!CN46 -> 294480 | U55: =Volume!CO46 -> 205080 | V55: =Volume!CP46 -> 362400 | W55: =Volume!CQ46 -> 501600 | X55: =Volume!CR46 -> 513600 | Y55: =Volume!CS46 -> 628800 | Z55: =Volume!CT46 -> 540000 | AA55: =Volume!CU46 -> 787680 | ... AE55: =Volume!CY46 -> 592560 | AF55: =SUM(V55:AE55) -> 5341200 | AH55: Box 8000 Full 2.0 | AI55: SOP01.4 | AJ55: BAT | AK55: 45698 | AL55: Box 8K Full | AM55: 0 | AN55: 0 | AO55: 0 | AP55: 384000 | BD55: 0 | BE55: 0 | BF55: 0 | BG55: 0 | BH55: 0 | BI55: 0 | BJ55: 0 | BK55: 0 | BL55: 0 | BM55: 0 | BN55: 0 | BO55: 0 | BP55: 0 | BQ55: 0 | BR55: 0 | BS55: 0 | BT55: 0 | BU55: 0 | BV55: 0 | BW55: 0 | BX55: 0 | BY55: 0 | BZ55: 0 | CA55: 0 | CB55: 0 | CC55: 0 | CD55: 0 | CE55: 0 | CF55: 0 | CG55: 0 | CH55: 0 | CI55: 0 | CJ55: 0 | CK55: 0 | CL55: 348000 | CM55: 36000 | CN55: 84960 | CO55: 4080 | CP55: 116280 | CQ55: 77520 | CR55: 206280 | CS55: 65640 | CT55: 77040 | CU55: 80160 | CV55: 76680 | CW55: 83520 | CX55: 143520 | CY55: 71520 | AZH55: ''''''''' | AZJ55: ''''''''''''''''''''''''''''''''''''''' | AZK55: ''''''''''''''''''''''''''''''''''''''''''''''''''''''''''''''''''''''''''''''''''''''''''''''''''''''''''''''''''''''''''''''''''''''''''''''''''''''''''''''''''''''''''''''''''''''''''''''''''''''''''''''''''''''''''''''''''''''''''''''''''''''''''''''''''''''''''''''''''''''''''''''''''''''''''''''''''''''''''''''''''''''''''''''''''''''''''''''''''''''''''''''''''''''''''''''''''''''''''''''''''''''''''''''''''''''''''''''''''''''''''''''''''''''''''''''''''''''''''''''''''''''''''''''''''''''''''''''''''''''''''''''''''''''''''''''''''''''''''''''''''''''''''''''''''''''''''''''''''''''''''''''''''''''''''''''''''''''''''''''''''''''''''''''''''''''''''''''''''''''''''''''''''''''''''''''''''''''''''''''''''''''''''''''''''''''''''''''''''''''''''''''''''''''''''''''''''''''''''''''''''''''''''''''''''''''''''''''''''''''''''''''''''''''''''''''''''''''''''''''''''''''''''''''''''''''''''''''''''''''''''''''''''''''''''''''''''''''''''''''''''''''''''''''''''''''''''''''''''''''''''''''''''''''''''''''''''''''''''''''''''''''''''''''''''''''''''''''''''''''''''''''''''''''''''''''''''''''''''''''''''''''''''''''''''''''''''''''''''''''''''''''''''''''''''''''''''''''''''''''''''''''''''''''''''''''''''''''''''''''''''''''''''''''''''''''''''''''''''''''''''''''''''''''''''''''''''''''''''''''''''''''''''''''''''''''''''''''''''''''''''''''''''''''''''
A56: 48 | B56: RF047_DP1500 | C56: DP 1500 | D56: DP 1500 tooling | F56: 4508000 | G56: 12961000 | H56: 303000 | I56: 180000 | J56: 324000 | K56: 984000 | L56: 912000 | M56: 226000 | N56: 60000 | O56: 288000 | P56: 218000 | AF56: =SUM(V56:AE56) -> 0 | AH56: Alto Cartridges-IND | AI56: SOP1.4 | AJ56: RJR | AK56: 45719 | AL56: Alto Cartridges-IND | AM56: 0 | AN56: 168097600 | AO56: 255515000 | AP56: 240955000 | AQ56: 0 | AR56: 0 | AS56: 0 | AT56: 0 | AU56: 0 | AV56: 0 | AW56: 0 | AX56: 0 | AY56: 0 | AZ56: 0 | BA56: 0 | BB56: 0 | BD56: 0 | BE56: 0 | BF56: 0 | BG56: 0 | BH56: 1500000 | BI56: 8525800 | BJ56: 20464600 | BK56: 29343800 | BL56: 27249800 | BM56: 20437500 | BN56: 27980700 | BO56: 32595400 | BP56: 30914000 | BQ56: 31018300 | BR56: 27736300 | BS56: 20107700 | BT56: 25062300 | BU56: 25527600 | BV56: 23250400 | BW56: 13933400 | BX56: 8697000 | BY56: 3530100 | BZ56: 24994500 | CA56: 20743400 | CB56: 18696800 | CC56: 26612200 | CD56: 24709600 | CE56: 15849900 | CF56: 31753100 | CG56: 18403700 | CH56: 25102700 | CI56: 27982200 | CJ56: 9598800 | CK56: 13374000 | CL56: 15867000 | CM56: 13005000 | CN56: 28556.8 | CO56: 14936.8 | CP56: 45748.2 | CQ56: 39757.8 | CR56: 24774.6 | CS56: 21123 | CT56: 26758.8 | CU56: 21960 | CV56: 20235.6 | CW56: 24805.8 | CX56: 19515.6 | CY56: 24748.2
A57: 49 | B57: RF048_Box1k | C57: BOX 1K | D57: BOX 1000 | G57: 9072000 | H57: 2569344 | I57: 651264 | J57: 1993776 | K57: 1203648 | L57: 647600 | M57: 411280 | N57: 192288 | O57: 108000 | P57: 24096 | AF57: =SUM(V57:AE57) -> 0 | AH57: Alto Device | AI57: SOP1.4 | AJ57: RJR | AK57: 45719 | AL57: Alto Device | AM57: 14653350 | AN57: 17110575 | AO57: 5737450 | AP57: 2190800 | AQ57: 1981200 | AR57: 309000 | AS57: 1156200 | AT57: 1657200 | AU57: 1011000 | AV57: 1050000 | AW57: 789600 | AX57: 744000 | AY57: 1297800 | AZ57: 1524150 | BA57: 1623600 | BB57: 1509600 | BD57: 1485600 | BE57: 660000 | BF57: 1605865 | BG57: 1854200 | BH57: 1775000 | BI57: 2027900 | BJ57: 1732450 | BK57: 1542350 | BL57: 681200 | BM57: 933600 | BN57: 1074410 | BO57: 1738000 | BP57: 1056750 | BQ57: 1672800 | BR57: 2378700 | BS57: 116850 | BT57: 29600 | BU57: 174650 | BV57: 226900 | BW57: 81200 | BX57: 0 | BY57: 0 | BZ57: 0 | CA57: 0 | CB57: 0 | CC57: 292500 | CD57: 301700 | CE57: 290600 | CF57: 431700 | CG57: 123200 | CH57: 416300 | CI57: 0 | CJ57: 0 | CK57: 91200 | CL57: 117600 | CM57: 126000 | CN57: 260400 | CO57: 319200 | CP57: 302400 | CQ57: 268800 | CR57: 336000 | CS57: 260400 | CT57: 294000 | CU57: 226800 | CV57: 327600 | CW57: 256200 | CX57: 201600 | CY57: 260400
A58: 50 | B58: RF049_Modi2.0 | C58: Modi 2.0 | D58: Vuse Go 2.0 5K Box Full(Include Sensa) | L58: 1257720 | M58: 1734480 | N58: 1765872 | O58: 1740168 | P58: 1307520 | Q58: 1000560 | R58: 593352 | S58: 398280 | T58: =Volume!CN52 -> 446688 | U58: =Volume!CO52 -> 303144 | V58: =Volume!CP52 -> 214656 | W58: =Volume!CQ52 -> 173640 | X58: =Volume!CR52 -> 239520 | Y58: =Volume!CS52 -> 149400 | Z58: =Volume!CT52 -> 143040 | AA58: =Volume!CU52 -> 214080 | ... AE58: =Volume!CY52 -> 167040 | AF58: =SUM(V58:AE58) -> 2097696 | AH58: Alto bundle kit | AI58: SOP1.4 | AJ58: RJR | AK58: 45719 | AL58: Alto bundle kit | AM58: 0 | AN58: 0 | AO58: 7777400 | AP58: 8478450 | AQ58: 0 | AR58: 0 | AS58: 0 | AT58: 0 | AU58: 0 | AV58: 0 | AW58: 0 | AX58: 0 | AY58: 0 | AZ58: 0 | BA58: 0 | BB58: 0 | BD58: 0 | BE58: 0 | BF58: 0 | BG58: 0 | BH58: 0 | BI58: 0 | BJ58: 0 | BK58: 0 | BL58: 0 | BM58: 0 | BN58: 0 | BO58: 0 | BP58: 509000 | BQ58: 538250 | BR58: 0 | BS58: 1135100 | BT58: 701600 | BU58: 231550 | BV58: 1056000 | BW58: 644200 | BX58: 253600 | BY58: 471000 | BZ58: 829900 | CA58: 1407200 | CB58: 1122000 | CC58: 121500 | CD58: 351700 | CE58: 381400 | CF58: 109300 | CG58: 90550 | CH58: 429600 | CI58: 950400 | CJ58: 1489800 | CK58: 1238550 | CL58: 769050 | CM58: 1424600 | CN58: 983400 | CO58: 579600 | CP58: 621750 | CQ58: 197400 | CR58: 732350 | CS58: 460600 | CT58: 575750 | CU58: 523600 | CV58: 684950 | CW58: 516600 | CX58: 428400 | CY58: 541800
A59: 51 | B59: RF050_Modi2.0 | C59: Modi 2.0 | D59: Vuse Go 2.0 8K Box Full | Q59: 312000 | R59: 36000 | S59: 8160 | T59: =Volume!CN55 -> 84960 | U59: =Volume!CO55 -> 4080 | V59: =Volume!CP55 -> 116280 | W59: =Volume!CQ55 -> 77520 | X59: =Volume!CR55 -> 206280 | Y59: =Volume!CS55 -> 65640 | Z59: =Volume!CT55 -> 77040 | AA59: =Volume!CU55 -> 80160 | ... AE59: =Volume!CY55 -> 71520 | AF59: =SUM(V59:AE59) -> 998160 | AH59: Alto Pods total (cartridge +bundle kit pod) | AI59: SOP1.4 | AJ59: RJR | AK59: 45635 | AL59: Alto Pods total (cartridge +bundle kit pod) | AM59: 370859400 | AN59: 265877200 | AO59: 263292400 | AP59: 249433450 | CB59: 19818800 | CC59: 26733700 | CD59: 25061300 | CE59: 16231300 | CF59: 31862400 | CG59: 18494250 | CH59: 25532300 | CI59: 28932600 | CJ59: 11088600 | CK59: 14612550 | CL59: 16636050 | CM59: 14429600 | CN59: 29540200 | CO59: 15516400 | CP59: 46369950 | CQ59: 39955200 | CR59: 25506950 | CS59: 21583600 | CT59: 27334550 | CU59: 22483600 | CV59: 20920550 | CW59: 25322400 | CX59: 19944000 | CY59: 25290000
A60: 52 | B60: RF051_Modi2.0 | C60: Modi 2.0 | D60: Vuse Go 2.0 3K Box Full | Q60: 845000 | R60: 522880 | T60: =Volume!CN49 -> 24120 | U60: =Volume!CO49 -> 208032 | V60: =Volume!CP49 -> 96000 | W60: =Volume!CQ49 -> 36096 | X60: =Volume!CR49 -> 271824 | Y60: =Volume!CS49 -> 490848 | Z60: =Volume!CT49 -> 338460 | AA60: =Volume!CU49 -> 457272 | ... AE60: =Volume!CY49 -> 447432 | AF60: =SUM(V60:AE60) -> 3276816 | AH60: Prismatic Taste Kit | AI60: SOP1.4 | AJ60: RJR | AK60: 45719 | AL60: Prismatic Taste Kit | AM60: 0 | AN60: 0 | AO60: 0 | AP60: 2910050 | BD60: 0 | BE60: 0 | BF60: 0 | BG60: 0 | BH60: 0 | BI60: 0 | BJ60: 0 | BK60: 0 | BL60: 0 | BM60: 0 | BN60: 0 | BO60: 0 | BP60: 0 | BQ60: 0 | BR60: 0 | BS60: 0 | BT60: 0 | BU60: 0 | BV60: 0 | BW60: 0 | BX60: 0 | BY60: 0 | BZ60: 0 | CA60: 0 | CB60: 0 | CC60: 0 | CD60: 0 | CE60: 450000 | CF60: 351000 | CG60: 392600 | CH60: 196500 | CI60: 337500 | CJ60: 171000 | CK60: 434800 | CL60: 375050 | CM60: 201600 | CN60: 0 | CO60: 189000 | CP60: 24000 | CQ60: 0 | CR60: 0 | CS60: 0 | CT60: 84000 | CU60: 84000 | CV60: 105000 | CW60: 180600 | CX60: 151200 | CY60: 168000
A61: 53 | B61: RF052_epod3pod | C61: ePod3 Pod | D61: ePod3 Pod tooling | G61: 12285257 | H61: 1074798 | I61: 65733 | J61: 894985 | K61: 906260 | L61: 1097616 | M61: 617546 | N61: 612910 | O61: 277678 | P61: 193824 | T61: 0 | AF61: =SUM(V61:AE61) -> 0 | AH61: Prismatic Pod | AI61: SOP1.4 | AJ61: RJR | AK61: 45719 | AL61: Prismatic Pods | AM61: 0 | AN61: 0 | AO61: 0 | AP61: 19002900 | BD61: 0 | BE61: 0 | BF61: 0 | BG61: 0 | BH61: 0 | BI61: 0 | BJ61: 0 | BK61: 0 | BL61: 0 | BM61: 0 | BN61: 0 | BO61: 0 | BP61: 0 | BQ61: 0 | BR61: 0 | BS61: 0 | BT61: 0 | BU61: 0 | BV61: 0 | BW61: 0 | BX61: 0 | BY61: 0 | BZ61: 0 | CA61: 0 | CB61: 0 | CC61: 0 | CD61: 0 | CE61: 3211800 | CF61: 2988300 | CG61: 1850100 | CH61: 3589500 | CI61: 3864300 | CJ61: 3416400 | CK61: 0 | CL61: 82500 | CM61: 0 | CN61: 0 | CO61: 97500 | CP61: 0 | CQ61: 0 | CR61: 0 | CS61: 0 | CT61: 0 | CU61: 0 | CV61: 0 | CW61: 0 | CX61: 0 | CY61: 0
A62: 54 | B62: RF053_Alto | C62: Alto | D62: Alto tooling | F62: 195500900 | G62: 255515000 | H62: 22785000 | I62: 22092200 | J62: 25589000 | K62: 18498600 | L62: 30742700 | M62: 18494250 | N62: 25532300 | O62: 28932600 | P62: 11088600 | Q62: 14612550 | R62: 17543850 | S62: 18060400 | T62: =Volume!CN59 -> 29540200 | U62: =Volume!CO59 -> 15516400 | V62: =Volume!CP59 -> 46369950 | W62: =Volume!CQ59 -> 39955200 | X62: =Volume!CR59 -> 25506950 | Y62: =Volume!CS59 -> 21583600 | Z62: =Volume!CT59 -> 27334550 | AA62: =Volume!CU59 -> 22483600 | ... AE62: =Volume!CY59 -> 25290000 | AF62: =SUM(V62:AE62) -> 274710800 | AH62: Prismatic Pods total(cartridge+Taste kit） | AI62: SOP1.4 | AJ62: RJR | AK62: 45719 | AL62: Prismatic Pods total(cartridge+Taste kit） | AM62: 0 | AN62: 0 | AO62: 0 | AP62: 24823000 | CB62: 0 | CC62: 0 | CD62: 0 | CE62: 4111800 | CF62: 3690300 | CG62: 2635300 | CH62: 3982500 | CI62: 4539300 | CJ62: 3758400 | CK62: 869600 | CL62: 832600 | CM62: 403200 | CN62: 0 | CO62: 475500 | CP62: 48000 | CQ62: 0 | CR62: 0 | CS62: 0 | CT62: 168000 | CU62: 168000 | CV62: 210000 | CW62: 361200 | CX62: 302400 | CY62: 336000
A63: 55 | B63: RF054_Hestia1.1 | C63: Hestia 1.1 | D63: Hestia 1.1 tooling NON-smart unique+ECN | AF63: =SUM(V63:AE63) -> 0 | AH63: Sensa 5K | AI63: RJR FC_0206 | AJ63: RJR | AK63: 45694 | AL63: Alto 5K Full | AM63: 0 | AN63: 0 | AO63: 0 | AP63: 3299400 | BD63: 0 | BE63: 0 | BF63: 0 | BG63: 0 | BH63: 0 | BI63: 0 | BJ63: 0 | BK63: 0 | BL63: 0 | BM63: 0 | BN63: 0 | BO63: 0 | BP63: 0 | BQ63: 0 | BR63: 0 | BS63: 0 | BT63: 0 | BU63: 0 | BV63: 0 | BW63: 0 | BX63: 0 | BY63: 0 | BZ63: 0 | CA63: 0 | CB63: 0 | CC63: 0 | CD63: 0 | CE63: 0 | CF63: 728760 | CG63: 1410720 | CH63: 434160 | CI63: 376920 | CJ63: 348840 | CK63: 0 | CL63: 0 | CM63: 0 | CN63: 0 | CO63: 0 | CP63: 0 | CQ63: 0 | CR63: 0 | CS63: 0 | CT63: 0 | CU63: 0 | CV63: 0 | CW63: 0 | CX63: 0 | CY63: 0
A64: 56 | B64: RF055_Hestia1.1 | C64: Hestia 1.1 | D64: Hestia 1.1 tooling initial smart and commont parts | T64: 0 | U64: =Volume!CO14 -> 29970 | V64: =Volume!CP14 -> 576000 | W64: =Volume!CQ14 -> 811150 | X64: =Volume!CR14 -> 1104660 | Y64: =Volume!CS14 -> 817540 | Z64: =Volume!CT14 -> 476460 | AA64: =Volume!CU14 -> 606300 | AB64: =Volume!CV14 -> 610230 | ... AE64: =Volume!CY14 -> 613260 | AF64: =SUM(V64:AE64) -> 6679340 | AI64: SOP12.1 | AM64: 521304320 | AN64: 468436913 | AO64: 397158290 | AP64: 469298356 | AQ64: 9366300 | AR64: 5088060 | AS64: 10606320 | AT64: 9598860 | AU64: 14671980 | AV64: 14349580 | AW64: 12979220 | AX64: 15256580 | AY64: 15964420 | AZ64: 12569000 | BA64: 15497160 | BB64: 14497440 | BD64: 15559440 | BE64: 12012360 | BF64: 18465130 | BG64: 19798430 | BH64: 23406028 | BI64: 26965023 | BJ64: 37630703 | BK64: 43853585 | BL64: 58256164 | BM64: 32802598 | BN64: 42920800 | BO64: 48233339 | BP64: 41323124 | BQ64: 41261193 | BR64: 45338256 | BS64: 35612524 | BT64: 37187474 | BU64: 39990544 | BV64: 36028066 | BW64: 27053480 | BX64: 26089463 | BY64: 17352266 | BZ64: 41595510 | CA64: 29854630 | CB64: 31128050 | CC64: 32641880 | CD64: 35407550 | CE64: 30530144 | CF64: 51927022 | CG64: 47492450 | CH64: 48987358 | CI64: 57967194 | CJ64: 37012910 | CK64: 32432066 | CL64: 32111920 | CM64: 31659812 | CN64: 49325134 | CO64: 24094072 | CP64: 33634028 | CQ64: 34681186 | CR64: 30539856 | CS64: 34099475 | CT64: 36698503 | CU64: 35034668 | CV64: 32811629 | CW64: 35888193 | CX64: 32888857 | CY64: 33677829
A65: 57 | B65: RF056_Hestia1.1 | C65: Hestia 1.1 | D65: Hestia 1.1 tooling incremental | U65: =Volume!CO14 -> 29970 | V65: =Volume!CP14 -> 576000 | W65: =Volume!CQ14 -> 811150 | X65: =Volume!CR14 -> 1104660 | Y65: =Volume!CS14 -> 817540 | Z65: =Volume!CT14 -> 476460 | AA65: =Volume!CU14 -> 606300 | AB65: =Volume!CV14 -> 610230 | ... AE65: =Volume!CY14 -> 613260 | AF65: =SUM(V65:AE65) -> 6679340 | AI65: Cartridges Total | AM65: 0 | AN65: 86189947 | AO65: 102047186 | AP65: 97469652 | AQ65: 0 | AR65: 0 | AS65: 0 | AT65: 0 | AU65: 0 | AV65: 0 | AW65: 0 | AX65: 0 | AY65: 0 | AZ65: 0 | BA65: 0 | BB65: 0 | BD65: 0 | BE65: 0 | BF65: 0 | BG65: 932000 | BH65: 2904000 | BI65: 6345360 | BJ65: 12084000 | BK65: 12364000 | BL65: 14666000 | BM65: 7120798 | BN65: 18203789 | BO65: 11570000 | BP65: 9075800 | BQ65: 8437600 | BR65: 10342600 | BS65: 14465200 | BT65: 8559800 | BU65: 7514600 | BV65: 6556800 | BW65: 7044946 | BX65: 9026320 | BY65: 9701480 | BZ65: 8363040 | CA65: 2959000 | CB65: 3799544 | CC65: 2069304 | CD65: 3374376 | CE65: 5449368 | CF65: 8148152 | CG65: 10331936 | CH65: 10161984 | CI65: 13723968 | CJ65: 10955448 | CK65: 12221840 | CL65: 10098556 | CM65: 7135176 | CN65: 4385016 | CO65: 3352744 | CP65: 3298140 | CQ65: 5150200 | CR65: 5252844 | CS65: 7607097 | CT65: 6144799 | CU65: 7092410 | CV65: 6236532 | CW65: 6095646 | CX65: 7886988 | CY65: 6036936
A66: 58 | B66: RF057_KumaE2.0 | C66: Kuma E 2.0 | D66: Kuma E 2.0 Pen tooling initial | AF66: =SUM(V66:AE66) -> 0 | AI66: Disposable Total | AM66: 21928601 | AN66: 25418470 | AO66: 9400250 | AP66: 16174136 | AQ66: 2336600 | AR66: 685900 | AS66: 1486000 | AT66: 2171200 | AU66: 1403100 | AV66: 1722345 | AW66: 1580200 | AX66: 1325700 | AY66: 1790900 | AZ66: 2290731 | BA66: 2414600 | BB66: 2365600 | BD66: 2103000 | BE66: 1225400 | BF66: 2524265 | BG66: 2861600 | BH66: 2498600 | BI66: 2780600 | BJ66: 2321650 | BK66: 2133650 | BL66: 1317255 | BM66: 978600 | BN66: 1238200 | BO66: 1862200 | BP66: 1660750 | BQ66: 2520350 | BR66: 2498900 | BS66: 1497550 | BT66: 1281100 | BU66: 802600 | BV66: 1513800 | BW66: 1122900 | BX66: 687800 | BY66: 697700 | BZ66: 1070200 | CA66: 1824000 | CB66: 1333100 | CC66: 563500 | CD66: 980500 | CE66: 1567120 | CF66: 1174100 | CG66: 762090 | CH66: 1363576 | CI66: 1433940 | CJ66: 1771560 | CK66: 1946150 | CL66: 1380500 | CM66: 1898000 | CN66: 1628186 | CO66: 1005872 | CP66: 719520 | CQ66: 959628 | CR66: 751372 | CS66: 758202 | CT66: 943514 | CU66: 907316 | CV66: 858682 | CW66: 1061394 | CX66: 884696 | CY66: 1075695
A67: 59 | B67: RF058_KumaE2.0 | C67: Kuma E 2.0 | D67: Kuma E 2.0 Pen tooling incremental | AF67: =SUM(V67:AE67) -> 0
A68: 60 | B68: RF059_Mimosa1.0 | C68: Mimosa | D68: Mimosa 1.0 tooling initial | T68: 0 | U68: 3744 | V68: 72000 | W68: 153000 | X68: 99000 | Y68: 18000 | Z68: 36336 | AA68: 56016 | AB68: 38736 | AC68: 46032 | AD68: 44928 | AE68: 43776 | AF68: =SUM(V68:AE68) -> 607824
A69: 61 | B69: RF060_Mimosa1.0 | C69: Mimosa | D69: Mimosa 1.0 tooling incremental | T69: 0 | U69: 3744 | V69: 72000 | W69: 153000 | X69: 99000 | Y69: 18000 | Z69: 36336 | AA69: 56016 | AB69: 38736 | AC69: 46032 | AD69: 44928 | AE69: 43776 | AF69: =SUM(V69:AE69) -> 607824
A70: 62 | B70: RF061_PrismaticPod | C70: Prismatic Pod | D70: China | V70: 106560 | AF70: =SUM(V70:AE70) -> 106560
A71: 63 | B71: RF062_PrismaticPod | C71: Prismatic Pod | D71: Prismatic Pod Indo Black | AF71: =SUM(V71:AE71) -> 0
A72: 64 | B72: RF063_PrismaticPod | C72: Prismatic Pod | D72: Prismatic Pod Indo white | AF72: =SUM(V72:AE72) -> 0
A73: 65 | B73: RF064_MimosaSmart | C73: Mimosa | D73: Mimosa 1.0 - PCBA Tooling | T73: 0 | U73: 3744 | V73: 72000 | W73: 153000 | X73: 99000 | Y73: 18000 | Z73: 36336 | AA73: 56016 | AB73: 38736 | AC73: 46032 | AD73: 44928 | AE73: 43776 | AF73: =SUM(V73:AE73) -> 607824
A74: 66 | B74: RF065_Epod3 | C74: Epod 3 | D74: Epod 3 - PCBA Tooling | T74: 89492 | AF74: =SUM(V74:AE74) -> 0
A75: 67 | B75: RF066_Epod3+ | C75: Epod 3+ | D75: Epod 3+ - PCBA Tooling | T75: 27600 | AF75: =SUM(V75:AE75) -> 0
A76: 68 | B76: RF067_Hestia1.1 | C76: Hestia 1.1 | D76: Hestia 1.1 - PCBA Tooling | T76: 0 | U76: =Volume!CO14 -> 29970 | V76: =Volume!CP14 -> 576000 | W76: =Volume!CQ14 -> 811150 | X76: =Volume!CR14 -> 1104660 | Y76: =Volume!CS14 -> 817540 | Z76: =Volume!CT14 -> 476460 | AA76: =Volume!CU14 -> 606300 | AB76: =Volume!CV14 -> 610230 | ... AE76: =Volume!CY14 -> 613260 | AF76: =SUM(V76:AE76) -> 6679340
A77: 69 | B77: RF068_KumaE2.0PenNZ | C77: Kuma E 2.0 Pen NZ | D77: Kuma E 2.0 Pen NZ - PCBA Tooling | AF77: =SUM(V77:AE77) -> 0
A78: 70 | B78: RF069_KumaE2.0Box | C78: Kuma E 2.0 Box | D78: Kuma E 2.0 Box - PCBA Tooling | AF78: =SUM(V78:AE78) -> 0
A79: 71 | B79: RF070_KumaEMax | C79: Kuma E Max | D79: Kuma E Max - PCBA Tooling | AF79: =SUM(V79:AE79) -> 0
A80: 72 | B80: RF071_Aquila-US | C80: Aquila-US | D80: Aquila-US - PCBA Tooling | AF80: =SUM(V80:AE80) -> 0
A81: 73 | B81: RF072_PrismaticPod | C81: Prismatic Pod | D81: Indo POD T1 transfer Capex | AF81: =SUM(V81:AE81) -> 0
A82: 74 | B82: RF073_Hestia1.0 | C82: Hestia 1.0 | D82: ePod 2 to Hestia1.0 / ePod compatible line (6th line) | AF82: =SUM(V82:AE82) -> 0
A83: 76 | C83: Kuma E 2.0 Box | D83: Kuma E 2.0 Box Tooling
A84: 77 | C84: Prismatic Kit | D84: Primsmatic Kit VAT/qualification cost
C85: Kuma E 2.0 Pen ROW | D85: Kuma E 2.0 Pen ROW - PCBA Tooling
C86: VEGA | D86: Automation CFU Line (ACCRUED)
C87: VEGA | D87: Tax Stamp
C88: VEGA | D88: VEGA tooling
C89: Kuma E Max | D89: Kuma E Max Tooling
