Workbook

Sheet HESA Student
A1: UKPRN | B1: HE provider | C1: Russell Group | D1: Country of HE provider | E1: Region of HE provider | F1: Level of study | G1: Mode of study | H1: Academic Year | I1: Number
A2: 10007783 | B2: The University of Aberdeen | C2: Non-member | D2: Scotland | E2: Scotland | F2: Postgraduate (research) | G2: Full-time | H2: 2023/24 | I2: 710
A3: 10007783 | B3: The University of Aberdeen | C3: Non-member | D3: Scotland | E3: Scotland | F3: Postgraduate (research) | G3: Part-time | H3: 2023/24 | I3: 190
A4: 10007849 | B4: Abertay University | C4: Non-member | D4: Scotland | E4: Scotland | F4: Postgraduate (research) | G4: Full-time | H4: 2023/24 | I4: 50
A5: 10007849 | B5: Abertay University | C5: Non-member | D5: Scotland | E5: Scotland | F5: Postgraduate (research) | G5: Part-time | H5: 2023/24 | I5: 30
A6: 10007856 | B6: Aberystwyth University | C6: Non-member | D6: Wales | E6: Wales | F6: Postgraduate (research) | G6: Full-time | H6: 2023/24 | I6: 210
A7: 10007856 | B7: Aberystwyth University | C7: Non-member | D7: Wales | E7: Wales | F7: Postgraduate (research) | G7: Part-time | H7: 2023/24 | I7: 95
A8: 10000163 | B8: AECC University College | C8: Non-member | D8: England | E8: South West | F8: Postgraduate (research) | G8: Full-time | H8: 2023/24 | I8: 0
A9: 10000163 | B9: AECC University College | C9: Non-member | D9: England | E9: South West | F9: Postgraduate (research) | G9: Part-time | H9: 2023/24 | I9: 0
A10: 10000291 | B10: Anglia Ruskin University | C10: Non-member | D10: England | E10: East of England | F10: Postgraduate (research) | G10: Full-time | H10: 2023/24 | I10: 190
A11: 10000291 | B11: Anglia Ruskin University | C11: Non-member | D11: England | E11: East of England | F11: Postgraduate (research) | G11: Part-time | H11: 2023/24 | I11: 450
A12: 10007759 | B12: Aston University | C12: Non-member | D12: England | E12: West Midlands | F12: Postgraduate (research) | G12: Full-time | H12: 2023/24 | I12: 285
A13: 10007759 | B13: Aston University | C13: Non-member | D13: England | E13: West Midlands | F13: Postgraduate (research) | G13: Part-time | H13: 2023/24 | I13: 95
... A3923: 10007167 | B3923: The University of York | C3923: Member | D3923: England | E3923: Yorkshire and The Humber | F3923: Other undergraduate | G3923: Part-time | H3923: 2021/22 | I3923: 315

Sheet HESA Staff
A1: UKPRN | B1: Russell Group | C1: Country of HE provider | D1: Region of HE provider | E1: Mode of employment | F1: Academic Year | G1: Number | H1: university
A2: 10007783 | B2: Non-member | C2: Scotland | D2: Scotland | E2: Full-time | F2: 2020/21 | G2: 1020 | H2: =VLOOKUP(A2,University!A:A,1,FALSE) -> 10007783
A3: 10007783 | B3: Non-member | C3: Scotland | D3: Scotland | E3: Part-time | F3: 2020/21 | G3: 525 | H3: =VLOOKUP(A3,University!A:A,1,FALSE) -> 10007783
A4: 10007849 | B4: Non-member | C4: Scotland | D4: Scotland | E4: Full-time | F4: 2020/21 | G4: 180 | H4: =VLOOKUP(A4,University!A:A,1,FALSE) -> 10007849
A5: 10007849 | B5: Non-member | C5: Scotland | D5: Scotland | E5: Part-time | F5: 2020/21 | G5: 30 | H5: =VLOOKUP(A5,University!A:A,1,FALSE) -> 10007849
A6: 10007856 | B6: Non-member | C6: Wales | D6: Wales | E6: Full-time | F6: 2020/21 | G6: 430 | H6: =VLOOKUP(A6,University!A:A,1,FALSE) -> 10007856
A7: 10007856 | B7: Non-member | C7: Wales | D7: Wales | E7: Part-time | F7: 2020/21 | G7: 270 | H7: =VLOOKUP(A7,University!A:A,1,FALSE) -> 10007856
A8: 10067853 | B8: Non-member | C8: England | D8: South East | E8: Full-time | F8: 2020/21 | G8: 10 | H8: =VLOOKUP(A8,University!A:A,1,FALSE) -> 10067853
A9: 10067853 | B9: Non-member | C9: England | D9: South East | E9: Part-time | F9: 2020/21 | G9: 95 | H9: =VLOOKUP(A9,University!A:A,1,FALSE) -> 10067853
A10: 10000163 | B10: Non-member | C10: England | D10: South West | E10: Full-time | F10: 2020/21 | G10: 30 | H10: =VLOOKUP(A10,University!A:A,1,FALSE) -> 10000163
A11: 10000163 | B11: Non-member | C11: England | D11: South West | E11: Part-time | F11: 2020/21 | G11: 25 | H11: =VLOOKUP(A11,University!A:A,1,FALSE) -> 10000163
A12: 10000291 | B12: Non-member | C12: England | D12: East of England | E12: Full-time | F12: 2020/21 | G12: 590 | H12: =VLOOKUP(A12,University!A:A,1,FALSE) -> 10000291
A13: 10000291 | B13: Non-member | C13: England | D13: East of England | E13: Part-time | F13: 2020/21 | G13: 240 | H13: =VLOOKUP(A13,University!A:A,1,FALSE) -> 10000291
... A1623: 10007167 | B1623: Member | C1623: England | D1623: Yorkshire and The Humber | E1623: Part-time | F1623: 2022/23 | G1623: 805 | H1623: =VLOOKUP(A1623,University!A:A,1,FALSE) -> 10007167

Sheet HESA Finance
A1: UKPRN | B1: HE Provider | C1: Country of HE provider | D1: Region of HE provider | E1: Academic year | F1: HESA cost centre grouping | G1: HESA cost centre | H1: Source of income | I1: Source of Income grouping | J1: Income(£000s) | K1: univerisity
A2: 10007783 | B2: The University of Aberdeen | C2: Scotland | D2: Scotland | E2: 2023/24 | F2: Academic departments | G2: Total academic departments | H2: 1a Biotechnology and Biological Sciences Research Council (BBSRC) | I2: Research Councils | J2: 2810 | K2: =VLOOKUP(A2,University!A:A,1,FALSE) -> 10007783
A3: 10007783 | B3: The University of Aberdeen | C3: Scotland | D3: Scotland | E3: 2023/24 | F3: Academic departments | G3: Total academic departments | H3: 1b Medical Research Council (MRC) | I3: Research Councils | J3: 1384 | K3: =VLOOKUP(A3,University!A:A,1,FALSE) -> 10007783
A4: 10007783 | B4: The University of Aberdeen | C4: Scotland | D4: Scotland | E4: 2023/24 | F4: Academic departments | G4: Total academic departments | H4: 1c Natural Environment Research Council (NERC) | I4: Research Councils | J4: 3041 | K4: =VLOOKUP(A4,University!A:A,1,FALSE) -> 10007783
A5: 10007783 | B5: The University of Aberdeen | C5: Scotland | D5: Scotland | E5: 2023/24 | F5: Academic departments | G5: Total academic departments | H5: 1d Engineering and Physical Sciences Research Council (EPSRC) | I5: Research Councils | J5: 1512 | K5: =VLOOKUP(A5,University!A:A,1,FALSE) -> 10007783
A6: 10007783 | B6: The University of Aberdeen | C6: Scotland | D6: Scotland | E6: 2023/24 | F6: Academic departments | G6: Total academic departments | H6: 1e Economic and Social Research Council (ESRC) | I6: Research Councils | J6: 728 | K6: =VLOOKUP(A6,University!A:A,1,FALSE) -> 10007783
A7: 10007783 | B7: The University of Aberdeen | C7: Scotland | D7: Scotland | E7: 2023/24 | F7: Academic departments | G7: Total academic departments | H7: 1f Arts & Humanities Research Council (AHRC) | I7: Research Councils | J7: 527 | K7: =VLOOKUP(A7,University!A:A,1,FALSE) -> 10007783
A8: 10007783 | B8: The University of Aberdeen | C8: Scotland | D8: Scotland | E8: 2023/24 | F8: Academic departments | G8: Total academic departments | H8: 1g Science & Technology Facilities Council (STFC) | I8: Research Councils | J8: -1 | K8: =VLOOKUP(A8,University!A:A,1,FALSE) -> 10007783
A9: 10007783 | B9: The University of Aberdeen | C9: Scotland | D9: Scotland | E9: 2023/24 | F9: Academic departments | G9: Total academic departments | H9: 1h UK Research and Innovation | I9: Research Councils | J9: 51 | K9: =VLOOKUP(A9,University!A:A,1,FALSE) -> 10007783
A10: 10007783 | B10: The University of Aberdeen | C10: Scotland | D10: Scotland | E10: 2023/24 | F10: Academic departments | G10: Total academic departments | H10: 1i Other | I10: Research Councils | J10: 937 | K10: =VLOOKUP(A10,University!A:A,1,FALSE) -> 10007783
A11: 10007783 | B11: The University of Aberdeen | C11: Scotland | D11: Scotland | E11: 2023/24 | F11: Academic departments | G11: Total academic departments | H11: 2 UK-based charities (open competitive process) | I11: UK-based charities | J11: 7139 | K11: =VLOOKUP(A11,University!A:A,1,FALSE) -> 10007783
A12: 10007783 | B12: The University of Aberdeen | C12: Scotland | D12: Scotland | E12: 2023/24 | F12: Academic departments | G12: Total academic departments | H12: 3 UK based charities (other) | I12: UK-based charities | J12: 3626 | K12: =VLOOKUP(A12,University!A:A,1,FALSE) -> 10007783
A13: 10007783 | B13: The University of Aberdeen | C13: Scotland | D13: Scotland | E13: 2023/24 | F13: Academic departments | G13: Total academic departments | H13: 4 UK central government bodies/local authorities, health and hospital authorities | I13: UK central government | J13: 16910 | K13: =VLOOKUP(A13,University!A:A,1,FALSE) -> 10007783
... A2414: 10007167 | B2414: The University of York | C2414: England | D2414: Yorkshire and The Humber | E2414: 2023/24 | F2414: Administration & central services | G2414: Total administration & central services | H2414: 4 UK central government bodies/local authorities, health and hospital authorities | I2414: UK central government | J2414: 26 | K2414: =VLOOKUP(A2414,University!A:A,1,FALSE) -> 10007167

Sheet University
A1: UKPRN | B1: HE provider | C1: Russell Group | D1: Country of HE provider | E1: Region of HE provider | F1: staff | G1: finance
A2: 10000163 | B2: AECC University College | C2: Non-member | D2: England | E2: South West | F2: =VLOOKUP(A2,'HESA Staff'!A:A,1,FALSE) -> 10000163 | G2: =VLOOKUP(A2,'HESA Finance'!A:A,1,FALSE) -> 10000163
A3: 10000291 | B3: Anglia Ruskin University | C3: Non-member | D3: England | E3: East of England | F3: =VLOOKUP(A3,'HESA Staff'!A:A,1,FALSE) -> 10000291 | G3: =VLOOKUP(A3,'HESA Finance'!A:A,1,FALSE) -> 10000291
A4: 10000385 | B4: The Arts University Bournemouth | C4: Non-member | D4: England | E4: South West | F4: =VLOOKUP(A4,'HESA Staff'!A:A,1,FALSE) -> 10000385 | G4: =VLOOKUP(A4,'HESA Finance'!A:A,1,FALSE) -> 10000385
A5: 10000571 | B5: Bath Spa University | C5: Non-member | D5: England | E5: South West | F5: =VLOOKUP(A5,'HESA Staff'!A:A,1,FALSE) -> 10000571 | G5: =VLOOKUP(A5,'HESA Finance'!A:A,1,FALSE) -> 10000571
A6: 10000712 | B6: University College Birmingham | C6: Non-member | D6: England | E6: West Midlands | F6: =VLOOKUP(A6,'HESA Staff'!A:A,1,FALSE) -> 10000712 | G6: =VLOOKUP(A6,'HESA Finance'!A:A,1,FALSE) -> #N/A
A7: 10000824 | B7: Bournemouth University | C7: Non-member | D7: England | E7: South West | F7: =VLOOKUP(A7,'HESA Staff'!A:A,1,FALSE) -> 10000824 | G7: =VLOOKUP(A7,'HESA Finance'!A:A,1,FALSE) -> 10000824
A8: 10000886 | B8: The University of Brighton | C8: Non-member | D8: England | E8: South East | F8: =VLOOKUP(A8,'HESA Staff'!A:A,1,FALSE) -> 10000886 | G8: =VLOOKUP(A8,'HESA Finance'!A:A,1,FALSE) -> 10000886
A9: 10000936 | B9: The University College of Osteopathy | C9: Non-member | D9: England | E9: London | F9: =VLOOKUP(A9,'HESA Staff'!A:A,1,FALSE) -> 10000936 | G9: =VLOOKUP(A9,'HESA Finance'!A:A,1,FALSE) -> 10000936
A10: 10000961 | B10: Brunel University London | C10: Non-member | D10: England | E10: London | F10: =VLOOKUP(A10,'HESA Staff'!A:A,1,FALSE) -> 10000961 | G10: =VLOOKUP(A10,'HESA Finance'!A:A,1,FALSE) -> 10000961
A11: 10000975 | B11: Buckinghamshire New University | C11: Non-member | D11: England | E11: South East | F11: =VLOOKUP(A11,'HESA Staff'!A:A,1,FALSE) -> 10000975 | G11: =VLOOKUP(A11,'HESA Finance'!A:A,1,FALSE) -> 10000975
A12: 10001143 | B12: Canterbury Christ Church University | C12: Non-member | D12: England | E12: South East | F12: =VLOOKUP(A12,'HESA Staff'!A:A,1,FALSE) -> 10001143 | G12: =VLOOKUP(A12,'HESA Finance'!A:A,1,FALSE) -> 10001143
A13: 10001264 | B13: Central School of Ballet | C13: Non-member | D13: England | E13: London | F13: =VLOOKUP(A13,'HESA Staff'!A:A,1,FALSE) -> 10001264 | G13: =VLOOKUP(A13,'HESA Finance'!A:A,1,FALSE) -> #N/A
... A214: 10088214 | B214: S P Jain London School of Management Limited | C214: Non-member | D214: England | E214: South East | F214: =VLOOKUP(A214,'HESA Staff'!A:A,1,FALSE) -> 10088214 | G214: =VLOOKUP(A214,'HESA Finance'!A:A,1,FALSE) -> #N/A

Sheet validation
A3: 行标签 | B3: 计数项:UKPRN
A4: 10000163 | B4: 1
A5: 10000291 | B5: 1
A6: 10000385 | B6: 1
A7: 10000571 | B7: 1
A8: 10000712 | B8: 1
A9: 10000824 | B9: 1
A10: 10000886 | B10: 1
A11: 10000936 | B11: 1
A12: 10000961 | B12: 1
A13: 10000975 | B13: 1
A14: 10001143 | B14: 1
A15: 10001264 | B15: 1
... A216: 10088214 | B216: 1
A217: (空白)
A218: 总计 | B218: 213
